Workbook
Name \4: #REF!
Name \4: #REF!
Name \6: #REF!
Name \6: #REF!
Name \A: #REF!
Name \A: #REF!
Name \E: #REF!
Name \I: #REF!
Name \M: #REF!
Name \N: #REF!
Name \O: #REF!
Name \U: #REF!
Name __DAT1: #REF!
Name __DAT10: #REF!
Name __DAT11: #REF!
Name __DAT12: #REF!
Name __DAT13: #REF!
Name __DAT14: #REF!
Name __DAT2: #REF!
Name __DAT3: #REF!
Name __DAT4: #REF!
Name __DAT5: #REF!
Name __DAT6: #REF!
Name __DAT7: #REF!
Name __DAT8: #REF!
Name __DAT9: #REF!
Name _DAT1: #REF!
Name _DAT10: #REF!
Name _DAT11: #REF!
Name _DAT12: #REF!
Name _DAT13: #REF!
Name _DAT14: #REF!
Name _DAT15: #REF!
Name _DAT16: #REF!
Name _DAT17: #REF!
Name _DAT18: #REF!
Name _DAT19: #REF!
Name _DAT2: #REF!
Name _DAT20: #REF!
Name _DAT21: #REF!
Name _DAT3: #REF!
Name _DAT4: #REF!
Name _DAT5: #REF!
Name _DAT6: #REF!
Name _DAT7: #REF!
Name _DAT8: #REF!
Name _DAT9: #REF!
Name ACERO: #REF!
Name ACERO: #REF!
Name adegas: [2]PP!#REF!
Name adegpressão: [2]PP!#REF!
Name AGUA: #REF!
Name AGUA: #REF!
Name ALAMBRE: #REF!
Name ana_bajante_pluvial_3pulg: [3]ANA!$F$536
Name ana_caja_inspeccion: [3]ANA!$F$907
Name ana_codo_pvc_drenaje_2pulgx45: [3]ANA!$F$324
Name ana_codo_pvc_drenaje_3pulgx45: [3]ANA!$F$331
Name ana_codo_pvc_drenaje_4pulgx45: [3]ANA!$F$338
Name ana_codo_pvc_presion_1.5pulg: [3]ANA!$F$275

Sheet Consideraciones 
A3: Conograma de Insumos de Hispanoamerica
A4: Fecha | B4: Detalles
B5: Presupuesto levantando segun plano de Veron
B6: Hispano America No se posee plano
B7: Se considero revestimiento para baños y asistido
B8: Se considero pisos para baños
B9: Se considero 250 mts pisos antideslizante
B10: Generadores electricos de 500 kW 2 unidades
B11: Neveras nuevo lineamiento Arneg
B12: Muebles IMS nuevo modelos
B13: Bomper igual a las americas
B14: Se considero UN horno Rational
B15: Monto de la gondola, tomado de la Forteza segun MC05
B16: Visual M esta evauando los maniqui (puede que cambie el monto)
B17: Bomba contra incendio considerada de 1,500 vertical

Sheet Plan OI
C1: Presupuesto Detallado - Propuesta para Sirena Compacta Hispanoamerica
C2: Area de Compras de Activos
C4: Fecha Version: | D4: Alto Nivel | E4: Alto Nivel Rev III | I4: Plan Detallado DOP | L4: Plan Detallado USD
D5: Total Presupuesto [USD] | E5: Total Presupuesto [USD] | G5: Ppto OI [DOP] | H5: Ppto Capex [DOP] | I5: Total Iniciativa [DOP] | J5: Ppto OI [USD] | K5: Ppto Capex [USD] | L5: Total Iniciativa [USD]
C6: TOTAL GENERAL ESTIMADO | D6: =D9+D10+D11 -> 3179486.8 | E6: =E9+E10+E11 -> 2530056.7 | G6: =SUM(G9:G11) -> 2.1075093e+08 | H6: =SUM(H9:H11) -> 0 | I6: =H6+G6 -> 2.1075093e+08 | J6: =SUM(J9:J11) -> 3472008.8 | K6: =SUM(K9:K11) -> 0 | L6: =K6+J6 -> 3472008.8
C8: Resumen de Partidas
C9: EQUIPAMIENTO | D9: =SUMIF(PPto[Gran Part.],$C9,PPto[Total '[USD']]) -> 2901152.5 | E9: =SUMIF(PPto[Gran Part.],$C9,PPto[Total '[USD']3]) -> 2391748.5 | G9: =SUMIF(PPto[Gran Part.],$C9,PPto[Ppto. OI '[DOP']2]) -> 1.9535958e+08 | H9: =SUMIF(PPto[Gran Part.],$C9,PPto[Ppto. Capex '[DOP']]) -> 0 | I9: =SUMIF(PPto[Gran Part.],$C9,PPto[Total '[DOP']]) -> 1.9535958e+08 | J9: =SUMIF(PPto[Gran Part.],C9,PPto[Ppto. OI '[USD']]) -> 3218444.5 | K9: =SUMIF(PPto[Gran Part.],C9,PPto[Ppto. Capex '[USD']]) -> 0 | L9: =K9+J9 -> 3218444.5
C10: EDIFICACIÓN | D10: =SUMIF(PPto[Gran Part.],$C10,PPto[Total '[USD']]) -> 278334.38 | E10: =SUMIF(PPto[Gran Part.],$C10,PPto[Total '[USD']3]) -> 138308.14 | G10: =SUMIF(PPto[Gran Part.],$C10,PPto[Ppto. OI '[DOP']2]) -> 15391355 | H10: =SUMIF(PPto[Gran Part.],$C10,PPto[Ppto. Capex '[DOP']]) -> 0 | I10: =SUMIF(PPto[Gran Part.],$C10,PPto[Total '[DOP']]) -> 15391355 | J10: =SUMIF(PPto[Gran Part.],C10,PPto[Ppto. OI '[USD']]) -> 253564.32 | K10: =SUMIF(PPto[Gran Part.],C10,PPto[Ppto. Capex '[USD']]) -> 0 | L10: =K10+J10 -> 253564.32
C11: TERRENO | D11: 0 | E11: 0 | G11: =SUMIF(PPto[Gran Part.],$C11,PPto[Ppto. OI '[DOP']2]) -> 0 | H11: =SUMIF(PPto[Gran Part.],$C11,PPto[Ppto. Capex '[DOP']]) -> 0 | I11: =H11+G11 -> 0 | J11: =SUMIF(PPto[Gran Part.],C11,PPto[Ppto. OI '[USD']]) -> 0 | K11: =SUMIF(PPto[Gran Part.],C11,PPto[Ppto. Capex '[USD']]) -> 0 | L11: =K11+J11 -> 0
C12: Gasto | D12: 0 | E12: 0 | G12: =SUMIF(PPto[Gran Part.],$C12,PPto[Ppto. OI '[DOP']2]) -> 0 | H12: =SUMIF(PPto[Gran Part.],$C12,PPto[Ppto. Capex '[DOP']]) -> 0 | I12: =H12+G12 -> 0 | J12: =SUMIF(PPto[Gran Part.],C12,PPto[Ppto. OI '[USD']]) -> 0 | K12: =SUMIF(PPto[Gran Part.],C12,PPto[Ppto. Capex '[USD']]) -> 0 | L12: =K12+J12 -> 0 | P12: 753760
C14: Área de la Localidad | P14: 85000
C15: M² Construcción | P15: =+P12+P14 -> 838760
C16: M² Sala de Ventas
C17: M² Terreno
G18: OI | H18: Capex | J18: OI | K18: Capex
A19: Part. | B19: Gran Part. | C19: Edificación, Instalaciones y Equipamientos | D19: Total [USD] | E19: Total [USD]3 | F19: Columna2 | G19: Ppto. OI [DOP]2 | H19: Ppto. Capex [DOP] | I19: Total [DOP] | J19: Ppto. OI [USD] | K19: Ppto. Capex [USD] | L19: Total [USD]2 | M19: Total [USD]22
A20: 1 | C20: 1.00 Estudios Preliminares | D20: =SUM(D21:D27) -> 0 | E20: =SUM(E21:E27) -> 0 | G20: =SUM(G21:G29) -> 0 | H20: =SUM(H21:H29) -> 0 | I20: =PPto[[#This Row],[Ppto. Capex '[DOP']]]+PPto[[#This Row],[Ppto. OI '[DOP']2]] -> 0 | J20: =SUM(J21:J29) -> 0 | K20: =SUM(K21:K29) -> 0 | L20: =PPto[[#This Row],[Ppto. Capex '[USD']]]+PPto[[#This Row],[Ppto. OI '[USD']]] -> 0
A21: 1.01 | B21: Edificación | C21: 1.01 Diseño arquitectónico | D21: 0 | E21: 0 | G21: =SUMIFS(BD.PD[Ppto. Orden Interna '[DOP']],BD.PD[Pos],PPto[[#This Row],[Part.]],BD.PD[Tipo Ppto],G$18) -> 0 | H21: =SUMIFS(BD.PD[Ppto. Orden Interna '[DOP']],BD.PD[Pos],PPto[[#This Row],[Part.]],BD.PD[Tipo Ppto],H$18) -> 0 | I21: =PPto[[#This Row],[Ppto. Capex '[DOP']]]+PPto[[#This Row],[Ppto. OI '[DOP']2]] -> 0 | J21: =SUMIFS(BD.PD[Ppto. Orden Interna '[USD']],BD.PD[Pos],PPto[[#This Row],[Part.]],BD.PD[Tipo Ppto],J$18) -> 0 | K21: =SUMIFS(BD.PD[Ppto. Orden Interna '[USD']],BD.PD[Pos],PPto[[#This Row],[Part.]],BD.PD[Tipo Ppto],K$18) -> 0 | L21: =PPto[[#This Row],[Ppto. Capex '[USD']]]+PPto[[#This Row],[Ppto. OI '[USD']]] -> 0
A22: 1.02 | B22: Edificación | C22: 1.02 Diseño estructural | D22: 0 | E22: 0 | G22: =SUMIFS(BD.PD[Ppto. Orden Interna '[DOP']],BD.PD[Pos],PPto[[#This Row],[Part.]],BD.PD[Tipo Ppto],G$18) -> 0 | H22: =SUMIFS(BD.PD[Ppto. Orden Interna '[DOP']],BD.PD[Pos],PPto[[#This Row],[Part.]],BD.PD[Tipo Ppto],H$18) -> 0 | I22: =PPto[[#This Row],[Ppto. Capex '[DOP']]]+PPto[[#This Row],[Ppto. OI '[DOP']2]] -> 0 | J22: =SUMIFS(BD.PD[Ppto. Orden Interna '[USD']],BD.PD[Pos],PPto[[#This Row],[Part.]],BD.PD[Tipo Ppto],J$18) -> 0 | K22: =SUMIFS(BD.PD[Ppto. Orden Interna '[USD']],BD.PD[Pos],PPto[[#This Row],[Part.]],BD.PD[Tipo Ppto],K$18) -> 0 | L22: =PPto[[#This Row],[Ppto. Capex '[USD']]]+PPto[[#This Row],[Ppto. OI '[USD']]] -> 0
A23: 1.03 | B23: Edificación | C23: 1.03 Diseño electromecánico | D23: 0 | E23: 0 | G23: =SUMIFS(BD.PD[Ppto. Orden Interna '[DOP']],BD.PD[Pos],PPto[[#This Row],[Part.]],BD.PD[Tipo Ppto],G$18) -> 0 | H23: =SUMIFS(BD.PD[Ppto. Orden Interna '[DOP']],BD.PD[Pos],PPto[[#This Row],[Part.]],BD.PD[Tipo Ppto],H$18) -> 0 | I23: =PPto[[#This Row],[Ppto. Capex '[DOP']]]+PPto[[#This Row],[Ppto. OI '[DOP']2]] -> 0 | J23: =SUMIFS(BD.PD[Ppto. Orden Interna '[USD']],BD.PD[Pos],PPto[[#This Row],[Part.]],BD.PD[Tipo Ppto],J$18) -> 0 | K23: =SUMIFS(BD.PD[Ppto. Orden Interna '[USD']],BD.PD[Pos],PPto[[#This Row],[Part.]],BD.PD[Tipo Ppto],K$18) -> 0 | L23: =PPto[[#This Row],[Ppto. Capex '[USD']]]+PPto[[#This Row],[Ppto. OI '[USD']]] -> 0
A24: 1.04 | B24: Edificación | C24: 1.04 Diseño sanitario | D24: 0 | E24: 0 | G24: =SUMIFS(BD.PD[Ppto. Orden Interna '[DOP']],BD.PD[Pos],PPto[[#This Row],[Part.]],BD.PD[Tipo Ppto],G$18) -> 0 | H24: =SUMIFS(BD.PD[Ppto. Orden Interna '[DOP']],BD.PD[Pos],PPto[[#This Row],[Part.]],BD.PD[Tipo Ppto],H$18) -> 0 | I24: =PPto[[#This Row],[Ppto. Capex '[DOP']]]+PPto[[#This Row],[Ppto. OI '[DOP']2]] -> 0 | J24: =SUMIFS(BD.PD[Ppto. Orden Interna '[USD']],BD.PD[Pos],PPto[[#This Row],[Part.]],BD.PD[Tipo Ppto],J$18) -> 0 | K24: =SUMIFS(BD.PD[Ppto. Orden Interna '[USD']],BD.PD[Pos],PPto[[#This Row],[Part.]],BD.PD[Tipo Ppto],K$18) -> 0 | L24: =PPto[[#This Row],[Ppto. Capex '[USD']]]+PPto[[#This Row],[Ppto. OI '[USD']]] -> 0
A25: 1.05 | B25: Edificación | C25: 1.05 Estudio Geotécnico | D25: 0 | E25: 0 | G25: =SUMIFS(BD.PD[Ppto. Orden Interna '[DOP']],BD.PD[Pos],PPto[[#This Row],[Part.]],BD.PD[Tipo Ppto],G$18) -> 0 | H25: =SUMIFS(BD.PD[Ppto. Orden Interna '[DOP']],BD.PD[Pos],PPto[[#This Row],[Part.]],BD.PD[Tipo Ppto],H$18) -> 0 | I25: =PPto[[#This Row],[Ppto. Capex '[DOP']]]+PPto[[#This Row],[Ppto. OI '[DOP']2]] -> 0 | J25: =SUMIFS(BD.PD[Ppto. Orden Interna '[USD']],BD.PD[Pos],PPto[[#This Row],[Part.]],BD.PD[Tipo Ppto],J$18) -> 0 | K25: =SUMIFS(BD.PD[Ppto. Orden Interna '[USD']],BD.PD[Pos],PPto[[#This Row],[Part.]],BD.PD[Tipo Ppto],K$18) -> 0 | L25: =PPto[[#This Row],[Ppto. Capex '[USD']]]+PPto[[#This Row],[Ppto. OI '[USD']]] -> 0
A26: 1.06 | B26: Edificación | C26: 1.06 Levantamiento topográfico | D26: 0 | E26: 0 | G26: =SUMIFS(BD.PD[Ppto. Orden Interna '[DOP']],BD.PD[Pos],PPto[[#This Row],[Part.]],BD.PD[Tipo Ppto],G$18) -> 0 | H26: =SUMIFS(BD.PD[Ppto. Orden Interna '[DOP']],BD.PD[Pos],PPto[[#This Row],[Part.]],BD.PD[Tipo Ppto],H$18) -> 0 | I26: =PPto[[#This Row],[Ppto. Capex '[DOP']]]+PPto[[#This Row],[Ppto. OI '[DOP']2]] -> 0 | J26: =SUMIFS(BD.PD[Ppto. Orden Interna '[USD']],BD.PD[Pos],PPto[[#This Row],[Part.]],BD.PD[Tipo Ppto],J$18) -> 0 | K26: =SUMIFS(BD.PD[Ppto. Orden Interna '[USD']],BD.PD[Pos],PPto[[#This Row],[Part.]],BD.PD[Tipo Ppto],K$18) -> 0 | L26: =PPto[[#This Row],[Ppto. Capex '[USD']]]+PPto[[#This Row],[Ppto. OI '[USD']]] -> 0
A27: 1.07 | B27: Edificación | C27: 1.07 Permisos | D27: 0 | E27: 0 | G27: =SUMIFS(BD.PD[Ppto. Orden Interna '[DOP']],BD.PD[Pos],PPto[[#This Row],[Part.]],BD.PD[Tipo Ppto],G$18) -> 0 | H27: =SUMIFS(BD.PD[Ppto. Orden Interna '[DOP']],BD.PD[Pos],PPto[[#This Row],[Part.]],BD.PD[Tipo Ppto],H$18) -> 0 | I27: =PPto[[#This Row],[Ppto. Capex '[DOP']]]+PPto[[#This Row],[Ppto. OI '[DOP']2]] -> 0 | J27: =SUMIFS(BD.PD[Ppto. Orden Interna '[USD']],BD.PD[Pos],PPto[[#This Row],[Part.]],BD.PD[Tipo Ppto],J$18) -> 0 | K27: =SUMIFS(BD.PD[Ppto. Orden Interna '[USD']],BD.PD[Pos],PPto[[#This Row],[Part.]],BD.PD[Tipo Ppto],K$18) -> 0 | L27: =PPto[[#This Row],[Ppto. Capex '[USD']]]+PPto[[#This Row],[Ppto. OI '[USD']]] -> 0
A28: 1.08 | B28: Edificación | C28: 1.08 Diseño sistema contra incendios | D28: 0 | E28: 0 | G28: =SUMIFS(BD.PD[Ppto. Orden Interna '[DOP']],BD.PD[Pos],PPto[[#This Row],[Part.]],BD.PD[Tipo Ppto],G$18) -> 0 | H28: =SUMIFS(BD.PD[Ppto. Orden Interna '[DOP']],BD.PD[Pos],PPto[[#This Row],[Part.]],BD.PD[Tipo Ppto],H$18) -> 0 | I28: =PPto[[#This Row],[Ppto. Capex '[DOP']]]+PPto[[#This Row],[Ppto. OI '[DOP']2]] -> 0 | J28: =SUMIFS(BD.PD[Ppto. Orden Interna '[USD']],BD.PD[Pos],PPto[[#This Row],[Part.]],BD.PD[Tipo Ppto],J$18) -> 0 | K28: =SUMIFS(BD.PD[Ppto. Orden Interna '[USD']],BD.PD[Pos],PPto[[#This Row],[Part.]],BD.PD[Tipo Ppto],K$18) -> 0 | L28: =PPto[[#This Row],[Ppto. Capex '[USD']]]+PPto[[#This Row],[Ppto. OI '[USD']]] -> 0
A29: 1.09 | B29: Edificación | C29: 1.09 Diseño sistema gas | D29: 0 | E29: 0 | G29: =SUMIFS(BD.PD[Ppto. Orden Interna '[DOP']],BD.PD[Pos],PPto[[#This Row],[Part.]],BD.PD[Tipo Ppto],G$18) -> 0 | H29: =SUMIFS(BD.PD[Ppto. Orden Interna '[DOP']],BD.PD[Pos],PPto[[#This Row],[Part.]],BD.PD[Tipo Ppto],H$18) -> 0 | I29: =PPto[[#This Row],[Ppto. Capex '[DOP']]]+PPto[[#This Row],[Ppto. OI '[DOP']2]] -> 0 | J29: =SUMIFS(BD.PD[Ppto. Orden Interna '[USD']],BD.PD[Pos],PPto[[#This Row],[Part.]],BD.PD[Tipo Ppto],J$18) -> 0 | K29: =SUMIFS(BD.PD[Ppto. Orden Interna '[USD']],BD.PD[Pos],PPto[[#This Row],[Part.]],BD.PD[Tipo Ppto],K$18) -> 0 | L29: =PPto[[#This Row],[Ppto. Capex '[USD']]]+PPto[[#This Row],[Ppto. OI '[USD']]] -> 0
A30: 2 | C30: 2.00 Obra Civil | D30: =SUM(D31:D41) -> 278334.38 | E30: =SUM(E31:E41) -> 138308.14 | G30: =SUM(G31:G41) -> 15391355 | H30: =SUM(H31:H41) -> 0 | I30: =PPto[[#This Row],[Ppto. Capex '[DOP']]]+PPto[[#This Row],[Ppto. OI '[DOP']2]] -> 15391355 | J30: =SUM(J31:J41) -> 253564.32 | K30: =SUM(K31:K41) -> 0 | L30: =PPto[[#This Row],[Ppto. Capex '[USD']]]+PPto[[#This Row],[Ppto. OI '[USD']]] -> 253564.32 | M30: Adicionales
A31: 2.01 | B31: Edificación | C31: 2.01 Edificación - Obra Civil | D31: 161119.6 | E31: 8428.7 | G31: =SUMIFS(BD.PD[Ppto. Orden Interna '[DOP']],BD.PD[Pos],PPto[[#This Row],[Part.]],BD.PD[Tipo Ppto],G$18) -> 1073527 | H31: =SUMIFS(BD.PD[Ppto. Orden Interna '[DOP']],BD.PD[Pos],PPto[[#This Row],[Part.]],BD.PD[Tipo Ppto],H$18) -> 0 | I31: =PPto[[#This Row],[Ppto. Capex '[DOP']]]+PPto[[#This Row],[Ppto. OI '[DOP']2]] -> 1073527 | J31: =SUMIFS(BD.PD[Ppto. Orden Interna '[USD']],BD.PD[Pos],PPto[[#This Row],[Part.]],BD.PD[Tipo Ppto],J$18) -> 17685.782 | K31: =SUMIFS(BD.PD[Ppto. Orden Interna '[USD']],BD.PD[Pos],PPto[[#This Row],[Part.]],BD.PD[Tipo Ppto],K$18) -> 0 | L31: =PPto[[#This Row],[Ppto. Capex '[USD']]]+PPto[[#This Row],[Ppto. OI '[USD']]] -> 17685.782
A32: 2.02 | B32: Edificación | C32: 2.02 Edificación - Estructura Metálica | D32: 0 | E32: 0 | G32: =SUMIFS(BD.PD[Ppto. Orden Interna '[DOP']],BD.PD[Pos],PPto[[#This Row],[Part.]],BD.PD[Tipo Ppto],G$18) -> 0 | H32: =SUMIFS(BD.PD[Ppto. Orden Interna '[DOP']],BD.PD[Pos],PPto[[#This Row],[Part.]],BD.PD[Tipo Ppto],H$18) -> 0 | I32: =PPto[[#This Row],[Ppto. Capex '[DOP']]]+PPto[[#This Row],[Ppto. OI '[DOP']2]] -> 0 | J32: =SUMIFS(BD.PD[Ppto. Orden Interna '[USD']],BD.PD[Pos],PPto[[#This Row],[Part.]],BD.PD[Tipo Ppto],J$18) -> 0 | K32: =SUMIFS(BD.PD[Ppto. Orden Interna '[USD']],BD.PD[Pos],PPto[[#This Row],[Part.]],BD.PD[Tipo Ppto],K$18) -> 0 | L32: =PPto[[#This Row],[Ppto. Capex '[USD']]]+PPto[[#This Row],[Ppto. OI '[USD']]] -> 0
A33: 2.03 | B33: Edificación | C33: 2.03 Edificación - Techo S.S. y Cerramientos Multipanel | D33: 0 | E33: 0 | G33: =SUMIFS(BD.PD[Ppto. Orden Interna '[DOP']],BD.PD[Pos],PPto[[#This Row],[Part.]],BD.PD[Tipo Ppto],G$18) -> 0 | H33: =SUMIFS(BD.PD[Ppto. Orden Interna '[DOP']],BD.PD[Pos],PPto[[#This Row],[Part.]],BD.PD[Tipo Ppto],H$18) -> 0 | I33: =PPto[[#This Row],[Ppto. Capex '[DOP']]]+PPto[[#This Row],[Ppto. OI '[DOP']2]] -> 0 | J33: =SUMIFS(BD.PD[Ppto. Orden Interna '[USD']],BD.PD[Pos],PPto[[#This Row],[Part.]],BD.PD[Tipo Ppto],J$18) -> 0 | K33: =SUMIFS(BD.PD[Ppto. Orden Interna '[USD']],BD.PD[Pos],PPto[[#This Row],[Part.]],BD.PD[Tipo Ppto],K$18) -> 0 | L33: =PPto[[#This Row],[Ppto. Capex '[USD']]]+PPto[[#This Row],[Ppto. OI '[USD']]] -> 0
A34: 2.04 | B34: Edificación | C34: 2.04 Edificación - Tragaluces "Skylights" | D34: 0 | E34: 0 | G34: =SUMIFS(BD.PD[Ppto. Orden Interna '[DOP']],BD.PD[Pos],PPto[[#This Row],[Part.]],BD.PD[Tipo Ppto],G$18) -> 0 | H34: =SUMIFS(BD.PD[Ppto. Orden Interna '[DOP']],BD.PD[Pos],PPto[[#This Row],[Part.]],BD.PD[Tipo Ppto],H$18) -> 0 | I34: =PPto[[#This Row],[Ppto. Capex '[DOP']]]+PPto[[#This Row],[Ppto. OI '[DOP']2]] -> 0 | J34: =SUMIFS(BD.PD[Ppto. Orden Interna '[USD']],BD.PD[Pos],PPto[[#This Row],[Part.]],BD.PD[Tipo Ppto],J$18) -> 0 | K34: =SUMIFS(BD.PD[Ppto. Orden Interna '[USD']],BD.PD[Pos],PPto[[#This Row],[Part.]],BD.PD[Tipo Ppto],K$18) -> 0 | L34: =PPto[[#This Row],[Ppto. Capex '[USD']]]+PPto[[#This Row],[Ppto. OI '[USD']]] -> 0
A35: 2.05 | B35: Edificación | C35: 2.05 Instalaciones Sanitarias | D35: 25100 | E35: 24520 | G35: =SUMIFS(BD.PD[Ppto. Orden Interna '[DOP']],BD.PD[Pos],PPto[[#This Row],[Part.]],BD.PD[Tipo Ppto],G$18) -> 1523570 | H35: =SUMIFS(BD.PD[Ppto. Orden Interna '[DOP']],BD.PD[Pos],PPto[[#This Row],[Part.]],BD.PD[Tipo Ppto],H$18) -> 0 | I35: =PPto[[#This Row],[Ppto. Capex '[DOP']]]+PPto[[#This Row],[Ppto. OI '[DOP']2]] -> 1523570 | J35: =SUMIFS(BD.PD[Ppto. Orden Interna '[USD']],BD.PD[Pos],PPto[[#This Row],[Part.]],BD.PD[Tipo Ppto],J$18) -> 25100 | K35: =SUMIFS(BD.PD[Ppto. Orden Interna '[USD']],BD.PD[Pos],PPto[[#This Row],[Part.]],BD.PD[Tipo Ppto],K$18) -> 0 | L35: =PPto[[#This Row],[Ppto. Capex '[USD']]]+PPto[[#This Row],[Ppto. OI '[USD']]] -> 25100
A36: 2.06 | B36: Edificación | C36: 2.06 Instalación de Gas | D36: 0 | E36: 0 | G36: =SUMIFS(BD.PD[Ppto. Orden Interna '[DOP']],BD.PD[Pos],PPto[[#This Row],[Part.]],BD.PD[Tipo Ppto],G$18) -> 454500 | H36: =SUMIFS(BD.PD[Ppto. Orden Interna '[DOP']],BD.PD[Pos],PPto[[#This Row],[Part.]],BD.PD[Tipo Ppto],H$18) -> 0 | I36: =PPto[[#This Row],[Ppto. Capex '[DOP']]]+PPto[[#This Row],[Ppto. OI '[DOP']2]] -> 454500 | J36: =SUMIFS(BD.PD[Ppto. Orden Interna '[USD']],BD.PD[Pos],PPto[[#This Row],[Part.]],BD.PD[Tipo Ppto],J$18) -> 7487.6442 | K36: =SUMIFS(BD.PD[Ppto. Orden Interna '[USD']],BD.PD[Pos],PPto[[#This Row],[Part.]],BD.PD[Tipo Ppto],K$18) -> 0 | L36: =PPto[[#This Row],[Ppto. Capex '[USD']]]+PPto[[#This Row],[Ppto. OI '[USD']]] -> 7487.6442
A37: 2.07 | B37: Edificación | C37: 2.07 Sistema Contra Incendios | D37: 8266.7758 | E37: 6432.69 | G37: =SUMIFS(BD.PD[Ppto. Orden Interna '[DOP']],BD.PD[Pos],PPto[[#This Row],[Part.]],BD.PD[Tipo Ppto],G$18) -> 6105348.6 | H37: =SUMIFS(BD.PD[Ppto. Orden Interna '[DOP']],BD.PD[Pos],PPto[[#This Row],[Part.]],BD.PD[Tipo Ppto],H$18) -> 0 | I37: =PPto[[#This Row],[Ppto. Capex '[DOP']]]+PPto[[#This Row],[Ppto. OI '[DOP']2]] -> 6105348.6 | J37: =SUMIFS(BD.PD[Ppto. Orden Interna '[USD']],BD.PD[Pos],PPto[[#This Row],[Part.]],BD.PD[Tipo Ppto],J$18) -> 100582.35 | K37: =SUMIFS(BD.PD[Ppto. Orden Interna '[USD']],BD.PD[Pos],PPto[[#This Row],[Part.]],BD.PD[Tipo Ppto],K$18) -> 0 | L37: =PPto[[#This Row],[Ppto. Capex '[USD']]]+PPto[[#This Row],[Ppto. OI '[USD']]] -> 100582.35
A38: 2.08 | B38: Edificación | C38: 2.08 Instalaciones Mecánicas | D38: 83848 | E38: 88350 | G38: =SUMIFS(BD.PD[Ppto. Orden Interna '[DOP']],BD.PD[Pos],PPto[[#This Row],[Part.]],BD.PD[Tipo Ppto],G$18) -> 5334408.9 | H38: =SUMIFS(BD.PD[Ppto. Orden Interna '[DOP']],BD.PD[Pos],PPto[[#This Row],[Part.]],BD.PD[Tipo Ppto],H$18) -> 0 | I38: =PPto[[#This Row],[Ppto. Capex '[DOP']]]+PPto[[#This Row],[Ppto. OI '[DOP']2]] -> 5334408.9 | J38: =SUMIFS(BD.PD[Ppto. Orden Interna '[USD']],BD.PD[Pos],PPto[[#This Row],[Part.]],BD.PD[Tipo Ppto],J$18) -> 87881.531 | K38: =SUMIFS(BD.PD[Ppto. Orden Interna '[USD']],BD.PD[Pos],PPto[[#This Row],[Part.]],BD.PD[Tipo Ppto],K$18) -> 0 | L38: =PPto[[#This Row],[Ppto. Capex '[USD']]]+PPto[[#This Row],[Ppto. OI '[USD']]] -> 87881.531
A39: 2.09 | B39: Edificación | C39: 2.09 Rejillas y Sumideros | D39: 0 | E39: 10576.75 | G39: =SUMIFS(BD.PD[Ppto. Orden Interna '[DOP']],BD.PD[Pos],PPto[[#This Row],[Part.]],BD.PD[Tipo Ppto],G$18) -> 900000 | H39: =SUMIFS(BD.PD[Ppto. Orden Interna '[DOP']],BD.PD[Pos],PPto[[#This Row],[Part.]],BD.PD[Tipo Ppto],H$18) -> 0 | I39: =PPto[[#This Row],[Ppto. Capex '[DOP']]]+PPto[[#This Row],[Ppto. OI '[DOP']2]] -> 900000 | J39: =SUMIFS(BD.PD[Ppto. Orden Interna '[USD']],BD.PD[Pos],PPto[[#This Row],[Part.]],BD.PD[Tipo Ppto],J$18) -> 14827.018 | K39: =SUMIFS(BD.PD[Ppto. Orden Interna '[USD']],BD.PD[Pos],PPto[[#This Row],[Part.]],BD.PD[Tipo Ppto],K$18) -> 0 | L39: =PPto[[#This Row],[Ppto. Capex '[USD']]]+PPto[[#This Row],[Ppto. OI '[USD']]] -> 14827.018 | M39: Rejillas y sumideros del nuevo proveedor
A40: 2.1 | B40: Edificación | C40: 2.10 Supervisión Civil y Sanitaria | D40: 0 | E40: 0 | G40: =SUMIFS(BD.PD[Ppto. Orden Interna '[DOP']],BD.PD[Pos],PPto[[#This Row],[Part.]],BD.PD[Tipo Ppto],G$18) -> 0 | H40: =SUMIFS(BD.PD[Ppto. Orden Interna '[DOP']],BD.PD[Pos],PPto[[#This Row],[Part.]],BD.PD[Tipo Ppto],H$18) -> 0 | I40: =PPto[[#This Row],[Ppto. Capex '[DOP']]]+PPto[[#This Row],[Ppto. OI '[DOP']2]] -> 0 | J40: =SUMIFS(BD.PD[Ppto. Orden Interna '[USD']],BD.PD[Pos],PPto[[#This Row],[Part.]],BD.PD[Tipo Ppto],J$18) -> 0 | K40: =SUMIFS(BD.PD[Ppto. Orden Interna '[USD']],BD.PD[Pos],PPto[[#This Row],[Part.]],BD.PD[Tipo Ppto],K$18) -> 0 | L40: =PPto[[#This Row],[Ppto. Capex '[USD']]]+PPto[[#This Row],[Ppto. OI '[USD']]] -> 0
A41: 2.11 | B41: Edificación | C41: 2.11 Supervisión Arquitectónica | D41: 0 | E41: 0 | G41: =SUMIFS(BD.PD[Ppto. Orden Interna '[DOP']],BD.PD[Pos],PPto[[#This Row],[Part.]],BD.PD[Tipo Ppto],G$18) -> 0 | H41: =SUMIFS(BD.PD[Ppto. Orden Interna '[DOP']],BD.PD[Pos],PPto[[#This Row],[Part.]],BD.PD[Tipo Ppto],H$18) -> 0 | I41: =PPto[[#This Row],[Ppto. Capex '[DOP']]]+PPto[[#This Row],[Ppto. OI '[DOP']2]] -> 0 | J41: =SUMIFS(BD.PD[Ppto. Orden Interna '[USD']],BD.PD[Pos],PPto[[#This Row],[Part.]],BD.PD[Tipo Ppto],J$18) -> 0 | K41: =SUMIFS(BD.PD[Ppto. Orden Interna '[USD']],BD.PD[Pos],PPto[[#This Row],[Part.]],BD.PD[Tipo Ppto],K$18) -> 0 | L41: =PPto[[#This Row],[Ppto. Capex '[USD']]]+PPto[[#This Row],[Ppto. OI '[USD']]] -> 0
A42: 3 | C42: 3.00 Sistema Eléctrico | D42: =SUM(D43:D46) -> 146108.56 | E42: =SUM(E43:E46) -> 146562.4 | G42: =SUM(G43:G46) -> 30715852 | H42: =SUM(H43:H46) -> 0 | I42: =PPto[[#This Row],[Ppto. Capex '[DOP']]]+PPto[[#This Row],[Ppto. OI '[DOP']2]] -> 30715852 | J42: =SUM(J43:J46) -> 506027.22 | K42: =SUM(K43:K46) -> 0 | L42: =PPto[[#This Row],[Ppto. Capex '[USD']]]+PPto[[#This Row],[Ppto. OI '[USD']]] -> 506027.22
A43: 3.01 | B43: Equipamiento | C43: 3.01 Instalaciones Eléctricas | D43: 0 | E43: 0 | G43: =SUMIFS(BD.PD[Ppto. Orden Interna '[DOP']],BD.PD[Pos],PPto[[#This Row],[Part.]],BD.PD[Tipo Ppto],G$18) -> 19624310 | H43: =SUMIFS(BD.PD[Ppto. Orden Interna '[DOP']],BD.PD[Pos],PPto[[#This Row],[Part.]],BD.PD[Tipo Ppto],H$18) -> 0 | I43: =PPto[[#This Row],[Ppto. Capex '[DOP']]]+PPto[[#This Row],[Ppto. OI '[DOP']2]] -> 19624310 | J43: =SUMIFS(BD.PD[Ppto. Orden Interna '[USD']],BD.PD[Pos],PPto[[#This Row],[Part.]],BD.PD[Tipo Ppto],J$18) -> 323300 | K43: =SUMIFS(BD.PD[Ppto. Orden Interna '[USD']],BD.PD[Pos],PPto[[#This Row],[Part.]],BD.PD[Tipo Ppto],K$18) -> 0 | L43: =PPto[[#This Row],[Ppto. Capex '[USD']]]+PPto[[#This Row],[Ppto. OI '[USD']]] -> 323300
A44: 3.02 | B44: Equipamiento | C44: 3.02 Supervisión Eléctrica | D44: 0 | E44: 0 | G44: =SUMIFS(BD.PD[Ppto. Orden Interna '[DOP']],BD.PD[Pos],PPto[[#This Row],[Part.]],BD.PD[Tipo Ppto],G$18) -> 0 | H44: =SUMIFS(BD.PD[Ppto. Orden Interna '[DOP']],BD.PD[Pos],PPto[[#This Row],[Part.]],BD.PD[Tipo Ppto],H$18) -> 0 | I44: =PPto[[#This Row],[Ppto. Capex '[DOP']]]+PPto[[#This Row],[Ppto. OI '[DOP']2]] -> 0 | J44: =SUMIFS(BD.PD[Ppto. Orden Interna '[USD']],BD.PD[Pos],PPto[[#This Row],[Part.]],BD.PD[Tipo Ppto],J$18) -> 0 | K44: =SUMIFS(BD.PD[Ppto. Orden Interna '[USD']],BD.PD[Pos],PPto[[#This Row],[Part.]],BD.PD[Tipo Ppto],K$18) -> 0 | L44: =PPto[[#This Row],[Ppto. Capex '[USD']]]+PPto[[#This Row],[Ppto. OI '[USD']]] -> 0
A45: 3.03 | B45: Equipamiento | C45: 3.03 Generadores | D45: 130677.96 | E45: 130677.96 | G45: =SUMIFS(BD.PD[Ppto. Orden Interna '[DOP']],BD.PD[Pos],PPto[[#This Row],[Part.]],BD.PD[Tipo Ppto],G$18) -> 10030931 | H45: =SUMIFS(BD.PD[Ppto. Orden Interna '[DOP']],BD.PD[Pos],PPto[[#This Row],[Part.]],BD.PD[Tipo Ppto],H$18) -> 0 | I45: =PPto[[#This Row],[Ppto. Capex '[DOP']]]+PPto[[#This Row],[Ppto. OI '[DOP']2]] -> 10030931 | J45: =SUMIFS(BD.PD[Ppto. Orden Interna '[USD']],BD.PD[Pos],PPto[[#This Row],[Part.]],BD.PD[Tipo Ppto],J$18) -> 165254.22 | K45: =SUMIFS(BD.PD[Ppto. Orden Interna '[USD']],BD.PD[Pos],PPto[[#This Row],[Part.]],BD.PD[Tipo Ppto],K$18) -> 0 | L45: =PPto[[#This Row],[Ppto. Capex '[USD']]]+PPto[[#This Row],[Ppto. OI '[USD']]] -> 165254.22
A46: 3.04 | B46: Equipamiento | C46: 3.04 Inversor y UPS | D46: 15430.602 | E46: 15884.444 | G46: =SUMIFS(BD.PD[Ppto. Orden Interna '[DOP']],BD.PD[Pos],PPto[[#This Row],[Part.]],BD.PD[Tipo Ppto],G$18) -> 1060611.1 | H46: =SUMIFS(BD.PD[Ppto. Orden Interna '[DOP']],BD.PD[Pos],PPto[[#This Row],[Part.]],BD.PD[Tipo Ppto],H$18) -> 0 | I46: =PPto[[#This Row],[Ppto. Capex '[DOP']]]+PPto[[#This Row],[Ppto. OI '[DOP']2]] -> 1060611.1 | J46: =SUMIFS(BD.PD[Ppto. Orden Interna '[USD']],BD.PD[Pos],PPto[[#This Row],[Part.]],BD.PD[Tipo Ppto],J$18) -> 17473 | K46: =SUMIFS(BD.PD[Ppto. Orden Interna '[USD']],BD.PD[Pos],PPto[[#This Row],[Part.]],BD.PD[Tipo Ppto],K$18) -> 0 | L46: =PPto[[#This Row],[Ppto. Capex '[USD']]]+PPto[[#This Row],[Ppto. OI '[USD']]] -> 17473
A47: 4 | C47: 4.00 Sistema de Climatización | D47: =SUM(D48:D50) -> 17671.381 | E47: =SUM(E48:E50) -> 17671.381 | G47: =SUM(G48:G50) -> 6739429.1 | H47: =SUM(H48:H50) -> 0 | I47: =PPto[[#This Row],[Ppto. Capex '[DOP']]]+PPto[[#This Row],[Ppto. OI '[DOP']2]] -> 6739429.1 | J47: =SUM(J48:J50) -> 111028.49 | K47: =SUM(K48:K50) -> 0 | L47: =PPto[[#This Row],[Ppto. Capex '[USD']]]+PPto[[#This Row],[Ppto. OI '[USD']]] -> 111028.49 | M47: Adicionales
A48: 4.01 | B48: Equipamiento | C48: 4.01 Suministro e instalación de Equipos | D48: 0 | E48: 0 | G48: =SUMIFS(BD.PD[Ppto. Orden Interna '[DOP']],BD.PD[Pos],PPto[[#This Row],[Part.]],BD.PD[Tipo Ppto],G$18) -> 5620061.3 | H48: =SUMIFS(BD.PD[Ppto. Orden Interna '[DOP']],BD.PD[Pos],PPto[[#This Row],[Part.]],BD.PD[Tipo Ppto],H$18) -> 0 | I48: =PPto[[#This Row],[Ppto. Capex '[DOP']]]+PPto[[#This Row],[Ppto. OI '[DOP']2]] -> 5620061.3 | J48: =SUMIFS(BD.PD[Ppto. Orden Interna '[USD']],BD.PD[Pos],PPto[[#This Row],[Part.]],BD.PD[Tipo Ppto],J$18) -> 92587.5 | K48: =SUMIFS(BD.PD[Ppto. Orden Interna '[USD']],BD.PD[Pos],PPto[[#This Row],[Part.]],BD.PD[Tipo Ppto],K$18) -> 0 | L48: =PPto[[#This Row],[Ppto. Capex '[USD']]]+PPto[[#This Row],[Ppto. OI '[USD']]] -> 92587.5 | M48: Aires acondicionados
A49: 4.02 | B49: Equipamiento | C49: 4.02 Supervisión Mecánica | D49: 0 | E49: 0 | G49: =SUMIFS(BD.PD[Ppto. Orden Interna '[DOP']],BD.PD[Pos],PPto[[#This Row],[Part.]],BD.PD[Tipo Ppto],G$18) -> 0 | H49: =SUMIFS(BD.PD[Ppto. Orden Interna '[DOP']],BD.PD[Pos],PPto[[#This Row],[Part.]],BD.PD[Tipo Ppto],H$18) -> 0 | I49: =PPto[[#This Row],[Ppto. Capex '[DOP']]]+PPto[[#This Row],[Ppto. OI '[DOP']2]] -> 0 | J49: =SUMIFS(BD.PD[Ppto. Orden Interna '[USD']],BD.PD[Pos],PPto[[#This Row],[Part.]],BD.PD[Tipo Ppto],J$18) -> 0 | K49: =SUMIFS(BD.PD[Ppto. Orden Interna '[USD']],BD.PD[Pos],PPto[[#This Row],[Part.]],BD.PD[Tipo Ppto],K$18) -> 0 | L49: =PPto[[#This Row],[Ppto. Capex '[USD']]]+PPto[[#This Row],[Ppto. OI '[USD']]] -> 0
A50: 4.03 | B50: Equipamiento | C50: 4.03 Sistema de Extracción cocina | D50: 17671.381 | E50: 17671.381 | G50: =SUMIFS(BD.PD[Ppto. Orden Interna '[DOP']],BD.PD[Pos],PPto[[#This Row],[Part.]],BD.PD[Tipo Ppto],G$18) -> 1119367.9 | H50: =SUMIFS(BD.PD[Ppto. Orden Interna '[DOP']],BD.PD[Pos],PPto[[#This Row],[Part.]],BD.PD[Tipo Ppto],H$18) -> 0 | I50: =PPto[[#This Row],[Ppto. Capex '[DOP']]]+PPto[[#This Row],[Ppto. OI '[DOP']2]] -> 1119367.9 | J50: =SUMIFS(BD.PD[Ppto. Orden Interna '[USD']],BD.PD[Pos],PPto[[#This Row],[Part.]],BD.PD[Tipo Ppto],J$18) -> 18440.986 | K50: =SUMIFS(BD.PD[Ppto. Orden Interna '[USD']],BD.PD[Pos],PPto[[#This Row],[Part.]],BD.PD[Tipo Ppto],K$18) -> 0 | L50: =PPto[[#This Row],[Ppto. Capex '[USD']]]+PPto[[#This Row],[Ppto. OI '[USD']]] -> 18440.986
A51: 5 | C51: 5.00 Frio Alimentario | D51: =SUM(D52:D58) -> 1189624.4 | E51: =SUM(E52:E58) -> 971189.8 | G51: =SUM(G52:G58) -> 81656647 | H51: =SUM(H52:H58) -> 0 | I51: =PPto[[#This Row],[Ppto. Capex '[DOP']]]+PPto[[#This Row],[Ppto. OI '[DOP']2]] -> 81656647 | J51: =SUM(J52:J58) -> 1345249.5 | K51: =SUM(K52:K58) -> 0 | L51: =PPto[[#This Row],[Ppto. Capex '[USD']]]+PPto[[#This Row],[Ppto. OI '[USD']]] -> 1345249.5
A52: 5.01 | B52: Equipamiento | C52: 5.01 Paneles | D52: 279003.09 | E52: 170220 | G52: =SUMIFS(BD.PD[Ppto. Orden Interna '[DOP']],BD.PD[Pos],PPto[[#This Row],[Part.]],BD.PD[Tipo Ppto],G$18) -> 11182113 | H52: =SUMIFS(BD.PD[Ppto. Orden Interna '[DOP']],BD.PD[Pos],PPto[[#This Row],[Part.]],BD.PD[Tipo Ppto],H$18) -> 0 | I52: =PPto[[#This Row],[Ppto. Capex '[DOP']]]+PPto[[#This Row],[Ppto. OI '[DOP']2]] -> 11182113 | J52: =SUMIFS(BD.PD[Ppto. Orden Interna '[USD']],BD.PD[Pos],PPto[[#This Row],[Part.]],BD.PD[Tipo Ppto],J$18) -> 184219.32 | K52: =SUMIFS(BD.PD[Ppto. Orden Interna '[USD']],BD.PD[Pos],PPto[[#This Row],[Part.]],BD.PD[Tipo Ppto],K$18) -> 0 | L52: =PPto[[#This Row],[Ppto. Capex '[USD']]]+PPto[[#This Row],[Ppto. OI '[USD']]] -> 184219.32 | M52: Adicionales
A53: 5.02 | B53: Equipamiento | C53: 5.02 FRP y Diamond Plate | D53: 51676.037 | E53: 38430 | G53: =SUMIFS(BD.PD[Ppto. Orden Interna '[DOP']],BD.PD[Pos],PPto[[#This Row],[Part.]],BD.PD[Tipo Ppto],G$18) -> 7638149.3 | H53: =SUMIFS(BD.PD[Ppto. Orden Interna '[DOP']],BD.PD[Pos],PPto[[#This Row],[Part.]],BD.PD[Tipo Ppto],H$18) -> 0 | I53: =PPto[[#This Row],[Ppto. Capex '[DOP']]]+PPto[[#This Row],[Ppto. OI '[DOP']2]] -> 7638149.3 | J53: =SUMIFS(BD.PD[Ppto. Orden Interna '[USD']],BD.PD[Pos],PPto[[#This Row],[Part.]],BD.PD[Tipo Ppto],J$18) -> 125834.42 | K53: =SUMIFS(BD.PD[Ppto. Orden Interna '[USD']],BD.PD[Pos],PPto[[#This Row],[Part.]],BD.PD[Tipo Ppto],K$18) -> 0 | L53: =PPto[[#This Row],[Ppto. Capex '[USD']]]+PPto[[#This Row],[Ppto. OI '[USD']]] -> 125834.42
A54: 5.03 | B54: Equipamiento | C54: 5.03 Neveras, Centrales y Evaporadores | D54: 589970.59 | E54: 504260.3 | G54: =SUMIFS(BD.PD[Ppto. Orden Interna '[DOP']],BD.PD[Pos],PPto[[#This Row],[Part.]],BD.PD[Tipo Ppto],G$18) -> 36192650 | H54: =SUMIFS(BD.PD[Ppto. Orden Interna '[DOP']],BD.PD[Pos],PPto[[#This Row],[Part.]],BD.PD[Tipo Ppto],H$18) -> 0 | I54: =PPto[[#This Row],[Ppto. Capex '[DOP']]]+PPto[[#This Row],[Ppto. OI '[DOP']2]] -> 36192650 | J54: =SUMIFS(BD.PD[Ppto. Orden Interna '[USD']],BD.PD[Pos],PPto[[#This Row],[Part.]],BD.PD[Tipo Ppto],J$18) -> 596254.54 | K54: =SUMIFS(BD.PD[Ppto. Orden Interna '[USD']],BD.PD[Pos],PPto[[#This Row],[Part.]],BD.PD[Tipo Ppto],K$18) -> 0 | L54: =PPto[[#This Row],[Ppto. Capex '[USD']]]+PPto[[#This Row],[Ppto. OI '[USD']]] -> 596254.54 | M54: Neveras y centrales R404
A55: 5.04 | B55: Equipamiento | C55: 5.04 Bumpers Mcue/ Rack | D55: 30149.493 | E55: 30149.493 | G55: =SUMIFS(BD.PD[Ppto. Orden Interna '[DOP']],BD.PD[Pos],PPto[[#This Row],[Part.]],BD.PD[Tipo Ppto],G$18) -> 2027497.6 | H55: =SUMIFS(BD.PD[Ppto. Orden Interna '[DOP']],BD.PD[Pos],PPto[[#This Row],[Part.]],BD.PD[Tipo Ppto],H$18) -> 0 | I55: =PPto[[#This Row],[Ppto. Capex '[DOP']]]+PPto[[#This Row],[Ppto. OI '[DOP']2]] -> 2027497.6 | J55: =SUMIFS(BD.PD[Ppto. Orden Interna '[USD']],BD.PD[Pos],PPto[[#This Row],[Part.]],BD.PD[Tipo Ppto],J$18) -> 33401.937 | K55: =SUMIFS(BD.PD[Ppto. Orden Interna '[USD']],BD.PD[Pos],PPto[[#This Row],[Part.]],BD.PD[Tipo Ppto],K$18) -> 0 | L55: =PPto[[#This Row],[Ppto. Capex '[USD']]]+PPto[[#This Row],[Ppto. OI '[USD']]] -> 33401.937
A56: 5.05 | B56: Equipamiento | C56: 5.05 Trameria Cuarto Frio | D56: 34455.645 | E56: 43050 | G56: =SUMIFS(BD.PD[Ppto. Orden Interna '[DOP']],BD.PD[Pos],PPto[[#This Row],[Part.]],BD.PD[Tipo Ppto],G$18) -> 2272000 | H56: =SUMIFS(BD.PD[Ppto. Orden Interna '[DOP']],BD.PD[Pos],PPto[[#This Row],[Part.]],BD.PD[Tipo Ppto],H$18) -> 0 | I56: =PPto[[#This Row],[Ppto. Capex '[DOP']]]+PPto[[#This Row],[Ppto. OI '[DOP']2]] -> 2272000 | J56: =SUMIFS(BD.PD[Ppto. Orden Interna '[USD']],BD.PD[Pos],PPto[[#This Row],[Part.]],BD.PD[Tipo Ppto],J$18) -> 37429.984 | K56: =SUMIFS(BD.PD[Ppto. Orden Interna '[USD']],BD.PD[Pos],PPto[[#This Row],[Part.]],BD.PD[Tipo Ppto],K$18) -> 0 | L56: =PPto[[#This Row],[Ppto. Capex '[USD']]]+PPto[[#This Row],[Ppto. OI '[USD']]] -> 37429.984
A57: 5.06 | B57: Equipamiento | C57: 5.06 Instalacion Frio Alimentario | D57: 170833.33 | E57: 161460 | G57: =SUMIFS(BD.PD[Ppto. Orden Interna '[DOP']],BD.PD[Pos],PPto[[#This Row],[Part.]],BD.PD[Tipo Ppto],G$18) -> 17196833 | H57: =SUMIFS(BD.PD[Ppto. Orden Interna '[DOP']],BD.PD[Pos],PPto[[#This Row],[Part.]],BD.PD[Tipo Ppto],H$18) -> 0 | I57: =PPto[[#This Row],[Ppto. Capex '[DOP']]]+PPto[[#This Row],[Ppto. OI '[DOP']2]] -> 17196833 | J57: =SUMIFS(BD.PD[Ppto. Orden Interna '[USD']],BD.PD[Pos],PPto[[#This Row],[Part.]],BD.PD[Tipo Ppto],J$18) -> 283308.62 | K57: =SUMIFS(BD.PD[Ppto. Orden Interna '[USD']],BD.PD[Pos],PPto[[#This Row],[Part.]],BD.PD[Tipo Ppto],K$18) -> 0 | L57: =PPto[[#This Row],[Ppto. Capex '[USD']]]+PPto[[#This Row],[Ppto. OI '[USD']]] -> 283308.62
A58: 5.07 | B58: Equipamiento | C58: 5.07 Chase Doors | D58: 33536.25 | E58: 23620 | G58: =SUMIFS(BD.PD[Ppto. Orden Interna '[DOP']],BD.PD[Pos],PPto[[#This Row],[Part.]],BD.PD[Tipo Ppto],G$18) -> 5147403.7 | H58: =SUMIFS(BD.PD[Ppto. Orden Interna '[DOP']],BD.PD[Pos],PPto[[#This Row],[Part.]],BD.PD[Tipo Ppto],H$18) -> 0 | I58: =PPto[[#This Row],[Ppto. Capex '[DOP']]]+PPto[[#This Row],[Ppto. OI '[DOP']2]] -> 5147403.7 | J58: =SUMIFS(BD.PD[Ppto. Orden Interna '[USD']],BD.PD[Pos],PPto[[#This Row],[Part.]],BD.PD[Tipo Ppto],J$18) -> 84800.72 | K58: =SUMIFS(BD.PD[Ppto. Orden Interna '[USD']],BD.PD[Pos],PPto[[#This Row],[Part.]],BD.PD[Tipo Ppto],K$18) -> 0 | L58: =PPto[[#This Row],[Ppto. Capex '[USD']]]+PPto[[#This Row],[Ppto. OI '[USD']]] -> 84800.72
A59: 6 | C59: 6.00 Tecnología, Seguridad y Tesorería | D59: =SUM(D60:D64) -> 35818.001 | E59: =SUM(E60:E64) -> 35818.001 | G59: =SUM(G60:G64) -> 2162880 | H59: =SUM(H60:H64) -> 0 | I59: =PPto[[#This Row],[Ppto. Capex '[DOP']]]+PPto[[#This Row],[Ppto. OI '[DOP']2]] -> 2162880 | J59: =SUM(J60:J64) -> 35632.29 | K59: =SUM(K60:K64) -> 0 | L59: =PPto[[#This Row],[Ppto. Capex '[USD']]]+PPto[[#This Row],[Ppto. OI '[USD']]] -> 35632.29
A60: 6.01 | B60: Equipamiento | C60: 6.01 Sistema de cámaras CCTV | D60: 0 | E60: 0 | G60: =SUMIFS(BD.PD[Ppto. Orden Interna '[DOP']],BD.PD[Pos],PPto[[#This Row],[Part.]],BD.PD[Tipo Ppto],G$18) -> 0 | H60: =SUMIFS(BD.PD[Ppto. Orden Interna '[DOP']],BD.PD[Pos],PPto[[#This Row],[Part.]],BD.PD[Tipo Ppto],H$18) -> 0 | I60: =PPto[[#This Row],[Ppto. Capex '[DOP']]]+PPto[[#This Row],[Ppto. OI '[DOP']2]] -> 0 | J60: =SUMIFS(BD.PD[Ppto. Orden Interna '[USD']],BD.PD[Pos],PPto[[#This Row],[Part.]],BD.PD[Tipo Ppto],J$18) -> 0 | K60: =SUMIFS(BD.PD[Ppto. Orden Interna '[USD']],BD.PD[Pos],PPto[[#This Row],[Part.]],BD.PD[Tipo Ppto],K$18) -> 0 | L60: =PPto[[#This Row],[Ppto. Capex '[USD']]]+PPto[[#This Row],[Ppto. OI '[USD']]] -> 0
A61: 6.02 | B61: Equipamiento | C61: 6.02 Antenas detección de robo | D61: 0 | E61: 0 | G61: =SUMIFS(BD.PD[Ppto. Orden Interna '[DOP']],BD.PD[Pos],PPto[[#This Row],[Part.]],BD.PD[Tipo Ppto],G$18) -> 0 | H61: =SUMIFS(BD.PD[Ppto. Orden Interna '[DOP']],BD.PD[Pos],PPto[[#This Row],[Part.]],BD.PD[Tipo Ppto],H$18) -> 0 | I61: =PPto[[#This Row],[Ppto. Capex '[DOP']]]+PPto[[#This Row],[Ppto. OI '[DOP']2]] -> 0 | J61: =SUMIFS(BD.PD[Ppto. Orden Interna '[USD']],BD.PD[Pos],PPto[[#This Row],[Part.]],BD.PD[Tipo Ppto],J$18) -> 0 | K61: =SUMIFS(BD.PD[Ppto. Orden Interna '[USD']],BD.PD[Pos],PPto[[#This Row],[Part.]],BD.PD[Tipo Ppto],K$18) -> 0 | L61: =PPto[[#This Row],[Ppto. Capex '[USD']]]+PPto[[#This Row],[Ppto. OI '[USD']]] -> 0
A62: 6.03 | B62: Equipamiento | C62: 6.03 Puntos de Venta | D62: 0 | E62: 0 | G62: =SUMIFS(BD.PD[Ppto. Orden Interna '[DOP']],BD.PD[Pos],PPto[[#This Row],[Part.]],BD.PD[Tipo Ppto],G$18) -> 0 | H62: =SUMIFS(BD.PD[Ppto. Orden Interna '[DOP']],BD.PD[Pos],PPto[[#This Row],[Part.]],BD.PD[Tipo Ppto],H$18) -> 0 | I62: =PPto[[#This Row],[Ppto. Capex '[DOP']]]+PPto[[#This Row],[Ppto. OI '[DOP']2]] -> 0 | J62: =SUMIFS(BD.PD[Ppto. Orden Interna '[USD']],BD.PD[Pos],PPto[[#This Row],[Part.]],BD.PD[Tipo Ppto],J$18) -> 0 | K62: =SUMIFS(BD.PD[Ppto. Orden Interna '[USD']],BD.PD[Pos],PPto[[#This Row],[Part.]],BD.PD[Tipo Ppto],K$18) -> 0 | L62: =PPto[[#This Row],[Ppto. Capex '[USD']]]+PPto[[#This Row],[Ppto. OI '[USD']]] -> 0
A63: 6.04 | B63: Equipamiento | C63: 6.04 Instalación de data y voz / Antenas de techo | D63: 0 | E63: 0 | G63: =SUMIFS(BD.PD[Ppto. Orden Interna '[DOP']],BD.PD[Pos],PPto[[#This Row],[Part.]],BD.PD[Tipo Ppto],G$18) -> 0 | H63: =SUMIFS(BD.PD[Ppto. Orden Interna '[DOP']],BD.PD[Pos],PPto[[#This Row],[Part.]],BD.PD[Tipo Ppto],H$18) -> 0 | I63: =PPto[[#This Row],[Ppto. Capex '[DOP']]]+PPto[[#This Row],[Ppto. OI '[DOP']2]] -> 0 | J63: =SUMIFS(BD.PD[Ppto. Orden Interna '[USD']],BD.PD[Pos],PPto[[#This Row],[Part.]],BD.PD[Tipo Ppto],J$18) -> 0 | K63: =SUMIFS(BD.PD[Ppto. Orden Interna '[USD']],BD.PD[Pos],PPto[[#This Row],[Part.]],BD.PD[Tipo Ppto],K$18) -> 0 | L63: =PPto[[#This Row],[Ppto. Capex '[USD']]]+PPto[[#This Row],[Ppto. OI '[USD']]] -> 0
A64: 6.05 | B64: Equipamiento | C64: 6.05 Otros sum e inst Tecnología y Seguridad Y Tesoreria | D64: 35818.001 | E64: 35818.001 | G64: =SUMIFS(BD.PD[Ppto. Orden Interna '[DOP']],BD.PD[Pos],PPto[[#This Row],[Part.]],BD.PD[Tipo Ppto],G$18) -> 2162880 | H64: =SUMIFS(BD.PD[Ppto. Orden Interna '[DOP']],BD.PD[Pos],PPto[[#This Row],[Part.]],BD.PD[Tipo Ppto],H$18) -> 0 | I64: =PPto[[#This Row],[Ppto. Capex '[DOP']]]+PPto[[#This Row],[Ppto. OI '[DOP']2]] -> 2162880 | J64: =SUMIFS(BD.PD[Ppto. Orden Interna '[USD']],BD.PD[Pos],PPto[[#This Row],[Part.]],BD.PD[Tipo Ppto],J$18) -> 35632.29 | K64: =SUMIFS(BD.PD[Ppto. Orden Interna '[USD']],BD.PD[Pos],PPto[[#This Row],[Part.]],BD.PD[Tipo Ppto],K$18) -> 0 | L64: =PPto[[#This Row],[Ppto. Capex '[USD']]]+PPto[[#This Row],[Ppto. OI '[USD']]] -> 35632.29
A65: 7 | C65: 7.00 Equipamiento Produccion | D65: =SUM(D66:D72) -> 416815.7 | E65: =SUM(E66:E72) -> 422298.68 | G65: =SUM(G66:G72) -> 25633530 | H65: =SUM(H66:H72) -> 0 | I65: =PPto[[#This Row],[Ppto. Capex '[DOP']]]+PPto[[#This Row],[Ppto. OI '[DOP']2]] -> 25633530 | J65: =SUM(J66:J72) -> 422298.68 | K65: =SUM(K66:K72) -> 0 | L65: =PPto[[#This Row],[Ppto. Capex '[USD']]]+PPto[[#This Row],[Ppto. OI '[USD']]] -> 422298.68 | M65: Adicionales
A66: 7.01 | B66: Equipamiento | C66: 7.01 Equipamiento de Acero Inoxidable | D66: 21337.879 | E66: =PPto[[#This Row],[Ppto. Capex '[USD']]]+PPto[[#This Row],[Ppto. OI '[USD']]] -> 51185.964 | G66: =SUMIFS(BD.PD[Ppto. Orden Interna '[DOP']],BD.PD[Pos],PPto[[#This Row],[Part.]],BD.PD[Tipo Ppto],G$18) -> 3106988 | H66: =SUMIFS(BD.PD[Ppto. Orden Interna '[DOP']],BD.PD[Pos],PPto[[#This Row],[Part.]],BD.PD[Tipo Ppto],H$18) -> 0 | I66: =PPto[[#This Row],[Ppto. Capex '[DOP']]]+PPto[[#This Row],[Ppto. OI '[DOP']2]] -> 3106988 | J66: =SUMIFS(BD.PD[Ppto. Orden Interna '[USD']],BD.PD[Pos],PPto[[#This Row],[Part.]],BD.PD[Tipo Ppto],J$18) -> 51185.964 | K66: =SUMIFS(BD.PD[Ppto. Orden Interna '[USD']],BD.PD[Pos],PPto[[#This Row],[Part.]],BD.PD[Tipo Ppto],K$18) -> 0 | L66: =PPto[[#This Row],[Ppto. Capex '[USD']]]+PPto[[#This Row],[Ppto. OI '[USD']]] -> 51185.964
A67: 7.02 | B67: Equipamiento | C67: 7.02 Cocina, Patio Comidas y Rostizería | D67: 51651.609 | E67: =PPto[[#This Row],[Ppto. Capex '[USD']]]+PPto[[#This Row],[Ppto. OI '[USD']]] -> 50902.905 | G67: =SUMIFS(BD.PD[Ppto. Orden Interna '[DOP']],BD.PD[Pos],PPto[[#This Row],[Part.]],BD.PD[Tipo Ppto],G$18) -> 3089806.3 | H67: =SUMIFS(BD.PD[Ppto. Orden Interna '[DOP']],BD.PD[Pos],PPto[[#This Row],[Part.]],BD.PD[Tipo Ppto],H$18) -> 0 | I67: =PPto[[#This Row],[Ppto. Capex '[DOP']]]+PPto[[#This Row],[Ppto. OI '[DOP']2]] -> 3089806.3 | J67: =SUMIFS(BD.PD[Ppto. Orden Interna '[USD']],BD.PD[Pos],PPto[[#This Row],[Part.]],BD.PD[Tipo Ppto],J$18) -> 50902.905 | K67: =SUMIFS(BD.PD[Ppto. Orden Interna '[USD']],BD.PD[Pos],PPto[[#This Row],[Part.]],BD.PD[Tipo Ppto],K$18) -> 0 | L67: =PPto[[#This Row],[Ppto. Capex '[USD']]]+PPto[[#This Row],[Ppto. OI '[USD']]] -> 50902.905 | M67: 2 Hornos Rarional
A68: 7.03 | B68: Equipamiento | C68: 7.03 Equipamiento Carniceria, Pescadería y Delicatesen | D68: 55943.109 | E68: =PPto[[#This Row],[Ppto. Capex '[USD']]]+PPto[[#This Row],[Ppto. OI '[USD']]] -> 55255.663 | G68: =SUMIFS(BD.PD[Ppto. Orden Interna '[DOP']],BD.PD[Pos],PPto[[#This Row],[Part.]],BD.PD[Tipo Ppto],G$18) -> 3354018.8 | H68: =SUMIFS(BD.PD[Ppto. Orden Interna '[DOP']],BD.PD[Pos],PPto[[#This Row],[Part.]],BD.PD[Tipo Ppto],H$18) -> 0 | I68: =PPto[[#This Row],[Ppto. Capex '[DOP']]]+PPto[[#This Row],[Ppto. OI '[DOP']2]] -> 3354018.8 | J68: =SUMIFS(BD.PD[Ppto. Orden Interna '[USD']],BD.PD[Pos],PPto[[#This Row],[Part.]],BD.PD[Tipo Ppto],J$18) -> 55255.663 | K68: =SUMIFS(BD.PD[Ppto. Orden Interna '[USD']],BD.PD[Pos],PPto[[#This Row],[Part.]],BD.PD[Tipo Ppto],K$18) -> 0 | L68: =PPto[[#This Row],[Ppto. Capex '[USD']]]+PPto[[#This Row],[Ppto. OI '[USD']]] -> 55255.663
A69: 7.04 | B69: Equipamiento | C69: 7.04 Equipamiento de Panaderia, Reposteria y Rosticería | D69: 212892.01 | E69: =PPto[[#This Row],[Ppto. Capex '[USD']]]+PPto[[#This Row],[Ppto. OI '[USD']]] -> 170469.41 | G69: =SUMIFS(BD.PD[Ppto. Orden Interna '[DOP']],BD.PD[Pos],PPto[[#This Row],[Part.]],BD.PD[Tipo Ppto],G$18) -> 10347493 | H69: =SUMIFS(BD.PD[Ppto. Orden Interna '[DOP']],BD.PD[Pos],PPto[[#This Row],[Part.]],BD.PD[Tipo Ppto],H$18) -> 0 | I69: =PPto[[#This Row],[Ppto. Capex '[DOP']]]+PPto[[#This Row],[Ppto. OI '[DOP']2]] -> 10347493 | J69: =SUMIFS(BD.PD[Ppto. Orden Interna '[USD']],BD.PD[Pos],PPto[[#This Row],[Part.]],BD.PD[Tipo Ppto],J$18) -> 170469.41 | K69: =SUMIFS(BD.PD[Ppto. Orden Interna '[USD']],BD.PD[Pos],PPto[[#This Row],[Part.]],BD.PD[Tipo Ppto],K$18) -> 0 | L69: =PPto[[#This Row],[Ppto. Capex '[USD']]]+PPto[[#This Row],[Ppto. OI '[USD']]] -> 170469.41 | M69: Fermentadora y 2 Hornos dobles de pan
A70: 7.05 | B70: Equipamiento | C70: 7.05 Equipamiento de Frutas y Vegetales | D70: 74991.096 | E70: =PPto[[#This Row],[Ppto. Capex '[USD']]]+PPto[[#This Row],[Ppto. OI '[USD']]] -> 94484.741 | G70: =SUMIFS(BD.PD[Ppto. Orden Interna '[DOP']],BD.PD[Pos],PPto[[#This Row],[Part.]],BD.PD[Tipo Ppto],G$18) -> 5735223.8 | H70: =SUMIFS(BD.PD[Ppto. Orden Interna '[DOP']],BD.PD[Pos],PPto[[#This Row],[Part.]],BD.PD[Tipo Ppto],H$18) -> 0 | I70: =PPto[[#This Row],[Ppto. Capex '[DOP']]]+PPto[[#This Row],[Ppto. OI '[DOP']2]] -> 5735223.8 | J70: =SUMIFS(BD.PD[Ppto. Orden Interna '[USD']],BD.PD[Pos],PPto[[#This Row],[Part.]],BD.PD[Tipo Ppto],J$18) -> 94484.741 | K70: =SUMIFS(BD.PD[Ppto. Orden Interna '[USD']],BD.PD[Pos],PPto[[#This Row],[Part.]],BD.PD[Tipo Ppto],K$18) -> 0 | L70: =PPto[[#This Row],[Ppto. Capex '[USD']]]+PPto[[#This Row],[Ppto. OI '[USD']]] -> 94484.741
A71: 7.06 | B71: Equipamiento | C71: 7.06 Balanzas | D71: 0 | E71: =PPto[[#This Row],[Ppto. Capex '[USD']]]+PPto[[#This Row],[Ppto. OI '[USD']]] -> 0 | G71: =SUMIFS(BD.PD[Ppto. Orden Interna '[DOP']],BD.PD[Pos],PPto[[#This Row],[Part.]],BD.PD[Tipo Ppto],G$18) -> 0 | H71: =SUMIFS(BD.PD[Ppto. Orden Interna '[DOP']],BD.PD[Pos],PPto[[#This Row],[Part.]],BD.PD[Tipo Ppto],H$18) -> 0 | I71: =PPto[[#This Row],[Ppto. Capex '[DOP']]]+PPto[[#This Row],[Ppto. OI '[DOP']2]] -> 0 | J71: =SUMIFS(BD.PD[Ppto. Orden Interna '[USD']],BD.PD[Pos],PPto[[#This Row],[Part.]],BD.PD[Tipo Ppto],J$18) -> 0 | K71: =SUMIFS(BD.PD[Ppto. Orden Interna '[USD']],BD.PD[Pos],PPto[[#This Row],[Part.]],BD.PD[Tipo Ppto],K$18) -> 0 | L71: =PPto[[#This Row],[Ppto. Capex '[USD']]]+PPto[[#This Row],[Ppto. OI '[USD']]] -> 0
A72: 7.07 | B72: Equipamiento | C72: 7.07 Otros Equipamientos de Producción | D72: 0 | E72: =PPto[[#This Row],[Ppto. Capex '[USD']]]+PPto[[#This Row],[Ppto. OI '[USD']]] -> 0 | G72: =SUMIFS(BD.PD[Ppto. Orden Interna '[DOP']],BD.PD[Pos],PPto[[#This Row],[Part.]],BD.PD[Tipo Ppto],G$18) -> 0 | H72: =SUMIFS(BD.PD[Ppto. Orden Interna '[DOP']],BD.PD[Pos],PPto[[#This Row],[Part.]],BD.PD[Tipo Ppto],H$18) -> 0 | I72: =PPto[[#This Row],[Ppto. Capex '[DOP']]]+PPto[[#This Row],[Ppto. OI '[DOP']2]] -> 0 | J72: =SUMIFS(BD.PD[Ppto. Orden Interna '[USD']],BD.PD[Pos],PPto[[#This Row],[Part.]],BD.PD[Tipo Ppto],J$18) -> 0 | K72: =SUMIFS(BD.PD[Ppto. Orden Interna '[USD']],BD.PD[Pos],PPto[[#This Row],[Part.]],BD.PD[Tipo Ppto],K$18) -> 0 | L72: =PPto[[#This Row],[Ppto. Capex '[USD']]]+PPto[[#This Row],[Ppto. OI '[USD']]] -> 0
A73: 8 | C73: 8.00 Equipamiento Tienda | D73: =SUM(D74:D81) -> 1095114.4 | E73: =SUM(E74:E81) -> 798208.27 | G73: =SUM(G74:G81) -> 48451242 | H73: =SUM(H74:H81) -> 0 | I73: =PPto[[#This Row],[Ppto. Capex '[DOP']]]+PPto[[#This Row],[Ppto. OI '[DOP']2]] -> 48451242 | J73: =SUM(J74:J81) -> 798208.27 | K73: =SUM(K74:K81) -> 0 | L73: =PPto[[#This Row],[Ppto. Capex '[USD']]]+PPto[[#This Row],[Ppto. OI '[USD']]] -> 798208.27
A74: 8.01 | B74: Equipamiento | C74: 8.01 Gondolas | D74: 599762.98 | E74: =PPto[[#This Row],[Ppto. Capex '[USD']]]+PPto[[#This Row],[Ppto. OI '[USD']]] -> 170007.35 | G74: =SUMIFS(BD.PD[Ppto. Orden Interna '[DOP']],BD.PD[Pos],PPto[[#This Row],[Part.]],BD.PD[Tipo Ppto],G$18) -> 10319446 | H74: =SUMIFS(BD.PD[Ppto. Orden Interna '[DOP']],BD.PD[Pos],PPto[[#This Row],[Part.]],BD.PD[Tipo Ppto],H$18) -> 0 | I74: =PPto[[#This Row],[Ppto. Capex '[DOP']]]+PPto[[#This Row],[Ppto. OI '[DOP']2]] -> 10319446 | J74: =SUMIFS(BD.PD[Ppto. Orden Interna '[USD']],BD.PD[Pos],PPto[[#This Row],[Part.]],BD.PD[Tipo Ppto],J$18) -> 170007.35 | K74: =SUMIFS(BD.PD[Ppto. Orden Interna '[USD']],BD.PD[Pos],PPto[[#This Row],[Part.]],BD.PD[Tipo Ppto],K$18) -> 0 | L74: =PPto[[#This Row],[Ppto. Capex '[USD']]]+PPto[[#This Row],[Ppto. OI '[USD']]] -> 170007.35
A75: 8.02 | B75: Equipamiento | C75: 8.02 Checkout | D75: 83931.609 | E75: =PPto[[#This Row],[Ppto. Capex '[USD']]]+PPto[[#This Row],[Ppto. OI '[USD']]] -> 32178.762 | G75: =SUMIFS(BD.PD[Ppto. Orden Interna '[DOP']],BD.PD[Pos],PPto[[#This Row],[Part.]],BD.PD[Tipo Ppto],G$18) -> 1953250.9 | H75: =SUMIFS(BD.PD[Ppto. Orden Interna '[DOP']],BD.PD[Pos],PPto[[#This Row],[Part.]],BD.PD[Tipo Ppto],H$18) -> 0 | I75: =PPto[[#This Row],[Ppto. Capex '[DOP']]]+PPto[[#This Row],[Ppto. OI '[DOP']2]] -> 1953250.9 | J75: =SUMIFS(BD.PD[Ppto. Orden Interna '[USD']],BD.PD[Pos],PPto[[#This Row],[Part.]],BD.PD[Tipo Ppto],J$18) -> 32178.762 | K75: =SUMIFS(BD.PD[Ppto. Orden Interna '[USD']],BD.PD[Pos],PPto[[#This Row],[Part.]],BD.PD[Tipo Ppto],K$18) -> 0 | L75: =PPto[[#This Row],[Ppto. Capex '[USD']]]+PPto[[#This Row],[Ppto. OI '[USD']]] -> 32178.762 | M75: 12 und
A76: 8.03 | B76: Equipamiento | C76: 8.03 Carritos, Canastas y Accesorios | D76: 48527.703 | E76: =PPto[[#This Row],[Ppto. Capex '[USD']]]+PPto[[#This Row],[Ppto. OI '[USD']]] -> 221014.82 | G76: =SUMIFS(BD.PD[Ppto. Orden Interna '[DOP']],BD.PD[Pos],PPto[[#This Row],[Part.]],BD.PD[Tipo Ppto],G$18) -> 13415599 | H76: =SUMIFS(BD.PD[Ppto. Orden Interna '[DOP']],BD.PD[Pos],PPto[[#This Row],[Part.]],BD.PD[Tipo Ppto],H$18) -> 0 | I76: =PPto[[#This Row],[Ppto. Capex '[DOP']]]+PPto[[#This Row],[Ppto. OI '[DOP']2]] -> 13415599 | J76: =SUMIFS(BD.PD[Ppto. Orden Interna '[USD']],BD.PD[Pos],PPto[[#This Row],[Part.]],BD.PD[Tipo Ppto],J$18) -> 221014.82 | K76: =SUMIFS(BD.PD[Ppto. Orden Interna '[USD']],BD.PD[Pos],PPto[[#This Row],[Part.]],BD.PD[Tipo Ppto],K$18) -> 0 | L76: =PPto[[#This Row],[Ppto. Capex '[USD']]]+PPto[[#This Row],[Ppto. OI '[USD']]] -> 221014.82
A77: 8.04 | B77: Equipamiento | C77: 8.04 Trameria Almacen | D77: 54383.795 | E77: =PPto[[#This Row],[Ppto. Capex '[USD']]]+PPto[[#This Row],[Ppto. OI '[USD']]] -> 57261.821 | G77: =SUMIFS(BD.PD[Ppto. Orden Interna '[DOP']],BD.PD[Pos],PPto[[#This Row],[Part.]],BD.PD[Tipo Ppto],G$18) -> 3475792.5 | H77: =SUMIFS(BD.PD[Ppto. Orden Interna '[DOP']],BD.PD[Pos],PPto[[#This Row],[Part.]],BD.PD[Tipo Ppto],H$18) -> 0 | I77: =PPto[[#This Row],[Ppto. Capex '[DOP']]]+PPto[[#This Row],[Ppto. OI '[DOP']2]] -> 3475792.5 | J77: =SUMIFS(BD.PD[Ppto. Orden Interna '[USD']],BD.PD[Pos],PPto[[#This Row],[Part.]],BD.PD[Tipo Ppto],J$18) -> 57261.821 | K77: =SUMIFS(BD.PD[Ppto. Orden Interna '[USD']],BD.PD[Pos],PPto[[#This Row],[Part.]],BD.PD[Tipo Ppto],K$18) -> 0 | L77: =PPto[[#This Row],[Ppto. Capex '[USD']]]+PPto[[#This Row],[Ppto. OI '[USD']]] -> 57261.821
A78: 8.05 | B78: Equipamiento | C78: 8.05 Mobiliario no operacional para Tiendas | D78: 96620.274 | E78: =PPto[[#This Row],[Ppto. Capex '[USD']]]+PPto[[#This Row],[Ppto. OI '[USD']]] -> 84346.761 | G78: =SUMIFS(BD.PD[Ppto. Orden Interna '[DOP']],BD.PD[Pos],PPto[[#This Row],[Part.]],BD.PD[Tipo Ppto],G$18) -> 5119848.4 | H78: =SUMIFS(BD.PD[Ppto. Orden Interna '[DOP']],BD.PD[Pos],PPto[[#This Row],[Part.]],BD.PD[Tipo Ppto],H$18) -> 0 | I78: =PPto[[#This Row],[Ppto. Capex '[DOP']]]+PPto[[#This Row],[Ppto. OI '[DOP']2]] -> 5119848.4 | J78: =SUMIFS(BD.PD[Ppto. Orden Interna '[USD']],BD.PD[Pos],PPto[[#This Row],[Part.]],BD.PD[Tipo Ppto],J$18) -> 84346.761 | K78: =SUMIFS(BD.PD[Ppto. Orden Interna '[USD']],BD.PD[Pos],PPto[[#This Row],[Part.]],BD.PD[Tipo Ppto],K$18) -> 0 | L78: =PPto[[#This Row],[Ppto. Capex '[USD']]]+PPto[[#This Row],[Ppto. OI '[USD']]] -> 84346.761 | M78: Se estan considerando los mobiliarios de Food Cord
A79: 8.06 | B79: Equipamiento | C79: 8.06 Otros Equipamientos de Tienda | D79: 19588.978 | E79: =PPto[[#This Row],[Ppto. Capex '[USD']]]+PPto[[#This Row],[Ppto. OI '[USD']]] -> 48807.122 | G79: =SUMIFS(BD.PD[Ppto. Orden Interna '[DOP']],BD.PD[Pos],PPto[[#This Row],[Part.]],BD.PD[Tipo Ppto],G$18) -> 2962592.3 | H79: =SUMIFS(BD.PD[Ppto. Orden Interna '[DOP']],BD.PD[Pos],PPto[[#This Row],[Part.]],BD.PD[Tipo Ppto],H$18) -> 0 | I79: =PPto[[#This Row],[Ppto. Capex '[DOP']]]+PPto[[#This Row],[Ppto. OI '[DOP']2]] -> 2962592.3 | J79: =SUMIFS(BD.PD[Ppto. Orden Interna '[USD']],BD.PD[Pos],PPto[[#This Row],[Part.]],BD.PD[Tipo Ppto],J$18) -> 48807.122 | K79: =SUMIFS(BD.PD[Ppto. Orden Interna '[USD']],BD.PD[Pos],PPto[[#This Row],[Part.]],BD.PD[Tipo Ppto],K$18) -> 0 | L79: =PPto[[#This Row],[Ppto. Capex '[USD']]]+PPto[[#This Row],[Ppto. OI '[USD']]] -> 48807.122
A80: 8.07 | B80: Equipamiento | C80: 8.07 Señalizacion interiores | D80: 113999.04 | E80: =PPto[[#This Row],[Ppto. Capex '[USD']]]+PPto[[#This Row],[Ppto. OI '[USD']]] -> 118143.53 | G80: =SUMIFS(BD.PD[Ppto. Orden Interna '[DOP']],BD.PD[Pos],PPto[[#This Row],[Part.]],BD.PD[Tipo Ppto],G$18) -> 7171312.4 | H80: =SUMIFS(BD.PD[Ppto. Orden Interna '[DOP']],BD.PD[Pos],PPto[[#This Row],[Part.]],BD.PD[Tipo Ppto],H$18) -> 0 | I80: =PPto[[#This Row],[Ppto. Capex '[DOP']]]+PPto[[#This Row],[Ppto. OI '[DOP']2]] -> 7171312.4 | J80: =SUMIFS(BD.PD[Ppto. Orden Interna '[USD']],BD.PD[Pos],PPto[[#This Row],[Part.]],BD.PD[Tipo Ppto],J$18) -> 118143.53 | K80: =SUMIFS(BD.PD[Ppto. Orden Interna '[USD']],BD.PD[Pos],PPto[[#This Row],[Part.]],BD.PD[Tipo Ppto],K$18) -> 0 | L80: =PPto[[#This Row],[Ppto. Capex '[USD']]]+PPto[[#This Row],[Ppto. OI '[USD']]] -> 118143.53
A81: 8.08 | B81: Equipamiento | C81: 8.08 Señalizacion exteriores | D81: 78300 | E81: =PPto[[#This Row],[Ppto. Capex '[USD']]]+PPto[[#This Row],[Ppto. OI '[USD']]] -> 66448.105 | G81: =SUMIFS(BD.PD[Ppto. Orden Interna '[DOP']],BD.PD[Pos],PPto[[#This Row],[Part.]],BD.PD[Tipo Ppto],G$18) -> 4033400 | H81: =SUMIFS(BD.PD[Ppto. Orden Interna '[DOP']],BD.PD[Pos],PPto[[#This Row],[Part.]],BD.PD[Tipo Ppto],H$18) -> 0 | I81: =PPto[[#This Row],[Ppto. Capex '[DOP']]]+PPto[[#This Row],[Ppto. OI '[DOP']2]] -> 4033400 | J81: =SUMIFS(BD.PD[Ppto. Orden Interna '[USD']],BD.PD[Pos],PPto[[#This Row],[Part.]],BD.PD[Tipo Ppto],J$18) -> 66448.105 | K81: =SUMIFS(BD.PD[Ppto. Orden Interna '[USD']],BD.PD[Pos],PPto[[#This Row],[Part.]],BD.PD[Tipo Ppto],K$18) -> 0 | L81: =PPto[[#This Row],[Ppto. Capex '[USD']]]+PPto[[#This Row],[Ppto. OI '[USD']]] -> 66448.105
A82: 9 | C82: 9.00 Otros | D82: =SUM(D83:D88) -> 0 | E82: =SUM(E83:E88) -> 0 | G82: =SUM(G83:G88) -> 0 | H82: =SUM(H83:H88) -> 0 | I82: =PPto[[#This Row],[Ppto. Capex '[DOP']]]+PPto[[#This Row],[Ppto. OI '[DOP']2]] -> 0 | J82: =SUM(J83:J88) -> 0 | K82: =SUM(K83:K88) -> 0 | L82: =PPto[[#This Row],[Ppto. Capex '[USD']]]+PPto[[#This Row],[Ppto. OI '[USD']]] -> 0
A83: 9.01 | B83: Gasto | C83: 9.01 COMERCIALIZACION | D83: =SUM(D84:D90) -> 0 | E83: =SUM(E84:E90) -> 0 | G83: =SUMIFS(BD.PD[Ppto. Orden Interna '[DOP']],BD.PD[Pos],PPto[[#This Row],[Part.]],BD.PD[Tipo Ppto],G$18) -> 0 | H83: =SUMIFS(BD.PD[Ppto. Orden Interna '[DOP']],BD.PD[Pos],PPto[[#This Row],[Part.]],BD.PD[Tipo Ppto],H$18) -> 0 | I83: =PPto[[#This Row],[Ppto. Capex '[DOP']]]+PPto[[#This Row],[Ppto. OI '[DOP']2]] -> 0 | J83: =SUMIFS(BD.PD[Ppto. Orden Interna '[USD']],BD.PD[Pos],PPto[[#This Row],[Part.]],BD.PD[Tipo Ppto],J$18) -> 0 | K83: =SUMIFS(BD.PD[Ppto. Orden Interna '[USD']],BD.PD[Pos],PPto[[#This Row],[Part.]],BD.PD[Tipo Ppto],K$18) -> 0 | L83: =PPto[[#This Row],[Ppto. Capex '[USD']]]+PPto[[#This Row],[Ppto. OI '[USD']]] -> 0
A84: 9.02 | B84: Gasto | C84: 9.02 INSUMOS | D84: =SUM(D85:D91) -> 0 | E84: =SUM(E85:E91) -> 0 | G84: =SUMIFS(BD.PD[Ppto. Orden Interna '[DOP']],BD.PD[Pos],PPto[[#This Row],[Part.]],BD.PD[Tipo Ppto],G$18) -> 0 | H84: =SUMIFS(BD.PD[Ppto. Orden Interna '[DOP']],BD.PD[Pos],PPto[[#This Row],[Part.]],BD.PD[Tipo Ppto],H$18) -> 0 | I84: =PPto[[#This Row],[Ppto. Capex '[DOP']]]+PPto[[#This Row],[Ppto. OI '[DOP']2]] -> 0 | J84: =SUMIFS(BD.PD[Ppto. Orden Interna '[USD']],BD.PD[Pos],PPto[[#This Row],[Part.]],BD.PD[Tipo Ppto],J$18) -> 0 | K84: =SUMIFS(BD.PD[Ppto. Orden Interna '[USD']],BD.PD[Pos],PPto[[#This Row],[Part.]],BD.PD[Tipo Ppto],K$18) -> 0 | L84: =PPto[[#This Row],[Ppto. Capex '[USD']]]+PPto[[#This Row],[Ppto. OI '[USD']]] -> 0
A85: 9.03 | B85: Gasto | C85: 9.03 PUBLICIDAD Y MERCADEO | D85: =SUM(D86:D92) -> 0 | E85: =SUM(E86:E92) -> 0 | G85: =SUMIFS(BD.PD[Ppto. Orden Interna '[DOP']],BD.PD[Pos],PPto[[#This Row],[Part.]],BD.PD[Tipo Ppto],G$18) -> 0 | H85: =SUMIFS(BD.PD[Ppto. Orden Interna '[DOP']],BD.PD[Pos],PPto[[#This Row],[Part.]],BD.PD[Tipo Ppto],H$18) -> 0 | I85: =PPto[[#This Row],[Ppto. Capex '[DOP']]]+PPto[[#This Row],[Ppto. OI '[DOP']2]] -> 0 | J85: =SUMIFS(BD.PD[Ppto. Orden Interna '[USD']],BD.PD[Pos],PPto[[#This Row],[Part.]],BD.PD[Tipo Ppto],J$18) -> 0 | K85: =SUMIFS(BD.PD[Ppto. Orden Interna '[USD']],BD.PD[Pos],PPto[[#This Row],[Part.]],BD.PD[Tipo Ppto],K$18) -> 0 | L85: =PPto[[#This Row],[Ppto. Capex '[USD']]]+PPto[[#This Row],[Ppto. OI '[USD']]] -> 0
A86: 9.04 | B86: Gasto | C86: 9.04 MONTAJE | D86: =SUM(D87:D93) -> 0 | E86: =SUM(E87:E93) -> 0 | G86: =SUMIFS(BD.PD[Ppto. Orden Interna '[DOP']],BD.PD[Pos],PPto[[#This Row],[Part.]],BD.PD[Tipo Ppto],G$18) -> 0 | H86: =SUMIFS(BD.PD[Ppto. Orden Interna '[DOP']],BD.PD[Pos],PPto[[#This Row],[Part.]],BD.PD[Tipo Ppto],H$18) -> 0 | I86: =PPto[[#This Row],[Ppto. Capex '[DOP']]]+PPto[[#This Row],[Ppto. OI '[DOP']2]] -> 0 | J86: =SUMIFS(BD.PD[Ppto. Orden Interna '[USD']],BD.PD[Pos],PPto[[#This Row],[Part.]],BD.PD[Tipo Ppto],J$18) -> 0 | K86: =SUMIFS(BD.PD[Ppto. Orden Interna '[USD']],BD.PD[Pos],PPto[[#This Row],[Part.]],BD.PD[Tipo Ppto],K$18) -> 0 | L86: =PPto[[#This Row],[Ppto. Capex '[USD']]]+PPto[[#This Row],[Ppto. OI '[USD']]] -> 0
A87: 9.05 | B87: Gasto | C87: 9.05 DECORACIÓN TEMPORADAS | D87: =SUM(D88:D94) -> 0 | E87: =SUM(E88:E94) -> 0 | G87: =SUMIFS(BD.PD[Ppto. Orden Interna '[DOP']],BD.PD[Pos],PPto[[#This Row],[Part.]],BD.PD[Tipo Ppto],G$18) -> 0 | H87: =SUMIFS(BD.PD[Ppto. Orden Interna '[DOP']],BD.PD[Pos],PPto[[#This Row],[Part.]],BD.PD[Tipo Ppto],H$18) -> 0 | I87: =PPto[[#This Row],[Ppto. Capex '[DOP']]]+PPto[[#This Row],[Ppto. OI '[DOP']2]] -> 0 | J87: =SUMIFS(BD.PD[Ppto. Orden Interna '[USD']],BD.PD[Pos],PPto[[#This Row],[Part.]],BD.PD[Tipo Ppto],J$18) -> 0 | K87: =SUMIFS(BD.PD[Ppto. Orden Interna '[USD']],BD.PD[Pos],PPto[[#This Row],[Part.]],BD.PD[Tipo Ppto],K$18) -> 0 | L87: =PPto[[#This Row],[Ppto. Capex '[USD']]]+PPto[[#This Row],[Ppto. OI '[USD']]] -> 0
A88: 9.06 | B88: Gasto | C88: 9.06 - | D88: =SUM(D89:D95) -> 0 | E88: =SUM(E89:E95) -> 0 | G88: =SUMIFS(BD.PD[Ppto. Orden Interna '[DOP']],BD.PD[Pos],PPto[[#This Row],[Part.]],BD.PD[Tipo Ppto],G$18) -> 0 | H88: =SUMIFS(BD.PD[Ppto. Orden Interna '[DOP']],BD.PD[Pos],PPto[[#This Row],[Part.]],BD.PD[Tipo Ppto],H$18) -> 0 | I88: =PPto[[#This Row],[Ppto. Capex '[DOP']]]+PPto[[#This Row],[Ppto. OI '[DOP']2]] -> 0 | J88: =SUMIFS(BD.PD[Ppto. Orden Interna '[USD']],BD.PD[Pos],PPto[[#This Row],[Part.]],BD.PD[Tipo Ppto],J$18) -> 0 | K88: =SUMIFS(BD.PD[Ppto. Orden Interna '[USD']],BD.PD[Pos],PPto[[#This Row],[Part.]],BD.PD[Tipo Ppto],K$18) -> 0 | L88: =PPto[[#This Row],[Ppto. Capex '[USD']]]+PPto[[#This Row],[Ppto. OI '[USD']]] -> 0

Sheet Flujo de Caja
D1: 1 | E1: 2 | F1: 3 | G1: 4 | H1: 5 | I1: 6 | J1: 7 | K1: 8 | L1: 9 | M1: 10 | N1: 11 | O1: 12 | P1: 13 | Q1: 14 | R1: 15 | S1: 16 | T1: 17 | U1: 18 | V1: 19 | W1: 20 | X1: 21 | Y1: 22 | Z1: 23 | AA1: 24
AB2: Rojo: La sumatoria de pagos no coincide con Ppto.
B3: Apertura Diciembre 2026 | D3: Flujo de Caja Iniciativa
B4: ='Plan OI'!C1 -> Presupuesto Detallado - Propuesta para Sirena Compacta Hispanoamerica | D4: Enero | E4: Febrero | F4: Marzo | G4: Abril | H4: Mayo | I4: Junio | J4: Julio | K4: Agosto | L4: Septiembre | M4: Octubre | N4: Noviembre | O4: Diciembre | P4: Enero | Q4: Febrero | R4: Marzo | S4: Abril | T4: Mayo | U4: Junio | V4: Julio | W4: Agosto | X4: Septiembre | Y4: Octubre | Z4: Noviembre | AA4: Diciembre
A5: Part. | B5: Edificación, Instalaciones y Equipamientos | C5: Ppto OI [DOP] | D5: P1 | E5: P2 | F5: P3 | G5: P4 | H5: P5 | I5: P6 | J5: P7 | K5: P8 | L5: P9 | M5: P10 | N5: P11 | O5: P12 | P5: P13 | Q5: P14 | R5: P15 | S5: P16 | T5: P17 | U5: P18 | V5: P19 | W5: P20 | X5: P21 | Y5: P22 | Z5: P23 | AA5: P24 | AB5: Total Ppto.
A6: 1 | B6: =VLOOKUP(Tabla3[[#This Row],[Part.]],PPto[],3,FALSE) -> 1.00 Estudios Preliminares | C6: =SUM(C7:C15) -> 0 | D6: =SUM(D7:D15) -> 0 | E6: =SUM(E7:E15) -> 0 | F6: =SUM(F7:F15) -> 0 | G6: =SUM(G7:G15) -> 0 | H6: =SUM(H7:H15) -> 0 | I6: =SUM(I7:I15) -> 0 | J6: =SUM(J7:J15) -> 0 | ... AA6: =SUM(AA7:AA15) -> 0 | AB6: =SUM(Tabla3[[#This Row],[P1]:[P24]]) -> 0
A7: 1.01 | B7: =VLOOKUP(Tabla3[[#This Row],[Part.]],PPto[],3,FALSE) -> 1.01 Diseño arquitectónico | C7: =SUMIF(BD.PD[Pos],Tabla3[[#This Row],[Part.]],BD.PD[Ppto. Orden Interna '[DOP']]) -> 0 | D7: =SUMIFS(BD.PD[Pago 1],BD.PD[Per.P1],D$1,BD.PD[Pos],Tabla3[[#This Row],[Part.]])+SUMIFS(BD.PD[Pago 2],BD.PD[Per.P2],D$1,BD.PD[Pos],Tabla3[[#This Row],[Part.]])+SUMIFS(BD.PD[Pago 3],BD.PD[Per.P3],D$1,BD.PD[Pos],Tabla3[[#This Row],[Part.]])+SUMIFS(BD.PD[Pago 4],BD.PD[Per.P4],D$1,BD.PD[Pos],Tabla3[[#This Row],[Part.]])+SUMIFS(BD.PD[Pago 5],BD.PD[Per.P5],D$1,BD.PD[Pos],Tabla3[[#This Row],[Part.]]) -> 0 | E7: =SUMIFS(BD.PD[Pago 1],BD.PD[Per.P1],E$1,BD.PD[Pos],Tabla3[[#This Row],[Part.]])+SUMIFS(BD.PD[Pago 2],BD.PD[Per.P2],E$1,BD.PD[Pos],Tabla3[[#This Row],[Part.]])+SUMIFS(BD.PD[Pago 3],BD.PD[Per.P3],E$1,BD.PD[Pos],Tabla3[[#This Row],[Part.]])+SUMIFS(BD.PD[Pago 4],BD.PD[Per.P4],E$1,BD.PD[Pos],Tabla3[[#This Row],[Part.]])+SUMIFS(BD.PD[Pago 5],BD.PD[Per.P5],E$1,BD.PD[Pos],Tabla3[[#This Row],[Part.]]) -> 0 | F7: =SUMIFS(BD.PD[Pago 1],BD.PD[Per.P1],F$1,BD.PD[Pos],Tabla3[[#This Row],[Part.]])+SUMIFS(BD.PD[Pago 2],BD.PD[Per.P2],F$1,BD.PD[Pos],Tabla3[[#This Row],[Part.]])+SUMIFS(BD.PD[Pago 3],BD.PD[Per.P3],F$1,BD.PD[Pos],Tabla3[[#This Row],[Part.]])+SUMIFS(BD.PD[Pago 4],BD.PD[Per.P4],F$1,BD.PD[Pos],Tabla3[[#This Row],[Part.]])+SUMIFS(BD.PD[Pago 5],BD.PD[Per.P5],F$1,BD.PD[Pos],Tabla3[[#This Row],[Part.]]) -> 0 | G7: =SUMIFS(BD.PD[Pago 1],BD.PD[Per.P1],G$1,BD.PD[Pos],Tabla3[[#This Row],[Part.]])+SUMIFS(BD.PD[Pago 2],BD.PD[Per.P2],G$1,BD.PD[Pos],Tabla3[[#This Row],[Part.]])+SUMIFS(BD.PD[Pago 3],BD.PD[Per.P3],G$1,BD.PD[Pos],Tabla3[[#This Row],[Part.]])+SUMIFS(BD.PD[Pago 4],BD.PD[Per.P4],G$1,BD.PD[Pos],Tabla3[[#This Row],[Part.]])+SUMIFS(BD.PD[Pago 5],BD.PD[Per.P5],G$1,BD.PD[Pos],Tabla3[[#This Row],[Part.]]) -> 0 | H7: =SUMIFS(BD.PD[Pago 1],BD.PD[Per.P1],H$1,BD.PD[Pos],Tabla3[[#This Row],[Part.]])+SUMIFS(BD.PD[Pago 2],BD.PD[Per.P2],H$1,BD.PD[Pos],Tabla3[[#This Row],[Part.]])+SUMIFS(BD.PD[Pago 3],BD.PD[Per.P3],H$1,BD.PD[Pos],Tabla3[[#This Row],[Part.]])+SUMIFS(BD.PD[Pago 4],BD.PD[Per.P4],H$1,BD.PD[Pos],Tabla3[[#This Row],[Part.]])+SUMIFS(BD.PD[Pago 5],BD.PD[Per.P5],H$1,BD.PD[Pos],Tabla3[[#This Row],[Part.]]) -> 0 | I7: =SUMIFS(BD.PD[Pago 1],BD.PD[Per.P1],I$1,BD.PD[Pos],Tabla3[[#This Row],[Part.]])+SUMIFS(BD.PD[Pago 2],BD.PD[Per.P2],I$1,BD.PD[Pos],Tabla3[[#This Row],[Part.]])+SUMIFS(BD.PD[Pago 3],BD.PD[Per.P3],I$1,BD.PD[Pos],Tabla3[[#This Row],[Part.]])+SUMIFS(BD.PD[Pago 4],BD.PD[Per.P4],I$1,BD.PD[Pos],Tabla3[[#This Row],[Part.]])+SUMIFS(BD.PD[Pago 5],BD.PD[Per.P5],I$1,BD.PD[Pos],Tabla3[[#This Row],[Part.]]) -> 0 | J7: =SUMIFS(BD.PD[Pago 1],BD.PD[Per.P1],J$1,BD.PD[Pos],Tabla3[[#This Row],[Part.]])+SUMIFS(BD.PD[Pago 2],BD.PD[Per.P2],J$1,BD.PD[Pos],Tabla3[[#This Row],[Part.]])+SUMIFS(BD.PD[Pago 3],BD.PD[Per.P3],J$1,BD.PD[Pos],Tabla3[[#This Row],[Part.]])+SUMIFS(BD.PD[Pago 4],BD.PD[Per.P4],J$1,BD.PD[Pos],Tabla3[[#This Row],[Part.]])+SUMIFS(BD.PD[Pago 5],BD.PD[Per.P5],J$1,BD.PD[Pos],Tabla3[[#This Row],[Part.]]) -> 0 | K7: =SUMIFS(BD.PD[Pago 1],BD.PD[Per.P1],K$1,BD.PD[Pos],Tabla3[[#This Row],[Part.]])+SUMIFS(BD.PD[Pago 2],BD.PD[Per.P2],K$1,BD.PD[Pos],Tabla3[[#This Row],[Part.]])+SUMIFS(BD.PD[Pago 3],BD.PD[Per.P3],K$1,BD.PD[Pos],Tabla3[[#This Row],[Part.]])+SUMIFS(BD.PD[Pago 4],BD.PD[Per.P4],K$1,BD.PD[Pos],Tabla3[[#This Row],[Part.]])+SUMIFS(BD.PD[Pago 5],BD.PD[Per.P5],K$1,BD.PD[Pos],Tabla3[[#This Row],[Part.]]) -> 0 | ... AA7: =SUMIFS(BD.PD[Pago 1],BD.PD[Per.P1],AA$1,BD.PD[Pos],Tabla3[[#This Row],[Part.]])+SUMIFS(BD.PD[Pago 2],BD.PD[Per.P2],AA$1,BD.PD[Pos],Tabla3[[#This Row],[Part.]])+SUMIFS(BD.PD[Pago 3],BD.PD[Per.P3],AA$1,BD.PD[Pos],Tabla3[[#This Row],[Part.]])+SUMIFS(BD.PD[Pago 4],BD.PD[Per.P4],AA$1,BD.PD[Pos],Tabla3[[#This Row],[Part.]])+SUMIFS(BD.PD[Pago 5],BD.PD[Per.P5],AA$1,BD.PD[Pos],Tabla3[[#This Row],[Part.]]) -> 0 | AB7: =SUM(Tabla3[[#This Row],[P1]:[P24]]) -> 0
A8: 1.02 | B8: =VLOOKUP(Tabla3[[#This Row],[Part.]],PPto[],3,FALSE) -> 1.02 Diseño estructural | C8: =SUMIF(BD.PD[Pos],Tabla3[[#This Row],[Part.]],BD.PD[Ppto. Orden Interna '[DOP']]) -> 0 | D8: =SUMIFS(BD.PD[Pago 1],BD.PD[Per.P1],D$1,BD.PD[Pos],Tabla3[[#This Row],[Part.]])+SUMIFS(BD.PD[Pago 2],BD.PD[Per.P2],D$1,BD.PD[Pos],Tabla3[[#This Row],[Part.]])+SUMIFS(BD.PD[Pago 3],BD.PD[Per.P3],D$1,BD.PD[Pos],Tabla3[[#This Row],[Part.]])+SUMIFS(BD.PD[Pago 4],BD.PD[Per.P4],D$1,BD.PD[Pos],Tabla3[[#This Row],[Part.]])+SUMIFS(BD.PD[Pago 5],BD.PD[Per.P5],D$1,BD.PD[Pos],Tabla3[[#This Row],[Part.]]) -> 0 | E8: =SUMIFS(BD.PD[Pago 1],BD.PD[Per.P1],E$1,BD.PD[Pos],Tabla3[[#This Row],[Part.]])+SUMIFS(BD.PD[Pago 2],BD.PD[Per.P2],E$1,BD.PD[Pos],Tabla3[[#This Row],[Part.]])+SUMIFS(BD.PD[Pago 3],BD.PD[Per.P3],E$1,BD.PD[Pos],Tabla3[[#This Row],[Part.]])+SUMIFS(BD.PD[Pago 4],BD.PD[Per.P4],E$1,BD.PD[Pos],Tabla3[[#This Row],[Part.]])+SUMIFS(BD.PD[Pago 5],BD.PD[Per.P5],E$1,BD.PD[Pos],Tabla3[[#This Row],[Part.]]) -> 0 | F8: =SUMIFS(BD.PD[Pago 1],BD.PD[Per.P1],F$1,BD.PD[Pos],Tabla3[[#This Row],[Part.]])+SUMIFS(BD.PD[Pago 2],BD.PD[Per.P2],F$1,BD.PD[Pos],Tabla3[[#This Row],[Part.]])+SUMIFS(BD.PD[Pago 3],BD.PD[Per.P3],F$1,BD.PD[Pos],Tabla3[[#This Row],[Part.]])+SUMIFS(BD.PD[Pago 4],BD.PD[Per.P4],F$1,BD.PD[Pos],Tabla3[[#This Row],[Part.]])+SUMIFS(BD.PD[Pago 5],BD.PD[Per.P5],F$1,BD.PD[Pos],Tabla3[[#This Row],[Part.]]) -> 0 | G8: =SUMIFS(BD.PD[Pago 1],BD.PD[Per.P1],G$1,BD.PD[Pos],Tabla3[[#This Row],[Part.]])+SUMIFS(BD.PD[Pago 2],BD.PD[Per.P2],G$1,BD.PD[Pos],Tabla3[[#This Row],[Part.]])+SUMIFS(BD.PD[Pago 3],BD.PD[Per.P3],G$1,BD.PD[Pos],Tabla3[[#This Row],[Part.]])+SUMIFS(BD.PD[Pago 4],BD.PD[Per.P4],G$1,BD.PD[Pos],Tabla3[[#This Row],[Part.]])+SUMIFS(BD.PD[Pago 5],BD.PD[Per.P5],G$1,BD.PD[Pos],Tabla3[[#This Row],[Part.]]) -> 0 | H8: =SUMIFS(BD.PD[Pago 1],BD.PD[Per.P1],H$1,BD.PD[Pos],Tabla3[[#This Row],[Part.]])+SUMIFS(BD.PD[Pago 2],BD.PD[Per.P2],H$1,BD.PD[Pos],Tabla3[[#This Row],[Part.]])+SUMIFS(BD.PD[Pago 3],BD.PD[Per.P3],H$1,BD.PD[Pos],Tabla3[[#This Row],[Part.]])+SUMIFS(BD.PD[Pago 4],BD.PD[Per.P4],H$1,BD.PD[Pos],Tabla3[[#This Row],[Part.]])+SUMIFS(BD.PD[Pago 5],BD.PD[Per.P5],H$1,BD.PD[Pos],Tabla3[[#This Row],[Part.]]) -> 0 | I8: =SUMIFS(BD.PD[Pago 1],BD.PD[Per.P1],I$1,BD.PD[Pos],Tabla3[[#This Row],[Part.]])+SUMIFS(BD.PD[Pago 2],BD.PD[Per.P2],I$1,BD.PD[Pos],Tabla3[[#This Row],[Part.]])+SUMIFS(BD.PD[Pago 3],BD.PD[Per.P3],I$1,BD.PD[Pos],Tabla3[[#This Row],[Part.]])+SUMIFS(BD.PD[Pago 4],BD.PD[Per.P4],I$1,BD.PD[Pos],Tabla3[[#This Row],[Part.]])+SUMIFS(BD.PD[Pago 5],BD.PD[Per.P5],I$1,BD.PD[Pos],Tabla3[[#This Row],[Part.]]) -> 0 | J8: =SUMIFS(BD.PD[Pago 1],BD.PD[Per.P1],J$1,BD.PD[Pos],Tabla3[[#This Row],[Part.]])+SUMIFS(BD.PD[Pago 2],BD.PD[Per.P2],J$1,BD.PD[Pos],Tabla3[[#This Row],[Part.]])+SUMIFS(BD.PD[Pago 3],BD.PD[Per.P3],J$1,BD.PD[Pos],Tabla3[[#This Row],[Part.]])+SUMIFS(BD.PD[Pago 4],BD.PD[Per.P4],J$1,BD.PD[Pos],Tabla3[[#This Row],[Part.]])+SUMIFS(BD.PD[Pago 5],BD.PD[Per.P5],J$1,BD.PD[Pos],Tabla3[[#This Row],[Part.]]) -> 0 | K8: =SUMIFS(BD.PD[Pago 1],BD.PD[Per.P1],K$1,BD.PD[Pos],Tabla3[[#This Row],[Part.]])+SUMIFS(BD.PD[Pago 2],BD.PD[Per.P2],K$1,BD.PD[Pos],Tabla3[[#This Row],[Part.]])+SUMIFS(BD.PD[Pago 3],BD.PD[Per.P3],K$1,BD.PD[Pos],Tabla3[[#This Row],[Part.]])+SUMIFS(BD.PD[Pago 4],BD.PD[Per.P4],K$1,BD.PD[Pos],Tabla3[[#This Row],[Part.]])+SUMIFS(BD.PD[Pago 5],BD.PD[Per.P5],K$1,BD.PD[Pos],Tabla3[[#This Row],[Part.]]) -> 0 | ... AA8: =SUMIFS(BD.PD[Pago 1],BD.PD[Per.P1],AA$1,BD.PD[Pos],Tabla3[[#This Row],[Part.]])+SUMIFS(BD.PD[Pago 2],BD.PD[Per.P2],AA$1,BD.PD[Pos],Tabla3[[#This Row],[Part.]])+SUMIFS(BD.PD[Pago 3],BD.PD[Per.P3],AA$1,BD.PD[Pos],Tabla3[[#This Row],[Part.]])+SUMIFS(BD.PD[Pago 4],BD.PD[Per.P4],AA$1,BD.PD[Pos],Tabla3[[#This Row],[Part.]])+SUMIFS(BD.PD[Pago 5],BD.PD[Per.P5],AA$1,BD.PD[Pos],Tabla3[[#This Row],[Part.]]) -> 0 | AB8: =SUM(Tabla3[[#This Row],[P1]:[P24]]) -> 0
A9: 1.03 | B9: =VLOOKUP(Tabla3[[#This Row],[Part.]],PPto[],3,FALSE) -> 1.03 Diseño electromecánico | C9: =SUMIF(BD.PD[Pos],Tabla3[[#This Row],[Part.]],BD.PD[Ppto. Orden Interna '[DOP']]) -> 0 | D9: =SUMIFS(BD.PD[Pago 1],BD.PD[Per.P1],D$1,BD.PD[Pos],Tabla3[[#This Row],[Part.]])+SUMIFS(BD.PD[Pago 2],BD.PD[Per.P2],D$1,BD.PD[Pos],Tabla3[[#This Row],[Part.]])+SUMIFS(BD.PD[Pago 3],BD.PD[Per.P3],D$1,BD.PD[Pos],Tabla3[[#This Row],[Part.]])+SUMIFS(BD.PD[Pago 4],BD.PD[Per.P4],D$1,BD.PD[Pos],Tabla3[[#This Row],[Part.]])+SUMIFS(BD.PD[Pago 5],BD.PD[Per.P5],D$1,BD.PD[Pos],Tabla3[[#This Row],[Part.]]) -> 0 | E9: =SUMIFS(BD.PD[Pago 1],BD.PD[Per.P1],E$1,BD.PD[Pos],Tabla3[[#This Row],[Part.]])+SUMIFS(BD.PD[Pago 2],BD.PD[Per.P2],E$1,BD.PD[Pos],Tabla3[[#This Row],[Part.]])+SUMIFS(BD.PD[Pago 3],BD.PD[Per.P3],E$1,BD.PD[Pos],Tabla3[[#This Row],[Part.]])+SUMIFS(BD.PD[Pago 4],BD.PD[Per.P4],E$1,BD.PD[Pos],Tabla3[[#This Row],[Part.]])+SUMIFS(BD.PD[Pago 5],BD.PD[Per.P5],E$1,BD.PD[Pos],Tabla3[[#This Row],[Part.]]) -> 0 | F9: =SUMIFS(BD.PD[Pago 1],BD.PD[Per.P1],F$1,BD.PD[Pos],Tabla3[[#This Row],[Part.]])+SUMIFS(BD.PD[Pago 2],BD.PD[Per.P2],F$1,BD.PD[Pos],Tabla3[[#This Row],[Part.]])+SUMIFS(BD.PD[Pago 3],BD.PD[Per.P3],F$1,BD.PD[Pos],Tabla3[[#This Row],[Part.]])+SUMIFS(BD.PD[Pago 4],BD.PD[Per.P4],F$1,BD.PD[Pos],Tabla3[[#This Row],[Part.]])+SUMIFS(BD.PD[Pago 5],BD.PD[Per.P5],F$1,BD.PD[Pos],Tabla3[[#This Row],[Part.]]) -> 0 | G9: =SUMIFS(BD.PD[Pago 1],BD.PD[Per.P1],G$1,BD.PD[Pos],Tabla3[[#This Row],[Part.]])+SUMIFS(BD.PD[Pago 2],BD.PD[Per.P2],G$1,BD.PD[Pos],Tabla3[[#This Row],[Part.]])+SUMIFS(BD.PD[Pago 3],BD.PD[Per.P3],G$1,BD.PD[Pos],Tabla3[[#This Row],[Part.]])+SUMIFS(BD.PD[Pago 4],BD.PD[Per.P4],G$1,BD.PD[Pos],Tabla3[[#This Row],[Part.]])+SUMIFS(BD.PD[Pago 5],BD.PD[Per.P5],G$1,BD.PD[Pos],Tabla3[[#This Row],[Part.]]) -> 0 | H9: =SUMIFS(BD.PD[Pago 1],BD.PD[Per.P1],H$1,BD.PD[Pos],Tabla3[[#This Row],[Part.]])+SUMIFS(BD.PD[Pago 2],BD.PD[Per.P2],H$1,BD.PD[Pos],Tabla3[[#This Row],[Part.]])+SUMIFS(BD.PD[Pago 3],BD.PD[Per.P3],H$1,BD.PD[Pos],Tabla3[[#This Row],[Part.]])+SUMIFS(BD.PD[Pago 4],BD.PD[Per.P4],H$1,BD.PD[Pos],Tabla3[[#This Row],[Part.]])+SUMIFS(BD.PD[Pago 5],BD.PD[Per.P5],H$1,BD.PD[Pos],Tabla3[[#This Row],[Part.]]) -> 0 | I9: =SUMIFS(BD.PD[Pago 1],BD.PD[Per.P1],I$1,BD.PD[Pos],Tabla3[[#This Row],[Part.]])+SUMIFS(BD.PD[Pago 2],BD.PD[Per.P2],I$1,BD.PD[Pos],Tabla3[[#This Row],[Part.]])+SUMIFS(BD.PD[Pago 3],BD.PD[Per.P3],I$1,BD.PD[Pos],Tabla3[[#This Row],[Part.]])+SUMIFS(BD.PD[Pago 4],BD.PD[Per.P4],I$1,BD.PD[Pos],Tabla3[[#This Row],[Part.]])+SUMIFS(BD.PD[Pago 5],BD.PD[Per.P5],I$1,BD.PD[Pos],Tabla3[[#This Row],[Part.]]) -> 0 | J9: =SUMIFS(BD.PD[Pago 1],BD.PD[Per.P1],J$1,BD.PD[Pos],Tabla3[[#This Row],[Part.]])+SUMIFS(BD.PD[Pago 2],BD.PD[Per.P2],J$1,BD.PD[Pos],Tabla3[[#This Row],[Part.]])+SUMIFS(BD.PD[Pago 3],BD.PD[Per.P3],J$1,BD.PD[Pos],Tabla3[[#This Row],[Part.]])+SUMIFS(BD.PD[Pago 4],BD.PD[Per.P4],J$1,BD.PD[Pos],Tabla3[[#This Row],[Part.]])+SUMIFS(BD.PD[Pago 5],BD.PD[Per.P5],J$1,BD.PD[Pos],Tabla3[[#This Row],[Part.]]) -> 0 | K9: =SUMIFS(BD.PD[Pago 1],BD.PD[Per.P1],K$1,BD.PD[Pos],Tabla3[[#This Row],[Part.]])+SUMIFS(BD.PD[Pago 2],BD.PD[Per.P2],K$1,BD.PD[Pos],Tabla3[[#This Row],[Part.]])+SUMIFS(BD.PD[Pago 3],BD.PD[Per.P3],K$1,BD.PD[Pos],Tabla3[[#This Row],[Part.]])+SUMIFS(BD.PD[Pago 4],BD.PD[Per.P4],K$1,BD.PD[Pos],Tabla3[[#This Row],[Part.]])+SUMIFS(BD.PD[Pago 5],BD.PD[Per.P5],K$1,BD.PD[Pos],Tabla3[[#This Row],[Part.]]) -> 0 | ... AA9: =SUMIFS(BD.PD[Pago 1],BD.PD[Per.P1],AA$1,BD.PD[Pos],Tabla3[[#This Row],[Part.]])+SUMIFS(BD.PD[Pago 2],BD.PD[Per.P2],AA$1,BD.PD[Pos],Tabla3[[#This Row],[Part.]])+SUMIFS(BD.PD[Pago 3],BD.PD[Per.P3],AA$1,BD.PD[Pos],Tabla3[[#This Row],[Part.]])+SUMIFS(BD.PD[Pago 4],BD.PD[Per.P4],AA$1,BD.PD[Pos],Tabla3[[#This Row],[Part.]])+SUMIFS(BD.PD[Pago 5],BD.PD[Per.P5],AA$1,BD.PD[Pos],Tabla3[[#This Row],[Part.]]) -> 0 | AB9: =SUM(Tabla3[[#This Row],[P1]:[P24]]) -> 0
A10: 1.04 | B10: =VLOOKUP(Tabla3[[#This Row],[Part.]],PPto[],3,FALSE) -> 1.04 Diseño sanitario | C10: =SUMIF(BD.PD[Pos],Tabla3[[#This Row],[Part.]],BD.PD[Ppto. Orden Interna '[DOP']]) -> 0 | D10: =SUMIFS(BD.PD[Pago 1],BD.PD[Per.P1],D$1,BD.PD[Pos],Tabla3[[#This Row],[Part.]])+SUMIFS(BD.PD[Pago 2],BD.PD[Per.P2],D$1,BD.PD[Pos],Tabla3[[#This Row],[Part.]])+SUMIFS(BD.PD[Pago 3],BD.PD[Per.P3],D$1,BD.PD[Pos],Tabla3[[#This Row],[Part.]])+SUMIFS(BD.PD[Pago 4],BD.PD[Per.P4],D$1,BD.PD[Pos],Tabla3[[#This Row],[Part.]])+SUMIFS(BD.PD[Pago 5],BD.PD[Per.P5],D$1,BD.PD[Pos],Tabla3[[#This Row],[Part.]]) -> 0 | E10: =SUMIFS(BD.PD[Pago 1],BD.PD[Per.P1],E$1,BD.PD[Pos],Tabla3[[#This Row],[Part.]])+SUMIFS(BD.PD[Pago 2],BD.PD[Per.P2],E$1,BD.PD[Pos],Tabla3[[#This Row],[Part.]])+SUMIFS(BD.PD[Pago 3],BD.PD[Per.P3],E$1,BD.PD[Pos],Tabla3[[#This Row],[Part.]])+SUMIFS(BD.PD[Pago 4],BD.PD[Per.P4],E$1,BD.PD[Pos],Tabla3[[#This Row],[Part.]])+SUMIFS(BD.PD[Pago 5],BD.PD[Per.P5],E$1,BD.PD[Pos],Tabla3[[#This Row],[Part.]]) -> 0 | F10: =SUMIFS(BD.PD[Pago 1],BD.PD[Per.P1],F$1,BD.PD[Pos],Tabla3[[#This Row],[Part.]])+SUMIFS(BD.PD[Pago 2],BD.PD[Per.P2],F$1,BD.PD[Pos],Tabla3[[#This Row],[Part.]])+SUMIFS(BD.PD[Pago 3],BD.PD[Per.P3],F$1,BD.PD[Pos],Tabla3[[#This Row],[Part.]])+SUMIFS(BD.PD[Pago 4],BD.PD[Per.P4],F$1,BD.PD[Pos],Tabla3[[#This Row],[Part.]])+SUMIFS(BD.PD[Pago 5],BD.PD[Per.P5],F$1,BD.PD[Pos],Tabla3[[#This Row],[Part.]]) -> 0 | G10: =SUMIFS(BD.PD[Pago 1],BD.PD[Per.P1],G$1,BD.PD[Pos],Tabla3[[#This Row],[Part.]])+SUMIFS(BD.PD[Pago 2],BD.PD[Per.P2],G$1,BD.PD[Pos],Tabla3[[#This Row],[Part.]])+SUMIFS(BD.PD[Pago 3],BD.PD[Per.P3],G$1,BD.PD[Pos],Tabla3[[#This Row],[Part.]])+SUMIFS(BD.PD[Pago 4],BD.PD[Per.P4],G$1,BD.PD[Pos],Tabla3[[#This Row],[Part.]])+SUMIFS(BD.PD[Pago 5],BD.PD[Per.P5],G$1,BD.PD[Pos],Tabla3[[#This Row],[Part.]]) -> 0 | H10: =SUMIFS(BD.PD[Pago 1],BD.PD[Per.P1],H$1,BD.PD[Pos],Tabla3[[#This Row],[Part.]])+SUMIFS(BD.PD[Pago 2],BD.PD[Per.P2],H$1,BD.PD[Pos],Tabla3[[#This Row],[Part.]])+SUMIFS(BD.PD[Pago 3],BD.PD[Per.P3],H$1,BD.PD[Pos],Tabla3[[#This Row],[Part.]])+SUMIFS(BD.PD[Pago 4],BD.PD[Per.P4],H$1,BD.PD[Pos],Tabla3[[#This Row],[Part.]])+SUMIFS(BD.PD[Pago 5],BD.PD[Per.P5],H$1,BD.PD[Pos],Tabla3[[#This Row],[Part.]]) -> 0 | I10: =SUMIFS(BD.PD[Pago 1],BD.PD[Per.P1],I$1,BD.PD[Pos],Tabla3[[#This Row],[Part.]])+SUMIFS(BD.PD[Pago 2],BD.PD[Per.P2],I$1,BD.PD[Pos],Tabla3[[#This Row],[Part.]])+SUMIFS(BD.PD[Pago 3],BD.PD[Per.P3],I$1,BD.PD[Pos],Tabla3[[#This Row],[Part.]])+SUMIFS(BD.PD[Pago 4],BD.PD[Per.P4],I$1,BD.PD[Pos],Tabla3[[#This Row],[Part.]])+SUMIFS(BD.PD[Pago 5],BD.PD[Per.P5],I$1,BD.PD[Pos],Tabla3[[#This Row],[Part.]]) -> 0 | J10: =SUMIFS(BD.PD[Pago 1],BD.PD[Per.P1],J$1,BD.PD[Pos],Tabla3[[#This Row],[Part.]])+SUMIFS(BD.PD[Pago 2],BD.PD[Per.P2],J$1,BD.PD[Pos],Tabla3[[#This Row],[Part.]])+SUMIFS(BD.PD[Pago 3],BD.PD[Per.P3],J$1,BD.PD[Pos],Tabla3[[#This Row],[Part.]])+SUMIFS(BD.PD[Pago 4],BD.PD[Per.P4],J$1,BD.PD[Pos],Tabla3[[#This Row],[Part.]])+SUMIFS(BD.PD[Pago 5],BD.PD[Per.P5],J$1,BD.PD[Pos],Tabla3[[#This Row],[Part.]]) -> 0 | K10: =SUMIFS(BD.PD[Pago 1],BD.PD[Per.P1],K$1,BD.PD[Pos],Tabla3[[#This Row],[Part.]])+SUMIFS(BD.PD[Pago 2],BD.PD[Per.P2],K$1,BD.PD[Pos],Tabla3[[#This Row],[Part.]])+SUMIFS(BD.PD[Pago 3],BD.PD[Per.P3],K$1,BD.PD[Pos],Tabla3[[#This Row],[Part.]])+SUMIFS(BD.PD[Pago 4],BD.PD[Per.P4],K$1,BD.PD[Pos],Tabla3[[#This Row],[Part.]])+SUMIFS(BD.PD[Pago 5],BD.PD[Per.P5],K$1,BD.PD[Pos],Tabla3[[#This Row],[Part.]]) -> 0 | ... AA10: =SUMIFS(BD.PD[Pago 1],BD.PD[Per.P1],AA$1,BD.PD[Pos],Tabla3[[#This Row],[Part.]])+SUMIFS(BD.PD[Pago 2],BD.PD[Per.P2],AA$1,BD.PD[Pos],Tabla3[[#This Row],[Part.]])+SUMIFS(BD.PD[Pago 3],BD.PD[Per.P3],AA$1,BD.PD[Pos],Tabla3[[#This Row],[Part.]])+SUMIFS(BD.PD[Pago 4],BD.PD[Per.P4],AA$1,BD.PD[Pos],Tabla3[[#This Row],[Part.]])+SUMIFS(BD.PD[Pago 5],BD.PD[Per.P5],AA$1,BD.PD[Pos],Tabla3[[#This Row],[Part.]]) -> 0 | AB10: =SUM(Tabla3[[#This Row],[P1]:[P24]]) -> 0
A11: 1.05 | B11: =VLOOKUP(Tabla3[[#This Row],[Part.]],PPto[],3,FALSE) -> 1.05 Estudio Geotécnico | C11: =SUMIF(BD.PD[Pos],Tabla3[[#This Row],[Part.]],BD.PD[Ppto. Orden Interna '[DOP']]) -> 0 | D11: =SUMIFS(BD.PD[Pago 1],BD.PD[Per.P1],D$1,BD.PD[Pos],Tabla3[[#This Row],[Part.]])+SUMIFS(BD.PD[Pago 2],BD.PD[Per.P2],D$1,BD.PD[Pos],Tabla3[[#This Row],[Part.]])+SUMIFS(BD.PD[Pago 3],BD.PD[Per.P3],D$1,BD.PD[Pos],Tabla3[[#This Row],[Part.]])+SUMIFS(BD.PD[Pago 4],BD.PD[Per.P4],D$1,BD.PD[Pos],Tabla3[[#This Row],[Part.]])+SUMIFS(BD.PD[Pago 5],BD.PD[Per.P5],D$1,BD.PD[Pos],Tabla3[[#This Row],[Part.]]) -> 0 | E11: =SUMIFS(BD.PD[Pago 1],BD.PD[Per.P1],E$1,BD.PD[Pos],Tabla3[[#This Row],[Part.]])+SUMIFS(BD.PD[Pago 2],BD.PD[Per.P2],E$1,BD.PD[Pos],Tabla3[[#This Row],[Part.]])+SUMIFS(BD.PD[Pago 3],BD.PD[Per.P3],E$1,BD.PD[Pos],Tabla3[[#This Row],[Part.]])+SUMIFS(BD.PD[Pago 4],BD.PD[Per.P4],E$1,BD.PD[Pos],Tabla3[[#This Row],[Part.]])+SUMIFS(BD.PD[Pago 5],BD.PD[Per.P5],E$1,BD.PD[Pos],Tabla3[[#This Row],[Part.]]) -> 0 | F11: =SUMIFS(BD.PD[Pago 1],BD.PD[Per.P1],F$1,BD.PD[Pos],Tabla3[[#This Row],[Part.]])+SUMIFS(BD.PD[Pago 2],BD.PD[Per.P2],F$1,BD.PD[Pos],Tabla3[[#This Row],[Part.]])+SUMIFS(BD.PD[Pago 3],BD.PD[Per.P3],F$1,BD.PD[Pos],Tabla3[[#This Row],[Part.]])+SUMIFS(BD.PD[Pago 4],BD.PD[Per.P4],F$1,BD.PD[Pos],Tabla3[[#This Row],[Part.]])+SUMIFS(BD.PD[Pago 5],BD.PD[Per.P5],F$1,BD.PD[Pos],Tabla3[[#This Row],[Part.]]) -> 0 | G11: =SUMIFS(BD.PD[Pago 1],BD.PD[Per.P1],G$1,BD.PD[Pos],Tabla3[[#This Row],[Part.]])+SUMIFS(BD.PD[Pago 2],BD.PD[Per.P2],G$1,BD.PD[Pos],Tabla3[[#This Row],[Part.]])+SUMIFS(BD.PD[Pago 3],BD.PD[Per.P3],G$1,BD.PD[Pos],Tabla3[[#This Row],[Part.]])+SUMIFS(BD.PD[Pago 4],BD.PD[Per.P4],G$1,BD.PD[Pos],Tabla3[[#This Row],[Part.]])+SUMIFS(BD.PD[Pago 5],BD.PD[Per.P5],G$1,BD.PD[Pos],Tabla3[[#This Row],[Part.]]) -> 0 | H11: =SUMIFS(BD.PD[Pago 1],BD.PD[Per.P1],H$1,BD.PD[Pos],Tabla3[[#This Row],[Part.]])+SUMIFS(BD.PD[Pago 2],BD.PD[Per.P2],H$1,BD.PD[Pos],Tabla3[[#This Row],[Part.]])+SUMIFS(BD.PD[Pago 3],BD.PD[Per.P3],H$1,BD.PD[Pos],Tabla3[[#This Row],[Part.]])+SUMIFS(BD.PD[Pago 4],BD.PD[Per.P4],H$1,BD.PD[Pos],Tabla3[[#This Row],[Part.]])+SUMIFS(BD.PD[Pago 5],BD.PD[Per.P5],H$1,BD.PD[Pos],Tabla3[[#This Row],[Part.]]) -> 0 | I11: =SUMIFS(BD.PD[Pago 1],BD.PD[Per.P1],I$1,BD.PD[Pos],Tabla3[[#This Row],[Part.]])+SUMIFS(BD.PD[Pago 2],BD.PD[Per.P2],I$1,BD.PD[Pos],Tabla3[[#This Row],[Part.]])+SUMIFS(BD.PD[Pago 3],BD.PD[Per.P3],I$1,BD.PD[Pos],Tabla3[[#This Row],[Part.]])+SUMIFS(BD.PD[Pago 4],BD.PD[Per.P4],I$1,BD.PD[Pos],Tabla3[[#This Row],[Part.]])+SUMIFS(BD.PD[Pago 5],BD.PD[Per.P5],I$1,BD.PD[Pos],Tabla3[[#This Row],[Part.]]) -> 0 | J11: =SUMIFS(BD.PD[Pago 1],BD.PD[Per.P1],J$1,BD.PD[Pos],Tabla3[[#This Row],[Part.]])+SUMIFS(BD.PD[Pago 2],BD.PD[Per.P2],J$1,BD.PD[Pos],Tabla3[[#This Row],[Part.]])+SUMIFS(BD.PD[Pago 3],BD.PD[Per.P3],J$1,BD.PD[Pos],Tabla3[[#This Row],[Part.]])+SUMIFS(BD.PD[Pago 4],BD.PD[Per.P4],J$1,BD.PD[Pos],Tabla3[[#This Row],[Part.]])+SUMIFS(BD.PD[Pago 5],BD.PD[Per.P5],J$1,BD.PD[Pos],Tabla3[[#This Row],[Part.]]) -> 0 | K11: =SUMIFS(BD.PD[Pago 1],BD.PD[Per.P1],K$1,BD.PD[Pos],Tabla3[[#This Row],[Part.]])+SUMIFS(BD.PD[Pago 2],BD.PD[Per.P2],K$1,BD.PD[Pos],Tabla3[[#This Row],[Part.]])+SUMIFS(BD.PD[Pago 3],BD.PD[Per.P3],K$1,BD.PD[Pos],Tabla3[[#This Row],[Part.]])+SUMIFS(BD.PD[Pago 4],BD.PD[Per.P4],K$1,BD.PD[Pos],Tabla3[[#This Row],[Part.]])+SUMIFS(BD.PD[Pago 5],BD.PD[Per.P5],K$1,BD.PD[Pos],Tabla3[[#This Row],[Part.]]) -> 0 | ... AA11: =SUMIFS(BD.PD[Pago 1],BD.PD[Per.P1],AA$1,BD.PD[Pos],Tabla3[[#This Row],[Part.]])+SUMIFS(BD.PD[Pago 2],BD.PD[Per.P2],AA$1,BD.PD[Pos],Tabla3[[#This Row],[Part.]])+SUMIFS(BD.PD[Pago 3],BD.PD[Per.P3],AA$1,BD.PD[Pos],Tabla3[[#This Row],[Part.]])+SUMIFS(BD.PD[Pago 4],BD.PD[Per.P4],AA$1,BD.PD[Pos],Tabla3[[#This Row],[Part.]])+SUMIFS(BD.PD[Pago 5],BD.PD[Per.P5],AA$1,BD.PD[Pos],Tabla3[[#This Row],[Part.]]) -> 0 | AB11: =SUM(Tabla3[[#This Row],[P1]:[P24]]) -> 0
A12: 1.06 | B12: =VLOOKUP(Tabla3[[#This Row],[Part.]],PPto[],3,FALSE) -> 1.06 Levantamiento topográfico | C12: =SUMIF(BD.PD[Pos],Tabla3[[#This Row],[Part.]],BD.PD[Ppto. Orden Interna '[DOP']]) -> 0 | D12: =SUMIFS(BD.PD[Pago 1],BD.PD[Per.P1],D$1,BD.PD[Pos],Tabla3[[#This Row],[Part.]])+SUMIFS(BD.PD[Pago 2],BD.PD[Per.P2],D$1,BD.PD[Pos],Tabla3[[#This Row],[Part.]])+SUMIFS(BD.PD[Pago 3],BD.PD[Per.P3],D$1,BD.PD[Pos],Tabla3[[#This Row],[Part.]])+SUMIFS(BD.PD[Pago 4],BD.PD[Per.P4],D$1,BD.PD[Pos],Tabla3[[#This Row],[Part.]])+SUMIFS(BD.PD[Pago 5],BD.PD[Per.P5],D$1,BD.PD[Pos],Tabla3[[#This Row],[Part.]]) -> 0 | E12: =SUMIFS(BD.PD[Pago 1],BD.PD[Per.P1],E$1,BD.PD[Pos],Tabla3[[#This Row],[Part.]])+SUMIFS(BD.PD[Pago 2],BD.PD[Per.P2],E$1,BD.PD[Pos],Tabla3[[#This Row],[Part.]])+SUMIFS(BD.PD[Pago 3],BD.PD[Per.P3],E$1,BD.PD[Pos],Tabla3[[#This Row],[Part.]])+SUMIFS(BD.PD[Pago 4],BD.PD[Per.P4],E$1,BD.PD[Pos],Tabla3[[#This Row],[Part.]])+SUMIFS(BD.PD[Pago 5],BD.PD[Per.P5],E$1,BD.PD[Pos],Tabla3[[#This Row],[Part.]]) -> 0 | F12: =SUMIFS(BD.PD[Pago 1],BD.PD[Per.P1],F$1,BD.PD[Pos],Tabla3[[#This Row],[Part.]])+SUMIFS(BD.PD[Pago 2],BD.PD[Per.P2],F$1,BD.PD[Pos],Tabla3[[#This Row],[Part.]])+SUMIFS(BD.PD[Pago 3],BD.PD[Per.P3],F$1,BD.PD[Pos],Tabla3[[#This Row],[Part.]])+SUMIFS(BD.PD[Pago 4],BD.PD[Per.P4],F$1,BD.PD[Pos],Tabla3[[#This Row],[Part.]])+SUMIFS(BD.PD[Pago 5],BD.PD[Per.P5],F$1,BD.PD[Pos],Tabla3[[#This Row],[Part.]]) -> 0 | G12: =SUMIFS(BD.PD[Pago 1],BD.PD[Per.P1],G$1,BD.PD[Pos],Tabla3[[#This Row],[Part.]])+SUMIFS(BD.PD[Pago 2],BD.PD[Per.P2],G$1,BD.PD[Pos],Tabla3[[#This Row],[Part.]])+SUMIFS(BD.PD[Pago 3],BD.PD[Per.P3],G$1,BD.PD[Pos],Tabla3[[#This Row],[Part.]])+SUMIFS(BD.PD[Pago 4],BD.PD[Per.P4],G$1,BD.PD[Pos],Tabla3[[#This Row],[Part.]])+SUMIFS(BD.PD[Pago 5],BD.PD[Per.P5],G$1,BD.PD[Pos],Tabla3[[#This Row],[Part.]]) -> 0 | H12: =SUMIFS(BD.PD[Pago 1],BD.PD[Per.P1],H$1,BD.PD[Pos],Tabla3[[#This Row],[Part.]])+SUMIFS(BD.PD[Pago 2],BD.PD[Per.P2],H$1,BD.PD[Pos],Tabla3[[#This Row],[Part.]])+SUMIFS(BD.PD[Pago 3],BD.PD[Per.P3],H$1,BD.PD[Pos],Tabla3[[#This Row],[Part.]])+SUMIFS(BD.PD[Pago 4],BD.PD[Per.P4],H$1,BD.PD[Pos],Tabla3[[#This Row],[Part.]])+SUMIFS(BD.PD[Pago 5],BD.PD[Per.P5],H$1,BD.PD[Pos],Tabla3[[#This Row],[Part.]]) -> 0 | I12: =SUMIFS(BD.PD[Pago 1],BD.PD[Per.P1],I$1,BD.PD[Pos],Tabla3[[#This Row],[Part.]])+SUMIFS(BD.PD[Pago 2],BD.PD[Per.P2],I$1,BD.PD[Pos],Tabla3[[#This Row],[Part.]])+SUMIFS(BD.PD[Pago 3],BD.PD[Per.P3],I$1,BD.PD[Pos],Tabla3[[#This Row],[Part.]])+SUMIFS(BD.PD[Pago 4],BD.PD[Per.P4],I$1,BD.PD[Pos],Tabla3[[#This Row],[Part.]])+SUMIFS(BD.PD[Pago 5],BD.PD[Per.P5],I$1,BD.PD[Pos],Tabla3[[#This Row],[Part.]]) -> 0 | J12: =SUMIFS(BD.PD[Pago 1],BD.PD[Per.P1],J$1,BD.PD[Pos],Tabla3[[#This Row],[Part.]])+SUMIFS(BD.PD[Pago 2],BD.PD[Per.P2],J$1,BD.PD[Pos],Tabla3[[#This Row],[Part.]])+SUMIFS(BD.PD[Pago 3],BD.PD[Per.P3],J$1,BD.PD[Pos],Tabla3[[#This Row],[Part.]])+SUMIFS(BD.PD[Pago 4],BD.PD[Per.P4],J$1,BD.PD[Pos],Tabla3[[#This Row],[Part.]])+SUMIFS(BD.PD[Pago 5],BD.PD[Per.P5],J$1,BD.PD[Pos],Tabla3[[#This Row],[Part.]]) -> 0 | K12: =SUMIFS(BD.PD[Pago 1],BD.PD[Per.P1],K$1,BD.PD[Pos],Tabla3[[#This Row],[Part.]])+SUMIFS(BD.PD[Pago 2],BD.PD[Per.P2],K$1,BD.PD[Pos],Tabla3[[#This Row],[Part.]])+SUMIFS(BD.PD[Pago 3],BD.PD[Per.P3],K$1,BD.PD[Pos],Tabla3[[#This Row],[Part.]])+SUMIFS(BD.PD[Pago 4],BD.PD[Per.P4],K$1,BD.PD[Pos],Tabla3[[#This Row],[Part.]])+SUMIFS(BD.PD[Pago 5],BD.PD[Per.P5],K$1,BD.PD[Pos],Tabla3[[#This Row],[Part.]]) -> 0 | ... AA12: =SUMIFS(BD.PD[Pago 1],BD.PD[Per.P1],AA$1,BD.PD[Pos],Tabla3[[#This Row],[Part.]])+SUMIFS(BD.PD[Pago 2],BD.PD[Per.P2],AA$1,BD.PD[Pos],Tabla3[[#This Row],[Part.]])+SUMIFS(BD.PD[Pago 3],BD.PD[Per.P3],AA$1,BD.PD[Pos],Tabla3[[#This Row],[Part.]])+SUMIFS(BD.PD[Pago 4],BD.PD[Per.P4],AA$1,BD.PD[Pos],Tabla3[[#This Row],[Part.]])+SUMIFS(BD.PD[Pago 5],BD.PD[Per.P5],AA$1,BD.PD[Pos],Tabla3[[#This Row],[Part.]]) -> 0 | AB12: =SUM(Tabla3[[#This Row],[P1]:[P24]]) -> 0
A13: 1.07 | B13: =VLOOKUP(Tabla3[[#This Row],[Part.]],PPto[],3,FALSE) -> 1.07 Permisos | C13: =SUMIF(BD.PD[Pos],Tabla3[[#This Row],[Part.]],BD.PD[Ppto. Orden Interna '[DOP']]) -> 0 | D13: =SUMIFS(BD.PD[Pago 1],BD.PD[Per.P1],D$1,BD.PD[Pos],Tabla3[[#This Row],[Part.]])+SUMIFS(BD.PD[Pago 2],BD.PD[Per.P2],D$1,BD.PD[Pos],Tabla3[[#This Row],[Part.]])+SUMIFS(BD.PD[Pago 3],BD.PD[Per.P3],D$1,BD.PD[Pos],Tabla3[[#This Row],[Part.]])+SUMIFS(BD.PD[Pago 4],BD.PD[Per.P4],D$1,BD.PD[Pos],Tabla3[[#This Row],[Part.]])+SUMIFS(BD.PD[Pago 5],BD.PD[Per.P5],D$1,BD.PD[Pos],Tabla3[[#This Row],[Part.]]) -> 0 | E13: =SUMIFS(BD.PD[Pago 1],BD.PD[Per.P1],E$1,BD.PD[Pos],Tabla3[[#This Row],[Part.]])+SUMIFS(BD.PD[Pago 2],BD.PD[Per.P2],E$1,BD.PD[Pos],Tabla3[[#This Row],[Part.]])+SUMIFS(BD.PD[Pago 3],BD.PD[Per.P3],E$1,BD.PD[Pos],Tabla3[[#This Row],[Part.]])+SUMIFS(BD.PD[Pago 4],BD.PD[Per.P4],E$1,BD.PD[Pos],Tabla3[[#This Row],[Part.]])+SUMIFS(BD.PD[Pago 5],BD.PD[Per.P5],E$1,BD.PD[Pos],Tabla3[[#This Row],[Part.]]) -> 0 | F13: =SUMIFS(BD.PD[Pago 1],BD.PD[Per.P1],F$1,BD.PD[Pos],Tabla3[[#This Row],[Part.]])+SUMIFS(BD.PD[Pago 2],BD.PD[Per.P2],F$1,BD.PD[Pos],Tabla3[[#This Row],[Part.]])+SUMIFS(BD.PD[Pago 3],BD.PD[Per.P3],F$1,BD.PD[Pos],Tabla3[[#This Row],[Part.]])+SUMIFS(BD.PD[Pago 4],BD.PD[Per.P4],F$1,BD.PD[Pos],Tabla3[[#This Row],[Part.]])+SUMIFS(BD.PD[Pago 5],BD.PD[Per.P5],F$1,BD.PD[Pos],Tabla3[[#This Row],[Part.]]) -> 0 | G13: =SUMIFS(BD.PD[Pago 1],BD.PD[Per.P1],G$1,BD.PD[Pos],Tabla3[[#This Row],[Part.]])+SUMIFS(BD.PD[Pago 2],BD.PD[Per.P2],G$1,BD.PD[Pos],Tabla3[[#This Row],[Part.]])+SUMIFS(BD.PD[Pago 3],BD.PD[Per.P3],G$1,BD.PD[Pos],Tabla3[[#This Row],[Part.]])+SUMIFS(BD.PD[Pago 4],BD.PD[Per.P4],G$1,BD.PD[Pos],Tabla3[[#This Row],[Part.]])+SUMIFS(BD.PD[Pago 5],BD.PD[Per.P5],G$1,BD.PD[Pos],Tabla3[[#This Row],[Part.]]) -> 0 | H13: =SUMIFS(BD.PD[Pago 1],BD.PD[Per.P1],H$1,BD.PD[Pos],Tabla3[[#This Row],[Part.]])+SUMIFS(BD.PD[Pago 2],BD.PD[Per.P2],H$1,BD.PD[Pos],Tabla3[[#This Row],[Part.]])+SUMIFS(BD.PD[Pago 3],BD.PD[Per.P3],H$1,BD.PD[Pos],Tabla3[[#This Row],[Part.]])+SUMIFS(BD.PD[Pago 4],BD.PD[Per.P4],H$1,BD.PD[Pos],Tabla3[[#This Row],[Part.]])+SUMIFS(BD.PD[Pago 5],BD.PD[Per.P5],H$1,BD.PD[Pos],Tabla3[[#This Row],[Part.]]) -> 0 | I13: =SUMIFS(BD.PD[Pago 1],BD.PD[Per.P1],I$1,BD.PD[Pos],Tabla3[[#This Row],[Part.]])+SUMIFS(BD.PD[Pago 2],BD.PD[Per.P2],I$1,BD.PD[Pos],Tabla3[[#This Row],[Part.]])+SUMIFS(BD.PD[Pago 3],BD.PD[Per.P3],I$1,BD.PD[Pos],Tabla3[[#This Row],[Part.]])+SUMIFS(BD.PD[Pago 4],BD.PD[Per.P4],I$1,BD.PD[Pos],Tabla3[[#This Row],[Part.]])+SUMIFS(BD.PD[Pago 5],BD.PD[Per.P5],I$1,BD.PD[Pos],Tabla3[[#This Row],[Part.]]) -> 0 | J13: =SUMIFS(BD.PD[Pago 1],BD.PD[Per.P1],J$1,BD.PD[Pos],Tabla3[[#This Row],[Part.]])+SUMIFS(BD.PD[Pago 2],BD.PD[Per.P2],J$1,BD.PD[Pos],Tabla3[[#This Row],[Part.]])+SUMIFS(BD.PD[Pago 3],BD.PD[Per.P3],J$1,BD.PD[Pos],Tabla3[[#This Row],[Part.]])+SUMIFS(BD.PD[Pago 4],BD.PD[Per.P4],J$1,BD.PD[Pos],Tabla3[[#This Row],[Part.]])+SUMIFS(BD.PD[Pago 5],BD.PD[Per.P5],J$1,BD.PD[Pos],Tabla3[[#This Row],[Part.]]) -> 0 | K13: =SUMIFS(BD.PD[Pago 1],BD.PD[Per.P1],K$1,BD.PD[Pos],Tabla3[[#This Row],[Part.]])+SUMIFS(BD.PD[Pago 2],BD.PD[Per.P2],K$1,BD.PD[Pos],Tabla3[[#This Row],[Part.]])+SUMIFS(BD.PD[Pago 3],BD.PD[Per.P3],K$1,BD.PD[Pos],Tabla3[[#This Row],[Part.]])+SUMIFS(BD.PD[Pago 4],BD.PD[Per.P4],K$1,BD.PD[Pos],Tabla3[[#This Row],[Part.]])+SUMIFS(BD.PD[Pago 5],BD.PD[Per.P5],K$1,BD.PD[Pos],Tabla3[[#This Row],[Part.]]) -> 0 | ... AA13: =SUMIFS(BD.PD[Pago 1],BD.PD[Per.P1],AA$1,BD.PD[Pos],Tabla3[[#This Row],[Part.]])+SUMIFS(BD.PD[Pago 2],BD.PD[Per.P2],AA$1,BD.PD[Pos],Tabla3[[#This Row],[Part.]])+SUMIFS(BD.PD[Pago 3],BD.PD[Per.P3],AA$1,BD.PD[Pos],Tabla3[[#This Row],[Part.]])+SUMIFS(BD.PD[Pago 4],BD.PD[Per.P4],AA$1,BD.PD[Pos],Tabla3[[#This Row],[Part.]])+SUMIFS(BD.PD[Pago 5],BD.PD[Per.P5],AA$1,BD.PD[Pos],Tabla3[[#This Row],[Part.]]) -> 0 | AB13: =SUM(Tabla3[[#This Row],[P1]:[P24]]) -> 0
A14: 1.08 | B14: =VLOOKUP(Tabla3[[#This Row],[Part.]],PPto[],3,FALSE) -> 1.08 Diseño sistema contra incendios | C14: =SUMIF(BD.PD[Pos],Tabla3[[#This Row],[Part.]],BD.PD[Ppto. Orden Interna '[DOP']]) -> 0 | D14: =SUMIFS(BD.PD[Pago 1],BD.PD[Per.P1],D$1,BD.PD[Pos],Tabla3[[#This Row],[Part.]])+SUMIFS(BD.PD[Pago 2],BD.PD[Per.P2],D$1,BD.PD[Pos],Tabla3[[#This Row],[Part.]])+SUMIFS(BD.PD[Pago 3],BD.PD[Per.P3],D$1,BD.PD[Pos],Tabla3[[#This Row],[Part.]])+SUMIFS(BD.PD[Pago 4],BD.PD[Per.P4],D$1,BD.PD[Pos],Tabla3[[#This Row],[Part.]])+SUMIFS(BD.PD[Pago 5],BD.PD[Per.P5],D$1,BD.PD[Pos],Tabla3[[#This Row],[Part.]]) -> 0 | E14: =SUMIFS(BD.PD[Pago 1],BD.PD[Per.P1],E$1,BD.PD[Pos],Tabla3[[#This Row],[Part.]])+SUMIFS(BD.PD[Pago 2],BD.PD[Per.P2],E$1,BD.PD[Pos],Tabla3[[#This Row],[Part.]])+SUMIFS(BD.PD[Pago 3],BD.PD[Per.P3],E$1,BD.PD[Pos],Tabla3[[#This Row],[Part.]])+SUMIFS(BD.PD[Pago 4],BD.PD[Per.P4],E$1,BD.PD[Pos],Tabla3[[#This Row],[Part.]])+SUMIFS(BD.PD[Pago 5],BD.PD[Per.P5],E$1,BD.PD[Pos],Tabla3[[#This Row],[Part.]]) -> 0 | F14: =SUMIFS(BD.PD[Pago 1],BD.PD[Per.P1],F$1,BD.PD[Pos],Tabla3[[#This Row],[Part.]])+SUMIFS(BD.PD[Pago 2],BD.PD[Per.P2],F$1,BD.PD[Pos],Tabla3[[#This Row],[Part.]])+SUMIFS(BD.PD[Pago 3],BD.PD[Per.P3],F$1,BD.PD[Pos],Tabla3[[#This Row],[Part.]])+SUMIFS(BD.PD[Pago 4],BD.PD[Per.P4],F$1,BD.PD[Pos],Tabla3[[#This Row],[Part.]])+SUMIFS(BD.PD[Pago 5],BD.PD[Per.P5],F$1,BD.PD[Pos],Tabla3[[#This Row],[Part.]]) -> 0 | G14: =SUMIFS(BD.PD[Pago 1],BD.PD[Per.P1],G$1,BD.PD[Pos],Tabla3[[#This Row],[Part.]])+SUMIFS(BD.PD[Pago 2],BD.PD[Per.P2],G$1,BD.PD[Pos],Tabla3[[#This Row],[Part.]])+SUMIFS(BD.PD[Pago 3],BD.PD[Per.P3],G$1,BD.PD[Pos],Tabla3[[#This Row],[Part.]])+SUMIFS(BD.PD[Pago 4],BD.PD[Per.P4],G$1,BD.PD[Pos],Tabla3[[#This Row],[Part.]])+SUMIFS(BD.PD[Pago 5],BD.PD[Per.P5],G$1,BD.PD[Pos],Tabla3[[#This Row],[Part.]]) -> 0 | H14: =SUMIFS(BD.PD[Pago 1],BD.PD[Per.P1],H$1,BD.PD[Pos],Tabla3[[#This Row],[Part.]])+SUMIFS(BD.PD[Pago 2],BD.PD[Per.P2],H$1,BD.PD[Pos],Tabla3[[#This Row],[Part.]])+SUMIFS(BD.PD[Pago 3],BD.PD[Per.P3],H$1,BD.PD[Pos],Tabla3[[#This Row],[Part.]])+SUMIFS(BD.PD[Pago 4],BD.PD[Per.P4],H$1,BD.PD[Pos],Tabla3[[#This Row],[Part.]])+SUMIFS(BD.PD[Pago 5],BD.PD[Per.P5],H$1,BD.PD[Pos],Tabla3[[#This Row],[Part.]]) -> 0 | I14: =SUMIFS(BD.PD[Pago 1],BD.PD[Per.P1],I$1,BD.PD[Pos],Tabla3[[#This Row],[Part.]])+SUMIFS(BD.PD[Pago 2],BD.PD[Per.P2],I$1,BD.PD[Pos],Tabla3[[#This Row],[Part.]])+SUMIFS(BD.PD[Pago 3],BD.PD[Per.P3],I$1,BD.PD[Pos],Tabla3[[#This Row],[Part.]])+SUMIFS(BD.PD[Pago 4],BD.PD[Per.P4],I$1,BD.PD[Pos],Tabla3[[#This Row],[Part.]])+SUMIFS(BD.PD[Pago 5],BD.PD[Per.P5],I$1,BD.PD[Pos],Tabla3[[#This Row],[Part.]]) -> 0 | J14: =SUMIFS(BD.PD[Pago 1],BD.PD[Per.P1],J$1,BD.PD[Pos],Tabla3[[#This Row],[Part.]])+SUMIFS(BD.PD[Pago 2],BD.PD[Per.P2],J$1,BD.PD[Pos],Tabla3[[#This Row],[Part.]])+SUMIFS(BD.PD[Pago 3],BD.PD[Per.P3],J$1,BD.PD[Pos],Tabla3[[#This Row],[Part.]])+SUMIFS(BD.PD[Pago 4],BD.PD[Per.P4],J$1,BD.PD[Pos],Tabla3[[#This Row],[Part.]])+SUMIFS(BD.PD[Pago 5],BD.PD[Per.P5],J$1,BD.PD[Pos],Tabla3[[#This Row],[Part.]]) -> 0 | K14: =SUMIFS(BD.PD[Pago 1],BD.PD[Per.P1],K$1,BD.PD[Pos],Tabla3[[#This Row],[Part.]])+SUMIFS(BD.PD[Pago 2],BD.PD[Per.P2],K$1,BD.PD[Pos],Tabla3[[#This Row],[Part.]])+SUMIFS(BD.PD[Pago 3],BD.PD[Per.P3],K$1,BD.PD[Pos],Tabla3[[#This Row],[Part.]])+SUMIFS(BD.PD[Pago 4],BD.PD[Per.P4],K$1,BD.PD[Pos],Tabla3[[#This Row],[Part.]])+SUMIFS(BD.PD[Pago 5],BD.PD[Per.P5],K$1,BD.PD[Pos],Tabla3[[#This Row],[Part.]]) -> 0 | ... AA14: =SUMIFS(BD.PD[Pago 1],BD.PD[Per.P1],AA$1,BD.PD[Pos],Tabla3[[#This Row],[Part.]])+SUMIFS(BD.PD[Pago 2],BD.PD[Per.P2],AA$1,BD.PD[Pos],Tabla3[[#This Row],[Part.]])+SUMIFS(BD.PD[Pago 3],BD.PD[Per.P3],AA$1,BD.PD[Pos],Tabla3[[#This Row],[Part.]])+SUMIFS(BD.PD[Pago 4],BD.PD[Per.P4],AA$1,BD.PD[Pos],Tabla3[[#This Row],[Part.]])+SUMIFS(BD.PD[Pago 5],BD.PD[Per.P5],AA$1,BD.PD[Pos],Tabla3[[#This Row],[Part.]]) -> 0 | AB14: =SUM(Tabla3[[#This Row],[P1]:[P24]]) -> 0
A15: 1.09 | B15: =VLOOKUP(Tabla3[[#This Row],[Part.]],PPto[],3,FALSE) -> 1.09 Diseño sistema gas | C15: =SUMIF(BD.PD[Pos],Tabla3[[#This Row],[Part.]],BD.PD[Ppto. Orden Interna '[DOP']]) -> 0 | D15: =SUMIFS(BD.PD[Pago 1],BD.PD[Per.P1],D$1,BD.PD[Pos],Tabla3[[#This Row],[Part.]])+SUMIFS(BD.PD[Pago 2],BD.PD[Per.P2],D$1,BD.PD[Pos],Tabla3[[#This Row],[Part.]])+SUMIFS(BD.PD[Pago 3],BD.PD[Per.P3],D$1,BD.PD[Pos],Tabla3[[#This Row],[Part.]])+SUMIFS(BD.PD[Pago 4],BD.PD[Per.P4],D$1,BD.PD[Pos],Tabla3[[#This Row],[Part.]])+SUMIFS(BD.PD[Pago 5],BD.PD[Per.P5],D$1,BD.PD[Pos],Tabla3[[#This Row],[Part.]]) -> 0 | E15: =SUMIFS(BD.PD[Pago 1],BD.PD[Per.P1],E$1,BD.PD[Pos],Tabla3[[#This Row],[Part.]])+SUMIFS(BD.PD[Pago 2],BD.PD[Per.P2],E$1,BD.PD[Pos],Tabla3[[#This Row],[Part.]])+SUMIFS(BD.PD[Pago 3],BD.PD[Per.P3],E$1,BD.PD[Pos],Tabla3[[#This Row],[Part.]])+SUMIFS(BD.PD[Pago 4],BD.PD[Per.P4],E$1,BD.PD[Pos],Tabla3[[#This Row],[Part.]])+SUMIFS(BD.PD[Pago 5],BD.PD[Per.P5],E$1,BD.PD[Pos],Tabla3[[#This Row],[Part.]]) -> 0 | F15: =SUMIFS(BD.PD[Pago 1],BD.PD[Per.P1],F$1,BD.PD[Pos],Tabla3[[#This Row],[Part.]])+SUMIFS(BD.PD[Pago 2],BD.PD[Per.P2],F$1,BD.PD[Pos],Tabla3[[#This Row],[Part.]])+SUMIFS(BD.PD[Pago 3],BD.PD[Per.P3],F$1,BD.PD[Pos],Tabla3[[#This Row],[Part.]])+SUMIFS(BD.PD[Pago 4],BD.PD[Per.P4],F$1,BD.PD[Pos],Tabla3[[#This Row],[Part.]])+SUMIFS(BD.PD[Pago 5],BD.PD[Per.P5],F$1,BD.PD[Pos],Tabla3[[#This Row],[Part.]]) -> 0 | G15: =SUMIFS(BD.PD[Pago 1],BD.PD[Per.P1],G$1,BD.PD[Pos],Tabla3[[#This Row],[Part.]])+SUMIFS(BD.PD[Pago 2],BD.PD[Per.P2],G$1,BD.PD[Pos],Tabla3[[#This Row],[Part.]])+SUMIFS(BD.PD[Pago 3],BD.PD[Per.P3],G$1,BD.PD[Pos],Tabla3[[#This Row],[Part.]])+SUMIFS(BD.PD[Pago 4],BD.PD[Per.P4],G$1,BD.PD[Pos],Tabla3[[#This Row],[Part.]])+SUMIFS(BD.PD[Pago 5],BD.PD[Per.P5],G$1,BD.PD[Pos],Tabla3[[#This Row],[Part.]]) -> 0 | H15: =SUMIFS(BD.PD[Pago 1],BD.PD[Per.P1],H$1,BD.PD[Pos],Tabla3[[#This Row],[Part.]])+SUMIFS(BD.PD[Pago 2],BD.PD[Per.P2],H$1,BD.PD[Pos],Tabla3[[#This Row],[Part.]])+SUMIFS(BD.PD[Pago 3],BD.PD[Per.P3],H$1,BD.PD[Pos],Tabla3[[#This Row],[Part.]])+SUMIFS(BD.PD[Pago 4],BD.PD[Per.P4],H$1,BD.PD[Pos],Tabla3[[#This Row],[Part.]])+SUMIFS(BD.PD[Pago 5],BD.PD[Per.P5],H$1,BD.PD[Pos],Tabla3[[#This Row],[Part.]]) -> 0 | I15: =SUMIFS(BD.PD[Pago 1],BD.PD[Per.P1],I$1,BD.PD[Pos],Tabla3[[#This Row],[Part.]])+SUMIFS(BD.PD[Pago 2],BD.PD[Per.P2],I$1,BD.PD[Pos],Tabla3[[#This Row],[Part.]])+SUMIFS(BD.PD[Pago 3],BD.PD[Per.P3],I$1,BD.PD[Pos],Tabla3[[#This Row],[Part.]])+SUMIFS(BD.PD[Pago 4],BD.PD[Per.P4],I$1,BD.PD[Pos],Tabla3[[#This Row],[Part.]])+SUMIFS(BD.PD[Pago 5],BD.PD[Per.P5],I$1,BD.PD[Pos],Tabla3[[#This Row],[Part.]]) -> 0 | J15: =SUMIFS(BD.PD[Pago 1],BD.PD[Per.P1],J$1,BD.PD[Pos],Tabla3[[#This Row],[Part.]])+SUMIFS(BD.PD[Pago 2],BD.PD[Per.P2],J$1,BD.PD[Pos],Tabla3[[#This Row],[Part.]])+SUMIFS(BD.PD[Pago 3],BD.PD[Per.P3],J$1,BD.PD[Pos],Tabla3[[#This Row],[Part.]])+SUMIFS(BD.PD[Pago 4],BD.PD[Per.P4],J$1,BD.PD[Pos],Tabla3[[#This Row],[Part.]])+SUMIFS(BD.PD[Pago 5],BD.PD[Per.P5],J$1,BD.PD[Pos],Tabla3[[#This Row],[Part.]]) -> 0 | K15: =SUMIFS(BD.PD[Pago 1],BD.PD[Per.P1],K$1,BD.PD[Pos],Tabla3[[#This Row],[Part.]])+SUMIFS(BD.PD[Pago 2],BD.PD[Per.P2],K$1,BD.PD[Pos],Tabla3[[#This Row],[Part.]])+SUMIFS(BD.PD[Pago 3],BD.PD[Per.P3],K$1,BD.PD[Pos],Tabla3[[#This Row],[Part.]])+SUMIFS(BD.PD[Pago 4],BD.PD[Per.P4],K$1,BD.PD[Pos],Tabla3[[#This Row],[Part.]])+SUMIFS(BD.PD[Pago 5],BD.PD[Per.P5],K$1,BD.PD[Pos],Tabla3[[#This Row],[Part.]]) -> 0 | ... AA15: =SUMIFS(BD.PD[Pago 1],BD.PD[Per.P1],AA$1,BD.PD[Pos],Tabla3[[#This Row],[Part.]])+SUMIFS(BD.PD[Pago 2],BD.PD[Per.P2],AA$1,BD.PD[Pos],Tabla3[[#This Row],[Part.]])+SUMIFS(BD.PD[Pago 3],BD.PD[Per.P3],AA$1,BD.PD[Pos],Tabla3[[#This Row],[Part.]])+SUMIFS(BD.PD[Pago 4],BD.PD[Per.P4],AA$1,BD.PD[Pos],Tabla3[[#This Row],[Part.]])+SUMIFS(BD.PD[Pago 5],BD.PD[Per.P5],AA$1,BD.PD[Pos],Tabla3[[#This Row],[Part.]]) -> 0 | AB15: =SUM(Tabla3[[#This Row],[P1]:[P24]]) -> 0
A16: 2 | B16: =VLOOKUP(Tabla3[[#This Row],[Part.]],PPto[],3,FALSE) -> 2.00 Obra Civil | C16: =SUM(C17:C27) -> 15391355 | D16: =SUM(D17:D27) -> 0 | E16: =SUM(E17:E27) -> 0 | F16: =SUM(F17:F27) -> 2413668.7 | G16: =SUM(G17:G27) -> 0 | H16: =SUM(H17:H27) -> 2215515.8 | I16: =SUM(I17:I27) -> 0 | J16: =SUM(J17:J27) -> 0 | ... AA16: =SUM(AA17:AA27) -> 2847245 | AB16: =SUM(Tabla3[[#This Row],[P1]:[P24]]) -> 15391355
A17: 2.01 | B17: =VLOOKUP(Tabla3[[#This Row],[Part.]],PPto[],3,FALSE) -> 2.01 Edificación - Obra Civil | C17: =SUMIF(BD.PD[Pos],Tabla3[[#This Row],[Part.]],BD.PD[Ppto. Orden Interna '[DOP']]) -> 1073527 | D17: =SUMIFS(BD.PD[Pago 1],BD.PD[Per.P1],D$1,BD.PD[Pos],Tabla3[[#This Row],[Part.]])+SUMIFS(BD.PD[Pago 2],BD.PD[Per.P2],D$1,BD.PD[Pos],Tabla3[[#This Row],[Part.]])+SUMIFS(BD.PD[Pago 3],BD.PD[Per.P3],D$1,BD.PD[Pos],Tabla3[[#This Row],[Part.]])+SUMIFS(BD.PD[Pago 4],BD.PD[Per.P4],D$1,BD.PD[Pos],Tabla3[[#This Row],[Part.]])+SUMIFS(BD.PD[Pago 5],BD.PD[Per.P5],D$1,BD.PD[Pos],Tabla3[[#This Row],[Part.]]) -> 0 | E17: =SUMIFS(BD.PD[Pago 1],BD.PD[Per.P1],E$1,BD.PD[Pos],Tabla3[[#This Row],[Part.]])+SUMIFS(BD.PD[Pago 2],BD.PD[Per.P2],E$1,BD.PD[Pos],Tabla3[[#This Row],[Part.]])+SUMIFS(BD.PD[Pago 3],BD.PD[Per.P3],E$1,BD.PD[Pos],Tabla3[[#This Row],[Part.]])+SUMIFS(BD.PD[Pago 4],BD.PD[Per.P4],E$1,BD.PD[Pos],Tabla3[[#This Row],[Part.]])+SUMIFS(BD.PD[Pago 5],BD.PD[Per.P5],E$1,BD.PD[Pos],Tabla3[[#This Row],[Part.]]) -> 0 | F17: =SUMIFS(BD.PD[Pago 1],BD.PD[Per.P1],F$1,BD.PD[Pos],Tabla3[[#This Row],[Part.]])+SUMIFS(BD.PD[Pago 2],BD.PD[Per.P2],F$1,BD.PD[Pos],Tabla3[[#This Row],[Part.]])+SUMIFS(BD.PD[Pago 3],BD.PD[Per.P3],F$1,BD.PD[Pos],Tabla3[[#This Row],[Part.]])+SUMIFS(BD.PD[Pago 4],BD.PD[Per.P4],F$1,BD.PD[Pos],Tabla3[[#This Row],[Part.]])+SUMIFS(BD.PD[Pago 5],BD.PD[Per.P5],F$1,BD.PD[Pos],Tabla3[[#This Row],[Part.]]) -> 0 | G17: =SUMIFS(BD.PD[Pago 1],BD.PD[Per.P1],G$1,BD.PD[Pos],Tabla3[[#This Row],[Part.]])+SUMIFS(BD.PD[Pago 2],BD.PD[Per.P2],G$1,BD.PD[Pos],Tabla3[[#This Row],[Part.]])+SUMIFS(BD.PD[Pago 3],BD.PD[Per.P3],G$1,BD.PD[Pos],Tabla3[[#This Row],[Part.]])+SUMIFS(BD.PD[Pago 4],BD.PD[Per.P4],G$1,BD.PD[Pos],Tabla3[[#This Row],[Part.]])+SUMIFS(BD.PD[Pago 5],BD.PD[Per.P5],G$1,BD.PD[Pos],Tabla3[[#This Row],[Part.]]) -> 0 | H17: =SUMIFS(BD.PD[Pago 1],BD.PD[Per.P1],H$1,BD.PD[Pos],Tabla3[[#This Row],[Part.]])+SUMIFS(BD.PD[Pago 2],BD.PD[Per.P2],H$1,BD.PD[Pos],Tabla3[[#This Row],[Part.]])+SUMIFS(BD.PD[Pago 3],BD.PD[Per.P3],H$1,BD.PD[Pos],Tabla3[[#This Row],[Part.]])+SUMIFS(BD.PD[Pago 4],BD.PD[Per.P4],H$1,BD.PD[Pos],Tabla3[[#This Row],[Part.]])+SUMIFS(BD.PD[Pago 5],BD.PD[Per.P5],H$1,BD.PD[Pos],Tabla3[[#This Row],[Part.]]) -> 0 | I17: =SUMIFS(BD.PD[Pago 1],BD.PD[Per.P1],I$1,BD.PD[Pos],Tabla3[[#This Row],[Part.]])+SUMIFS(BD.PD[Pago 2],BD.PD[Per.P2],I$1,BD.PD[Pos],Tabla3[[#This Row],[Part.]])+SUMIFS(BD.PD[Pago 3],BD.PD[Per.P3],I$1,BD.PD[Pos],Tabla3[[#This Row],[Part.]])+SUMIFS(BD.PD[Pago 4],BD.PD[Per.P4],I$1,BD.PD[Pos],Tabla3[[#This Row],[Part.]])+SUMIFS(BD.PD[Pago 5],BD.PD[Per.P5],I$1,BD.PD[Pos],Tabla3[[#This Row],[Part.]]) -> 0 | J17: =SUMIFS(BD.PD[Pago 1],BD.PD[Per.P1],J$1,BD.PD[Pos],Tabla3[[#This Row],[Part.]])+SUMIFS(BD.PD[Pago 2],BD.PD[Per.P2],J$1,BD.PD[Pos],Tabla3[[#This Row],[Part.]])+SUMIFS(BD.PD[Pago 3],BD.PD[Per.P3],J$1,BD.PD[Pos],Tabla3[[#This Row],[Part.]])+SUMIFS(BD.PD[Pago 4],BD.PD[Per.P4],J$1,BD.PD[Pos],Tabla3[[#This Row],[Part.]])+SUMIFS(BD.PD[Pago 5],BD.PD[Per.P5],J$1,BD.PD[Pos],Tabla3[[#This Row],[Part.]]) -> 0 | K17: =SUMIFS(BD.PD[Pago 1],BD.PD[Per.P1],K$1,BD.PD[Pos],Tabla3[[#This Row],[Part.]])+SUMIFS(BD.PD[Pago 2],BD.PD[Per.P2],K$1,BD.PD[Pos],Tabla3[[#This Row],[Part.]])+SUMIFS(BD.PD[Pago 3],BD.PD[Per.P3],K$1,BD.PD[Pos],Tabla3[[#This Row],[Part.]])+SUMIFS(BD.PD[Pago 4],BD.PD[Per.P4],K$1,BD.PD[Pos],Tabla3[[#This Row],[Part.]])+SUMIFS(BD.PD[Pago 5],BD.PD[Per.P5],K$1,BD.PD[Pos],Tabla3[[#This Row],[Part.]]) -> 0 | ... AA17: =SUMIFS(BD.PD[Pago 1],BD.PD[Per.P1],AA$1,BD.PD[Pos],Tabla3[[#This Row],[Part.]])+SUMIFS(BD.PD[Pago 2],BD.PD[Per.P2],AA$1,BD.PD[Pos],Tabla3[[#This Row],[Part.]])+SUMIFS(BD.PD[Pago 3],BD.PD[Per.P3],AA$1,BD.PD[Pos],Tabla3[[#This Row],[Part.]])+SUMIFS(BD.PD[Pago 4],BD.PD[Per.P4],AA$1,BD.PD[Pos],Tabla3[[#This Row],[Part.]])+SUMIFS(BD.PD[Pago 5],BD.PD[Per.P5],AA$1,BD.PD[Pos],Tabla3[[#This Row],[Part.]]) -> 536763.48 | AB17: =SUM(Tabla3[[#This Row],[P1]:[P24]]) -> 1073527
A18: 2.02 | B18: =VLOOKUP(Tabla3[[#This Row],[Part.]],PPto[],3,FALSE) -> 2.02 Edificación - Estructura Metálica | C18: =SUMIF(BD.PD[Pos],Tabla3[[#This Row],[Part.]],BD.PD[Ppto. Orden Interna '[DOP']]) -> 0 | D18: =SUMIFS(BD.PD[Pago 1],BD.PD[Per.P1],D$1,BD.PD[Pos],Tabla3[[#This Row],[Part.]])+SUMIFS(BD.PD[Pago 2],BD.PD[Per.P2],D$1,BD.PD[Pos],Tabla3[[#This Row],[Part.]])+SUMIFS(BD.PD[Pago 3],BD.PD[Per.P3],D$1,BD.PD[Pos],Tabla3[[#This Row],[Part.]])+SUMIFS(BD.PD[Pago 4],BD.PD[Per.P4],D$1,BD.PD[Pos],Tabla3[[#This Row],[Part.]])+SUMIFS(BD.PD[Pago 5],BD.PD[Per.P5],D$1,BD.PD[Pos],Tabla3[[#This Row],[Part.]]) -> 0 | E18: =SUMIFS(BD.PD[Pago 1],BD.PD[Per.P1],E$1,BD.PD[Pos],Tabla3[[#This Row],[Part.]])+SUMIFS(BD.PD[Pago 2],BD.PD[Per.P2],E$1,BD.PD[Pos],Tabla3[[#This Row],[Part.]])+SUMIFS(BD.PD[Pago 3],BD.PD[Per.P3],E$1,BD.PD[Pos],Tabla3[[#This Row],[Part.]])+SUMIFS(BD.PD[Pago 4],BD.PD[Per.P4],E$1,BD.PD[Pos],Tabla3[[#This Row],[Part.]])+SUMIFS(BD.PD[Pago 5],BD.PD[Per.P5],E$1,BD.PD[Pos],Tabla3[[#This Row],[Part.]]) -> 0 | F18: =SUMIFS(BD.PD[Pago 1],BD.PD[Per.P1],F$1,BD.PD[Pos],Tabla3[[#This Row],[Part.]])+SUMIFS(BD.PD[Pago 2],BD.PD[Per.P2],F$1,BD.PD[Pos],Tabla3[[#This Row],[Part.]])+SUMIFS(BD.PD[Pago 3],BD.PD[Per.P3],F$1,BD.PD[Pos],Tabla3[[#This Row],[Part.]])+SUMIFS(BD.PD[Pago 4],BD.PD[Per.P4],F$1,BD.PD[Pos],Tabla3[[#This Row],[Part.]])+SUMIFS(BD.PD[Pago 5],BD.PD[Per.P5],F$1,BD.PD[Pos],Tabla3[[#This Row],[Part.]]) -> 0 | G18: =SUMIFS(BD.PD[Pago 1],BD.PD[Per.P1],G$1,BD.PD[Pos],Tabla3[[#This Row],[Part.]])+SUMIFS(BD.PD[Pago 2],BD.PD[Per.P2],G$1,BD.PD[Pos],Tabla3[[#This Row],[Part.]])+SUMIFS(BD.PD[Pago 3],BD.PD[Per.P3],G$1,BD.PD[Pos],Tabla3[[#This Row],[Part.]])+SUMIFS(BD.PD[Pago 4],BD.PD[Per.P4],G$1,BD.PD[Pos],Tabla3[[#This Row],[Part.]])+SUMIFS(BD.PD[Pago 5],BD.PD[Per.P5],G$1,BD.PD[Pos],Tabla3[[#This Row],[Part.]]) -> 0 | H18: =SUMIFS(BD.PD[Pago 1],BD.PD[Per.P1],H$1,BD.PD[Pos],Tabla3[[#This Row],[Part.]])+SUMIFS(BD.PD[Pago 2],BD.PD[Per.P2],H$1,BD.PD[Pos],Tabla3[[#This Row],[Part.]])+SUMIFS(BD.PD[Pago 3],BD.PD[Per.P3],H$1,BD.PD[Pos],Tabla3[[#This Row],[Part.]])+SUMIFS(BD.PD[Pago 4],BD.PD[Per.P4],H$1,BD.PD[Pos],Tabla3[[#This Row],[Part.]])+SUMIFS(BD.PD[Pago 5],BD.PD[Per.P5],H$1,BD.PD[Pos],Tabla3[[#This Row],[Part.]]) -> 0 | I18: =SUMIFS(BD.PD[Pago 1],BD.PD[Per.P1],I$1,BD.PD[Pos],Tabla3[[#This Row],[Part.]])+SUMIFS(BD.PD[Pago 2],BD.PD[Per.P2],I$1,BD.PD[Pos],Tabla3[[#This Row],[Part.]])+SUMIFS(BD.PD[Pago 3],BD.PD[Per.P3],I$1,BD.PD[Pos],Tabla3[[#This Row],[Part.]])+SUMIFS(BD.PD[Pago 4],BD.PD[Per.P4],I$1,BD.PD[Pos],Tabla3[[#This Row],[Part.]])+SUMIFS(BD.PD[Pago 5],BD.PD[Per.P5],I$1,BD.PD[Pos],Tabla3[[#This Row],[Part.]]) -> 0 | J18: =SUMIFS(BD.PD[Pago 1],BD.PD[Per.P1],J$1,BD.PD[Pos],Tabla3[[#This Row],[Part.]])+SUMIFS(BD.PD[Pago 2],BD.PD[Per.P2],J$1,BD.PD[Pos],Tabla3[[#This Row],[Part.]])+SUMIFS(BD.PD[Pago 3],BD.PD[Per.P3],J$1,BD.PD[Pos],Tabla3[[#This Row],[Part.]])+SUMIFS(BD.PD[Pago 4],BD.PD[Per.P4],J$1,BD.PD[Pos],Tabla3[[#This Row],[Part.]])+SUMIFS(BD.PD[Pago 5],BD.PD[Per.P5],J$1,BD.PD[Pos],Tabla3[[#This Row],[Part.]]) -> 0 | K18: =SUMIFS(BD.PD[Pago 1],BD.PD[Per.P1],K$1,BD.PD[Pos],Tabla3[[#This Row],[Part.]])+SUMIFS(BD.PD[Pago 2],BD.PD[Per.P2],K$1,BD.PD[Pos],Tabla3[[#This Row],[Part.]])+SUMIFS(BD.PD[Pago 3],BD.PD[Per.P3],K$1,BD.PD[Pos],Tabla3[[#This Row],[Part.]])+SUMIFS(BD.PD[Pago 4],BD.PD[Per.P4],K$1,BD.PD[Pos],Tabla3[[#This Row],[Part.]])+SUMIFS(BD.PD[Pago 5],BD.PD[Per.P5],K$1,BD.PD[Pos],Tabla3[[#This Row],[Part.]]) -> 0 | ... AA18: =SUMIFS(BD.PD[Pago 1],BD.PD[Per.P1],AA$1,BD.PD[Pos],Tabla3[[#This Row],[Part.]])+SUMIFS(BD.PD[Pago 2],BD.PD[Per.P2],AA$1,BD.PD[Pos],Tabla3[[#This Row],[Part.]])+SUMIFS(BD.PD[Pago 3],BD.PD[Per.P3],AA$1,BD.PD[Pos],Tabla3[[#This Row],[Part.]])+SUMIFS(BD.PD[Pago 4],BD.PD[Per.P4],AA$1,BD.PD[Pos],Tabla3[[#This Row],[Part.]])+SUMIFS(BD.PD[Pago 5],BD.PD[Per.P5],AA$1,BD.PD[Pos],Tabla3[[#This Row],[Part.]]) -> 0 | AB18: =SUM(Tabla3[[#This Row],[P1]:[P24]]) -> 0
A19: 2.03 | B19: =VLOOKUP(Tabla3[[#This Row],[Part.]],PPto[],3,FALSE) -> 2.03 Edificación - Techo S.S. y Cerramientos Multipanel | C19: =SUMIF(BD.PD[Pos],Tabla3[[#This Row],[Part.]],BD.PD[Ppto. Orden Interna '[DOP']]) -> 0 | D19: =SUMIFS(BD.PD[Pago 1],BD.PD[Per.P1],D$1,BD.PD[Pos],Tabla3[[#This Row],[Part.]])+SUMIFS(BD.PD[Pago 2],BD.PD[Per.P2],D$1,BD.PD[Pos],Tabla3[[#This Row],[Part.]])+SUMIFS(BD.PD[Pago 3],BD.PD[Per.P3],D$1,BD.PD[Pos],Tabla3[[#This Row],[Part.]])+SUMIFS(BD.PD[Pago 4],BD.PD[Per.P4],D$1,BD.PD[Pos],Tabla3[[#This Row],[Part.]])+SUMIFS(BD.PD[Pago 5],BD.PD[Per.P5],D$1,BD.PD[Pos],Tabla3[[#This Row],[Part.]]) -> 0 | E19: =SUMIFS(BD.PD[Pago 1],BD.PD[Per.P1],E$1,BD.PD[Pos],Tabla3[[#This Row],[Part.]])+SUMIFS(BD.PD[Pago 2],BD.PD[Per.P2],E$1,BD.PD[Pos],Tabla3[[#This Row],[Part.]])+SUMIFS(BD.PD[Pago 3],BD.PD[Per.P3],E$1,BD.PD[Pos],Tabla3[[#This Row],[Part.]])+SUMIFS(BD.PD[Pago 4],BD.PD[Per.P4],E$1,BD.PD[Pos],Tabla3[[#This Row],[Part.]])+SUMIFS(BD.PD[Pago 5],BD.PD[Per.P5],E$1,BD.PD[Pos],Tabla3[[#This Row],[Part.]]) -> 0 | F19: =SUMIFS(BD.PD[Pago 1],BD.PD[Per.P1],F$1,BD.PD[Pos],Tabla3[[#This Row],[Part.]])+SUMIFS(BD.PD[Pago 2],BD.PD[Per.P2],F$1,BD.PD[Pos],Tabla3[[#This Row],[Part.]])+SUMIFS(BD.PD[Pago 3],BD.PD[Per.P3],F$1,BD.PD[Pos],Tabla3[[#This Row],[Part.]])+SUMIFS(BD.PD[Pago 4],BD.PD[Per.P4],F$1,BD.PD[Pos],Tabla3[[#This Row],[Part.]])+SUMIFS(BD.PD[Pago 5],BD.PD[Per.P5],F$1,BD.PD[Pos],Tabla3[[#This Row],[Part.]]) -> 0 | G19: =SUMIFS(BD.PD[Pago 1],BD.PD[Per.P1],G$1,BD.PD[Pos],Tabla3[[#This Row],[Part.]])+SUMIFS(BD.PD[Pago 2],BD.PD[Per.P2],G$1,BD.PD[Pos],Tabla3[[#This Row],[Part.]])+SUMIFS(BD.PD[Pago 3],BD.PD[Per.P3],G$1,BD.PD[Pos],Tabla3[[#This Row],[Part.]])+SUMIFS(BD.PD[Pago 4],BD.PD[Per.P4],G$1,BD.PD[Pos],Tabla3[[#This Row],[Part.]])+SUMIFS(BD.PD[Pago 5],BD.PD[Per.P5],G$1,BD.PD[Pos],Tabla3[[#This Row],[Part.]]) -> 0 | H19: =SUMIFS(BD.PD[Pago 1],BD.PD[Per.P1],H$1,BD.PD[Pos],Tabla3[[#This Row],[Part.]])+SUMIFS(BD.PD[Pago 2],BD.PD[Per.P2],H$1,BD.PD[Pos],Tabla3[[#This Row],[Part.]])+SUMIFS(BD.PD[Pago 3],BD.PD[Per.P3],H$1,BD.PD[Pos],Tabla3[[#This Row],[Part.]])+SUMIFS(BD.PD[Pago 4],BD.PD[Per.P4],H$1,BD.PD[Pos],Tabla3[[#This Row],[Part.]])+SUMIFS(BD.PD[Pago 5],BD.PD[Per.P5],H$1,BD.PD[Pos],Tabla3[[#This Row],[Part.]]) -> 0 | I19: =SUMIFS(BD.PD[Pago 1],BD.PD[Per.P1],I$1,BD.PD[Pos],Tabla3[[#This Row],[Part.]])+SUMIFS(BD.PD[Pago 2],BD.PD[Per.P2],I$1,BD.PD[Pos],Tabla3[[#This Row],[Part.]])+SUMIFS(BD.PD[Pago 3],BD.PD[Per.P3],I$1,BD.PD[Pos],Tabla3[[#This Row],[Part.]])+SUMIFS(BD.PD[Pago 4],BD.PD[Per.P4],I$1,BD.PD[Pos],Tabla3[[#This Row],[Part.]])+SUMIFS(BD.PD[Pago 5],BD.PD[Per.P5],I$1,BD.PD[Pos],Tabla3[[#This Row],[Part.]]) -> 0 | J19: =SUMIFS(BD.PD[Pago 1],BD.PD[Per.P1],J$1,BD.PD[Pos],Tabla3[[#This Row],[Part.]])+SUMIFS(BD.PD[Pago 2],BD.PD[Per.P2],J$1,BD.PD[Pos],Tabla3[[#This Row],[Part.]])+SUMIFS(BD.PD[Pago 3],BD.PD[Per.P3],J$1,BD.PD[Pos],Tabla3[[#This Row],[Part.]])+SUMIFS(BD.PD[Pago 4],BD.PD[Per.P4],J$1,BD.PD[Pos],Tabla3[[#This Row],[Part.]])+SUMIFS(BD.PD[Pago 5],BD.PD[Per.P5],J$1,BD.PD[Pos],Tabla3[[#This Row],[Part.]]) -> 0 | K19: =SUMIFS(BD.PD[Pago 1],BD.PD[Per.P1],K$1,BD.PD[Pos],Tabla3[[#This Row],[Part.]])+SUMIFS(BD.PD[Pago 2],BD.PD[Per.P2],K$1,BD.PD[Pos],Tabla3[[#This Row],[Part.]])+SUMIFS(BD.PD[Pago 3],BD.PD[Per.P3],K$1,BD.PD[Pos],Tabla3[[#This Row],[Part.]])+SUMIFS(BD.PD[Pago 4],BD.PD[Per.P4],K$1,BD.PD[Pos],Tabla3[[#This Row],[Part.]])+SUMIFS(BD.PD[Pago 5],BD.PD[Per.P5],K$1,BD.PD[Pos],Tabla3[[#This Row],[Part.]]) -> 0 | ... AA19: =SUMIFS(BD.PD[Pago 1],BD.PD[Per.P1],AA$1,BD.PD[Pos],Tabla3[[#This Row],[Part.]])+SUMIFS(BD.PD[Pago 2],BD.PD[Per.P2],AA$1,BD.PD[Pos],Tabla3[[#This Row],[Part.]])+SUMIFS(BD.PD[Pago 3],BD.PD[Per.P3],AA$1,BD.PD[Pos],Tabla3[[#This Row],[Part.]])+SUMIFS(BD.PD[Pago 4],BD.PD[Per.P4],AA$1,BD.PD[Pos],Tabla3[[#This Row],[Part.]])+SUMIFS(BD.PD[Pago 5],BD.PD[Per.P5],AA$1,BD.PD[Pos],Tabla3[[#This Row],[Part.]]) -> 0 | AB19: =SUM(Tabla3[[#This Row],[P1]:[P24]]) -> 0
A20: 2.04 | B20: =VLOOKUP(Tabla3[[#This Row],[Part.]],PPto[],3,FALSE) -> 2.04 Edificación - Tragaluces "Skylights" | C20: =SUMIF(BD.PD[Pos],Tabla3[[#This Row],[Part.]],BD.PD[Ppto. Orden Interna '[DOP']]) -> 0 | D20: =SUMIFS(BD.PD[Pago 1],BD.PD[Per.P1],D$1,BD.PD[Pos],Tabla3[[#This Row],[Part.]])+SUMIFS(BD.PD[Pago 2],BD.PD[Per.P2],D$1,BD.PD[Pos],Tabla3[[#This Row],[Part.]])+SUMIFS(BD.PD[Pago 3],BD.PD[Per.P3],D$1,BD.PD[Pos],Tabla3[[#This Row],[Part.]])+SUMIFS(BD.PD[Pago 4],BD.PD[Per.P4],D$1,BD.PD[Pos],Tabla3[[#This Row],[Part.]])+SUMIFS(BD.PD[Pago 5],BD.PD[Per.P5],D$1,BD.PD[Pos],Tabla3[[#This Row],[Part.]]) -> 0 | E20: =SUMIFS(BD.PD[Pago 1],BD.PD[Per.P1],E$1,BD.PD[Pos],Tabla3[[#This Row],[Part.]])+SUMIFS(BD.PD[Pago 2],BD.PD[Per.P2],E$1,BD.PD[Pos],Tabla3[[#This Row],[Part.]])+SUMIFS(BD.PD[Pago 3],BD.PD[Per.P3],E$1,BD.PD[Pos],Tabla3[[#This Row],[Part.]])+SUMIFS(BD.PD[Pago 4],BD.PD[Per.P4],E$1,BD.PD[Pos],Tabla3[[#This Row],[Part.]])+SUMIFS(BD.PD[Pago 5],BD.PD[Per.P5],E$1,BD.PD[Pos],Tabla3[[#This Row],[Part.]]) -> 0 | F20: =SUMIFS(BD.PD[Pago 1],BD.PD[Per.P1],F$1,BD.PD[Pos],Tabla3[[#This Row],[Part.]])+SUMIFS(BD.PD[Pago 2],BD.PD[Per.P2],F$1,BD.PD[Pos],Tabla3[[#This Row],[Part.]])+SUMIFS(BD.PD[Pago 3],BD.PD[Per.P3],F$1,BD.PD[Pos],Tabla3[[#This Row],[Part.]])+SUMIFS(BD.PD[Pago 4],BD.PD[Per.P4],F$1,BD.PD[Pos],Tabla3[[#This Row],[Part.]])+SUMIFS(BD.PD[Pago 5],BD.PD[Per.P5],F$1,BD.PD[Pos],Tabla3[[#This Row],[Part.]]) -> 0 | G20: =SUMIFS(BD.PD[Pago 1],BD.PD[Per.P1],G$1,BD.PD[Pos],Tabla3[[#This Row],[Part.]])+SUMIFS(BD.PD[Pago 2],BD.PD[Per.P2],G$1,BD.PD[Pos],Tabla3[[#This Row],[Part.]])+SUMIFS(BD.PD[Pago 3],BD.PD[Per.P3],G$1,BD.PD[Pos],Tabla3[[#This Row],[Part.]])+SUMIFS(BD.PD[Pago 4],BD.PD[Per.P4],G$1,BD.PD[Pos],Tabla3[[#This Row],[Part.]])+SUMIFS(BD.PD[Pago 5],BD.PD[Per.P5],G$1,BD.PD[Pos],Tabla3[[#This Row],[Part.]]) -> 0 | H20: =SUMIFS(BD.PD[Pago 1],BD.PD[Per.P1],H$1,BD.PD[Pos],Tabla3[[#This Row],[Part.]])+SUMIFS(BD.PD[Pago 2],BD.PD[Per.P2],H$1,BD.PD[Pos],Tabla3[[#This Row],[Part.]])+SUMIFS(BD.PD[Pago 3],BD.PD[Per.P3],H$1,BD.PD[Pos],Tabla3[[#This Row],[Part.]])+SUMIFS(BD.PD[Pago 4],BD.PD[Per.P4],H$1,BD.PD[Pos],Tabla3[[#This Row],[Part.]])+SUMIFS(BD.PD[Pago 5],BD.PD[Per.P5],H$1,BD.PD[Pos],Tabla3[[#This Row],[Part.]]) -> 0 | I20: =SUMIFS(BD.PD[Pago 1],BD.PD[Per.P1],I$1,BD.PD[Pos],Tabla3[[#This Row],[Part.]])+SUMIFS(BD.PD[Pago 2],BD.PD[Per.P2],I$1,BD.PD[Pos],Tabla3[[#This Row],[Part.]])+SUMIFS(BD.PD[Pago 3],BD.PD[Per.P3],I$1,BD.PD[Pos],Tabla3[[#This Row],[Part.]])+SUMIFS(BD.PD[Pago 4],BD.PD[Per.P4],I$1,BD.PD[Pos],Tabla3[[#This Row],[Part.]])+SUMIFS(BD.PD[Pago 5],BD.PD[Per.P5],I$1,BD.PD[Pos],Tabla3[[#This Row],[Part.]]) -> 0 | J20: =SUMIFS(BD.PD[Pago 1],BD.PD[Per.P1],J$1,BD.PD[Pos],Tabla3[[#This Row],[Part.]])+SUMIFS(BD.PD[Pago 2],BD.PD[Per.P2],J$1,BD.PD[Pos],Tabla3[[#This Row],[Part.]])+SUMIFS(BD.PD[Pago 3],BD.PD[Per.P3],J$1,BD.PD[Pos],Tabla3[[#This Row],[Part.]])+SUMIFS(BD.PD[Pago 4],BD.PD[Per.P4],J$1,BD.PD[Pos],Tabla3[[#This Row],[Part.]])+SUMIFS(BD.PD[Pago 5],BD.PD[Per.P5],J$1,BD.PD[Pos],Tabla3[[#This Row],[Part.]]) -> 0 | K20: =SUMIFS(BD.PD[Pago 1],BD.PD[Per.P1],K$1,BD.PD[Pos],Tabla3[[#This Row],[Part.]])+SUMIFS(BD.PD[Pago 2],BD.PD[Per.P2],K$1,BD.PD[Pos],Tabla3[[#This Row],[Part.]])+SUMIFS(BD.PD[Pago 3],BD.PD[Per.P3],K$1,BD.PD[Pos],Tabla3[[#This Row],[Part.]])+SUMIFS(BD.PD[Pago 4],BD.PD[Per.P4],K$1,BD.PD[Pos],Tabla3[[#This Row],[Part.]])+SUMIFS(BD.PD[Pago 5],BD.PD[Per.P5],K$1,BD.PD[Pos],Tabla3[[#This Row],[Part.]]) -> 0 | ... AA20: =SUMIFS(BD.PD[Pago 1],BD.PD[Per.P1],AA$1,BD.PD[Pos],Tabla3[[#This Row],[Part.]])+SUMIFS(BD.PD[Pago 2],BD.PD[Per.P2],AA$1,BD.PD[Pos],Tabla3[[#This Row],[Part.]])+SUMIFS(BD.PD[Pago 3],BD.PD[Per.P3],AA$1,BD.PD[Pos],Tabla3[[#This Row],[Part.]])+SUMIFS(BD.PD[Pago 4],BD.PD[Per.P4],AA$1,BD.PD[Pos],Tabla3[[#This Row],[Part.]])+SUMIFS(BD.PD[Pago 5],BD.PD[Per.P5],AA$1,BD.PD[Pos],Tabla3[[#This Row],[Part.]]) -> 0 | AB20: =SUM(Tabla3[[#This Row],[P1]:[P24]]) -> 0
A21: 2.05 | B21: =VLOOKUP(Tabla3[[#This Row],[Part.]],PPto[],3,FALSE) -> 2.05 Instalaciones Sanitarias | C21: =SUMIF(BD.PD[Pos],Tabla3[[#This Row],[Part.]],BD.PD[Ppto. Orden Interna '[DOP']]) -> 1523570 | D21: =SUMIFS(BD.PD[Pago 1],BD.PD[Per.P1],D$1,BD.PD[Pos],Tabla3[[#This Row],[Part.]])+SUMIFS(BD.PD[Pago 2],BD.PD[Per.P2],D$1,BD.PD[Pos],Tabla3[[#This Row],[Part.]])+SUMIFS(BD.PD[Pago 3],BD.PD[Per.P3],D$1,BD.PD[Pos],Tabla3[[#This Row],[Part.]])+SUMIFS(BD.PD[Pago 4],BD.PD[Per.P4],D$1,BD.PD[Pos],Tabla3[[#This Row],[Part.]])+SUMIFS(BD.PD[Pago 5],BD.PD[Per.P5],D$1,BD.PD[Pos],Tabla3[[#This Row],[Part.]]) -> 0 | E21: =SUMIFS(BD.PD[Pago 1],BD.PD[Per.P1],E$1,BD.PD[Pos],Tabla3[[#This Row],[Part.]])+SUMIFS(BD.PD[Pago 2],BD.PD[Per.P2],E$1,BD.PD[Pos],Tabla3[[#This Row],[Part.]])+SUMIFS(BD.PD[Pago 3],BD.PD[Per.P3],E$1,BD.PD[Pos],Tabla3[[#This Row],[Part.]])+SUMIFS(BD.PD[Pago 4],BD.PD[Per.P4],E$1,BD.PD[Pos],Tabla3[[#This Row],[Part.]])+SUMIFS(BD.PD[Pago 5],BD.PD[Per.P5],E$1,BD.PD[Pos],Tabla3[[#This Row],[Part.]]) -> 0 | F21: =SUMIFS(BD.PD[Pago 1],BD.PD[Per.P1],F$1,BD.PD[Pos],Tabla3[[#This Row],[Part.]])+SUMIFS(BD.PD[Pago 2],BD.PD[Per.P2],F$1,BD.PD[Pos],Tabla3[[#This Row],[Part.]])+SUMIFS(BD.PD[Pago 3],BD.PD[Per.P3],F$1,BD.PD[Pos],Tabla3[[#This Row],[Part.]])+SUMIFS(BD.PD[Pago 4],BD.PD[Per.P4],F$1,BD.PD[Pos],Tabla3[[#This Row],[Part.]])+SUMIFS(BD.PD[Pago 5],BD.PD[Per.P5],F$1,BD.PD[Pos],Tabla3[[#This Row],[Part.]]) -> 0 | G21: =SUMIFS(BD.PD[Pago 1],BD.PD[Per.P1],G$1,BD.PD[Pos],Tabla3[[#This Row],[Part.]])+SUMIFS(BD.PD[Pago 2],BD.PD[Per.P2],G$1,BD.PD[Pos],Tabla3[[#This Row],[Part.]])+SUMIFS(BD.PD[Pago 3],BD.PD[Per.P3],G$1,BD.PD[Pos],Tabla3[[#This Row],[Part.]])+SUMIFS(BD.PD[Pago 4],BD.PD[Per.P4],G$1,BD.PD[Pos],Tabla3[[#This Row],[Part.]])+SUMIFS(BD.PD[Pago 5],BD.PD[Per.P5],G$1,BD.PD[Pos],Tabla3[[#This Row],[Part.]]) -> 0 | H21: =SUMIFS(BD.PD[Pago 1],BD.PD[Per.P1],H$1,BD.PD[Pos],Tabla3[[#This Row],[Part.]])+SUMIFS(BD.PD[Pago 2],BD.PD[Per.P2],H$1,BD.PD[Pos],Tabla3[[#This Row],[Part.]])+SUMIFS(BD.PD[Pago 3],BD.PD[Per.P3],H$1,BD.PD[Pos],Tabla3[[#This Row],[Part.]])+SUMIFS(BD.PD[Pago 4],BD.PD[Per.P4],H$1,BD.PD[Pos],Tabla3[[#This Row],[Part.]])+SUMIFS(BD.PD[Pago 5],BD.PD[Per.P5],H$1,BD.PD[Pos],Tabla3[[#This Row],[Part.]]) -> 0 | I21: =SUMIFS(BD.PD[Pago 1],BD.PD[Per.P1],I$1,BD.PD[Pos],Tabla3[[#This Row],[Part.]])+SUMIFS(BD.PD[Pago 2],BD.PD[Per.P2],I$1,BD.PD[Pos],Tabla3[[#This Row],[Part.]])+SUMIFS(BD.PD[Pago 3],BD.PD[Per.P3],I$1,BD.PD[Pos],Tabla3[[#This Row],[Part.]])+SUMIFS(BD.PD[Pago 4],BD.PD[Per.P4],I$1,BD.PD[Pos],Tabla3[[#This Row],[Part.]])+SUMIFS(BD.PD[Pago 5],BD.PD[Per.P5],I$1,BD.PD[Pos],Tabla3[[#This Row],[Part.]]) -> 0 | J21: =SUMIFS(BD.PD[Pago 1],BD.PD[Per.P1],J$1,BD.PD[Pos],Tabla3[[#This Row],[Part.]])+SUMIFS(BD.PD[Pago 2],BD.PD[Per.P2],J$1,BD.PD[Pos],Tabla3[[#This Row],[Part.]])+SUMIFS(BD.PD[Pago 3],BD.PD[Per.P3],J$1,BD.PD[Pos],Tabla3[[#This Row],[Part.]])+SUMIFS(BD.PD[Pago 4],BD.PD[Per.P4],J$1,BD.PD[Pos],Tabla3[[#This Row],[Part.]])+SUMIFS(BD.PD[Pago 5],BD.PD[Per.P5],J$1,BD.PD[Pos],Tabla3[[#This Row],[Part.]]) -> 0 | K21: =SUMIFS(BD.PD[Pago 1],BD.PD[Per.P1],K$1,BD.PD[Pos],Tabla3[[#This Row],[Part.]])+SUMIFS(BD.PD[Pago 2],BD.PD[Per.P2],K$1,BD.PD[Pos],Tabla3[[#This Row],[Part.]])+SUMIFS(BD.PD[Pago 3],BD.PD[Per.P3],K$1,BD.PD[Pos],Tabla3[[#This Row],[Part.]])+SUMIFS(BD.PD[Pago 4],BD.PD[Per.P4],K$1,BD.PD[Pos],Tabla3[[#This Row],[Part.]])+SUMIFS(BD.PD[Pago 5],BD.PD[Per.P5],K$1,BD.PD[Pos],Tabla3[[#This Row],[Part.]]) -> 0 | ... AA21: =SUMIFS(BD.PD[Pago 1],BD.PD[Per.P1],AA$1,BD.PD[Pos],Tabla3[[#This Row],[Part.]])+SUMIFS(BD.PD[Pago 2],BD.PD[Per.P2],AA$1,BD.PD[Pos],Tabla3[[#This Row],[Part.]])+SUMIFS(BD.PD[Pago 3],BD.PD[Per.P3],AA$1,BD.PD[Pos],Tabla3[[#This Row],[Part.]])+SUMIFS(BD.PD[Pago 4],BD.PD[Per.P4],AA$1,BD.PD[Pos],Tabla3[[#This Row],[Part.]])+SUMIFS(BD.PD[Pago 5],BD.PD[Per.P5],AA$1,BD.PD[Pos],Tabla3[[#This Row],[Part.]]) -> 761785 | AB21: =SUM(Tabla3[[#This Row],[P1]:[P24]]) -> 1523570
A22: 2.06 | B22: =VLOOKUP(Tabla3[[#This Row],[Part.]],PPto[],3,FALSE) -> 2.06 Instalación de Gas | C22: =SUMIF(BD.PD[Pos],Tabla3[[#This Row],[Part.]],BD.PD[Ppto. Orden Interna '[DOP']]) -> 454500 | D22: =SUMIFS(BD.PD[Pago 1],BD.PD[Per.P1],D$1,BD.PD[Pos],Tabla3[[#This Row],[Part.]])+SUMIFS(BD.PD[Pago 2],BD.PD[Per.P2],D$1,BD.PD[Pos],Tabla3[[#This Row],[Part.]])+SUMIFS(BD.PD[Pago 3],BD.PD[Per.P3],D$1,BD.PD[Pos],Tabla3[[#This Row],[Part.]])+SUMIFS(BD.PD[Pago 4],BD.PD[Per.P4],D$1,BD.PD[Pos],Tabla3[[#This Row],[Part.]])+SUMIFS(BD.PD[Pago 5],BD.PD[Per.P5],D$1,BD.PD[Pos],Tabla3[[#This Row],[Part.]]) -> 0 | E22: =SUMIFS(BD.PD[Pago 1],BD.PD[Per.P1],E$1,BD.PD[Pos],Tabla3[[#This Row],[Part.]])+SUMIFS(BD.PD[Pago 2],BD.PD[Per.P2],E$1,BD.PD[Pos],Tabla3[[#This Row],[Part.]])+SUMIFS(BD.PD[Pago 3],BD.PD[Per.P3],E$1,BD.PD[Pos],Tabla3[[#This Row],[Part.]])+SUMIFS(BD.PD[Pago 4],BD.PD[Per.P4],E$1,BD.PD[Pos],Tabla3[[#This Row],[Part.]])+SUMIFS(BD.PD[Pago 5],BD.PD[Per.P5],E$1,BD.PD[Pos],Tabla3[[#This Row],[Part.]]) -> 0 | F22: =SUMIFS(BD.PD[Pago 1],BD.PD[Per.P1],F$1,BD.PD[Pos],Tabla3[[#This Row],[Part.]])+SUMIFS(BD.PD[Pago 2],BD.PD[Per.P2],F$1,BD.PD[Pos],Tabla3[[#This Row],[Part.]])+SUMIFS(BD.PD[Pago 3],BD.PD[Per.P3],F$1,BD.PD[Pos],Tabla3[[#This Row],[Part.]])+SUMIFS(BD.PD[Pago 4],BD.PD[Per.P4],F$1,BD.PD[Pos],Tabla3[[#This Row],[Part.]])+SUMIFS(BD.PD[Pago 5],BD.PD[Per.P5],F$1,BD.PD[Pos],Tabla3[[#This Row],[Part.]]) -> 0 | G22: =SUMIFS(BD.PD[Pago 1],BD.PD[Per.P1],G$1,BD.PD[Pos],Tabla3[[#This Row],[Part.]])+SUMIFS(BD.PD[Pago 2],BD.PD[Per.P2],G$1,BD.PD[Pos],Tabla3[[#This Row],[Part.]])+SUMIFS(BD.PD[Pago 3],BD.PD[Per.P3],G$1,BD.PD[Pos],Tabla3[[#This Row],[Part.]])+SUMIFS(BD.PD[Pago 4],BD.PD[Per.P4],G$1,BD.PD[Pos],Tabla3[[#This Row],[Part.]])+SUMIFS(BD.PD[Pago 5],BD.PD[Per.P5],G$1,BD.PD[Pos],Tabla3[[#This Row],[Part.]]) -> 0 | H22: =SUMIFS(BD.PD[Pago 1],BD.PD[Per.P1],H$1,BD.PD[Pos],Tabla3[[#This Row],[Part.]])+SUMIFS(BD.PD[Pago 2],BD.PD[Per.P2],H$1,BD.PD[Pos],Tabla3[[#This Row],[Part.]])+SUMIFS(BD.PD[Pago 3],BD.PD[Per.P3],H$1,BD.PD[Pos],Tabla3[[#This Row],[Part.]])+SUMIFS(BD.PD[Pago 4],BD.PD[Per.P4],H$1,BD.PD[Pos],Tabla3[[#This Row],[Part.]])+SUMIFS(BD.PD[Pago 5],BD.PD[Per.P5],H$1,BD.PD[Pos],Tabla3[[#This Row],[Part.]]) -> 0 | I22: =SUMIFS(BD.PD[Pago 1],BD.PD[Per.P1],I$1,BD.PD[Pos],Tabla3[[#This Row],[Part.]])+SUMIFS(BD.PD[Pago 2],BD.PD[Per.P2],I$1,BD.PD[Pos],Tabla3[[#This Row],[Part.]])+SUMIFS(BD.PD[Pago 3],BD.PD[Per.P3],I$1,BD.PD[Pos],Tabla3[[#This Row],[Part.]])+SUMIFS(BD.PD[Pago 4],BD.PD[Per.P4],I$1,BD.PD[Pos],Tabla3[[#This Row],[Part.]])+SUMIFS(BD.PD[Pago 5],BD.PD[Per.P5],I$1,BD.PD[Pos],Tabla3[[#This Row],[Part.]]) -> 0 | J22: =SUMIFS(BD.PD[Pago 1],BD.PD[Per.P1],J$1,BD.PD[Pos],Tabla3[[#This Row],[Part.]])+SUMIFS(BD.PD[Pago 2],BD.PD[Per.P2],J$1,BD.PD[Pos],Tabla3[[#This Row],[Part.]])+SUMIFS(BD.PD[Pago 3],BD.PD[Per.P3],J$1,BD.PD[Pos],Tabla3[[#This Row],[Part.]])+SUMIFS(BD.PD[Pago 4],BD.PD[Per.P4],J$1,BD.PD[Pos],Tabla3[[#This Row],[Part.]])+SUMIFS(BD.PD[Pago 5],BD.PD[Per.P5],J$1,BD.PD[Pos],Tabla3[[#This Row],[Part.]]) -> 0 | K22: =SUMIFS(BD.PD[Pago 1],BD.PD[Per.P1],K$1,BD.PD[Pos],Tabla3[[#This Row],[Part.]])+SUMIFS(BD.PD[Pago 2],BD.PD[Per.P2],K$1,BD.PD[Pos],Tabla3[[#This Row],[Part.]])+SUMIFS(BD.PD[Pago 3],BD.PD[Per.P3],K$1,BD.PD[Pos],Tabla3[[#This Row],[Part.]])+SUMIFS(BD.PD[Pago 4],BD.PD[Per.P4],K$1,BD.PD[Pos],Tabla3[[#This Row],[Part.]])+SUMIFS(BD.PD[Pago 5],BD.PD[Per.P5],K$1,BD.PD[Pos],Tabla3[[#This Row],[Part.]]) -> 0 | ... AA22: =SUMIFS(BD.PD[Pago 1],BD.PD[Per.P1],AA$1,BD.PD[Pos],Tabla3[[#This Row],[Part.]])+SUMIFS(BD.PD[Pago 2],BD.PD[Per.P2],AA$1,BD.PD[Pos],Tabla3[[#This Row],[Part.]])+SUMIFS(BD.PD[Pago 3],BD.PD[Per.P3],AA$1,BD.PD[Pos],Tabla3[[#This Row],[Part.]])+SUMIFS(BD.PD[Pago 4],BD.PD[Per.P4],AA$1,BD.PD[Pos],Tabla3[[#This Row],[Part.]])+SUMIFS(BD.PD[Pago 5],BD.PD[Per.P5],AA$1,BD.PD[Pos],Tabla3[[#This Row],[Part.]]) -> 227250 | AB22: =SUM(Tabla3[[#This Row],[P1]:[P24]]) -> 454500
A23: 2.07 | B23: =VLOOKUP(Tabla3[[#This Row],[Part.]],PPto[],3,FALSE) -> 2.07 Sistema Contra Incendios | C23: =SUMIF(BD.PD[Pos],Tabla3[[#This Row],[Part.]],BD.PD[Ppto. Orden Interna '[DOP']]) -> 6105348.6 | D23: =SUMIFS(BD.PD[Pago 1],BD.PD[Per.P1],D$1,BD.PD[Pos],Tabla3[[#This Row],[Part.]])+SUMIFS(BD.PD[Pago 2],BD.PD[Per.P2],D$1,BD.PD[Pos],Tabla3[[#This Row],[Part.]])+SUMIFS(BD.PD[Pago 3],BD.PD[Per.P3],D$1,BD.PD[Pos],Tabla3[[#This Row],[Part.]])+SUMIFS(BD.PD[Pago 4],BD.PD[Per.P4],D$1,BD.PD[Pos],Tabla3[[#This Row],[Part.]])+SUMIFS(BD.PD[Pago 5],BD.PD[Per.P5],D$1,BD.PD[Pos],Tabla3[[#This Row],[Part.]]) -> 0 | E23: =SUMIFS(BD.PD[Pago 1],BD.PD[Per.P1],E$1,BD.PD[Pos],Tabla3[[#This Row],[Part.]])+SUMIFS(BD.PD[Pago 2],BD.PD[Per.P2],E$1,BD.PD[Pos],Tabla3[[#This Row],[Part.]])+SUMIFS(BD.PD[Pago 3],BD.PD[Per.P3],E$1,BD.PD[Pos],Tabla3[[#This Row],[Part.]])+SUMIFS(BD.PD[Pago 4],BD.PD[Per.P4],E$1,BD.PD[Pos],Tabla3[[#This Row],[Part.]])+SUMIFS(BD.PD[Pago 5],BD.PD[Per.P5],E$1,BD.PD[Pos],Tabla3[[#This Row],[Part.]]) -> 0 | F23: =SUMIFS(BD.PD[Pago 1],BD.PD[Per.P1],F$1,BD.PD[Pos],Tabla3[[#This Row],[Part.]])+SUMIFS(BD.PD[Pago 2],BD.PD[Per.P2],F$1,BD.PD[Pos],Tabla3[[#This Row],[Part.]])+SUMIFS(BD.PD[Pago 3],BD.PD[Per.P3],F$1,BD.PD[Pos],Tabla3[[#This Row],[Part.]])+SUMIFS(BD.PD[Pago 4],BD.PD[Per.P4],F$1,BD.PD[Pos],Tabla3[[#This Row],[Part.]])+SUMIFS(BD.PD[Pago 5],BD.PD[Per.P5],F$1,BD.PD[Pos],Tabla3[[#This Row],[Part.]]) -> 2413668.7 | G23: =SUMIFS(BD.PD[Pago 1],BD.PD[Per.P1],G$1,BD.PD[Pos],Tabla3[[#This Row],[Part.]])+SUMIFS(BD.PD[Pago 2],BD.PD[Per.P2],G$1,BD.PD[Pos],Tabla3[[#This Row],[Part.]])+SUMIFS(BD.PD[Pago 3],BD.PD[Per.P3],G$1,BD.PD[Pos],Tabla3[[#This Row],[Part.]])+SUMIFS(BD.PD[Pago 4],BD.PD[Per.P4],G$1,BD.PD[Pos],Tabla3[[#This Row],[Part.]])+SUMIFS(BD.PD[Pago 5],BD.PD[Per.P5],G$1,BD.PD[Pos],Tabla3[[#This Row],[Part.]]) -> 0 | H23: =SUMIFS(BD.PD[Pago 1],BD.PD[Per.P1],H$1,BD.PD[Pos],Tabla3[[#This Row],[Part.]])+SUMIFS(BD.PD[Pago 2],BD.PD[Per.P2],H$1,BD.PD[Pos],Tabla3[[#This Row],[Part.]])+SUMIFS(BD.PD[Pago 3],BD.PD[Per.P3],H$1,BD.PD[Pos],Tabla3[[#This Row],[Part.]])+SUMIFS(BD.PD[Pago 4],BD.PD[Per.P4],H$1,BD.PD[Pos],Tabla3[[#This Row],[Part.]])+SUMIFS(BD.PD[Pago 5],BD.PD[Per.P5],H$1,BD.PD[Pos],Tabla3[[#This Row],[Part.]]) -> 0 | I23: =SUMIFS(BD.PD[Pago 1],BD.PD[Per.P1],I$1,BD.PD[Pos],Tabla3[[#This Row],[Part.]])+SUMIFS(BD.PD[Pago 2],BD.PD[Per.P2],I$1,BD.PD[Pos],Tabla3[[#This Row],[Part.]])+SUMIFS(BD.PD[Pago 3],BD.PD[Per.P3],I$1,BD.PD[Pos],Tabla3[[#This Row],[Part.]])+SUMIFS(BD.PD[Pago 4],BD.PD[Per.P4],I$1,BD.PD[Pos],Tabla3[[#This Row],[Part.]])+SUMIFS(BD.PD[Pago 5],BD.PD[Per.P5],I$1,BD.PD[Pos],Tabla3[[#This Row],[Part.]]) -> 0 | J23: =SUMIFS(BD.PD[Pago 1],BD.PD[Per.P1],J$1,BD.PD[Pos],Tabla3[[#This Row],[Part.]])+SUMIFS(BD.PD[Pago 2],BD.PD[Per.P2],J$1,BD.PD[Pos],Tabla3[[#This Row],[Part.]])+SUMIFS(BD.PD[Pago 3],BD.PD[Per.P3],J$1,BD.PD[Pos],Tabla3[[#This Row],[Part.]])+SUMIFS(BD.PD[Pago 4],BD.PD[Per.P4],J$1,BD.PD[Pos],Tabla3[[#This Row],[Part.]])+SUMIFS(BD.PD[Pago 5],BD.PD[Per.P5],J$1,BD.PD[Pos],Tabla3[[#This Row],[Part.]]) -> 0 | K23: =SUMIFS(BD.PD[Pago 1],BD.PD[Per.P1],K$1,BD.PD[Pos],Tabla3[[#This Row],[Part.]])+SUMIFS(BD.PD[Pago 2],BD.PD[Per.P2],K$1,BD.PD[Pos],Tabla3[[#This Row],[Part.]])+SUMIFS(BD.PD[Pago 3],BD.PD[Per.P3],K$1,BD.PD[Pos],Tabla3[[#This Row],[Part.]])+SUMIFS(BD.PD[Pago 4],BD.PD[Per.P4],K$1,BD.PD[Pos],Tabla3[[#This Row],[Part.]])+SUMIFS(BD.PD[Pago 5],BD.PD[Per.P5],K$1,BD.PD[Pos],Tabla3[[#This Row],[Part.]]) -> 0 | ... AA23: =SUMIFS(BD.PD[Pago 1],BD.PD[Per.P1],AA$1,BD.PD[Pos],Tabla3[[#This Row],[Part.]])+SUMIFS(BD.PD[Pago 2],BD.PD[Per.P2],AA$1,BD.PD[Pos],Tabla3[[#This Row],[Part.]])+SUMIFS(BD.PD[Pago 3],BD.PD[Per.P3],AA$1,BD.PD[Pos],Tabla3[[#This Row],[Part.]])+SUMIFS(BD.PD[Pago 4],BD.PD[Per.P4],AA$1,BD.PD[Pos],Tabla3[[#This Row],[Part.]])+SUMIFS(BD.PD[Pago 5],BD.PD[Per.P5],AA$1,BD.PD[Pos],Tabla3[[#This Row],[Part.]]) -> 0 | AB23: =SUM(Tabla3[[#This Row],[P1]:[P24]]) -> 6105348.6
A24: 2.08 | B24: =VLOOKUP(Tabla3[[#This Row],[Part.]],PPto[],3,FALSE) -> 2.08 Instalaciones Mecánicas | C24: =SUMIF(BD.PD[Pos],Tabla3[[#This Row],[Part.]],BD.PD[Ppto. Orden Interna '[DOP']]) -> 5334408.9 | D24: =SUMIFS(BD.PD[Pago 1],BD.PD[Per.P1],D$1,BD.PD[Pos],Tabla3[[#This Row],[Part.]])+SUMIFS(BD.PD[Pago 2],BD.PD[Per.P2],D$1,BD.PD[Pos],Tabla3[[#This Row],[Part.]])+SUMIFS(BD.PD[Pago 3],BD.PD[Per.P3],D$1,BD.PD[Pos],Tabla3[[#This Row],[Part.]])+SUMIFS(BD.PD[Pago 4],BD.PD[Per.P4],D$1,BD.PD[Pos],Tabla3[[#This Row],[Part.]])+SUMIFS(BD.PD[Pago 5],BD.PD[Per.P5],D$1,BD.PD[Pos],Tabla3[[#This Row],[Part.]]) -> 0 | E24: =SUMIFS(BD.PD[Pago 1],BD.PD[Per.P1],E$1,BD.PD[Pos],Tabla3[[#This Row],[Part.]])+SUMIFS(BD.PD[Pago 2],BD.PD[Per.P2],E$1,BD.PD[Pos],Tabla3[[#This Row],[Part.]])+SUMIFS(BD.PD[Pago 3],BD.PD[Per.P3],E$1,BD.PD[Pos],Tabla3[[#This Row],[Part.]])+SUMIFS(BD.PD[Pago 4],BD.PD[Per.P4],E$1,BD.PD[Pos],Tabla3[[#This Row],[Part.]])+SUMIFS(BD.PD[Pago 5],BD.PD[Per.P5],E$1,BD.PD[Pos],Tabla3[[#This Row],[Part.]]) -> 0 | F24: =SUMIFS(BD.PD[Pago 1],BD.PD[Per.P1],F$1,BD.PD[Pos],Tabla3[[#This Row],[Part.]])+SUMIFS(BD.PD[Pago 2],BD.PD[Per.P2],F$1,BD.PD[Pos],Tabla3[[#This Row],[Part.]])+SUMIFS(BD.PD[Pago 3],BD.PD[Per.P3],F$1,BD.PD[Pos],Tabla3[[#This Row],[Part.]])+SUMIFS(BD.PD[Pago 4],BD.PD[Per.P4],F$1,BD.PD[Pos],Tabla3[[#This Row],[Part.]])+SUMIFS(BD.PD[Pago 5],BD.PD[Per.P5],F$1,BD.PD[Pos],Tabla3[[#This Row],[Part.]]) -> 0 | G24: =SUMIFS(BD.PD[Pago 1],BD.PD[Per.P1],G$1,BD.PD[Pos],Tabla3[[#This Row],[Part.]])+SUMIFS(BD.PD[Pago 2],BD.PD[Per.P2],G$1,BD.PD[Pos],Tabla3[[#This Row],[Part.]])+SUMIFS(BD.PD[Pago 3],BD.PD[Per.P3],G$1,BD.PD[Pos],Tabla3[[#This Row],[Part.]])+SUMIFS(BD.PD[Pago 4],BD.PD[Per.P4],G$1,BD.PD[Pos],Tabla3[[#This Row],[Part.]])+SUMIFS(BD.PD[Pago 5],BD.PD[Per.P5],G$1,BD.PD[Pos],Tabla3[[#This Row],[Part.]]) -> 0 | H24: =SUMIFS(BD.PD[Pago 1],BD.PD[Per.P1],H$1,BD.PD[Pos],Tabla3[[#This Row],[Part.]])+SUMIFS(BD.PD[Pago 2],BD.PD[Per.P2],H$1,BD.PD[Pos],Tabla3[[#This Row],[Part.]])+SUMIFS(BD.PD[Pago 3],BD.PD[Per.P3],H$1,BD.PD[Pos],Tabla3[[#This Row],[Part.]])+SUMIFS(BD.PD[Pago 4],BD.PD[Per.P4],H$1,BD.PD[Pos],Tabla3[[#This Row],[Part.]])+SUMIFS(BD.PD[Pago 5],BD.PD[Per.P5],H$1,BD.PD[Pos],Tabla3[[#This Row],[Part.]]) -> 2215515.8 | I24: =SUMIFS(BD.PD[Pago 1],BD.PD[Per.P1],I$1,BD.PD[Pos],Tabla3[[#This Row],[Part.]])+SUMIFS(BD.PD[Pago 2],BD.PD[Per.P2],I$1,BD.PD[Pos],Tabla3[[#This Row],[Part.]])+SUMIFS(BD.PD[Pago 3],BD.PD[Per.P3],I$1,BD.PD[Pos],Tabla3[[#This Row],[Part.]])+SUMIFS(BD.PD[Pago 4],BD.PD[Per.P4],I$1,BD.PD[Pos],Tabla3[[#This Row],[Part.]])+SUMIFS(BD.PD[Pago 5],BD.PD[Per.P5],I$1,BD.PD[Pos],Tabla3[[#This Row],[Part.]]) -> 0 | J24: =SUMIFS(BD.PD[Pago 1],BD.PD[Per.P1],J$1,BD.PD[Pos],Tabla3[[#This Row],[Part.]])+SUMIFS(BD.PD[Pago 2],BD.PD[Per.P2],J$1,BD.PD[Pos],Tabla3[[#This Row],[Part.]])+SUMIFS(BD.PD[Pago 3],BD.PD[Per.P3],J$1,BD.PD[Pos],Tabla3[[#This Row],[Part.]])+SUMIFS(BD.PD[Pago 4],BD.PD[Per.P4],J$1,BD.PD[Pos],Tabla3[[#This Row],[Part.]])+SUMIFS(BD.PD[Pago 5],BD.PD[Per.P5],J$1,BD.PD[Pos],Tabla3[[#This Row],[Part.]]) -> 0 | K24: =SUMIFS(BD.PD[Pago 1],BD.PD[Per.P1],K$1,BD.PD[Pos],Tabla3[[#This Row],[Part.]])+SUMIFS(BD.PD[Pago 2],BD.PD[Per.P2],K$1,BD.PD[Pos],Tabla3[[#This Row],[Part.]])+SUMIFS(BD.PD[Pago 3],BD.PD[Per.P3],K$1,BD.PD[Pos],Tabla3[[#This Row],[Part.]])+SUMIFS(BD.PD[Pago 4],BD.PD[Per.P4],K$1,BD.PD[Pos],Tabla3[[#This Row],[Part.]])+SUMIFS(BD.PD[Pago 5],BD.PD[Per.P5],K$1,BD.PD[Pos],Tabla3[[#This Row],[Part.]]) -> 0 | ... AA24: =SUMIFS(BD.PD[Pago 1],BD.PD[Per.P1],AA$1,BD.PD[Pos],Tabla3[[#This Row],[Part.]])+SUMIFS(BD.PD[Pago 2],BD.PD[Per.P2],AA$1,BD.PD[Pos],Tabla3[[#This Row],[Part.]])+SUMIFS(BD.PD[Pago 3],BD.PD[Per.P3],AA$1,BD.PD[Pos],Tabla3[[#This Row],[Part.]])+SUMIFS(BD.PD[Pago 4],BD.PD[Per.P4],AA$1,BD.PD[Pos],Tabla3[[#This Row],[Part.]])+SUMIFS(BD.PD[Pago 5],BD.PD[Per.P5],AA$1,BD.PD[Pos],Tabla3[[#This Row],[Part.]]) -> 1321446.6 | AB24: =SUM(Tabla3[[#This Row],[P1]:[P24]]) -> 5334408.9
A25: 2.09 | B25: =VLOOKUP(Tabla3[[#This Row],[Part.]],PPto[],3,FALSE) -> 2.09 Rejillas y Sumideros | C25: =SUMIF(BD.PD[Pos],Tabla3[[#This Row],[Part.]],BD.PD[Ppto. Orden Interna '[DOP']]) -> 900000 | D25: =SUMIFS(BD.PD[Pago 1],BD.PD[Per.P1],D$1,BD.PD[Pos],Tabla3[[#This Row],[Part.]])+SUMIFS(BD.PD[Pago 2],BD.PD[Per.P2],D$1,BD.PD[Pos],Tabla3[[#This Row],[Part.]])+SUMIFS(BD.PD[Pago 3],BD.PD[Per.P3],D$1,BD.PD[Pos],Tabla3[[#This Row],[Part.]])+SUMIFS(BD.PD[Pago 4],BD.PD[Per.P4],D$1,BD.PD[Pos],Tabla3[[#This Row],[Part.]])+SUMIFS(BD.PD[Pago 5],BD.PD[Per.P5],D$1,BD.PD[Pos],Tabla3[[#This Row],[Part.]]) -> 0 | E25: =SUMIFS(BD.PD[Pago 1],BD.PD[Per.P1],E$1,BD.PD[Pos],Tabla3[[#This Row],[Part.]])+SUMIFS(BD.PD[Pago 2],BD.PD[Per.P2],E$1,BD.PD[Pos],Tabla3[[#This Row],[Part.]])+SUMIFS(BD.PD[Pago 3],BD.PD[Per.P3],E$1,BD.PD[Pos],Tabla3[[#This Row],[Part.]])+SUMIFS(BD.PD[Pago 4],BD.PD[Per.P4],E$1,BD.PD[Pos],Tabla3[[#This Row],[Part.]])+SUMIFS(BD.PD[Pago 5],BD.PD[Per.P5],E$1,BD.PD[Pos],Tabla3[[#This Row],[Part.]]) -> 0 | F25: =SUMIFS(BD.PD[Pago 1],BD.PD[Per.P1],F$1,BD.PD[Pos],Tabla3[[#This Row],[Part.]])+SUMIFS(BD.PD[Pago 2],BD.PD[Per.P2],F$1,BD.PD[Pos],Tabla3[[#This Row],[Part.]])+SUMIFS(BD.PD[Pago 3],BD.PD[Per.P3],F$1,BD.PD[Pos],Tabla3[[#This Row],[Part.]])+SUMIFS(BD.PD[Pago 4],BD.PD[Per.P4],F$1,BD.PD[Pos],Tabla3[[#This Row],[Part.]])+SUMIFS(BD.PD[Pago 5],BD.PD[Per.P5],F$1,BD.PD[Pos],Tabla3[[#This Row],[Part.]]) -> 0 | G25: =SUMIFS(BD.PD[Pago 1],BD.PD[Per.P1],G$1,BD.PD[Pos],Tabla3[[#This Row],[Part.]])+SUMIFS(BD.PD[Pago 2],BD.PD[Per.P2],G$1,BD.PD[Pos],Tabla3[[#This Row],[Part.]])+SUMIFS(BD.PD[Pago 3],BD.PD[Per.P3],G$1,BD.PD[Pos],Tabla3[[#This Row],[Part.]])+SUMIFS(BD.PD[Pago 4],BD.PD[Per.P4],G$1,BD.PD[Pos],Tabla3[[#This Row],[Part.]])+SUMIFS(BD.PD[Pago 5],BD.PD[Per.P5],G$1,BD.PD[Pos],Tabla3[[#This Row],[Part.]]) -> 0 | H25: =SUMIFS(BD.PD[Pago 1],BD.PD[Per.P1],H$1,BD.PD[Pos],Tabla3[[#This Row],[Part.]])+SUMIFS(BD.PD[Pago 2],BD.PD[Per.P2],H$1,BD.PD[Pos],Tabla3[[#This Row],[Part.]])+SUMIFS(BD.PD[Pago 3],BD.PD[Per.P3],H$1,BD.PD[Pos],Tabla3[[#This Row],[Part.]])+SUMIFS(BD.PD[Pago 4],BD.PD[Per.P4],H$1,BD.PD[Pos],Tabla3[[#This Row],[Part.]])+SUMIFS(BD.PD[Pago 5],BD.PD[Per.P5],H$1,BD.PD[Pos],Tabla3[[#This Row],[Part.]]) -> 0 | I25: =SUMIFS(BD.PD[Pago 1],BD.PD[Per.P1],I$1,BD.PD[Pos],Tabla3[[#This Row],[Part.]])+SUMIFS(BD.PD[Pago 2],BD.PD[Per.P2],I$1,BD.PD[Pos],Tabla3[[#This Row],[Part.]])+SUMIFS(BD.PD[Pago 3],BD.PD[Per.P3],I$1,BD.PD[Pos],Tabla3[[#This Row],[Part.]])+SUMIFS(BD.PD[Pago 4],BD.PD[Per.P4],I$1,BD.PD[Pos],Tabla3[[#This Row],[Part.]])+SUMIFS(BD.PD[Pago 5],BD.PD[Per.P5],I$1,BD.PD[Pos],Tabla3[[#This Row],[Part.]]) -> 0 | J25: =SUMIFS(BD.PD[Pago 1],BD.PD[Per.P1],J$1,BD.PD[Pos],Tabla3[[#This Row],[Part.]])+SUMIFS(BD.PD[Pago 2],BD.PD[Per.P2],J$1,BD.PD[Pos],Tabla3[[#This Row],[Part.]])+SUMIFS(BD.PD[Pago 3],BD.PD[Per.P3],J$1,BD.PD[Pos],Tabla3[[#This Row],[Part.]])+SUMIFS(BD.PD[Pago 4],BD.PD[Per.P4],J$1,BD.PD[Pos],Tabla3[[#This Row],[Part.]])+SUMIFS(BD.PD[Pago 5],BD.PD[Per.P5],J$1,BD.PD[Pos],Tabla3[[#This Row],[Part.]]) -> 0 | K25: =SUMIFS(BD.PD[Pago 1],BD.PD[Per.P1],K$1,BD.PD[Pos],Tabla3[[#This Row],[Part.]])+SUMIFS(BD.PD[Pago 2],BD.PD[Per.P2],K$1,BD.PD[Pos],Tabla3[[#This Row],[Part.]])+SUMIFS(BD.PD[Pago 3],BD.PD[Per.P3],K$1,BD.PD[Pos],Tabla3[[#This Row],[Part.]])+SUMIFS(BD.PD[Pago 4],BD.PD[Per.P4],K$1,BD.PD[Pos],Tabla3[[#This Row],[Part.]])+SUMIFS(BD.PD[Pago 5],BD.PD[Per.P5],K$1,BD.PD[Pos],Tabla3[[#This Row],[Part.]]) -> 0 | ... AA25: =SUMIFS(BD.PD[Pago 1],BD.PD[Per.P1],AA$1,BD.PD[Pos],Tabla3[[#This Row],[Part.]])+SUMIFS(BD.PD[Pago 2],BD.PD[Per.P2],AA$1,BD.PD[Pos],Tabla3[[#This Row],[Part.]])+SUMIFS(BD.PD[Pago 3],BD.PD[Per.P3],AA$1,BD.PD[Pos],Tabla3[[#This Row],[Part.]])+SUMIFS(BD.PD[Pago 4],BD.PD[Per.P4],AA$1,BD.PD[Pos],Tabla3[[#This Row],[Part.]])+SUMIFS(BD.PD[Pago 5],BD.PD[Per.P5],AA$1,BD.PD[Pos],Tabla3[[#This Row],[Part.]]) -> 0 | AB25: =SUM(Tabla3[[#This Row],[P1]:[P24]]) -> 900000
A26: 2.1 | B26: =VLOOKUP(Tabla3[[#This Row],[Part.]],PPto[],3,FALSE) -> 2.10 Supervisión Civil y Sanitaria | C26: =SUMIF(BD.PD[Pos],Tabla3[[#This Row],[Part.]],BD.PD[Ppto. Orden Interna '[DOP']]) -> 0 | D26: =SUMIFS(BD.PD[Pago 1],BD.PD[Per.P1],D$1,BD.PD[Pos],Tabla3[[#This Row],[Part.]])+SUMIFS(BD.PD[Pago 2],BD.PD[Per.P2],D$1,BD.PD[Pos],Tabla3[[#This Row],[Part.]])+SUMIFS(BD.PD[Pago 3],BD.PD[Per.P3],D$1,BD.PD[Pos],Tabla3[[#This Row],[Part.]])+SUMIFS(BD.PD[Pago 4],BD.PD[Per.P4],D$1,BD.PD[Pos],Tabla3[[#This Row],[Part.]])+SUMIFS(BD.PD[Pago 5],BD.PD[Per.P5],D$1,BD.PD[Pos],Tabla3[[#This Row],[Part.]]) -> 0 | E26: =SUMIFS(BD.PD[Pago 1],BD.PD[Per.P1],E$1,BD.PD[Pos],Tabla3[[#This Row],[Part.]])+SUMIFS(BD.PD[Pago 2],BD.PD[Per.P2],E$1,BD.PD[Pos],Tabla3[[#This Row],[Part.]])+SUMIFS(BD.PD[Pago 3],BD.PD[Per.P3],E$1,BD.PD[Pos],Tabla3[[#This Row],[Part.]])+SUMIFS(BD.PD[Pago 4],BD.PD[Per.P4],E$1,BD.PD[Pos],Tabla3[[#This Row],[Part.]])+SUMIFS(BD.PD[Pago 5],BD.PD[Per.P5],E$1,BD.PD[Pos],Tabla3[[#This Row],[Part.]]) -> 0 | F26: =SUMIFS(BD.PD[Pago 1],BD.PD[Per.P1],F$1,BD.PD[Pos],Tabla3[[#This Row],[Part.]])+SUMIFS(BD.PD[Pago 2],BD.PD[Per.P2],F$1,BD.PD[Pos],Tabla3[[#This Row],[Part.]])+SUMIFS(BD.PD[Pago 3],BD.PD[Per.P3],F$1,BD.PD[Pos],Tabla3[[#This Row],[Part.]])+SUMIFS(BD.PD[Pago 4],BD.PD[Per.P4],F$1,BD.PD[Pos],Tabla3[[#This Row],[Part.]])+SUMIFS(BD.PD[Pago 5],BD.PD[Per.P5],F$1,BD.PD[Pos],Tabla3[[#This Row],[Part.]]) -> 0 | G26: =SUMIFS(BD.PD[Pago 1],BD.PD[Per.P1],G$1,BD.PD[Pos],Tabla3[[#This Row],[Part.]])+SUMIFS(BD.PD[Pago 2],BD.PD[Per.P2],G$1,BD.PD[Pos],Tabla3[[#This Row],[Part.]])+SUMIFS(BD.PD[Pago 3],BD.PD[Per.P3],G$1,BD.PD[Pos],Tabla3[[#This Row],[Part.]])+SUMIFS(BD.PD[Pago 4],BD.PD[Per.P4],G$1,BD.PD[Pos],Tabla3[[#This Row],[Part.]])+SUMIFS(BD.PD[Pago 5],BD.PD[Per.P5],G$1,BD.PD[Pos],Tabla3[[#This Row],[Part.]]) -> 0 | H26: =SUMIFS(BD.PD[Pago 1],BD.PD[Per.P1],H$1,BD.PD[Pos],Tabla3[[#This Row],[Part.]])+SUMIFS(BD.PD[Pago 2],BD.PD[Per.P2],H$1,BD.PD[Pos],Tabla3[[#This Row],[Part.]])+SUMIFS(BD.PD[Pago 3],BD.PD[Per.P3],H$1,BD.PD[Pos],Tabla3[[#This Row],[Part.]])+SUMIFS(BD.PD[Pago 4],BD.PD[Per.P4],H$1,BD.PD[Pos],Tabla3[[#This Row],[Part.]])+SUMIFS(BD.PD[Pago 5],BD.PD[Per.P5],H$1,BD.PD[Pos],Tabla3[[#This Row],[Part.]]) -> 0 | I26: =SUMIFS(BD.PD[Pago 1],BD.PD[Per.P1],I$1,BD.PD[Pos],Tabla3[[#This Row],[Part.]])+SUMIFS(BD.PD[Pago 2],BD.PD[Per.P2],I$1,BD.PD[Pos],Tabla3[[#This Row],[Part.]])+SUMIFS(BD.PD[Pago 3],BD.PD[Per.P3],I$1,BD.PD[Pos],Tabla3[[#This Row],[Part.]])+SUMIFS(BD.PD[Pago 4],BD.PD[Per.P4],I$1,BD.PD[Pos],Tabla3[[#This Row],[Part.]])+SUMIFS(BD.PD[Pago 5],BD.PD[Per.P5],I$1,BD.PD[Pos],Tabla3[[#This Row],[Part.]]) -> 0 | J26: =SUMIFS(BD.PD[Pago 1],BD.PD[Per.P1],J$1,BD.PD[Pos],Tabla3[[#This Row],[Part.]])+SUMIFS(BD.PD[Pago 2],BD.PD[Per.P2],J$1,BD.PD[Pos],Tabla3[[#This Row],[Part.]])+SUMIFS(BD.PD[Pago 3],BD.PD[Per.P3],J$1,BD.PD[Pos],Tabla3[[#This Row],[Part.]])+SUMIFS(BD.PD[Pago 4],BD.PD[Per.P4],J$1,BD.PD[Pos],Tabla3[[#This Row],[Part.]])+SUMIFS(BD.PD[Pago 5],BD.PD[Per.P5],J$1,BD.PD[Pos],Tabla3[[#This Row],[Part.]]) -> 0 | K26: =SUMIFS(BD.PD[Pago 1],BD.PD[Per.P1],K$1,BD.PD[Pos],Tabla3[[#This Row],[Part.]])+SUMIFS(BD.PD[Pago 2],BD.PD[Per.P2],K$1,BD.PD[Pos],Tabla3[[#This Row],[Part.]])+SUMIFS(BD.PD[Pago 3],BD.PD[Per.P3],K$1,BD.PD[Pos],Tabla3[[#This Row],[Part.]])+SUMIFS(BD.PD[Pago 4],BD.PD[Per.P4],K$1,BD.PD[Pos],Tabla3[[#This Row],[Part.]])+SUMIFS(BD.PD[Pago 5],BD.PD[Per.P5],K$1,BD.PD[Pos],Tabla3[[#This Row],[Part.]]) -> 0 | ... AA26: =SUMIFS(BD.PD[Pago 1],BD.PD[Per.P1],AA$1,BD.PD[Pos],Tabla3[[#This Row],[Part.]])+SUMIFS(BD.PD[Pago 2],BD.PD[Per.P2],AA$1,BD.PD[Pos],Tabla3[[#This Row],[Part.]])+SUMIFS(BD.PD[Pago 3],BD.PD[Per.P3],AA$1,BD.PD[Pos],Tabla3[[#This Row],[Part.]])+SUMIFS(BD.PD[Pago 4],BD.PD[Per.P4],AA$1,BD.PD[Pos],Tabla3[[#This Row],[Part.]])+SUMIFS(BD.PD[Pago 5],BD.PD[Per.P5],AA$1,BD.PD[Pos],Tabla3[[#This Row],[Part.]]) -> 0 | AB26: =SUM(Tabla3[[#This Row],[P1]:[P24]]) -> 0
A27: 2.11 | B27: =VLOOKUP(Tabla3[[#This Row],[Part.]],PPto[],3,FALSE) -> 2.11 Supervisión Arquitectónica | C27: =SUMIF(BD.PD[Pos],Tabla3[[#This Row],[Part.]],BD.PD[Ppto. Orden Interna '[DOP']]) -> 0 | D27: =SUMIFS(BD.PD[Pago 1],BD.PD[Per.P1],D$1,BD.PD[Pos],Tabla3[[#This Row],[Part.]])+SUMIFS(BD.PD[Pago 2],BD.PD[Per.P2],D$1,BD.PD[Pos],Tabla3[[#This Row],[Part.]])+SUMIFS(BD.PD[Pago 3],BD.PD[Per.P3],D$1,BD.PD[Pos],Tabla3[[#This Row],[Part.]])+SUMIFS(BD.PD[Pago 4],BD.PD[Per.P4],D$1,BD.PD[Pos],Tabla3[[#This Row],[Part.]])+SUMIFS(BD.PD[Pago 5],BD.PD[Per.P5],D$1,BD.PD[Pos],Tabla3[[#This Row],[Part.]]) -> 0 | E27: =SUMIFS(BD.PD[Pago 1],BD.PD[Per.P1],E$1,BD.PD[Pos],Tabla3[[#This Row],[Part.]])+SUMIFS(BD.PD[Pago 2],BD.PD[Per.P2],E$1,BD.PD[Pos],Tabla3[[#This Row],[Part.]])+SUMIFS(BD.PD[Pago 3],BD.PD[Per.P3],E$1,BD.PD[Pos],Tabla3[[#This Row],[Part.]])+SUMIFS(BD.PD[Pago 4],BD.PD[Per.P4],E$1,BD.PD[Pos],Tabla3[[#This Row],[Part.]])+SUMIFS(BD.PD[Pago 5],BD.PD[Per.P5],E$1,BD.PD[Pos],Tabla3[[#This Row],[Part.]]) -> 0 | F27: =SUMIFS(BD.PD[Pago 1],BD.PD[Per.P1],F$1,BD.PD[Pos],Tabla3[[#This Row],[Part.]])+SUMIFS(BD.PD[Pago 2],BD.PD[Per.P2],F$1,BD.PD[Pos],Tabla3[[#This Row],[Part.]])+SUMIFS(BD.PD[Pago 3],BD.PD[Per.P3],F$1,BD.PD[Pos],Tabla3[[#This Row],[Part.]])+SUMIFS(BD.PD[Pago 4],BD.PD[Per.P4],F$1,BD.PD[Pos],Tabla3[[#This Row],[Part.]])+SUMIFS(BD.PD[Pago 5],BD.PD[Per.P5],F$1,BD.PD[Pos],Tabla3[[#This Row],[Part.]]) -> 0 | G27: =SUMIFS(BD.PD[Pago 1],BD.PD[Per.P1],G$1,BD.PD[Pos],Tabla3[[#This Row],[Part.]])+SUMIFS(BD.PD[Pago 2],BD.PD[Per.P2],G$1,BD.PD[Pos],Tabla3[[#This Row],[Part.]])+SUMIFS(BD.PD[Pago 3],BD.PD[Per.P3],G$1,BD.PD[Pos],Tabla3[[#This Row],[Part.]])+SUMIFS(BD.PD[Pago 4],BD.PD[Per.P4],G$1,BD.PD[Pos],Tabla3[[#This Row],[Part.]])+SUMIFS(BD.PD[Pago 5],BD.PD[Per.P5],G$1,BD.PD[Pos],Tabla3[[#This Row],[Part.]]) -> 0 | H27: =SUMIFS(BD.PD[Pago 1],BD.PD[Per.P1],H$1,BD.PD[Pos],Tabla3[[#This Row],[Part.]])+SUMIFS(BD.PD[Pago 2],BD.PD[Per.P2],H$1,BD.PD[Pos],Tabla3[[#This Row],[Part.]])+SUMIFS(BD.PD[Pago 3],BD.PD[Per.P3],H$1,BD.PD[Pos],Tabla3[[#This Row],[Part.]])+SUMIFS(BD.PD[Pago 4],BD.PD[Per.P4],H$1,BD.PD[Pos],Tabla3[[#This Row],[Part.]])+SUMIFS(BD.PD[Pago 5],BD.PD[Per.P5],H$1,BD.PD[Pos],Tabla3[[#This Row],[Part.]]) -> 0 | I27: =SUMIFS(BD.PD[Pago 1],BD.PD[Per.P1],I$1,BD.PD[Pos],Tabla3[[#This Row],[Part.]])+SUMIFS(BD.PD[Pago 2],BD.PD[Per.P2],I$1,BD.PD[Pos],Tabla3[[#This Row],[Part.]])+SUMIFS(BD.PD[Pago 3],BD.PD[Per.P3],I$1,BD.PD[Pos],Tabla3[[#This Row],[Part.]])+SUMIFS(BD.PD[Pago 4],BD.PD[Per.P4],I$1,BD.PD[Pos],Tabla3[[#This Row],[Part.]])+SUMIFS(BD.PD[Pago 5],BD.PD[Per.P5],I$1,BD.PD[Pos],Tabla3[[#This Row],[Part.]]) -> 0 | J27: =SUMIFS(BD.PD[Pago 1],BD.PD[Per.P1],J$1,BD.PD[Pos],Tabla3[[#This Row],[Part.]])+SUMIFS(BD.PD[Pago 2],BD.PD[Per.P2],J$1,BD.PD[Pos],Tabla3[[#This Row],[Part.]])+SUMIFS(BD.PD[Pago 3],BD.PD[Per.P3],J$1,BD.PD[Pos],Tabla3[[#This Row],[Part.]])+SUMIFS(BD.PD[Pago 4],BD.PD[Per.P4],J$1,BD.PD[Pos],Tabla3[[#This Row],[Part.]])+SUMIFS(BD.PD[Pago 5],BD.PD[Per.P5],J$1,BD.PD[Pos],Tabla3[[#This Row],[Part.]]) -> 0 | K27: =SUMIFS(BD.PD[Pago 1],BD.PD[Per.P1],K$1,BD.PD[Pos],Tabla3[[#This Row],[Part.]])+SUMIFS(BD.PD[Pago 2],BD.PD[Per.P2],K$1,BD.PD[Pos],Tabla3[[#This Row],[Part.]])+SUMIFS(BD.PD[Pago 3],BD.PD[Per.P3],K$1,BD.PD[Pos],Tabla3[[#This Row],[Part.]])+SUMIFS(BD.PD[Pago 4],BD.PD[Per.P4],K$1,BD.PD[Pos],Tabla3[[#This Row],[Part.]])+SUMIFS(BD.PD[Pago 5],BD.PD[Per.P5],K$1,BD.PD[Pos],Tabla3[[#This Row],[Part.]]) -> 0 | ... AA27: =SUMIFS(BD.PD[Pago 1],BD.PD[Per.P1],AA$1,BD.PD[Pos],Tabla3[[#This Row],[Part.]])+SUMIFS(BD.PD[Pago 2],BD.PD[Per.P2],AA$1,BD.PD[Pos],Tabla3[[#This Row],[Part.]])+SUMIFS(BD.PD[Pago 3],BD.PD[Per.P3],AA$1,BD.PD[Pos],Tabla3[[#This Row],[Part.]])+SUMIFS(BD.PD[Pago 4],BD.PD[Per.P4],AA$1,BD.PD[Pos],Tabla3[[#This Row],[Part.]])+SUMIFS(BD.PD[Pago 5],BD.PD[Per.P5],AA$1,BD.PD[Pos],Tabla3[[#This Row],[Part.]]) -> 0 | AB27: =SUM(Tabla3[[#This Row],[P1]:[P24]]) -> 0
A28: 3 | B28: =VLOOKUP(Tabla3[[#This Row],[Part.]],PPto[],3,FALSE) -> 3.00 Sistema Eléctrico | C28: =SUM(C29:C32) -> 30715852 | D28: =SUM(D29:D32) -> 0 | E28: =SUM(E29:E32) -> 0 | F28: =SUM(F29:F32) -> 0 | G28: =SUM(G29:G32) -> 0 | H28: =SUM(H29:H32) -> 0 | I28: =SUM(I29:I32) -> 0 | J28: =SUM(J29:J32) -> 0 | ... Y28: =SUM(Y29:Y32) -> 11091542 | AA28: =SUM(AA29:AA36) -> 10259902 | AB28: =SUM(Tabla3[[#This Row],[P1]:[P24]]) -> 31163599
A29: 3.01 | B29: =VLOOKUP(Tabla3[[#This Row],[Part.]],PPto[],3,FALSE) -> 3.01 Instalaciones Eléctricas | C29: =SUMIF(BD.PD[Pos],Tabla3[[#This Row],[Part.]],BD.PD[Ppto. Orden Interna '[DOP']]) -> 19624310 | D29: =SUMIFS(BD.PD[Pago 1],BD.PD[Per.P1],D$1,BD.PD[Pos],Tabla3[[#This Row],[Part.]])+SUMIFS(BD.PD[Pago 2],BD.PD[Per.P2],D$1,BD.PD[Pos],Tabla3[[#This Row],[Part.]])+SUMIFS(BD.PD[Pago 3],BD.PD[Per.P3],D$1,BD.PD[Pos],Tabla3[[#This Row],[Part.]])+SUMIFS(BD.PD[Pago 4],BD.PD[Per.P4],D$1,BD.PD[Pos],Tabla3[[#This Row],[Part.]])+SUMIFS(BD.PD[Pago 5],BD.PD[Per.P5],D$1,BD.PD[Pos],Tabla3[[#This Row],[Part.]]) -> 0 | E29: =SUMIFS(BD.PD[Pago 1],BD.PD[Per.P1],E$1,BD.PD[Pos],Tabla3[[#This Row],[Part.]])+SUMIFS(BD.PD[Pago 2],BD.PD[Per.P2],E$1,BD.PD[Pos],Tabla3[[#This Row],[Part.]])+SUMIFS(BD.PD[Pago 3],BD.PD[Per.P3],E$1,BD.PD[Pos],Tabla3[[#This Row],[Part.]])+SUMIFS(BD.PD[Pago 4],BD.PD[Per.P4],E$1,BD.PD[Pos],Tabla3[[#This Row],[Part.]])+SUMIFS(BD.PD[Pago 5],BD.PD[Per.P5],E$1,BD.PD[Pos],Tabla3[[#This Row],[Part.]]) -> 0 | F29: =SUMIFS(BD.PD[Pago 1],BD.PD[Per.P1],F$1,BD.PD[Pos],Tabla3[[#This Row],[Part.]])+SUMIFS(BD.PD[Pago 2],BD.PD[Per.P2],F$1,BD.PD[Pos],Tabla3[[#This Row],[Part.]])+SUMIFS(BD.PD[Pago 3],BD.PD[Per.P3],F$1,BD.PD[Pos],Tabla3[[#This Row],[Part.]])+SUMIFS(BD.PD[Pago 4],BD.PD[Per.P4],F$1,BD.PD[Pos],Tabla3[[#This Row],[Part.]])+SUMIFS(BD.PD[Pago 5],BD.PD[Per.P5],F$1,BD.PD[Pos],Tabla3[[#This Row],[Part.]]) -> 0 | G29: =SUMIFS(BD.PD[Pago 1],BD.PD[Per.P1],G$1,BD.PD[Pos],Tabla3[[#This Row],[Part.]])+SUMIFS(BD.PD[Pago 2],BD.PD[Per.P2],G$1,BD.PD[Pos],Tabla3[[#This Row],[Part.]])+SUMIFS(BD.PD[Pago 3],BD.PD[Per.P3],G$1,BD.PD[Pos],Tabla3[[#This Row],[Part.]])+SUMIFS(BD.PD[Pago 4],BD.PD[Per.P4],G$1,BD.PD[Pos],Tabla3[[#This Row],[Part.]])+SUMIFS(BD.PD[Pago 5],BD.PD[Per.P5],G$1,BD.PD[Pos],Tabla3[[#This Row],[Part.]]) -> 0 | H29: =SUMIFS(BD.PD[Pago 1],BD.PD[Per.P1],H$1,BD.PD[Pos],Tabla3[[#This Row],[Part.]])+SUMIFS(BD.PD[Pago 2],BD.PD[Per.P2],H$1,BD.PD[Pos],Tabla3[[#This Row],[Part.]])+SUMIFS(BD.PD[Pago 3],BD.PD[Per.P3],H$1,BD.PD[Pos],Tabla3[[#This Row],[Part.]])+SUMIFS(BD.PD[Pago 4],BD.PD[Per.P4],H$1,BD.PD[Pos],Tabla3[[#This Row],[Part.]])+SUMIFS(BD.PD[Pago 5],BD.PD[Per.P5],H$1,BD.PD[Pos],Tabla3[[#This Row],[Part.]]) -> 0 | I29: =SUMIFS(BD.PD[Pago 1],BD.PD[Per.P1],I$1,BD.PD[Pos],Tabla3[[#This Row],[Part.]])+SUMIFS(BD.PD[Pago 2],BD.PD[Per.P2],I$1,BD.PD[Pos],Tabla3[[#This Row],[Part.]])+SUMIFS(BD.PD[Pago 3],BD.PD[Per.P3],I$1,BD.PD[Pos],Tabla3[[#This Row],[Part.]])+SUMIFS(BD.PD[Pago 4],BD.PD[Per.P4],I$1,BD.PD[Pos],Tabla3[[#This Row],[Part.]])+SUMIFS(BD.PD[Pago 5],BD.PD[Per.P5],I$1,BD.PD[Pos],Tabla3[[#This Row],[Part.]]) -> 0 | J29: =SUMIFS(BD.PD[Pago 1],BD.PD[Per.P1],J$1,BD.PD[Pos],Tabla3[[#This Row],[Part.]])+SUMIFS(BD.PD[Pago 2],BD.PD[Per.P2],J$1,BD.PD[Pos],Tabla3[[#This Row],[Part.]])+SUMIFS(BD.PD[Pago 3],BD.PD[Per.P3],J$1,BD.PD[Pos],Tabla3[[#This Row],[Part.]])+SUMIFS(BD.PD[Pago 4],BD.PD[Per.P4],J$1,BD.PD[Pos],Tabla3[[#This Row],[Part.]])+SUMIFS(BD.PD[Pago 5],BD.PD[Per.P5],J$1,BD.PD[Pos],Tabla3[[#This Row],[Part.]]) -> 0 | K29: =SUMIFS(BD.PD[Pago 1],BD.PD[Per.P1],K$1,BD.PD[Pos],Tabla3[[#This Row],[Part.]])+SUMIFS(BD.PD[Pago 2],BD.PD[Per.P2],K$1,BD.PD[Pos],Tabla3[[#This Row],[Part.]])+SUMIFS(BD.PD[Pago 3],BD.PD[Per.P3],K$1,BD.PD[Pos],Tabla3[[#This Row],[Part.]])+SUMIFS(BD.PD[Pago 4],BD.PD[Per.P4],K$1,BD.PD[Pos],Tabla3[[#This Row],[Part.]])+SUMIFS(BD.PD[Pago 5],BD.PD[Per.P5],K$1,BD.PD[Pos],Tabla3[[#This Row],[Part.]]) -> 0 | ... AA29: =SUMIFS(BD.PD[Pago 1],BD.PD[Per.P1],AA$1,BD.PD[Pos],Tabla3[[#This Row],[Part.]])+SUMIFS(BD.PD[Pago 2],BD.PD[Per.P2],AA$1,BD.PD[Pos],Tabla3[[#This Row],[Part.]])+SUMIFS(BD.PD[Pago 3],BD.PD[Per.P3],AA$1,BD.PD[Pos],Tabla3[[#This Row],[Part.]])+SUMIFS(BD.PD[Pago 4],BD.PD[Per.P4],AA$1,BD.PD[Pos],Tabla3[[#This Row],[Part.]])+SUMIFS(BD.PD[Pago 5],BD.PD[Per.P5],AA$1,BD.PD[Pos],Tabla3[[#This Row],[Part.]]) -> 9812155 | AB29: =SUM(Tabla3[[#This Row],[P1]:[P24]]) -> 19624310
A30: 3.02 | B30: =VLOOKUP(Tabla3[[#This Row],[Part.]],PPto[],3,FALSE) -> 3.02 Supervisión Eléctrica | C30: =SUMIF(BD.PD[Pos],Tabla3[[#This Row],[Part.]],BD.PD[Ppto. Orden Interna '[DOP']]) -> 0 | D30: =SUMIFS(BD.PD[Pago 1],BD.PD[Per.P1],D$1,BD.PD[Pos],Tabla3[[#This Row],[Part.]])+SUMIFS(BD.PD[Pago 2],BD.PD[Per.P2],D$1,BD.PD[Pos],Tabla3[[#This Row],[Part.]])+SUMIFS(BD.PD[Pago 3],BD.PD[Per.P3],D$1,BD.PD[Pos],Tabla3[[#This Row],[Part.]])+SUMIFS(BD.PD[Pago 4],BD.PD[Per.P4],D$1,BD.PD[Pos],Tabla3[[#This Row],[Part.]])+SUMIFS(BD.PD[Pago 5],BD.PD[Per.P5],D$1,BD.PD[Pos],Tabla3[[#This Row],[Part.]]) -> 0 | E30: =SUMIFS(BD.PD[Pago 1],BD.PD[Per.P1],E$1,BD.PD[Pos],Tabla3[[#This Row],[Part.]])+SUMIFS(BD.PD[Pago 2],BD.PD[Per.P2],E$1,BD.PD[Pos],Tabla3[[#This Row],[Part.]])+SUMIFS(BD.PD[Pago 3],BD.PD[Per.P3],E$1,BD.PD[Pos],Tabla3[[#This Row],[Part.]])+SUMIFS(BD.PD[Pago 4],BD.PD[Per.P4],E$1,BD.PD[Pos],Tabla3[[#This Row],[Part.]])+SUMIFS(BD.PD[Pago 5],BD.PD[Per.P5],E$1,BD.PD[Pos],Tabla3[[#This Row],[Part.]]) -> 0 | F30: =SUMIFS(BD.PD[Pago 1],BD.PD[Per.P1],F$1,BD.PD[Pos],Tabla3[[#This Row],[Part.]])+SUMIFS(BD.PD[Pago 2],BD.PD[Per.P2],F$1,BD.PD[Pos],Tabla3[[#This Row],[Part.]])+SUMIFS(BD.PD[Pago 3],BD.PD[Per.P3],F$1,BD.PD[Pos],Tabla3[[#This Row],[Part.]])+SUMIFS(BD.PD[Pago 4],BD.PD[Per.P4],F$1,BD.PD[Pos],Tabla3[[#This Row],[Part.]])+SUMIFS(BD.PD[Pago 5],BD.PD[Per.P5],F$1,BD.PD[Pos],Tabla3[[#This Row],[Part.]]) -> 0 | G30: =SUMIFS(BD.PD[Pago 1],BD.PD[Per.P1],G$1,BD.PD[Pos],Tabla3[[#This Row],[Part.]])+SUMIFS(BD.PD[Pago 2],BD.PD[Per.P2],G$1,BD.PD[Pos],Tabla3[[#This Row],[Part.]])+SUMIFS(BD.PD[Pago 3],BD.PD[Per.P3],G$1,BD.PD[Pos],Tabla3[[#This Row],[Part.]])+SUMIFS(BD.PD[Pago 4],BD.PD[Per.P4],G$1,BD.PD[Pos],Tabla3[[#This Row],[Part.]])+SUMIFS(BD.PD[Pago 5],BD.PD[Per.P5],G$1,BD.PD[Pos],Tabla3[[#This Row],[Part.]]) -> 0 | H30: =SUMIFS(BD.PD[Pago 1],BD.PD[Per.P1],H$1,BD.PD[Pos],Tabla3[[#This Row],[Part.]])+SUMIFS(BD.PD[Pago 2],BD.PD[Per.P2],H$1,BD.PD[Pos],Tabla3[[#This Row],[Part.]])+SUMIFS(BD.PD[Pago 3],BD.PD[Per.P3],H$1,BD.PD[Pos],Tabla3[[#This Row],[Part.]])+SUMIFS(BD.PD[Pago 4],BD.PD[Per.P4],H$1,BD.PD[Pos],Tabla3[[#This Row],[Part.]])+SUMIFS(BD.PD[Pago 5],BD.PD[Per.P5],H$1,BD.PD[Pos],Tabla3[[#This Row],[Part.]]) -> 0 | I30: =SUMIFS(BD.PD[Pago 1],BD.PD[Per.P1],I$1,BD.PD[Pos],Tabla3[[#This Row],[Part.]])+SUMIFS(BD.PD[Pago 2],BD.PD[Per.P2],I$1,BD.PD[Pos],Tabla3[[#This Row],[Part.]])+SUMIFS(BD.PD[Pago 3],BD.PD[Per.P3],I$1,BD.PD[Pos],Tabla3[[#This Row],[Part.]])+SUMIFS(BD.PD[Pago 4],BD.PD[Per.P4],I$1,BD.PD[Pos],Tabla3[[#This Row],[Part.]])+SUMIFS(BD.PD[Pago 5],BD.PD[Per.P5],I$1,BD.PD[Pos],Tabla3[[#This Row],[Part.]]) -> 0 | J30: =SUMIFS(BD.PD[Pago 1],BD.PD[Per.P1],J$1,BD.PD[Pos],Tabla3[[#This Row],[Part.]])+SUMIFS(BD.PD[Pago 2],BD.PD[Per.P2],J$1,BD.PD[Pos],Tabla3[[#This Row],[Part.]])+SUMIFS(BD.PD[Pago 3],BD.PD[Per.P3],J$1,BD.PD[Pos],Tabla3[[#This Row],[Part.]])+SUMIFS(BD.PD[Pago 4],BD.PD[Per.P4],J$1,BD.PD[Pos],Tabla3[[#This Row],[Part.]])+SUMIFS(BD.PD[Pago 5],BD.PD[Per.P5],J$1,BD.PD[Pos],Tabla3[[#This Row],[Part.]]) -> 0 | K30: =SUMIFS(BD.PD[Pago 1],BD.PD[Per.P1],K$1,BD.PD[Pos],Tabla3[[#This Row],[Part.]])+SUMIFS(BD.PD[Pago 2],BD.PD[Per.P2],K$1,BD.PD[Pos],Tabla3[[#This Row],[Part.]])+SUMIFS(BD.PD[Pago 3],BD.PD[Per.P3],K$1,BD.PD[Pos],Tabla3[[#This Row],[Part.]])+SUMIFS(BD.PD[Pago 4],BD.PD[Per.P4],K$1,BD.PD[Pos],Tabla3[[#This Row],[Part.]])+SUMIFS(BD.PD[Pago 5],BD.PD[Per.P5],K$1,BD.PD[Pos],Tabla3[[#This Row],[Part.]]) -> 0 | ... AA30: =SUMIFS(BD.PD[Pago 1],BD.PD[Per.P1],AA$1,BD.PD[Pos],Tabla3[[#This Row],[Part.]])+SUMIFS(BD.PD[Pago 2],BD.PD[Per.P2],AA$1,BD.PD[Pos],Tabla3[[#This Row],[Part.]])+SUMIFS(BD.PD[Pago 3],BD.PD[Per.P3],AA$1,BD.PD[Pos],Tabla3[[#This Row],[Part.]])+SUMIFS(BD.PD[Pago 4],BD.PD[Per.P4],AA$1,BD.PD[Pos],Tabla3[[#This Row],[Part.]])+SUMIFS(BD.PD[Pago 5],BD.PD[Per.P5],AA$1,BD.PD[Pos],Tabla3[[#This Row],[Part.]]) -> 0 | AB30: =SUM(Tabla3[[#This Row],[P1]:[P24]]) -> 0
A31: 3.03 | B31: =VLOOKUP(Tabla3[[#This Row],[Part.]],PPto[],3,FALSE) -> 3.03 Generadores | C31: =SUMIF(BD.PD[Pos],Tabla3[[#This Row],[Part.]],BD.PD[Ppto. Orden Interna '[DOP']]) -> 10030931 | D31: =SUMIFS(BD.PD[Pago 1],BD.PD[Per.P1],D$1,BD.PD[Pos],Tabla3[[#This Row],[Part.]])+SUMIFS(BD.PD[Pago 2],BD.PD[Per.P2],D$1,BD.PD[Pos],Tabla3[[#This Row],[Part.]])+SUMIFS(BD.PD[Pago 3],BD.PD[Per.P3],D$1,BD.PD[Pos],Tabla3[[#This Row],[Part.]])+SUMIFS(BD.PD[Pago 4],BD.PD[Per.P4],D$1,BD.PD[Pos],Tabla3[[#This Row],[Part.]])+SUMIFS(BD.PD[Pago 5],BD.PD[Per.P5],D$1,BD.PD[Pos],Tabla3[[#This Row],[Part.]]) -> 0 | E31: =SUMIFS(BD.PD[Pago 1],BD.PD[Per.P1],E$1,BD.PD[Pos],Tabla3[[#This Row],[Part.]])+SUMIFS(BD.PD[Pago 2],BD.PD[Per.P2],E$1,BD.PD[Pos],Tabla3[[#This Row],[Part.]])+SUMIFS(BD.PD[Pago 3],BD.PD[Per.P3],E$1,BD.PD[Pos],Tabla3[[#This Row],[Part.]])+SUMIFS(BD.PD[Pago 4],BD.PD[Per.P4],E$1,BD.PD[Pos],Tabla3[[#This Row],[Part.]])+SUMIFS(BD.PD[Pago 5],BD.PD[Per.P5],E$1,BD.PD[Pos],Tabla3[[#This Row],[Part.]]) -> 0 | F31: =SUMIFS(BD.PD[Pago 1],BD.PD[Per.P1],F$1,BD.PD[Pos],Tabla3[[#This Row],[Part.]])+SUMIFS(BD.PD[Pago 2],BD.PD[Per.P2],F$1,BD.PD[Pos],Tabla3[[#This Row],[Part.]])+SUMIFS(BD.PD[Pago 3],BD.PD[Per.P3],F$1,BD.PD[Pos],Tabla3[[#This Row],[Part.]])+SUMIFS(BD.PD[Pago 4],BD.PD[Per.P4],F$1,BD.PD[Pos],Tabla3[[#This Row],[Part.]])+SUMIFS(BD.PD[Pago 5],BD.PD[Per.P5],F$1,BD.PD[Pos],Tabla3[[#This Row],[Part.]]) -> 0 | G31: =SUMIFS(BD.PD[Pago 1],BD.PD[Per.P1],G$1,BD.PD[Pos],Tabla3[[#This Row],[Part.]])+SUMIFS(BD.PD[Pago 2],BD.PD[Per.P2],G$1,BD.PD[Pos],Tabla3[[#This Row],[Part.]])+SUMIFS(BD.PD[Pago 3],BD.PD[Per.P3],G$1,BD.PD[Pos],Tabla3[[#This Row],[Part.]])+SUMIFS(BD.PD[Pago 4],BD.PD[Per.P4],G$1,BD.PD[Pos],Tabla3[[#This Row],[Part.]])+SUMIFS(BD.PD[Pago 5],BD.PD[Per.P5],G$1,BD.PD[Pos],Tabla3[[#This Row],[Part.]]) -> 0 | H31: =SUMIFS(BD.PD[Pago 1],BD.PD[Per.P1],H$1,BD.PD[Pos],Tabla3[[#This Row],[Part.]])+SUMIFS(BD.PD[Pago 2],BD.PD[Per.P2],H$1,BD.PD[Pos],Tabla3[[#This Row],[Part.]])+SUMIFS(BD.PD[Pago 3],BD.PD[Per.P3],H$1,BD.PD[Pos],Tabla3[[#This Row],[Part.]])+SUMIFS(BD.PD[Pago 4],BD.PD[Per.P4],H$1,BD.PD[Pos],Tabla3[[#This Row],[Part.]])+SUMIFS(BD.PD[Pago 5],BD.PD[Per.P5],H$1,BD.PD[Pos],Tabla3[[#This Row],[Part.]]) -> 0 | I31: =SUMIFS(BD.PD[Pago 1],BD.PD[Per.P1],I$1,BD.PD[Pos],Tabla3[[#This Row],[Part.]])+SUMIFS(BD.PD[Pago 2],BD.PD[Per.P2],I$1,BD.PD[Pos],Tabla3[[#This Row],[Part.]])+SUMIFS(BD.PD[Pago 3],BD.PD[Per.P3],I$1,BD.PD[Pos],Tabla3[[#This Row],[Part.]])+SUMIFS(BD.PD[Pago 4],BD.PD[Per.P4],I$1,BD.PD[Pos],Tabla3[[#This Row],[Part.]])+SUMIFS(BD.PD[Pago 5],BD.PD[Per.P5],I$1,BD.PD[Pos],Tabla3[[#This Row],[Part.]]) -> 0 | J31: =SUMIFS(BD.PD[Pago 1],BD.PD[Per.P1],J$1,BD.PD[Pos],Tabla3[[#This Row],[Part.]])+SUMIFS(BD.PD[Pago 2],BD.PD[Per.P2],J$1,BD.PD[Pos],Tabla3[[#This Row],[Part.]])+SUMIFS(BD.PD[Pago 3],BD.PD[Per.P3],J$1,BD.PD[Pos],Tabla3[[#This Row],[Part.]])+SUMIFS(BD.PD[Pago 4],BD.PD[Per.P4],J$1,BD.PD[Pos],Tabla3[[#This Row],[Part.]])+SUMIFS(BD.PD[Pago 5],BD.PD[Per.P5],J$1,BD.PD[Pos],Tabla3[[#This Row],[Part.]]) -> 0 | K31: =SUMIFS(BD.PD[Pago 1],BD.PD[Per.P1],K$1,BD.PD[Pos],Tabla3[[#This Row],[Part.]])+SUMIFS(BD.PD[Pago 2],BD.PD[Per.P2],K$1,BD.PD[Pos],Tabla3[[#This Row],[Part.]])+SUMIFS(BD.PD[Pago 3],BD.PD[Per.P3],K$1,BD.PD[Pos],Tabla3[[#This Row],[Part.]])+SUMIFS(BD.PD[Pago 4],BD.PD[Per.P4],K$1,BD.PD[Pos],Tabla3[[#This Row],[Part.]])+SUMIFS(BD.PD[Pago 5],BD.PD[Per.P5],K$1,BD.PD[Pos],Tabla3[[#This Row],[Part.]]) -> 0 | ... AA31: =SUMIFS(BD.PD[Pago 1],BD.PD[Per.P1],AA$1,BD.PD[Pos],Tabla3[[#This Row],[Part.]])+SUMIFS(BD.PD[Pago 2],BD.PD[Per.P2],AA$1,BD.PD[Pos],Tabla3[[#This Row],[Part.]])+SUMIFS(BD.PD[Pago 3],BD.PD[Per.P3],AA$1,BD.PD[Pos],Tabla3[[#This Row],[Part.]])+SUMIFS(BD.PD[Pago 4],BD.PD[Per.P4],AA$1,BD.PD[Pos],Tabla3[[#This Row],[Part.]])+SUMIFS(BD.PD[Pago 5],BD.PD[Per.P5],AA$1,BD.PD[Pos],Tabla3[[#This Row],[Part.]]) -> 0 | AB31: =SUM(Tabla3[[#This Row],[P1]:[P24]]) -> 10030931
A32: 3.04 | B32: =VLOOKUP(Tabla3[[#This Row],[Part.]],PPto[],3,FALSE) -> 3.04 Inversor y UPS | C32: =SUMIF(BD.PD[Pos],Tabla3[[#This Row],[Part.]],BD.PD[Ppto. Orden Interna '[DOP']]) -> 1060611.1 | D32: =SUMIFS(BD.PD[Pago 1],BD.PD[Per.P1],D$1,BD.PD[Pos],Tabla3[[#This Row],[Part.]])+SUMIFS(BD.PD[Pago 2],BD.PD[Per.P2],D$1,BD.PD[Pos],Tabla3[[#This Row],[Part.]])+SUMIFS(BD.PD[Pago 3],BD.PD[Per.P3],D$1,BD.PD[Pos],Tabla3[[#This Row],[Part.]])+SUMIFS(BD.PD[Pago 4],BD.PD[Per.P4],D$1,BD.PD[Pos],Tabla3[[#This Row],[Part.]])+SUMIFS(BD.PD[Pago 5],BD.PD[Per.P5],D$1,BD.PD[Pos],Tabla3[[#This Row],[Part.]]) -> 0 | E32: =SUMIFS(BD.PD[Pago 1],BD.PD[Per.P1],E$1,BD.PD[Pos],Tabla3[[#This Row],[Part.]])+SUMIFS(BD.PD[Pago 2],BD.PD[Per.P2],E$1,BD.PD[Pos],Tabla3[[#This Row],[Part.]])+SUMIFS(BD.PD[Pago 3],BD.PD[Per.P3],E$1,BD.PD[Pos],Tabla3[[#This Row],[Part.]])+SUMIFS(BD.PD[Pago 4],BD.PD[Per.P4],E$1,BD.PD[Pos],Tabla3[[#This Row],[Part.]])+SUMIFS(BD.PD[Pago 5],BD.PD[Per.P5],E$1,BD.PD[Pos],Tabla3[[#This Row],[Part.]]) -> 0 | F32: =SUMIFS(BD.PD[Pago 1],BD.PD[Per.P1],F$1,BD.PD[Pos],Tabla3[[#This Row],[Part.]])+SUMIFS(BD.PD[Pago 2],BD.PD[Per.P2],F$1,BD.PD[Pos],Tabla3[[#This Row],[Part.]])+SUMIFS(BD.PD[Pago 3],BD.PD[Per.P3],F$1,BD.PD[Pos],Tabla3[[#This Row],[Part.]])+SUMIFS(BD.PD[Pago 4],BD.PD[Per.P4],F$1,BD.PD[Pos],Tabla3[[#This Row],[Part.]])+SUMIFS(BD.PD[Pago 5],BD.PD[Per.P5],F$1,BD.PD[Pos],Tabla3[[#This Row],[Part.]]) -> 0 | G32: =SUMIFS(BD.PD[Pago 1],BD.PD[Per.P1],G$1,BD.PD[Pos],Tabla3[[#This Row],[Part.]])+SUMIFS(BD.PD[Pago 2],BD.PD[Per.P2],G$1,BD.PD[Pos],Tabla3[[#This Row],[Part.]])+SUMIFS(BD.PD[Pago 3],BD.PD[Per.P3],G$1,BD.PD[Pos],Tabla3[[#This Row],[Part.]])+SUMIFS(BD.PD[Pago 4],BD.PD[Per.P4],G$1,BD.PD[Pos],Tabla3[[#This Row],[Part.]])+SUMIFS(BD.PD[Pago 5],BD.PD[Per.P5],G$1,BD.PD[Pos],Tabla3[[#This Row],[Part.]]) -> 0 | H32: =SUMIFS(BD.PD[Pago 1],BD.PD[Per.P1],H$1,BD.PD[Pos],Tabla3[[#This Row],[Part.]])+SUMIFS(BD.PD[Pago 2],BD.PD[Per.P2],H$1,BD.PD[Pos],Tabla3[[#This Row],[Part.]])+SUMIFS(BD.PD[Pago 3],BD.PD[Per.P3],H$1,BD.PD[Pos],Tabla3[[#This Row],[Part.]])+SUMIFS(BD.PD[Pago 4],BD.PD[Per.P4],H$1,BD.PD[Pos],Tabla3[[#This Row],[Part.]])+SUMIFS(BD.PD[Pago 5],BD.PD[Per.P5],H$1,BD.PD[Pos],Tabla3[[#This Row],[Part.]]) -> 0 | I32: =SUMIFS(BD.PD[Pago 1],BD.PD[Per.P1],I$1,BD.PD[Pos],Tabla3[[#This Row],[Part.]])+SUMIFS(BD.PD[Pago 2],BD.PD[Per.P2],I$1,BD.PD[Pos],Tabla3[[#This Row],[Part.]])+SUMIFS(BD.PD[Pago 3],BD.PD[Per.P3],I$1,BD.PD[Pos],Tabla3[[#This Row],[Part.]])+SUMIFS(BD.PD[Pago 4],BD.PD[Per.P4],I$1,BD.PD[Pos],Tabla3[[#This Row],[Part.]])+SUMIFS(BD.PD[Pago 5],BD.PD[Per.P5],I$1,BD.PD[Pos],Tabla3[[#This Row],[Part.]]) -> 0 | J32: =SUMIFS(BD.PD[Pago 1],BD.PD[Per.P1],J$1,BD.PD[Pos],Tabla3[[#This Row],[Part.]])+SUMIFS(BD.PD[Pago 2],BD.PD[Per.P2],J$1,BD.PD[Pos],Tabla3[[#This Row],[Part.]])+SUMIFS(BD.PD[Pago 3],BD.PD[Per.P3],J$1,BD.PD[Pos],Tabla3[[#This Row],[Part.]])+SUMIFS(BD.PD[Pago 4],BD.PD[Per.P4],J$1,BD.PD[Pos],Tabla3[[#This Row],[Part.]])+SUMIFS(BD.PD[Pago 5],BD.PD[Per.P5],J$1,BD.PD[Pos],Tabla3[[#This Row],[Part.]]) -> 0 | K32: =SUMIFS(BD.PD[Pago 1],BD.PD[Per.P1],K$1,BD.PD[Pos],Tabla3[[#This Row],[Part.]])+SUMIFS(BD.PD[Pago 2],BD.PD[Per.P2],K$1,BD.PD[Pos],Tabla3[[#This Row],[Part.]])+SUMIFS(BD.PD[Pago 3],BD.PD[Per.P3],K$1,BD.PD[Pos],Tabla3[[#This Row],[Part.]])+SUMIFS(BD.PD[Pago 4],BD.PD[Per.P4],K$1,BD.PD[Pos],Tabla3[[#This Row],[Part.]])+SUMIFS(BD.PD[Pago 5],BD.PD[Per.P5],K$1,BD.PD[Pos],Tabla3[[#This Row],[Part.]]) -> 0 | ... AA32: =SUMIFS(BD.PD[Pago 1],BD.PD[Per.P1],AA$1,BD.PD[Pos],Tabla3[[#This Row],[Part.]])+SUMIFS(BD.PD[Pago 2],BD.PD[Per.P2],AA$1,BD.PD[Pos],Tabla3[[#This Row],[Part.]])+SUMIFS(BD.PD[Pago 3],BD.PD[Per.P3],AA$1,BD.PD[Pos],Tabla3[[#This Row],[Part.]])+SUMIFS(BD.PD[Pago 4],BD.PD[Per.P4],AA$1,BD.PD[Pos],Tabla3[[#This Row],[Part.]])+SUMIFS(BD.PD[Pago 5],BD.PD[Per.P5],AA$1,BD.PD[Pos],Tabla3[[#This Row],[Part.]]) -> 0 | AB32: =SUM(Tabla3[[#This Row],[P1]:[P24]]) -> 1060611.1
A33: 4 | B33: =VLOOKUP(Tabla3[[#This Row],[Part.]],PPto[],3,FALSE) -> 4.00 Sistema de Climatización | C33: =SUM(C34:C36) -> 6739429.1 | D33: =SUM(D34:D36) -> 0 | E33: =SUM(E34:E36) -> 0 | F33: =SUM(F34:F36) -> 0 | G33: =SUM(G34:G36) -> 0 | H33: =SUM(H34:H36) -> 0 | I33: =SUM(I34:I36) -> 0 | J33: =SUM(J34:J36) -> 0 | ... Y33: =SUM(Y34:Y36) -> 3481651.3 | AB33: =SUM(Tabla3[[#This Row],[P1]:[P24]]) -> 6291682
A34: 4.01 | B34: =VLOOKUP(Tabla3[[#This Row],[Part.]],PPto[],3,FALSE) -> 4.01 Suministro e instalación de Equipos | C34: =SUMIF(BD.PD[Pos],Tabla3[[#This Row],[Part.]],BD.PD[Ppto. Orden Interna '[DOP']]) -> 5620061.3 | D34: =SUMIFS(BD.PD[Pago 1],BD.PD[Per.P1],D$1,BD.PD[Pos],Tabla3[[#This Row],[Part.]])+SUMIFS(BD.PD[Pago 2],BD.PD[Per.P2],D$1,BD.PD[Pos],Tabla3[[#This Row],[Part.]])+SUMIFS(BD.PD[Pago 3],BD.PD[Per.P3],D$1,BD.PD[Pos],Tabla3[[#This Row],[Part.]])+SUMIFS(BD.PD[Pago 4],BD.PD[Per.P4],D$1,BD.PD[Pos],Tabla3[[#This Row],[Part.]])+SUMIFS(BD.PD[Pago 5],BD.PD[Per.P5],D$1,BD.PD[Pos],Tabla3[[#This Row],[Part.]]) -> 0 | E34: =SUMIFS(BD.PD[Pago 1],BD.PD[Per.P1],E$1,BD.PD[Pos],Tabla3[[#This Row],[Part.]])+SUMIFS(BD.PD[Pago 2],BD.PD[Per.P2],E$1,BD.PD[Pos],Tabla3[[#This Row],[Part.]])+SUMIFS(BD.PD[Pago 3],BD.PD[Per.P3],E$1,BD.PD[Pos],Tabla3[[#This Row],[Part.]])+SUMIFS(BD.PD[Pago 4],BD.PD[Per.P4],E$1,BD.PD[Pos],Tabla3[[#This Row],[Part.]])+SUMIFS(BD.PD[Pago 5],BD.PD[Per.P5],E$1,BD.PD[Pos],Tabla3[[#This Row],[Part.]]) -> 0 | F34: =SUMIFS(BD.PD[Pago 1],BD.PD[Per.P1],F$1,BD.PD[Pos],Tabla3[[#This Row],[Part.]])+SUMIFS(BD.PD[Pago 2],BD.PD[Per.P2],F$1,BD.PD[Pos],Tabla3[[#This Row],[Part.]])+SUMIFS(BD.PD[Pago 3],BD.PD[Per.P3],F$1,BD.PD[Pos],Tabla3[[#This Row],[Part.]])+SUMIFS(BD.PD[Pago 4],BD.PD[Per.P4],F$1,BD.PD[Pos],Tabla3[[#This Row],[Part.]])+SUMIFS(BD.PD[Pago 5],BD.PD[Per.P5],F$1,BD.PD[Pos],Tabla3[[#This Row],[Part.]]) -> 0 | G34: =SUMIFS(BD.PD[Pago 1],BD.PD[Per.P1],G$1,BD.PD[Pos],Tabla3[[#This Row],[Part.]])+SUMIFS(BD.PD[Pago 2],BD.PD[Per.P2],G$1,BD.PD[Pos],Tabla3[[#This Row],[Part.]])+SUMIFS(BD.PD[Pago 3],BD.PD[Per.P3],G$1,BD.PD[Pos],Tabla3[[#This Row],[Part.]])+SUMIFS(BD.PD[Pago 4],BD.PD[Per.P4],G$1,BD.PD[Pos],Tabla3[[#This Row],[Part.]])+SUMIFS(BD.PD[Pago 5],BD.PD[Per.P5],G$1,BD.PD[Pos],Tabla3[[#This Row],[Part.]]) -> 0 | H34: =SUMIFS(BD.PD[Pago 1],BD.PD[Per.P1],H$1,BD.PD[Pos],Tabla3[[#This Row],[Part.]])+SUMIFS(BD.PD[Pago 2],BD.PD[Per.P2],H$1,BD.PD[Pos],Tabla3[[#This Row],[Part.]])+SUMIFS(BD.PD[Pago 3],BD.PD[Per.P3],H$1,BD.PD[Pos],Tabla3[[#This Row],[Part.]])+SUMIFS(BD.PD[Pago 4],BD.PD[Per.P4],H$1,BD.PD[Pos],Tabla3[[#This Row],[Part.]])+SUMIFS(BD.PD[Pago 5],BD.PD[Per.P5],H$1,BD.PD[Pos],Tabla3[[#This Row],[Part.]]) -> 0 | I34: =SUMIFS(BD.PD[Pago 1],BD.PD[Per.P1],I$1,BD.PD[Pos],Tabla3[[#This Row],[Part.]])+SUMIFS(BD.PD[Pago 2],BD.PD[Per.P2],I$1,BD.PD[Pos],Tabla3[[#This Row],[Part.]])+SUMIFS(BD.PD[Pago 3],BD.PD[Per.P3],I$1,BD.PD[Pos],Tabla3[[#This Row],[Part.]])+SUMIFS(BD.PD[Pago 4],BD.PD[Per.P4],I$1,BD.PD[Pos],Tabla3[[#This Row],[Part.]])+SUMIFS(BD.PD[Pago 5],BD.PD[Per.P5],I$1,BD.PD[Pos],Tabla3[[#This Row],[Part.]]) -> 0 | J34: =SUMIFS(BD.PD[Pago 1],BD.PD[Per.P1],J$1,BD.PD[Pos],Tabla3[[#This Row],[Part.]])+SUMIFS(BD.PD[Pago 2],BD.PD[Per.P2],J$1,BD.PD[Pos],Tabla3[[#This Row],[Part.]])+SUMIFS(BD.PD[Pago 3],BD.PD[Per.P3],J$1,BD.PD[Pos],Tabla3[[#This Row],[Part.]])+SUMIFS(BD.PD[Pago 4],BD.PD[Per.P4],J$1,BD.PD[Pos],Tabla3[[#This Row],[Part.]])+SUMIFS(BD.PD[Pago 5],BD.PD[Per.P5],J$1,BD.PD[Pos],Tabla3[[#This Row],[Part.]]) -> 0 | K34: =SUMIFS(BD.PD[Pago 1],BD.PD[Per.P1],K$1,BD.PD[Pos],Tabla3[[#This Row],[Part.]])+SUMIFS(BD.PD[Pago 2],BD.PD[Per.P2],K$1,BD.PD[Pos],Tabla3[[#This Row],[Part.]])+SUMIFS(BD.PD[Pago 3],BD.PD[Per.P3],K$1,BD.PD[Pos],Tabla3[[#This Row],[Part.]])+SUMIFS(BD.PD[Pago 4],BD.PD[Per.P4],K$1,BD.PD[Pos],Tabla3[[#This Row],[Part.]])+SUMIFS(BD.PD[Pago 5],BD.PD[Per.P5],K$1,BD.PD[Pos],Tabla3[[#This Row],[Part.]]) -> 0 | ... AA34: =SUMIFS(BD.PD[Pago 1],BD.PD[Per.P1],AA$1,BD.PD[Pos],Tabla3[[#This Row],[Part.]])+SUMIFS(BD.PD[Pago 2],BD.PD[Per.P2],AA$1,BD.PD[Pos],Tabla3[[#This Row],[Part.]])+SUMIFS(BD.PD[Pago 3],BD.PD[Per.P3],AA$1,BD.PD[Pos],Tabla3[[#This Row],[Part.]])+SUMIFS(BD.PD[Pago 4],BD.PD[Per.P4],AA$1,BD.PD[Pos],Tabla3[[#This Row],[Part.]])+SUMIFS(BD.PD[Pago 5],BD.PD[Per.P5],AA$1,BD.PD[Pos],Tabla3[[#This Row],[Part.]]) -> 0 | AB34: =SUM(Tabla3[[#This Row],[P1]:[P24]]) -> 5620061.3
A35: 4.02 | B35: =VLOOKUP(Tabla3[[#This Row],[Part.]],PPto[],3,FALSE) -> 4.02 Supervisión Mecánica | C35: =SUMIF(BD.PD[Pos],Tabla3[[#This Row],[Part.]],BD.PD[Ppto. Orden Interna '[DOP']]) -> 0 | D35: =SUMIFS(BD.PD[Pago 1],BD.PD[Per.P1],D$1,BD.PD[Pos],Tabla3[[#This Row],[Part.]])+SUMIFS(BD.PD[Pago 2],BD.PD[Per.P2],D$1,BD.PD[Pos],Tabla3[[#This Row],[Part.]])+SUMIFS(BD.PD[Pago 3],BD.PD[Per.P3],D$1,BD.PD[Pos],Tabla3[[#This Row],[Part.]])+SUMIFS(BD.PD[Pago 4],BD.PD[Per.P4],D$1,BD.PD[Pos],Tabla3[[#This Row],[Part.]])+SUMIFS(BD.PD[Pago 5],BD.PD[Per.P5],D$1,BD.PD[Pos],Tabla3[[#This Row],[Part.]]) -> 0 | E35: =SUMIFS(BD.PD[Pago 1],BD.PD[Per.P1],E$1,BD.PD[Pos],Tabla3[[#This Row],[Part.]])+SUMIFS(BD.PD[Pago 2],BD.PD[Per.P2],E$1,BD.PD[Pos],Tabla3[[#This Row],[Part.]])+SUMIFS(BD.PD[Pago 3],BD.PD[Per.P3],E$1,BD.PD[Pos],Tabla3[[#This Row],[Part.]])+SUMIFS(BD.PD[Pago 4],BD.PD[Per.P4],E$1,BD.PD[Pos],Tabla3[[#This Row],[Part.]])+SUMIFS(BD.PD[Pago 5],BD.PD[Per.P5],E$1,BD.PD[Pos],Tabla3[[#This Row],[Part.]]) -> 0 | F35: =SUMIFS(BD.PD[Pago 1],BD.PD[Per.P1],F$1,BD.PD[Pos],Tabla3[[#This Row],[Part.]])+SUMIFS(BD.PD[Pago 2],BD.PD[Per.P2],F$1,BD.PD[Pos],Tabla3[[#This Row],[Part.]])+SUMIFS(BD.PD[Pago 3],BD.PD[Per.P3],F$1,BD.PD[Pos],Tabla3[[#This Row],[Part.]])+SUMIFS(BD.PD[Pago 4],BD.PD[Per.P4],F$1,BD.PD[Pos],Tabla3[[#This Row],[Part.]])+SUMIFS(BD.PD[Pago 5],BD.PD[Per.P5],F$1,BD.PD[Pos],Tabla3[[#This Row],[Part.]]) -> 0 | G35: =SUMIFS(BD.PD[Pago 1],BD.PD[Per.P1],G$1,BD.PD[Pos],Tabla3[[#This Row],[Part.]])+SUMIFS(BD.PD[Pago 2],BD.PD[Per.P2],G$1,BD.PD[Pos],Tabla3[[#This Row],[Part.]])+SUMIFS(BD.PD[Pago 3],BD.PD[Per.P3],G$1,BD.PD[Pos],Tabla3[[#This Row],[Part.]])+SUMIFS(BD.PD[Pago 4],BD.PD[Per.P4],G$1,BD.PD[Pos],Tabla3[[#This Row],[Part.]])+SUMIFS(BD.PD[Pago 5],BD.PD[Per.P5],G$1,BD.PD[Pos],Tabla3[[#This Row],[Part.]]) -> 0 | H35: =SUMIFS(BD.PD[Pago 1],BD.PD[Per.P1],H$1,BD.PD[Pos],Tabla3[[#This Row],[Part.]])+SUMIFS(BD.PD[Pago 2],BD.PD[Per.P2],H$1,BD.PD[Pos],Tabla3[[#This Row],[Part.]])+SUMIFS(BD.PD[Pago 3],BD.PD[Per.P3],H$1,BD.PD[Pos],Tabla3[[#This Row],[Part.]])+SUMIFS(BD.PD[Pago 4],BD.PD[Per.P4],H$1,BD.PD[Pos],Tabla3[[#This Row],[Part.]])+SUMIFS(BD.PD[Pago 5],BD.PD[Per.P5],H$1,BD.PD[Pos],Tabla3[[#This Row],[Part.]]) -> 0 | I35: =SUMIFS(BD.PD[Pago 1],BD.PD[Per.P1],I$1,BD.PD[Pos],Tabla3[[#This Row],[Part.]])+SUMIFS(BD.PD[Pago 2],BD.PD[Per.P2],I$1,BD.PD[Pos],Tabla3[[#This Row],[Part.]])+SUMIFS(BD.PD[Pago 3],BD.PD[Per.P3],I$1,BD.PD[Pos],Tabla3[[#This Row],[Part.]])+SUMIFS(BD.PD[Pago 4],BD.PD[Per.P4],I$1,BD.PD[Pos],Tabla3[[#This Row],[Part.]])+SUMIFS(BD.PD[Pago 5],BD.PD[Per.P5],I$1,BD.PD[Pos],Tabla3[[#This Row],[Part.]]) -> 0 | J35: =SUMIFS(BD.PD[Pago 1],BD.PD[Per.P1],J$1,BD.PD[Pos],Tabla3[[#This Row],[Part.]])+SUMIFS(BD.PD[Pago 2],BD.PD[Per.P2],J$1,BD.PD[Pos],Tabla3[[#This Row],[Part.]])+SUMIFS(BD.PD[Pago 3],BD.PD[Per.P3],J$1,BD.PD[Pos],Tabla3[[#This Row],[Part.]])+SUMIFS(BD.PD[Pago 4],BD.PD[Per.P4],J$1,BD.PD[Pos],Tabla3[[#This Row],[Part.]])+SUMIFS(BD.PD[Pago 5],BD.PD[Per.P5],J$1,BD.PD[Pos],Tabla3[[#This Row],[Part.]]) -> 0 | K35: =SUMIFS(BD.PD[Pago 1],BD.PD[Per.P1],K$1,BD.PD[Pos],Tabla3[[#This Row],[Part.]])+SUMIFS(BD.PD[Pago 2],BD.PD[Per.P2],K$1,BD.PD[Pos],Tabla3[[#This Row],[Part.]])+SUMIFS(BD.PD[Pago 3],BD.PD[Per.P3],K$1,BD.PD[Pos],Tabla3[[#This Row],[Part.]])+SUMIFS(BD.PD[Pago 4],BD.PD[Per.P4],K$1,BD.PD[Pos],Tabla3[[#This Row],[Part.]])+SUMIFS(BD.PD[Pago 5],BD.PD[Per.P5],K$1,BD.PD[Pos],Tabla3[[#This Row],[Part.]]) -> 0 | ... AA35: =SUMIFS(BD.PD[Pago 1],BD.PD[Per.P1],AA$1,BD.PD[Pos],Tabla3[[#This Row],[Part.]])+SUMIFS(BD.PD[Pago 2],BD.PD[Per.P2],AA$1,BD.PD[Pos],Tabla3[[#This Row],[Part.]])+SUMIFS(BD.PD[Pago 3],BD.PD[Per.P3],AA$1,BD.PD[Pos],Tabla3[[#This Row],[Part.]])+SUMIFS(BD.PD[Pago 4],BD.PD[Per.P4],AA$1,BD.PD[Pos],Tabla3[[#This Row],[Part.]])+SUMIFS(BD.PD[Pago 5],BD.PD[Per.P5],AA$1,BD.PD[Pos],Tabla3[[#This Row],[Part.]]) -> 0 | AB35: =SUM(Tabla3[[#This Row],[P1]:[P24]]) -> 0
A36: 4.03 | B36: =VLOOKUP(Tabla3[[#This Row],[Part.]],PPto[],3,FALSE) -> 4.03 Sistema de Extracción cocina | C36: =SUMIF(BD.PD[Pos],Tabla3[[#This Row],[Part.]],BD.PD[Ppto. Orden Interna '[DOP']]) -> 1119367.9 | D36: =SUMIFS(BD.PD[Pago 1],BD.PD[Per.P1],D$1,BD.PD[Pos],Tabla3[[#This Row],[Part.]])+SUMIFS(BD.PD[Pago 2],BD.PD[Per.P2],D$1,BD.PD[Pos],Tabla3[[#This Row],[Part.]])+SUMIFS(BD.PD[Pago 3],BD.PD[Per.P3],D$1,BD.PD[Pos],Tabla3[[#This Row],[Part.]])+SUMIFS(BD.PD[Pago 4],BD.PD[Per.P4],D$1,BD.PD[Pos],Tabla3[[#This Row],[Part.]])+SUMIFS(BD.PD[Pago 5],BD.PD[Per.P5],D$1,BD.PD[Pos],Tabla3[[#This Row],[Part.]]) -> 0 | E36: =SUMIFS(BD.PD[Pago 1],BD.PD[Per.P1],E$1,BD.PD[Pos],Tabla3[[#This Row],[Part.]])+SUMIFS(BD.PD[Pago 2],BD.PD[Per.P2],E$1,BD.PD[Pos],Tabla3[[#This Row],[Part.]])+SUMIFS(BD.PD[Pago 3],BD.PD[Per.P3],E$1,BD.PD[Pos],Tabla3[[#This Row],[Part.]])+SUMIFS(BD.PD[Pago 4],BD.PD[Per.P4],E$1,BD.PD[Pos],Tabla3[[#This Row],[Part.]])+SUMIFS(BD.PD[Pago 5],BD.PD[Per.P5],E$1,BD.PD[Pos],Tabla3[[#This Row],[Part.]]) -> 0 | F36: =SUMIFS(BD.PD[Pago 1],BD.PD[Per.P1],F$1,BD.PD[Pos],Tabla3[[#This Row],[Part.]])+SUMIFS(BD.PD[Pago 2],BD.PD[Per.P2],F$1,BD.PD[Pos],Tabla3[[#This Row],[Part.]])+SUMIFS(BD.PD[Pago 3],BD.PD[Per.P3],F$1,BD.PD[Pos],Tabla3[[#This Row],[Part.]])+SUMIFS(BD.PD[Pago 4],BD.PD[Per.P4],F$1,BD.PD[Pos],Tabla3[[#This Row],[Part.]])+SUMIFS(BD.PD[Pago 5],BD.PD[Per.P5],F$1,BD.PD[Pos],Tabla3[[#This Row],[Part.]]) -> 0 | G36: =SUMIFS(BD.PD[Pago 1],BD.PD[Per.P1],G$1,BD.PD[Pos],Tabla3[[#This Row],[Part.]])+SUMIFS(BD.PD[Pago 2],BD.PD[Per.P2],G$1,BD.PD[Pos],Tabla3[[#This Row],[Part.]])+SUMIFS(BD.PD[Pago 3],BD.PD[Per.P3],G$1,BD.PD[Pos],Tabla3[[#This Row],[Part.]])+SUMIFS(BD.PD[Pago 4],BD.PD[Per.P4],G$1,BD.PD[Pos],Tabla3[[#This Row],[Part.]])+SUMIFS(BD.PD[Pago 5],BD.PD[Per.P5],G$1,BD.PD[Pos],Tabla3[[#This Row],[Part.]]) -> 0 | H36: =SUMIFS(BD.PD[Pago 1],BD.PD[Per.P1],H$1,BD.PD[Pos],Tabla3[[#This Row],[Part.]])+SUMIFS(BD.PD[Pago 2],BD.PD[Per.P2],H$1,BD.PD[Pos],Tabla3[[#This Row],[Part.]])+SUMIFS(BD.PD[Pago 3],BD.PD[Per.P3],H$1,BD.PD[Pos],Tabla3[[#This Row],[Part.]])+SUMIFS(BD.PD[Pago 4],BD.PD[Per.P4],H$1,BD.PD[Pos],Tabla3[[#This Row],[Part.]])+SUMIFS(BD.PD[Pago 5],BD.PD[Per.P5],H$1,BD.PD[Pos],Tabla3[[#This Row],[Part.]]) -> 0 | I36: =SUMIFS(BD.PD[Pago 1],BD.PD[Per.P1],I$1,BD.PD[Pos],Tabla3[[#This Row],[Part.]])+SUMIFS(BD.PD[Pago 2],BD.PD[Per.P2],I$1,BD.PD[Pos],Tabla3[[#This Row],[Part.]])+SUMIFS(BD.PD[Pago 3],BD.PD[Per.P3],I$1,BD.PD[Pos],Tabla3[[#This Row],[Part.]])+SUMIFS(BD.PD[Pago 4],BD.PD[Per.P4],I$1,BD.PD[Pos],Tabla3[[#This Row],[Part.]])+SUMIFS(BD.PD[Pago 5],BD.PD[Per.P5],I$1,BD.PD[Pos],Tabla3[[#This Row],[Part.]]) -> 0 | J36: =SUMIFS(BD.PD[Pago 1],BD.PD[Per.P1],J$1,BD.PD[Pos],Tabla3[[#This Row],[Part.]])+SUMIFS(BD.PD[Pago 2],BD.PD[Per.P2],J$1,BD.PD[Pos],Tabla3[[#This Row],[Part.]])+SUMIFS(BD.PD[Pago 3],BD.PD[Per.P3],J$1,BD.PD[Pos],Tabla3[[#This Row],[Part.]])+SUMIFS(BD.PD[Pago 4],BD.PD[Per.P4],J$1,BD.PD[Pos],Tabla3[[#This Row],[Part.]])+SUMIFS(BD.PD[Pago 5],BD.PD[Per.P5],J$1,BD.PD[Pos],Tabla3[[#This Row],[Part.]]) -> 0 | K36: =SUMIFS(BD.PD[Pago 1],BD.PD[Per.P1],K$1,BD.PD[Pos],Tabla3[[#This Row],[Part.]])+SUMIFS(BD.PD[Pago 2],BD.PD[Per.P2],K$1,BD.PD[Pos],Tabla3[[#This Row],[Part.]])+SUMIFS(BD.PD[Pago 3],BD.PD[Per.P3],K$1,BD.PD[Pos],Tabla3[[#This Row],[Part.]])+SUMIFS(BD.PD[Pago 4],BD.PD[Per.P4],K$1,BD.PD[Pos],Tabla3[[#This Row],[Part.]])+SUMIFS(BD.PD[Pago 5],BD.PD[Per.P5],K$1,BD.PD[Pos],Tabla3[[#This Row],[Part.]]) -> 0 | ... AA36: =SUMIFS(BD.PD[Pago 1],BD.PD[Per.P1],AA$1,BD.PD[Pos],Tabla3[[#This Row],[Part.]])+SUMIFS(BD.PD[Pago 2],BD.PD[Per.P2],AA$1,BD.PD[Pos],Tabla3[[#This Row],[Part.]])+SUMIFS(BD.PD[Pago 3],BD.PD[Per.P3],AA$1,BD.PD[Pos],Tabla3[[#This Row],[Part.]])+SUMIFS(BD.PD[Pago 4],BD.PD[Per.P4],AA$1,BD.PD[Pos],Tabla3[[#This Row],[Part.]])+SUMIFS(BD.PD[Pago 5],BD.PD[Per.P5],AA$1,BD.PD[Pos],Tabla3[[#This Row],[Part.]]) -> 447747.14 | AB36: =SUM(Tabla3[[#This Row],[P1]:[P24]]) -> 1119367.9
A37: 5 | B37: =VLOOKUP(Tabla3[[#This Row],[Part.]],PPto[],3,FALSE) -> 5.00 Frio Alimentario | C37: =SUM(C38:C44) -> 81656647 | D37: =SUM(D38:D44) -> 0 | E37: =SUM(E38:E44) -> 0 | F37: =SUM(F38:F44) -> 0 | G37: =SUM(G38:G44) -> 0 | H37: =SUM(H38:H44) -> 0 | I37: =SUM(I38:I44) -> 0 | J37: =SUM(J38:J44) -> 0 | ... Y37: =SUM(Y38:Y44) -> 21011011 | AA37: =SUM(AA38:AA44) -> 16380255 | AB37: =SUM(Tabla3[[#This Row],[P1]:[P24]]) -> 81656647
A38: 5.01 | B38: =VLOOKUP(Tabla3[[#This Row],[Part.]],PPto[],3,FALSE) -> 5.01 Paneles | C38: =SUMIF(BD.PD[Pos],Tabla3[[#This Row],[Part.]],BD.PD[Ppto. Orden Interna '[DOP']]) -> 11182113 | D38: =SUMIFS(BD.PD[Pago 1],BD.PD[Per.P1],D$1,BD.PD[Pos],Tabla3[[#This Row],[Part.]])+SUMIFS(BD.PD[Pago 2],BD.PD[Per.P2],D$1,BD.PD[Pos],Tabla3[[#This Row],[Part.]])+SUMIFS(BD.PD[Pago 3],BD.PD[Per.P3],D$1,BD.PD[Pos],Tabla3[[#This Row],[Part.]])+SUMIFS(BD.PD[Pago 4],BD.PD[Per.P4],D$1,BD.PD[Pos],Tabla3[[#This Row],[Part.]])+SUMIFS(BD.PD[Pago 5],BD.PD[Per.P5],D$1,BD.PD[Pos],Tabla3[[#This Row],[Part.]]) -> 0 | E38: =SUMIFS(BD.PD[Pago 1],BD.PD[Per.P1],E$1,BD.PD[Pos],Tabla3[[#This Row],[Part.]])+SUMIFS(BD.PD[Pago 2],BD.PD[Per.P2],E$1,BD.PD[Pos],Tabla3[[#This Row],[Part.]])+SUMIFS(BD.PD[Pago 3],BD.PD[Per.P3],E$1,BD.PD[Pos],Tabla3[[#This Row],[Part.]])+SUMIFS(BD.PD[Pago 4],BD.PD[Per.P4],E$1,BD.PD[Pos],Tabla3[[#This Row],[Part.]])+SUMIFS(BD.PD[Pago 5],BD.PD[Per.P5],E$1,BD.PD[Pos],Tabla3[[#This Row],[Part.]]) -> 0 | F38: =SUMIFS(BD.PD[Pago 1],BD.PD[Per.P1],F$1,BD.PD[Pos],Tabla3[[#This Row],[Part.]])+SUMIFS(BD.PD[Pago 2],BD.PD[Per.P2],F$1,BD.PD[Pos],Tabla3[[#This Row],[Part.]])+SUMIFS(BD.PD[Pago 3],BD.PD[Per.P3],F$1,BD.PD[Pos],Tabla3[[#This Row],[Part.]])+SUMIFS(BD.PD[Pago 4],BD.PD[Per.P4],F$1,BD.PD[Pos],Tabla3[[#This Row],[Part.]])+SUMIFS(BD.PD[Pago 5],BD.PD[Per.P5],F$1,BD.PD[Pos],Tabla3[[#This Row],[Part.]]) -> 0 | G38: =SUMIFS(BD.PD[Pago 1],BD.PD[Per.P1],G$1,BD.PD[Pos],Tabla3[[#This Row],[Part.]])+SUMIFS(BD.PD[Pago 2],BD.PD[Per.P2],G$1,BD.PD[Pos],Tabla3[[#This Row],[Part.]])+SUMIFS(BD.PD[Pago 3],BD.PD[Per.P3],G$1,BD.PD[Pos],Tabla3[[#This Row],[Part.]])+SUMIFS(BD.PD[Pago 4],BD.PD[Per.P4],G$1,BD.PD[Pos],Tabla3[[#This Row],[Part.]])+SUMIFS(BD.PD[Pago 5],BD.PD[Per.P5],G$1,BD.PD[Pos],Tabla3[[#This Row],[Part.]]) -> 0 | H38: =SUMIFS(BD.PD[Pago 1],BD.PD[Per.P1],H$1,BD.PD[Pos],Tabla3[[#This Row],[Part.]])+SUMIFS(BD.PD[Pago 2],BD.PD[Per.P2],H$1,BD.PD[Pos],Tabla3[[#This Row],[Part.]])+SUMIFS(BD.PD[Pago 3],BD.PD[Per.P3],H$1,BD.PD[Pos],Tabla3[[#This Row],[Part.]])+SUMIFS(BD.PD[Pago 4],BD.PD[Per.P4],H$1,BD.PD[Pos],Tabla3[[#This Row],[Part.]])+SUMIFS(BD.PD[Pago 5],BD.PD[Per.P5],H$1,BD.PD[Pos],Tabla3[[#This Row],[Part.]]) -> 0 | I38: =SUMIFS(BD.PD[Pago 1],BD.PD[Per.P1],I$1,BD.PD[Pos],Tabla3[[#This Row],[Part.]])+SUMIFS(BD.PD[Pago 2],BD.PD[Per.P2],I$1,BD.PD[Pos],Tabla3[[#This Row],[Part.]])+SUMIFS(BD.PD[Pago 3],BD.PD[Per.P3],I$1,BD.PD[Pos],Tabla3[[#This Row],[Part.]])+SUMIFS(BD.PD[Pago 4],BD.PD[Per.P4],I$1,BD.PD[Pos],Tabla3[[#This Row],[Part.]])+SUMIFS(BD.PD[Pago 5],BD.PD[Per.P5],I$1,BD.PD[Pos],Tabla3[[#This Row],[Part.]]) -> 0 | J38: =SUMIFS(BD.PD[Pago 1],BD.PD[Per.P1],J$1,BD.PD[Pos],Tabla3[[#This Row],[Part.]])+SUMIFS(BD.PD[Pago 2],BD.PD[Per.P2],J$1,BD.PD[Pos],Tabla3[[#This Row],[Part.]])+SUMIFS(BD.PD[Pago 3],BD.PD[Per.P3],J$1,BD.PD[Pos],Tabla3[[#This Row],[Part.]])+SUMIFS(BD.PD[Pago 4],BD.PD[Per.P4],J$1,BD.PD[Pos],Tabla3[[#This Row],[Part.]])+SUMIFS(BD.PD[Pago 5],BD.PD[Per.P5],J$1,BD.PD[Pos],Tabla3[[#This Row],[Part.]]) -> 0 | K38: =SUMIFS(BD.PD[Pago 1],BD.PD[Per.P1],K$1,BD.PD[Pos],Tabla3[[#This Row],[Part.]])+SUMIFS(BD.PD[Pago 2],BD.PD[Per.P2],K$1,BD.PD[Pos],Tabla3[[#This Row],[Part.]])+SUMIFS(BD.PD[Pago 3],BD.PD[Per.P3],K$1,BD.PD[Pos],Tabla3[[#This Row],[Part.]])+SUMIFS(BD.PD[Pago 4],BD.PD[Per.P4],K$1,BD.PD[Pos],Tabla3[[#This Row],[Part.]])+SUMIFS(BD.PD[Pago 5],BD.PD[Per.P5],K$1,BD.PD[Pos],Tabla3[[#This Row],[Part.]]) -> 0 | ... AA38: =SUMIFS(BD.PD[Pago 1],BD.PD[Per.P1],AA$1,BD.PD[Pos],Tabla3[[#This Row],[Part.]])+SUMIFS(BD.PD[Pago 2],BD.PD[Per.P2],AA$1,BD.PD[Pos],Tabla3[[#This Row],[Part.]])+SUMIFS(BD.PD[Pago 3],BD.PD[Per.P3],AA$1,BD.PD[Pos],Tabla3[[#This Row],[Part.]])+SUMIFS(BD.PD[Pago 4],BD.PD[Per.P4],AA$1,BD.PD[Pos],Tabla3[[#This Row],[Part.]])+SUMIFS(BD.PD[Pago 5],BD.PD[Per.P5],AA$1,BD.PD[Pos],Tabla3[[#This Row],[Part.]]) -> 5591056.4 | AB38: =SUM(Tabla3[[#This Row],[P1]:[P24]]) -> 11182113
A39: 5.02 | B39: =VLOOKUP(Tabla3[[#This Row],[Part.]],PPto[],3,FALSE) -> 5.02 FRP y Diamond Plate | C39: =SUMIF(BD.PD[Pos],Tabla3[[#This Row],[Part.]],BD.PD[Ppto. Orden Interna '[DOP']]) -> 7638149.3 | D39: =SUMIFS(BD.PD[Pago 1],BD.PD[Per.P1],D$1,BD.PD[Pos],Tabla3[[#This Row],[Part.]])+SUMIFS(BD.PD[Pago 2],BD.PD[Per.P2],D$1,BD.PD[Pos],Tabla3[[#This Row],[Part.]])+SUMIFS(BD.PD[Pago 3],BD.PD[Per.P3],D$1,BD.PD[Pos],Tabla3[[#This Row],[Part.]])+SUMIFS(BD.PD[Pago 4],BD.PD[Per.P4],D$1,BD.PD[Pos],Tabla3[[#This Row],[Part.]])+SUMIFS(BD.PD[Pago 5],BD.PD[Per.P5],D$1,BD.PD[Pos],Tabla3[[#This Row],[Part.]]) -> 0 | E39: =SUMIFS(BD.PD[Pago 1],BD.PD[Per.P1],E$1,BD.PD[Pos],Tabla3[[#This Row],[Part.]])+SUMIFS(BD.PD[Pago 2],BD.PD[Per.P2],E$1,BD.PD[Pos],Tabla3[[#This Row],[Part.]])+SUMIFS(BD.PD[Pago 3],BD.PD[Per.P3],E$1,BD.PD[Pos],Tabla3[[#This Row],[Part.]])+SUMIFS(BD.PD[Pago 4],BD.PD[Per.P4],E$1,BD.PD[Pos],Tabla3[[#This Row],[Part.]])+SUMIFS(BD.PD[Pago 5],BD.PD[Per.P5],E$1,BD.PD[Pos],Tabla3[[#This Row],[Part.]]) -> 0 | F39: =SUMIFS(BD.PD[Pago 1],BD.PD[Per.P1],F$1,BD.PD[Pos],Tabla3[[#This Row],[Part.]])+SUMIFS(BD.PD[Pago 2],BD.PD[Per.P2],F$1,BD.PD[Pos],Tabla3[[#This Row],[Part.]])+SUMIFS(BD.PD[Pago 3],BD.PD[Per.P3],F$1,BD.PD[Pos],Tabla3[[#This Row],[Part.]])+SUMIFS(BD.PD[Pago 4],BD.PD[Per.P4],F$1,BD.PD[Pos],Tabla3[[#This Row],[Part.]])+SUMIFS(BD.PD[Pago 5],BD.PD[Per.P5],F$1,BD.PD[Pos],Tabla3[[#This Row],[Part.]]) -> 0 | G39: =SUMIFS(BD.PD[Pago 1],BD.PD[Per.P1],G$1,BD.PD[Pos],Tabla3[[#This Row],[Part.]])+SUMIFS(BD.PD[Pago 2],BD.PD[Per.P2],G$1,BD.PD[Pos],Tabla3[[#This Row],[Part.]])+SUMIFS(BD.PD[Pago 3],BD.PD[Per.P3],G$1,BD.PD[Pos],Tabla3[[#This Row],[Part.]])+SUMIFS(BD.PD[Pago 4],BD.PD[Per.P4],G$1,BD.PD[Pos],Tabla3[[#This Row],[Part.]])+SUMIFS(BD.PD[Pago 5],BD.PD[Per.P5],G$1,BD.PD[Pos],Tabla3[[#This Row],[Part.]]) -> 0 | H39: =SUMIFS(BD.PD[Pago 1],BD.PD[Per.P1],H$1,BD.PD[Pos],Tabla3[[#This Row],[Part.]])+SUMIFS(BD.PD[Pago 2],BD.PD[Per.P2],H$1,BD.PD[Pos],Tabla3[[#This Row],[Part.]])+SUMIFS(BD.PD[Pago 3],BD.PD[Per.P3],H$1,BD.PD[Pos],Tabla3[[#This Row],[Part.]])+SUMIFS(BD.PD[Pago 4],BD.PD[Per.P4],H$1,BD.PD[Pos],Tabla3[[#This Row],[Part.]])+SUMIFS(BD.PD[Pago 5],BD.PD[Per.P5],H$1,BD.PD[Pos],Tabla3[[#This Row],[Part.]]) -> 0 | I39: =SUMIFS(BD.PD[Pago 1],BD.PD[Per.P1],I$1,BD.PD[Pos],Tabla3[[#This Row],[Part.]])+SUMIFS(BD.PD[Pago 2],BD.PD[Per.P2],I$1,BD.PD[Pos],Tabla3[[#This Row],[Part.]])+SUMIFS(BD.PD[Pago 3],BD.PD[Per.P3],I$1,BD.PD[Pos],Tabla3[[#This Row],[Part.]])+SUMIFS(BD.PD[Pago 4],BD.PD[Per.P4],I$1,BD.PD[Pos],Tabla3[[#This Row],[Part.]])+SUMIFS(BD.PD[Pago 5],BD.PD[Per.P5],I$1,BD.PD[Pos],Tabla3[[#This Row],[Part.]]) -> 0 | J39: =SUMIFS(BD.PD[Pago 1],BD.PD[Per.P1],J$1,BD.PD[Pos],Tabla3[[#This Row],[Part.]])+SUMIFS(BD.PD[Pago 2],BD.PD[Per.P2],J$1,BD.PD[Pos],Tabla3[[#This Row],[Part.]])+SUMIFS(BD.PD[Pago 3],BD.PD[Per.P3],J$1,BD.PD[Pos],Tabla3[[#This Row],[Part.]])+SUMIFS(BD.PD[Pago 4],BD.PD[Per.P4],J$1,BD.PD[Pos],Tabla3[[#This Row],[Part.]])+SUMIFS(BD.PD[Pago 5],BD.PD[Per.P5],J$1,BD.PD[Pos],Tabla3[[#This Row],[Part.]]) -> 0 | K39: =SUMIFS(BD.PD[Pago 1],BD.PD[Per.P1],K$1,BD.PD[Pos],Tabla3[[#This Row],[Part.]])+SUMIFS(BD.PD[Pago 2],BD.PD[Per.P2],K$1,BD.PD[Pos],Tabla3[[#This Row],[Part.]])+SUMIFS(BD.PD[Pago 3],BD.PD[Per.P3],K$1,BD.PD[Pos],Tabla3[[#This Row],[Part.]])+SUMIFS(BD.PD[Pago 4],BD.PD[Per.P4],K$1,BD.PD[Pos],Tabla3[[#This Row],[Part.]])+SUMIFS(BD.PD[Pago 5],BD.PD[Per.P5],K$1,BD.PD[Pos],Tabla3[[#This Row],[Part.]]) -> 0 | ... AA39: =SUMIFS(BD.PD[Pago 1],BD.PD[Per.P1],AA$1,BD.PD[Pos],Tabla3[[#This Row],[Part.]])+SUMIFS(BD.PD[Pago 2],BD.PD[Per.P2],AA$1,BD.PD[Pos],Tabla3[[#This Row],[Part.]])+SUMIFS(BD.PD[Pago 3],BD.PD[Per.P3],AA$1,BD.PD[Pos],Tabla3[[#This Row],[Part.]])+SUMIFS(BD.PD[Pago 4],BD.PD[Per.P4],AA$1,BD.PD[Pos],Tabla3[[#This Row],[Part.]])+SUMIFS(BD.PD[Pago 5],BD.PD[Per.P5],AA$1,BD.PD[Pos],Tabla3[[#This Row],[Part.]]) -> 0 | AB39: =SUM(Tabla3[[#This Row],[P1]:[P24]]) -> 7638149.3
A40: 5.03 | B40: =VLOOKUP(Tabla3[[#This Row],[Part.]],PPto[],3,FALSE) -> 5.03 Neveras, Centrales y Evaporadores | C40: =SUMIF(BD.PD[Pos],Tabla3[[#This Row],[Part.]],BD.PD[Ppto. Orden Interna '[DOP']]) -> 36192650 | D40: =SUMIFS(BD.PD[Pago 1],BD.PD[Per.P1],D$1,BD.PD[Pos],Tabla3[[#This Row],[Part.]])+SUMIFS(BD.PD[Pago 2],BD.PD[Per.P2],D$1,BD.PD[Pos],Tabla3[[#This Row],[Part.]])+SUMIFS(BD.PD[Pago 3],BD.PD[Per.P3],D$1,BD.PD[Pos],Tabla3[[#This Row],[Part.]])+SUMIFS(BD.PD[Pago 4],BD.PD[Per.P4],D$1,BD.PD[Pos],Tabla3[[#This Row],[Part.]])+SUMIFS(BD.PD[Pago 5],BD.PD[Per.P5],D$1,BD.PD[Pos],Tabla3[[#This Row],[Part.]]) -> 0 | E40: =SUMIFS(BD.PD[Pago 1],BD.PD[Per.P1],E$1,BD.PD[Pos],Tabla3[[#This Row],[Part.]])+SUMIFS(BD.PD[Pago 2],BD.PD[Per.P2],E$1,BD.PD[Pos],Tabla3[[#This Row],[Part.]])+SUMIFS(BD.PD[Pago 3],BD.PD[Per.P3],E$1,BD.PD[Pos],Tabla3[[#This Row],[Part.]])+SUMIFS(BD.PD[Pago 4],BD.PD[Per.P4],E$1,BD.PD[Pos],Tabla3[[#This Row],[Part.]])+SUMIFS(BD.PD[Pago 5],BD.PD[Per.P5],E$1,BD.PD[Pos],Tabla3[[#This Row],[Part.]]) -> 0 | F40: =SUMIFS(BD.PD[Pago 1],BD.PD[Per.P1],F$1,BD.PD[Pos],Tabla3[[#This Row],[Part.]])+SUMIFS(BD.PD[Pago 2],BD.PD[Per.P2],F$1,BD.PD[Pos],Tabla3[[#This Row],[Part.]])+SUMIFS(BD.PD[Pago 3],BD.PD[Per.P3],F$1,BD.PD[Pos],Tabla3[[#This Row],[Part.]])+SUMIFS(BD.PD[Pago 4],BD.PD[Per.P4],F$1,BD.PD[Pos],Tabla3[[#This Row],[Part.]])+SUMIFS(BD.PD[Pago 5],BD.PD[Per.P5],F$1,BD.PD[Pos],Tabla3[[#This Row],[Part.]]) -> 0 | G40: =SUMIFS(BD.PD[Pago 1],BD.PD[Per.P1],G$1,BD.PD[Pos],Tabla3[[#This Row],[Part.]])+SUMIFS(BD.PD[Pago 2],BD.PD[Per.P2],G$1,BD.PD[Pos],Tabla3[[#This Row],[Part.]])+SUMIFS(BD.PD[Pago 3],BD.PD[Per.P3],G$1,BD.PD[Pos],Tabla3[[#This Row],[Part.]])+SUMIFS(BD.PD[Pago 4],BD.PD[Per.P4],G$1,BD.PD[Pos],Tabla3[[#This Row],[Part.]])+SUMIFS(BD.PD[Pago 5],BD.PD[Per.P5],G$1,BD.PD[Pos],Tabla3[[#This Row],[Part.]]) -> 0 | H40: =SUMIFS(BD.PD[Pago 1],BD.PD[Per.P1],H$1,BD.PD[Pos],Tabla3[[#This Row],[Part.]])+SUMIFS(BD.PD[Pago 2],BD.PD[Per.P2],H$1,BD.PD[Pos],Tabla3[[#This Row],[Part.]])+SUMIFS(BD.PD[Pago 3],BD.PD[Per.P3],H$1,BD.PD[Pos],Tabla3[[#This Row],[Part.]])+SUMIFS(BD.PD[Pago 4],BD.PD[Per.P4],H$1,BD.PD[Pos],Tabla3[[#This Row],[Part.]])+SUMIFS(BD.PD[Pago 5],BD.PD[Per.P5],H$1,BD.PD[Pos],Tabla3[[#This Row],[Part.]]) -> 0 | I40: =SUMIFS(BD.PD[Pago 1],BD.PD[Per.P1],I$1,BD.PD[Pos],Tabla3[[#This Row],[Part.]])+SUMIFS(BD.PD[Pago 2],BD.PD[Per.P2],I$1,BD.PD[Pos],Tabla3[[#This Row],[Part.]])+SUMIFS(BD.PD[Pago 3],BD.PD[Per.P3],I$1,BD.PD[Pos],Tabla3[[#This Row],[Part.]])+SUMIFS(BD.PD[Pago 4],BD.PD[Per.P4],I$1,BD.PD[Pos],Tabla3[[#This Row],[Part.]])+SUMIFS(BD.PD[Pago 5],BD.PD[Per.P5],I$1,BD.PD[Pos],Tabla3[[#This Row],[Part.]]) -> 0 | J40: =SUMIFS(BD.PD[Pago 1],BD.PD[Per.P1],J$1,BD.PD[Pos],Tabla3[[#This Row],[Part.]])+SUMIFS(BD.PD[Pago 2],BD.PD[Per.P2],J$1,BD.PD[Pos],Tabla3[[#This Row],[Part.]])+SUMIFS(BD.PD[Pago 3],BD.PD[Per.P3],J$1,BD.PD[Pos],Tabla3[[#This Row],[Part.]])+SUMIFS(BD.PD[Pago 4],BD.PD[Per.P4],J$1,BD.PD[Pos],Tabla3[[#This Row],[Part.]])+SUMIFS(BD.PD[Pago 5],BD.PD[Per.P5],J$1,BD.PD[Pos],Tabla3[[#This Row],[Part.]]) -> 0 | K40: =SUMIFS(BD.PD[Pago 1],BD.PD[Per.P1],K$1,BD.PD[Pos],Tabla3[[#This Row],[Part.]])+SUMIFS(BD.PD[Pago 2],BD.PD[Per.P2],K$1,BD.PD[Pos],Tabla3[[#This Row],[Part.]])+SUMIFS(BD.PD[Pago 3],BD.PD[Per.P3],K$1,BD.PD[Pos],Tabla3[[#This Row],[Part.]])+SUMIFS(BD.PD[Pago 4],BD.PD[Per.P4],K$1,BD.PD[Pos],Tabla3[[#This Row],[Part.]])+SUMIFS(BD.PD[Pago 5],BD.PD[Per.P5],K$1,BD.PD[Pos],Tabla3[[#This Row],[Part.]]) -> 0 | ... AA40: =SUMIFS(BD.PD[Pago 1],BD.PD[Per.P1],AA$1,BD.PD[Pos],Tabla3[[#This Row],[Part.]])+SUMIFS(BD.PD[Pago 2],BD.PD[Per.P2],AA$1,BD.PD[Pos],Tabla3[[#This Row],[Part.]])+SUMIFS(BD.PD[Pago 3],BD.PD[Per.P3],AA$1,BD.PD[Pos],Tabla3[[#This Row],[Part.]])+SUMIFS(BD.PD[Pago 4],BD.PD[Per.P4],AA$1,BD.PD[Pos],Tabla3[[#This Row],[Part.]])+SUMIFS(BD.PD[Pago 5],BD.PD[Per.P5],AA$1,BD.PD[Pos],Tabla3[[#This Row],[Part.]]) -> 323015.05 | AB40: =SUM(Tabla3[[#This Row],[P1]:[P24]]) -> 36192650
A41: 5.04 | B41: =VLOOKUP(Tabla3[[#This Row],[Part.]],PPto[],3,FALSE) -> 5.04 Bumpers Mcue/ Rack | C41: =SUMIF(BD.PD[Pos],Tabla3[[#This Row],[Part.]],BD.PD[Ppto. Orden Interna '[DOP']]) -> 2027497.6 | D41: =SUMIFS(BD.PD[Pago 1],BD.PD[Per.P1],D$1,BD.PD[Pos],Tabla3[[#This Row],[Part.]])+SUMIFS(BD.PD[Pago 2],BD.PD[Per.P2],D$1,BD.PD[Pos],Tabla3[[#This Row],[Part.]])+SUMIFS(BD.PD[Pago 3],BD.PD[Per.P3],D$1,BD.PD[Pos],Tabla3[[#This Row],[Part.]])+SUMIFS(BD.PD[Pago 4],BD.PD[Per.P4],D$1,BD.PD[Pos],Tabla3[[#This Row],[Part.]])+SUMIFS(BD.PD[Pago 5],BD.PD[Per.P5],D$1,BD.PD[Pos],Tabla3[[#This Row],[Part.]]) -> 0 | E41: =SUMIFS(BD.PD[Pago 1],BD.PD[Per.P1],E$1,BD.PD[Pos],Tabla3[[#This Row],[Part.]])+SUMIFS(BD.PD[Pago 2],BD.PD[Per.P2],E$1,BD.PD[Pos],Tabla3[[#This Row],[Part.]])+SUMIFS(BD.PD[Pago 3],BD.PD[Per.P3],E$1,BD.PD[Pos],Tabla3[[#This Row],[Part.]])+SUMIFS(BD.PD[Pago 4],BD.PD[Per.P4],E$1,BD.PD[Pos],Tabla3[[#This Row],[Part.]])+SUMIFS(BD.PD[Pago 5],BD.PD[Per.P5],E$1,BD.PD[Pos],Tabla3[[#This Row],[Part.]]) -> 0 | F41: =SUMIFS(BD.PD[Pago 1],BD.PD[Per.P1],F$1,BD.PD[Pos],Tabla3[[#This Row],[Part.]])+SUMIFS(BD.PD[Pago 2],BD.PD[Per.P2],F$1,BD.PD[Pos],Tabla3[[#This Row],[Part.]])+SUMIFS(BD.PD[Pago 3],BD.PD[Per.P3],F$1,BD.PD[Pos],Tabla3[[#This Row],[Part.]])+SUMIFS(BD.PD[Pago 4],BD.PD[Per.P4],F$1,BD.PD[Pos],Tabla3[[#This Row],[Part.]])+SUMIFS(BD.PD[Pago 5],BD.PD[Per.P5],F$1,BD.PD[Pos],Tabla3[[#This Row],[Part.]]) -> 0 | G41: =SUMIFS(BD.PD[Pago 1],BD.PD[Per.P1],G$1,BD.PD[Pos],Tabla3[[#This Row],[Part.]])+SUMIFS(BD.PD[Pago 2],BD.PD[Per.P2],G$1,BD.PD[Pos],Tabla3[[#This Row],[Part.]])+SUMIFS(BD.PD[Pago 3],BD.PD[Per.P3],G$1,BD.PD[Pos],Tabla3[[#This Row],[Part.]])+SUMIFS(BD.PD[Pago 4],BD.PD[Per.P4],G$1,BD.PD[Pos],Tabla3[[#This Row],[Part.]])+SUMIFS(BD.PD[Pago 5],BD.PD[Per.P5],G$1,BD.PD[Pos],Tabla3[[#This Row],[Part.]]) -> 0 | H41: =SUMIFS(BD.PD[Pago 1],BD.PD[Per.P1],H$1,BD.PD[Pos],Tabla3[[#This Row],[Part.]])+SUMIFS(BD.PD[Pago 2],BD.PD[Per.P2],H$1,BD.PD[Pos],Tabla3[[#This Row],[Part.]])+SUMIFS(BD.PD[Pago 3],BD.PD[Per.P3],H$1,BD.PD[Pos],Tabla3[[#This Row],[Part.]])+SUMIFS(BD.PD[Pago 4],BD.PD[Per.P4],H$1,BD.PD[Pos],Tabla3[[#This Row],[Part.]])+SUMIFS(BD.PD[Pago 5],BD.PD[Per.P5],H$1,BD.PD[Pos],Tabla3[[#This Row],[Part.]]) -> 0 | I41: =SUMIFS(BD.PD[Pago 1],BD.PD[Per.P1],I$1,BD.PD[Pos],Tabla3[[#This Row],[Part.]])+SUMIFS(BD.PD[Pago 2],BD.PD[Per.P2],I$1,BD.PD[Pos],Tabla3[[#This Row],[Part.]])+SUMIFS(BD.PD[Pago 3],BD.PD[Per.P3],I$1,BD.PD[Pos],Tabla3[[#This Row],[Part.]])+SUMIFS(BD.PD[Pago 4],BD.PD[Per.P4],I$1,BD.PD[Pos],Tabla3[[#This Row],[Part.]])+SUMIFS(BD.PD[Pago 5],BD.PD[Per.P5],I$1,BD.PD[Pos],Tabla3[[#This Row],[Part.]]) -> 0 | J41: =SUMIFS(BD.PD[Pago 1],BD.PD[Per.P1],J$1,BD.PD[Pos],Tabla3[[#This Row],[Part.]])+SUMIFS(BD.PD[Pago 2],BD.PD[Per.P2],J$1,BD.PD[Pos],Tabla3[[#This Row],[Part.]])+SUMIFS(BD.PD[Pago 3],BD.PD[Per.P3],J$1,BD.PD[Pos],Tabla3[[#This Row],[Part.]])+SUMIFS(BD.PD[Pago 4],BD.PD[Per.P4],J$1,BD.PD[Pos],Tabla3[[#This Row],[Part.]])+SUMIFS(BD.PD[Pago 5],BD.PD[Per.P5],J$1,BD.PD[Pos],Tabla3[[#This Row],[Part.]]) -> 0 | K41: =SUMIFS(BD.PD[Pago 1],BD.PD[Per.P1],K$1,BD.PD[Pos],Tabla3[[#This Row],[Part.]])+SUMIFS(BD.PD[Pago 2],BD.PD[Per.P2],K$1,BD.PD[Pos],Tabla3[[#This Row],[Part.]])+SUMIFS(BD.PD[Pago 3],BD.PD[Per.P3],K$1,BD.PD[Pos],Tabla3[[#This Row],[Part.]])+SUMIFS(BD.PD[Pago 4],BD.PD[Per.P4],K$1,BD.PD[Pos],Tabla3[[#This Row],[Part.]])+SUMIFS(BD.PD[Pago 5],BD.PD[Per.P5],K$1,BD.PD[Pos],Tabla3[[#This Row],[Part.]]) -> 0 | ... AA41: =SUMIFS(BD.PD[Pago 1],BD.PD[Per.P1],AA$1,BD.PD[Pos],Tabla3[[#This Row],[Part.]])+SUMIFS(BD.PD[Pago 2],BD.PD[Per.P2],AA$1,BD.PD[Pos],Tabla3[[#This Row],[Part.]])+SUMIFS(BD.PD[Pago 3],BD.PD[Per.P3],AA$1,BD.PD[Pos],Tabla3[[#This Row],[Part.]])+SUMIFS(BD.PD[Pago 4],BD.PD[Per.P4],AA$1,BD.PD[Pos],Tabla3[[#This Row],[Part.]])+SUMIFS(BD.PD[Pago 5],BD.PD[Per.P5],AA$1,BD.PD[Pos],Tabla3[[#This Row],[Part.]]) -> 1013748.8 | AB41: =SUM(Tabla3[[#This Row],[P1]:[P24]]) -> 2027497.6
A42: 5.05 | B42: =VLOOKUP(Tabla3[[#This Row],[Part.]],PPto[],3,FALSE) -> 5.05 Trameria Cuarto Frio | C42: =SUMIF(BD.PD[Pos],Tabla3[[#This Row],[Part.]],BD.PD[Ppto. Orden Interna '[DOP']]) -> 2272000 | D42: =SUMIFS(BD.PD[Pago 1],BD.PD[Per.P1],D$1,BD.PD[Pos],Tabla3[[#This Row],[Part.]])+SUMIFS(BD.PD[Pago 2],BD.PD[Per.P2],D$1,BD.PD[Pos],Tabla3[[#This Row],[Part.]])+SUMIFS(BD.PD[Pago 3],BD.PD[Per.P3],D$1,BD.PD[Pos],Tabla3[[#This Row],[Part.]])+SUMIFS(BD.PD[Pago 4],BD.PD[Per.P4],D$1,BD.PD[Pos],Tabla3[[#This Row],[Part.]])+SUMIFS(BD.PD[Pago 5],BD.PD[Per.P5],D$1,BD.PD[Pos],Tabla3[[#This Row],[Part.]]) -> 0 | E42: =SUMIFS(BD.PD[Pago 1],BD.PD[Per.P1],E$1,BD.PD[Pos],Tabla3[[#This Row],[Part.]])+SUMIFS(BD.PD[Pago 2],BD.PD[Per.P2],E$1,BD.PD[Pos],Tabla3[[#This Row],[Part.]])+SUMIFS(BD.PD[Pago 3],BD.PD[Per.P3],E$1,BD.PD[Pos],Tabla3[[#This Row],[Part.]])+SUMIFS(BD.PD[Pago 4],BD.PD[Per.P4],E$1,BD.PD[Pos],Tabla3[[#This Row],[Part.]])+SUMIFS(BD.PD[Pago 5],BD.PD[Per.P5],E$1,BD.PD[Pos],Tabla3[[#This Row],[Part.]]) -> 0 | F42: =SUMIFS(BD.PD[Pago 1],BD.PD[Per.P1],F$1,BD.PD[Pos],Tabla3[[#This Row],[Part.]])+SUMIFS(BD.PD[Pago 2],BD.PD[Per.P2],F$1,BD.PD[Pos],Tabla3[[#This Row],[Part.]])+SUMIFS(BD.PD[Pago 3],BD.PD[Per.P3],F$1,BD.PD[Pos],Tabla3[[#This Row],[Part.]])+SUMIFS(BD.PD[Pago 4],BD.PD[Per.P4],F$1,BD.PD[Pos],Tabla3[[#This Row],[Part.]])+SUMIFS(BD.PD[Pago 5],BD.PD[Per.P5],F$1,BD.PD[Pos],Tabla3[[#This Row],[Part.]]) -> 0 | G42: =SUMIFS(BD.PD[Pago 1],BD.PD[Per.P1],G$1,BD.PD[Pos],Tabla3[[#This Row],[Part.]])+SUMIFS(BD.PD[Pago 2],BD.PD[Per.P2],G$1,BD.PD[Pos],Tabla3[[#This Row],[Part.]])+SUMIFS(BD.PD[Pago 3],BD.PD[Per.P3],G$1,BD.PD[Pos],Tabla3[[#This Row],[Part.]])+SUMIFS(BD.PD[Pago 4],BD.PD[Per.P4],G$1,BD.PD[Pos],Tabla3[[#This Row],[Part.]])+SUMIFS(BD.PD[Pago 5],BD.PD[Per.P5],G$1,BD.PD[Pos],Tabla3[[#This Row],[Part.]]) -> 0 | H42: =SUMIFS(BD.PD[Pago 1],BD.PD[Per.P1],H$1,BD.PD[Pos],Tabla3[[#This Row],[Part.]])+SUMIFS(BD.PD[Pago 2],BD.PD[Per.P2],H$1,BD.PD[Pos],Tabla3[[#This Row],[Part.]])+SUMIFS(BD.PD[Pago 3],BD.PD[Per.P3],H$1,BD.PD[Pos],Tabla3[[#This Row],[Part.]])+SUMIFS(BD.PD[Pago 4],BD.PD[Per.P4],H$1,BD.PD[Pos],Tabla3[[#This Row],[Part.]])+SUMIFS(BD.PD[Pago 5],BD.PD[Per.P5],H$1,BD.PD[Pos],Tabla3[[#This Row],[Part.]]) -> 0 | I42: =SUMIFS(BD.PD[Pago 1],BD.PD[Per.P1],I$1,BD.PD[Pos],Tabla3[[#This Row],[Part.]])+SUMIFS(BD.PD[Pago 2],BD.PD[Per.P2],I$1,BD.PD[Pos],Tabla3[[#This Row],[Part.]])+SUMIFS(BD.PD[Pago 3],BD.PD[Per.P3],I$1,BD.PD[Pos],Tabla3[[#This Row],[Part.]])+SUMIFS(BD.PD[Pago 4],BD.PD[Per.P4],I$1,BD.PD[Pos],Tabla3[[#This Row],[Part.]])+SUMIFS(BD.PD[Pago 5],BD.PD[Per.P5],I$1,BD.PD[Pos],Tabla3[[#This Row],[Part.]]) -> 0 | J42: =SUMIFS(BD.PD[Pago 1],BD.PD[Per.P1],J$1,BD.PD[Pos],Tabla3[[#This Row],[Part.]])+SUMIFS(BD.PD[Pago 2],BD.PD[Per.P2],J$1,BD.PD[Pos],Tabla3[[#This Row],[Part.]])+SUMIFS(BD.PD[Pago 3],BD.PD[Per.P3],J$1,BD.PD[Pos],Tabla3[[#This Row],[Part.]])+SUMIFS(BD.PD[Pago 4],BD.PD[Per.P4],J$1,BD.PD[Pos],Tabla3[[#This Row],[Part.]])+SUMIFS(BD.PD[Pago 5],BD.PD[Per.P5],J$1,BD.PD[Pos],Tabla3[[#This Row],[Part.]]) -> 0 | K42: =SUMIFS(BD.PD[Pago 1],BD.PD[Per.P1],K$1,BD.PD[Pos],Tabla3[[#This Row],[Part.]])+SUMIFS(BD.PD[Pago 2],BD.PD[Per.P2],K$1,BD.PD[Pos],Tabla3[[#This Row],[Part.]])+SUMIFS(BD.PD[Pago 3],BD.PD[Per.P3],K$1,BD.PD[Pos],Tabla3[[#This Row],[Part.]])+SUMIFS(BD.PD[Pago 4],BD.PD[Per.P4],K$1,BD.PD[Pos],Tabla3[[#This Row],[Part.]])+SUMIFS(BD.PD[Pago 5],BD.PD[Per.P5],K$1,BD.PD[Pos],Tabla3[[#This Row],[Part.]]) -> 0 | ... AA42: =SUMIFS(BD.PD[Pago 1],BD.PD[Per.P1],AA$1,BD.PD[Pos],Tabla3[[#This Row],[Part.]])+SUMIFS(BD.PD[Pago 2],BD.PD[Per.P2],AA$1,BD.PD[Pos],Tabla3[[#This Row],[Part.]])+SUMIFS(BD.PD[Pago 3],BD.PD[Per.P3],AA$1,BD.PD[Pos],Tabla3[[#This Row],[Part.]])+SUMIFS(BD.PD[Pago 4],BD.PD[Per.P4],AA$1,BD.PD[Pos],Tabla3[[#This Row],[Part.]])+SUMIFS(BD.PD[Pago 5],BD.PD[Per.P5],AA$1,BD.PD[Pos],Tabla3[[#This Row],[Part.]]) -> 0 | AB42: =SUM(Tabla3[[#This Row],[P1]:[P24]]) -> 2272000
A43: 5.06 | B43: =VLOOKUP(Tabla3[[#This Row],[Part.]],PPto[],3,FALSE) -> 5.06 Instalacion Frio Alimentario | C43: =SUMIF(BD.PD[Pos],Tabla3[[#This Row],[Part.]],BD.PD[Ppto. Orden Interna '[DOP']]) -> 17196833 | D43: =SUMIFS(BD.PD[Pago 1],BD.PD[Per.P1],D$1,BD.PD[Pos],Tabla3[[#This Row],[Part.]])+SUMIFS(BD.PD[Pago 2],BD.PD[Per.P2],D$1,BD.PD[Pos],Tabla3[[#This Row],[Part.]])+SUMIFS(BD.PD[Pago 3],BD.PD[Per.P3],D$1,BD.PD[Pos],Tabla3[[#This Row],[Part.]])+SUMIFS(BD.PD[Pago 4],BD.PD[Per.P4],D$1,BD.PD[Pos],Tabla3[[#This Row],[Part.]])+SUMIFS(BD.PD[Pago 5],BD.PD[Per.P5],D$1,BD.PD[Pos],Tabla3[[#This Row],[Part.]]) -> 0 | E43: =SUMIFS(BD.PD[Pago 1],BD.PD[Per.P1],E$1,BD.PD[Pos],Tabla3[[#This Row],[Part.]])+SUMIFS(BD.PD[Pago 2],BD.PD[Per.P2],E$1,BD.PD[Pos],Tabla3[[#This Row],[Part.]])+SUMIFS(BD.PD[Pago 3],BD.PD[Per.P3],E$1,BD.PD[Pos],Tabla3[[#This Row],[Part.]])+SUMIFS(BD.PD[Pago 4],BD.PD[Per.P4],E$1,BD.PD[Pos],Tabla3[[#This Row],[Part.]])+SUMIFS(BD.PD[Pago 5],BD.PD[Per.P5],E$1,BD.PD[Pos],Tabla3[[#This Row],[Part.]]) -> 0 | F43: =SUMIFS(BD.PD[Pago 1],BD.PD[Per.P1],F$1,BD.PD[Pos],Tabla3[[#This Row],[Part.]])+SUMIFS(BD.PD[Pago 2],BD.PD[Per.P2],F$1,BD.PD[Pos],Tabla3[[#This Row],[Part.]])+SUMIFS(BD.PD[Pago 3],BD.PD[Per.P3],F$1,BD.PD[Pos],Tabla3[[#This Row],[Part.]])+SUMIFS(BD.PD[Pago 4],BD.PD[Per.P4],F$1,BD.PD[Pos],Tabla3[[#This Row],[Part.]])+SUMIFS(BD.PD[Pago 5],BD.PD[Per.P5],F$1,BD.PD[Pos],Tabla3[[#This Row],[Part.]]) -> 0 | G43: =SUMIFS(BD.PD[Pago 1],BD.PD[Per.P1],G$1,BD.PD[Pos],Tabla3[[#This Row],[Part.]])+SUMIFS(BD.PD[Pago 2],BD.PD[Per.P2],G$1,BD.PD[Pos],Tabla3[[#This Row],[Part.]])+SUMIFS(BD.PD[Pago 3],BD.PD[Per.P3],G$1,BD.PD[Pos],Tabla3[[#This Row],[Part.]])+SUMIFS(BD.PD[Pago 4],BD.PD[Per.P4],G$1,BD.PD[Pos],Tabla3[[#This Row],[Part.]])+SUMIFS(BD.PD[Pago 5],BD.PD[Per.P5],G$1,BD.PD[Pos],Tabla3[[#This Row],[Part.]]) -> 0 | H43: =SUMIFS(BD.PD[Pago 1],BD.PD[Per.P1],H$1,BD.PD[Pos],Tabla3[[#This Row],[Part.]])+SUMIFS(BD.PD[Pago 2],BD.PD[Per.P2],H$1,BD.PD[Pos],Tabla3[[#This Row],[Part.]])+SUMIFS(BD.PD[Pago 3],BD.PD[Per.P3],H$1,BD.PD[Pos],Tabla3[[#This Row],[Part.]])+SUMIFS(BD.PD[Pago 4],BD.PD[Per.P4],H$1,BD.PD[Pos],Tabla3[[#This Row],[Part.]])+SUMIFS(BD.PD[Pago 5],BD.PD[Per.P5],H$1,BD.PD[Pos],Tabla3[[#This Row],[Part.]]) -> 0 | I43: =SUMIFS(BD.PD[Pago 1],BD.PD[Per.P1],I$1,BD.PD[Pos],Tabla3[[#This Row],[Part.]])+SUMIFS(BD.PD[Pago 2],BD.PD[Per.P2],I$1,BD.PD[Pos],Tabla3[[#This Row],[Part.]])+SUMIFS(BD.PD[Pago 3],BD.PD[Per.P3],I$1,BD.PD[Pos],Tabla3[[#This Row],[Part.]])+SUMIFS(BD.PD[Pago 4],BD.PD[Per.P4],I$1,BD.PD[Pos],Tabla3[[#This Row],[Part.]])+SUMIFS(BD.PD[Pago 5],BD.PD[Per.P5],I$1,BD.PD[Pos],Tabla3[[#This Row],[Part.]]) -> 0 | J43: =SUMIFS(BD.PD[Pago 1],BD.PD[Per.P1],J$1,BD.PD[Pos],Tabla3[[#This Row],[Part.]])+SUMIFS(BD.PD[Pago 2],BD.PD[Per.P2],J$1,BD.PD[Pos],Tabla3[[#This Row],[Part.]])+SUMIFS(BD.PD[Pago 3],BD.PD[Per.P3],J$1,BD.PD[Pos],Tabla3[[#This Row],[Part.]])+SUMIFS(BD.PD[Pago 4],BD.PD[Per.P4],J$1,BD.PD[Pos],Tabla3[[#This Row],[Part.]])+SUMIFS(BD.PD[Pago 5],BD.PD[Per.P5],J$1,BD.PD[Pos],Tabla3[[#This Row],[Part.]]) -> 0 | K43: =SUMIFS(BD.PD[Pago 1],BD.PD[Per.P1],K$1,BD.PD[Pos],Tabla3[[#This Row],[Part.]])+SUMIFS(BD.PD[Pago 2],BD.PD[Per.P2],K$1,BD.PD[Pos],Tabla3[[#This Row],[Part.]])+SUMIFS(BD.PD[Pago 3],BD.PD[Per.P3],K$1,BD.PD[Pos],Tabla3[[#This Row],[Part.]])+SUMIFS(BD.PD[Pago 4],BD.PD[Per.P4],K$1,BD.PD[Pos],Tabla3[[#This Row],[Part.]])+SUMIFS(BD.PD[Pago 5],BD.PD[Per.P5],K$1,BD.PD[Pos],Tabla3[[#This Row],[Part.]]) -> 0 | ... AA43: =SUMIFS(BD.PD[Pago 1],BD.PD[Per.P1],AA$1,BD.PD[Pos],Tabla3[[#This Row],[Part.]])+SUMIFS(BD.PD[Pago 2],BD.PD[Per.P2],AA$1,BD.PD[Pos],Tabla3[[#This Row],[Part.]])+SUMIFS(BD.PD[Pago 3],BD.PD[Per.P3],AA$1,BD.PD[Pos],Tabla3[[#This Row],[Part.]])+SUMIFS(BD.PD[Pago 4],BD.PD[Per.P4],AA$1,BD.PD[Pos],Tabla3[[#This Row],[Part.]])+SUMIFS(BD.PD[Pago 5],BD.PD[Per.P5],AA$1,BD.PD[Pos],Tabla3[[#This Row],[Part.]]) -> 6878733.3 | AB43: =SUM(Tabla3[[#This Row],[P1]:[P24]]) -> 17196833
A44: 5.07 | B44: =VLOOKUP(Tabla3[[#This Row],[Part.]],PPto[],3,FALSE) -> 5.07 Chase Doors | C44: =SUMIF(BD.PD[Pos],Tabla3[[#This Row],[Part.]],BD.PD[Ppto. Orden Interna '[DOP']]) -> 5147403.7 | D44: =SUMIFS(BD.PD[Pago 1],BD.PD[Per.P1],D$1,BD.PD[Pos],Tabla3[[#This Row],[Part.]])+SUMIFS(BD.PD[Pago 2],BD.PD[Per.P2],D$1,BD.PD[Pos],Tabla3[[#This Row],[Part.]])+SUMIFS(BD.PD[Pago 3],BD.PD[Per.P3],D$1,BD.PD[Pos],Tabla3[[#This Row],[Part.]])+SUMIFS(BD.PD[Pago 4],BD.PD[Per.P4],D$1,BD.PD[Pos],Tabla3[[#This Row],[Part.]])+SUMIFS(BD.PD[Pago 5],BD.PD[Per.P5],D$1,BD.PD[Pos],Tabla3[[#This Row],[Part.]]) -> 0 | E44: =SUMIFS(BD.PD[Pago 1],BD.PD[Per.P1],E$1,BD.PD[Pos],Tabla3[[#This Row],[Part.]])+SUMIFS(BD.PD[Pago 2],BD.PD[Per.P2],E$1,BD.PD[Pos],Tabla3[[#This Row],[Part.]])+SUMIFS(BD.PD[Pago 3],BD.PD[Per.P3],E$1,BD.PD[Pos],Tabla3[[#This Row],[Part.]])+SUMIFS(BD.PD[Pago 4],BD.PD[Per.P4],E$1,BD.PD[Pos],Tabla3[[#This Row],[Part.]])+SUMIFS(BD.PD[Pago 5],BD.PD[Per.P5],E$1,BD.PD[Pos],Tabla3[[#This Row],[Part.]]) -> 0 | F44: =SUMIFS(BD.PD[Pago 1],BD.PD[Per.P1],F$1,BD.PD[Pos],Tabla3[[#This Row],[Part.]])+SUMIFS(BD.PD[Pago 2],BD.PD[Per.P2],F$1,BD.PD[Pos],Tabla3[[#This Row],[Part.]])+SUMIFS(BD.PD[Pago 3],BD.PD[Per.P3],F$1,BD.PD[Pos],Tabla3[[#This Row],[Part.]])+SUMIFS(BD.PD[Pago 4],BD.PD[Per.P4],F$1,BD.PD[Pos],Tabla3[[#This Row],[Part.]])+SUMIFS(BD.PD[Pago 5],BD.PD[Per.P5],F$1,BD.PD[Pos],Tabla3[[#This Row],[Part.]]) -> 0 | G44: =SUMIFS(BD.PD[Pago 1],BD.PD[Per.P1],G$1,BD.PD[Pos],Tabla3[[#This Row],[Part.]])+SUMIFS(BD.PD[Pago 2],BD.PD[Per.P2],G$1,BD.PD[Pos],Tabla3[[#This Row],[Part.]])+SUMIFS(BD.PD[Pago 3],BD.PD[Per.P3],G$1,BD.PD[Pos],Tabla3[[#This Row],[Part.]])+SUMIFS(BD.PD[Pago 4],BD.PD[Per.P4],G$1,BD.PD[Pos],Tabla3[[#This Row],[Part.]])+SUMIFS(BD.PD[Pago 5],BD.PD[Per.P5],G$1,BD.PD[Pos],Tabla3[[#This Row],[Part.]]) -> 0 | H44: =SUMIFS(BD.PD[Pago 1],BD.PD[Per.P1],H$1,BD.PD[Pos],Tabla3[[#This Row],[Part.]])+SUMIFS(BD.PD[Pago 2],BD.PD[Per.P2],H$1,BD.PD[Pos],Tabla3[[#This Row],[Part.]])+SUMIFS(BD.PD[Pago 3],BD.PD[Per.P3],H$1,BD.PD[Pos],Tabla3[[#This Row],[Part.]])+SUMIFS(BD.PD[Pago 4],BD.PD[Per.P4],H$1,BD.PD[Pos],Tabla3[[#This Row],[Part.]])+SUMIFS(BD.PD[Pago 5],BD.PD[Per.P5],H$1,BD.PD[Pos],Tabla3[[#This Row],[Part.]]) -> 0 | I44: =SUMIFS(BD.PD[Pago 1],BD.PD[Per.P1],I$1,BD.PD[Pos],Tabla3[[#This Row],[Part.]])+SUMIFS(BD.PD[Pago 2],BD.PD[Per.P2],I$1,BD.PD[Pos],Tabla3[[#This Row],[Part.]])+SUMIFS(BD.PD[Pago 3],BD.PD[Per.P3],I$1,BD.PD[Pos],Tabla3[[#This Row],[Part.]])+SUMIFS(BD.PD[Pago 4],BD.PD[Per.P4],I$1,BD.PD[Pos],Tabla3[[#This Row],[Part.]])+SUMIFS(BD.PD[Pago 5],BD.PD[Per.P5],I$1,BD.PD[Pos],Tabla3[[#This Row],[Part.]]) -> 0 | J44: =SUMIFS(BD.PD[Pago 1],BD.PD[Per.P1],J$1,BD.PD[Pos],Tabla3[[#This Row],[Part.]])+SUMIFS(BD.PD[Pago 2],BD.PD[Per.P2],J$1,BD.PD[Pos],Tabla3[[#This Row],[Part.]])+SUMIFS(BD.PD[Pago 3],BD.PD[Per.P3],J$1,BD.PD[Pos],Tabla3[[#This Row],[Part.]])+SUMIFS(BD.PD[Pago 4],BD.PD[Per.P4],J$1,BD.PD[Pos],Tabla3[[#This Row],[Part.]])+SUMIFS(BD.PD[Pago 5],BD.PD[Per.P5],J$1,BD.PD[Pos],Tabla3[[#This Row],[Part.]]) -> 0 | K44: =SUMIFS(BD.PD[Pago 1],BD.PD[Per.P1],K$1,BD.PD[Pos],Tabla3[[#This Row],[Part.]])+SUMIFS(BD.PD[Pago 2],BD.PD[Per.P2],K$1,BD.PD[Pos],Tabla3[[#This Row],[Part.]])+SUMIFS(BD.PD[Pago 3],BD.PD[Per.P3],K$1,BD.PD[Pos],Tabla3[[#This Row],[Part.]])+SUMIFS(BD.PD[Pago 4],BD.PD[Per.P4],K$1,BD.PD[Pos],Tabla3[[#This Row],[Part.]])+SUMIFS(BD.PD[Pago 5],BD.PD[Per.P5],K$1,BD.PD[Pos],Tabla3[[#This Row],[Part.]]) -> 0 | ... AA44: =SUMIFS(BD.PD[Pago 1],BD.PD[Per.P1],AA$1,BD.PD[Pos],Tabla3[[#This Row],[Part.]])+SUMIFS(BD.PD[Pago 2],BD.PD[Per.P2],AA$1,BD.PD[Pos],Tabla3[[#This Row],[Part.]])+SUMIFS(BD.PD[Pago 3],BD.PD[Per.P3],AA$1,BD.PD[Pos],Tabla3[[#This Row],[Part.]])+SUMIFS(BD.PD[Pago 4],BD.PD[Per.P4],AA$1,BD.PD[Pos],Tabla3[[#This Row],[Part.]])+SUMIFS(BD.PD[Pago 5],BD.PD[Per.P5],AA$1,BD.PD[Pos],Tabla3[[#This Row],[Part.]]) -> 2573701.9 | AB44: =SUM(Tabla3[[#This Row],[P1]:[P24]]) -> 5147403.7
A45: 6 | B45: =VLOOKUP(Tabla3[[#This Row],[Part.]],PPto[],3,FALSE) -> 6.00 Tecnología, Seguridad y Tesorería | C45: =SUM(C46:C50) -> 2162880 | D45: =SUM(D46:D50) -> 0 | E45: =SUM(E46:E50) -> 0 | F45: =SUM(F46:F50) -> 0 | G45: =SUM(G46:G50) -> 0 | H45: =SUM(H46:H50) -> 0 | I45: =SUM(I46:I50) -> 0 | J45: =SUM(J46:J50) -> 0 | ... Y45: =SUM(Y46:Y50) -> 745965.47 | AA45: =SUM(AA46:AA50) -> 130098.47 | AB45: =SUM(Tabla3[[#This Row],[P1]:[P24]]) -> 2162880
A46: 6.01 | B46: =VLOOKUP(Tabla3[[#This Row],[Part.]],PPto[],3,FALSE) -> 6.01 Sistema de cámaras CCTV | C46: =SUMIF(BD.PD[Pos],Tabla3[[#This Row],[Part.]],BD.PD[Ppto. Orden Interna '[DOP']]) -> 0 | D46: =SUMIFS(BD.PD[Pago 1],BD.PD[Per.P1],D$1,BD.PD[Pos],Tabla3[[#This Row],[Part.]])+SUMIFS(BD.PD[Pago 2],BD.PD[Per.P2],D$1,BD.PD[Pos],Tabla3[[#This Row],[Part.]])+SUMIFS(BD.PD[Pago 3],BD.PD[Per.P3],D$1,BD.PD[Pos],Tabla3[[#This Row],[Part.]])+SUMIFS(BD.PD[Pago 4],BD.PD[Per.P4],D$1,BD.PD[Pos],Tabla3[[#This Row],[Part.]])+SUMIFS(BD.PD[Pago 5],BD.PD[Per.P5],D$1,BD.PD[Pos],Tabla3[[#This Row],[Part.]]) -> 0 | E46: =SUMIFS(BD.PD[Pago 1],BD.PD[Per.P1],E$1,BD.PD[Pos],Tabla3[[#This Row],[Part.]])+SUMIFS(BD.PD[Pago 2],BD.PD[Per.P2],E$1,BD.PD[Pos],Tabla3[[#This Row],[Part.]])+SUMIFS(BD.PD[Pago 3],BD.PD[Per.P3],E$1,BD.PD[Pos],Tabla3[[#This Row],[Part.]])+SUMIFS(BD.PD[Pago 4],BD.PD[Per.P4],E$1,BD.PD[Pos],Tabla3[[#This Row],[Part.]])+SUMIFS(BD.PD[Pago 5],BD.PD[Per.P5],E$1,BD.PD[Pos],Tabla3[[#This Row],[Part.]]) -> 0 | F46: =SUMIFS(BD.PD[Pago 1],BD.PD[Per.P1],F$1,BD.PD[Pos],Tabla3[[#This Row],[Part.]])+SUMIFS(BD.PD[Pago 2],BD.PD[Per.P2],F$1,BD.PD[Pos],Tabla3[[#This Row],[Part.]])+SUMIFS(BD.PD[Pago 3],BD.PD[Per.P3],F$1,BD.PD[Pos],Tabla3[[#This Row],[Part.]])+SUMIFS(BD.PD[Pago 4],BD.PD[Per.P4],F$1,BD.PD[Pos],Tabla3[[#This Row],[Part.]])+SUMIFS(BD.PD[Pago 5],BD.PD[Per.P5],F$1,BD.PD[Pos],Tabla3[[#This Row],[Part.]]) -> 0 | G46: =SUMIFS(BD.PD[Pago 1],BD.PD[Per.P1],G$1,BD.PD[Pos],Tabla3[[#This Row],[Part.]])+SUMIFS(BD.PD[Pago 2],BD.PD[Per.P2],G$1,BD.PD[Pos],Tabla3[[#This Row],[Part.]])+SUMIFS(BD.PD[Pago 3],BD.PD[Per.P3],G$1,BD.PD[Pos],Tabla3[[#This Row],[Part.]])+SUMIFS(BD.PD[Pago 4],BD.PD[Per.P4],G$1,BD.PD[Pos],Tabla3[[#This Row],[Part.]])+SUMIFS(BD.PD[Pago 5],BD.PD[Per.P5],G$1,BD.PD[Pos],Tabla3[[#This Row],[Part.]]) -> 0 | H46: =SUMIFS(BD.PD[Pago 1],BD.PD[Per.P1],H$1,BD.PD[Pos],Tabla3[[#This Row],[Part.]])+SUMIFS(BD.PD[Pago 2],BD.PD[Per.P2],H$1,BD.PD[Pos],Tabla3[[#This Row],[Part.]])+SUMIFS(BD.PD[Pago 3],BD.PD[Per.P3],H$1,BD.PD[Pos],Tabla3[[#This Row],[Part.]])+SUMIFS(BD.PD[Pago 4],BD.PD[Per.P4],H$1,BD.PD[Pos],Tabla3[[#This Row],[Part.]])+SUMIFS(BD.PD[Pago 5],BD.PD[Per.P5],H$1,BD.PD[Pos],Tabla3[[#This Row],[Part.]]) -> 0 | I46: =SUMIFS(BD.PD[Pago 1],BD.PD[Per.P1],I$1,BD.PD[Pos],Tabla3[[#This Row],[Part.]])+SUMIFS(BD.PD[Pago 2],BD.PD[Per.P2],I$1,BD.PD[Pos],Tabla3[[#This Row],[Part.]])+SUMIFS(BD.PD[Pago 3],BD.PD[Per.P3],I$1,BD.PD[Pos],Tabla3[[#This Row],[Part.]])+SUMIFS(BD.PD[Pago 4],BD.PD[Per.P4],I$1,BD.PD[Pos],Tabla3[[#This Row],[Part.]])+SUMIFS(BD.PD[Pago 5],BD.PD[Per.P5],I$1,BD.PD[Pos],Tabla3[[#This Row],[Part.]]) -> 0 | J46: =SUMIFS(BD.PD[Pago 1],BD.PD[Per.P1],J$1,BD.PD[Pos],Tabla3[[#This Row],[Part.]])+SUMIFS(BD.PD[Pago 2],BD.PD[Per.P2],J$1,BD.PD[Pos],Tabla3[[#This Row],[Part.]])+SUMIFS(BD.PD[Pago 3],BD.PD[Per.P3],J$1,BD.PD[Pos],Tabla3[[#This Row],[Part.]])+SUMIFS(BD.PD[Pago 4],BD.PD[Per.P4],J$1,BD.PD[Pos],Tabla3[[#This Row],[Part.]])+SUMIFS(BD.PD[Pago 5],BD.PD[Per.P5],J$1,BD.PD[Pos],Tabla3[[#This Row],[Part.]]) -> 0 | K46: =SUMIFS(BD.PD[Pago 1],BD.PD[Per.P1],K$1,BD.PD[Pos],Tabla3[[#This Row],[Part.]])+SUMIFS(BD.PD[Pago 2],BD.PD[Per.P2],K$1,BD.PD[Pos],Tabla3[[#This Row],[Part.]])+SUMIFS(BD.PD[Pago 3],BD.PD[Per.P3],K$1,BD.PD[Pos],Tabla3[[#This Row],[Part.]])+SUMIFS(BD.PD[Pago 4],BD.PD[Per.P4],K$1,BD.PD[Pos],Tabla3[[#This Row],[Part.]])+SUMIFS(BD.PD[Pago 5],BD.PD[Per.P5],K$1,BD.PD[Pos],Tabla3[[#This Row],[Part.]]) -> 0 | ... AA46: =SUMIFS(BD.PD[Pago 1],BD.PD[Per.P1],AA$1,BD.PD[Pos],Tabla3[[#This Row],[Part.]])+SUMIFS(BD.PD[Pago 2],BD.PD[Per.P2],AA$1,BD.PD[Pos],Tabla3[[#This Row],[Part.]])+SUMIFS(BD.PD[Pago 3],BD.PD[Per.P3],AA$1,BD.PD[Pos],Tabla3[[#This Row],[Part.]])+SUMIFS(BD.PD[Pago 4],BD.PD[Per.P4],AA$1,BD.PD[Pos],Tabla3[[#This Row],[Part.]])+SUMIFS(BD.PD[Pago 5],BD.PD[Per.P5],AA$1,BD.PD[Pos],Tabla3[[#This Row],[Part.]]) -> 0 | AB46: =SUM(Tabla3[[#This Row],[P1]:[P24]]) -> 0
