Workbook
Name \4: #REF!
Name \4: #REF!
Name \4: #REF!
Name \6: #REF!
Name \6: #REF!
Name \6: #REF!
Name \A: #REF!
Name \A: #REF!
Name \A: #REF!
Name \E: #REF!
Name \E: #REF!
Name \I: #REF!
Name \I: #REF!
Name \M: #REF!
Name \M: #REF!
Name \N: #REF!
Name \N: #REF!
Name \O: #REF!
Name \O: #REF!
Name \U: #REF!
Name \U: #REF!
Name __DAT1: #REF!
Name __DAT10: #REF!
Name __DAT11: #REF!
Name __DAT12: #REF!
Name __DAT13: #REF!
Name __DAT14: #REF!
Name __DAT2: #REF!
Name __DAT3: #REF!
Name __DAT4: #REF!
Name __DAT5: #REF!
Name __DAT6: #REF!
Name __DAT7: #REF!
Name __DAT8: #REF!
Name __DAT9: #REF!
Name _DAT1: #REF!
Name _DAT10: #REF!
Name _DAT11: #REF!
Name _DAT12: #REF!
Name _DAT13: #REF!
Name _DAT14: #REF!
Name _DAT15: #REF!
Name _DAT16: #REF!
Name _DAT17: #REF!
Name _DAT18: #REF!
Name _DAT19: #REF!
Name _DAT2: #REF!
Name _DAT20: #REF!
Name _DAT21: #REF!
Name _DAT3: #REF!
Name _DAT4: #REF!
Name _DAT5: #REF!
Name _DAT6: #REF!
Name _DAT7: #REF!
Name _DAT8: #REF!
Name _DAT9: #REF!
Name ACERO: #REF!
Name ACERO: #REF!
Name ACERO: #REF!
Name ACERO: #REF!

Sheet Actualización

Sheet Plan OI
C1: Presupuesto Detallado - Propuesta para Sirena Compacta Mao
C2: Area de Compras de Activos
C3: 45512
C5: Fecha Version: 04/09/2029 | D5: Alto Nivel | E5: Plan detallado Aprobado | I5: Plan Detallado DOP | L5: Plan Detallado en ejecución
D6: Total Presupuesto [USD] | E6: Total Presupuesto [USD] | G6: Ppto OI [DOP] | H6: Ppto Capex [DOP] | I6: Total Iniciativa [DOP] | J6: Ppto OI [USD] | K6: Ppto Capex [USD] | L6: Total Iniciativa [USD]
C7: TOTAL GENERAL ESTIMADO | D7: =D10+D11+D12 -> 3179486.8 | E7: =E10+E11+E12 -> 2950565.9 | G7: =SUM(G10:G12) -> 1.8021213e+08 | H7: =SUM(H10:H12) -> 0 | I7: =H7+G7 -> 1.8021213e+08 | J7: =SUM(J10:J12) -> 2860509.9 | K7: =SUM(K10:K12) -> 0 | L7: =K7+J7 -> 2860509.9
C9: Resumen de Partidas
C10: EQUIPAMIENTO | D10: =SUMIF(PPto[Gran Part.],$C10,PPto[Total '[USD']]) -> 2901152.5 | E10: =SUMIF(PPto[Gran Part.],$C10,PPto[Total '[USD']3]) -> 2728452.2 | G10: =SUMIF(PPto[Gran Part.],$C10,PPto[Ppto. OI '[DOP']2]) -> 1.6825576e+08 | H10: =SUMIF(PPto[Gran Part.],$C10,PPto[Ppto. Capex '[DOP']]) -> 0 | I10: =SUMIF(PPto[Gran Part.],$C10,PPto[Total '[DOP']]) -> 1.6825576e+08 | J10: =SUMIF(PPto[Gran Part.],C10,PPto[Ppto. OI '[USD']]) -> 2670726.3 | K10: =SUMIF(PPto[Gran Part.],C10,PPto[Ppto. Capex '[USD']]) -> 0 | L10: =K10+J10 -> 2670726.3
C11: EDIFICACIÓN | D11: =SUMIF(PPto[Gran Part.],$C11,PPto[Total '[USD']]) -> 278334.38 | E11: =SUMIF(PPto[Gran Part.],$C11,PPto[Total '[USD']3]) -> 222113.72 | G11: =SUMIF(PPto[Gran Part.],$C11,PPto[Ppto. OI '[DOP']2]) -> 11956367 | H11: =SUMIF(PPto[Gran Part.],$C11,PPto[Ppto. Capex '[DOP']]) -> 0 | I11: =SUMIF(PPto[Gran Part.],$C11,PPto[Total '[DOP']]) -> 11956367 | J11: =SUMIF(PPto[Gran Part.],C11,PPto[Ppto. OI '[USD']]) -> 189783.61 | K11: =SUMIF(PPto[Gran Part.],C11,PPto[Ppto. Capex '[USD']]) -> 0 | L11: =K11+J11 -> 189783.61
C12: TERRENO | D12: 0 | E12: 0 | G12: =SUMIF(PPto[Gran Part.],$C12,PPto[Ppto. OI '[DOP']2]) -> 0 | H12: =SUMIF(PPto[Gran Part.],$C12,PPto[Ppto. Capex '[DOP']]) -> 0 | I12: =H12+G12 -> 0 | J12: =SUMIF(PPto[Gran Part.],C12,PPto[Ppto. OI '[USD']]) -> 0 | K12: =SUMIF(PPto[Gran Part.],C12,PPto[Ppto. Capex '[USD']]) -> 0 | L12: =K12+J12 -> 0
C13: Gasto | D13: 0 | E13: 0 | G13: =SUMIF(PPto[Gran Part.],$C13,PPto[Ppto. OI '[DOP']2]) -> 0 | H13: =SUMIF(PPto[Gran Part.],$C13,PPto[Ppto. Capex '[DOP']]) -> 0 | I13: =H13+G13 -> 0 | J13: =SUMIF(PPto[Gran Part.],C13,PPto[Ppto. OI '[USD']]) -> 0 | K13: =SUMIF(PPto[Gran Part.],C13,PPto[Ppto. Capex '[USD']]) -> 0 | L13: =K13+J13 -> 0
C15: Área de la Localidad
C16: M² Construcción
C17: M² Sala de Ventas
C18: M² Terreno
G19: OI | H19: Capex | J19: OI | K19: Capex
A20: Part. | B20: Gran Part. | C20: Edificación, Instalaciones y Equipamientos | D20: Total [USD] | E20: Total [USD]3 | F20: Columna2 | G20: Ppto. OI [DOP]2 | H20: Ppto. Capex [DOP] | I20: Total [DOP] | J20: Ppto. OI [USD] | K20: Ppto. Capex [USD] | L20: Total [USD]2 | M20: Columna1 | N20: Ahorro según ejecución
A21: 1 | C21: 1.00 Estudios Preliminares | D21: =SUM(D22:D28) -> 0 | E21: =SUM(E22:E28) -> 0 | G21: =SUM(G22:G30) -> 0 | H21: =SUM(H22:H30) -> 0 | I21: =PPto[[#This Row],[Ppto. Capex '[DOP']]]+PPto[[#This Row],[Ppto. OI '[DOP']2]] -> 0 | J21: =SUM(J22:J30) -> 0 | K21: =SUM(K22:K30) -> 0 | L21: =PPto[[#This Row],[Ppto. Capex '[USD']]]+PPto[[#This Row],[Ppto. OI '[USD']]] -> 0 | N21: =+PPto[[#This Row],[Total '[USD']3]]-PPto[[#This Row],[Total '[USD']2]] -> 0
A22: 1.01 | B22: Edificación | C22: 1.01 Diseño arquitectónico | D22: 0 | E22: 0 | G22: =SUMIFS(BD.PD[Ppto. Orden Interna '[DOP']],BD.PD[Pos],PPto[[#This Row],[Part.]],BD.PD[Tipo Ppto],G$19) -> 0 | H22: =SUMIFS(BD.PD[Ppto. Orden Interna '[DOP']],BD.PD[Pos],PPto[[#This Row],[Part.]],BD.PD[Tipo Ppto],H$19) -> 0 | I22: =PPto[[#This Row],[Ppto. Capex '[DOP']]]+PPto[[#This Row],[Ppto. OI '[DOP']2]] -> 0 | J22: =SUMIFS(BD.PD[Ppto. Orden Interna '[USD']],BD.PD[Pos],PPto[[#This Row],[Part.]],BD.PD[Tipo Ppto],J$19) -> 0 | K22: =SUMIFS(BD.PD[Ppto. Orden Interna '[USD']],BD.PD[Pos],PPto[[#This Row],[Part.]],BD.PD[Tipo Ppto],K$19) -> 0 | L22: =PPto[[#This Row],[Ppto. Capex '[USD']]]+PPto[[#This Row],[Ppto. OI '[USD']]] -> 0 | N22: =+PPto[[#This Row],[Total '[USD']3]]-PPto[[#This Row],[Total '[USD']2]] -> 0
A23: 1.02 | B23: Edificación | C23: 1.02 Diseño estructural | D23: 0 | E23: 0 | G23: =SUMIFS(BD.PD[Ppto. Orden Interna '[DOP']],BD.PD[Pos],PPto[[#This Row],[Part.]],BD.PD[Tipo Ppto],G$19) -> 0 | H23: =SUMIFS(BD.PD[Ppto. Orden Interna '[DOP']],BD.PD[Pos],PPto[[#This Row],[Part.]],BD.PD[Tipo Ppto],H$19) -> 0 | I23: =PPto[[#This Row],[Ppto. Capex '[DOP']]]+PPto[[#This Row],[Ppto. OI '[DOP']2]] -> 0 | J23: =SUMIFS(BD.PD[Ppto. Orden Interna '[USD']],BD.PD[Pos],PPto[[#This Row],[Part.]],BD.PD[Tipo Ppto],J$19) -> 0 | K23: =SUMIFS(BD.PD[Ppto. Orden Interna '[USD']],BD.PD[Pos],PPto[[#This Row],[Part.]],BD.PD[Tipo Ppto],K$19) -> 0 | L23: =PPto[[#This Row],[Ppto. Capex '[USD']]]+PPto[[#This Row],[Ppto. OI '[USD']]] -> 0 | N23: =+PPto[[#This Row],[Total '[USD']3]]-PPto[[#This Row],[Total '[USD']2]] -> 0
A24: 1.03 | B24: Edificación | C24: 1.03 Diseño electromecánico | D24: 0 | E24: 0 | G24: =SUMIFS(BD.PD[Ppto. Orden Interna '[DOP']],BD.PD[Pos],PPto[[#This Row],[Part.]],BD.PD[Tipo Ppto],G$19) -> 0 | H24: =SUMIFS(BD.PD[Ppto. Orden Interna '[DOP']],BD.PD[Pos],PPto[[#This Row],[Part.]],BD.PD[Tipo Ppto],H$19) -> 0 | I24: =PPto[[#This Row],[Ppto. Capex '[DOP']]]+PPto[[#This Row],[Ppto. OI '[DOP']2]] -> 0 | J24: =SUMIFS(BD.PD[Ppto. Orden Interna '[USD']],BD.PD[Pos],PPto[[#This Row],[Part.]],BD.PD[Tipo Ppto],J$19) -> 0 | K24: =SUMIFS(BD.PD[Ppto. Orden Interna '[USD']],BD.PD[Pos],PPto[[#This Row],[Part.]],BD.PD[Tipo Ppto],K$19) -> 0 | L24: =PPto[[#This Row],[Ppto. Capex '[USD']]]+PPto[[#This Row],[Ppto. OI '[USD']]] -> 0 | N24: =+PPto[[#This Row],[Total '[USD']3]]-PPto[[#This Row],[Total '[USD']2]] -> 0
A25: 1.04 | B25: Edificación | C25: 1.04 Diseño sanitario | D25: 0 | E25: 0 | G25: =SUMIFS(BD.PD[Ppto. Orden Interna '[DOP']],BD.PD[Pos],PPto[[#This Row],[Part.]],BD.PD[Tipo Ppto],G$19) -> 0 | H25: =SUMIFS(BD.PD[Ppto. Orden Interna '[DOP']],BD.PD[Pos],PPto[[#This Row],[Part.]],BD.PD[Tipo Ppto],H$19) -> 0 | I25: =PPto[[#This Row],[Ppto. Capex '[DOP']]]+PPto[[#This Row],[Ppto. OI '[DOP']2]] -> 0 | J25: =SUMIFS(BD.PD[Ppto. Orden Interna '[USD']],BD.PD[Pos],PPto[[#This Row],[Part.]],BD.PD[Tipo Ppto],J$19) -> 0 | K25: =SUMIFS(BD.PD[Ppto. Orden Interna '[USD']],BD.PD[Pos],PPto[[#This Row],[Part.]],BD.PD[Tipo Ppto],K$19) -> 0 | L25: =PPto[[#This Row],[Ppto. Capex '[USD']]]+PPto[[#This Row],[Ppto. OI '[USD']]] -> 0 | N25: =+PPto[[#This Row],[Total '[USD']3]]-PPto[[#This Row],[Total '[USD']2]] -> 0
A26: 1.05 | B26: Edificación | C26: 1.05 Estudio Geotécnico | D26: 0 | E26: 0 | G26: =SUMIFS(BD.PD[Ppto. Orden Interna '[DOP']],BD.PD[Pos],PPto[[#This Row],[Part.]],BD.PD[Tipo Ppto],G$19) -> 0 | H26: =SUMIFS(BD.PD[Ppto. Orden Interna '[DOP']],BD.PD[Pos],PPto[[#This Row],[Part.]],BD.PD[Tipo Ppto],H$19) -> 0 | I26: =PPto[[#This Row],[Ppto. Capex '[DOP']]]+PPto[[#This Row],[Ppto. OI '[DOP']2]] -> 0 | J26: =SUMIFS(BD.PD[Ppto. Orden Interna '[USD']],BD.PD[Pos],PPto[[#This Row],[Part.]],BD.PD[Tipo Ppto],J$19) -> 0 | K26: =SUMIFS(BD.PD[Ppto. Orden Interna '[USD']],BD.PD[Pos],PPto[[#This Row],[Part.]],BD.PD[Tipo Ppto],K$19) -> 0 | L26: =PPto[[#This Row],[Ppto. Capex '[USD']]]+PPto[[#This Row],[Ppto. OI '[USD']]] -> 0 | N26: =+PPto[[#This Row],[Total '[USD']3]]-PPto[[#This Row],[Total '[USD']2]] -> 0
A27: 1.06 | B27: Edificación | C27: 1.06 Levantamiento topográfico | D27: 0 | E27: 0 | G27: =SUMIFS(BD.PD[Ppto. Orden Interna '[DOP']],BD.PD[Pos],PPto[[#This Row],[Part.]],BD.PD[Tipo Ppto],G$19) -> 0 | H27: =SUMIFS(BD.PD[Ppto. Orden Interna '[DOP']],BD.PD[Pos],PPto[[#This Row],[Part.]],BD.PD[Tipo Ppto],H$19) -> 0 | I27: =PPto[[#This Row],[Ppto. Capex '[DOP']]]+PPto[[#This Row],[Ppto. OI '[DOP']2]] -> 0 | J27: =SUMIFS(BD.PD[Ppto. Orden Interna '[USD']],BD.PD[Pos],PPto[[#This Row],[Part.]],BD.PD[Tipo Ppto],J$19) -> 0 | K27: =SUMIFS(BD.PD[Ppto. Orden Interna '[USD']],BD.PD[Pos],PPto[[#This Row],[Part.]],BD.PD[Tipo Ppto],K$19) -> 0 | L27: =PPto[[#This Row],[Ppto. Capex '[USD']]]+PPto[[#This Row],[Ppto. OI '[USD']]] -> 0 | N27: =+PPto[[#This Row],[Total '[USD']3]]-PPto[[#This Row],[Total '[USD']2]] -> 0
A28: 1.07 | B28: Edificación | C28: 1.07 Permisos | D28: 0 | E28: 0 | G28: =SUMIFS(BD.PD[Ppto. Orden Interna '[DOP']],BD.PD[Pos],PPto[[#This Row],[Part.]],BD.PD[Tipo Ppto],G$19) -> 0 | H28: =SUMIFS(BD.PD[Ppto. Orden Interna '[DOP']],BD.PD[Pos],PPto[[#This Row],[Part.]],BD.PD[Tipo Ppto],H$19) -> 0 | I28: =PPto[[#This Row],[Ppto. Capex '[DOP']]]+PPto[[#This Row],[Ppto. OI '[DOP']2]] -> 0 | J28: =SUMIFS(BD.PD[Ppto. Orden Interna '[USD']],BD.PD[Pos],PPto[[#This Row],[Part.]],BD.PD[Tipo Ppto],J$19) -> 0 | K28: =SUMIFS(BD.PD[Ppto. Orden Interna '[USD']],BD.PD[Pos],PPto[[#This Row],[Part.]],BD.PD[Tipo Ppto],K$19) -> 0 | L28: =PPto[[#This Row],[Ppto. Capex '[USD']]]+PPto[[#This Row],[Ppto. OI '[USD']]] -> 0 | N28: =+PPto[[#This Row],[Total '[USD']3]]-PPto[[#This Row],[Total '[USD']2]] -> 0
A29: 1.08 | B29: Edificación | C29: 1.08 Diseño sistema contra incendios | D29: 0 | E29: 0 | G29: =SUMIFS(BD.PD[Ppto. Orden Interna '[DOP']],BD.PD[Pos],PPto[[#This Row],[Part.]],BD.PD[Tipo Ppto],G$19) -> 0 | H29: =SUMIFS(BD.PD[Ppto. Orden Interna '[DOP']],BD.PD[Pos],PPto[[#This Row],[Part.]],BD.PD[Tipo Ppto],H$19) -> 0 | I29: =PPto[[#This Row],[Ppto. Capex '[DOP']]]+PPto[[#This Row],[Ppto. OI '[DOP']2]] -> 0 | J29: =SUMIFS(BD.PD[Ppto. Orden Interna '[USD']],BD.PD[Pos],PPto[[#This Row],[Part.]],BD.PD[Tipo Ppto],J$19) -> 0 | K29: =SUMIFS(BD.PD[Ppto. Orden Interna '[USD']],BD.PD[Pos],PPto[[#This Row],[Part.]],BD.PD[Tipo Ppto],K$19) -> 0 | L29: =PPto[[#This Row],[Ppto. Capex '[USD']]]+PPto[[#This Row],[Ppto. OI '[USD']]] -> 0 | N29: =+PPto[[#This Row],[Total '[USD']3]]-PPto[[#This Row],[Total '[USD']2]] -> 0
A30: 1.09 | B30: Edificación | C30: 1.09 Diseño sistema gas | D30: 0 | E30: 0 | G30: =SUMIFS(BD.PD[Ppto. Orden Interna '[DOP']],BD.PD[Pos],PPto[[#This Row],[Part.]],BD.PD[Tipo Ppto],G$19) -> 0 | H30: =SUMIFS(BD.PD[Ppto. Orden Interna '[DOP']],BD.PD[Pos],PPto[[#This Row],[Part.]],BD.PD[Tipo Ppto],H$19) -> 0 | I30: =PPto[[#This Row],[Ppto. Capex '[DOP']]]+PPto[[#This Row],[Ppto. OI '[DOP']2]] -> 0 | J30: =SUMIFS(BD.PD[Ppto. Orden Interna '[USD']],BD.PD[Pos],PPto[[#This Row],[Part.]],BD.PD[Tipo Ppto],J$19) -> 0 | K30: =SUMIFS(BD.PD[Ppto. Orden Interna '[USD']],BD.PD[Pos],PPto[[#This Row],[Part.]],BD.PD[Tipo Ppto],K$19) -> 0 | L30: =PPto[[#This Row],[Ppto. Capex '[USD']]]+PPto[[#This Row],[Ppto. OI '[USD']]] -> 0 | N30: =+PPto[[#This Row],[Total '[USD']3]]-PPto[[#This Row],[Total '[USD']2]] -> 0
A31: 2 | C31: 2.00 Obra Civil | D31: =SUM(D32:D42) -> 278334.38 | E31: =SUM(E32:E42) -> 222113.72 | G31: =SUM(G32:G42) -> 11956367 | H31: =SUM(H32:H42) -> 0 | I31: =PPto[[#This Row],[Ppto. Capex '[DOP']]]+PPto[[#This Row],[Ppto. OI '[DOP']2]] -> 11956367 | J31: =SUM(J32:J42) -> 189783.61 | K31: =SUM(K32:K42) -> 0 | L31: =PPto[[#This Row],[Ppto. Capex '[USD']]]+PPto[[#This Row],[Ppto. OI '[USD']]] -> 189783.61
A32: 2.01 | B32: Edificación | C32: 2.01 Edificación - Obra Civil | D32: 161119.6 | E32: 8353.66 | G32: =SUMIFS(BD.PD[Ppto. Orden Interna '[DOP']],BD.PD[Pos],PPto[[#This Row],[Part.]],BD.PD[Tipo Ppto],G$19) -> 526280.58 | H32: =SUMIFS(BD.PD[Ppto. Orden Interna '[DOP']],BD.PD[Pos],PPto[[#This Row],[Part.]],BD.PD[Tipo Ppto],H$19) -> 0 | I32: =PPto[[#This Row],[Ppto. Capex '[DOP']]]+PPto[[#This Row],[Ppto. OI '[DOP']2]] -> 526280.58 | J32: =SUMIFS(BD.PD[Ppto. Orden Interna '[USD']],BD.PD[Pos],PPto[[#This Row],[Part.]],BD.PD[Tipo Ppto],J$19) -> 8353.66 | K32: =SUMIFS(BD.PD[Ppto. Orden Interna '[USD']],BD.PD[Pos],PPto[[#This Row],[Part.]],BD.PD[Tipo Ppto],K$19) -> 0 | L32: =PPto[[#This Row],[Ppto. Capex '[USD']]]+PPto[[#This Row],[Ppto. OI '[USD']]] -> 8353.66 | N32: =+PPto[[#This Row],[Total '[USD']3]]-PPto[[#This Row],[Total '[USD']2]] -> 0
A33: 2.02 | B33: Edificación | C33: 2.02 Edificación - Estructura Metálica | D33: 0 | E33: 0 | G33: =SUMIFS(BD.PD[Ppto. Orden Interna '[DOP']],BD.PD[Pos],PPto[[#This Row],[Part.]],BD.PD[Tipo Ppto],G$19) -> 0 | H33: =SUMIFS(BD.PD[Ppto. Orden Interna '[DOP']],BD.PD[Pos],PPto[[#This Row],[Part.]],BD.PD[Tipo Ppto],H$19) -> 0 | I33: =PPto[[#This Row],[Ppto. Capex '[DOP']]]+PPto[[#This Row],[Ppto. OI '[DOP']2]] -> 0 | J33: =SUMIFS(BD.PD[Ppto. Orden Interna '[USD']],BD.PD[Pos],PPto[[#This Row],[Part.]],BD.PD[Tipo Ppto],J$19) -> 0 | K33: =SUMIFS(BD.PD[Ppto. Orden Interna '[USD']],BD.PD[Pos],PPto[[#This Row],[Part.]],BD.PD[Tipo Ppto],K$19) -> 0 | L33: =PPto[[#This Row],[Ppto. Capex '[USD']]]+PPto[[#This Row],[Ppto. OI '[USD']]] -> 0 | N33: =+PPto[[#This Row],[Total '[USD']3]]-PPto[[#This Row],[Total '[USD']2]] -> 0
A34: 2.03 | B34: Edificación | C34: 2.03 Edificación - Techo S.S. y Cerramientos Multipanel | D34: 0 | E34: 0 | G34: =SUMIFS(BD.PD[Ppto. Orden Interna '[DOP']],BD.PD[Pos],PPto[[#This Row],[Part.]],BD.PD[Tipo Ppto],G$19) -> 0 | H34: =SUMIFS(BD.PD[Ppto. Orden Interna '[DOP']],BD.PD[Pos],PPto[[#This Row],[Part.]],BD.PD[Tipo Ppto],H$19) -> 0 | I34: =PPto[[#This Row],[Ppto. Capex '[DOP']]]+PPto[[#This Row],[Ppto. OI '[DOP']2]] -> 0 | J34: =SUMIFS(BD.PD[Ppto. Orden Interna '[USD']],BD.PD[Pos],PPto[[#This Row],[Part.]],BD.PD[Tipo Ppto],J$19) -> 0 | K34: =SUMIFS(BD.PD[Ppto. Orden Interna '[USD']],BD.PD[Pos],PPto[[#This Row],[Part.]],BD.PD[Tipo Ppto],K$19) -> 0 | L34: =PPto[[#This Row],[Ppto. Capex '[USD']]]+PPto[[#This Row],[Ppto. OI '[USD']]] -> 0 | N34: =+PPto[[#This Row],[Total '[USD']3]]-PPto[[#This Row],[Total '[USD']2]] -> 0
A35: 2.04 | B35: Edificación | C35: 2.04 Edificación - Tragaluces "Skylights" | D35: 0 | E35: 0 | G35: =SUMIFS(BD.PD[Ppto. Orden Interna '[DOP']],BD.PD[Pos],PPto[[#This Row],[Part.]],BD.PD[Tipo Ppto],G$19) -> 0 | H35: =SUMIFS(BD.PD[Ppto. Orden Interna '[DOP']],BD.PD[Pos],PPto[[#This Row],[Part.]],BD.PD[Tipo Ppto],H$19) -> 0 | I35: =PPto[[#This Row],[Ppto. Capex '[DOP']]]+PPto[[#This Row],[Ppto. OI '[DOP']2]] -> 0 | J35: =SUMIFS(BD.PD[Ppto. Orden Interna '[USD']],BD.PD[Pos],PPto[[#This Row],[Part.]],BD.PD[Tipo Ppto],J$19) -> 0 | K35: =SUMIFS(BD.PD[Ppto. Orden Interna '[USD']],BD.PD[Pos],PPto[[#This Row],[Part.]],BD.PD[Tipo Ppto],K$19) -> 0 | L35: =PPto[[#This Row],[Ppto. Capex '[USD']]]+PPto[[#This Row],[Ppto. OI '[USD']]] -> 0 | N35: =+PPto[[#This Row],[Total '[USD']3]]-PPto[[#This Row],[Total '[USD']2]] -> 0
A36: 2.05 | B36: Edificación | C36: 2.05 Instalaciones Sanitarias | D36: 25100 | E36: 15099.42 | G36: =SUMIFS(BD.PD[Ppto. Orden Interna '[DOP']],BD.PD[Pos],PPto[[#This Row],[Part.]],BD.PD[Tipo Ppto],G$19) -> 1071000 | H36: =SUMIFS(BD.PD[Ppto. Orden Interna '[DOP']],BD.PD[Pos],PPto[[#This Row],[Part.]],BD.PD[Tipo Ppto],H$19) -> 0 | I36: =PPto[[#This Row],[Ppto. Capex '[DOP']]]+PPto[[#This Row],[Ppto. OI '[DOP']2]] -> 1071000 | J36: =SUMIFS(BD.PD[Ppto. Orden Interna '[USD']],BD.PD[Pos],PPto[[#This Row],[Part.]],BD.PD[Tipo Ppto],J$19) -> 17000 | K36: =SUMIFS(BD.PD[Ppto. Orden Interna '[USD']],BD.PD[Pos],PPto[[#This Row],[Part.]],BD.PD[Tipo Ppto],K$19) -> 0 | L36: =PPto[[#This Row],[Ppto. Capex '[USD']]]+PPto[[#This Row],[Ppto. OI '[USD']]] -> 17000 | N36: =+PPto[[#This Row],[Total '[USD']3]]-PPto[[#This Row],[Total '[USD']2]] -> -1900.5797
A37: 2.06 | B37: Edificación | C37: 2.06 Instalación de Gas | D37: 0 | E37: 7260.3834 | G37: =SUMIFS(BD.PD[Ppto. Orden Interna '[DOP']],BD.PD[Pos],PPto[[#This Row],[Part.]],BD.PD[Tipo Ppto],G$19) -> 0 | H37: =SUMIFS(BD.PD[Ppto. Orden Interna '[DOP']],BD.PD[Pos],PPto[[#This Row],[Part.]],BD.PD[Tipo Ppto],H$19) -> 0 | I37: =PPto[[#This Row],[Ppto. Capex '[DOP']]]+PPto[[#This Row],[Ppto. OI '[DOP']2]] -> 0 | J37: =SUMIFS(BD.PD[Ppto. Orden Interna '[USD']],BD.PD[Pos],PPto[[#This Row],[Part.]],BD.PD[Tipo Ppto],J$19) -> 0 | K37: =SUMIFS(BD.PD[Ppto. Orden Interna '[USD']],BD.PD[Pos],PPto[[#This Row],[Part.]],BD.PD[Tipo Ppto],K$19) -> 0 | L37: =PPto[[#This Row],[Ppto. Capex '[USD']]]+PPto[[#This Row],[Ppto. OI '[USD']]] -> 0 | N37: =+PPto[[#This Row],[Total '[USD']3]]-PPto[[#This Row],[Total '[USD']2]] -> 7260.3834
A38: 2.07 | B38: Edificación | C38: 2.07 Sistema Contra Incendios | D38: 8266.7758 | E38: 114712.49 | G38: =SUMIFS(BD.PD[Ppto. Orden Interna '[DOP']],BD.PD[Pos],PPto[[#This Row],[Part.]],BD.PD[Tipo Ppto],G$19) -> 6294056 | H38: =SUMIFS(BD.PD[Ppto. Orden Interna '[DOP']],BD.PD[Pos],PPto[[#This Row],[Part.]],BD.PD[Tipo Ppto],H$19) -> 0 | I38: =PPto[[#This Row],[Ppto. Capex '[DOP']]]+PPto[[#This Row],[Ppto. OI '[DOP']2]] -> 6294056 | J38: =SUMIFS(BD.PD[Ppto. Orden Interna '[USD']],BD.PD[Pos],PPto[[#This Row],[Part.]],BD.PD[Tipo Ppto],J$19) -> 99905.65 | K38: =SUMIFS(BD.PD[Ppto. Orden Interna '[USD']],BD.PD[Pos],PPto[[#This Row],[Part.]],BD.PD[Tipo Ppto],K$19) -> 0 | L38: =PPto[[#This Row],[Ppto. Capex '[USD']]]+PPto[[#This Row],[Ppto. OI '[USD']]] -> 99905.65 | N38: =+PPto[[#This Row],[Total '[USD']3]]-PPto[[#This Row],[Total '[USD']2]] -> 14806.836
A39: 2.08 | B39: Edificación | C39: 2.08 Instalaciones Mecánicas | D39: 83848 | E39: 65014.422 | G39: =SUMIFS(BD.PD[Ppto. Orden Interna '[DOP']],BD.PD[Pos],PPto[[#This Row],[Part.]],BD.PD[Tipo Ppto],G$19) -> 3329609.7 | H39: =SUMIFS(BD.PD[Ppto. Orden Interna '[DOP']],BD.PD[Pos],PPto[[#This Row],[Part.]],BD.PD[Tipo Ppto],H$19) -> 0 | I39: =PPto[[#This Row],[Ppto. Capex '[DOP']]]+PPto[[#This Row],[Ppto. OI '[DOP']2]] -> 3329609.7 | J39: =SUMIFS(BD.PD[Ppto. Orden Interna '[USD']],BD.PD[Pos],PPto[[#This Row],[Part.]],BD.PD[Tipo Ppto],J$19) -> 52850.947 | K39: =SUMIFS(BD.PD[Ppto. Orden Interna '[USD']],BD.PD[Pos],PPto[[#This Row],[Part.]],BD.PD[Tipo Ppto],K$19) -> 0 | L39: =PPto[[#This Row],[Ppto. Capex '[USD']]]+PPto[[#This Row],[Ppto. OI '[USD']]] -> 52850.947 | N39: =+PPto[[#This Row],[Total '[USD']3]]-PPto[[#This Row],[Total '[USD']2]] -> 12163.475
A40: 2.09 | B40: Edificación | C40: 2.09 Rejillas y Sumideros | D40: 0 | E40: 11673.35 | G40: =SUMIFS(BD.PD[Ppto. Orden Interna '[DOP']],BD.PD[Pos],PPto[[#This Row],[Part.]],BD.PD[Tipo Ppto],G$19) -> 735421.05 | H40: =SUMIFS(BD.PD[Ppto. Orden Interna '[DOP']],BD.PD[Pos],PPto[[#This Row],[Part.]],BD.PD[Tipo Ppto],H$19) -> 0 | I40: =PPto[[#This Row],[Ppto. Capex '[DOP']]]+PPto[[#This Row],[Ppto. OI '[DOP']2]] -> 735421.05 | J40: =SUMIFS(BD.PD[Ppto. Orden Interna '[USD']],BD.PD[Pos],PPto[[#This Row],[Part.]],BD.PD[Tipo Ppto],J$19) -> 11673.35 | K40: =SUMIFS(BD.PD[Ppto. Orden Interna '[USD']],BD.PD[Pos],PPto[[#This Row],[Part.]],BD.PD[Tipo Ppto],K$19) -> 0 | L40: =PPto[[#This Row],[Ppto. Capex '[USD']]]+PPto[[#This Row],[Ppto. OI '[USD']]] -> 11673.35 | M40: Rejillas y sumideros del nuevo proveedor | N40: =+PPto[[#This Row],[Total '[USD']3]]-PPto[[#This Row],[Total '[USD']2]] -> 0
A41: 2.1 | B41: Edificación | C41: 2.10 Supervisión Civil y Sanitaria | D41: 0 | E41: 0 | G41: =SUMIFS(BD.PD[Ppto. Orden Interna '[DOP']],BD.PD[Pos],PPto[[#This Row],[Part.]],BD.PD[Tipo Ppto],G$19) -> 0 | H41: =SUMIFS(BD.PD[Ppto. Orden Interna '[DOP']],BD.PD[Pos],PPto[[#This Row],[Part.]],BD.PD[Tipo Ppto],H$19) -> 0 | I41: =PPto[[#This Row],[Ppto. Capex '[DOP']]]+PPto[[#This Row],[Ppto. OI '[DOP']2]] -> 0 | J41: =SUMIFS(BD.PD[Ppto. Orden Interna '[USD']],BD.PD[Pos],PPto[[#This Row],[Part.]],BD.PD[Tipo Ppto],J$19) -> 0 | K41: =SUMIFS(BD.PD[Ppto. Orden Interna '[USD']],BD.PD[Pos],PPto[[#This Row],[Part.]],BD.PD[Tipo Ppto],K$19) -> 0 | L41: =PPto[[#This Row],[Ppto. Capex '[USD']]]+PPto[[#This Row],[Ppto. OI '[USD']]] -> 0 | N41: =+PPto[[#This Row],[Total '[USD']3]]-PPto[[#This Row],[Total '[USD']2]] -> 0
A42: 2.11 | B42: Edificación | C42: 2.11 Supervisión Arquitectónica | D42: 0 | E42: 0 | G42: =SUMIFS(BD.PD[Ppto. Orden Interna '[DOP']],BD.PD[Pos],PPto[[#This Row],[Part.]],BD.PD[Tipo Ppto],G$19) -> 0 | H42: =SUMIFS(BD.PD[Ppto. Orden Interna '[DOP']],BD.PD[Pos],PPto[[#This Row],[Part.]],BD.PD[Tipo Ppto],H$19) -> 0 | I42: =PPto[[#This Row],[Ppto. Capex '[DOP']]]+PPto[[#This Row],[Ppto. OI '[DOP']2]] -> 0 | J42: =SUMIFS(BD.PD[Ppto. Orden Interna '[USD']],BD.PD[Pos],PPto[[#This Row],[Part.]],BD.PD[Tipo Ppto],J$19) -> 0 | K42: =SUMIFS(BD.PD[Ppto. Orden Interna '[USD']],BD.PD[Pos],PPto[[#This Row],[Part.]],BD.PD[Tipo Ppto],K$19) -> 0 | L42: =PPto[[#This Row],[Ppto. Capex '[USD']]]+PPto[[#This Row],[Ppto. OI '[USD']]] -> 0 | N42: =+PPto[[#This Row],[Total '[USD']3]]-PPto[[#This Row],[Total '[USD']2]] -> 0
A43: 3 | C43: 3.00 Sistema Eléctrico | D43: =SUM(D44:D47) -> 146108.56 | E43: =SUM(E44:E47) -> 180559.13 | G43: =SUM(G44:G47) -> 27933332 | H43: =SUM(H44:H47) -> 0 | I43: =PPto[[#This Row],[Ppto. Capex '[DOP']]]+PPto[[#This Row],[Ppto. OI '[DOP']2]] -> 27933332 | J43: =SUM(J44:J47) -> 443386.23 | K43: =SUM(K44:K47) -> 0 | L43: =PPto[[#This Row],[Ppto. Capex '[USD']]]+PPto[[#This Row],[Ppto. OI '[USD']]] -> 443386.23 | N43: =+PPto[[#This Row],[Total '[USD']3]]-PPto[[#This Row],[Total '[USD']2]] -> -262827.1
A44: 3.01 | B44: Equipamiento | C44: 3.01 Instalaciones Eléctricas | D44: 0 | E44: 0 | G44: =SUMIFS(BD.PD[Ppto. Orden Interna '[DOP']],BD.PD[Pos],PPto[[#This Row],[Part.]],BD.PD[Tipo Ppto],G$19) -> 16303582 | H44: =SUMIFS(BD.PD[Ppto. Orden Interna '[DOP']],BD.PD[Pos],PPto[[#This Row],[Part.]],BD.PD[Tipo Ppto],H$19) -> 0 | I44: =PPto[[#This Row],[Ppto. Capex '[DOP']]]+PPto[[#This Row],[Ppto. OI '[DOP']2]] -> 16303582 | J44: =SUMIFS(BD.PD[Ppto. Orden Interna '[USD']],BD.PD[Pos],PPto[[#This Row],[Part.]],BD.PD[Tipo Ppto],J$19) -> 258787.01 | K44: =SUMIFS(BD.PD[Ppto. Orden Interna '[USD']],BD.PD[Pos],PPto[[#This Row],[Part.]],BD.PD[Tipo Ppto],K$19) -> 0 | L44: =PPto[[#This Row],[Ppto. Capex '[USD']]]+PPto[[#This Row],[Ppto. OI '[USD']]] -> 258787.01 | N44: =+PPto[[#This Row],[Total '[USD']3]]-PPto[[#This Row],[Total '[USD']2]] -> -258787.01
A45: 3.02 | B45: Equipamiento | C45: 3.02 Supervisión Eléctrica | D45: 0 | E45: 0 | G45: =SUMIFS(BD.PD[Ppto. Orden Interna '[DOP']],BD.PD[Pos],PPto[[#This Row],[Part.]],BD.PD[Tipo Ppto],G$19) -> 0 | H45: =SUMIFS(BD.PD[Ppto. Orden Interna '[DOP']],BD.PD[Pos],PPto[[#This Row],[Part.]],BD.PD[Tipo Ppto],H$19) -> 0 | I45: =PPto[[#This Row],[Ppto. Capex '[DOP']]]+PPto[[#This Row],[Ppto. OI '[DOP']2]] -> 0 | J45: =SUMIFS(BD.PD[Ppto. Orden Interna '[USD']],BD.PD[Pos],PPto[[#This Row],[Part.]],BD.PD[Tipo Ppto],J$19) -> 0 | K45: =SUMIFS(BD.PD[Ppto. Orden Interna '[USD']],BD.PD[Pos],PPto[[#This Row],[Part.]],BD.PD[Tipo Ppto],K$19) -> 0 | L45: =PPto[[#This Row],[Ppto. Capex '[USD']]]+PPto[[#This Row],[Ppto. OI '[USD']]] -> 0 | N45: =+PPto[[#This Row],[Total '[USD']3]]-PPto[[#This Row],[Total '[USD']2]] -> 0
A46: 3.03 | B46: Equipamiento | C46: 3.03 Generadores | D46: 130677.96 | E46: 165254.22 | G46: =SUMIFS(BD.PD[Ppto. Orden Interna '[DOP']],BD.PD[Pos],PPto[[#This Row],[Part.]],BD.PD[Tipo Ppto],G$19) -> 10411016 | H46: =SUMIFS(BD.PD[Ppto. Orden Interna '[DOP']],BD.PD[Pos],PPto[[#This Row],[Part.]],BD.PD[Tipo Ppto],H$19) -> 0 | I46: =PPto[[#This Row],[Ppto. Capex '[DOP']]]+PPto[[#This Row],[Ppto. OI '[DOP']2]] -> 10411016 | J46: =SUMIFS(BD.PD[Ppto. Orden Interna '[USD']],BD.PD[Pos],PPto[[#This Row],[Part.]],BD.PD[Tipo Ppto],J$19) -> 165254.22 | K46: =SUMIFS(BD.PD[Ppto. Orden Interna '[USD']],BD.PD[Pos],PPto[[#This Row],[Part.]],BD.PD[Tipo Ppto],K$19) -> 0 | L46: =PPto[[#This Row],[Ppto. Capex '[USD']]]+PPto[[#This Row],[Ppto. OI '[USD']]] -> 165254.22 | N46: =+PPto[[#This Row],[Total '[USD']3]]-PPto[[#This Row],[Total '[USD']2]] -> 0
A47: 3.04 | B47: Equipamiento | C47: 3.04 Inversor y UPS | D47: 15430.602 | E47: 15304.914 | G47: =SUMIFS(BD.PD[Ppto. Orden Interna '[DOP']],BD.PD[Pos],PPto[[#This Row],[Part.]],BD.PD[Tipo Ppto],G$19) -> 1218735 | H47: =SUMIFS(BD.PD[Ppto. Orden Interna '[DOP']],BD.PD[Pos],PPto[[#This Row],[Part.]],BD.PD[Tipo Ppto],H$19) -> 0 | I47: =PPto[[#This Row],[Ppto. Capex '[DOP']]]+PPto[[#This Row],[Ppto. OI '[DOP']2]] -> 1218735 | J47: =SUMIFS(BD.PD[Ppto. Orden Interna '[USD']],BD.PD[Pos],PPto[[#This Row],[Part.]],BD.PD[Tipo Ppto],J$19) -> 19345 | K47: =SUMIFS(BD.PD[Ppto. Orden Interna '[USD']],BD.PD[Pos],PPto[[#This Row],[Part.]],BD.PD[Tipo Ppto],K$19) -> 0 | L47: =PPto[[#This Row],[Ppto. Capex '[USD']]]+PPto[[#This Row],[Ppto. OI '[USD']]] -> 19345 | N47: =+PPto[[#This Row],[Total '[USD']3]]-PPto[[#This Row],[Total '[USD']2]] -> -4040.0864
A48: 4 | C48: 4.00 Sistema de Climatización | D48: =SUM(D49:D51) -> 17671.381 | E48: =SUM(E49:E51) -> 274404.11 | G48: =SUM(G49:G51) -> 7596030.8 | H48: =SUM(H49:H51) -> 0 | I48: =PPto[[#This Row],[Ppto. Capex '[DOP']]]+PPto[[#This Row],[Ppto. OI '[DOP']2]] -> 7596030.8 | J48: =SUM(J49:J51) -> 120571.92 | K48: =SUM(K49:K51) -> 0 | L48: =PPto[[#This Row],[Ppto. Capex '[USD']]]+PPto[[#This Row],[Ppto. OI '[USD']]] -> 120571.92 | M48: Adicionales
A49: 4.01 | B49: Equipamiento | C49: 4.01 Suministro e instalación de Equipos | D49: 0 | E49: 255437.67 | G49: =SUMIFS(BD.PD[Ppto. Orden Interna '[DOP']],BD.PD[Pos],PPto[[#This Row],[Part.]],BD.PD[Tipo Ppto],G$19) -> 6416313.8 | H49: =SUMIFS(BD.PD[Ppto. Orden Interna '[DOP']],BD.PD[Pos],PPto[[#This Row],[Part.]],BD.PD[Tipo Ppto],H$19) -> 0 | I49: =PPto[[#This Row],[Ppto. Capex '[DOP']]]+PPto[[#This Row],[Ppto. OI '[DOP']2]] -> 6416313.8 | J49: =SUMIFS(BD.PD[Ppto. Orden Interna '[USD']],BD.PD[Pos],PPto[[#This Row],[Part.]],BD.PD[Tipo Ppto],J$19) -> 101846.25 | K49: =SUMIFS(BD.PD[Ppto. Orden Interna '[USD']],BD.PD[Pos],PPto[[#This Row],[Part.]],BD.PD[Tipo Ppto],K$19) -> 0 | L49: =PPto[[#This Row],[Ppto. Capex '[USD']]]+PPto[[#This Row],[Ppto. OI '[USD']]] -> 101846.25 | M49: Aires acondicionados | N49: =+PPto[[#This Row],[Total '[USD']3]]-PPto[[#This Row],[Total '[USD']2]] -> 153591.42
A50: 4.02 | B50: Equipamiento | C50: 4.02 Supervisión Mecánica | D50: 0 | E50: 0 | G50: =SUMIFS(BD.PD[Ppto. Orden Interna '[DOP']],BD.PD[Pos],PPto[[#This Row],[Part.]],BD.PD[Tipo Ppto],G$19) -> 0 | H50: =SUMIFS(BD.PD[Ppto. Orden Interna '[DOP']],BD.PD[Pos],PPto[[#This Row],[Part.]],BD.PD[Tipo Ppto],H$19) -> 0 | I50: =PPto[[#This Row],[Ppto. Capex '[DOP']]]+PPto[[#This Row],[Ppto. OI '[DOP']2]] -> 0 | J50: =SUMIFS(BD.PD[Ppto. Orden Interna '[USD']],BD.PD[Pos],PPto[[#This Row],[Part.]],BD.PD[Tipo Ppto],J$19) -> 0 | K50: =SUMIFS(BD.PD[Ppto. Orden Interna '[USD']],BD.PD[Pos],PPto[[#This Row],[Part.]],BD.PD[Tipo Ppto],K$19) -> 0 | L50: =PPto[[#This Row],[Ppto. Capex '[USD']]]+PPto[[#This Row],[Ppto. OI '[USD']]] -> 0 | N50: =+PPto[[#This Row],[Total '[USD']3]]-PPto[[#This Row],[Total '[USD']2]] -> 0
A51: 4.03 | B51: Equipamiento | C51: 4.03 Sistema de Extracción cocina | D51: 17671.381 | E51: 18966.438 | G51: =SUMIFS(BD.PD[Ppto. Orden Interna '[DOP']],BD.PD[Pos],PPto[[#This Row],[Part.]],BD.PD[Tipo Ppto],G$19) -> 1179717 | H51: =SUMIFS(BD.PD[Ppto. Orden Interna '[DOP']],BD.PD[Pos],PPto[[#This Row],[Part.]],BD.PD[Tipo Ppto],H$19) -> 0 | I51: =PPto[[#This Row],[Ppto. Capex '[DOP']]]+PPto[[#This Row],[Ppto. OI '[DOP']2]] -> 1179717 | J51: =SUMIFS(BD.PD[Ppto. Orden Interna '[USD']],BD.PD[Pos],PPto[[#This Row],[Part.]],BD.PD[Tipo Ppto],J$19) -> 18725.667 | K51: =SUMIFS(BD.PD[Ppto. Orden Interna '[USD']],BD.PD[Pos],PPto[[#This Row],[Part.]],BD.PD[Tipo Ppto],K$19) -> 0 | L51: =PPto[[#This Row],[Ppto. Capex '[USD']]]+PPto[[#This Row],[Ppto. OI '[USD']]] -> 18725.667 | N51: =+PPto[[#This Row],[Total '[USD']3]]-PPto[[#This Row],[Total '[USD']2]] -> 240.77183
A52: 5 | C52: 5.00 Frio Alimentario | D52: =SUM(D53:D59) -> 1189624.4 | E52: =SUM(E53:E59) -> 1043362.4 | G52: =SUM(G53:G59) -> 67449917 | H52: =SUM(H53:H59) -> 0 | I52: =PPto[[#This Row],[Ppto. Capex '[DOP']]]+PPto[[#This Row],[Ppto. OI '[DOP']2]] -> 67449917 | J52: =SUM(J53:J59) -> 1070633.6 | K52: =SUM(K53:K59) -> 0 | L52: =PPto[[#This Row],[Ppto. Capex '[USD']]]+PPto[[#This Row],[Ppto. OI '[USD']]] -> 1070633.6
A53: 5.01 | B53: Equipamiento | C53: 5.01 Paneles | D53: 279003.09 | E53: 157500 | G53: =SUMIFS(BD.PD[Ppto. Orden Interna '[DOP']],BD.PD[Pos],PPto[[#This Row],[Part.]],BD.PD[Tipo Ppto],G$19) -> 9989501.8 | H53: =SUMIFS(BD.PD[Ppto. Orden Interna '[DOP']],BD.PD[Pos],PPto[[#This Row],[Part.]],BD.PD[Tipo Ppto],H$19) -> 0 | I53: =PPto[[#This Row],[Ppto. Capex '[DOP']]]+PPto[[#This Row],[Ppto. OI '[DOP']2]] -> 9989501.8 | J53: =SUMIFS(BD.PD[Ppto. Orden Interna '[USD']],BD.PD[Pos],PPto[[#This Row],[Part.]],BD.PD[Tipo Ppto],J$19) -> 158563.52 | K53: =SUMIFS(BD.PD[Ppto. Orden Interna '[USD']],BD.PD[Pos],PPto[[#This Row],[Part.]],BD.PD[Tipo Ppto],K$19) -> 0 | L53: =PPto[[#This Row],[Ppto. Capex '[USD']]]+PPto[[#This Row],[Ppto. OI '[USD']]] -> 158563.52 | M53: Adicionales | N53: =+PPto[[#This Row],[Total '[USD']3]]-PPto[[#This Row],[Total '[USD']2]] -> -1063.52
A54: 5.02 | B54: Equipamiento | C54: 5.02 FRP y Diamond Plate | D54: 51676.037 | E54: 32571.346 | G54: =SUMIFS(BD.PD[Ppto. Orden Interna '[DOP']],BD.PD[Pos],PPto[[#This Row],[Part.]],BD.PD[Tipo Ppto],G$19) -> 1810132.4 | H54: =SUMIFS(BD.PD[Ppto. Orden Interna '[DOP']],BD.PD[Pos],PPto[[#This Row],[Part.]],BD.PD[Tipo Ppto],H$19) -> 0 | I54: =PPto[[#This Row],[Ppto. Capex '[DOP']]]+PPto[[#This Row],[Ppto. OI '[DOP']2]] -> 1810132.4 | J54: =SUMIFS(BD.PD[Ppto. Orden Interna '[USD']],BD.PD[Pos],PPto[[#This Row],[Part.]],BD.PD[Tipo Ppto],J$19) -> 28732.26 | K54: =SUMIFS(BD.PD[Ppto. Orden Interna '[USD']],BD.PD[Pos],PPto[[#This Row],[Part.]],BD.PD[Tipo Ppto],K$19) -> 0 | L54: =PPto[[#This Row],[Ppto. Capex '[USD']]]+PPto[[#This Row],[Ppto. OI '[USD']]] -> 28732.26 | N54: =+PPto[[#This Row],[Total '[USD']3]]-PPto[[#This Row],[Total '[USD']2]] -> 3839.0865
A55: 5.03 | B55: Equipamiento | C55: 5.03 Neveras, Centrales y Evaporadores | D55: 589970.59 | E55: 545308.28 | G55: =SUMIFS(BD.PD[Ppto. Orden Interna '[DOP']],BD.PD[Pos],PPto[[#This Row],[Part.]],BD.PD[Tipo Ppto],G$19) -> 40348896 | H55: =SUMIFS(BD.PD[Ppto. Orden Interna '[DOP']],BD.PD[Pos],PPto[[#This Row],[Part.]],BD.PD[Tipo Ppto],H$19) -> 0 | I55: =PPto[[#This Row],[Ppto. Capex '[DOP']]]+PPto[[#This Row],[Ppto. OI '[DOP']2]] -> 40348896 | J55: =SUMIFS(BD.PD[Ppto. Orden Interna '[USD']],BD.PD[Pos],PPto[[#This Row],[Part.]],BD.PD[Tipo Ppto],J$19) -> 640458.67 | K55: =SUMIFS(BD.PD[Ppto. Orden Interna '[USD']],BD.PD[Pos],PPto[[#This Row],[Part.]],BD.PD[Tipo Ppto],K$19) -> 0 | L55: =PPto[[#This Row],[Ppto. Capex '[USD']]]+PPto[[#This Row],[Ppto. OI '[USD']]] -> 640458.67 | M55: Neveras y centrales R404 | N55: =+PPto[[#This Row],[Total '[USD']3]]-PPto[[#This Row],[Total '[USD']2]] -> -95150.384
A56: 5.04 | B56: Equipamiento | C56: 5.04 Bumpers Mcue/ Rack | D56: 30149.493 | E56: 28768.6 | G56: =SUMIFS(BD.PD[Ppto. Orden Interna '[DOP']],BD.PD[Pos],PPto[[#This Row],[Part.]],BD.PD[Tipo Ppto],G$19) -> 1658065 | H56: =SUMIFS(BD.PD[Ppto. Orden Interna '[DOP']],BD.PD[Pos],PPto[[#This Row],[Part.]],BD.PD[Tipo Ppto],H$19) -> 0 | I56: =PPto[[#This Row],[Ppto. Capex '[DOP']]]+PPto[[#This Row],[Ppto. OI '[DOP']2]] -> 1658065 | J56: =SUMIFS(BD.PD[Ppto. Orden Interna '[USD']],BD.PD[Pos],PPto[[#This Row],[Part.]],BD.PD[Tipo Ppto],J$19) -> 26318.492 | K56: =SUMIFS(BD.PD[Ppto. Orden Interna '[USD']],BD.PD[Pos],PPto[[#This Row],[Part.]],BD.PD[Tipo Ppto],K$19) -> 0 | L56: =PPto[[#This Row],[Ppto. Capex '[USD']]]+PPto[[#This Row],[Ppto. OI '[USD']]] -> 26318.492 | N56: =+PPto[[#This Row],[Total '[USD']3]]-PPto[[#This Row],[Total '[USD']2]] -> 2450.1076
A57: 5.05 | B57: Equipamiento | C57: 5.05 Trameria Cuarto Frio | D57: 34455.645 | E57: 37028.754 | G57: =SUMIFS(BD.PD[Ppto. Orden Interna '[DOP']],BD.PD[Pos],PPto[[#This Row],[Part.]],BD.PD[Tipo Ppto],G$19) -> 1960694.2 | H57: =SUMIFS(BD.PD[Ppto. Orden Interna '[DOP']],BD.PD[Pos],PPto[[#This Row],[Part.]],BD.PD[Tipo Ppto],H$19) -> 0 | I57: =PPto[[#This Row],[Ppto. Capex '[DOP']]]+PPto[[#This Row],[Ppto. OI '[DOP']2]] -> 1960694.2 | J57: =SUMIFS(BD.PD[Ppto. Orden Interna '[USD']],BD.PD[Pos],PPto[[#This Row],[Part.]],BD.PD[Tipo Ppto],J$19) -> 31122.13 | K57: =SUMIFS(BD.PD[Ppto. Orden Interna '[USD']],BD.PD[Pos],PPto[[#This Row],[Part.]],BD.PD[Tipo Ppto],K$19) -> 0 | L57: =PPto[[#This Row],[Ppto. Capex '[USD']]]+PPto[[#This Row],[Ppto. OI '[USD']]] -> 31122.13 | N57: =+PPto[[#This Row],[Total '[USD']3]]-PPto[[#This Row],[Total '[USD']2]] -> 5906.6235
A58: 5.06 | B58: Equipamiento | C58: 5.06 Instalacion Frio Alimentario | D58: 170833.33 | E58: 168492.01 | G58: =SUMIFS(BD.PD[Ppto. Orden Interna '[DOP']],BD.PD[Pos],PPto[[#This Row],[Part.]],BD.PD[Tipo Ppto],G$19) -> 8254359.2 | H58: =SUMIFS(BD.PD[Ppto. Orden Interna '[DOP']],BD.PD[Pos],PPto[[#This Row],[Part.]],BD.PD[Tipo Ppto],H$19) -> 0 | I58: =PPto[[#This Row],[Ppto. Capex '[DOP']]]+PPto[[#This Row],[Ppto. OI '[DOP']2]] -> 8254359.2 | J58: =SUMIFS(BD.PD[Ppto. Orden Interna '[USD']],BD.PD[Pos],PPto[[#This Row],[Part.]],BD.PD[Tipo Ppto],J$19) -> 131021.58 | K58: =SUMIFS(BD.PD[Ppto. Orden Interna '[USD']],BD.PD[Pos],PPto[[#This Row],[Part.]],BD.PD[Tipo Ppto],K$19) -> 0 | L58: =PPto[[#This Row],[Ppto. Capex '[USD']]]+PPto[[#This Row],[Ppto. OI '[USD']]] -> 131021.58 | N58: =+PPto[[#This Row],[Total '[USD']3]]-PPto[[#This Row],[Total '[USD']2]] -> 37470.438
A59: 5.07 | B59: Equipamiento | C59: 5.07 Chase Doors | D59: 33536.25 | E59: 73693.435 | G59: =SUMIFS(BD.PD[Ppto. Orden Interna '[DOP']],BD.PD[Pos],PPto[[#This Row],[Part.]],BD.PD[Tipo Ppto],G$19) -> 3428267.8 | H59: =SUMIFS(BD.PD[Ppto. Orden Interna '[DOP']],BD.PD[Pos],PPto[[#This Row],[Part.]],BD.PD[Tipo Ppto],H$19) -> 0 | I59: =PPto[[#This Row],[Ppto. Capex '[DOP']]]+PPto[[#This Row],[Ppto. OI '[DOP']2]] -> 3428267.8 | J59: =SUMIFS(BD.PD[Ppto. Orden Interna '[USD']],BD.PD[Pos],PPto[[#This Row],[Part.]],BD.PD[Tipo Ppto],J$19) -> 54416.95 | K59: =SUMIFS(BD.PD[Ppto. Orden Interna '[USD']],BD.PD[Pos],PPto[[#This Row],[Part.]],BD.PD[Tipo Ppto],K$19) -> 0 | L59: =PPto[[#This Row],[Ppto. Capex '[USD']]]+PPto[[#This Row],[Ppto. OI '[USD']]] -> 54416.95 | N59: =+PPto[[#This Row],[Total '[USD']3]]-PPto[[#This Row],[Total '[USD']2]] -> 19276.485
A60: 6 | C60: 6.00 Tecnología, Seguridad y Tesorería | D60: =SUM(D61:D65) -> 35818.001 | E60: =SUM(E61:E65) -> 38430.065 | G60: =SUM(G61:G65) -> 2381525.7 | H60: =SUM(H61:H65) -> 0 | I60: =PPto[[#This Row],[Ppto. Capex '[DOP']]]+PPto[[#This Row],[Ppto. OI '[DOP']2]] -> 2381525.7 | J60: =SUM(J61:J65) -> 37801.996 | K60: =SUM(K61:K65) -> 0 | L60: =PPto[[#This Row],[Ppto. Capex '[USD']]]+PPto[[#This Row],[Ppto. OI '[USD']]] -> 37801.996
A61: 6.01 | B61: Equipamiento | C61: 6.01 Sistema de cámaras CCTV | D61: 0 | E61: 0 | G61: =SUMIFS(BD.PD[Ppto. Orden Interna '[DOP']],BD.PD[Pos],PPto[[#This Row],[Part.]],BD.PD[Tipo Ppto],G$19) -> 0 | H61: =SUMIFS(BD.PD[Ppto. Orden Interna '[DOP']],BD.PD[Pos],PPto[[#This Row],[Part.]],BD.PD[Tipo Ppto],H$19) -> 0 | I61: =PPto[[#This Row],[Ppto. Capex '[DOP']]]+PPto[[#This Row],[Ppto. OI '[DOP']2]] -> 0 | J61: =SUMIFS(BD.PD[Ppto. Orden Interna '[USD']],BD.PD[Pos],PPto[[#This Row],[Part.]],BD.PD[Tipo Ppto],J$19) -> 0 | K61: =SUMIFS(BD.PD[Ppto. Orden Interna '[USD']],BD.PD[Pos],PPto[[#This Row],[Part.]],BD.PD[Tipo Ppto],K$19) -> 0 | L61: =PPto[[#This Row],[Ppto. Capex '[USD']]]+PPto[[#This Row],[Ppto. OI '[USD']]] -> 0 | N61: =+PPto[[#This Row],[Total '[USD']3]]-PPto[[#This Row],[Total '[USD']2]] -> 0
A62: 6.02 | B62: Equipamiento | C62: 6.02 Antenas detección de robo | D62: 0 | E62: 0 | G62: =SUMIFS(BD.PD[Ppto. Orden Interna '[DOP']],BD.PD[Pos],PPto[[#This Row],[Part.]],BD.PD[Tipo Ppto],G$19) -> 0 | H62: =SUMIFS(BD.PD[Ppto. Orden Interna '[DOP']],BD.PD[Pos],PPto[[#This Row],[Part.]],BD.PD[Tipo Ppto],H$19) -> 0 | I62: =PPto[[#This Row],[Ppto. Capex '[DOP']]]+PPto[[#This Row],[Ppto. OI '[DOP']2]] -> 0 | J62: =SUMIFS(BD.PD[Ppto. Orden Interna '[USD']],BD.PD[Pos],PPto[[#This Row],[Part.]],BD.PD[Tipo Ppto],J$19) -> 0 | K62: =SUMIFS(BD.PD[Ppto. Orden Interna '[USD']],BD.PD[Pos],PPto[[#This Row],[Part.]],BD.PD[Tipo Ppto],K$19) -> 0 | L62: =PPto[[#This Row],[Ppto. Capex '[USD']]]+PPto[[#This Row],[Ppto. OI '[USD']]] -> 0 | N62: =+PPto[[#This Row],[Total '[USD']3]]-PPto[[#This Row],[Total '[USD']2]] -> 0
A63: 6.03 | B63: Equipamiento | C63: 6.03 Puntos de Venta | D63: 0 | E63: 0 | G63: =SUMIFS(BD.PD[Ppto. Orden Interna '[DOP']],BD.PD[Pos],PPto[[#This Row],[Part.]],BD.PD[Tipo Ppto],G$19) -> 0 | H63: =SUMIFS(BD.PD[Ppto. Orden Interna '[DOP']],BD.PD[Pos],PPto[[#This Row],[Part.]],BD.PD[Tipo Ppto],H$19) -> 0 | I63: =PPto[[#This Row],[Ppto. Capex '[DOP']]]+PPto[[#This Row],[Ppto. OI '[DOP']2]] -> 0 | J63: =SUMIFS(BD.PD[Ppto. Orden Interna '[USD']],BD.PD[Pos],PPto[[#This Row],[Part.]],BD.PD[Tipo Ppto],J$19) -> 0 | K63: =SUMIFS(BD.PD[Ppto. Orden Interna '[USD']],BD.PD[Pos],PPto[[#This Row],[Part.]],BD.PD[Tipo Ppto],K$19) -> 0 | L63: =PPto[[#This Row],[Ppto. Capex '[USD']]]+PPto[[#This Row],[Ppto. OI '[USD']]] -> 0 | N63: =+PPto[[#This Row],[Total '[USD']3]]-PPto[[#This Row],[Total '[USD']2]] -> 0
A64: 6.04 | B64: Equipamiento | C64: 6.04 Instalación de data y voz / Antenas de techo | D64: 0 | E64: 0 | G64: =SUMIFS(BD.PD[Ppto. Orden Interna '[DOP']],BD.PD[Pos],PPto[[#This Row],[Part.]],BD.PD[Tipo Ppto],G$19) -> 0 | H64: =SUMIFS(BD.PD[Ppto. Orden Interna '[DOP']],BD.PD[Pos],PPto[[#This Row],[Part.]],BD.PD[Tipo Ppto],H$19) -> 0 | I64: =PPto[[#This Row],[Ppto. Capex '[DOP']]]+PPto[[#This Row],[Ppto. OI '[DOP']2]] -> 0 | J64: =SUMIFS(BD.PD[Ppto. Orden Interna '[USD']],BD.PD[Pos],PPto[[#This Row],[Part.]],BD.PD[Tipo Ppto],J$19) -> 0 | K64: =SUMIFS(BD.PD[Ppto. Orden Interna '[USD']],BD.PD[Pos],PPto[[#This Row],[Part.]],BD.PD[Tipo Ppto],K$19) -> 0 | L64: =PPto[[#This Row],[Ppto. Capex '[USD']]]+PPto[[#This Row],[Ppto. OI '[USD']]] -> 0 | N64: =+PPto[[#This Row],[Total '[USD']3]]-PPto[[#This Row],[Total '[USD']2]] -> 0
A65: 6.05 | B65: Equipamiento | C65: 6.05 Otros sum e inst Tecnología y Seguridad Y Tesoreria | D65: 35818.001 | E65: 38430.065 | G65: =SUMIFS(BD.PD[Ppto. Orden Interna '[DOP']],BD.PD[Pos],PPto[[#This Row],[Part.]],BD.PD[Tipo Ppto],G$19) -> 2381525.7 | H65: =SUMIFS(BD.PD[Ppto. Orden Interna '[DOP']],BD.PD[Pos],PPto[[#This Row],[Part.]],BD.PD[Tipo Ppto],H$19) -> 0 | I65: =PPto[[#This Row],[Ppto. Capex '[DOP']]]+PPto[[#This Row],[Ppto. OI '[DOP']2]] -> 2381525.7 | J65: =SUMIFS(BD.PD[Ppto. Orden Interna '[USD']],BD.PD[Pos],PPto[[#This Row],[Part.]],BD.PD[Tipo Ppto],J$19) -> 37801.996 | K65: =SUMIFS(BD.PD[Ppto. Orden Interna '[USD']],BD.PD[Pos],PPto[[#This Row],[Part.]],BD.PD[Tipo Ppto],K$19) -> 0 | L65: =PPto[[#This Row],[Ppto. Capex '[USD']]]+PPto[[#This Row],[Ppto. OI '[USD']]] -> 37801.996 | N65: =+PPto[[#This Row],[Total '[USD']3]]-PPto[[#This Row],[Total '[USD']2]] -> 628.0687
A66: 7 | C66: 7.00 Equipamiento Produccion | D66: =SUM(D67:D73) -> 416815.7 | E66: =SUM(E67:E73) -> 381984.75 | G66: =SUM(G67:G73) -> 22980868 | H66: =SUM(H67:H73) -> 0 | I66: =PPto[[#This Row],[Ppto. Capex '[DOP']]]+PPto[[#This Row],[Ppto. OI '[DOP']2]] -> 22980868 | J66: =SUM(J67:J73) -> 364775.68 | K66: =SUM(K67:K73) -> 0 | L66: =PPto[[#This Row],[Ppto. Capex '[USD']]]+PPto[[#This Row],[Ppto. OI '[USD']]] -> 364775.68 | M66: Adicionales
A67: 7.01 | B67: Equipamiento | C67: 7.01 Equipamiento de Acero Inoxidable | D67: 21337.879 | E67: 30264.521 | G67: =SUMIFS(BD.PD[Ppto. Orden Interna '[DOP']],BD.PD[Pos],PPto[[#This Row],[Part.]],BD.PD[Tipo Ppto],G$19) -> 1279133.7 | H67: =SUMIFS(BD.PD[Ppto. Orden Interna '[DOP']],BD.PD[Pos],PPto[[#This Row],[Part.]],BD.PD[Tipo Ppto],H$19) -> 0 | I67: =PPto[[#This Row],[Ppto. Capex '[DOP']]]+PPto[[#This Row],[Ppto. OI '[DOP']2]] -> 1279133.7 | J67: =SUMIFS(BD.PD[Ppto. Orden Interna '[USD']],BD.PD[Pos],PPto[[#This Row],[Part.]],BD.PD[Tipo Ppto],J$19) -> 20303.71 | K67: =SUMIFS(BD.PD[Ppto. Orden Interna '[USD']],BD.PD[Pos],PPto[[#This Row],[Part.]],BD.PD[Tipo Ppto],K$19) -> 0 | L67: =PPto[[#This Row],[Ppto. Capex '[USD']]]+PPto[[#This Row],[Ppto. OI '[USD']]] -> 20303.71 | N67: =+PPto[[#This Row],[Total '[USD']3]]-PPto[[#This Row],[Total '[USD']2]] -> 9960.8112
A68: 7.02 | B68: Equipamiento | C68: 7.02 Cocina, Patio Comidas y Rostizería | D68: 51651.609 | E68: 65026.095 | G68: =SUMIFS(BD.PD[Ppto. Orden Interna '[DOP']],BD.PD[Pos],PPto[[#This Row],[Part.]],BD.PD[Tipo Ppto],G$19) -> 4069547.5 | H68: =SUMIFS(BD.PD[Ppto. Orden Interna '[DOP']],BD.PD[Pos],PPto[[#This Row],[Part.]],BD.PD[Tipo Ppto],H$19) -> 0 | I68: =PPto[[#This Row],[Ppto. Capex '[DOP']]]+PPto[[#This Row],[Ppto. OI '[DOP']2]] -> 4069547.5 | J68: =SUMIFS(BD.PD[Ppto. Orden Interna '[USD']],BD.PD[Pos],PPto[[#This Row],[Part.]],BD.PD[Tipo Ppto],J$19) -> 64595.991 | K68: =SUMIFS(BD.PD[Ppto. Orden Interna '[USD']],BD.PD[Pos],PPto[[#This Row],[Part.]],BD.PD[Tipo Ppto],K$19) -> 0 | L68: =PPto[[#This Row],[Ppto. Capex '[USD']]]+PPto[[#This Row],[Ppto. OI '[USD']]] -> 64595.991 | M68: 2 Hornos Rarional | N68: =+PPto[[#This Row],[Total '[USD']3]]-PPto[[#This Row],[Total '[USD']2]] -> 430.10356
A69: 7.03 | B69: Equipamiento | C69: 7.03 Equipamiento Carniceria, Pescadería y Delicatesen | D69: 55943.109 | E69: 53605.92 | G69: =SUMIFS(BD.PD[Ppto. Orden Interna '[DOP']],BD.PD[Pos],PPto[[#This Row],[Part.]],BD.PD[Tipo Ppto],G$19) -> 3354018.7 | H69: =SUMIFS(BD.PD[Ppto. Orden Interna '[DOP']],BD.PD[Pos],PPto[[#This Row],[Part.]],BD.PD[Tipo Ppto],H$19) -> 0 | I69: =PPto[[#This Row],[Ppto. Capex '[DOP']]]+PPto[[#This Row],[Ppto. OI '[DOP']2]] -> 3354018.7 | J69: =SUMIFS(BD.PD[Ppto. Orden Interna '[USD']],BD.PD[Pos],PPto[[#This Row],[Part.]],BD.PD[Tipo Ppto],J$19) -> 53238.393 | K69: =SUMIFS(BD.PD[Ppto. Orden Interna '[USD']],BD.PD[Pos],PPto[[#This Row],[Part.]],BD.PD[Tipo Ppto],K$19) -> 0 | L69: =PPto[[#This Row],[Ppto. Capex '[USD']]]+PPto[[#This Row],[Ppto. OI '[USD']]] -> 53238.393 | N69: =+PPto[[#This Row],[Total '[USD']3]]-PPto[[#This Row],[Total '[USD']2]] -> 367.52762
A70: 7.04 | B70: Equipamiento | C70: 7.04 Equipamiento de Panaderia, Reposteria y Rosticería | D70: 212892.01 | E70: 170136.86 | G70: =SUMIFS(BD.PD[Ppto. Orden Interna '[DOP']],BD.PD[Pos],PPto[[#This Row],[Part.]],BD.PD[Tipo Ppto],G$19) -> 10525418 | H70: =SUMIFS(BD.PD[Ppto. Orden Interna '[DOP']],BD.PD[Pos],PPto[[#This Row],[Part.]],BD.PD[Tipo Ppto],H$19) -> 0 | I70: =PPto[[#This Row],[Ppto. Capex '[DOP']]]+PPto[[#This Row],[Ppto. OI '[DOP']2]] -> 10525418 | J70: =SUMIFS(BD.PD[Ppto. Orden Interna '[USD']],BD.PD[Pos],PPto[[#This Row],[Part.]],BD.PD[Tipo Ppto],J$19) -> 167070.12 | K70: =SUMIFS(BD.PD[Ppto. Orden Interna '[USD']],BD.PD[Pos],PPto[[#This Row],[Part.]],BD.PD[Tipo Ppto],K$19) -> 0 | L70: =PPto[[#This Row],[Ppto. Capex '[USD']]]+PPto[[#This Row],[Ppto. OI '[USD']]] -> 167070.12 | M70: Fermentadora y 2 Hornos dobles de pan | N70: =+PPto[[#This Row],[Total '[USD']3]]-PPto[[#This Row],[Total '[USD']2]] -> 3066.7395
A71: 7.05 | B71: Equipamiento | C71: 7.05 Equipamiento de Frutas y Vegetales | D71: 74991.096 | E71: 62951.349 | G71: =SUMIFS(BD.PD[Ppto. Orden Interna '[DOP']],BD.PD[Pos],PPto[[#This Row],[Part.]],BD.PD[Tipo Ppto],G$19) -> 3752749.8 | H71: =SUMIFS(BD.PD[Ppto. Orden Interna '[DOP']],BD.PD[Pos],PPto[[#This Row],[Part.]],BD.PD[Tipo Ppto],H$19) -> 0 | I71: =PPto[[#This Row],[Ppto. Capex '[DOP']]]+PPto[[#This Row],[Ppto. OI '[DOP']2]] -> 3752749.8 | J71: =SUMIFS(BD.PD[Ppto. Orden Interna '[USD']],BD.PD[Pos],PPto[[#This Row],[Part.]],BD.PD[Tipo Ppto],J$19) -> 59567.457 | K71: =SUMIFS(BD.PD[Ppto. Orden Interna '[USD']],BD.PD[Pos],PPto[[#This Row],[Part.]],BD.PD[Tipo Ppto],K$19) -> 0 | L71: =PPto[[#This Row],[Ppto. Capex '[USD']]]+PPto[[#This Row],[Ppto. OI '[USD']]] -> 59567.457 | N71: =+PPto[[#This Row],[Total '[USD']3]]-PPto[[#This Row],[Total '[USD']2]] -> 3383.8923
A72: 7.06 | B72: Equipamiento | C72: 7.06 Balanzas | D72: 0 | E72: =PPto[[#This Row],[Ppto. Capex '[USD']]]+PPto[[#This Row],[Ppto. OI '[USD']]] -> 0 | G72: =SUMIFS(BD.PD[Ppto. Orden Interna '[DOP']],BD.PD[Pos],PPto[[#This Row],[Part.]],BD.PD[Tipo Ppto],G$19) -> 0 | H72: =SUMIFS(BD.PD[Ppto. Orden Interna '[DOP']],BD.PD[Pos],PPto[[#This Row],[Part.]],BD.PD[Tipo Ppto],H$19) -> 0 | I72: =PPto[[#This Row],[Ppto. Capex '[DOP']]]+PPto[[#This Row],[Ppto. OI '[DOP']2]] -> 0 | J72: =SUMIFS(BD.PD[Ppto. Orden Interna '[USD']],BD.PD[Pos],PPto[[#This Row],[Part.]],BD.PD[Tipo Ppto],J$19) -> 0 | K72: =SUMIFS(BD.PD[Ppto. Orden Interna '[USD']],BD.PD[Pos],PPto[[#This Row],[Part.]],BD.PD[Tipo Ppto],K$19) -> 0 | L72: =PPto[[#This Row],[Ppto. Capex '[USD']]]+PPto[[#This Row],[Ppto. OI '[USD']]] -> 0 | N72: =+PPto[[#This Row],[Total '[USD']3]]-PPto[[#This Row],[Total '[USD']2]] -> 0
A73: 7.07 | B73: Equipamiento | C73: 7.07 Otros Equipamientos de Producción | D73: 0 | E73: =PPto[[#This Row],[Ppto. Capex '[USD']]]+PPto[[#This Row],[Ppto. OI '[USD']]] -> 0 | G73: =SUMIFS(BD.PD[Ppto. Orden Interna '[DOP']],BD.PD[Pos],PPto[[#This Row],[Part.]],BD.PD[Tipo Ppto],G$19) -> 0 | H73: =SUMIFS(BD.PD[Ppto. Orden Interna '[DOP']],BD.PD[Pos],PPto[[#This Row],[Part.]],BD.PD[Tipo Ppto],H$19) -> 0 | I73: =PPto[[#This Row],[Ppto. Capex '[DOP']]]+PPto[[#This Row],[Ppto. OI '[DOP']2]] -> 0 | J73: =SUMIFS(BD.PD[Ppto. Orden Interna '[USD']],BD.PD[Pos],PPto[[#This Row],[Part.]],BD.PD[Tipo Ppto],J$19) -> 0 | K73: =SUMIFS(BD.PD[Ppto. Orden Interna '[USD']],BD.PD[Pos],PPto[[#This Row],[Part.]],BD.PD[Tipo Ppto],K$19) -> 0 | L73: =PPto[[#This Row],[Ppto. Capex '[USD']]]+PPto[[#This Row],[Ppto. OI '[USD']]] -> 0 | N73: =+PPto[[#This Row],[Total '[USD']3]]-PPto[[#This Row],[Total '[USD']2]] -> 0
A74: 8 | C74: 8.00 Equipamiento Tienda | D74: =SUM(D75:D82) -> 1095114.4 | E74: =SUM(E75:E82) -> 809711.72 | G74: =SUM(G75:G82) -> 39914085 | H74: =SUM(H75:H82) -> 0 | I74: =PPto[[#This Row],[Ppto. Capex '[DOP']]]+PPto[[#This Row],[Ppto. OI '[DOP']2]] -> 39914085 | J74: =SUM(J75:J82) -> 633556.9 | K74: =SUM(K75:K82) -> 0 | L74: =PPto[[#This Row],[Ppto. Capex '[USD']]]+PPto[[#This Row],[Ppto. OI '[USD']]] -> 633556.9
A75: 8.01 | B75: Equipamiento | C75: 8.01 Gondolas | D75: 599762.98 | E75: 355289 | G75: =SUMIFS(BD.PD[Ppto. Orden Interna '[DOP']],BD.PD[Pos],PPto[[#This Row],[Part.]],BD.PD[Tipo Ppto],G$19) -> 13583578 | H75: =SUMIFS(BD.PD[Ppto. Orden Interna '[DOP']],BD.PD[Pos],PPto[[#This Row],[Part.]],BD.PD[Tipo Ppto],H$19) -> 0 | I75: =PPto[[#This Row],[Ppto. Capex '[DOP']]]+PPto[[#This Row],[Ppto. OI '[DOP']2]] -> 13583578 | J75: =SUMIFS(BD.PD[Ppto. Orden Interna '[USD']],BD.PD[Pos],PPto[[#This Row],[Part.]],BD.PD[Tipo Ppto],J$19) -> 215612.35 | K75: =SUMIFS(BD.PD[Ppto. Orden Interna '[USD']],BD.PD[Pos],PPto[[#This Row],[Part.]],BD.PD[Tipo Ppto],K$19) -> 0 | L75: =PPto[[#This Row],[Ppto. Capex '[USD']]]+PPto[[#This Row],[Ppto. OI '[USD']]] -> 215612.35 | N75: =+PPto[[#This Row],[Total '[USD']3]]-PPto[[#This Row],[Total '[USD']2]] -> 139676.65
A76: 8.02 | B76: Equipamiento | C76: 8.02 Checkout | D76: 83931.609 | E76: 48231.141 | G76: =SUMIFS(BD.PD[Ppto. Orden Interna '[DOP']],BD.PD[Pos],PPto[[#This Row],[Part.]],BD.PD[Tipo Ppto],G$19) -> 2389277.3 | H76: =SUMIFS(BD.PD[Ppto. Orden Interna '[DOP']],BD.PD[Pos],PPto[[#This Row],[Part.]],BD.PD[Tipo Ppto],H$19) -> 0 | I76: =PPto[[#This Row],[Ppto. Capex '[DOP']]]+PPto[[#This Row],[Ppto. OI '[DOP']2]] -> 2389277.3 | J76: =SUMIFS(BD.PD[Ppto. Orden Interna '[USD']],BD.PD[Pos],PPto[[#This Row],[Part.]],BD.PD[Tipo Ppto],J$19) -> 37925.037 | K76: =SUMIFS(BD.PD[Ppto. Orden Interna '[USD']],BD.PD[Pos],PPto[[#This Row],[Part.]],BD.PD[Tipo Ppto],K$19) -> 0 | L76: =PPto[[#This Row],[Ppto. Capex '[USD']]]+PPto[[#This Row],[Ppto. OI '[USD']]] -> 37925.037 | M76: 12 und | N76: =+PPto[[#This Row],[Total '[USD']3]]-PPto[[#This Row],[Total '[USD']2]] -> 10306.104
A77: 8.03 | B77: Equipamiento | C77: 8.03 Carritos, Canastas y Accesorios | D77: 48527.703 | E77: 46512.175 | G77: =SUMIFS(BD.PD[Ppto. Orden Interna '[DOP']],BD.PD[Pos],PPto[[#This Row],[Part.]],BD.PD[Tipo Ppto],G$19) -> 2911662.2 | H77: =SUMIFS(BD.PD[Ppto. Orden Interna '[DOP']],BD.PD[Pos],PPto[[#This Row],[Part.]],BD.PD[Tipo Ppto],H$19) -> 0 | I77: =PPto[[#This Row],[Ppto. Capex '[DOP']]]+PPto[[#This Row],[Ppto. OI '[DOP']2]] -> 2911662.2 | J77: =SUMIFS(BD.PD[Ppto. Orden Interna '[USD']],BD.PD[Pos],PPto[[#This Row],[Part.]],BD.PD[Tipo Ppto],J$19) -> 46216.86 | K77: =SUMIFS(BD.PD[Ppto. Orden Interna '[USD']],BD.PD[Pos],PPto[[#This Row],[Part.]],BD.PD[Tipo Ppto],K$19) -> 0 | L77: =PPto[[#This Row],[Ppto. Capex '[USD']]]+PPto[[#This Row],[Ppto. OI '[USD']]] -> 46216.86 | N77: =+PPto[[#This Row],[Total '[USD']3]]-PPto[[#This Row],[Total '[USD']2]] -> 295.3154
A78: 8.04 | B78: Equipamiento | C78: 8.04 Trameria Almacen | D78: 54383.795 | E78: 23083.51 | G78: =SUMIFS(BD.PD[Ppto. Orden Interna '[DOP']],BD.PD[Pos],PPto[[#This Row],[Part.]],BD.PD[Tipo Ppto],G$19) -> 969778.33 | H78: =SUMIFS(BD.PD[Ppto. Orden Interna '[DOP']],BD.PD[Pos],PPto[[#This Row],[Part.]],BD.PD[Tipo Ppto],H$19) -> 0 | I78: =PPto[[#This Row],[Ppto. Capex '[DOP']]]+PPto[[#This Row],[Ppto. OI '[DOP']2]] -> 969778.33 | J78: =SUMIFS(BD.PD[Ppto. Orden Interna '[USD']],BD.PD[Pos],PPto[[#This Row],[Part.]],BD.PD[Tipo Ppto],J$19) -> 15393.307 | K78: =SUMIFS(BD.PD[Ppto. Orden Interna '[USD']],BD.PD[Pos],PPto[[#This Row],[Part.]],BD.PD[Tipo Ppto],K$19) -> 0 | L78: =PPto[[#This Row],[Ppto. Capex '[USD']]]+PPto[[#This Row],[Ppto. OI '[USD']]] -> 15393.307 | N78: =+PPto[[#This Row],[Total '[USD']3]]-PPto[[#This Row],[Total '[USD']2]] -> 7690.2027
A79: 8.05 | B79: Equipamiento | C79: 8.05 Mobiliario no operacional para Tiendas | D79: 96620.274 | E79: 106439.12 | G79: =SUMIFS(BD.PD[Ppto. Orden Interna '[DOP']],BD.PD[Pos],PPto[[#This Row],[Part.]],BD.PD[Tipo Ppto],G$19) -> 5077430.7 | H79: =SUMIFS(BD.PD[Ppto. Orden Interna '[DOP']],BD.PD[Pos],PPto[[#This Row],[Part.]],BD.PD[Tipo Ppto],H$19) -> 0 | I79: =PPto[[#This Row],[Ppto. Capex '[DOP']]]+PPto[[#This Row],[Ppto. OI '[DOP']2]] -> 5077430.7 | J79: =SUMIFS(BD.PD[Ppto. Orden Interna '[USD']],BD.PD[Pos],PPto[[#This Row],[Part.]],BD.PD[Tipo Ppto],J$19) -> 80594.138 | K79: =SUMIFS(BD.PD[Ppto. Orden Interna '[USD']],BD.PD[Pos],PPto[[#This Row],[Part.]],BD.PD[Tipo Ppto],K$19) -> 0 | L79: =PPto[[#This Row],[Ppto. Capex '[USD']]]+PPto[[#This Row],[Ppto. OI '[USD']]] -> 80594.138 | M79: Se estan considerando los mobiliarios de Food Cord | N79: =+PPto[[#This Row],[Total '[USD']3]]-PPto[[#This Row],[Total '[USD']2]] -> 25844.983
A80: 8.06 | B80: Equipamiento | C80: 8.06 Otros Equipamientos de Tienda | D80: 19588.978 | E80: 44550.663 | G80: =SUMIFS(BD.PD[Ppto. Orden Interna '[DOP']],BD.PD[Pos],PPto[[#This Row],[Part.]],BD.PD[Tipo Ppto],G$19) -> 2445041.3 | H80: =SUMIFS(BD.PD[Ppto. Orden Interna '[DOP']],BD.PD[Pos],PPto[[#This Row],[Part.]],BD.PD[Tipo Ppto],H$19) -> 0 | I80: =PPto[[#This Row],[Ppto. Capex '[DOP']]]+PPto[[#This Row],[Ppto. OI '[DOP']2]] -> 2445041.3 | J80: =SUMIFS(BD.PD[Ppto. Orden Interna '[USD']],BD.PD[Pos],PPto[[#This Row],[Part.]],BD.PD[Tipo Ppto],J$19) -> 38810.179 | K80: =SUMIFS(BD.PD[Ppto. Orden Interna '[USD']],BD.PD[Pos],PPto[[#This Row],[Part.]],BD.PD[Tipo Ppto],K$19) -> 0 | L80: =PPto[[#This Row],[Ppto. Capex '[USD']]]+PPto[[#This Row],[Ppto. OI '[USD']]] -> 38810.179 | N80: =+PPto[[#This Row],[Total '[USD']3]]-PPto[[#This Row],[Total '[USD']2]] -> 5740.4839
A81: 8.07 | B81: Equipamiento | C81: 8.07 Señalizacion interiores | D81: 113999.04 | E81: 123730.71 | G81: =SUMIFS(BD.PD[Ppto. Orden Interna '[DOP']],BD.PD[Pos],PPto[[#This Row],[Part.]],BD.PD[Tipo Ppto],G$19) -> 7718195.2 | H81: =SUMIFS(BD.PD[Ppto. Orden Interna '[DOP']],BD.PD[Pos],PPto[[#This Row],[Part.]],BD.PD[Tipo Ppto],H$19) -> 0 | I81: =PPto[[#This Row],[Ppto. Capex '[DOP']]]+PPto[[#This Row],[Ppto. OI '[DOP']2]] -> 7718195.2 | J81: =SUMIFS(BD.PD[Ppto. Orden Interna '[USD']],BD.PD[Pos],PPto[[#This Row],[Part.]],BD.PD[Tipo Ppto],J$19) -> 122511.03 | K81: =SUMIFS(BD.PD[Ppto. Orden Interna '[USD']],BD.PD[Pos],PPto[[#This Row],[Part.]],BD.PD[Tipo Ppto],K$19) -> 0 | L81: =PPto[[#This Row],[Ppto. Capex '[USD']]]+PPto[[#This Row],[Ppto. OI '[USD']]] -> 122511.03 | N81: =+PPto[[#This Row],[Total '[USD']3]]-PPto[[#This Row],[Total '[USD']2]] -> 1219.6751
A82: 8.08 | B82: Equipamiento | C82: 8.08 Señalizacion exteriores | D82: 78300 | E82: 61875.399 | G82: =SUMIFS(BD.PD[Ppto. Orden Interna '[DOP']],BD.PD[Pos],PPto[[#This Row],[Part.]],BD.PD[Tipo Ppto],G$19) -> 4819122 | H82: =SUMIFS(BD.PD[Ppto. Orden Interna '[DOP']],BD.PD[Pos],PPto[[#This Row],[Part.]],BD.PD[Tipo Ppto],H$19) -> 0 | I82: =PPto[[#This Row],[Ppto. Capex '[DOP']]]+PPto[[#This Row],[Ppto. OI '[DOP']2]] -> 4819122 | J82: =SUMIFS(BD.PD[Ppto. Orden Interna '[USD']],BD.PD[Pos],PPto[[#This Row],[Part.]],BD.PD[Tipo Ppto],J$19) -> 76494 | K82: =SUMIFS(BD.PD[Ppto. Orden Interna '[USD']],BD.PD[Pos],PPto[[#This Row],[Part.]],BD.PD[Tipo Ppto],K$19) -> 0 | L82: =PPto[[#This Row],[Ppto. Capex '[USD']]]+PPto[[#This Row],[Ppto. OI '[USD']]] -> 76494 | N82: =+PPto[[#This Row],[Total '[USD']3]]-PPto[[#This Row],[Total '[USD']2]] -> -14618.601
A83: 9 | C83: 9.00 Otros | D83: =SUM(D84:D89) -> 0 | E83: =SUM(E84:E89) -> 0 | G83: =SUM(G84:G89) -> 0 | H83: =SUM(H84:H89) -> 0 | I83: =PPto[[#This Row],[Ppto. Capex '[DOP']]]+PPto[[#This Row],[Ppto. OI '[DOP']2]] -> 0 | J83: =SUM(J84:J89) -> 0 | K83: =SUM(K84:K89) -> 0 | L83: =PPto[[#This Row],[Ppto. Capex '[USD']]]+PPto[[#This Row],[Ppto. OI '[USD']]] -> 0 | N83: =+PPto[[#This Row],[Total '[USD']3]]-PPto[[#This Row],[Total '[USD']2]] -> 0
A84: 9.01 | B84: Gasto | C84: 9.01 COMERCIALIZACION | D84: =SUM(D85:D91) -> 0 | E84: =SUM(E85:E91) -> 0 | G84: =SUMIFS(BD.PD[Ppto. Orden Interna '[DOP']],BD.PD[Pos],PPto[[#This Row],[Part.]],BD.PD[Tipo Ppto],G$19) -> 0 | H84: =SUMIFS(BD.PD[Ppto. Orden Interna '[DOP']],BD.PD[Pos],PPto[[#This Row],[Part.]],BD.PD[Tipo Ppto],H$19) -> 0 | I84: =PPto[[#This Row],[Ppto. Capex '[DOP']]]+PPto[[#This Row],[Ppto. OI '[DOP']2]] -> 0 | J84: =SUMIFS(BD.PD[Ppto. Orden Interna '[USD']],BD.PD[Pos],PPto[[#This Row],[Part.]],BD.PD[Tipo Ppto],J$19) -> 0 | K84: =SUMIFS(BD.PD[Ppto. Orden Interna '[USD']],BD.PD[Pos],PPto[[#This Row],[Part.]],BD.PD[Tipo Ppto],K$19) -> 0 | L84: =PPto[[#This Row],[Ppto. Capex '[USD']]]+PPto[[#This Row],[Ppto. OI '[USD']]] -> 0 | N84: =+PPto[[#This Row],[Total '[USD']3]]-PPto[[#This Row],[Total '[USD']2]] -> 0
A85: 9.02 | B85: Gasto | C85: 9.02 INSUMOS | D85: =SUM(D86:D92) -> 0 | E85: =SUM(E86:E92) -> 0 | G85: =SUMIFS(BD.PD[Ppto. Orden Interna '[DOP']],BD.PD[Pos],PPto[[#This Row],[Part.]],BD.PD[Tipo Ppto],G$19) -> 0 | H85: =SUMIFS(BD.PD[Ppto. Orden Interna '[DOP']],BD.PD[Pos],PPto[[#This Row],[Part.]],BD.PD[Tipo Ppto],H$19) -> 0 | I85: =PPto[[#This Row],[Ppto. Capex '[DOP']]]+PPto[[#This Row],[Ppto. OI '[DOP']2]] -> 0 | J85: =SUMIFS(BD.PD[Ppto. Orden Interna '[USD']],BD.PD[Pos],PPto[[#This Row],[Part.]],BD.PD[Tipo Ppto],J$19) -> 0 | K85: =SUMIFS(BD.PD[Ppto. Orden Interna '[USD']],BD.PD[Pos],PPto[[#This Row],[Part.]],BD.PD[Tipo Ppto],K$19) -> 0 | L85: =PPto[[#This Row],[Ppto. Capex '[USD']]]+PPto[[#This Row],[Ppto. OI '[USD']]] -> 0 | N85: =+PPto[[#This Row],[Total '[USD']3]]-PPto[[#This Row],[Total '[USD']2]] -> 0
A86: 9.03 | B86: Gasto | C86: 9.03 PUBLICIDAD Y MERCADEO | D86: =SUM(D87:D93) -> 0 | E86: =SUM(E87:E93) -> 0 | G86: =SUMIFS(BD.PD[Ppto. Orden Interna '[DOP']],BD.PD[Pos],PPto[[#This Row],[Part.]],BD.PD[Tipo Ppto],G$19) -> 0 | H86: =SUMIFS(BD.PD[Ppto. Orden Interna '[DOP']],BD.PD[Pos],PPto[[#This Row],[Part.]],BD.PD[Tipo Ppto],H$19) -> 0 | I86: =PPto[[#This Row],[Ppto. Capex '[DOP']]]+PPto[[#This Row],[Ppto. OI '[DOP']2]] -> 0 | J86: =SUMIFS(BD.PD[Ppto. Orden Interna '[USD']],BD.PD[Pos],PPto[[#This Row],[Part.]],BD.PD[Tipo Ppto],J$19) -> 0 | K86: =SUMIFS(BD.PD[Ppto. Orden Interna '[USD']],BD.PD[Pos],PPto[[#This Row],[Part.]],BD.PD[Tipo Ppto],K$19) -> 0 | L86: =PPto[[#This Row],[Ppto. Capex '[USD']]]+PPto[[#This Row],[Ppto. OI '[USD']]] -> 0 | N86: =+PPto[[#This Row],[Total '[USD']3]]-PPto[[#This Row],[Total '[USD']2]] -> 0
A87: 9.04 | B87: Gasto | C87: 9.04 MONTAJE | D87: =SUM(D88:D94) -> 0 | E87: =SUM(E88:E94) -> 0 | G87: =SUMIFS(BD.PD[Ppto. Orden Interna '[DOP']],BD.PD[Pos],PPto[[#This Row],[Part.]],BD.PD[Tipo Ppto],G$19) -> 0 | H87: =SUMIFS(BD.PD[Ppto. Orden Interna '[DOP']],BD.PD[Pos],PPto[[#This Row],[Part.]],BD.PD[Tipo Ppto],H$19) -> 0 | I87: =PPto[[#This Row],[Ppto. Capex '[DOP']]]+PPto[[#This Row],[Ppto. OI '[DOP']2]] -> 0 | J87: =SUMIFS(BD.PD[Ppto. Orden Interna '[USD']],BD.PD[Pos],PPto[[#This Row],[Part.]],BD.PD[Tipo Ppto],J$19) -> 0 | K87: =SUMIFS(BD.PD[Ppto. Orden Interna '[USD']],BD.PD[Pos],PPto[[#This Row],[Part.]],BD.PD[Tipo Ppto],K$19) -> 0 | L87: =PPto[[#This Row],[Ppto. Capex '[USD']]]+PPto[[#This Row],[Ppto. OI '[USD']]] -> 0 | N87: =+PPto[[#This Row],[Total '[USD']3]]-PPto[[#This Row],[Total '[USD']2]] -> 0
A88: 9.05 | B88: Gasto | C88: 9.05 DECORACIÓN TEMPORADAS | D88: =SUM(D89:D95) -> 0 | E88: =SUM(E89:E95) -> 0 | G88: =SUMIFS(BD.PD[Ppto. Orden Interna '[DOP']],BD.PD[Pos],PPto[[#This Row],[Part.]],BD.PD[Tipo Ppto],G$19) -> 0 | H88: =SUMIFS(BD.PD[Ppto. Orden Interna '[DOP']],BD.PD[Pos],PPto[[#This Row],[Part.]],BD.PD[Tipo Ppto],H$19) -> 0 | I88: =PPto[[#This Row],[Ppto. Capex '[DOP']]]+PPto[[#This Row],[Ppto. OI '[DOP']2]] -> 0 | J88: =SUMIFS(BD.PD[Ppto. Orden Interna '[USD']],BD.PD[Pos],PPto[[#This Row],[Part.]],BD.PD[Tipo Ppto],J$19) -> 0 | K88: =SUMIFS(BD.PD[Ppto. Orden Interna '[USD']],BD.PD[Pos],PPto[[#This Row],[Part.]],BD.PD[Tipo Ppto],K$19) -> 0 | L88: =PPto[[#This Row],[Ppto. Capex '[USD']]]+PPto[[#This Row],[Ppto. OI '[USD']]] -> 0 | N88: =+PPto[[#This Row],[Total '[USD']3]]-PPto[[#This Row],[Total '[USD']2]] -> 0
A89: 9.06 | B89: Gasto | C89: 9.06 - | D89: =SUM(D90:D96) -> 0 | E89: =SUM(E90:E96) -> 0 | G89: =SUMIFS(BD.PD[Ppto. Orden Interna '[DOP']],BD.PD[Pos],PPto[[#This Row],[Part.]],BD.PD[Tipo Ppto],G$19) -> 0 | H89: =SUMIFS(BD.PD[Ppto. Orden Interna '[DOP']],BD.PD[Pos],PPto[[#This Row],[Part.]],BD.PD[Tipo Ppto],H$19) -> 0 | I89: =PPto[[#This Row],[Ppto. Capex '[DOP']]]+PPto[[#This Row],[Ppto. OI '[DOP']2]] -> 0 | J89: =SUMIFS(BD.PD[Ppto. Orden Interna '[USD']],BD.PD[Pos],PPto[[#This Row],[Part.]],BD.PD[Tipo Ppto],J$19) -> 0 | K89: =SUMIFS(BD.PD[Ppto. Orden Interna '[USD']],BD.PD[Pos],PPto[[#This Row],[Part.]],BD.PD[Tipo Ppto],K$19) -> 0 | L89: =PPto[[#This Row],[Ppto. Capex '[USD']]]+PPto[[#This Row],[Ppto. OI '[USD']]] -> 0 | N89: =+PPto[[#This Row],[Total '[USD']3]]-PPto[[#This Row],[Total '[USD']2]] -> 0

Sheet Hoja1
A3: Etiquetas de fila | B3: Suma de Ppto. Orden Interna [DOP] | C3: Suma de Ppto. Orden Interna [USD] | D3: Suma de Pago 1 | E3: Suma de Pago 2 | F3: Suma de Pago 3 | G3: Suma de Pago 4 | H3: Suma de Pago 5
A4: 2.01 Edificación - Obra Civil | B4: 395146.08 | C4: 6272.16 | D4: 197573.04 | E4: 197573.04 | F4: 0 | G4: 0 | H4: 0
A5: MARAZZI PISO PROGRESS ANTHRACITE 30X60MK | B5: 56758.968 | C5: 900.936 | D5: 28379.484 | E5: 28379.484 | F5: 0 | G5: 0 | H5: 0
A6: MARAZZI RAGNO CONCEPT GRIGIO 30X60CM | B6: 281195.71 | C6: 4463.424 | D6: 140597.86 | E6: 140597.86 | F6: 0 | G6: 0 | H6: 0
A7: MARAZZI REV MATERIKA STR SAT 3D 40X120MM | B7: 57191.4 | C7: 907.8 | D7: 28595.7 | E7: 28595.7 | F7: 0 | G7: 0 | H7: 0
A8: 2.05 Instalaciones Sanitarias | B8: 1071000 | C8: 17000 | D8: 535500 | E8: 535500 | F8: 0 | G8: 0 | H8: 0
A9: SISTEMA DE PURIFICACION DE AGUA COMPLETO | B9: 1071000 | C9: 17000 | D9: 535500 | E9: 535500 | F9: 0 | G9: 0 | H9: 0
A10: 2.06 Instalación de Gas | B10: 363276.8 | C10: 5766.2984 | D10: 181638.4 | E10: 181638.4 | F10: 0 | G10: 0 | H10: 0
A11: SISTEMA DETECCION GAS COCINA | B11: 363276.8 | C11: 5766.2984 | D11: 181638.4 | E11: 181638.4 | F11: 0 | G11: 0 | H11: 0
A12: 2.07 Sistema Contra Incendios | B12: 6895286.1 | C12: 109448.99 | D12: 4089545.3 | E12: 2805740.8 | F12: 0 | G12: 0 | H12: 0
A13: BOMBA SCI 1,500 GPM @145 PSI | B13: 5611481.6 | C13: 89071.136 | D13: 2805740.8 | E13: 2805740.8 | F13: 0 | G13: 0 | H13: 0
A14: COVER PARA EXTINTOR C02 10-20LBS | B14: 7635.6 | C14: 121.2 | D14: 7635.6 | E14: 0 | F14: 0 | G14: 0 | H14: 0
A15: EXTINTOR ABC HALOTRON AGENTE LIMPIO 11LB | B15: 211506.12 | C15: 3357.24 | D15: 211506.12 | E15: 0 | F15: 0 | G15: 0 | H15: 0
... A307: Total general | B307: 1.6632645e+08 | C307: 2640102.4 | D307: 90395093 | E307: 75931357 | F307: 0 | G307: 0 | H307: 0

Sheet Flujo de Caja
D1: 1 | E1: 2 | F1: 3 | G1: 4 | H1: 5 | I1: 6 | J1: 7 | K1: 8 | L1: 9 | M1: 10 | N1: 11 | O1: 12 | P1: 13 | Q1: 14 | R1: 15 | S1: 16 | T1: 17 | U1: 18 | V1: 19 | W1: 20 | X1: 21 | Y1: 22 | Z1: 23 | AA1: 24 | AB1: 25 | AC1: 26 | AD1: 27 | AE1: 28 | AF1: 29 | AG1: 30
AH2: Rojo: La sumatoria de pagos no coincide con Ppto.
B3: Apertura Noviembre 2026 | D3: Flujo de Caja Iniciativa
B4: ='Plan OI'!C1 -> Presupuesto Detallado - Propuesta para Sirena Compacta Mao | D4: Enero | E4: Febrero | F4: Marzo | G4: Abril | H4: Mayo | I4: Junio | J4: Julio | K4: Agosto | L4: Septiembre | M4: Octubre | N4: Noviembre | O4: Diciembre | P4: Enero | Q4: Febrero | R4: Marzo | S4: Abril | T4: Mayo | U4: Junio | V4: Julio | W4: Agosto | X4: Septiembre | Y4: Octubre | Z4: Noviembre | AA4: Diciembre
A5: Part. | B5: Edificación, Instalaciones y Equipamientos | C5: Ppto OI [DOP] | D5: P1 | E5: P2 | F5: P3 | G5: P4 | H5: P5 | I5: P6 | J5: P7 | K5: P8 | L5: P9 | M5: P10 | N5: P11 | O5: P12 | P5: P13 | Q5: P14 | R5: P15 | S5: P16 | T5: P17 | U5: P18 | V5: P19 | W5: P20 | X5: P21 | Y5: P22 | Z5: P23 | AA5: P24 | AB5: P245 | AC5: P246 | AD5: P243 | AE5: P244 | AF5: P242 | AG5: P25 | AH5: Total Ppto.
A6: 1 | B6: =VLOOKUP(Tabla3[[#This Row],[Part.]],PPto[],3,FALSE) -> 1.00 Estudios Preliminares | C6: =SUM(C7:C15) -> 0 | D6: =SUM(D7:D15) -> 0 | E6: =SUM(E7:E15) -> 0 | F6: =SUM(F7:F15) -> 0 | G6: =SUM(G7:G15) -> 0 | H6: =SUM(H7:H15) -> 0 | I6: =SUM(I7:I15) -> 0 | J6: =SUM(J7:J15) -> 0 | ... AA6: =SUM(AA7:AA15) -> 0 | AB6: =SUMIFS(BD.PD[Pago 1],BD.PD[Per.P1],AB$1,BD.PD[Pos],Tabla3[[#This Row],[Part.]])+SUMIFS(BD.PD[Pago 2],BD.PD[Per.P2],AB$1,BD.PD[Pos],Tabla3[[#This Row],[Part.]])+SUMIFS(BD.PD[Pago 3],BD.PD[Per.P3],AB$1,BD.PD[Pos],Tabla3[[#This Row],[Part.]])+SUMIFS(BD.PD[Pago 4],BD.PD[Per.P4],AB$1,BD.PD[Pos],Tabla3[[#This Row],[Part.]])+SUMIFS(BD.PD[Pago 5],BD.PD[Per.P5],AB$1,BD.PD[Pos],Tabla3[[#This Row],[Part.]]) -> 0 | AC6: =SUMIFS(BD.PD[Pago 1],BD.PD[Per.P1],AC$1,BD.PD[Pos],Tabla3[[#This Row],[Part.]])+SUMIFS(BD.PD[Pago 2],BD.PD[Per.P2],AC$1,BD.PD[Pos],Tabla3[[#This Row],[Part.]])+SUMIFS(BD.PD[Pago 3],BD.PD[Per.P3],AC$1,BD.PD[Pos],Tabla3[[#This Row],[Part.]])+SUMIFS(BD.PD[Pago 4],BD.PD[Per.P4],AC$1,BD.PD[Pos],Tabla3[[#This Row],[Part.]])+SUMIFS(BD.PD[Pago 5],BD.PD[Per.P5],AC$1,BD.PD[Pos],Tabla3[[#This Row],[Part.]]) -> 0 | AD6: =SUMIFS(BD.PD[Pago 1],BD.PD[Per.P1],AD$1,BD.PD[Pos],Tabla3[[#This Row],[Part.]])+SUMIFS(BD.PD[Pago 2],BD.PD[Per.P2],AD$1,BD.PD[Pos],Tabla3[[#This Row],[Part.]])+SUMIFS(BD.PD[Pago 3],BD.PD[Per.P3],AD$1,BD.PD[Pos],Tabla3[[#This Row],[Part.]])+SUMIFS(BD.PD[Pago 4],BD.PD[Per.P4],AD$1,BD.PD[Pos],Tabla3[[#This Row],[Part.]])+SUMIFS(BD.PD[Pago 5],BD.PD[Per.P5],AD$1,BD.PD[Pos],Tabla3[[#This Row],[Part.]]) -> 0 | AE6: =SUMIFS(BD.PD[Pago 1],BD.PD[Per.P1],AE$1,BD.PD[Pos],Tabla3[[#This Row],[Part.]])+SUMIFS(BD.PD[Pago 2],BD.PD[Per.P2],AE$1,BD.PD[Pos],Tabla3[[#This Row],[Part.]])+SUMIFS(BD.PD[Pago 3],BD.PD[Per.P3],AE$1,BD.PD[Pos],Tabla3[[#This Row],[Part.]])+SUMIFS(BD.PD[Pago 4],BD.PD[Per.P4],AE$1,BD.PD[Pos],Tabla3[[#This Row],[Part.]])+SUMIFS(BD.PD[Pago 5],BD.PD[Per.P5],AE$1,BD.PD[Pos],Tabla3[[#This Row],[Part.]]) -> 0 | AF6: =SUMIFS(BD.PD[Pago 1],BD.PD[Per.P1],AF$1,BD.PD[Pos],Tabla3[[#This Row],[Part.]])+SUMIFS(BD.PD[Pago 2],BD.PD[Per.P2],AF$1,BD.PD[Pos],Tabla3[[#This Row],[Part.]])+SUMIFS(BD.PD[Pago 3],BD.PD[Per.P3],AF$1,BD.PD[Pos],Tabla3[[#This Row],[Part.]])+SUMIFS(BD.PD[Pago 4],BD.PD[Per.P4],AF$1,BD.PD[Pos],Tabla3[[#This Row],[Part.]])+SUMIFS(BD.PD[Pago 5],BD.PD[Per.P5],AF$1,BD.PD[Pos],Tabla3[[#This Row],[Part.]]) -> 0 | AG6: =SUMIFS(BD.PD[Pago 1],BD.PD[Per.P1],AG$1,BD.PD[Pos],Tabla3[[#This Row],[Part.]])+SUMIFS(BD.PD[Pago 2],BD.PD[Per.P2],AG$1,BD.PD[Pos],Tabla3[[#This Row],[Part.]])+SUMIFS(BD.PD[Pago 3],BD.PD[Per.P3],AG$1,BD.PD[Pos],Tabla3[[#This Row],[Part.]])+SUMIFS(BD.PD[Pago 4],BD.PD[Per.P4],AG$1,BD.PD[Pos],Tabla3[[#This Row],[Part.]])+SUMIFS(BD.PD[Pago 5],BD.PD[Per.P5],AG$1,BD.PD[Pos],Tabla3[[#This Row],[Part.]]) -> 0 | AH6: =SUM(Tabla3[[#This Row],[P1]:[P24]]) -> 0
A7: 1.01 | B7: =VLOOKUP(Tabla3[[#This Row],[Part.]],PPto[],3,FALSE) -> 1.01 Diseño arquitectónico | C7: =SUMIF(BD.PD[Pos],Tabla3[[#This Row],[Part.]],BD.PD[Ppto. Orden Interna '[DOP']]) -> 0 | D7: =SUMIFS(BD.PD[Pago 1],BD.PD[Per.P1],D$1,BD.PD[Pos],Tabla3[[#This Row],[Part.]])+SUMIFS(BD.PD[Pago 2],BD.PD[Per.P2],D$1,BD.PD[Pos],Tabla3[[#This Row],[Part.]])+SUMIFS(BD.PD[Pago 3],BD.PD[Per.P3],D$1,BD.PD[Pos],Tabla3[[#This Row],[Part.]])+SUMIFS(BD.PD[Pago 4],BD.PD[Per.P4],D$1,BD.PD[Pos],Tabla3[[#This Row],[Part.]])+SUMIFS(BD.PD[Pago 5],BD.PD[Per.P5],D$1,BD.PD[Pos],Tabla3[[#This Row],[Part.]]) -> 0 | E7: =SUMIFS(BD.PD[Pago 1],BD.PD[Per.P1],E$1,BD.PD[Pos],Tabla3[[#This Row],[Part.]])+SUMIFS(BD.PD[Pago 2],BD.PD[Per.P2],E$1,BD.PD[Pos],Tabla3[[#This Row],[Part.]])+SUMIFS(BD.PD[Pago 3],BD.PD[Per.P3],E$1,BD.PD[Pos],Tabla3[[#This Row],[Part.]])+SUMIFS(BD.PD[Pago 4],BD.PD[Per.P4],E$1,BD.PD[Pos],Tabla3[[#This Row],[Part.]])+SUMIFS(BD.PD[Pago 5],BD.PD[Per.P5],E$1,BD.PD[Pos],Tabla3[[#This Row],[Part.]]) -> 0 | F7: =SUMIFS(BD.PD[Pago 1],BD.PD[Per.P1],F$1,BD.PD[Pos],Tabla3[[#This Row],[Part.]])+SUMIFS(BD.PD[Pago 2],BD.PD[Per.P2],F$1,BD.PD[Pos],Tabla3[[#This Row],[Part.]])+SUMIFS(BD.PD[Pago 3],BD.PD[Per.P3],F$1,BD.PD[Pos],Tabla3[[#This Row],[Part.]])+SUMIFS(BD.PD[Pago 4],BD.PD[Per.P4],F$1,BD.PD[Pos],Tabla3[[#This Row],[Part.]])+SUMIFS(BD.PD[Pago 5],BD.PD[Per.P5],F$1,BD.PD[Pos],Tabla3[[#This Row],[Part.]]) -> 0 | G7: =SUMIFS(BD.PD[Pago 1],BD.PD[Per.P1],G$1,BD.PD[Pos],Tabla3[[#This Row],[Part.]])+SUMIFS(BD.PD[Pago 2],BD.PD[Per.P2],G$1,BD.PD[Pos],Tabla3[[#This Row],[Part.]])+SUMIFS(BD.PD[Pago 3],BD.PD[Per.P3],G$1,BD.PD[Pos],Tabla3[[#This Row],[Part.]])+SUMIFS(BD.PD[Pago 4],BD.PD[Per.P4],G$1,BD.PD[Pos],Tabla3[[#This Row],[Part.]])+SUMIFS(BD.PD[Pago 5],BD.PD[Per.P5],G$1,BD.PD[Pos],Tabla3[[#This Row],[Part.]]) -> 0 | H7: =SUMIFS(BD.PD[Pago 1],BD.PD[Per.P1],H$1,BD.PD[Pos],Tabla3[[#This Row],[Part.]])+SUMIFS(BD.PD[Pago 2],BD.PD[Per.P2],H$1,BD.PD[Pos],Tabla3[[#This Row],[Part.]])+SUMIFS(BD.PD[Pago 3],BD.PD[Per.P3],H$1,BD.PD[Pos],Tabla3[[#This Row],[Part.]])+SUMIFS(BD.PD[Pago 4],BD.PD[Per.P4],H$1,BD.PD[Pos],Tabla3[[#This Row],[Part.]])+SUMIFS(BD.PD[Pago 5],BD.PD[Per.P5],H$1,BD.PD[Pos],Tabla3[[#This Row],[Part.]]) -> 0 | I7: =SUMIFS(BD.PD[Pago 1],BD.PD[Per.P1],I$1,BD.PD[Pos],Tabla3[[#This Row],[Part.]])+SUMIFS(BD.PD[Pago 2],BD.PD[Per.P2],I$1,BD.PD[Pos],Tabla3[[#This Row],[Part.]])+SUMIFS(BD.PD[Pago 3],BD.PD[Per.P3],I$1,BD.PD[Pos],Tabla3[[#This Row],[Part.]])+SUMIFS(BD.PD[Pago 4],BD.PD[Per.P4],I$1,BD.PD[Pos],Tabla3[[#This Row],[Part.]])+SUMIFS(BD.PD[Pago 5],BD.PD[Per.P5],I$1,BD.PD[Pos],Tabla3[[#This Row],[Part.]]) -> 0 | J7: =SUMIFS(BD.PD[Pago 1],BD.PD[Per.P1],J$1,BD.PD[Pos],Tabla3[[#This Row],[Part.]])+SUMIFS(BD.PD[Pago 2],BD.PD[Per.P2],J$1,BD.PD[Pos],Tabla3[[#This Row],[Part.]])+SUMIFS(BD.PD[Pago 3],BD.PD[Per.P3],J$1,BD.PD[Pos],Tabla3[[#This Row],[Part.]])+SUMIFS(BD.PD[Pago 4],BD.PD[Per.P4],J$1,BD.PD[Pos],Tabla3[[#This Row],[Part.]])+SUMIFS(BD.PD[Pago 5],BD.PD[Per.P5],J$1,BD.PD[Pos],Tabla3[[#This Row],[Part.]]) -> 0 | K7: =SUMIFS(BD.PD[Pago 1],BD.PD[Per.P1],K$1,BD.PD[Pos],Tabla3[[#This Row],[Part.]])+SUMIFS(BD.PD[Pago 2],BD.PD[Per.P2],K$1,BD.PD[Pos],Tabla3[[#This Row],[Part.]])+SUMIFS(BD.PD[Pago 3],BD.PD[Per.P3],K$1,BD.PD[Pos],Tabla3[[#This Row],[Part.]])+SUMIFS(BD.PD[Pago 4],BD.PD[Per.P4],K$1,BD.PD[Pos],Tabla3[[#This Row],[Part.]])+SUMIFS(BD.PD[Pago 5],BD.PD[Per.P5],K$1,BD.PD[Pos],Tabla3[[#This Row],[Part.]]) -> 0 | ... AG7: =SUMIFS(BD.PD[Pago 1],BD.PD[Per.P1],AG$1,BD.PD[Pos],Tabla3[[#This Row],[Part.]])+SUMIFS(BD.PD[Pago 2],BD.PD[Per.P2],AG$1,BD.PD[Pos],Tabla3[[#This Row],[Part.]])+SUMIFS(BD.PD[Pago 3],BD.PD[Per.P3],AG$1,BD.PD[Pos],Tabla3[[#This Row],[Part.]])+SUMIFS(BD.PD[Pago 4],BD.PD[Per.P4],AG$1,BD.PD[Pos],Tabla3[[#This Row],[Part.]])+SUMIFS(BD.PD[Pago 5],BD.PD[Per.P5],AG$1,BD.PD[Pos],Tabla3[[#This Row],[Part.]]) -> 0 | AH7: =SUM(Tabla3[[#This Row],[P1]:[P24]]) -> 0
A8: 1.02 | B8: =VLOOKUP(Tabla3[[#This Row],[Part.]],PPto[],3,FALSE) -> 1.02 Diseño estructural | C8: =SUMIF(BD.PD[Pos],Tabla3[[#This Row],[Part.]],BD.PD[Ppto. Orden Interna '[DOP']]) -> 0 | D8: =SUMIFS(BD.PD[Pago 1],BD.PD[Per.P1],D$1,BD.PD[Pos],Tabla3[[#This Row],[Part.]])+SUMIFS(BD.PD[Pago 2],BD.PD[Per.P2],D$1,BD.PD[Pos],Tabla3[[#This Row],[Part.]])+SUMIFS(BD.PD[Pago 3],BD.PD[Per.P3],D$1,BD.PD[Pos],Tabla3[[#This Row],[Part.]])+SUMIFS(BD.PD[Pago 4],BD.PD[Per.P4],D$1,BD.PD[Pos],Tabla3[[#This Row],[Part.]])+SUMIFS(BD.PD[Pago 5],BD.PD[Per.P5],D$1,BD.PD[Pos],Tabla3[[#This Row],[Part.]]) -> 0 | E8: =SUMIFS(BD.PD[Pago 1],BD.PD[Per.P1],E$1,BD.PD[Pos],Tabla3[[#This Row],[Part.]])+SUMIFS(BD.PD[Pago 2],BD.PD[Per.P2],E$1,BD.PD[Pos],Tabla3[[#This Row],[Part.]])+SUMIFS(BD.PD[Pago 3],BD.PD[Per.P3],E$1,BD.PD[Pos],Tabla3[[#This Row],[Part.]])+SUMIFS(BD.PD[Pago 4],BD.PD[Per.P4],E$1,BD.PD[Pos],Tabla3[[#This Row],[Part.]])+SUMIFS(BD.PD[Pago 5],BD.PD[Per.P5],E$1,BD.PD[Pos],Tabla3[[#This Row],[Part.]]) -> 0 | F8: =SUMIFS(BD.PD[Pago 1],BD.PD[Per.P1],F$1,BD.PD[Pos],Tabla3[[#This Row],[Part.]])+SUMIFS(BD.PD[Pago 2],BD.PD[Per.P2],F$1,BD.PD[Pos],Tabla3[[#This Row],[Part.]])+SUMIFS(BD.PD[Pago 3],BD.PD[Per.P3],F$1,BD.PD[Pos],Tabla3[[#This Row],[Part.]])+SUMIFS(BD.PD[Pago 4],BD.PD[Per.P4],F$1,BD.PD[Pos],Tabla3[[#This Row],[Part.]])+SUMIFS(BD.PD[Pago 5],BD.PD[Per.P5],F$1,BD.PD[Pos],Tabla3[[#This Row],[Part.]]) -> 0 | G8: =SUMIFS(BD.PD[Pago 1],BD.PD[Per.P1],G$1,BD.PD[Pos],Tabla3[[#This Row],[Part.]])+SUMIFS(BD.PD[Pago 2],BD.PD[Per.P2],G$1,BD.PD[Pos],Tabla3[[#This Row],[Part.]])+SUMIFS(BD.PD[Pago 3],BD.PD[Per.P3],G$1,BD.PD[Pos],Tabla3[[#This Row],[Part.]])+SUMIFS(BD.PD[Pago 4],BD.PD[Per.P4],G$1,BD.PD[Pos],Tabla3[[#This Row],[Part.]])+SUMIFS(BD.PD[Pago 5],BD.PD[Per.P5],G$1,BD.PD[Pos],Tabla3[[#This Row],[Part.]]) -> 0 | H8: =SUMIFS(BD.PD[Pago 1],BD.PD[Per.P1],H$1,BD.PD[Pos],Tabla3[[#This Row],[Part.]])+SUMIFS(BD.PD[Pago 2],BD.PD[Per.P2],H$1,BD.PD[Pos],Tabla3[[#This Row],[Part.]])+SUMIFS(BD.PD[Pago 3],BD.PD[Per.P3],H$1,BD.PD[Pos],Tabla3[[#This Row],[Part.]])+SUMIFS(BD.PD[Pago 4],BD.PD[Per.P4],H$1,BD.PD[Pos],Tabla3[[#This Row],[Part.]])+SUMIFS(BD.PD[Pago 5],BD.PD[Per.P5],H$1,BD.PD[Pos],Tabla3[[#This Row],[Part.]]) -> 0 | I8: =SUMIFS(BD.PD[Pago 1],BD.PD[Per.P1],I$1,BD.PD[Pos],Tabla3[[#This Row],[Part.]])+SUMIFS(BD.PD[Pago 2],BD.PD[Per.P2],I$1,BD.PD[Pos],Tabla3[[#This Row],[Part.]])+SUMIFS(BD.PD[Pago 3],BD.PD[Per.P3],I$1,BD.PD[Pos],Tabla3[[#This Row],[Part.]])+SUMIFS(BD.PD[Pago 4],BD.PD[Per.P4],I$1,BD.PD[Pos],Tabla3[[#This Row],[Part.]])+SUMIFS(BD.PD[Pago 5],BD.PD[Per.P5],I$1,BD.PD[Pos],Tabla3[[#This Row],[Part.]]) -> 0 | J8: =SUMIFS(BD.PD[Pago 1],BD.PD[Per.P1],J$1,BD.PD[Pos],Tabla3[[#This Row],[Part.]])+SUMIFS(BD.PD[Pago 2],BD.PD[Per.P2],J$1,BD.PD[Pos],Tabla3[[#This Row],[Part.]])+SUMIFS(BD.PD[Pago 3],BD.PD[Per.P3],J$1,BD.PD[Pos],Tabla3[[#This Row],[Part.]])+SUMIFS(BD.PD[Pago 4],BD.PD[Per.P4],J$1,BD.PD[Pos],Tabla3[[#This Row],[Part.]])+SUMIFS(BD.PD[Pago 5],BD.PD[Per.P5],J$1,BD.PD[Pos],Tabla3[[#This Row],[Part.]]) -> 0 | K8: =SUMIFS(BD.PD[Pago 1],BD.PD[Per.P1],K$1,BD.PD[Pos],Tabla3[[#This Row],[Part.]])+SUMIFS(BD.PD[Pago 2],BD.PD[Per.P2],K$1,BD.PD[Pos],Tabla3[[#This Row],[Part.]])+SUMIFS(BD.PD[Pago 3],BD.PD[Per.P3],K$1,BD.PD[Pos],Tabla3[[#This Row],[Part.]])+SUMIFS(BD.PD[Pago 4],BD.PD[Per.P4],K$1,BD.PD[Pos],Tabla3[[#This Row],[Part.]])+SUMIFS(BD.PD[Pago 5],BD.PD[Per.P5],K$1,BD.PD[Pos],Tabla3[[#This Row],[Part.]]) -> 0 | ... AG8: =SUMIFS(BD.PD[Pago 1],BD.PD[Per.P1],AG$1,BD.PD[Pos],Tabla3[[#This Row],[Part.]])+SUMIFS(BD.PD[Pago 2],BD.PD[Per.P2],AG$1,BD.PD[Pos],Tabla3[[#This Row],[Part.]])+SUMIFS(BD.PD[Pago 3],BD.PD[Per.P3],AG$1,BD.PD[Pos],Tabla3[[#This Row],[Part.]])+SUMIFS(BD.PD[Pago 4],BD.PD[Per.P4],AG$1,BD.PD[Pos],Tabla3[[#This Row],[Part.]])+SUMIFS(BD.PD[Pago 5],BD.PD[Per.P5],AG$1,BD.PD[Pos],Tabla3[[#This Row],[Part.]]) -> 0 | AH8: =SUM(Tabla3[[#This Row],[P1]:[P24]]) -> 0
A9: 1.03 | B9: =VLOOKUP(Tabla3[[#This Row],[Part.]],PPto[],3,FALSE) -> 1.03 Diseño electromecánico | C9: =SUMIF(BD.PD[Pos],Tabla3[[#This Row],[Part.]],BD.PD[Ppto. Orden Interna '[DOP']]) -> 0 | D9: =SUMIFS(BD.PD[Pago 1],BD.PD[Per.P1],D$1,BD.PD[Pos],Tabla3[[#This Row],[Part.]])+SUMIFS(BD.PD[Pago 2],BD.PD[Per.P2],D$1,BD.PD[Pos],Tabla3[[#This Row],[Part.]])+SUMIFS(BD.PD[Pago 3],BD.PD[Per.P3],D$1,BD.PD[Pos],Tabla3[[#This Row],[Part.]])+SUMIFS(BD.PD[Pago 4],BD.PD[Per.P4],D$1,BD.PD[Pos],Tabla3[[#This Row],[Part.]])+SUMIFS(BD.PD[Pago 5],BD.PD[Per.P5],D$1,BD.PD[Pos],Tabla3[[#This Row],[Part.]]) -> 0 | E9: =SUMIFS(BD.PD[Pago 1],BD.PD[Per.P1],E$1,BD.PD[Pos],Tabla3[[#This Row],[Part.]])+SUMIFS(BD.PD[Pago 2],BD.PD[Per.P2],E$1,BD.PD[Pos],Tabla3[[#This Row],[Part.]])+SUMIFS(BD.PD[Pago 3],BD.PD[Per.P3],E$1,BD.PD[Pos],Tabla3[[#This Row],[Part.]])+SUMIFS(BD.PD[Pago 4],BD.PD[Per.P4],E$1,BD.PD[Pos],Tabla3[[#This Row],[Part.]])+SUMIFS(BD.PD[Pago 5],BD.PD[Per.P5],E$1,BD.PD[Pos],Tabla3[[#This Row],[Part.]]) -> 0 | F9: =SUMIFS(BD.PD[Pago 1],BD.PD[Per.P1],F$1,BD.PD[Pos],Tabla3[[#This Row],[Part.]])+SUMIFS(BD.PD[Pago 2],BD.PD[Per.P2],F$1,BD.PD[Pos],Tabla3[[#This Row],[Part.]])+SUMIFS(BD.PD[Pago 3],BD.PD[Per.P3],F$1,BD.PD[Pos],Tabla3[[#This Row],[Part.]])+SUMIFS(BD.PD[Pago 4],BD.PD[Per.P4],F$1,BD.PD[Pos],Tabla3[[#This Row],[Part.]])+SUMIFS(BD.PD[Pago 5],BD.PD[Per.P5],F$1,BD.PD[Pos],Tabla3[[#This Row],[Part.]]) -> 0 | G9: =SUMIFS(BD.PD[Pago 1],BD.PD[Per.P1],G$1,BD.PD[Pos],Tabla3[[#This Row],[Part.]])+SUMIFS(BD.PD[Pago 2],BD.PD[Per.P2],G$1,BD.PD[Pos],Tabla3[[#This Row],[Part.]])+SUMIFS(BD.PD[Pago 3],BD.PD[Per.P3],G$1,BD.PD[Pos],Tabla3[[#This Row],[Part.]])+SUMIFS(BD.PD[Pago 4],BD.PD[Per.P4],G$1,BD.PD[Pos],Tabla3[[#This Row],[Part.]])+SUMIFS(BD.PD[Pago 5],BD.PD[Per.P5],G$1,BD.PD[Pos],Tabla3[[#This Row],[Part.]]) -> 0 | H9: =SUMIFS(BD.PD[Pago 1],BD.PD[Per.P1],H$1,BD.PD[Pos],Tabla3[[#This Row],[Part.]])+SUMIFS(BD.PD[Pago 2],BD.PD[Per.P2],H$1,BD.PD[Pos],Tabla3[[#This Row],[Part.]])+SUMIFS(BD.PD[Pago 3],BD.PD[Per.P3],H$1,BD.PD[Pos],Tabla3[[#This Row],[Part.]])+SUMIFS(BD.PD[Pago 4],BD.PD[Per.P4],H$1,BD.PD[Pos],Tabla3[[#This Row],[Part.]])+SUMIFS(BD.PD[Pago 5],BD.PD[Per.P5],H$1,BD.PD[Pos],Tabla3[[#This Row],[Part.]]) -> 0 | I9: =SUMIFS(BD.PD[Pago 1],BD.PD[Per.P1],I$1,BD.PD[Pos],Tabla3[[#This Row],[Part.]])+SUMIFS(BD.PD[Pago 2],BD.PD[Per.P2],I$1,BD.PD[Pos],Tabla3[[#This Row],[Part.]])+SUMIFS(BD.PD[Pago 3],BD.PD[Per.P3],I$1,BD.PD[Pos],Tabla3[[#This Row],[Part.]])+SUMIFS(BD.PD[Pago 4],BD.PD[Per.P4],I$1,BD.PD[Pos],Tabla3[[#This Row],[Part.]])+SUMIFS(BD.PD[Pago 5],BD.PD[Per.P5],I$1,BD.PD[Pos],Tabla3[[#This Row],[Part.]]) -> 0 | J9: =SUMIFS(BD.PD[Pago 1],BD.PD[Per.P1],J$1,BD.PD[Pos],Tabla3[[#This Row],[Part.]])+SUMIFS(BD.PD[Pago 2],BD.PD[Per.P2],J$1,BD.PD[Pos],Tabla3[[#This Row],[Part.]])+SUMIFS(BD.PD[Pago 3],BD.PD[Per.P3],J$1,BD.PD[Pos],Tabla3[[#This Row],[Part.]])+SUMIFS(BD.PD[Pago 4],BD.PD[Per.P4],J$1,BD.PD[Pos],Tabla3[[#This Row],[Part.]])+SUMIFS(BD.PD[Pago 5],BD.PD[Per.P5],J$1,BD.PD[Pos],Tabla3[[#This Row],[Part.]]) -> 0 | K9: =SUMIFS(BD.PD[Pago 1],BD.PD[Per.P1],K$1,BD.PD[Pos],Tabla3[[#This Row],[Part.]])+SUMIFS(BD.PD[Pago 2],BD.PD[Per.P2],K$1,BD.PD[Pos],Tabla3[[#This Row],[Part.]])+SUMIFS(BD.PD[Pago 3],BD.PD[Per.P3],K$1,BD.PD[Pos],Tabla3[[#This Row],[Part.]])+SUMIFS(BD.PD[Pago 4],BD.PD[Per.P4],K$1,BD.PD[Pos],Tabla3[[#This Row],[Part.]])+SUMIFS(BD.PD[Pago 5],BD.PD[Per.P5],K$1,BD.PD[Pos],Tabla3[[#This Row],[Part.]]) -> 0 | ... AG9: =SUMIFS(BD.PD[Pago 1],BD.PD[Per.P1],AG$1,BD.PD[Pos],Tabla3[[#This Row],[Part.]])+SUMIFS(BD.PD[Pago 2],BD.PD[Per.P2],AG$1,BD.PD[Pos],Tabla3[[#This Row],[Part.]])+SUMIFS(BD.PD[Pago 3],BD.PD[Per.P3],AG$1,BD.PD[Pos],Tabla3[[#This Row],[Part.]])+SUMIFS(BD.PD[Pago 4],BD.PD[Per.P4],AG$1,BD.PD[Pos],Tabla3[[#This Row],[Part.]])+SUMIFS(BD.PD[Pago 5],BD.PD[Per.P5],AG$1,BD.PD[Pos],Tabla3[[#This Row],[Part.]]) -> 0 | AH9: =SUM(Tabla3[[#This Row],[P1]:[P24]]) -> 0
A10: 1.04 | B10: =VLOOKUP(Tabla3[[#This Row],[Part.]],PPto[],3,FALSE) -> 1.04 Diseño sanitario | C10: =SUMIF(BD.PD[Pos],Tabla3[[#This Row],[Part.]],BD.PD[Ppto. Orden Interna '[DOP']]) -> 0 | D10: =SUMIFS(BD.PD[Pago 1],BD.PD[Per.P1],D$1,BD.PD[Pos],Tabla3[[#This Row],[Part.]])+SUMIFS(BD.PD[Pago 2],BD.PD[Per.P2],D$1,BD.PD[Pos],Tabla3[[#This Row],[Part.]])+SUMIFS(BD.PD[Pago 3],BD.PD[Per.P3],D$1,BD.PD[Pos],Tabla3[[#This Row],[Part.]])+SUMIFS(BD.PD[Pago 4],BD.PD[Per.P4],D$1,BD.PD[Pos],Tabla3[[#This Row],[Part.]])+SUMIFS(BD.PD[Pago 5],BD.PD[Per.P5],D$1,BD.PD[Pos],Tabla3[[#This Row],[Part.]]) -> 0 | E10: =SUMIFS(BD.PD[Pago 1],BD.PD[Per.P1],E$1,BD.PD[Pos],Tabla3[[#This Row],[Part.]])+SUMIFS(BD.PD[Pago 2],BD.PD[Per.P2],E$1,BD.PD[Pos],Tabla3[[#This Row],[Part.]])+SUMIFS(BD.PD[Pago 3],BD.PD[Per.P3],E$1,BD.PD[Pos],Tabla3[[#This Row],[Part.]])+SUMIFS(BD.PD[Pago 4],BD.PD[Per.P4],E$1,BD.PD[Pos],Tabla3[[#This Row],[Part.]])+SUMIFS(BD.PD[Pago 5],BD.PD[Per.P5],E$1,BD.PD[Pos],Tabla3[[#This Row],[Part.]]) -> 0 | F10: =SUMIFS(BD.PD[Pago 1],BD.PD[Per.P1],F$1,BD.PD[Pos],Tabla3[[#This Row],[Part.]])+SUMIFS(BD.PD[Pago 2],BD.PD[Per.P2],F$1,BD.PD[Pos],Tabla3[[#This Row],[Part.]])+SUMIFS(BD.PD[Pago 3],BD.PD[Per.P3],F$1,BD.PD[Pos],Tabla3[[#This Row],[Part.]])+SUMIFS(BD.PD[Pago 4],BD.PD[Per.P4],F$1,BD.PD[Pos],Tabla3[[#This Row],[Part.]])+SUMIFS(BD.PD[Pago 5],BD.PD[Per.P5],F$1,BD.PD[Pos],Tabla3[[#This Row],[Part.]]) -> 0 | G10: =SUMIFS(BD.PD[Pago 1],BD.PD[Per.P1],G$1,BD.PD[Pos],Tabla3[[#This Row],[Part.]])+SUMIFS(BD.PD[Pago 2],BD.PD[Per.P2],G$1,BD.PD[Pos],Tabla3[[#This Row],[Part.]])+SUMIFS(BD.PD[Pago 3],BD.PD[Per.P3],G$1,BD.PD[Pos],Tabla3[[#This Row],[Part.]])+SUMIFS(BD.PD[Pago 4],BD.PD[Per.P4],G$1,BD.PD[Pos],Tabla3[[#This Row],[Part.]])+SUMIFS(BD.PD[Pago 5],BD.PD[Per.P5],G$1,BD.PD[Pos],Tabla3[[#This Row],[Part.]]) -> 0 | H10: =SUMIFS(BD.PD[Pago 1],BD.PD[Per.P1],H$1,BD.PD[Pos],Tabla3[[#This Row],[Part.]])+SUMIFS(BD.PD[Pago 2],BD.PD[Per.P2],H$1,BD.PD[Pos],Tabla3[[#This Row],[Part.]])+SUMIFS(BD.PD[Pago 3],BD.PD[Per.P3],H$1,BD.PD[Pos],Tabla3[[#This Row],[Part.]])+SUMIFS(BD.PD[Pago 4],BD.PD[Per.P4],H$1,BD.PD[Pos],Tabla3[[#This Row],[Part.]])+SUMIFS(BD.PD[Pago 5],BD.PD[Per.P5],H$1,BD.PD[Pos],Tabla3[[#This Row],[Part.]]) -> 0 | I10: =SUMIFS(BD.PD[Pago 1],BD.PD[Per.P1],I$1,BD.PD[Pos],Tabla3[[#This Row],[Part.]])+SUMIFS(BD.PD[Pago 2],BD.PD[Per.P2],I$1,BD.PD[Pos],Tabla3[[#This Row],[Part.]])+SUMIFS(BD.PD[Pago 3],BD.PD[Per.P3],I$1,BD.PD[Pos],Tabla3[[#This Row],[Part.]])+SUMIFS(BD.PD[Pago 4],BD.PD[Per.P4],I$1,BD.PD[Pos],Tabla3[[#This Row],[Part.]])+SUMIFS(BD.PD[Pago 5],BD.PD[Per.P5],I$1,BD.PD[Pos],Tabla3[[#This Row],[Part.]]) -> 0 | J10: =SUMIFS(BD.PD[Pago 1],BD.PD[Per.P1],J$1,BD.PD[Pos],Tabla3[[#This Row],[Part.]])+SUMIFS(BD.PD[Pago 2],BD.PD[Per.P2],J$1,BD.PD[Pos],Tabla3[[#This Row],[Part.]])+SUMIFS(BD.PD[Pago 3],BD.PD[Per.P3],J$1,BD.PD[Pos],Tabla3[[#This Row],[Part.]])+SUMIFS(BD.PD[Pago 4],BD.PD[Per.P4],J$1,BD.PD[Pos],Tabla3[[#This Row],[Part.]])+SUMIFS(BD.PD[Pago 5],BD.PD[Per.P5],J$1,BD.PD[Pos],Tabla3[[#This Row],[Part.]]) -> 0 | K10: =SUMIFS(BD.PD[Pago 1],BD.PD[Per.P1],K$1,BD.PD[Pos],Tabla3[[#This Row],[Part.]])+SUMIFS(BD.PD[Pago 2],BD.PD[Per.P2],K$1,BD.PD[Pos],Tabla3[[#This Row],[Part.]])+SUMIFS(BD.PD[Pago 3],BD.PD[Per.P3],K$1,BD.PD[Pos],Tabla3[[#This Row],[Part.]])+SUMIFS(BD.PD[Pago 4],BD.PD[Per.P4],K$1,BD.PD[Pos],Tabla3[[#This Row],[Part.]])+SUMIFS(BD.PD[Pago 5],BD.PD[Per.P5],K$1,BD.PD[Pos],Tabla3[[#This Row],[Part.]]) -> 0 | ... AG10: =SUMIFS(BD.PD[Pago 1],BD.PD[Per.P1],AG$1,BD.PD[Pos],Tabla3[[#This Row],[Part.]])+SUMIFS(BD.PD[Pago 2],BD.PD[Per.P2],AG$1,BD.PD[Pos],Tabla3[[#This Row],[Part.]])+SUMIFS(BD.PD[Pago 3],BD.PD[Per.P3],AG$1,BD.PD[Pos],Tabla3[[#This Row],[Part.]])+SUMIFS(BD.PD[Pago 4],BD.PD[Per.P4],AG$1,BD.PD[Pos],Tabla3[[#This Row],[Part.]])+SUMIFS(BD.PD[Pago 5],BD.PD[Per.P5],AG$1,BD.PD[Pos],Tabla3[[#This Row],[Part.]]) -> 0 | AH10: =SUM(Tabla3[[#This Row],[P1]:[P24]]) -> 0
A11: 1.05 | B11: =VLOOKUP(Tabla3[[#This Row],[Part.]],PPto[],3,FALSE) -> 1.05 Estudio Geotécnico | C11: =SUMIF(BD.PD[Pos],Tabla3[[#This Row],[Part.]],BD.PD[Ppto. Orden Interna '[DOP']]) -> 0 | D11: =SUMIFS(BD.PD[Pago 1],BD.PD[Per.P1],D$1,BD.PD[Pos],Tabla3[[#This Row],[Part.]])+SUMIFS(BD.PD[Pago 2],BD.PD[Per.P2],D$1,BD.PD[Pos],Tabla3[[#This Row],[Part.]])+SUMIFS(BD.PD[Pago 3],BD.PD[Per.P3],D$1,BD.PD[Pos],Tabla3[[#This Row],[Part.]])+SUMIFS(BD.PD[Pago 4],BD.PD[Per.P4],D$1,BD.PD[Pos],Tabla3[[#This Row],[Part.]])+SUMIFS(BD.PD[Pago 5],BD.PD[Per.P5],D$1,BD.PD[Pos],Tabla3[[#This Row],[Part.]]) -> 0 | E11: =SUMIFS(BD.PD[Pago 1],BD.PD[Per.P1],E$1,BD.PD[Pos],Tabla3[[#This Row],[Part.]])+SUMIFS(BD.PD[Pago 2],BD.PD[Per.P2],E$1,BD.PD[Pos],Tabla3[[#This Row],[Part.]])+SUMIFS(BD.PD[Pago 3],BD.PD[Per.P3],E$1,BD.PD[Pos],Tabla3[[#This Row],[Part.]])+SUMIFS(BD.PD[Pago 4],BD.PD[Per.P4],E$1,BD.PD[Pos],Tabla3[[#This Row],[Part.]])+SUMIFS(BD.PD[Pago 5],BD.PD[Per.P5],E$1,BD.PD[Pos],Tabla3[[#This Row],[Part.]]) -> 0 | F11: =SUMIFS(BD.PD[Pago 1],BD.PD[Per.P1],F$1,BD.PD[Pos],Tabla3[[#This Row],[Part.]])+SUMIFS(BD.PD[Pago 2],BD.PD[Per.P2],F$1,BD.PD[Pos],Tabla3[[#This Row],[Part.]])+SUMIFS(BD.PD[Pago 3],BD.PD[Per.P3],F$1,BD.PD[Pos],Tabla3[[#This Row],[Part.]])+SUMIFS(BD.PD[Pago 4],BD.PD[Per.P4],F$1,BD.PD[Pos],Tabla3[[#This Row],[Part.]])+SUMIFS(BD.PD[Pago 5],BD.PD[Per.P5],F$1,BD.PD[Pos],Tabla3[[#This Row],[Part.]]) -> 0 | G11: =SUMIFS(BD.PD[Pago 1],BD.PD[Per.P1],G$1,BD.PD[Pos],Tabla3[[#This Row],[Part.]])+SUMIFS(BD.PD[Pago 2],BD.PD[Per.P2],G$1,BD.PD[Pos],Tabla3[[#This Row],[Part.]])+SUMIFS(BD.PD[Pago 3],BD.PD[Per.P3],G$1,BD.PD[Pos],Tabla3[[#This Row],[Part.]])+SUMIFS(BD.PD[Pago 4],BD.PD[Per.P4],G$1,BD.PD[Pos],Tabla3[[#This Row],[Part.]])+SUMIFS(BD.PD[Pago 5],BD.PD[Per.P5],G$1,BD.PD[Pos],Tabla3[[#This Row],[Part.]]) -> 0 | H11: =SUMIFS(BD.PD[Pago 1],BD.PD[Per.P1],H$1,BD.PD[Pos],Tabla3[[#This Row],[Part.]])+SUMIFS(BD.PD[Pago 2],BD.PD[Per.P2],H$1,BD.PD[Pos],Tabla3[[#This Row],[Part.]])+SUMIFS(BD.PD[Pago 3],BD.PD[Per.P3],H$1,BD.PD[Pos],Tabla3[[#This Row],[Part.]])+SUMIFS(BD.PD[Pago 4],BD.PD[Per.P4],H$1,BD.PD[Pos],Tabla3[[#This Row],[Part.]])+SUMIFS(BD.PD[Pago 5],BD.PD[Per.P5],H$1,BD.PD[Pos],Tabla3[[#This Row],[Part.]]) -> 0 | I11: =SUMIFS(BD.PD[Pago 1],BD.PD[Per.P1],I$1,BD.PD[Pos],Tabla3[[#This Row],[Part.]])+SUMIFS(BD.PD[Pago 2],BD.PD[Per.P2],I$1,BD.PD[Pos],Tabla3[[#This Row],[Part.]])+SUMIFS(BD.PD[Pago 3],BD.PD[Per.P3],I$1,BD.PD[Pos],Tabla3[[#This Row],[Part.]])+SUMIFS(BD.PD[Pago 4],BD.PD[Per.P4],I$1,BD.PD[Pos],Tabla3[[#This Row],[Part.]])+SUMIFS(BD.PD[Pago 5],BD.PD[Per.P5],I$1,BD.PD[Pos],Tabla3[[#This Row],[Part.]]) -> 0 | J11: =SUMIFS(BD.PD[Pago 1],BD.PD[Per.P1],J$1,BD.PD[Pos],Tabla3[[#This Row],[Part.]])+SUMIFS(BD.PD[Pago 2],BD.PD[Per.P2],J$1,BD.PD[Pos],Tabla3[[#This Row],[Part.]])+SUMIFS(BD.PD[Pago 3],BD.PD[Per.P3],J$1,BD.PD[Pos],Tabla3[[#This Row],[Part.]])+SUMIFS(BD.PD[Pago 4],BD.PD[Per.P4],J$1,BD.PD[Pos],Tabla3[[#This Row],[Part.]])+SUMIFS(BD.PD[Pago 5],BD.PD[Per.P5],J$1,BD.PD[Pos],Tabla3[[#This Row],[Part.]]) -> 0 | K11: =SUMIFS(BD.PD[Pago 1],BD.PD[Per.P1],K$1,BD.PD[Pos],Tabla3[[#This Row],[Part.]])+SUMIFS(BD.PD[Pago 2],BD.PD[Per.P2],K$1,BD.PD[Pos],Tabla3[[#This Row],[Part.]])+SUMIFS(BD.PD[Pago 3],BD.PD[Per.P3],K$1,BD.PD[Pos],Tabla3[[#This Row],[Part.]])+SUMIFS(BD.PD[Pago 4],BD.PD[Per.P4],K$1,BD.PD[Pos],Tabla3[[#This Row],[Part.]])+SUMIFS(BD.PD[Pago 5],BD.PD[Per.P5],K$1,BD.PD[Pos],Tabla3[[#This Row],[Part.]]) -> 0 | ... AG11: =SUMIFS(BD.PD[Pago 1],BD.PD[Per.P1],AG$1,BD.PD[Pos],Tabla3[[#This Row],[Part.]])+SUMIFS(BD.PD[Pago 2],BD.PD[Per.P2],AG$1,BD.PD[Pos],Tabla3[[#This Row],[Part.]])+SUMIFS(BD.PD[Pago 3],BD.PD[Per.P3],AG$1,BD.PD[Pos],Tabla3[[#This Row],[Part.]])+SUMIFS(BD.PD[Pago 4],BD.PD[Per.P4],AG$1,BD.PD[Pos],Tabla3[[#This Row],[Part.]])+SUMIFS(BD.PD[Pago 5],BD.PD[Per.P5],AG$1,BD.PD[Pos],Tabla3[[#This Row],[Part.]]) -> 0 | AH11: =SUM(Tabla3[[#This Row],[P1]:[P24]]) -> 0
A12: 1.06 | B12: =VLOOKUP(Tabla3[[#This Row],[Part.]],PPto[],3,FALSE) -> 1.06 Levantamiento topográfico | C12: =SUMIF(BD.PD[Pos],Tabla3[[#This Row],[Part.]],BD.PD[Ppto. Orden Interna '[DOP']]) -> 0 | D12: =SUMIFS(BD.PD[Pago 1],BD.PD[Per.P1],D$1,BD.PD[Pos],Tabla3[[#This Row],[Part.]])+SUMIFS(BD.PD[Pago 2],BD.PD[Per.P2],D$1,BD.PD[Pos],Tabla3[[#This Row],[Part.]])+SUMIFS(BD.PD[Pago 3],BD.PD[Per.P3],D$1,BD.PD[Pos],Tabla3[[#This Row],[Part.]])+SUMIFS(BD.PD[Pago 4],BD.PD[Per.P4],D$1,BD.PD[Pos],Tabla3[[#This Row],[Part.]])+SUMIFS(BD.PD[Pago 5],BD.PD[Per.P5],D$1,BD.PD[Pos],Tabla3[[#This Row],[Part.]]) -> 0 | E12: =SUMIFS(BD.PD[Pago 1],BD.PD[Per.P1],E$1,BD.PD[Pos],Tabla3[[#This Row],[Part.]])+SUMIFS(BD.PD[Pago 2],BD.PD[Per.P2],E$1,BD.PD[Pos],Tabla3[[#This Row],[Part.]])+SUMIFS(BD.PD[Pago 3],BD.PD[Per.P3],E$1,BD.PD[Pos],Tabla3[[#This Row],[Part.]])+SUMIFS(BD.PD[Pago 4],BD.PD[Per.P4],E$1,BD.PD[Pos],Tabla3[[#This Row],[Part.]])+SUMIFS(BD.PD[Pago 5],BD.PD[Per.P5],E$1,BD.PD[Pos],Tabla3[[#This Row],[Part.]]) -> 0 | F12: =SUMIFS(BD.PD[Pago 1],BD.PD[Per.P1],F$1,BD.PD[Pos],Tabla3[[#This Row],[Part.]])+SUMIFS(BD.PD[Pago 2],BD.PD[Per.P2],F$1,BD.PD[Pos],Tabla3[[#This Row],[Part.]])+SUMIFS(BD.PD[Pago 3],BD.PD[Per.P3],F$1,BD.PD[Pos],Tabla3[[#This Row],[Part.]])+SUMIFS(BD.PD[Pago 4],BD.PD[Per.P4],F$1,BD.PD[Pos],Tabla3[[#This Row],[Part.]])+SUMIFS(BD.PD[Pago 5],BD.PD[Per.P5],F$1,BD.PD[Pos],Tabla3[[#This Row],[Part.]]) -> 0 | G12: =SUMIFS(BD.PD[Pago 1],BD.PD[Per.P1],G$1,BD.PD[Pos],Tabla3[[#This Row],[Part.]])+SUMIFS(BD.PD[Pago 2],BD.PD[Per.P2],G$1,BD.PD[Pos],Tabla3[[#This Row],[Part.]])+SUMIFS(BD.PD[Pago 3],BD.PD[Per.P3],G$1,BD.PD[Pos],Tabla3[[#This Row],[Part.]])+SUMIFS(BD.PD[Pago 4],BD.PD[Per.P4],G$1,BD.PD[Pos],Tabla3[[#This Row],[Part.]])+SUMIFS(BD.PD[Pago 5],BD.PD[Per.P5],G$1,BD.PD[Pos],Tabla3[[#This Row],[Part.]]) -> 0 | H12: =SUMIFS(BD.PD[Pago 1],BD.PD[Per.P1],H$1,BD.PD[Pos],Tabla3[[#This Row],[Part.]])+SUMIFS(BD.PD[Pago 2],BD.PD[Per.P2],H$1,BD.PD[Pos],Tabla3[[#This Row],[Part.]])+SUMIFS(BD.PD[Pago 3],BD.PD[Per.P3],H$1,BD.PD[Pos],Tabla3[[#This Row],[Part.]])+SUMIFS(BD.PD[Pago 4],BD.PD[Per.P4],H$1,BD.PD[Pos],Tabla3[[#This Row],[Part.]])+SUMIFS(BD.PD[Pago 5],BD.PD[Per.P5],H$1,BD.PD[Pos],Tabla3[[#This Row],[Part.]]) -> 0 | I12: =SUMIFS(BD.PD[Pago 1],BD.PD[Per.P1],I$1,BD.PD[Pos],Tabla3[[#This Row],[Part.]])+SUMIFS(BD.PD[Pago 2],BD.PD[Per.P2],I$1,BD.PD[Pos],Tabla3[[#This Row],[Part.]])+SUMIFS(BD.PD[Pago 3],BD.PD[Per.P3],I$1,BD.PD[Pos],Tabla3[[#This Row],[Part.]])+SUMIFS(BD.PD[Pago 4],BD.PD[Per.P4],I$1,BD.PD[Pos],Tabla3[[#This Row],[Part.]])+SUMIFS(BD.PD[Pago 5],BD.PD[Per.P5],I$1,BD.PD[Pos],Tabla3[[#This Row],[Part.]]) -> 0 | J12: =SUMIFS(BD.PD[Pago 1],BD.PD[Per.P1],J$1,BD.PD[Pos],Tabla3[[#This Row],[Part.]])+SUMIFS(BD.PD[Pago 2],BD.PD[Per.P2],J$1,BD.PD[Pos],Tabla3[[#This Row],[Part.]])+SUMIFS(BD.PD[Pago 3],BD.PD[Per.P3],J$1,BD.PD[Pos],Tabla3[[#This Row],[Part.]])+SUMIFS(BD.PD[Pago 4],BD.PD[Per.P4],J$1,BD.PD[Pos],Tabla3[[#This Row],[Part.]])+SUMIFS(BD.PD[Pago 5],BD.PD[Per.P5],J$1,BD.PD[Pos],Tabla3[[#This Row],[Part.]]) -> 0 | K12: =SUMIFS(BD.PD[Pago 1],BD.PD[Per.P1],K$1,BD.PD[Pos],Tabla3[[#This Row],[Part.]])+SUMIFS(BD.PD[Pago 2],BD.PD[Per.P2],K$1,BD.PD[Pos],Tabla3[[#This Row],[Part.]])+SUMIFS(BD.PD[Pago 3],BD.PD[Per.P3],K$1,BD.PD[Pos],Tabla3[[#This Row],[Part.]])+SUMIFS(BD.PD[Pago 4],BD.PD[Per.P4],K$1,BD.PD[Pos],Tabla3[[#This Row],[Part.]])+SUMIFS(BD.PD[Pago 5],BD.PD[Per.P5],K$1,BD.PD[Pos],Tabla3[[#This Row],[Part.]]) -> 0 | ... AG12: =SUMIFS(BD.PD[Pago 1],BD.PD[Per.P1],AG$1,BD.PD[Pos],Tabla3[[#This Row],[Part.]])+SUMIFS(BD.PD[Pago 2],BD.PD[Per.P2],AG$1,BD.PD[Pos],Tabla3[[#This Row],[Part.]])+SUMIFS(BD.PD[Pago 3],BD.PD[Per.P3],AG$1,BD.PD[Pos],Tabla3[[#This Row],[Part.]])+SUMIFS(BD.PD[Pago 4],BD.PD[Per.P4],AG$1,BD.PD[Pos],Tabla3[[#This Row],[Part.]])+SUMIFS(BD.PD[Pago 5],BD.PD[Per.P5],AG$1,BD.PD[Pos],Tabla3[[#This Row],[Part.]]) -> 0 | AH12: =SUM(Tabla3[[#This Row],[P1]:[P24]]) -> 0
A13: 1.07 | B13: =VLOOKUP(Tabla3[[#This Row],[Part.]],PPto[],3,FALSE) -> 1.07 Permisos | C13: =SUMIF(BD.PD[Pos],Tabla3[[#This Row],[Part.]],BD.PD[Ppto. Orden Interna '[DOP']]) -> 0 | D13: =SUMIFS(BD.PD[Pago 1],BD.PD[Per.P1],D$1,BD.PD[Pos],Tabla3[[#This Row],[Part.]])+SUMIFS(BD.PD[Pago 2],BD.PD[Per.P2],D$1,BD.PD[Pos],Tabla3[[#This Row],[Part.]])+SUMIFS(BD.PD[Pago 3],BD.PD[Per.P3],D$1,BD.PD[Pos],Tabla3[[#This Row],[Part.]])+SUMIFS(BD.PD[Pago 4],BD.PD[Per.P4],D$1,BD.PD[Pos],Tabla3[[#This Row],[Part.]])+SUMIFS(BD.PD[Pago 5],BD.PD[Per.P5],D$1,BD.PD[Pos],Tabla3[[#This Row],[Part.]]) -> 0 | E13: =SUMIFS(BD.PD[Pago 1],BD.PD[Per.P1],E$1,BD.PD[Pos],Tabla3[[#This Row],[Part.]])+SUMIFS(BD.PD[Pago 2],BD.PD[Per.P2],E$1,BD.PD[Pos],Tabla3[[#This Row],[Part.]])+SUMIFS(BD.PD[Pago 3],BD.PD[Per.P3],E$1,BD.PD[Pos],Tabla3[[#This Row],[Part.]])+SUMIFS(BD.PD[Pago 4],BD.PD[Per.P4],E$1,BD.PD[Pos],Tabla3[[#This Row],[Part.]])+SUMIFS(BD.PD[Pago 5],BD.PD[Per.P5],E$1,BD.PD[Pos],Tabla3[[#This Row],[Part.]]) -> 0 | F13: =SUMIFS(BD.PD[Pago 1],BD.PD[Per.P1],F$1,BD.PD[Pos],Tabla3[[#This Row],[Part.]])+SUMIFS(BD.PD[Pago 2],BD.PD[Per.P2],F$1,BD.PD[Pos],Tabla3[[#This Row],[Part.]])+SUMIFS(BD.PD[Pago 3],BD.PD[Per.P3],F$1,BD.PD[Pos],Tabla3[[#This Row],[Part.]])+SUMIFS(BD.PD[Pago 4],BD.PD[Per.P4],F$1,BD.PD[Pos],Tabla3[[#This Row],[Part.]])+SUMIFS(BD.PD[Pago 5],BD.PD[Per.P5],F$1,BD.PD[Pos],Tabla3[[#This Row],[Part.]]) -> 0 | G13: =SUMIFS(BD.PD[Pago 1],BD.PD[Per.P1],G$1,BD.PD[Pos],Tabla3[[#This Row],[Part.]])+SUMIFS(BD.PD[Pago 2],BD.PD[Per.P2],G$1,BD.PD[Pos],Tabla3[[#This Row],[Part.]])+SUMIFS(BD.PD[Pago 3],BD.PD[Per.P3],G$1,BD.PD[Pos],Tabla3[[#This Row],[Part.]])+SUMIFS(BD.PD[Pago 4],BD.PD[Per.P4],G$1,BD.PD[Pos],Tabla3[[#This Row],[Part.]])+SUMIFS(BD.PD[Pago 5],BD.PD[Per.P5],G$1,BD.PD[Pos],Tabla3[[#This Row],[Part.]]) -> 0 | H13: =SUMIFS(BD.PD[Pago 1],BD.PD[Per.P1],H$1,BD.PD[Pos],Tabla3[[#This Row],[Part.]])+SUMIFS(BD.PD[Pago 2],BD.PD[Per.P2],H$1,BD.PD[Pos],Tabla3[[#This Row],[Part.]])+SUMIFS(BD.PD[Pago 3],BD.PD[Per.P3],H$1,BD.PD[Pos],Tabla3[[#This Row],[Part.]])+SUMIFS(BD.PD[Pago 4],BD.PD[Per.P4],H$1,BD.PD[Pos],Tabla3[[#This Row],[Part.]])+SUMIFS(BD.PD[Pago 5],BD.PD[Per.P5],H$1,BD.PD[Pos],Tabla3[[#This Row],[Part.]]) -> 0 | I13: =SUMIFS(BD.PD[Pago 1],BD.PD[Per.P1],I$1,BD.PD[Pos],Tabla3[[#This Row],[Part.]])+SUMIFS(BD.PD[Pago 2],BD.PD[Per.P2],I$1,BD.PD[Pos],Tabla3[[#This Row],[Part.]])+SUMIFS(BD.PD[Pago 3],BD.PD[Per.P3],I$1,BD.PD[Pos],Tabla3[[#This Row],[Part.]])+SUMIFS(BD.PD[Pago 4],BD.PD[Per.P4],I$1,BD.PD[Pos],Tabla3[[#This Row],[Part.]])+SUMIFS(BD.PD[Pago 5],BD.PD[Per.P5],I$1,BD.PD[Pos],Tabla3[[#This Row],[Part.]]) -> 0 | J13: =SUMIFS(BD.PD[Pago 1],BD.PD[Per.P1],J$1,BD.PD[Pos],Tabla3[[#This Row],[Part.]])+SUMIFS(BD.PD[Pago 2],BD.PD[Per.P2],J$1,BD.PD[Pos],Tabla3[[#This Row],[Part.]])+SUMIFS(BD.PD[Pago 3],BD.PD[Per.P3],J$1,BD.PD[Pos],Tabla3[[#This Row],[Part.]])+SUMIFS(BD.PD[Pago 4],BD.PD[Per.P4],J$1,BD.PD[Pos],Tabla3[[#This Row],[Part.]])+SUMIFS(BD.PD[Pago 5],BD.PD[Per.P5],J$1,BD.PD[Pos],Tabla3[[#This Row],[Part.]]) -> 0 | K13: =SUMIFS(BD.PD[Pago 1],BD.PD[Per.P1],K$1,BD.PD[Pos],Tabla3[[#This Row],[Part.]])+SUMIFS(BD.PD[Pago 2],BD.PD[Per.P2],K$1,BD.PD[Pos],Tabla3[[#This Row],[Part.]])+SUMIFS(BD.PD[Pago 3],BD.PD[Per.P3],K$1,BD.PD[Pos],Tabla3[[#This Row],[Part.]])+SUMIFS(BD.PD[Pago 4],BD.PD[Per.P4],K$1,BD.PD[Pos],Tabla3[[#This Row],[Part.]])+SUMIFS(BD.PD[Pago 5],BD.PD[Per.P5],K$1,BD.PD[Pos],Tabla3[[#This Row],[Part.]]) -> 0 | ... AG13: =SUMIFS(BD.PD[Pago 1],BD.PD[Per.P1],AG$1,BD.PD[Pos],Tabla3[[#This Row],[Part.]])+SUMIFS(BD.PD[Pago 2],BD.PD[Per.P2],AG$1,BD.PD[Pos],Tabla3[[#This Row],[Part.]])+SUMIFS(BD.PD[Pago 3],BD.PD[Per.P3],AG$1,BD.PD[Pos],Tabla3[[#This Row],[Part.]])+SUMIFS(BD.PD[Pago 4],BD.PD[Per.P4],AG$1,BD.PD[Pos],Tabla3[[#This Row],[Part.]])+SUMIFS(BD.PD[Pago 5],BD.PD[Per.P5],AG$1,BD.PD[Pos],Tabla3[[#This Row],[Part.]]) -> 0 | AH13: =SUM(Tabla3[[#This Row],[P1]:[P24]]) -> 0
A14: 1.08 | B14: =VLOOKUP(Tabla3[[#This Row],[Part.]],PPto[],3,FALSE) -> 1.08 Diseño sistema contra incendios | C14: =SUMIF(BD.PD[Pos],Tabla3[[#This Row],[Part.]],BD.PD[Ppto. Orden Interna '[DOP']]) -> 0 | D14: =SUMIFS(BD.PD[Pago 1],BD.PD[Per.P1],D$1,BD.PD[Pos],Tabla3[[#This Row],[Part.]])+SUMIFS(BD.PD[Pago 2],BD.PD[Per.P2],D$1,BD.PD[Pos],Tabla3[[#This Row],[Part.]])+SUMIFS(BD.PD[Pago 3],BD.PD[Per.P3],D$1,BD.PD[Pos],Tabla3[[#This Row],[Part.]])+SUMIFS(BD.PD[Pago 4],BD.PD[Per.P4],D$1,BD.PD[Pos],Tabla3[[#This Row],[Part.]])+SUMIFS(BD.PD[Pago 5],BD.PD[Per.P5],D$1,BD.PD[Pos],Tabla3[[#This Row],[Part.]]) -> 0 | E14: =SUMIFS(BD.PD[Pago 1],BD.PD[Per.P1],E$1,BD.PD[Pos],Tabla3[[#This Row],[Part.]])+SUMIFS(BD.PD[Pago 2],BD.PD[Per.P2],E$1,BD.PD[Pos],Tabla3[[#This Row],[Part.]])+SUMIFS(BD.PD[Pago 3],BD.PD[Per.P3],E$1,BD.PD[Pos],Tabla3[[#This Row],[Part.]])+SUMIFS(BD.PD[Pago 4],BD.PD[Per.P4],E$1,BD.PD[Pos],Tabla3[[#This Row],[Part.]])+SUMIFS(BD.PD[Pago 5],BD.PD[Per.P5],E$1,BD.PD[Pos],Tabla3[[#This Row],[Part.]]) -> 0 | F14: =SUMIFS(BD.PD[Pago 1],BD.PD[Per.P1],F$1,BD.PD[Pos],Tabla3[[#This Row],[Part.]])+SUMIFS(BD.PD[Pago 2],BD.PD[Per.P2],F$1,BD.PD[Pos],Tabla3[[#This Row],[Part.]])+SUMIFS(BD.PD[Pago 3],BD.PD[Per.P3],F$1,BD.PD[Pos],Tabla3[[#This Row],[Part.]])+SUMIFS(BD.PD[Pago 4],BD.PD[Per.P4],F$1,BD.PD[Pos],Tabla3[[#This Row],[Part.]])+SUMIFS(BD.PD[Pago 5],BD.PD[Per.P5],F$1,BD.PD[Pos],Tabla3[[#This Row],[Part.]]) -> 0 | G14: =SUMIFS(BD.PD[Pago 1],BD.PD[Per.P1],G$1,BD.PD[Pos],Tabla3[[#This Row],[Part.]])+SUMIFS(BD.PD[Pago 2],BD.PD[Per.P2],G$1,BD.PD[Pos],Tabla3[[#This Row],[Part.]])+SUMIFS(BD.PD[Pago 3],BD.PD[Per.P3],G$1,BD.PD[Pos],Tabla3[[#This Row],[Part.]])+SUMIFS(BD.PD[Pago 4],BD.PD[Per.P4],G$1,BD.PD[Pos],Tabla3[[#This Row],[Part.]])+SUMIFS(BD.PD[Pago 5],BD.PD[Per.P5],G$1,BD.PD[Pos],Tabla3[[#This Row],[Part.]]) -> 0 | H14: =SUMIFS(BD.PD[Pago 1],BD.PD[Per.P1],H$1,BD.PD[Pos],Tabla3[[#This Row],[Part.]])+SUMIFS(BD.PD[Pago 2],BD.PD[Per.P2],H$1,BD.PD[Pos],Tabla3[[#This Row],[Part.]])+SUMIFS(BD.PD[Pago 3],BD.PD[Per.P3],H$1,BD.PD[Pos],Tabla3[[#This Row],[Part.]])+SUMIFS(BD.PD[Pago 4],BD.PD[Per.P4],H$1,BD.PD[Pos],Tabla3[[#This Row],[Part.]])+SUMIFS(BD.PD[Pago 5],BD.PD[Per.P5],H$1,BD.PD[Pos],Tabla3[[#This Row],[Part.]]) -> 0 | I14: =SUMIFS(BD.PD[Pago 1],BD.PD[Per.P1],I$1,BD.PD[Pos],Tabla3[[#This Row],[Part.]])+SUMIFS(BD.PD[Pago 2],BD.PD[Per.P2],I$1,BD.PD[Pos],Tabla3[[#This Row],[Part.]])+SUMIFS(BD.PD[Pago 3],BD.PD[Per.P3],I$1,BD.PD[Pos],Tabla3[[#This Row],[Part.]])+SUMIFS(BD.PD[Pago 4],BD.PD[Per.P4],I$1,BD.PD[Pos],Tabla3[[#This Row],[Part.]])+SUMIFS(BD.PD[Pago 5],BD.PD[Per.P5],I$1,BD.PD[Pos],Tabla3[[#This Row],[Part.]]) -> 0 | J14: =SUMIFS(BD.PD[Pago 1],BD.PD[Per.P1],J$1,BD.PD[Pos],Tabla3[[#This Row],[Part.]])+SUMIFS(BD.PD[Pago 2],BD.PD[Per.P2],J$1,BD.PD[Pos],Tabla3[[#This Row],[Part.]])+SUMIFS(BD.PD[Pago 3],BD.PD[Per.P3],J$1,BD.PD[Pos],Tabla3[[#This Row],[Part.]])+SUMIFS(BD.PD[Pago 4],BD.PD[Per.P4],J$1,BD.PD[Pos],Tabla3[[#This Row],[Part.]])+SUMIFS(BD.PD[Pago 5],BD.PD[Per.P5],J$1,BD.PD[Pos],Tabla3[[#This Row],[Part.]]) -> 0 | K14: =SUMIFS(BD.PD[Pago 1],BD.PD[Per.P1],K$1,BD.PD[Pos],Tabla3[[#This Row],[Part.]])+SUMIFS(BD.PD[Pago 2],BD.PD[Per.P2],K$1,BD.PD[Pos],Tabla3[[#This Row],[Part.]])+SUMIFS(BD.PD[Pago 3],BD.PD[Per.P3],K$1,BD.PD[Pos],Tabla3[[#This Row],[Part.]])+SUMIFS(BD.PD[Pago 4],BD.PD[Per.P4],K$1,BD.PD[Pos],Tabla3[[#This Row],[Part.]])+SUMIFS(BD.PD[Pago 5],BD.PD[Per.P5],K$1,BD.PD[Pos],Tabla3[[#This Row],[Part.]]) -> 0 | ... AG14: =SUMIFS(BD.PD[Pago 1],BD.PD[Per.P1],AG$1,BD.PD[Pos],Tabla3[[#This Row],[Part.]])+SUMIFS(BD.PD[Pago 2],BD.PD[Per.P2],AG$1,BD.PD[Pos],Tabla3[[#This Row],[Part.]])+SUMIFS(BD.PD[Pago 3],BD.PD[Per.P3],AG$1,BD.PD[Pos],Tabla3[[#This Row],[Part.]])+SUMIFS(BD.PD[Pago 4],BD.PD[Per.P4],AG$1,BD.PD[Pos],Tabla3[[#This Row],[Part.]])+SUMIFS(BD.PD[Pago 5],BD.PD[Per.P5],AG$1,BD.PD[Pos],Tabla3[[#This Row],[Part.]]) -> 0 | AH14: =SUM(Tabla3[[#This Row],[P1]:[P24]]) -> 0
A15: 1.09 | B15: =VLOOKUP(Tabla3[[#This Row],[Part.]],PPto[],3,FALSE) -> 1.09 Diseño sistema gas | C15: =SUMIF(BD.PD[Pos],Tabla3[[#This Row],[Part.]],BD.PD[Ppto. Orden Interna '[DOP']]) -> 0 | D15: =SUMIFS(BD.PD[Pago 1],BD.PD[Per.P1],D$1,BD.PD[Pos],Tabla3[[#This Row],[Part.]])+SUMIFS(BD.PD[Pago 2],BD.PD[Per.P2],D$1,BD.PD[Pos],Tabla3[[#This Row],[Part.]])+SUMIFS(BD.PD[Pago 3],BD.PD[Per.P3],D$1,BD.PD[Pos],Tabla3[[#This Row],[Part.]])+SUMIFS(BD.PD[Pago 4],BD.PD[Per.P4],D$1,BD.PD[Pos],Tabla3[[#This Row],[Part.]])+SUMIFS(BD.PD[Pago 5],BD.PD[Per.P5],D$1,BD.PD[Pos],Tabla3[[#This Row],[Part.]]) -> 0 | E15: =SUMIFS(BD.PD[Pago 1],BD.PD[Per.P1],E$1,BD.PD[Pos],Tabla3[[#This Row],[Part.]])+SUMIFS(BD.PD[Pago 2],BD.PD[Per.P2],E$1,BD.PD[Pos],Tabla3[[#This Row],[Part.]])+SUMIFS(BD.PD[Pago 3],BD.PD[Per.P3],E$1,BD.PD[Pos],Tabla3[[#This Row],[Part.]])+SUMIFS(BD.PD[Pago 4],BD.PD[Per.P4],E$1,BD.PD[Pos],Tabla3[[#This Row],[Part.]])+SUMIFS(BD.PD[Pago 5],BD.PD[Per.P5],E$1,BD.PD[Pos],Tabla3[[#This Row],[Part.]]) -> 0 | F15: =SUMIFS(BD.PD[Pago 1],BD.PD[Per.P1],F$1,BD.PD[Pos],Tabla3[[#This Row],[Part.]])+SUMIFS(BD.PD[Pago 2],BD.PD[Per.P2],F$1,BD.PD[Pos],Tabla3[[#This Row],[Part.]])+SUMIFS(BD.PD[Pago 3],BD.PD[Per.P3],F$1,BD.PD[Pos],Tabla3[[#This Row],[Part.]])+SUMIFS(BD.PD[Pago 4],BD.PD[Per.P4],F$1,BD.PD[Pos],Tabla3[[#This Row],[Part.]])+SUMIFS(BD.PD[Pago 5],BD.PD[Per.P5],F$1,BD.PD[Pos],Tabla3[[#This Row],[Part.]]) -> 0 | G15: =SUMIFS(BD.PD[Pago 1],BD.PD[Per.P1],G$1,BD.PD[Pos],Tabla3[[#This Row],[Part.]])+SUMIFS(BD.PD[Pago 2],BD.PD[Per.P2],G$1,BD.PD[Pos],Tabla3[[#This Row],[Part.]])+SUMIFS(BD.PD[Pago 3],BD.PD[Per.P3],G$1,BD.PD[Pos],Tabla3[[#This Row],[Part.]])+SUMIFS(BD.PD[Pago 4],BD.PD[Per.P4],G$1,BD.PD[Pos],Tabla3[[#This Row],[Part.]])+SUMIFS(BD.PD[Pago 5],BD.PD[Per.P5],G$1,BD.PD[Pos],Tabla3[[#This Row],[Part.]]) -> 0 | H15: =SUMIFS(BD.PD[Pago 1],BD.PD[Per.P1],H$1,BD.PD[Pos],Tabla3[[#This Row],[Part.]])+SUMIFS(BD.PD[Pago 2],BD.PD[Per.P2],H$1,BD.PD[Pos],Tabla3[[#This Row],[Part.]])+SUMIFS(BD.PD[Pago 3],BD.PD[Per.P3],H$1,BD.PD[Pos],Tabla3[[#This Row],[Part.]])+SUMIFS(BD.PD[Pago 4],BD.PD[Per.P4],H$1,BD.PD[Pos],Tabla3[[#This Row],[Part.]])+SUMIFS(BD.PD[Pago 5],BD.PD[Per.P5],H$1,BD.PD[Pos],Tabla3[[#This Row],[Part.]]) -> 0 | I15: =SUMIFS(BD.PD[Pago 1],BD.PD[Per.P1],I$1,BD.PD[Pos],Tabla3[[#This Row],[Part.]])+SUMIFS(BD.PD[Pago 2],BD.PD[Per.P2],I$1,BD.PD[Pos],Tabla3[[#This Row],[Part.]])+SUMIFS(BD.PD[Pago 3],BD.PD[Per.P3],I$1,BD.PD[Pos],Tabla3[[#This Row],[Part.]])+SUMIFS(BD.PD[Pago 4],BD.PD[Per.P4],I$1,BD.PD[Pos],Tabla3[[#This Row],[Part.]])+SUMIFS(BD.PD[Pago 5],BD.PD[Per.P5],I$1,BD.PD[Pos],Tabla3[[#This Row],[Part.]]) -> 0 | J15: =SUMIFS(BD.PD[Pago 1],BD.PD[Per.P1],J$1,BD.PD[Pos],Tabla3[[#This Row],[Part.]])+SUMIFS(BD.PD[Pago 2],BD.PD[Per.P2],J$1,BD.PD[Pos],Tabla3[[#This Row],[Part.]])+SUMIFS(BD.PD[Pago 3],BD.PD[Per.P3],J$1,BD.PD[Pos],Tabla3[[#This Row],[Part.]])+SUMIFS(BD.PD[Pago 4],BD.PD[Per.P4],J$1,BD.PD[Pos],Tabla3[[#This Row],[Part.]])+SUMIFS(BD.PD[Pago 5],BD.PD[Per.P5],J$1,BD.PD[Pos],Tabla3[[#This Row],[Part.]]) -> 0 | K15: =SUMIFS(BD.PD[Pago 1],BD.PD[Per.P1],K$1,BD.PD[Pos],Tabla3[[#This Row],[Part.]])+SUMIFS(BD.PD[Pago 2],BD.PD[Per.P2],K$1,BD.PD[Pos],Tabla3[[#This Row],[Part.]])+SUMIFS(BD.PD[Pago 3],BD.PD[Per.P3],K$1,BD.PD[Pos],Tabla3[[#This Row],[Part.]])+SUMIFS(BD.PD[Pago 4],BD.PD[Per.P4],K$1,BD.PD[Pos],Tabla3[[#This Row],[Part.]])+SUMIFS(BD.PD[Pago 5],BD.PD[Per.P5],K$1,BD.PD[Pos],Tabla3[[#This Row],[Part.]]) -> 0 | ... AG15: =SUMIFS(BD.PD[Pago 1],BD.PD[Per.P1],AG$1,BD.PD[Pos],Tabla3[[#This Row],[Part.]])+SUMIFS(BD.PD[Pago 2],BD.PD[Per.P2],AG$1,BD.PD[Pos],Tabla3[[#This Row],[Part.]])+SUMIFS(BD.PD[Pago 3],BD.PD[Per.P3],AG$1,BD.PD[Pos],Tabla3[[#This Row],[Part.]])+SUMIFS(BD.PD[Pago 4],BD.PD[Per.P4],AG$1,BD.PD[Pos],Tabla3[[#This Row],[Part.]])+SUMIFS(BD.PD[Pago 5],BD.PD[Per.P5],AG$1,BD.PD[Pos],Tabla3[[#This Row],[Part.]]) -> 0 | AH15: =SUM(Tabla3[[#This Row],[P1]:[P24]]) -> 0
A16: 2 | B16: =VLOOKUP(Tabla3[[#This Row],[Part.]],PPto[],3,FALSE) -> 2.00 Obra Civil | C16: =SUM(C17:C27) -> 11956367 | D16: =SUM(D17:D27) -> 2505125.7 | E16: =SUM(E17:E27) -> 0 | F16: =SUM(F17:F27) -> 294168.42 | G16: =SUM(G17:G27) -> 0 | H16: =SUM(H17:H27) -> 0 | I16: =SUM(I17:I27) -> 140597.86 | J16: =SUM(J17:J27) -> 0 | ... AA16: =SUM(AA17:AA27) -> 0 | AB16: =SUMIFS(BD.PD[Pago 1],BD.PD[Per.P1],AB$1,BD.PD[Pos],Tabla3[[#This Row],[Part.]])+SUMIFS(BD.PD[Pago 2],BD.PD[Per.P2],AB$1,BD.PD[Pos],Tabla3[[#This Row],[Part.]])+SUMIFS(BD.PD[Pago 3],BD.PD[Per.P3],AB$1,BD.PD[Pos],Tabla3[[#This Row],[Part.]])+SUMIFS(BD.PD[Pago 4],BD.PD[Per.P4],AB$1,BD.PD[Pos],Tabla3[[#This Row],[Part.]])+SUMIFS(BD.PD[Pago 5],BD.PD[Per.P5],AB$1,BD.PD[Pos],Tabla3[[#This Row],[Part.]]) -> 0 | AC16: =SUMIFS(BD.PD[Pago 1],BD.PD[Per.P1],AC$1,BD.PD[Pos],Tabla3[[#This Row],[Part.]])+SUMIFS(BD.PD[Pago 2],BD.PD[Per.P2],AC$1,BD.PD[Pos],Tabla3[[#This Row],[Part.]])+SUMIFS(BD.PD[Pago 3],BD.PD[Per.P3],AC$1,BD.PD[Pos],Tabla3[[#This Row],[Part.]])+SUMIFS(BD.PD[Pago 4],BD.PD[Per.P4],AC$1,BD.PD[Pos],Tabla3[[#This Row],[Part.]])+SUMIFS(BD.PD[Pago 5],BD.PD[Per.P5],AC$1,BD.PD[Pos],Tabla3[[#This Row],[Part.]]) -> 0 | AD16: =SUMIFS(BD.PD[Pago 1],BD.PD[Per.P1],AD$1,BD.PD[Pos],Tabla3[[#This Row],[Part.]])+SUMIFS(BD.PD[Pago 2],BD.PD[Per.P2],AD$1,BD.PD[Pos],Tabla3[[#This Row],[Part.]])+SUMIFS(BD.PD[Pago 3],BD.PD[Per.P3],AD$1,BD.PD[Pos],Tabla3[[#This Row],[Part.]])+SUMIFS(BD.PD[Pago 4],BD.PD[Per.P4],AD$1,BD.PD[Pos],Tabla3[[#This Row],[Part.]])+SUMIFS(BD.PD[Pago 5],BD.PD[Per.P5],AD$1,BD.PD[Pos],Tabla3[[#This Row],[Part.]]) -> 0 | AE16: =SUMIFS(BD.PD[Pago 1],BD.PD[Per.P1],AE$1,BD.PD[Pos],Tabla3[[#This Row],[Part.]])+SUMIFS(BD.PD[Pago 2],BD.PD[Per.P2],AE$1,BD.PD[Pos],Tabla3[[#This Row],[Part.]])+SUMIFS(BD.PD[Pago 3],BD.PD[Per.P3],AE$1,BD.PD[Pos],Tabla3[[#This Row],[Part.]])+SUMIFS(BD.PD[Pago 4],BD.PD[Per.P4],AE$1,BD.PD[Pos],Tabla3[[#This Row],[Part.]])+SUMIFS(BD.PD[Pago 5],BD.PD[Per.P5],AE$1,BD.PD[Pos],Tabla3[[#This Row],[Part.]]) -> 0 | AF16: =SUMIFS(BD.PD[Pago 1],BD.PD[Per.P1],AF$1,BD.PD[Pos],Tabla3[[#This Row],[Part.]])+SUMIFS(BD.PD[Pago 2],BD.PD[Per.P2],AF$1,BD.PD[Pos],Tabla3[[#This Row],[Part.]])+SUMIFS(BD.PD[Pago 3],BD.PD[Per.P3],AF$1,BD.PD[Pos],Tabla3[[#This Row],[Part.]])+SUMIFS(BD.PD[Pago 4],BD.PD[Per.P4],AF$1,BD.PD[Pos],Tabla3[[#This Row],[Part.]])+SUMIFS(BD.PD[Pago 5],BD.PD[Per.P5],AF$1,BD.PD[Pos],Tabla3[[#This Row],[Part.]]) -> 0 | AG16: =SUMIFS(BD.PD[Pago 1],BD.PD[Per.P1],AG$1,BD.PD[Pos],Tabla3[[#This Row],[Part.]])+SUMIFS(BD.PD[Pago 2],BD.PD[Per.P2],AG$1,BD.PD[Pos],Tabla3[[#This Row],[Part.]])+SUMIFS(BD.PD[Pago 3],BD.PD[Per.P3],AG$1,BD.PD[Pos],Tabla3[[#This Row],[Part.]])+SUMIFS(BD.PD[Pago 4],BD.PD[Per.P4],AG$1,BD.PD[Pos],Tabla3[[#This Row],[Part.]])+SUMIFS(BD.PD[Pago 5],BD.PD[Per.P5],AG$1,BD.PD[Pos],Tabla3[[#This Row],[Part.]]) -> 0 | AH16: =SUM(Tabla3[[#This Row],[P1]:[P24]]) -> 11956367
A17: 2.01 | B17: =VLOOKUP(Tabla3[[#This Row],[Part.]],PPto[],3,FALSE) -> 2.01 Edificación - Obra Civil | C17: =SUMIF(BD.PD[Pos],Tabla3[[#This Row],[Part.]],BD.PD[Ppto. Orden Interna '[DOP']]) -> 526280.58 | D17: =SUMIFS(BD.PD[Pago 1],BD.PD[Per.P1],D$1,BD.PD[Pos],Tabla3[[#This Row],[Part.]])+SUMIFS(BD.PD[Pago 2],BD.PD[Per.P2],D$1,BD.PD[Pos],Tabla3[[#This Row],[Part.]])+SUMIFS(BD.PD[Pago 3],BD.PD[Per.P3],D$1,BD.PD[Pos],Tabla3[[#This Row],[Part.]])+SUMIFS(BD.PD[Pago 4],BD.PD[Per.P4],D$1,BD.PD[Pos],Tabla3[[#This Row],[Part.]])+SUMIFS(BD.PD[Pago 5],BD.PD[Per.P5],D$1,BD.PD[Pos],Tabla3[[#This Row],[Part.]]) -> 0 | E17: =SUMIFS(BD.PD[Pago 1],BD.PD[Per.P1],E$1,BD.PD[Pos],Tabla3[[#This Row],[Part.]])+SUMIFS(BD.PD[Pago 2],BD.PD[Per.P2],E$1,BD.PD[Pos],Tabla3[[#This Row],[Part.]])+SUMIFS(BD.PD[Pago 3],BD.PD[Per.P3],E$1,BD.PD[Pos],Tabla3[[#This Row],[Part.]])+SUMIFS(BD.PD[Pago 4],BD.PD[Per.P4],E$1,BD.PD[Pos],Tabla3[[#This Row],[Part.]])+SUMIFS(BD.PD[Pago 5],BD.PD[Per.P5],E$1,BD.PD[Pos],Tabla3[[#This Row],[Part.]]) -> 0 | F17: =SUMIFS(BD.PD[Pago 1],BD.PD[Per.P1],F$1,BD.PD[Pos],Tabla3[[#This Row],[Part.]])+SUMIFS(BD.PD[Pago 2],BD.PD[Per.P2],F$1,BD.PD[Pos],Tabla3[[#This Row],[Part.]])+SUMIFS(BD.PD[Pago 3],BD.PD[Per.P3],F$1,BD.PD[Pos],Tabla3[[#This Row],[Part.]])+SUMIFS(BD.PD[Pago 4],BD.PD[Per.P4],F$1,BD.PD[Pos],Tabla3[[#This Row],[Part.]])+SUMIFS(BD.PD[Pago 5],BD.PD[Per.P5],F$1,BD.PD[Pos],Tabla3[[#This Row],[Part.]]) -> 0 | G17: =SUMIFS(BD.PD[Pago 1],BD.PD[Per.P1],G$1,BD.PD[Pos],Tabla3[[#This Row],[Part.]])+SUMIFS(BD.PD[Pago 2],BD.PD[Per.P2],G$1,BD.PD[Pos],Tabla3[[#This Row],[Part.]])+SUMIFS(BD.PD[Pago 3],BD.PD[Per.P3],G$1,BD.PD[Pos],Tabla3[[#This Row],[Part.]])+SUMIFS(BD.PD[Pago 4],BD.PD[Per.P4],G$1,BD.PD[Pos],Tabla3[[#This Row],[Part.]])+SUMIFS(BD.PD[Pago 5],BD.PD[Per.P5],G$1,BD.PD[Pos],Tabla3[[#This Row],[Part.]]) -> 0 | H17: =SUMIFS(BD.PD[Pago 1],BD.PD[Per.P1],H$1,BD.PD[Pos],Tabla3[[#This Row],[Part.]])+SUMIFS(BD.PD[Pago 2],BD.PD[Per.P2],H$1,BD.PD[Pos],Tabla3[[#This Row],[Part.]])+SUMIFS(BD.PD[Pago 3],BD.PD[Per.P3],H$1,BD.PD[Pos],Tabla3[[#This Row],[Part.]])+SUMIFS(BD.PD[Pago 4],BD.PD[Per.P4],H$1,BD.PD[Pos],Tabla3[[#This Row],[Part.]])+SUMIFS(BD.PD[Pago 5],BD.PD[Per.P5],H$1,BD.PD[Pos],Tabla3[[#This Row],[Part.]]) -> 0 | I17: =SUMIFS(BD.PD[Pago 1],BD.PD[Per.P1],I$1,BD.PD[Pos],Tabla3[[#This Row],[Part.]])+SUMIFS(BD.PD[Pago 2],BD.PD[Per.P2],I$1,BD.PD[Pos],Tabla3[[#This Row],[Part.]])+SUMIFS(BD.PD[Pago 3],BD.PD[Per.P3],I$1,BD.PD[Pos],Tabla3[[#This Row],[Part.]])+SUMIFS(BD.PD[Pago 4],BD.PD[Per.P4],I$1,BD.PD[Pos],Tabla3[[#This Row],[Part.]])+SUMIFS(BD.PD[Pago 5],BD.PD[Per.P5],I$1,BD.PD[Pos],Tabla3[[#This Row],[Part.]]) -> 140597.86 | J17: =SUMIFS(BD.PD[Pago 1],BD.PD[Per.P1],J$1,BD.PD[Pos],Tabla3[[#This Row],[Part.]])+SUMIFS(BD.PD[Pago 2],BD.PD[Per.P2],J$1,BD.PD[Pos],Tabla3[[#This Row],[Part.]])+SUMIFS(BD.PD[Pago 3],BD.PD[Per.P3],J$1,BD.PD[Pos],Tabla3[[#This Row],[Part.]])+SUMIFS(BD.PD[Pago 4],BD.PD[Per.P4],J$1,BD.PD[Pos],Tabla3[[#This Row],[Part.]])+SUMIFS(BD.PD[Pago 5],BD.PD[Per.P5],J$1,BD.PD[Pos],Tabla3[[#This Row],[Part.]]) -> 0 | K17: =SUMIFS(BD.PD[Pago 1],BD.PD[Per.P1],K$1,BD.PD[Pos],Tabla3[[#This Row],[Part.]])+SUMIFS(BD.PD[Pago 2],BD.PD[Per.P2],K$1,BD.PD[Pos],Tabla3[[#This Row],[Part.]])+SUMIFS(BD.PD[Pago 3],BD.PD[Per.P3],K$1,BD.PD[Pos],Tabla3[[#This Row],[Part.]])+SUMIFS(BD.PD[Pago 4],BD.PD[Per.P4],K$1,BD.PD[Pos],Tabla3[[#This Row],[Part.]])+SUMIFS(BD.PD[Pago 5],BD.PD[Per.P5],K$1,BD.PD[Pos],Tabla3[[#This Row],[Part.]]) -> 122542.43 | ... Z17: =SUMIFS(BD.PD[Pago 1],BD.PD[Per.P1],Z$1,BD.PD[Pos],Tabla3[[#This Row],[Part.]])+SUMIFS(BD.PD[Pago 2],BD.PD[Per.P2],Z$1,BD.PD[Pos],Tabla3[[#This Row],[Part.]])+SUMIFS(BD.PD[Pago 3],BD.PD[Per.P3],Z$1,BD.PD[Pos],Tabla3[[#This Row],[Part.]])+SUMIFS(BD.PD[Pago 4],BD.PD[Per.P4],Z$1,BD.PD[Pos],Tabla3[[#This Row],[Part.]])+SUMIFS(BD.PD[Pago 5],BD.PD[Per.P5],Z$1,BD.PD[Pos],Tabla3[[#This Row],[Part.]]) -> 0 | AB17: =SUMIFS(BD.PD[Pago 1],BD.PD[Per.P1],AB$1,BD.PD[Pos],Tabla3[[#This Row],[Part.]])+SUMIFS(BD.PD[Pago 2],BD.PD[Per.P2],AB$1,BD.PD[Pos],Tabla3[[#This Row],[Part.]])+SUMIFS(BD.PD[Pago 3],BD.PD[Per.P3],AB$1,BD.PD[Pos],Tabla3[[#This Row],[Part.]])+SUMIFS(BD.PD[Pago 4],BD.PD[Per.P4],AB$1,BD.PD[Pos],Tabla3[[#This Row],[Part.]])+SUMIFS(BD.PD[Pago 5],BD.PD[Per.P5],AB$1,BD.PD[Pos],Tabla3[[#This Row],[Part.]]) -> 0 | AC17: =SUMIFS(BD.PD[Pago 1],BD.PD[Per.P1],AC$1,BD.PD[Pos],Tabla3[[#This Row],[Part.]])+SUMIFS(BD.PD[Pago 2],BD.PD[Per.P2],AC$1,BD.PD[Pos],Tabla3[[#This Row],[Part.]])+SUMIFS(BD.PD[Pago 3],BD.PD[Per.P3],AC$1,BD.PD[Pos],Tabla3[[#This Row],[Part.]])+SUMIFS(BD.PD[Pago 4],BD.PD[Per.P4],AC$1,BD.PD[Pos],Tabla3[[#This Row],[Part.]])+SUMIFS(BD.PD[Pago 5],BD.PD[Per.P5],AC$1,BD.PD[Pos],Tabla3[[#This Row],[Part.]]) -> 0 | AD17: =SUMIFS(BD.PD[Pago 1],BD.PD[Per.P1],AD$1,BD.PD[Pos],Tabla3[[#This Row],[Part.]])+SUMIFS(BD.PD[Pago 2],BD.PD[Per.P2],AD$1,BD.PD[Pos],Tabla3[[#This Row],[Part.]])+SUMIFS(BD.PD[Pago 3],BD.PD[Per.P3],AD$1,BD.PD[Pos],Tabla3[[#This Row],[Part.]])+SUMIFS(BD.PD[Pago 4],BD.PD[Per.P4],AD$1,BD.PD[Pos],Tabla3[[#This Row],[Part.]])+SUMIFS(BD.PD[Pago 5],BD.PD[Per.P5],AD$1,BD.PD[Pos],Tabla3[[#This Row],[Part.]]) -> 0 | AE17: =SUMIFS(BD.PD[Pago 1],BD.PD[Per.P1],AE$1,BD.PD[Pos],Tabla3[[#This Row],[Part.]])+SUMIFS(BD.PD[Pago 2],BD.PD[Per.P2],AE$1,BD.PD[Pos],Tabla3[[#This Row],[Part.]])+SUMIFS(BD.PD[Pago 3],BD.PD[Per.P3],AE$1,BD.PD[Pos],Tabla3[[#This Row],[Part.]])+SUMIFS(BD.PD[Pago 4],BD.PD[Per.P4],AE$1,BD.PD[Pos],Tabla3[[#This Row],[Part.]])+SUMIFS(BD.PD[Pago 5],BD.PD[Per.P5],AE$1,BD.PD[Pos],Tabla3[[#This Row],[Part.]]) -> 0 | AF17: =SUMIFS(BD.PD[Pago 1],BD.PD[Per.P1],AF$1,BD.PD[Pos],Tabla3[[#This Row],[Part.]])+SUMIFS(BD.PD[Pago 2],BD.PD[Per.P2],AF$1,BD.PD[Pos],Tabla3[[#This Row],[Part.]])+SUMIFS(BD.PD[Pago 3],BD.PD[Per.P3],AF$1,BD.PD[Pos],Tabla3[[#This Row],[Part.]])+SUMIFS(BD.PD[Pago 4],BD.PD[Per.P4],AF$1,BD.PD[Pos],Tabla3[[#This Row],[Part.]])+SUMIFS(BD.PD[Pago 5],BD.PD[Per.P5],AF$1,BD.PD[Pos],Tabla3[[#This Row],[Part.]]) -> 0 | AG17: =SUMIFS(BD.PD[Pago 1],BD.PD[Per.P1],AG$1,BD.PD[Pos],Tabla3[[#This Row],[Part.]])+SUMIFS(BD.PD[Pago 2],BD.PD[Per.P2],AG$1,BD.PD[Pos],Tabla3[[#This Row],[Part.]])+SUMIFS(BD.PD[Pago 3],BD.PD[Per.P3],AG$1,BD.PD[Pos],Tabla3[[#This Row],[Part.]])+SUMIFS(BD.PD[Pago 4],BD.PD[Per.P4],AG$1,BD.PD[Pos],Tabla3[[#This Row],[Part.]])+SUMIFS(BD.PD[Pago 5],BD.PD[Per.P5],AG$1,BD.PD[Pos],Tabla3[[#This Row],[Part.]]) -> 0 | AH17: =SUM(Tabla3[[#This Row],[P1]:[P24]]) -> 526280.58
A18: 2.02 | B18: =VLOOKUP(Tabla3[[#This Row],[Part.]],PPto[],3,FALSE) -> 2.02 Edificación - Estructura Metálica | C18: =SUMIF(BD.PD[Pos],Tabla3[[#This Row],[Part.]],BD.PD[Ppto. Orden Interna '[DOP']]) -> 0 | D18: =SUMIFS(BD.PD[Pago 1],BD.PD[Per.P1],D$1,BD.PD[Pos],Tabla3[[#This Row],[Part.]])+SUMIFS(BD.PD[Pago 2],BD.PD[Per.P2],D$1,BD.PD[Pos],Tabla3[[#This Row],[Part.]])+SUMIFS(BD.PD[Pago 3],BD.PD[Per.P3],D$1,BD.PD[Pos],Tabla3[[#This Row],[Part.]])+SUMIFS(BD.PD[Pago 4],BD.PD[Per.P4],D$1,BD.PD[Pos],Tabla3[[#This Row],[Part.]])+SUMIFS(BD.PD[Pago 5],BD.PD[Per.P5],D$1,BD.PD[Pos],Tabla3[[#This Row],[Part.]]) -> 0 | E18: =SUMIFS(BD.PD[Pago 1],BD.PD[Per.P1],E$1,BD.PD[Pos],Tabla3[[#This Row],[Part.]])+SUMIFS(BD.PD[Pago 2],BD.PD[Per.P2],E$1,BD.PD[Pos],Tabla3[[#This Row],[Part.]])+SUMIFS(BD.PD[Pago 3],BD.PD[Per.P3],E$1,BD.PD[Pos],Tabla3[[#This Row],[Part.]])+SUMIFS(BD.PD[Pago 4],BD.PD[Per.P4],E$1,BD.PD[Pos],Tabla3[[#This Row],[Part.]])+SUMIFS(BD.PD[Pago 5],BD.PD[Per.P5],E$1,BD.PD[Pos],Tabla3[[#This Row],[Part.]]) -> 0 | F18: =SUMIFS(BD.PD[Pago 1],BD.PD[Per.P1],F$1,BD.PD[Pos],Tabla3[[#This Row],[Part.]])+SUMIFS(BD.PD[Pago 2],BD.PD[Per.P2],F$1,BD.PD[Pos],Tabla3[[#This Row],[Part.]])+SUMIFS(BD.PD[Pago 3],BD.PD[Per.P3],F$1,BD.PD[Pos],Tabla3[[#This Row],[Part.]])+SUMIFS(BD.PD[Pago 4],BD.PD[Per.P4],F$1,BD.PD[Pos],Tabla3[[#This Row],[Part.]])+SUMIFS(BD.PD[Pago 5],BD.PD[Per.P5],F$1,BD.PD[Pos],Tabla3[[#This Row],[Part.]]) -> 0 | G18: =SUMIFS(BD.PD[Pago 1],BD.PD[Per.P1],G$1,BD.PD[Pos],Tabla3[[#This Row],[Part.]])+SUMIFS(BD.PD[Pago 2],BD.PD[Per.P2],G$1,BD.PD[Pos],Tabla3[[#This Row],[Part.]])+SUMIFS(BD.PD[Pago 3],BD.PD[Per.P3],G$1,BD.PD[Pos],Tabla3[[#This Row],[Part.]])+SUMIFS(BD.PD[Pago 4],BD.PD[Per.P4],G$1,BD.PD[Pos],Tabla3[[#This Row],[Part.]])+SUMIFS(BD.PD[Pago 5],BD.PD[Per.P5],G$1,BD.PD[Pos],Tabla3[[#This Row],[Part.]]) -> 0 | H18: =SUMIFS(BD.PD[Pago 1],BD.PD[Per.P1],H$1,BD.PD[Pos],Tabla3[[#This Row],[Part.]])+SUMIFS(BD.PD[Pago 2],BD.PD[Per.P2],H$1,BD.PD[Pos],Tabla3[[#This Row],[Part.]])+SUMIFS(BD.PD[Pago 3],BD.PD[Per.P3],H$1,BD.PD[Pos],Tabla3[[#This Row],[Part.]])+SUMIFS(BD.PD[Pago 4],BD.PD[Per.P4],H$1,BD.PD[Pos],Tabla3[[#This Row],[Part.]])+SUMIFS(BD.PD[Pago 5],BD.PD[Per.P5],H$1,BD.PD[Pos],Tabla3[[#This Row],[Part.]]) -> 0 | I18: =SUMIFS(BD.PD[Pago 1],BD.PD[Per.P1],I$1,BD.PD[Pos],Tabla3[[#This Row],[Part.]])+SUMIFS(BD.PD[Pago 2],BD.PD[Per.P2],I$1,BD.PD[Pos],Tabla3[[#This Row],[Part.]])+SUMIFS(BD.PD[Pago 3],BD.PD[Per.P3],I$1,BD.PD[Pos],Tabla3[[#This Row],[Part.]])+SUMIFS(BD.PD[Pago 4],BD.PD[Per.P4],I$1,BD.PD[Pos],Tabla3[[#This Row],[Part.]])+SUMIFS(BD.PD[Pago 5],BD.PD[Per.P5],I$1,BD.PD[Pos],Tabla3[[#This Row],[Part.]]) -> 0 | J18: =SUMIFS(BD.PD[Pago 1],BD.PD[Per.P1],J$1,BD.PD[Pos],Tabla3[[#This Row],[Part.]])+SUMIFS(BD.PD[Pago 2],BD.PD[Per.P2],J$1,BD.PD[Pos],Tabla3[[#This Row],[Part.]])+SUMIFS(BD.PD[Pago 3],BD.PD[Per.P3],J$1,BD.PD[Pos],Tabla3[[#This Row],[Part.]])+SUMIFS(BD.PD[Pago 4],BD.PD[Per.P4],J$1,BD.PD[Pos],Tabla3[[#This Row],[Part.]])+SUMIFS(BD.PD[Pago 5],BD.PD[Per.P5],J$1,BD.PD[Pos],Tabla3[[#This Row],[Part.]]) -> 0 | K18: =SUMIFS(BD.PD[Pago 1],BD.PD[Per.P1],K$1,BD.PD[Pos],Tabla3[[#This Row],[Part.]])+SUMIFS(BD.PD[Pago 2],BD.PD[Per.P2],K$1,BD.PD[Pos],Tabla3[[#This Row],[Part.]])+SUMIFS(BD.PD[Pago 3],BD.PD[Per.P3],K$1,BD.PD[Pos],Tabla3[[#This Row],[Part.]])+SUMIFS(BD.PD[Pago 4],BD.PD[Per.P4],K$1,BD.PD[Pos],Tabla3[[#This Row],[Part.]])+SUMIFS(BD.PD[Pago 5],BD.PD[Per.P5],K$1,BD.PD[Pos],Tabla3[[#This Row],[Part.]]) -> 0 | ... AG18: =SUMIFS(BD.PD[Pago 1],BD.PD[Per.P1],AG$1,BD.PD[Pos],Tabla3[[#This Row],[Part.]])+SUMIFS(BD.PD[Pago 2],BD.PD[Per.P2],AG$1,BD.PD[Pos],Tabla3[[#This Row],[Part.]])+SUMIFS(BD.PD[Pago 3],BD.PD[Per.P3],AG$1,BD.PD[Pos],Tabla3[[#This Row],[Part.]])+SUMIFS(BD.PD[Pago 4],BD.PD[Per.P4],AG$1,BD.PD[Pos],Tabla3[[#This Row],[Part.]])+SUMIFS(BD.PD[Pago 5],BD.PD[Per.P5],AG$1,BD.PD[Pos],Tabla3[[#This Row],[Part.]]) -> 0 | AH18: =SUM(Tabla3[[#This Row],[P1]:[P24]]) -> 0
A19: 2.03 | B19: =VLOOKUP(Tabla3[[#This Row],[Part.]],PPto[],3,FALSE) -> 2.03 Edificación - Techo S.S. y Cerramientos Multipanel | C19: =SUMIF(BD.PD[Pos],Tabla3[[#This Row],[Part.]],BD.PD[Ppto. Orden Interna '[DOP']]) -> 0 | D19: =SUMIFS(BD.PD[Pago 1],BD.PD[Per.P1],D$1,BD.PD[Pos],Tabla3[[#This Row],[Part.]])+SUMIFS(BD.PD[Pago 2],BD.PD[Per.P2],D$1,BD.PD[Pos],Tabla3[[#This Row],[Part.]])+SUMIFS(BD.PD[Pago 3],BD.PD[Per.P3],D$1,BD.PD[Pos],Tabla3[[#This Row],[Part.]])+SUMIFS(BD.PD[Pago 4],BD.PD[Per.P4],D$1,BD.PD[Pos],Tabla3[[#This Row],[Part.]])+SUMIFS(BD.PD[Pago 5],BD.PD[Per.P5],D$1,BD.PD[Pos],Tabla3[[#This Row],[Part.]]) -> 0 | E19: =SUMIFS(BD.PD[Pago 1],BD.PD[Per.P1],E$1,BD.PD[Pos],Tabla3[[#This Row],[Part.]])+SUMIFS(BD.PD[Pago 2],BD.PD[Per.P2],E$1,BD.PD[Pos],Tabla3[[#This Row],[Part.]])+SUMIFS(BD.PD[Pago 3],BD.PD[Per.P3],E$1,BD.PD[Pos],Tabla3[[#This Row],[Part.]])+SUMIFS(BD.PD[Pago 4],BD.PD[Per.P4],E$1,BD.PD[Pos],Tabla3[[#This Row],[Part.]])+SUMIFS(BD.PD[Pago 5],BD.PD[Per.P5],E$1,BD.PD[Pos],Tabla3[[#This Row],[Part.]]) -> 0 | F19: =SUMIFS(BD.PD[Pago 1],BD.PD[Per.P1],F$1,BD.PD[Pos],Tabla3[[#This Row],[Part.]])+SUMIFS(BD.PD[Pago 2],BD.PD[Per.P2],F$1,BD.PD[Pos],Tabla3[[#This Row],[Part.]])+SUMIFS(BD.PD[Pago 3],BD.PD[Per.P3],F$1,BD.PD[Pos],Tabla3[[#This Row],[Part.]])+SUMIFS(BD.PD[Pago 4],BD.PD[Per.P4],F$1,BD.PD[Pos],Tabla3[[#This Row],[Part.]])+SUMIFS(BD.PD[Pago 5],BD.PD[Per.P5],F$1,BD.PD[Pos],Tabla3[[#This Row],[Part.]]) -> 0 | G19: =SUMIFS(BD.PD[Pago 1],BD.PD[Per.P1],G$1,BD.PD[Pos],Tabla3[[#This Row],[Part.]])+SUMIFS(BD.PD[Pago 2],BD.PD[Per.P2],G$1,BD.PD[Pos],Tabla3[[#This Row],[Part.]])+SUMIFS(BD.PD[Pago 3],BD.PD[Per.P3],G$1,BD.PD[Pos],Tabla3[[#This Row],[Part.]])+SUMIFS(BD.PD[Pago 4],BD.PD[Per.P4],G$1,BD.PD[Pos],Tabla3[[#This Row],[Part.]])+SUMIFS(BD.PD[Pago 5],BD.PD[Per.P5],G$1,BD.PD[Pos],Tabla3[[#This Row],[Part.]]) -> 0 | H19: =SUMIFS(BD.PD[Pago 1],BD.PD[Per.P1],H$1,BD.PD[Pos],Tabla3[[#This Row],[Part.]])+SUMIFS(BD.PD[Pago 2],BD.PD[Per.P2],H$1,BD.PD[Pos],Tabla3[[#This Row],[Part.]])+SUMIFS(BD.PD[Pago 3],BD.PD[Per.P3],H$1,BD.PD[Pos],Tabla3[[#This Row],[Part.]])+SUMIFS(BD.PD[Pago 4],BD.PD[Per.P4],H$1,BD.PD[Pos],Tabla3[[#This Row],[Part.]])+SUMIFS(BD.PD[Pago 5],BD.PD[Per.P5],H$1,BD.PD[Pos],Tabla3[[#This Row],[Part.]]) -> 0 | I19: =SUMIFS(BD.PD[Pago 1],BD.PD[Per.P1],I$1,BD.PD[Pos],Tabla3[[#This Row],[Part.]])+SUMIFS(BD.PD[Pago 2],BD.PD[Per.P2],I$1,BD.PD[Pos],Tabla3[[#This Row],[Part.]])+SUMIFS(BD.PD[Pago 3],BD.PD[Per.P3],I$1,BD.PD[Pos],Tabla3[[#This Row],[Part.]])+SUMIFS(BD.PD[Pago 4],BD.PD[Per.P4],I$1,BD.PD[Pos],Tabla3[[#This Row],[Part.]])+SUMIFS(BD.PD[Pago 5],BD.PD[Per.P5],I$1,BD.PD[Pos],Tabla3[[#This Row],[Part.]]) -> 0 | J19: =SUMIFS(BD.PD[Pago 1],BD.PD[Per.P1],J$1,BD.PD[Pos],Tabla3[[#This Row],[Part.]])+SUMIFS(BD.PD[Pago 2],BD.PD[Per.P2],J$1,BD.PD[Pos],Tabla3[[#This Row],[Part.]])+SUMIFS(BD.PD[Pago 3],BD.PD[Per.P3],J$1,BD.PD[Pos],Tabla3[[#This Row],[Part.]])+SUMIFS(BD.PD[Pago 4],BD.PD[Per.P4],J$1,BD.PD[Pos],Tabla3[[#This Row],[Part.]])+SUMIFS(BD.PD[Pago 5],BD.PD[Per.P5],J$1,BD.PD[Pos],Tabla3[[#This Row],[Part.]]) -> 0 | K19: =SUMIFS(BD.PD[Pago 1],BD.PD[Per.P1],K$1,BD.PD[Pos],Tabla3[[#This Row],[Part.]])+SUMIFS(BD.PD[Pago 2],BD.PD[Per.P2],K$1,BD.PD[Pos],Tabla3[[#This Row],[Part.]])+SUMIFS(BD.PD[Pago 3],BD.PD[Per.P3],K$1,BD.PD[Pos],Tabla3[[#This Row],[Part.]])+SUMIFS(BD.PD[Pago 4],BD.PD[Per.P4],K$1,BD.PD[Pos],Tabla3[[#This Row],[Part.]])+SUMIFS(BD.PD[Pago 5],BD.PD[Per.P5],K$1,BD.PD[Pos],Tabla3[[#This Row],[Part.]]) -> 0 | ... AG19: =SUMIFS(BD.PD[Pago 1],BD.PD[Per.P1],AG$1,BD.PD[Pos],Tabla3[[#This Row],[Part.]])+SUMIFS(BD.PD[Pago 2],BD.PD[Per.P2],AG$1,BD.PD[Pos],Tabla3[[#This Row],[Part.]])+SUMIFS(BD.PD[Pago 3],BD.PD[Per.P3],AG$1,BD.PD[Pos],Tabla3[[#This Row],[Part.]])+SUMIFS(BD.PD[Pago 4],BD.PD[Per.P4],AG$1,BD.PD[Pos],Tabla3[[#This Row],[Part.]])+SUMIFS(BD.PD[Pago 5],BD.PD[Per.P5],AG$1,BD.PD[Pos],Tabla3[[#This Row],[Part.]]) -> 0 | AH19: =SUM(Tabla3[[#This Row],[P1]:[P24]]) -> 0
A20: 2.04 | B20: =VLOOKUP(Tabla3[[#This Row],[Part.]],PPto[],3,FALSE) -> 2.04 Edificación - Tragaluces "Skylights" | C20: =SUMIF(BD.PD[Pos],Tabla3[[#This Row],[Part.]],BD.PD[Ppto. Orden Interna '[DOP']]) -> 0 | D20: =SUMIFS(BD.PD[Pago 1],BD.PD[Per.P1],D$1,BD.PD[Pos],Tabla3[[#This Row],[Part.]])+SUMIFS(BD.PD[Pago 2],BD.PD[Per.P2],D$1,BD.PD[Pos],Tabla3[[#This Row],[Part.]])+SUMIFS(BD.PD[Pago 3],BD.PD[Per.P3],D$1,BD.PD[Pos],Tabla3[[#This Row],[Part.]])+SUMIFS(BD.PD[Pago 4],BD.PD[Per.P4],D$1,BD.PD[Pos],Tabla3[[#This Row],[Part.]])+SUMIFS(BD.PD[Pago 5],BD.PD[Per.P5],D$1,BD.PD[Pos],Tabla3[[#This Row],[Part.]]) -> 0 | E20: =SUMIFS(BD.PD[Pago 1],BD.PD[Per.P1],E$1,BD.PD[Pos],Tabla3[[#This Row],[Part.]])+SUMIFS(BD.PD[Pago 2],BD.PD[Per.P2],E$1,BD.PD[Pos],Tabla3[[#This Row],[Part.]])+SUMIFS(BD.PD[Pago 3],BD.PD[Per.P3],E$1,BD.PD[Pos],Tabla3[[#This Row],[Part.]])+SUMIFS(BD.PD[Pago 4],BD.PD[Per.P4],E$1,BD.PD[Pos],Tabla3[[#This Row],[Part.]])+SUMIFS(BD.PD[Pago 5],BD.PD[Per.P5],E$1,BD.PD[Pos],Tabla3[[#This Row],[Part.]]) -> 0 | F20: =SUMIFS(BD.PD[Pago 1],BD.PD[Per.P1],F$1,BD.PD[Pos],Tabla3[[#This Row],[Part.]])+SUMIFS(BD.PD[Pago 2],BD.PD[Per.P2],F$1,BD.PD[Pos],Tabla3[[#This Row],[Part.]])+SUMIFS(BD.PD[Pago 3],BD.PD[Per.P3],F$1,BD.PD[Pos],Tabla3[[#This Row],[Part.]])+SUMIFS(BD.PD[Pago 4],BD.PD[Per.P4],F$1,BD.PD[Pos],Tabla3[[#This Row],[Part.]])+SUMIFS(BD.PD[Pago 5],BD.PD[Per.P5],F$1,BD.PD[Pos],Tabla3[[#This Row],[Part.]]) -> 0 | G20: =SUMIFS(BD.PD[Pago 1],BD.PD[Per.P1],G$1,BD.PD[Pos],Tabla3[[#This Row],[Part.]])+SUMIFS(BD.PD[Pago 2],BD.PD[Per.P2],G$1,BD.PD[Pos],Tabla3[[#This Row],[Part.]])+SUMIFS(BD.PD[Pago 3],BD.PD[Per.P3],G$1,BD.PD[Pos],Tabla3[[#This Row],[Part.]])+SUMIFS(BD.PD[Pago 4],BD.PD[Per.P4],G$1,BD.PD[Pos],Tabla3[[#This Row],[Part.]])+SUMIFS(BD.PD[Pago 5],BD.PD[Per.P5],G$1,BD.PD[Pos],Tabla3[[#This Row],[Part.]]) -> 0 | H20: =SUMIFS(BD.PD[Pago 1],BD.PD[Per.P1],H$1,BD.PD[Pos],Tabla3[[#This Row],[Part.]])+SUMIFS(BD.PD[Pago 2],BD.PD[Per.P2],H$1,BD.PD[Pos],Tabla3[[#This Row],[Part.]])+SUMIFS(BD.PD[Pago 3],BD.PD[Per.P3],H$1,BD.PD[Pos],Tabla3[[#This Row],[Part.]])+SUMIFS(BD.PD[Pago 4],BD.PD[Per.P4],H$1,BD.PD[Pos],Tabla3[[#This Row],[Part.]])+SUMIFS(BD.PD[Pago 5],BD.PD[Per.P5],H$1,BD.PD[Pos],Tabla3[[#This Row],[Part.]]) -> 0 | I20: =SUMIFS(BD.PD[Pago 1],BD.PD[Per.P1],I$1,BD.PD[Pos],Tabla3[[#This Row],[Part.]])+SUMIFS(BD.PD[Pago 2],BD.PD[Per.P2],I$1,BD.PD[Pos],Tabla3[[#This Row],[Part.]])+SUMIFS(BD.PD[Pago 3],BD.PD[Per.P3],I$1,BD.PD[Pos],Tabla3[[#This Row],[Part.]])+SUMIFS(BD.PD[Pago 4],BD.PD[Per.P4],I$1,BD.PD[Pos],Tabla3[[#This Row],[Part.]])+SUMIFS(BD.PD[Pago 5],BD.PD[Per.P5],I$1,BD.PD[Pos],Tabla3[[#This Row],[Part.]]) -> 0 | J20: =SUMIFS(BD.PD[Pago 1],BD.PD[Per.P1],J$1,BD.PD[Pos],Tabla3[[#This Row],[Part.]])+SUMIFS(BD.PD[Pago 2],BD.PD[Per.P2],J$1,BD.PD[Pos],Tabla3[[#This Row],[Part.]])+SUMIFS(BD.PD[Pago 3],BD.PD[Per.P3],J$1,BD.PD[Pos],Tabla3[[#This Row],[Part.]])+SUMIFS(BD.PD[Pago 4],BD.PD[Per.P4],J$1,BD.PD[Pos],Tabla3[[#This Row],[Part.]])+SUMIFS(BD.PD[Pago 5],BD.PD[Per.P5],J$1,BD.PD[Pos],Tabla3[[#This Row],[Part.]]) -> 0 | K20: =SUMIFS(BD.PD[Pago 1],BD.PD[Per.P1],K$1,BD.PD[Pos],Tabla3[[#This Row],[Part.]])+SUMIFS(BD.PD[Pago 2],BD.PD[Per.P2],K$1,BD.PD[Pos],Tabla3[[#This Row],[Part.]])+SUMIFS(BD.PD[Pago 3],BD.PD[Per.P3],K$1,BD.PD[Pos],Tabla3[[#This Row],[Part.]])+SUMIFS(BD.PD[Pago 4],BD.PD[Per.P4],K$1,BD.PD[Pos],Tabla3[[#This Row],[Part.]])+SUMIFS(BD.PD[Pago 5],BD.PD[Per.P5],K$1,BD.PD[Pos],Tabla3[[#This Row],[Part.]]) -> 0 | ... AG20: =SUMIFS(BD.PD[Pago 1],BD.PD[Per.P1],AG$1,BD.PD[Pos],Tabla3[[#This Row],[Part.]])+SUMIFS(BD.PD[Pago 2],BD.PD[Per.P2],AG$1,BD.PD[Pos],Tabla3[[#This Row],[Part.]])+SUMIFS(BD.PD[Pago 3],BD.PD[Per.P3],AG$1,BD.PD[Pos],Tabla3[[#This Row],[Part.]])+SUMIFS(BD.PD[Pago 4],BD.PD[Per.P4],AG$1,BD.PD[Pos],Tabla3[[#This Row],[Part.]])+SUMIFS(BD.PD[Pago 5],BD.PD[Per.P5],AG$1,BD.PD[Pos],Tabla3[[#This Row],[Part.]]) -> 0 | AH20: =SUM(Tabla3[[#This Row],[P1]:[P24]]) -> 0
A21: 2.05 | B21: =VLOOKUP(Tabla3[[#This Row],[Part.]],PPto[],3,FALSE) -> 2.05 Instalaciones Sanitarias | C21: =SUMIF(BD.PD[Pos],Tabla3[[#This Row],[Part.]],BD.PD[Ppto. Orden Interna '[DOP']]) -> 1071000 | D21: =SUMIFS(BD.PD[Pago 1],BD.PD[Per.P1],D$1,BD.PD[Pos],Tabla3[[#This Row],[Part.]])+SUMIFS(BD.PD[Pago 2],BD.PD[Per.P2],D$1,BD.PD[Pos],Tabla3[[#This Row],[Part.]])+SUMIFS(BD.PD[Pago 3],BD.PD[Per.P3],D$1,BD.PD[Pos],Tabla3[[#This Row],[Part.]])+SUMIFS(BD.PD[Pago 4],BD.PD[Per.P4],D$1,BD.PD[Pos],Tabla3[[#This Row],[Part.]])+SUMIFS(BD.PD[Pago 5],BD.PD[Per.P5],D$1,BD.PD[Pos],Tabla3[[#This Row],[Part.]]) -> 0 | E21: =SUMIFS(BD.PD[Pago 1],BD.PD[Per.P1],E$1,BD.PD[Pos],Tabla3[[#This Row],[Part.]])+SUMIFS(BD.PD[Pago 2],BD.PD[Per.P2],E$1,BD.PD[Pos],Tabla3[[#This Row],[Part.]])+SUMIFS(BD.PD[Pago 3],BD.PD[Per.P3],E$1,BD.PD[Pos],Tabla3[[#This Row],[Part.]])+SUMIFS(BD.PD[Pago 4],BD.PD[Per.P4],E$1,BD.PD[Pos],Tabla3[[#This Row],[Part.]])+SUMIFS(BD.PD[Pago 5],BD.PD[Per.P5],E$1,BD.PD[Pos],Tabla3[[#This Row],[Part.]]) -> 0 | F21: =SUMIFS(BD.PD[Pago 1],BD.PD[Per.P1],F$1,BD.PD[Pos],Tabla3[[#This Row],[Part.]])+SUMIFS(BD.PD[Pago 2],BD.PD[Per.P2],F$1,BD.PD[Pos],Tabla3[[#This Row],[Part.]])+SUMIFS(BD.PD[Pago 3],BD.PD[Per.P3],F$1,BD.PD[Pos],Tabla3[[#This Row],[Part.]])+SUMIFS(BD.PD[Pago 4],BD.PD[Per.P4],F$1,BD.PD[Pos],Tabla3[[#This Row],[Part.]])+SUMIFS(BD.PD[Pago 5],BD.PD[Per.P5],F$1,BD.PD[Pos],Tabla3[[#This Row],[Part.]]) -> 0 | G21: =SUMIFS(BD.PD[Pago 1],BD.PD[Per.P1],G$1,BD.PD[Pos],Tabla3[[#This Row],[Part.]])+SUMIFS(BD.PD[Pago 2],BD.PD[Per.P2],G$1,BD.PD[Pos],Tabla3[[#This Row],[Part.]])+SUMIFS(BD.PD[Pago 3],BD.PD[Per.P3],G$1,BD.PD[Pos],Tabla3[[#This Row],[Part.]])+SUMIFS(BD.PD[Pago 4],BD.PD[Per.P4],G$1,BD.PD[Pos],Tabla3[[#This Row],[Part.]])+SUMIFS(BD.PD[Pago 5],BD.PD[Per.P5],G$1,BD.PD[Pos],Tabla3[[#This Row],[Part.]]) -> 0 | H21: =SUMIFS(BD.PD[Pago 1],BD.PD[Per.P1],H$1,BD.PD[Pos],Tabla3[[#This Row],[Part.]])+SUMIFS(BD.PD[Pago 2],BD.PD[Per.P2],H$1,BD.PD[Pos],Tabla3[[#This Row],[Part.]])+SUMIFS(BD.PD[Pago 3],BD.PD[Per.P3],H$1,BD.PD[Pos],Tabla3[[#This Row],[Part.]])+SUMIFS(BD.PD[Pago 4],BD.PD[Per.P4],H$1,BD.PD[Pos],Tabla3[[#This Row],[Part.]])+SUMIFS(BD.PD[Pago 5],BD.PD[Per.P5],H$1,BD.PD[Pos],Tabla3[[#This Row],[Part.]]) -> 0 | I21: =SUMIFS(BD.PD[Pago 1],BD.PD[Per.P1],I$1,BD.PD[Pos],Tabla3[[#This Row],[Part.]])+SUMIFS(BD.PD[Pago 2],BD.PD[Per.P2],I$1,BD.PD[Pos],Tabla3[[#This Row],[Part.]])+SUMIFS(BD.PD[Pago 3],BD.PD[Per.P3],I$1,BD.PD[Pos],Tabla3[[#This Row],[Part.]])+SUMIFS(BD.PD[Pago 4],BD.PD[Per.P4],I$1,BD.PD[Pos],Tabla3[[#This Row],[Part.]])+SUMIFS(BD.PD[Pago 5],BD.PD[Per.P5],I$1,BD.PD[Pos],Tabla3[[#This Row],[Part.]]) -> 0 | J21: =SUMIFS(BD.PD[Pago 1],BD.PD[Per.P1],J$1,BD.PD[Pos],Tabla3[[#This Row],[Part.]])+SUMIFS(BD.PD[Pago 2],BD.PD[Per.P2],J$1,BD.PD[Pos],Tabla3[[#This Row],[Part.]])+SUMIFS(BD.PD[Pago 3],BD.PD[Per.P3],J$1,BD.PD[Pos],Tabla3[[#This Row],[Part.]])+SUMIFS(BD.PD[Pago 4],BD.PD[Per.P4],J$1,BD.PD[Pos],Tabla3[[#This Row],[Part.]])+SUMIFS(BD.PD[Pago 5],BD.PD[Per.P5],J$1,BD.PD[Pos],Tabla3[[#This Row],[Part.]]) -> 0 | K21: =SUMIFS(BD.PD[Pago 1],BD.PD[Per.P1],K$1,BD.PD[Pos],Tabla3[[#This Row],[Part.]])+SUMIFS(BD.PD[Pago 2],BD.PD[Per.P2],K$1,BD.PD[Pos],Tabla3[[#This Row],[Part.]])+SUMIFS(BD.PD[Pago 3],BD.PD[Per.P3],K$1,BD.PD[Pos],Tabla3[[#This Row],[Part.]])+SUMIFS(BD.PD[Pago 4],BD.PD[Per.P4],K$1,BD.PD[Pos],Tabla3[[#This Row],[Part.]])+SUMIFS(BD.PD[Pago 5],BD.PD[Per.P5],K$1,BD.PD[Pos],Tabla3[[#This Row],[Part.]]) -> 0 | ... AG21: =SUMIFS(BD.PD[Pago 1],BD.PD[Per.P1],AG$1,BD.PD[Pos],Tabla3[[#This Row],[Part.]])+SUMIFS(BD.PD[Pago 2],BD.PD[Per.P2],AG$1,BD.PD[Pos],Tabla3[[#This Row],[Part.]])+SUMIFS(BD.PD[Pago 3],BD.PD[Per.P3],AG$1,BD.PD[Pos],Tabla3[[#This Row],[Part.]])+SUMIFS(BD.PD[Pago 4],BD.PD[Per.P4],AG$1,BD.PD[Pos],Tabla3[[#This Row],[Part.]])+SUMIFS(BD.PD[Pago 5],BD.PD[Per.P5],AG$1,BD.PD[Pos],Tabla3[[#This Row],[Part.]]) -> 0 | AH21: =SUM(Tabla3[[#This Row],[P1]:[P24]]) -> 1071000
A22: 2.06 | B22: =VLOOKUP(Tabla3[[#This Row],[Part.]],PPto[],3,FALSE) -> 2.06 Instalación de Gas | C22: =SUMIF(BD.PD[Pos],Tabla3[[#This Row],[Part.]],BD.PD[Ppto. Orden Interna '[DOP']]) -> 0 | D22: =SUMIFS(BD.PD[Pago 1],BD.PD[Per.P1],D$1,BD.PD[Pos],Tabla3[[#This Row],[Part.]])+SUMIFS(BD.PD[Pago 2],BD.PD[Per.P2],D$1,BD.PD[Pos],Tabla3[[#This Row],[Part.]])+SUMIFS(BD.PD[Pago 3],BD.PD[Per.P3],D$1,BD.PD[Pos],Tabla3[[#This Row],[Part.]])+SUMIFS(BD.PD[Pago 4],BD.PD[Per.P4],D$1,BD.PD[Pos],Tabla3[[#This Row],[Part.]])+SUMIFS(BD.PD[Pago 5],BD.PD[Per.P5],D$1,BD.PD[Pos],Tabla3[[#This Row],[Part.]]) -> 0 | E22: =SUMIFS(BD.PD[Pago 1],BD.PD[Per.P1],E$1,BD.PD[Pos],Tabla3[[#This Row],[Part.]])+SUMIFS(BD.PD[Pago 2],BD.PD[Per.P2],E$1,BD.PD[Pos],Tabla3[[#This Row],[Part.]])+SUMIFS(BD.PD[Pago 3],BD.PD[Per.P3],E$1,BD.PD[Pos],Tabla3[[#This Row],[Part.]])+SUMIFS(BD.PD[Pago 4],BD.PD[Per.P4],E$1,BD.PD[Pos],Tabla3[[#This Row],[Part.]])+SUMIFS(BD.PD[Pago 5],BD.PD[Per.P5],E$1,BD.PD[Pos],Tabla3[[#This Row],[Part.]]) -> 0 | F22: =SUMIFS(BD.PD[Pago 1],BD.PD[Per.P1],F$1,BD.PD[Pos],Tabla3[[#This Row],[Part.]])+SUMIFS(BD.PD[Pago 2],BD.PD[Per.P2],F$1,BD.PD[Pos],Tabla3[[#This Row],[Part.]])+SUMIFS(BD.PD[Pago 3],BD.PD[Per.P3],F$1,BD.PD[Pos],Tabla3[[#This Row],[Part.]])+SUMIFS(BD.PD[Pago 4],BD.PD[Per.P4],F$1,BD.PD[Pos],Tabla3[[#This Row],[Part.]])+SUMIFS(BD.PD[Pago 5],BD.PD[Per.P5],F$1,BD.PD[Pos],Tabla3[[#This Row],[Part.]]) -> 0 | G22: =SUMIFS(BD.PD[Pago 1],BD.PD[Per.P1],G$1,BD.PD[Pos],Tabla3[[#This Row],[Part.]])+SUMIFS(BD.PD[Pago 2],BD.PD[Per.P2],G$1,BD.PD[Pos],Tabla3[[#This Row],[Part.]])+SUMIFS(BD.PD[Pago 3],BD.PD[Per.P3],G$1,BD.PD[Pos],Tabla3[[#This Row],[Part.]])+SUMIFS(BD.PD[Pago 4],BD.PD[Per.P4],G$1,BD.PD[Pos],Tabla3[[#This Row],[Part.]])+SUMIFS(BD.PD[Pago 5],BD.PD[Per.P5],G$1,BD.PD[Pos],Tabla3[[#This Row],[Part.]]) -> 0 | H22: =SUMIFS(BD.PD[Pago 1],BD.PD[Per.P1],H$1,BD.PD[Pos],Tabla3[[#This Row],[Part.]])+SUMIFS(BD.PD[Pago 2],BD.PD[Per.P2],H$1,BD.PD[Pos],Tabla3[[#This Row],[Part.]])+SUMIFS(BD.PD[Pago 3],BD.PD[Per.P3],H$1,BD.PD[Pos],Tabla3[[#This Row],[Part.]])+SUMIFS(BD.PD[Pago 4],BD.PD[Per.P4],H$1,BD.PD[Pos],Tabla3[[#This Row],[Part.]])+SUMIFS(BD.PD[Pago 5],BD.PD[Per.P5],H$1,BD.PD[Pos],Tabla3[[#This Row],[Part.]]) -> 0 | I22: =SUMIFS(BD.PD[Pago 1],BD.PD[Per.P1],I$1,BD.PD[Pos],Tabla3[[#This Row],[Part.]])+SUMIFS(BD.PD[Pago 2],BD.PD[Per.P2],I$1,BD.PD[Pos],Tabla3[[#This Row],[Part.]])+SUMIFS(BD.PD[Pago 3],BD.PD[Per.P3],I$1,BD.PD[Pos],Tabla3[[#This Row],[Part.]])+SUMIFS(BD.PD[Pago 4],BD.PD[Per.P4],I$1,BD.PD[Pos],Tabla3[[#This Row],[Part.]])+SUMIFS(BD.PD[Pago 5],BD.PD[Per.P5],I$1,BD.PD[Pos],Tabla3[[#This Row],[Part.]]) -> 0 | J22: =SUMIFS(BD.PD[Pago 1],BD.PD[Per.P1],J$1,BD.PD[Pos],Tabla3[[#This Row],[Part.]])+SUMIFS(BD.PD[Pago 2],BD.PD[Per.P2],J$1,BD.PD[Pos],Tabla3[[#This Row],[Part.]])+SUMIFS(BD.PD[Pago 3],BD.PD[Per.P3],J$1,BD.PD[Pos],Tabla3[[#This Row],[Part.]])+SUMIFS(BD.PD[Pago 4],BD.PD[Per.P4],J$1,BD.PD[Pos],Tabla3[[#This Row],[Part.]])+SUMIFS(BD.PD[Pago 5],BD.PD[Per.P5],J$1,BD.PD[Pos],Tabla3[[#This Row],[Part.]]) -> 0 | K22: =SUMIFS(BD.PD[Pago 1],BD.PD[Per.P1],K$1,BD.PD[Pos],Tabla3[[#This Row],[Part.]])+SUMIFS(BD.PD[Pago 2],BD.PD[Per.P2],K$1,BD.PD[Pos],Tabla3[[#This Row],[Part.]])+SUMIFS(BD.PD[Pago 3],BD.PD[Per.P3],K$1,BD.PD[Pos],Tabla3[[#This Row],[Part.]])+SUMIFS(BD.PD[Pago 4],BD.PD[Per.P4],K$1,BD.PD[Pos],Tabla3[[#This Row],[Part.]])+SUMIFS(BD.PD[Pago 5],BD.PD[Per.P5],K$1,BD.PD[Pos],Tabla3[[#This Row],[Part.]]) -> 0 | ... Z22: =SUMIFS(BD.PD[Pago 1],BD.PD[Per.P1],Z$1,BD.PD[Pos],Tabla3[[#This Row],[Part.]])+SUMIFS(BD.PD[Pago 2],BD.PD[Per.P2],Z$1,BD.PD[Pos],Tabla3[[#This Row],[Part.]])+SUMIFS(BD.PD[Pago 3],BD.PD[Per.P3],Z$1,BD.PD[Pos],Tabla3[[#This Row],[Part.]])+SUMIFS(BD.PD[Pago 4],BD.PD[Per.P4],Z$1,BD.PD[Pos],Tabla3[[#This Row],[Part.]])+SUMIFS(BD.PD[Pago 5],BD.PD[Per.P5],Z$1,BD.PD[Pos],Tabla3[[#This Row],[Part.]]) -> 0 | AB22: =SUMIFS(BD.PD[Pago 1],BD.PD[Per.P1],AB$1,BD.PD[Pos],Tabla3[[#This Row],[Part.]])+SUMIFS(BD.PD[Pago 2],BD.PD[Per.P2],AB$1,BD.PD[Pos],Tabla3[[#This Row],[Part.]])+SUMIFS(BD.PD[Pago 3],BD.PD[Per.P3],AB$1,BD.PD[Pos],Tabla3[[#This Row],[Part.]])+SUMIFS(BD.PD[Pago 4],BD.PD[Per.P4],AB$1,BD.PD[Pos],Tabla3[[#This Row],[Part.]])+SUMIFS(BD.PD[Pago 5],BD.PD[Per.P5],AB$1,BD.PD[Pos],Tabla3[[#This Row],[Part.]]) -> 0 | AC22: =SUMIFS(BD.PD[Pago 1],BD.PD[Per.P1],AC$1,BD.PD[Pos],Tabla3[[#This Row],[Part.]])+SUMIFS(BD.PD[Pago 2],BD.PD[Per.P2],AC$1,BD.PD[Pos],Tabla3[[#This Row],[Part.]])+SUMIFS(BD.PD[Pago 3],BD.PD[Per.P3],AC$1,BD.PD[Pos],Tabla3[[#This Row],[Part.]])+SUMIFS(BD.PD[Pago 4],BD.PD[Per.P4],AC$1,BD.PD[Pos],Tabla3[[#This Row],[Part.]])+SUMIFS(BD.PD[Pago 5],BD.PD[Per.P5],AC$1,BD.PD[Pos],Tabla3[[#This Row],[Part.]]) -> 0 | AD22: =SUMIFS(BD.PD[Pago 1],BD.PD[Per.P1],AD$1,BD.PD[Pos],Tabla3[[#This Row],[Part.]])+SUMIFS(BD.PD[Pago 2],BD.PD[Per.P2],AD$1,BD.PD[Pos],Tabla3[[#This Row],[Part.]])+SUMIFS(BD.PD[Pago 3],BD.PD[Per.P3],AD$1,BD.PD[Pos],Tabla3[[#This Row],[Part.]])+SUMIFS(BD.PD[Pago 4],BD.PD[Per.P4],AD$1,BD.PD[Pos],Tabla3[[#This Row],[Part.]])+SUMIFS(BD.PD[Pago 5],BD.PD[Per.P5],AD$1,BD.PD[Pos],Tabla3[[#This Row],[Part.]]) -> 0 | AE22: =SUMIFS(BD.PD[Pago 1],BD.PD[Per.P1],AE$1,BD.PD[Pos],Tabla3[[#This Row],[Part.]])+SUMIFS(BD.PD[Pago 2],BD.PD[Per.P2],AE$1,BD.PD[Pos],Tabla3[[#This Row],[Part.]])+SUMIFS(BD.PD[Pago 3],BD.PD[Per.P3],AE$1,BD.PD[Pos],Tabla3[[#This Row],[Part.]])+SUMIFS(BD.PD[Pago 4],BD.PD[Per.P4],AE$1,BD.PD[Pos],Tabla3[[#This Row],[Part.]])+SUMIFS(BD.PD[Pago 5],BD.PD[Per.P5],AE$1,BD.PD[Pos],Tabla3[[#This Row],[Part.]]) -> 0 | AF22: =SUMIFS(BD.PD[Pago 1],BD.PD[Per.P1],AF$1,BD.PD[Pos],Tabla3[[#This Row],[Part.]])+SUMIFS(BD.PD[Pago 2],BD.PD[Per.P2],AF$1,BD.PD[Pos],Tabla3[[#This Row],[Part.]])+SUMIFS(BD.PD[Pago 3],BD.PD[Per.P3],AF$1,BD.PD[Pos],Tabla3[[#This Row],[Part.]])+SUMIFS(BD.PD[Pago 4],BD.PD[Per.P4],AF$1,BD.PD[Pos],Tabla3[[#This Row],[Part.]])+SUMIFS(BD.PD[Pago 5],BD.PD[Per.P5],AF$1,BD.PD[Pos],Tabla3[[#This Row],[Part.]]) -> 0 | AG22: =SUMIFS(BD.PD[Pago 1],BD.PD[Per.P1],AG$1,BD.PD[Pos],Tabla3[[#This Row],[Part.]])+SUMIFS(BD.PD[Pago 2],BD.PD[Per.P2],AG$1,BD.PD[Pos],Tabla3[[#This Row],[Part.]])+SUMIFS(BD.PD[Pago 3],BD.PD[Per.P3],AG$1,BD.PD[Pos],Tabla3[[#This Row],[Part.]])+SUMIFS(BD.PD[Pago 4],BD.PD[Per.P4],AG$1,BD.PD[Pos],Tabla3[[#This Row],[Part.]])+SUMIFS(BD.PD[Pago 5],BD.PD[Per.P5],AG$1,BD.PD[Pos],Tabla3[[#This Row],[Part.]]) -> 0 | AH22: =SUM(Tabla3[[#This Row],[P1]:[P24]]) -> 0
A23: 2.07 | B23: =VLOOKUP(Tabla3[[#This Row],[Part.]],PPto[],3,FALSE) -> 2.07 Sistema Contra Incendios | C23: =SUMIF(BD.PD[Pos],Tabla3[[#This Row],[Part.]],BD.PD[Ppto. Orden Interna '[DOP']]) -> 6294056 | D23: =SUMIFS(BD.PD[Pago 1],BD.PD[Per.P1],D$1,BD.PD[Pos],Tabla3[[#This Row],[Part.]])+SUMIFS(BD.PD[Pago 2],BD.PD[Per.P2],D$1,BD.PD[Pos],Tabla3[[#This Row],[Part.]])+SUMIFS(BD.PD[Pago 3],BD.PD[Per.P3],D$1,BD.PD[Pos],Tabla3[[#This Row],[Part.]])+SUMIFS(BD.PD[Pago 4],BD.PD[Per.P4],D$1,BD.PD[Pos],Tabla3[[#This Row],[Part.]])+SUMIFS(BD.PD[Pago 5],BD.PD[Per.P5],D$1,BD.PD[Pos],Tabla3[[#This Row],[Part.]]) -> 2505125.7 | E23: =SUMIFS(BD.PD[Pago 1],BD.PD[Per.P1],E$1,BD.PD[Pos],Tabla3[[#This Row],[Part.]])+SUMIFS(BD.PD[Pago 2],BD.PD[Per.P2],E$1,BD.PD[Pos],Tabla3[[#This Row],[Part.]])+SUMIFS(BD.PD[Pago 3],BD.PD[Per.P3],E$1,BD.PD[Pos],Tabla3[[#This Row],[Part.]])+SUMIFS(BD.PD[Pago 4],BD.PD[Per.P4],E$1,BD.PD[Pos],Tabla3[[#This Row],[Part.]])+SUMIFS(BD.PD[Pago 5],BD.PD[Per.P5],E$1,BD.PD[Pos],Tabla3[[#This Row],[Part.]]) -> 0 | F23: =SUMIFS(BD.PD[Pago 1],BD.PD[Per.P1],F$1,BD.PD[Pos],Tabla3[[#This Row],[Part.]])+SUMIFS(BD.PD[Pago 2],BD.PD[Per.P2],F$1,BD.PD[Pos],Tabla3[[#This Row],[Part.]])+SUMIFS(BD.PD[Pago 3],BD.PD[Per.P3],F$1,BD.PD[Pos],Tabla3[[#This Row],[Part.]])+SUMIFS(BD.PD[Pago 4],BD.PD[Per.P4],F$1,BD.PD[Pos],Tabla3[[#This Row],[Part.]])+SUMIFS(BD.PD[Pago 5],BD.PD[Per.P5],F$1,BD.PD[Pos],Tabla3[[#This Row],[Part.]]) -> 0 | G23: =SUMIFS(BD.PD[Pago 1],BD.PD[Per.P1],G$1,BD.PD[Pos],Tabla3[[#This Row],[Part.]])+SUMIFS(BD.PD[Pago 2],BD.PD[Per.P2],G$1,BD.PD[Pos],Tabla3[[#This Row],[Part.]])+SUMIFS(BD.PD[Pago 3],BD.PD[Per.P3],G$1,BD.PD[Pos],Tabla3[[#This Row],[Part.]])+SUMIFS(BD.PD[Pago 4],BD.PD[Per.P4],G$1,BD.PD[Pos],Tabla3[[#This Row],[Part.]])+SUMIFS(BD.PD[Pago 5],BD.PD[Per.P5],G$1,BD.PD[Pos],Tabla3[[#This Row],[Part.]]) -> 0 | H23: =SUMIFS(BD.PD[Pago 1],BD.PD[Per.P1],H$1,BD.PD[Pos],Tabla3[[#This Row],[Part.]])+SUMIFS(BD.PD[Pago 2],BD.PD[Per.P2],H$1,BD.PD[Pos],Tabla3[[#This Row],[Part.]])+SUMIFS(BD.PD[Pago 3],BD.PD[Per.P3],H$1,BD.PD[Pos],Tabla3[[#This Row],[Part.]])+SUMIFS(BD.PD[Pago 4],BD.PD[Per.P4],H$1,BD.PD[Pos],Tabla3[[#This Row],[Part.]])+SUMIFS(BD.PD[Pago 5],BD.PD[Per.P5],H$1,BD.PD[Pos],Tabla3[[#This Row],[Part.]]) -> 0 | I23: =SUMIFS(BD.PD[Pago 1],BD.PD[Per.P1],I$1,BD.PD[Pos],Tabla3[[#This Row],[Part.]])+SUMIFS(BD.PD[Pago 2],BD.PD[Per.P2],I$1,BD.PD[Pos],Tabla3[[#This Row],[Part.]])+SUMIFS(BD.PD[Pago 3],BD.PD[Per.P3],I$1,BD.PD[Pos],Tabla3[[#This Row],[Part.]])+SUMIFS(BD.PD[Pago 4],BD.PD[Per.P4],I$1,BD.PD[Pos],Tabla3[[#This Row],[Part.]])+SUMIFS(BD.PD[Pago 5],BD.PD[Per.P5],I$1,BD.PD[Pos],Tabla3[[#This Row],[Part.]]) -> 0 | J23: =SUMIFS(BD.PD[Pago 1],BD.PD[Per.P1],J$1,BD.PD[Pos],Tabla3[[#This Row],[Part.]])+SUMIFS(BD.PD[Pago 2],BD.PD[Per.P2],J$1,BD.PD[Pos],Tabla3[[#This Row],[Part.]])+SUMIFS(BD.PD[Pago 3],BD.PD[Per.P3],J$1,BD.PD[Pos],Tabla3[[#This Row],[Part.]])+SUMIFS(BD.PD[Pago 4],BD.PD[Per.P4],J$1,BD.PD[Pos],Tabla3[[#This Row],[Part.]])+SUMIFS(BD.PD[Pago 5],BD.PD[Per.P5],J$1,BD.PD[Pos],Tabla3[[#This Row],[Part.]]) -> 0 | K23: =SUMIFS(BD.PD[Pago 1],BD.PD[Per.P1],K$1,BD.PD[Pos],Tabla3[[#This Row],[Part.]])+SUMIFS(BD.PD[Pago 2],BD.PD[Per.P2],K$1,BD.PD[Pos],Tabla3[[#This Row],[Part.]])+SUMIFS(BD.PD[Pago 3],BD.PD[Per.P3],K$1,BD.PD[Pos],Tabla3[[#This Row],[Part.]])+SUMIFS(BD.PD[Pago 4],BD.PD[Per.P4],K$1,BD.PD[Pos],Tabla3[[#This Row],[Part.]])+SUMIFS(BD.PD[Pago 5],BD.PD[Per.P5],K$1,BD.PD[Pos],Tabla3[[#This Row],[Part.]]) -> 2505125.7 | ... Z23: =SUMIFS(BD.PD[Pago 1],BD.PD[Per.P1],Z$1,BD.PD[Pos],Tabla3[[#This Row],[Part.]])+SUMIFS(BD.PD[Pago 2],BD.PD[Per.P2],Z$1,BD.PD[Pos],Tabla3[[#This Row],[Part.]])+SUMIFS(BD.PD[Pago 3],BD.PD[Per.P3],Z$1,BD.PD[Pos],Tabla3[[#This Row],[Part.]])+SUMIFS(BD.PD[Pago 4],BD.PD[Per.P4],Z$1,BD.PD[Pos],Tabla3[[#This Row],[Part.]])+SUMIFS(BD.PD[Pago 5],BD.PD[Per.P5],Z$1,BD.PD[Pos],Tabla3[[#This Row],[Part.]]) -> 0 | AB23: =SUMIFS(BD.PD[Pago 1],BD.PD[Per.P1],AB$1,BD.PD[Pos],Tabla3[[#This Row],[Part.]])+SUMIFS(BD.PD[Pago 2],BD.PD[Per.P2],AB$1,BD.PD[Pos],Tabla3[[#This Row],[Part.]])+SUMIFS(BD.PD[Pago 3],BD.PD[Per.P3],AB$1,BD.PD[Pos],Tabla3[[#This Row],[Part.]])+SUMIFS(BD.PD[Pago 4],BD.PD[Per.P4],AB$1,BD.PD[Pos],Tabla3[[#This Row],[Part.]])+SUMIFS(BD.PD[Pago 5],BD.PD[Per.P5],AB$1,BD.PD[Pos],Tabla3[[#This Row],[Part.]]) -> 0 | AC23: =SUMIFS(BD.PD[Pago 1],BD.PD[Per.P1],AC$1,BD.PD[Pos],Tabla3[[#This Row],[Part.]])+SUMIFS(BD.PD[Pago 2],BD.PD[Per.P2],AC$1,BD.PD[Pos],Tabla3[[#This Row],[Part.]])+SUMIFS(BD.PD[Pago 3],BD.PD[Per.P3],AC$1,BD.PD[Pos],Tabla3[[#This Row],[Part.]])+SUMIFS(BD.PD[Pago 4],BD.PD[Per.P4],AC$1,BD.PD[Pos],Tabla3[[#This Row],[Part.]])+SUMIFS(BD.PD[Pago 5],BD.PD[Per.P5],AC$1,BD.PD[Pos],Tabla3[[#This Row],[Part.]]) -> 0 | AD23: =SUMIFS(BD.PD[Pago 1],BD.PD[Per.P1],AD$1,BD.PD[Pos],Tabla3[[#This Row],[Part.]])+SUMIFS(BD.PD[Pago 2],BD.PD[Per.P2],AD$1,BD.PD[Pos],Tabla3[[#This Row],[Part.]])+SUMIFS(BD.PD[Pago 3],BD.PD[Per.P3],AD$1,BD.PD[Pos],Tabla3[[#This Row],[Part.]])+SUMIFS(BD.PD[Pago 4],BD.PD[Per.P4],AD$1,BD.PD[Pos],Tabla3[[#This Row],[Part.]])+SUMIFS(BD.PD[Pago 5],BD.PD[Per.P5],AD$1,BD.PD[Pos],Tabla3[[#This Row],[Part.]]) -> 0 | AE23: =SUMIFS(BD.PD[Pago 1],BD.PD[Per.P1],AE$1,BD.PD[Pos],Tabla3[[#This Row],[Part.]])+SUMIFS(BD.PD[Pago 2],BD.PD[Per.P2],AE$1,BD.PD[Pos],Tabla3[[#This Row],[Part.]])+SUMIFS(BD.PD[Pago 3],BD.PD[Per.P3],AE$1,BD.PD[Pos],Tabla3[[#This Row],[Part.]])+SUMIFS(BD.PD[Pago 4],BD.PD[Per.P4],AE$1,BD.PD[Pos],Tabla3[[#This Row],[Part.]])+SUMIFS(BD.PD[Pago 5],BD.PD[Per.P5],AE$1,BD.PD[Pos],Tabla3[[#This Row],[Part.]]) -> 0 | AF23: =SUMIFS(BD.PD[Pago 1],BD.PD[Per.P1],AF$1,BD.PD[Pos],Tabla3[[#This Row],[Part.]])+SUMIFS(BD.PD[Pago 2],BD.PD[Per.P2],AF$1,BD.PD[Pos],Tabla3[[#This Row],[Part.]])+SUMIFS(BD.PD[Pago 3],BD.PD[Per.P3],AF$1,BD.PD[Pos],Tabla3[[#This Row],[Part.]])+SUMIFS(BD.PD[Pago 4],BD.PD[Per.P4],AF$1,BD.PD[Pos],Tabla3[[#This Row],[Part.]])+SUMIFS(BD.PD[Pago 5],BD.PD[Per.P5],AF$1,BD.PD[Pos],Tabla3[[#This Row],[Part.]]) -> 0 | AG23: =SUMIFS(BD.PD[Pago 1],BD.PD[Per.P1],AG$1,BD.PD[Pos],Tabla3[[#This Row],[Part.]])+SUMIFS(BD.PD[Pago 2],BD.PD[Per.P2],AG$1,BD.PD[Pos],Tabla3[[#This Row],[Part.]])+SUMIFS(BD.PD[Pago 3],BD.PD[Per.P3],AG$1,BD.PD[Pos],Tabla3[[#This Row],[Part.]])+SUMIFS(BD.PD[Pago 4],BD.PD[Per.P4],AG$1,BD.PD[Pos],Tabla3[[#This Row],[Part.]])+SUMIFS(BD.PD[Pago 5],BD.PD[Per.P5],AG$1,BD.PD[Pos],Tabla3[[#This Row],[Part.]]) -> 0 | AH23: =SUM(Tabla3[[#This Row],[P1]:[P24]]) -> 6294056
A24: 2.08 | B24: =VLOOKUP(Tabla3[[#This Row],[Part.]],PPto[],3,FALSE) -> 2.08 Instalaciones Mecánicas | C24: =SUMIF(BD.PD[Pos],Tabla3[[#This Row],[Part.]],BD.PD[Ppto. Orden Interna '[DOP']]) -> 3329609.7 | D24: =SUMIFS(BD.PD[Pago 1],BD.PD[Per.P1],D$1,BD.PD[Pos],Tabla3[[#This Row],[Part.]])+SUMIFS(BD.PD[Pago 2],BD.PD[Per.P2],D$1,BD.PD[Pos],Tabla3[[#This Row],[Part.]])+SUMIFS(BD.PD[Pago 3],BD.PD[Per.P3],D$1,BD.PD[Pos],Tabla3[[#This Row],[Part.]])+SUMIFS(BD.PD[Pago 4],BD.PD[Per.P4],D$1,BD.PD[Pos],Tabla3[[#This Row],[Part.]])+SUMIFS(BD.PD[Pago 5],BD.PD[Per.P5],D$1,BD.PD[Pos],Tabla3[[#This Row],[Part.]]) -> 0 | E24: =SUMIFS(BD.PD[Pago 1],BD.PD[Per.P1],E$1,BD.PD[Pos],Tabla3[[#This Row],[Part.]])+SUMIFS(BD.PD[Pago 2],BD.PD[Per.P2],E$1,BD.PD[Pos],Tabla3[[#This Row],[Part.]])+SUMIFS(BD.PD[Pago 3],BD.PD[Per.P3],E$1,BD.PD[Pos],Tabla3[[#This Row],[Part.]])+SUMIFS(BD.PD[Pago 4],BD.PD[Per.P4],E$1,BD.PD[Pos],Tabla3[[#This Row],[Part.]])+SUMIFS(BD.PD[Pago 5],BD.PD[Per.P5],E$1,BD.PD[Pos],Tabla3[[#This Row],[Part.]]) -> 0 | F24: =SUMIFS(BD.PD[Pago 1],BD.PD[Per.P1],F$1,BD.PD[Pos],Tabla3[[#This Row],[Part.]])+SUMIFS(BD.PD[Pago 2],BD.PD[Per.P2],F$1,BD.PD[Pos],Tabla3[[#This Row],[Part.]])+SUMIFS(BD.PD[Pago 3],BD.PD[Per.P3],F$1,BD.PD[Pos],Tabla3[[#This Row],[Part.]])+SUMIFS(BD.PD[Pago 4],BD.PD[Per.P4],F$1,BD.PD[Pos],Tabla3[[#This Row],[Part.]])+SUMIFS(BD.PD[Pago 5],BD.PD[Per.P5],F$1,BD.PD[Pos],Tabla3[[#This Row],[Part.]]) -> 0 | G24: =SUMIFS(BD.PD[Pago 1],BD.PD[Per.P1],G$1,BD.PD[Pos],Tabla3[[#This Row],[Part.]])+SUMIFS(BD.PD[Pago 2],BD.PD[Per.P2],G$1,BD.PD[Pos],Tabla3[[#This Row],[Part.]])+SUMIFS(BD.PD[Pago 3],BD.PD[Per.P3],G$1,BD.PD[Pos],Tabla3[[#This Row],[Part.]])+SUMIFS(BD.PD[Pago 4],BD.PD[Per.P4],G$1,BD.PD[Pos],Tabla3[[#This Row],[Part.]])+SUMIFS(BD.PD[Pago 5],BD.PD[Per.P5],G$1,BD.PD[Pos],Tabla3[[#This Row],[Part.]]) -> 0 | H24: =SUMIFS(BD.PD[Pago 1],BD.PD[Per.P1],H$1,BD.PD[Pos],Tabla3[[#This Row],[Part.]])+SUMIFS(BD.PD[Pago 2],BD.PD[Per.P2],H$1,BD.PD[Pos],Tabla3[[#This Row],[Part.]])+SUMIFS(BD.PD[Pago 3],BD.PD[Per.P3],H$1,BD.PD[Pos],Tabla3[[#This Row],[Part.]])+SUMIFS(BD.PD[Pago 4],BD.PD[Per.P4],H$1,BD.PD[Pos],Tabla3[[#This Row],[Part.]])+SUMIFS(BD.PD[Pago 5],BD.PD[Per.P5],H$1,BD.PD[Pos],Tabla3[[#This Row],[Part.]]) -> 0 | I24: =SUMIFS(BD.PD[Pago 1],BD.PD[Per.P1],I$1,BD.PD[Pos],Tabla3[[#This Row],[Part.]])+SUMIFS(BD.PD[Pago 2],BD.PD[Per.P2],I$1,BD.PD[Pos],Tabla3[[#This Row],[Part.]])+SUMIFS(BD.PD[Pago 3],BD.PD[Per.P3],I$1,BD.PD[Pos],Tabla3[[#This Row],[Part.]])+SUMIFS(BD.PD[Pago 4],BD.PD[Per.P4],I$1,BD.PD[Pos],Tabla3[[#This Row],[Part.]])+SUMIFS(BD.PD[Pago 5],BD.PD[Per.P5],I$1,BD.PD[Pos],Tabla3[[#This Row],[Part.]]) -> 0 | J24: =SUMIFS(BD.PD[Pago 1],BD.PD[Per.P1],J$1,BD.PD[Pos],Tabla3[[#This Row],[Part.]])+SUMIFS(BD.PD[Pago 2],BD.PD[Per.P2],J$1,BD.PD[Pos],Tabla3[[#This Row],[Part.]])+SUMIFS(BD.PD[Pago 3],BD.PD[Per.P3],J$1,BD.PD[Pos],Tabla3[[#This Row],[Part.]])+SUMIFS(BD.PD[Pago 4],BD.PD[Per.P4],J$1,BD.PD[Pos],Tabla3[[#This Row],[Part.]])+SUMIFS(BD.PD[Pago 5],BD.PD[Per.P5],J$1,BD.PD[Pos],Tabla3[[#This Row],[Part.]]) -> 0 | K24: =SUMIFS(BD.PD[Pago 1],BD.PD[Per.P1],K$1,BD.PD[Pos],Tabla3[[#This Row],[Part.]])+SUMIFS(BD.PD[Pago 2],BD.PD[Per.P2],K$1,BD.PD[Pos],Tabla3[[#This Row],[Part.]])+SUMIFS(BD.PD[Pago 3],BD.PD[Per.P3],K$1,BD.PD[Pos],Tabla3[[#This Row],[Part.]])+SUMIFS(BD.PD[Pago 4],BD.PD[Per.P4],K$1,BD.PD[Pos],Tabla3[[#This Row],[Part.]])+SUMIFS(BD.PD[Pago 5],BD.PD[Per.P5],K$1,BD.PD[Pos],Tabla3[[#This Row],[Part.]]) -> 1912307.7 | ... Z24: =SUMIFS(BD.PD[Pago 1],BD.PD[Per.P1],Z$1,BD.PD[Pos],Tabla3[[#This Row],[Part.]])+SUMIFS(BD.PD[Pago 2],BD.PD[Per.P2],Z$1,BD.PD[Pos],Tabla3[[#This Row],[Part.]])+SUMIFS(BD.PD[Pago 3],BD.PD[Per.P3],Z$1,BD.PD[Pos],Tabla3[[#This Row],[Part.]])+SUMIFS(BD.PD[Pago 4],BD.PD[Per.P4],Z$1,BD.PD[Pos],Tabla3[[#This Row],[Part.]])+SUMIFS(BD.PD[Pago 5],BD.PD[Per.P5],Z$1,BD.PD[Pos],Tabla3[[#This Row],[Part.]]) -> 450351 | AB24: =SUMIFS(BD.PD[Pago 1],BD.PD[Per.P1],AB$1,BD.PD[Pos],Tabla3[[#This Row],[Part.]])+SUMIFS(BD.PD[Pago 2],BD.PD[Per.P2],AB$1,BD.PD[Pos],Tabla3[[#This Row],[Part.]])+SUMIFS(BD.PD[Pago 3],BD.PD[Per.P3],AB$1,BD.PD[Pos],Tabla3[[#This Row],[Part.]])+SUMIFS(BD.PD[Pago 4],BD.PD[Per.P4],AB$1,BD.PD[Pos],Tabla3[[#This Row],[Part.]])+SUMIFS(BD.PD[Pago 5],BD.PD[Per.P5],AB$1,BD.PD[Pos],Tabla3[[#This Row],[Part.]]) -> 0 | AC24: =SUMIFS(BD.PD[Pago 1],BD.PD[Per.P1],AC$1,BD.PD[Pos],Tabla3[[#This Row],[Part.]])+SUMIFS(BD.PD[Pago 2],BD.PD[Per.P2],AC$1,BD.PD[Pos],Tabla3[[#This Row],[Part.]])+SUMIFS(BD.PD[Pago 3],BD.PD[Per.P3],AC$1,BD.PD[Pos],Tabla3[[#This Row],[Part.]])+SUMIFS(BD.PD[Pago 4],BD.PD[Per.P4],AC$1,BD.PD[Pos],Tabla3[[#This Row],[Part.]])+SUMIFS(BD.PD[Pago 5],BD.PD[Per.P5],AC$1,BD.PD[Pos],Tabla3[[#This Row],[Part.]]) -> 0 | AD24: =SUMIFS(BD.PD[Pago 1],BD.PD[Per.P1],AD$1,BD.PD[Pos],Tabla3[[#This Row],[Part.]])+SUMIFS(BD.PD[Pago 2],BD.PD[Per.P2],AD$1,BD.PD[Pos],Tabla3[[#This Row],[Part.]])+SUMIFS(BD.PD[Pago 3],BD.PD[Per.P3],AD$1,BD.PD[Pos],Tabla3[[#This Row],[Part.]])+SUMIFS(BD.PD[Pago 4],BD.PD[Per.P4],AD$1,BD.PD[Pos],Tabla3[[#This Row],[Part.]])+SUMIFS(BD.PD[Pago 5],BD.PD[Per.P5],AD$1,BD.PD[Pos],Tabla3[[#This Row],[Part.]]) -> 0 | AE24: =SUMIFS(BD.PD[Pago 1],BD.PD[Per.P1],AE$1,BD.PD[Pos],Tabla3[[#This Row],[Part.]])+SUMIFS(BD.PD[Pago 2],BD.PD[Per.P2],AE$1,BD.PD[Pos],Tabla3[[#This Row],[Part.]])+SUMIFS(BD.PD[Pago 3],BD.PD[Per.P3],AE$1,BD.PD[Pos],Tabla3[[#This Row],[Part.]])+SUMIFS(BD.PD[Pago 4],BD.PD[Per.P4],AE$1,BD.PD[Pos],Tabla3[[#This Row],[Part.]])+SUMIFS(BD.PD[Pago 5],BD.PD[Per.P5],AE$1,BD.PD[Pos],Tabla3[[#This Row],[Part.]]) -> 0 | AF24: =SUMIFS(BD.PD[Pago 1],BD.PD[Per.P1],AF$1,BD.PD[Pos],Tabla3[[#This Row],[Part.]])+SUMIFS(BD.PD[Pago 2],BD.PD[Per.P2],AF$1,BD.PD[Pos],Tabla3[[#This Row],[Part.]])+SUMIFS(BD.PD[Pago 3],BD.PD[Per.P3],AF$1,BD.PD[Pos],Tabla3[[#This Row],[Part.]])+SUMIFS(BD.PD[Pago 4],BD.PD[Per.P4],AF$1,BD.PD[Pos],Tabla3[[#This Row],[Part.]])+SUMIFS(BD.PD[Pago 5],BD.PD[Per.P5],AF$1,BD.PD[Pos],Tabla3[[#This Row],[Part.]]) -> 0 | AG24: =SUMIFS(BD.PD[Pago 1],BD.PD[Per.P1],AG$1,BD.PD[Pos],Tabla3[[#This Row],[Part.]])+SUMIFS(BD.PD[Pago 2],BD.PD[Per.P2],AG$1,BD.PD[Pos],Tabla3[[#This Row],[Part.]])+SUMIFS(BD.PD[Pago 3],BD.PD[Per.P3],AG$1,BD.PD[Pos],Tabla3[[#This Row],[Part.]])+SUMIFS(BD.PD[Pago 4],BD.PD[Per.P4],AG$1,BD.PD[Pos],Tabla3[[#This Row],[Part.]])+SUMIFS(BD.PD[Pago 5],BD.PD[Per.P5],AG$1,BD.PD[Pos],Tabla3[[#This Row],[Part.]]) -> 0 | AH24: =SUM(Tabla3[[#This Row],[P1]:[P24]]) -> 3329609.7
A25: 2.09 | B25: =VLOOKUP(Tabla3[[#This Row],[Part.]],PPto[],3,FALSE) -> 2.09 Rejillas y Sumideros | C25: =SUMIF(BD.PD[Pos],Tabla3[[#This Row],[Part.]],BD.PD[Ppto. Orden Interna '[DOP']]) -> 735421.05 | D25: =SUMIFS(BD.PD[Pago 1],BD.PD[Per.P1],D$1,BD.PD[Pos],Tabla3[[#This Row],[Part.]])+SUMIFS(BD.PD[Pago 2],BD.PD[Per.P2],D$1,BD.PD[Pos],Tabla3[[#This Row],[Part.]])+SUMIFS(BD.PD[Pago 3],BD.PD[Per.P3],D$1,BD.PD[Pos],Tabla3[[#This Row],[Part.]])+SUMIFS(BD.PD[Pago 4],BD.PD[Per.P4],D$1,BD.PD[Pos],Tabla3[[#This Row],[Part.]])+SUMIFS(BD.PD[Pago 5],BD.PD[Per.P5],D$1,BD.PD[Pos],Tabla3[[#This Row],[Part.]]) -> 0 | E25: =SUMIFS(BD.PD[Pago 1],BD.PD[Per.P1],E$1,BD.PD[Pos],Tabla3[[#This Row],[Part.]])+SUMIFS(BD.PD[Pago 2],BD.PD[Per.P2],E$1,BD.PD[Pos],Tabla3[[#This Row],[Part.]])+SUMIFS(BD.PD[Pago 3],BD.PD[Per.P3],E$1,BD.PD[Pos],Tabla3[[#This Row],[Part.]])+SUMIFS(BD.PD[Pago 4],BD.PD[Per.P4],E$1,BD.PD[Pos],Tabla3[[#This Row],[Part.]])+SUMIFS(BD.PD[Pago 5],BD.PD[Per.P5],E$1,BD.PD[Pos],Tabla3[[#This Row],[Part.]]) -> 0 | F25: =SUMIFS(BD.PD[Pago 1],BD.PD[Per.P1],F$1,BD.PD[Pos],Tabla3[[#This Row],[Part.]])+SUMIFS(BD.PD[Pago 2],BD.PD[Per.P2],F$1,BD.PD[Pos],Tabla3[[#This Row],[Part.]])+SUMIFS(BD.PD[Pago 3],BD.PD[Per.P3],F$1,BD.PD[Pos],Tabla3[[#This Row],[Part.]])+SUMIFS(BD.PD[Pago 4],BD.PD[Per.P4],F$1,BD.PD[Pos],Tabla3[[#This Row],[Part.]])+SUMIFS(BD.PD[Pago 5],BD.PD[Per.P5],F$1,BD.PD[Pos],Tabla3[[#This Row],[Part.]]) -> 294168.42 | G25: =SUMIFS(BD.PD[Pago 1],BD.PD[Per.P1],G$1,BD.PD[Pos],Tabla3[[#This Row],[Part.]])+SUMIFS(BD.PD[Pago 2],BD.PD[Per.P2],G$1,BD.PD[Pos],Tabla3[[#This Row],[Part.]])+SUMIFS(BD.PD[Pago 3],BD.PD[Per.P3],G$1,BD.PD[Pos],Tabla3[[#This Row],[Part.]])+SUMIFS(BD.PD[Pago 4],BD.PD[Per.P4],G$1,BD.PD[Pos],Tabla3[[#This Row],[Part.]])+SUMIFS(BD.PD[Pago 5],BD.PD[Per.P5],G$1,BD.PD[Pos],Tabla3[[#This Row],[Part.]]) -> 0 | H25: =SUMIFS(BD.PD[Pago 1],BD.PD[Per.P1],H$1,BD.PD[Pos],Tabla3[[#This Row],[Part.]])+SUMIFS(BD.PD[Pago 2],BD.PD[Per.P2],H$1,BD.PD[Pos],Tabla3[[#This Row],[Part.]])+SUMIFS(BD.PD[Pago 3],BD.PD[Per.P3],H$1,BD.PD[Pos],Tabla3[[#This Row],[Part.]])+SUMIFS(BD.PD[Pago 4],BD.PD[Per.P4],H$1,BD.PD[Pos],Tabla3[[#This Row],[Part.]])+SUMIFS(BD.PD[Pago 5],BD.PD[Per.P5],H$1,BD.PD[Pos],Tabla3[[#This Row],[Part.]]) -> 0 | I25: =SUMIFS(BD.PD[Pago 1],BD.PD[Per.P1],I$1,BD.PD[Pos],Tabla3[[#This Row],[Part.]])+SUMIFS(BD.PD[Pago 2],BD.PD[Per.P2],I$1,BD.PD[Pos],Tabla3[[#This Row],[Part.]])+SUMIFS(BD.PD[Pago 3],BD.PD[Per.P3],I$1,BD.PD[Pos],Tabla3[[#This Row],[Part.]])+SUMIFS(BD.PD[Pago 4],BD.PD[Per.P4],I$1,BD.PD[Pos],Tabla3[[#This Row],[Part.]])+SUMIFS(BD.PD[Pago 5],BD.PD[Per.P5],I$1,BD.PD[Pos],Tabla3[[#This Row],[Part.]]) -> 0 | J25: =SUMIFS(BD.PD[Pago 1],BD.PD[Per.P1],J$1,BD.PD[Pos],Tabla3[[#This Row],[Part.]])+SUMIFS(BD.PD[Pago 2],BD.PD[Per.P2],J$1,BD.PD[Pos],Tabla3[[#This Row],[Part.]])+SUMIFS(BD.PD[Pago 3],BD.PD[Per.P3],J$1,BD.PD[Pos],Tabla3[[#This Row],[Part.]])+SUMIFS(BD.PD[Pago 4],BD.PD[Per.P4],J$1,BD.PD[Pos],Tabla3[[#This Row],[Part.]])+SUMIFS(BD.PD[Pago 5],BD.PD[Per.P5],J$1,BD.PD[Pos],Tabla3[[#This Row],[Part.]]) -> 0 | K25: =SUMIFS(BD.PD[Pago 1],BD.PD[Per.P1],K$1,BD.PD[Pos],Tabla3[[#This Row],[Part.]])+SUMIFS(BD.PD[Pago 2],BD.PD[Per.P2],K$1,BD.PD[Pos],Tabla3[[#This Row],[Part.]])+SUMIFS(BD.PD[Pago 3],BD.PD[Per.P3],K$1,BD.PD[Pos],Tabla3[[#This Row],[Part.]])+SUMIFS(BD.PD[Pago 4],BD.PD[Per.P4],K$1,BD.PD[Pos],Tabla3[[#This Row],[Part.]])+SUMIFS(BD.PD[Pago 5],BD.PD[Per.P5],K$1,BD.PD[Pos],Tabla3[[#This Row],[Part.]]) -> 441252.63 | ... Z25: =SUMIFS(BD.PD[Pago 1],BD.PD[Per.P1],Z$1,BD.PD[Pos],Tabla3[[#This Row],[Part.]])+SUMIFS(BD.PD[Pago 2],BD.PD[Per.P2],Z$1,BD.PD[Pos],Tabla3[[#This Row],[Part.]])+SUMIFS(BD.PD[Pago 3],BD.PD[Per.P3],Z$1,BD.PD[Pos],Tabla3[[#This Row],[Part.]])+SUMIFS(BD.PD[Pago 4],BD.PD[Per.P4],Z$1,BD.PD[Pos],Tabla3[[#This Row],[Part.]])+SUMIFS(BD.PD[Pago 5],BD.PD[Per.P5],Z$1,BD.PD[Pos],Tabla3[[#This Row],[Part.]]) -> 0 | AB25: =SUMIFS(BD.PD[Pago 1],BD.PD[Per.P1],AB$1,BD.PD[Pos],Tabla3[[#This Row],[Part.]])+SUMIFS(BD.PD[Pago 2],BD.PD[Per.P2],AB$1,BD.PD[Pos],Tabla3[[#This Row],[Part.]])+SUMIFS(BD.PD[Pago 3],BD.PD[Per.P3],AB$1,BD.PD[Pos],Tabla3[[#This Row],[Part.]])+SUMIFS(BD.PD[Pago 4],BD.PD[Per.P4],AB$1,BD.PD[Pos],Tabla3[[#This Row],[Part.]])+SUMIFS(BD.PD[Pago 5],BD.PD[Per.P5],AB$1,BD.PD[Pos],Tabla3[[#This Row],[Part.]]) -> 0 | AC25: =SUMIFS(BD.PD[Pago 1],BD.PD[Per.P1],AC$1,BD.PD[Pos],Tabla3[[#This Row],[Part.]])+SUMIFS(BD.PD[Pago 2],BD.PD[Per.P2],AC$1,BD.PD[Pos],Tabla3[[#This Row],[Part.]])+SUMIFS(BD.PD[Pago 3],BD.PD[Per.P3],AC$1,BD.PD[Pos],Tabla3[[#This Row],[Part.]])+SUMIFS(BD.PD[Pago 4],BD.PD[Per.P4],AC$1,BD.PD[Pos],Tabla3[[#This Row],[Part.]])+SUMIFS(BD.PD[Pago 5],BD.PD[Per.P5],AC$1,BD.PD[Pos],Tabla3[[#This Row],[Part.]]) -> 0 | AD25: =SUMIFS(BD.PD[Pago 1],BD.PD[Per.P1],AD$1,BD.PD[Pos],Tabla3[[#This Row],[Part.]])+SUMIFS(BD.PD[Pago 2],BD.PD[Per.P2],AD$1,BD.PD[Pos],Tabla3[[#This Row],[Part.]])+SUMIFS(BD.PD[Pago 3],BD.PD[Per.P3],AD$1,BD.PD[Pos],Tabla3[[#This Row],[Part.]])+SUMIFS(BD.PD[Pago 4],BD.PD[Per.P4],AD$1,BD.PD[Pos],Tabla3[[#This Row],[Part.]])+SUMIFS(BD.PD[Pago 5],BD.PD[Per.P5],AD$1,BD.PD[Pos],Tabla3[[#This Row],[Part.]]) -> 0 | AE25: =SUMIFS(BD.PD[Pago 1],BD.PD[Per.P1],AE$1,BD.PD[Pos],Tabla3[[#This Row],[Part.]])+SUMIFS(BD.PD[Pago 2],BD.PD[Per.P2],AE$1,BD.PD[Pos],Tabla3[[#This Row],[Part.]])+SUMIFS(BD.PD[Pago 3],BD.PD[Per.P3],AE$1,BD.PD[Pos],Tabla3[[#This Row],[Part.]])+SUMIFS(BD.PD[Pago 4],BD.PD[Per.P4],AE$1,BD.PD[Pos],Tabla3[[#This Row],[Part.]])+SUMIFS(BD.PD[Pago 5],BD.PD[Per.P5],AE$1,BD.PD[Pos],Tabla3[[#This Row],[Part.]]) -> 0 | AF25: =SUMIFS(BD.PD[Pago 1],BD.PD[Per.P1],AF$1,BD.PD[Pos],Tabla3[[#This Row],[Part.]])+SUMIFS(BD.PD[Pago 2],BD.PD[Per.P2],AF$1,BD.PD[Pos],Tabla3[[#This Row],[Part.]])+SUMIFS(BD.PD[Pago 3],BD.PD[Per.P3],AF$1,BD.PD[Pos],Tabla3[[#This Row],[Part.]])+SUMIFS(BD.PD[Pago 4],BD.PD[Per.P4],AF$1,BD.PD[Pos],Tabla3[[#This Row],[Part.]])+SUMIFS(BD.PD[Pago 5],BD.PD[Per.P5],AF$1,BD.PD[Pos],Tabla3[[#This Row],[Part.]]) -> 0 | AG25: =SUMIFS(BD.PD[Pago 1],BD.PD[Per.P1],AG$1,BD.PD[Pos],Tabla3[[#This Row],[Part.]])+SUMIFS(BD.PD[Pago 2],BD.PD[Per.P2],AG$1,BD.PD[Pos],Tabla3[[#This Row],[Part.]])+SUMIFS(BD.PD[Pago 3],BD.PD[Per.P3],AG$1,BD.PD[Pos],Tabla3[[#This Row],[Part.]])+SUMIFS(BD.PD[Pago 4],BD.PD[Per.P4],AG$1,BD.PD[Pos],Tabla3[[#This Row],[Part.]])+SUMIFS(BD.PD[Pago 5],BD.PD[Per.P5],AG$1,BD.PD[Pos],Tabla3[[#This Row],[Part.]]) -> 0 | AH25: =SUM(Tabla3[[#This Row],[P1]:[P24]]) -> 735421.05
A26: 2.1 | B26: =VLOOKUP(Tabla3[[#This Row],[Part.]],PPto[],3,FALSE) -> 2.10 Supervisión Civil y Sanitaria | C26: =SUMIF(BD.PD[Pos],Tabla3[[#This Row],[Part.]],BD.PD[Ppto. Orden Interna '[DOP']]) -> 0 | D26: =SUMIFS(BD.PD[Pago 1],BD.PD[Per.P1],D$1,BD.PD[Pos],Tabla3[[#This Row],[Part.]])+SUMIFS(BD.PD[Pago 2],BD.PD[Per.P2],D$1,BD.PD[Pos],Tabla3[[#This Row],[Part.]])+SUMIFS(BD.PD[Pago 3],BD.PD[Per.P3],D$1,BD.PD[Pos],Tabla3[[#This Row],[Part.]])+SUMIFS(BD.PD[Pago 4],BD.PD[Per.P4],D$1,BD.PD[Pos],Tabla3[[#This Row],[Part.]])+SUMIFS(BD.PD[Pago 5],BD.PD[Per.P5],D$1,BD.PD[Pos],Tabla3[[#This Row],[Part.]]) -> 0 | E26: =SUMIFS(BD.PD[Pago 1],BD.PD[Per.P1],E$1,BD.PD[Pos],Tabla3[[#This Row],[Part.]])+SUMIFS(BD.PD[Pago 2],BD.PD[Per.P2],E$1,BD.PD[Pos],Tabla3[[#This Row],[Part.]])+SUMIFS(BD.PD[Pago 3],BD.PD[Per.P3],E$1,BD.PD[Pos],Tabla3[[#This Row],[Part.]])+SUMIFS(BD.PD[Pago 4],BD.PD[Per.P4],E$1,BD.PD[Pos],Tabla3[[#This Row],[Part.]])+SUMIFS(BD.PD[Pago 5],BD.PD[Per.P5],E$1,BD.PD[Pos],Tabla3[[#This Row],[Part.]]) -> 0 | F26: =SUMIFS(BD.PD[Pago 1],BD.PD[Per.P1],F$1,BD.PD[Pos],Tabla3[[#This Row],[Part.]])+SUMIFS(BD.PD[Pago 2],BD.PD[Per.P2],F$1,BD.PD[Pos],Tabla3[[#This Row],[Part.]])+SUMIFS(BD.PD[Pago 3],BD.PD[Per.P3],F$1,BD.PD[Pos],Tabla3[[#This Row],[Part.]])+SUMIFS(BD.PD[Pago 4],BD.PD[Per.P4],F$1,BD.PD[Pos],Tabla3[[#This Row],[Part.]])+SUMIFS(BD.PD[Pago 5],BD.PD[Per.P5],F$1,BD.PD[Pos],Tabla3[[#This Row],[Part.]]) -> 0 | G26: =SUMIFS(BD.PD[Pago 1],BD.PD[Per.P1],G$1,BD.PD[Pos],Tabla3[[#This Row],[Part.]])+SUMIFS(BD.PD[Pago 2],BD.PD[Per.P2],G$1,BD.PD[Pos],Tabla3[[#This Row],[Part.]])+SUMIFS(BD.PD[Pago 3],BD.PD[Per.P3],G$1,BD.PD[Pos],Tabla3[[#This Row],[Part.]])+SUMIFS(BD.PD[Pago 4],BD.PD[Per.P4],G$1,BD.PD[Pos],Tabla3[[#This Row],[Part.]])+SUMIFS(BD.PD[Pago 5],BD.PD[Per.P5],G$1,BD.PD[Pos],Tabla3[[#This Row],[Part.]]) -> 0 | H26: =SUMIFS(BD.PD[Pago 1],BD.PD[Per.P1],H$1,BD.PD[Pos],Tabla3[[#This Row],[Part.]])+SUMIFS(BD.PD[Pago 2],BD.PD[Per.P2],H$1,BD.PD[Pos],Tabla3[[#This Row],[Part.]])+SUMIFS(BD.PD[Pago 3],BD.PD[Per.P3],H$1,BD.PD[Pos],Tabla3[[#This Row],[Part.]])+SUMIFS(BD.PD[Pago 4],BD.PD[Per.P4],H$1,BD.PD[Pos],Tabla3[[#This Row],[Part.]])+SUMIFS(BD.PD[Pago 5],BD.PD[Per.P5],H$1,BD.PD[Pos],Tabla3[[#This Row],[Part.]]) -> 0 | I26: =SUMIFS(BD.PD[Pago 1],BD.PD[Per.P1],I$1,BD.PD[Pos],Tabla3[[#This Row],[Part.]])+SUMIFS(BD.PD[Pago 2],BD.PD[Per.P2],I$1,BD.PD[Pos],Tabla3[[#This Row],[Part.]])+SUMIFS(BD.PD[Pago 3],BD.PD[Per.P3],I$1,BD.PD[Pos],Tabla3[[#This Row],[Part.]])+SUMIFS(BD.PD[Pago 4],BD.PD[Per.P4],I$1,BD.PD[Pos],Tabla3[[#This Row],[Part.]])+SUMIFS(BD.PD[Pago 5],BD.PD[Per.P5],I$1,BD.PD[Pos],Tabla3[[#This Row],[Part.]]) -> 0 | J26: =SUMIFS(BD.PD[Pago 1],BD.PD[Per.P1],J$1,BD.PD[Pos],Tabla3[[#This Row],[Part.]])+SUMIFS(BD.PD[Pago 2],BD.PD[Per.P2],J$1,BD.PD[Pos],Tabla3[[#This Row],[Part.]])+SUMIFS(BD.PD[Pago 3],BD.PD[Per.P3],J$1,BD.PD[Pos],Tabla3[[#This Row],[Part.]])+SUMIFS(BD.PD[Pago 4],BD.PD[Per.P4],J$1,BD.PD[Pos],Tabla3[[#This Row],[Part.]])+SUMIFS(BD.PD[Pago 5],BD.PD[Per.P5],J$1,BD.PD[Pos],Tabla3[[#This Row],[Part.]]) -> 0 | K26: =SUMIFS(BD.PD[Pago 1],BD.PD[Per.P1],K$1,BD.PD[Pos],Tabla3[[#This Row],[Part.]])+SUMIFS(BD.PD[Pago 2],BD.PD[Per.P2],K$1,BD.PD[Pos],Tabla3[[#This Row],[Part.]])+SUMIFS(BD.PD[Pago 3],BD.PD[Per.P3],K$1,BD.PD[Pos],Tabla3[[#This Row],[Part.]])+SUMIFS(BD.PD[Pago 4],BD.PD[Per.P4],K$1,BD.PD[Pos],Tabla3[[#This Row],[Part.]])+SUMIFS(BD.PD[Pago 5],BD.PD[Per.P5],K$1,BD.PD[Pos],Tabla3[[#This Row],[Part.]]) -> 0 | ... Z26: =SUMIFS(BD.PD[Pago 1],BD.PD[Per.P1],Z$1,BD.PD[Pos],Tabla3[[#This Row],[Part.]])+SUMIFS(BD.PD[Pago 2],BD.PD[Per.P2],Z$1,BD.PD[Pos],Tabla3[[#This Row],[Part.]])+SUMIFS(BD.PD[Pago 3],BD.PD[Per.P3],Z$1,BD.PD[Pos],Tabla3[[#This Row],[Part.]])+SUMIFS(BD.PD[Pago 4],BD.PD[Per.P4],Z$1,BD.PD[Pos],Tabla3[[#This Row],[Part.]])+SUMIFS(BD.PD[Pago 5],BD.PD[Per.P5],Z$1,BD.PD[Pos],Tabla3[[#This Row],[Part.]]) -> 0 | AB26: =SUMIFS(BD.PD[Pago 1],BD.PD[Per.P1],AB$1,BD.PD[Pos],Tabla3[[#This Row],[Part.]])+SUMIFS(BD.PD[Pago 2],BD.PD[Per.P2],AB$1,BD.PD[Pos],Tabla3[[#This Row],[Part.]])+SUMIFS(BD.PD[Pago 3],BD.PD[Per.P3],AB$1,BD.PD[Pos],Tabla3[[#This Row],[Part.]])+SUMIFS(BD.PD[Pago 4],BD.PD[Per.P4],AB$1,BD.PD[Pos],Tabla3[[#This Row],[Part.]])+SUMIFS(BD.PD[Pago 5],BD.PD[Per.P5],AB$1,BD.PD[Pos],Tabla3[[#This Row],[Part.]]) -> 0 | AC26: =SUMIFS(BD.PD[Pago 1],BD.PD[Per.P1],AC$1,BD.PD[Pos],Tabla3[[#This Row],[Part.]])+SUMIFS(BD.PD[Pago 2],BD.PD[Per.P2],AC$1,BD.PD[Pos],Tabla3[[#This Row],[Part.]])+SUMIFS(BD.PD[Pago 3],BD.PD[Per.P3],AC$1,BD.PD[Pos],Tabla3[[#This Row],[Part.]])+SUMIFS(BD.PD[Pago 4],BD.PD[Per.P4],AC$1,BD.PD[Pos],Tabla3[[#This Row],[Part.]])+SUMIFS(BD.PD[Pago 5],BD.PD[Per.P5],AC$1,BD.PD[Pos],Tabla3[[#This Row],[Part.]]) -> 0 | AD26: =SUMIFS(BD.PD[Pago 1],BD.PD[Per.P1],AD$1,BD.PD[Pos],Tabla3[[#This Row],[Part.]])+SUMIFS(BD.PD[Pago 2],BD.PD[Per.P2],AD$1,BD.PD[Pos],Tabla3[[#This Row],[Part.]])+SUMIFS(BD.PD[Pago 3],BD.PD[Per.P3],AD$1,BD.PD[Pos],Tabla3[[#This Row],[Part.]])+SUMIFS(BD.PD[Pago 4],BD.PD[Per.P4],AD$1,BD.PD[Pos],Tabla3[[#This Row],[Part.]])+SUMIFS(BD.PD[Pago 5],BD.PD[Per.P5],AD$1,BD.PD[Pos],Tabla3[[#This Row],[Part.]]) -> 0 | AE26: =SUMIFS(BD.PD[Pago 1],BD.PD[Per.P1],AE$1,BD.PD[Pos],Tabla3[[#This Row],[Part.]])+SUMIFS(BD.PD[Pago 2],BD.PD[Per.P2],AE$1,BD.PD[Pos],Tabla3[[#This Row],[Part.]])+SUMIFS(BD.PD[Pago 3],BD.PD[Per.P3],AE$1,BD.PD[Pos],Tabla3[[#This Row],[Part.]])+SUMIFS(BD.PD[Pago 4],BD.PD[Per.P4],AE$1,BD.PD[Pos],Tabla3[[#This Row],[Part.]])+SUMIFS(BD.PD[Pago 5],BD.PD[Per.P5],AE$1,BD.PD[Pos],Tabla3[[#This Row],[Part.]]) -> 0 | AF26: =SUMIFS(BD.PD[Pago 1],BD.PD[Per.P1],AF$1,BD.PD[Pos],Tabla3[[#This Row],[Part.]])+SUMIFS(BD.PD[Pago 2],BD.PD[Per.P2],AF$1,BD.PD[Pos],Tabla3[[#This Row],[Part.]])+SUMIFS(BD.PD[Pago 3],BD.PD[Per.P3],AF$1,BD.PD[Pos],Tabla3[[#This Row],[Part.]])+SUMIFS(BD.PD[Pago 4],BD.PD[Per.P4],AF$1,BD.PD[Pos],Tabla3[[#This Row],[Part.]])+SUMIFS(BD.PD[Pago 5],BD.PD[Per.P5],AF$1,BD.PD[Pos],Tabla3[[#This Row],[Part.]]) -> 0 | AG26: =SUMIFS(BD.PD[Pago 1],BD.PD[Per.P1],AG$1,BD.PD[Pos],Tabla3[[#This Row],[Part.]])+SUMIFS(BD.PD[Pago 2],BD.PD[Per.P2],AG$1,BD.PD[Pos],Tabla3[[#This Row],[Part.]])+SUMIFS(BD.PD[Pago 3],BD.PD[Per.P3],AG$1,BD.PD[Pos],Tabla3[[#This Row],[Part.]])+SUMIFS(BD.PD[Pago 4],BD.PD[Per.P4],AG$1,BD.PD[Pos],Tabla3[[#This Row],[Part.]])+SUMIFS(BD.PD[Pago 5],BD.PD[Per.P5],AG$1,BD.PD[Pos],Tabla3[[#This Row],[Part.]]) -> 0 | AH26: =SUM(Tabla3[[#This Row],[P1]:[P24]]) -> 0
A27: 2.11 | B27: =VLOOKUP(Tabla3[[#This Row],[Part.]],PPto[],3,FALSE) -> 2.11 Supervisión Arquitectónica | C27: =SUMIF(BD.PD[Pos],Tabla3[[#This Row],[Part.]],BD.PD[Ppto. Orden Interna '[DOP']]) -> 0 | D27: =SUMIFS(BD.PD[Pago 1],BD.PD[Per.P1],D$1,BD.PD[Pos],Tabla3[[#This Row],[Part.]])+SUMIFS(BD.PD[Pago 2],BD.PD[Per.P2],D$1,BD.PD[Pos],Tabla3[[#This Row],[Part.]])+SUMIFS(BD.PD[Pago 3],BD.PD[Per.P3],D$1,BD.PD[Pos],Tabla3[[#This Row],[Part.]])+SUMIFS(BD.PD[Pago 4],BD.PD[Per.P4],D$1,BD.PD[Pos],Tabla3[[#This Row],[Part.]])+SUMIFS(BD.PD[Pago 5],BD.PD[Per.P5],D$1,BD.PD[Pos],Tabla3[[#This Row],[Part.]]) -> 0 | E27: =SUMIFS(BD.PD[Pago 1],BD.PD[Per.P1],E$1,BD.PD[Pos],Tabla3[[#This Row],[Part.]])+SUMIFS(BD.PD[Pago 2],BD.PD[Per.P2],E$1,BD.PD[Pos],Tabla3[[#This Row],[Part.]])+SUMIFS(BD.PD[Pago 3],BD.PD[Per.P3],E$1,BD.PD[Pos],Tabla3[[#This Row],[Part.]])+SUMIFS(BD.PD[Pago 4],BD.PD[Per.P4],E$1,BD.PD[Pos],Tabla3[[#This Row],[Part.]])+SUMIFS(BD.PD[Pago 5],BD.PD[Per.P5],E$1,BD.PD[Pos],Tabla3[[#This Row],[Part.]]) -> 0 | F27: =SUMIFS(BD.PD[Pago 1],BD.PD[Per.P1],F$1,BD.PD[Pos],Tabla3[[#This Row],[Part.]])+SUMIFS(BD.PD[Pago 2],BD.PD[Per.P2],F$1,BD.PD[Pos],Tabla3[[#This Row],[Part.]])+SUMIFS(BD.PD[Pago 3],BD.PD[Per.P3],F$1,BD.PD[Pos],Tabla3[[#This Row],[Part.]])+SUMIFS(BD.PD[Pago 4],BD.PD[Per.P4],F$1,BD.PD[Pos],Tabla3[[#This Row],[Part.]])+SUMIFS(BD.PD[Pago 5],BD.PD[Per.P5],F$1,BD.PD[Pos],Tabla3[[#This Row],[Part.]]) -> 0 | G27: =SUMIFS(BD.PD[Pago 1],BD.PD[Per.P1],G$1,BD.PD[Pos],Tabla3[[#This Row],[Part.]])+SUMIFS(BD.PD[Pago 2],BD.PD[Per.P2],G$1,BD.PD[Pos],Tabla3[[#This Row],[Part.]])+SUMIFS(BD.PD[Pago 3],BD.PD[Per.P3],G$1,BD.PD[Pos],Tabla3[[#This Row],[Part.]])+SUMIFS(BD.PD[Pago 4],BD.PD[Per.P4],G$1,BD.PD[Pos],Tabla3[[#This Row],[Part.]])+SUMIFS(BD.PD[Pago 5],BD.PD[Per.P5],G$1,BD.PD[Pos],Tabla3[[#This Row],[Part.]]) -> 0 | H27: =SUMIFS(BD.PD[Pago 1],BD.PD[Per.P1],H$1,BD.PD[Pos],Tabla3[[#This Row],[Part.]])+SUMIFS(BD.PD[Pago 2],BD.PD[Per.P2],H$1,BD.PD[Pos],Tabla3[[#This Row],[Part.]])+SUMIFS(BD.PD[Pago 3],BD.PD[Per.P3],H$1,BD.PD[Pos],Tabla3[[#This Row],[Part.]])+SUMIFS(BD.PD[Pago 4],BD.PD[Per.P4],H$1,BD.PD[Pos],Tabla3[[#This Row],[Part.]])+SUMIFS(BD.PD[Pago 5],BD.PD[Per.P5],H$1,BD.PD[Pos],Tabla3[[#This Row],[Part.]]) -> 0 | I27: =SUMIFS(BD.PD[Pago 1],BD.PD[Per.P1],I$1,BD.PD[Pos],Tabla3[[#This Row],[Part.]])+SUMIFS(BD.PD[Pago 2],BD.PD[Per.P2],I$1,BD.PD[Pos],Tabla3[[#This Row],[Part.]])+SUMIFS(BD.PD[Pago 3],BD.PD[Per.P3],I$1,BD.PD[Pos],Tabla3[[#This Row],[Part.]])+SUMIFS(BD.PD[Pago 4],BD.PD[Per.P4],I$1,BD.PD[Pos],Tabla3[[#This Row],[Part.]])+SUMIFS(BD.PD[Pago 5],BD.PD[Per.P5],I$1,BD.PD[Pos],Tabla3[[#This Row],[Part.]]) -> 0 | J27: =SUMIFS(BD.PD[Pago 1],BD.PD[Per.P1],J$1,BD.PD[Pos],Tabla3[[#This Row],[Part.]])+SUMIFS(BD.PD[Pago 2],BD.PD[Per.P2],J$1,BD.PD[Pos],Tabla3[[#This Row],[Part.]])+SUMIFS(BD.PD[Pago 3],BD.PD[Per.P3],J$1,BD.PD[Pos],Tabla3[[#This Row],[Part.]])+SUMIFS(BD.PD[Pago 4],BD.PD[Per.P4],J$1,BD.PD[Pos],Tabla3[[#This Row],[Part.]])+SUMIFS(BD.PD[Pago 5],BD.PD[Per.P5],J$1,BD.PD[Pos],Tabla3[[#This Row],[Part.]]) -> 0 | K27: =SUMIFS(BD.PD[Pago 1],BD.PD[Per.P1],K$1,BD.PD[Pos],Tabla3[[#This Row],[Part.]])+SUMIFS(BD.PD[Pago 2],BD.PD[Per.P2],K$1,BD.PD[Pos],Tabla3[[#This Row],[Part.]])+SUMIFS(BD.PD[Pago 3],BD.PD[Per.P3],K$1,BD.PD[Pos],Tabla3[[#This Row],[Part.]])+SUMIFS(BD.PD[Pago 4],BD.PD[Per.P4],K$1,BD.PD[Pos],Tabla3[[#This Row],[Part.]])+SUMIFS(BD.PD[Pago 5],BD.PD[Per.P5],K$1,BD.PD[Pos],Tabla3[[#This Row],[Part.]]) -> 0 | ... Z27: =SUMIFS(BD.PD[Pago 1],BD.PD[Per.P1],Z$1,BD.PD[Pos],Tabla3[[#This Row],[Part.]])+SUMIFS(BD.PD[Pago 2],BD.PD[Per.P2],Z$1,BD.PD[Pos],Tabla3[[#This Row],[Part.]])+SUMIFS(BD.PD[Pago 3],BD.PD[Per.P3],Z$1,BD.PD[Pos],Tabla3[[#This Row],[Part.]])+SUMIFS(BD.PD[Pago 4],BD.PD[Per.P4],Z$1,BD.PD[Pos],Tabla3[[#This Row],[Part.]])+SUMIFS(BD.PD[Pago 5],BD.PD[Per.P5],Z$1,BD.PD[Pos],Tabla3[[#This Row],[Part.]]) -> 0 | AB27: =SUMIFS(BD.PD[Pago 1],BD.PD[Per.P1],AB$1,BD.PD[Pos],Tabla3[[#This Row],[Part.]])+SUMIFS(BD.PD[Pago 2],BD.PD[Per.P2],AB$1,BD.PD[Pos],Tabla3[[#This Row],[Part.]])+SUMIFS(BD.PD[Pago 3],BD.PD[Per.P3],AB$1,BD.PD[Pos],Tabla3[[#This Row],[Part.]])+SUMIFS(BD.PD[Pago 4],BD.PD[Per.P4],AB$1,BD.PD[Pos],Tabla3[[#This Row],[Part.]])+SUMIFS(BD.PD[Pago 5],BD.PD[Per.P5],AB$1,BD.PD[Pos],Tabla3[[#This Row],[Part.]]) -> 0 | AC27: =SUMIFS(BD.PD[Pago 1],BD.PD[Per.P1],AC$1,BD.PD[Pos],Tabla3[[#This Row],[Part.]])+SUMIFS(BD.PD[Pago 2],BD.PD[Per.P2],AC$1,BD.PD[Pos],Tabla3[[#This Row],[Part.]])+SUMIFS(BD.PD[Pago 3],BD.PD[Per.P3],AC$1,BD.PD[Pos],Tabla3[[#This Row],[Part.]])+SUMIFS(BD.PD[Pago 4],BD.PD[Per.P4],AC$1,BD.PD[Pos],Tabla3[[#This Row],[Part.]])+SUMIFS(BD.PD[Pago 5],BD.PD[Per.P5],AC$1,BD.PD[Pos],Tabla3[[#This Row],[Part.]]) -> 0 | AD27: =SUMIFS(BD.PD[Pago 1],BD.PD[Per.P1],AD$1,BD.PD[Pos],Tabla3[[#This Row],[Part.]])+SUMIFS(BD.PD[Pago 2],BD.PD[Per.P2],AD$1,BD.PD[Pos],Tabla3[[#This Row],[Part.]])+SUMIFS(BD.PD[Pago 3],BD.PD[Per.P3],AD$1,BD.PD[Pos],Tabla3[[#This Row],[Part.]])+SUMIFS(BD.PD[Pago 4],BD.PD[Per.P4],AD$1,BD.PD[Pos],Tabla3[[#This Row],[Part.]])+SUMIFS(BD.PD[Pago 5],BD.PD[Per.P5],AD$1,BD.PD[Pos],Tabla3[[#This Row],[Part.]]) -> 0 | AE27: =SUMIFS(BD.PD[Pago 1],BD.PD[Per.P1],AE$1,BD.PD[Pos],Tabla3[[#This Row],[Part.]])+SUMIFS(BD.PD[Pago 2],BD.PD[Per.P2],AE$1,BD.PD[Pos],Tabla3[[#This Row],[Part.]])+SUMIFS(BD.PD[Pago 3],BD.PD[Per.P3],AE$1,BD.PD[Pos],Tabla3[[#This Row],[Part.]])+SUMIFS(BD.PD[Pago 4],BD.PD[Per.P4],AE$1,BD.PD[Pos],Tabla3[[#This Row],[Part.]])+SUMIFS(BD.PD[Pago 5],BD.PD[Per.P5],AE$1,BD.PD[Pos],Tabla3[[#This Row],[Part.]]) -> 0 | AF27: =SUMIFS(BD.PD[Pago 1],BD.PD[Per.P1],AF$1,BD.PD[Pos],Tabla3[[#This Row],[Part.]])+SUMIFS(BD.PD[Pago 2],BD.PD[Per.P2],AF$1,BD.PD[Pos],Tabla3[[#This Row],[Part.]])+SUMIFS(BD.PD[Pago 3],BD.PD[Per.P3],AF$1,BD.PD[Pos],Tabla3[[#This Row],[Part.]])+SUMIFS(BD.PD[Pago 4],BD.PD[Per.P4],AF$1,BD.PD[Pos],Tabla3[[#This Row],[Part.]])+SUMIFS(BD.PD[Pago 5],BD.PD[Per.P5],AF$1,BD.PD[Pos],Tabla3[[#This Row],[Part.]]) -> 0 | AG27: =SUMIFS(BD.PD[Pago 1],BD.PD[Per.P1],AG$1,BD.PD[Pos],Tabla3[[#This Row],[Part.]])+SUMIFS(BD.PD[Pago 2],BD.PD[Per.P2],AG$1,BD.PD[Pos],Tabla3[[#This Row],[Part.]])+SUMIFS(BD.PD[Pago 3],BD.PD[Per.P3],AG$1,BD.PD[Pos],Tabla3[[#This Row],[Part.]])+SUMIFS(BD.PD[Pago 4],BD.PD[Per.P4],AG$1,BD.PD[Pos],Tabla3[[#This Row],[Part.]])+SUMIFS(BD.PD[Pago 5],BD.PD[Per.P5],AG$1,BD.PD[Pos],Tabla3[[#This Row],[Part.]]) -> 0 | AH27: =SUM(Tabla3[[#This Row],[P1]:[P24]]) -> 0
A28: 3 | B28: =VLOOKUP(Tabla3[[#This Row],[Part.]],PPto[],3,FALSE) -> 3.00 Sistema Eléctrico | C28: =SUM(C29:C32) -> 27933332 | D28: =SUM(D29:D32) -> 0 | E28: =SUM(E29:E32) -> 13357299 | F28: =SUM(F29:F32) -> 0 | G28: =SUM(G29:G32) -> 0 | H28: =SUM(H29:H32) -> 0 | I28: =SUM(I29:I32) -> 0 | J28: =SUM(J29:J32) -> 0 | ... N28: =SUM(N29:N32) -> 0 | O28: =SUM(O29:O39) -> 0 | P28: =SUM(P29:P32) -> 0 | Q28: =SUM(Q29:Q32) -> 0 | R28: =SUM(R29:R32) -> 0 | S28: =SUM(S29:S32) -> 0 | T28: =SUM(T29:T32) -> 0 | U28: =SUM(U29:U32) -> 0 | V28: =SUM(V29:V32) -> 0 | W28: =SUM(W29:W32) -> 0 | ... AA28: =SUM(AA29:AA32) -> 0 | AB28: =SUMIFS(BD.PD[Pago 1],BD.PD[Per.P1],AB$1,BD.PD[Pos],Tabla3[[#This Row],[Part.]])+SUMIFS(BD.PD[Pago 2],BD.PD[Per.P2],AB$1,BD.PD[Pos],Tabla3[[#This Row],[Part.]])+SUMIFS(BD.PD[Pago 3],BD.PD[Per.P3],AB$1,BD.PD[Pos],Tabla3[[#This Row],[Part.]])+SUMIFS(BD.PD[Pago 4],BD.PD[Per.P4],AB$1,BD.PD[Pos],Tabla3[[#This Row],[Part.]])+SUMIFS(BD.PD[Pago 5],BD.PD[Per.P5],AB$1,BD.PD[Pos],Tabla3[[#This Row],[Part.]]) -> 0 | AC28: =SUMIFS(BD.PD[Pago 1],BD.PD[Per.P1],AC$1,BD.PD[Pos],Tabla3[[#This Row],[Part.]])+SUMIFS(BD.PD[Pago 2],BD.PD[Per.P2],AC$1,BD.PD[Pos],Tabla3[[#This Row],[Part.]])+SUMIFS(BD.PD[Pago 3],BD.PD[Per.P3],AC$1,BD.PD[Pos],Tabla3[[#This Row],[Part.]])+SUMIFS(BD.PD[Pago 4],BD.PD[Per.P4],AC$1,BD.PD[Pos],Tabla3[[#This Row],[Part.]])+SUMIFS(BD.PD[Pago 5],BD.PD[Per.P5],AC$1,BD.PD[Pos],Tabla3[[#This Row],[Part.]]) -> 0 | AD28: =SUMIFS(BD.PD[Pago 1],BD.PD[Per.P1],AD$1,BD.PD[Pos],Tabla3[[#This Row],[Part.]])+SUMIFS(BD.PD[Pago 2],BD.PD[Per.P2],AD$1,BD.PD[Pos],Tabla3[[#This Row],[Part.]])+SUMIFS(BD.PD[Pago 3],BD.PD[Per.P3],AD$1,BD.PD[Pos],Tabla3[[#This Row],[Part.]])+SUMIFS(BD.PD[Pago 4],BD.PD[Per.P4],AD$1,BD.PD[Pos],Tabla3[[#This Row],[Part.]])+SUMIFS(BD.PD[Pago 5],BD.PD[Per.P5],AD$1,BD.PD[Pos],Tabla3[[#This Row],[Part.]]) -> 0 | AE28: =SUMIFS(BD.PD[Pago 1],BD.PD[Per.P1],AE$1,BD.PD[Pos],Tabla3[[#This Row],[Part.]])+SUMIFS(BD.PD[Pago 2],BD.PD[Per.P2],AE$1,BD.PD[Pos],Tabla3[[#This Row],[Part.]])+SUMIFS(BD.PD[Pago 3],BD.PD[Per.P3],AE$1,BD.PD[Pos],Tabla3[[#This Row],[Part.]])+SUMIFS(BD.PD[Pago 4],BD.PD[Per.P4],AE$1,BD.PD[Pos],Tabla3[[#This Row],[Part.]])+SUMIFS(BD.PD[Pago 5],BD.PD[Per.P5],AE$1,BD.PD[Pos],Tabla3[[#This Row],[Part.]]) -> 0 | AF28: =SUMIFS(BD.PD[Pago 1],BD.PD[Per.P1],AF$1,BD.PD[Pos],Tabla3[[#This Row],[Part.]])+SUMIFS(BD.PD[Pago 2],BD.PD[Per.P2],AF$1,BD.PD[Pos],Tabla3[[#This Row],[Part.]])+SUMIFS(BD.PD[Pago 3],BD.PD[Per.P3],AF$1,BD.PD[Pos],Tabla3[[#This Row],[Part.]])+SUMIFS(BD.PD[Pago 4],BD.PD[Per.P4],AF$1,BD.PD[Pos],Tabla3[[#This Row],[Part.]])+SUMIFS(BD.PD[Pago 5],BD.PD[Per.P5],AF$1,BD.PD[Pos],Tabla3[[#This Row],[Part.]]) -> 0 | AG28: =SUMIFS(BD.PD[Pago 1],BD.PD[Per.P1],AG$1,BD.PD[Pos],Tabla3[[#This Row],[Part.]])+SUMIFS(BD.PD[Pago 2],BD.PD[Per.P2],AG$1,BD.PD[Pos],Tabla3[[#This Row],[Part.]])+SUMIFS(BD.PD[Pago 3],BD.PD[Per.P3],AG$1,BD.PD[Pos],Tabla3[[#This Row],[Part.]])+SUMIFS(BD.PD[Pago 4],BD.PD[Per.P4],AG$1,BD.PD[Pos],Tabla3[[#This Row],[Part.]])+SUMIFS(BD.PD[Pago 5],BD.PD[Per.P5],AG$1,BD.PD[Pos],Tabla3[[#This Row],[Part.]]) -> 0 | AH28: =SUM(Tabla3[[#This Row],[P1]:[P24]]) -> 27933332
A29: 3.01 | B29: =VLOOKUP(Tabla3[[#This Row],[Part.]],PPto[],3,FALSE) -> 3.01 Instalaciones Eléctricas | C29: =SUMIF(BD.PD[Pos],Tabla3[[#This Row],[Part.]],BD.PD[Ppto. Orden Interna '[DOP']]) -> 16303582 | D29: =SUMIFS(BD.PD[Pago 1],BD.PD[Per.P1],D$1,BD.PD[Pos],Tabla3[[#This Row],[Part.]])+SUMIFS(BD.PD[Pago 2],BD.PD[Per.P2],D$1,BD.PD[Pos],Tabla3[[#This Row],[Part.]])+SUMIFS(BD.PD[Pago 3],BD.PD[Per.P3],D$1,BD.PD[Pos],Tabla3[[#This Row],[Part.]])+SUMIFS(BD.PD[Pago 4],BD.PD[Per.P4],D$1,BD.PD[Pos],Tabla3[[#This Row],[Part.]])+SUMIFS(BD.PD[Pago 5],BD.PD[Per.P5],D$1,BD.PD[Pos],Tabla3[[#This Row],[Part.]]) -> 0 | E29: =SUMIFS(BD.PD[Pago 1],BD.PD[Per.P1],E$1,BD.PD[Pos],Tabla3[[#This Row],[Part.]])+SUMIFS(BD.PD[Pago 2],BD.PD[Per.P2],E$1,BD.PD[Pos],Tabla3[[#This Row],[Part.]])+SUMIFS(BD.PD[Pago 3],BD.PD[Per.P3],E$1,BD.PD[Pos],Tabla3[[#This Row],[Part.]])+SUMIFS(BD.PD[Pago 4],BD.PD[Per.P4],E$1,BD.PD[Pos],Tabla3[[#This Row],[Part.]])+SUMIFS(BD.PD[Pago 5],BD.PD[Per.P5],E$1,BD.PD[Pos],Tabla3[[#This Row],[Part.]]) -> 8151790.8 | F29: =SUMIFS(BD.PD[Pago 1],BD.PD[Per.P1],F$1,BD.PD[Pos],Tabla3[[#This Row],[Part.]])+SUMIFS(BD.PD[Pago 2],BD.PD[Per.P2],F$1,BD.PD[Pos],Tabla3[[#This Row],[Part.]])+SUMIFS(BD.PD[Pago 3],BD.PD[Per.P3],F$1,BD.PD[Pos],Tabla3[[#This Row],[Part.]])+SUMIFS(BD.PD[Pago 4],BD.PD[Per.P4],F$1,BD.PD[Pos],Tabla3[[#This Row],[Part.]])+SUMIFS(BD.PD[Pago 5],BD.PD[Per.P5],F$1,BD.PD[Pos],Tabla3[[#This Row],[Part.]]) -> 0 | G29: =SUMIFS(BD.PD[Pago 1],BD.PD[Per.P1],G$1,BD.PD[Pos],Tabla3[[#This Row],[Part.]])+SUMIFS(BD.PD[Pago 2],BD.PD[Per.P2],G$1,BD.PD[Pos],Tabla3[[#This Row],[Part.]])+SUMIFS(BD.PD[Pago 3],BD.PD[Per.P3],G$1,BD.PD[Pos],Tabla3[[#This Row],[Part.]])+SUMIFS(BD.PD[Pago 4],BD.PD[Per.P4],G$1,BD.PD[Pos],Tabla3[[#This Row],[Part.]])+SUMIFS(BD.PD[Pago 5],BD.PD[Per.P5],G$1,BD.PD[Pos],Tabla3[[#This Row],[Part.]]) -> 0 | H29: =SUMIFS(BD.PD[Pago 1],BD.PD[Per.P1],H$1,BD.PD[Pos],Tabla3[[#This Row],[Part.]])+SUMIFS(BD.PD[Pago 2],BD.PD[Per.P2],H$1,BD.PD[Pos],Tabla3[[#This Row],[Part.]])+SUMIFS(BD.PD[Pago 3],BD.PD[Per.P3],H$1,BD.PD[Pos],Tabla3[[#This Row],[Part.]])+SUMIFS(BD.PD[Pago 4],BD.PD[Per.P4],H$1,BD.PD[Pos],Tabla3[[#This Row],[Part.]])+SUMIFS(BD.PD[Pago 5],BD.PD[Per.P5],H$1,BD.PD[Pos],Tabla3[[#This Row],[Part.]]) -> 0 | I29: =SUMIFS(BD.PD[Pago 1],BD.PD[Per.P1],I$1,BD.PD[Pos],Tabla3[[#This Row],[Part.]])+SUMIFS(BD.PD[Pago 2],BD.PD[Per.P2],I$1,BD.PD[Pos],Tabla3[[#This Row],[Part.]])+SUMIFS(BD.PD[Pago 3],BD.PD[Per.P3],I$1,BD.PD[Pos],Tabla3[[#This Row],[Part.]])+SUMIFS(BD.PD[Pago 4],BD.PD[Per.P4],I$1,BD.PD[Pos],Tabla3[[#This Row],[Part.]])+SUMIFS(BD.PD[Pago 5],BD.PD[Per.P5],I$1,BD.PD[Pos],Tabla3[[#This Row],[Part.]]) -> 0 | J29: =SUMIFS(BD.PD[Pago 1],BD.PD[Per.P1],J$1,BD.PD[Pos],Tabla3[[#This Row],[Part.]])+SUMIFS(BD.PD[Pago 2],BD.PD[Per.P2],J$1,BD.PD[Pos],Tabla3[[#This Row],[Part.]])+SUMIFS(BD.PD[Pago 3],BD.PD[Per.P3],J$1,BD.PD[Pos],Tabla3[[#This Row],[Part.]])+SUMIFS(BD.PD[Pago 4],BD.PD[Per.P4],J$1,BD.PD[Pos],Tabla3[[#This Row],[Part.]])+SUMIFS(BD.PD[Pago 5],BD.PD[Per.P5],J$1,BD.PD[Pos],Tabla3[[#This Row],[Part.]]) -> 0 | K29: =SUMIFS(BD.PD[Pago 1],BD.PD[Per.P1],K$1,BD.PD[Pos],Tabla3[[#This Row],[Part.]])+SUMIFS(BD.PD[Pago 2],BD.PD[Per.P2],K$1,BD.PD[Pos],Tabla3[[#This Row],[Part.]])+SUMIFS(BD.PD[Pago 3],BD.PD[Per.P3],K$1,BD.PD[Pos],Tabla3[[#This Row],[Part.]])+SUMIFS(BD.PD[Pago 4],BD.PD[Per.P4],K$1,BD.PD[Pos],Tabla3[[#This Row],[Part.]])+SUMIFS(BD.PD[Pago 5],BD.PD[Per.P5],K$1,BD.PD[Pos],Tabla3[[#This Row],[Part.]]) -> 0 | ... AG29: =SUMIFS(BD.PD[Pago 1],BD.PD[Per.P1],AG$1,BD.PD[Pos],Tabla3[[#This Row],[Part.]])+SUMIFS(BD.PD[Pago 2],BD.PD[Per.P2],AG$1,BD.PD[Pos],Tabla3[[#This Row],[Part.]])+SUMIFS(BD.PD[Pago 3],BD.PD[Per.P3],AG$1,BD.PD[Pos],Tabla3[[#This Row],[Part.]])+SUMIFS(BD.PD[Pago 4],BD.PD[Per.P4],AG$1,BD.PD[Pos],Tabla3[[#This Row],[Part.]])+SUMIFS(BD.PD[Pago 5],BD.PD[Per.P5],AG$1,BD.PD[Pos],Tabla3[[#This Row],[Part.]]) -> 0 | AH29: =SUM(Tabla3[[#This Row],[P1]:[P24]]) -> 16303582
A30: 3.02 | B30: =VLOOKUP(Tabla3[[#This Row],[Part.]],PPto[],3,FALSE) -> 3.02 Supervisión Eléctrica | C30: =SUMIF(BD.PD[Pos],Tabla3[[#This Row],[Part.]],BD.PD[Ppto. Orden Interna '[DOP']]) -> 0 | D30: =SUMIFS(BD.PD[Pago 1],BD.PD[Per.P1],D$1,BD.PD[Pos],Tabla3[[#This Row],[Part.]])+SUMIFS(BD.PD[Pago 2],BD.PD[Per.P2],D$1,BD.PD[Pos],Tabla3[[#This Row],[Part.]])+SUMIFS(BD.PD[Pago 3],BD.PD[Per.P3],D$1,BD.PD[Pos],Tabla3[[#This Row],[Part.]])+SUMIFS(BD.PD[Pago 4],BD.PD[Per.P4],D$1,BD.PD[Pos],Tabla3[[#This Row],[Part.]])+SUMIFS(BD.PD[Pago 5],BD.PD[Per.P5],D$1,BD.PD[Pos],Tabla3[[#This Row],[Part.]]) -> 0 | E30: =SUMIFS(BD.PD[Pago 1],BD.PD[Per.P1],E$1,BD.PD[Pos],Tabla3[[#This Row],[Part.]])+SUMIFS(BD.PD[Pago 2],BD.PD[Per.P2],E$1,BD.PD[Pos],Tabla3[[#This Row],[Part.]])+SUMIFS(BD.PD[Pago 3],BD.PD[Per.P3],E$1,BD.PD[Pos],Tabla3[[#This Row],[Part.]])+SUMIFS(BD.PD[Pago 4],BD.PD[Per.P4],E$1,BD.PD[Pos],Tabla3[[#This Row],[Part.]])+SUMIFS(BD.PD[Pago 5],BD.PD[Per.P5],E$1,BD.PD[Pos],Tabla3[[#This Row],[Part.]]) -> 0 | F30: =SUMIFS(BD.PD[Pago 1],BD.PD[Per.P1],F$1,BD.PD[Pos],Tabla3[[#This Row],[Part.]])+SUMIFS(BD.PD[Pago 2],BD.PD[Per.P2],F$1,BD.PD[Pos],Tabla3[[#This Row],[Part.]])+SUMIFS(BD.PD[Pago 3],BD.PD[Per.P3],F$1,BD.PD[Pos],Tabla3[[#This Row],[Part.]])+SUMIFS(BD.PD[Pago 4],BD.PD[Per.P4],F$1,BD.PD[Pos],Tabla3[[#This Row],[Part.]])+SUMIFS(BD.PD[Pago 5],BD.PD[Per.P5],F$1,BD.PD[Pos],Tabla3[[#This Row],[Part.]]) -> 0 | G30: =SUMIFS(BD.PD[Pago 1],BD.PD[Per.P1],G$1,BD.PD[Pos],Tabla3[[#This Row],[Part.]])+SUMIFS(BD.PD[Pago 2],BD.PD[Per.P2],G$1,BD.PD[Pos],Tabla3[[#This Row],[Part.]])+SUMIFS(BD.PD[Pago 3],BD.PD[Per.P3],G$1,BD.PD[Pos],Tabla3[[#This Row],[Part.]])+SUMIFS(BD.PD[Pago 4],BD.PD[Per.P4],G$1,BD.PD[Pos],Tabla3[[#This Row],[Part.]])+SUMIFS(BD.PD[Pago 5],BD.PD[Per.P5],G$1,BD.PD[Pos],Tabla3[[#This Row],[Part.]]) -> 0 | H30: =SUMIFS(BD.PD[Pago 1],BD.PD[Per.P1],H$1,BD.PD[Pos],Tabla3[[#This Row],[Part.]])+SUMIFS(BD.PD[Pago 2],BD.PD[Per.P2],H$1,BD.PD[Pos],Tabla3[[#This Row],[Part.]])+SUMIFS(BD.PD[Pago 3],BD.PD[Per.P3],H$1,BD.PD[Pos],Tabla3[[#This Row],[Part.]])+SUMIFS(BD.PD[Pago 4],BD.PD[Per.P4],H$1,BD.PD[Pos],Tabla3[[#This Row],[Part.]])+SUMIFS(BD.PD[Pago 5],BD.PD[Per.P5],H$1,BD.PD[Pos],Tabla3[[#This Row],[Part.]]) -> 0 | I30: =SUMIFS(BD.PD[Pago 1],BD.PD[Per.P1],I$1,BD.PD[Pos],Tabla3[[#This Row],[Part.]])+SUMIFS(BD.PD[Pago 2],BD.PD[Per.P2],I$1,BD.PD[Pos],Tabla3[[#This Row],[Part.]])+SUMIFS(BD.PD[Pago 3],BD.PD[Per.P3],I$1,BD.PD[Pos],Tabla3[[#This Row],[Part.]])+SUMIFS(BD.PD[Pago 4],BD.PD[Per.P4],I$1,BD.PD[Pos],Tabla3[[#This Row],[Part.]])+SUMIFS(BD.PD[Pago 5],BD.PD[Per.P5],I$1,BD.PD[Pos],Tabla3[[#This Row],[Part.]]) -> 0 | J30: =SUMIFS(BD.PD[Pago 1],BD.PD[Per.P1],J$1,BD.PD[Pos],Tabla3[[#This Row],[Part.]])+SUMIFS(BD.PD[Pago 2],BD.PD[Per.P2],J$1,BD.PD[Pos],Tabla3[[#This Row],[Part.]])+SUMIFS(BD.PD[Pago 3],BD.PD[Per.P3],J$1,BD.PD[Pos],Tabla3[[#This Row],[Part.]])+SUMIFS(BD.PD[Pago 4],BD.PD[Per.P4],J$1,BD.PD[Pos],Tabla3[[#This Row],[Part.]])+SUMIFS(BD.PD[Pago 5],BD.PD[Per.P5],J$1,BD.PD[Pos],Tabla3[[#This Row],[Part.]]) -> 0 | K30: =SUMIFS(BD.PD[Pago 1],BD.PD[Per.P1],K$1,BD.PD[Pos],Tabla3[[#This Row],[Part.]])+SUMIFS(BD.PD[Pago 2],BD.PD[Per.P2],K$1,BD.PD[Pos],Tabla3[[#This Row],[Part.]])+SUMIFS(BD.PD[Pago 3],BD.PD[Per.P3],K$1,BD.PD[Pos],Tabla3[[#This Row],[Part.]])+SUMIFS(BD.PD[Pago 4],BD.PD[Per.P4],K$1,BD.PD[Pos],Tabla3[[#This Row],[Part.]])+SUMIFS(BD.PD[Pago 5],BD.PD[Per.P5],K$1,BD.PD[Pos],Tabla3[[#This Row],[Part.]]) -> 0 | ... AG30: =SUMIFS(BD.PD[Pago 1],BD.PD[Per.P1],AG$1,BD.PD[Pos],Tabla3[[#This Row],[Part.]])+SUMIFS(BD.PD[Pago 2],BD.PD[Per.P2],AG$1,BD.PD[Pos],Tabla3[[#This Row],[Part.]])+SUMIFS(BD.PD[Pago 3],BD.PD[Per.P3],AG$1,BD.PD[Pos],Tabla3[[#This Row],[Part.]])+SUMIFS(BD.PD[Pago 4],BD.PD[Per.P4],AG$1,BD.PD[Pos],Tabla3[[#This Row],[Part.]])+SUMIFS(BD.PD[Pago 5],BD.PD[Per.P5],AG$1,BD.PD[Pos],Tabla3[[#This Row],[Part.]]) -> 0 | AH30: =SUM(Tabla3[[#This Row],[P1]:[P24]]) -> 0
A31: 3.03 | B31: =VLOOKUP(Tabla3[[#This Row],[Part.]],PPto[],3,FALSE) -> 3.03 Generadores | C31: =SUMIF(BD.PD[Pos],Tabla3[[#This Row],[Part.]],BD.PD[Ppto. Orden Interna '[DOP']]) -> 10411016 | D31: =SUMIFS(BD.PD[Pago 1],BD.PD[Per.P1],D$1,BD.PD[Pos],Tabla3[[#This Row],[Part.]])+SUMIFS(BD.PD[Pago 2],BD.PD[Per.P2],D$1,BD.PD[Pos],Tabla3[[#This Row],[Part.]])+SUMIFS(BD.PD[Pago 3],BD.PD[Per.P3],D$1,BD.PD[Pos],Tabla3[[#This Row],[Part.]])+SUMIFS(BD.PD[Pago 4],BD.PD[Per.P4],D$1,BD.PD[Pos],Tabla3[[#This Row],[Part.]])+SUMIFS(BD.PD[Pago 5],BD.PD[Per.P5],D$1,BD.PD[Pos],Tabla3[[#This Row],[Part.]]) -> 0 | E31: =SUMIFS(BD.PD[Pago 1],BD.PD[Per.P1],E$1,BD.PD[Pos],Tabla3[[#This Row],[Part.]])+SUMIFS(BD.PD[Pago 2],BD.PD[Per.P2],E$1,BD.PD[Pos],Tabla3[[#This Row],[Part.]])+SUMIFS(BD.PD[Pago 3],BD.PD[Per.P3],E$1,BD.PD[Pos],Tabla3[[#This Row],[Part.]])+SUMIFS(BD.PD[Pago 4],BD.PD[Per.P4],E$1,BD.PD[Pos],Tabla3[[#This Row],[Part.]])+SUMIFS(BD.PD[Pago 5],BD.PD[Per.P5],E$1,BD.PD[Pos],Tabla3[[#This Row],[Part.]]) -> 5205507.9 | F31: =SUMIFS(BD.PD[Pago 1],BD.PD[Per.P1],F$1,BD.PD[Pos],Tabla3[[#This Row],[Part.]])+SUMIFS(BD.PD[Pago 2],BD.PD[Per.P2],F$1,BD.PD[Pos],Tabla3[[#This Row],[Part.]])+SUMIFS(BD.PD[Pago 3],BD.PD[Per.P3],F$1,BD.PD[Pos],Tabla3[[#This Row],[Part.]])+SUMIFS(BD.PD[Pago 4],BD.PD[Per.P4],F$1,BD.PD[Pos],Tabla3[[#This Row],[Part.]])+SUMIFS(BD.PD[Pago 5],BD.PD[Per.P5],F$1,BD.PD[Pos],Tabla3[[#This Row],[Part.]]) -> 0 | G31: =SUMIFS(BD.PD[Pago 1],BD.PD[Per.P1],G$1,BD.PD[Pos],Tabla3[[#This Row],[Part.]])+SUMIFS(BD.PD[Pago 2],BD.PD[Per.P2],G$1,BD.PD[Pos],Tabla3[[#This Row],[Part.]])+SUMIFS(BD.PD[Pago 3],BD.PD[Per.P3],G$1,BD.PD[Pos],Tabla3[[#This Row],[Part.]])+SUMIFS(BD.PD[Pago 4],BD.PD[Per.P4],G$1,BD.PD[Pos],Tabla3[[#This Row],[Part.]])+SUMIFS(BD.PD[Pago 5],BD.PD[Per.P5],G$1,BD.PD[Pos],Tabla3[[#This Row],[Part.]]) -> 0 | H31: =SUMIFS(BD.PD[Pago 1],BD.PD[Per.P1],H$1,BD.PD[Pos],Tabla3[[#This Row],[Part.]])+SUMIFS(BD.PD[Pago 2],BD.PD[Per.P2],H$1,BD.PD[Pos],Tabla3[[#This Row],[Part.]])+SUMIFS(BD.PD[Pago 3],BD.PD[Per.P3],H$1,BD.PD[Pos],Tabla3[[#This Row],[Part.]])+SUMIFS(BD.PD[Pago 4],BD.PD[Per.P4],H$1,BD.PD[Pos],Tabla3[[#This Row],[Part.]])+SUMIFS(BD.PD[Pago 5],BD.PD[Per.P5],H$1,BD.PD[Pos],Tabla3[[#This Row],[Part.]]) -> 0 | I31: =SUMIFS(BD.PD[Pago 1],BD.PD[Per.P1],I$1,BD.PD[Pos],Tabla3[[#This Row],[Part.]])+SUMIFS(BD.PD[Pago 2],BD.PD[Per.P2],I$1,BD.PD[Pos],Tabla3[[#This Row],[Part.]])+SUMIFS(BD.PD[Pago 3],BD.PD[Per.P3],I$1,BD.PD[Pos],Tabla3[[#This Row],[Part.]])+SUMIFS(BD.PD[Pago 4],BD.PD[Per.P4],I$1,BD.PD[Pos],Tabla3[[#This Row],[Part.]])+SUMIFS(BD.PD[Pago 5],BD.PD[Per.P5],I$1,BD.PD[Pos],Tabla3[[#This Row],[Part.]]) -> 0 | J31: =SUMIFS(BD.PD[Pago 1],BD.PD[Per.P1],J$1,BD.PD[Pos],Tabla3[[#This Row],[Part.]])+SUMIFS(BD.PD[Pago 2],BD.PD[Per.P2],J$1,BD.PD[Pos],Tabla3[[#This Row],[Part.]])+SUMIFS(BD.PD[Pago 3],BD.PD[Per.P3],J$1,BD.PD[Pos],Tabla3[[#This Row],[Part.]])+SUMIFS(BD.PD[Pago 4],BD.PD[Per.P4],J$1,BD.PD[Pos],Tabla3[[#This Row],[Part.]])+SUMIFS(BD.PD[Pago 5],BD.PD[Per.P5],J$1,BD.PD[Pos],Tabla3[[#This Row],[Part.]]) -> 0 | K31: =SUMIFS(BD.PD[Pago 1],BD.PD[Per.P1],K$1,BD.PD[Pos],Tabla3[[#This Row],[Part.]])+SUMIFS(BD.PD[Pago 2],BD.PD[Per.P2],K$1,BD.PD[Pos],Tabla3[[#This Row],[Part.]])+SUMIFS(BD.PD[Pago 3],BD.PD[Per.P3],K$1,BD.PD[Pos],Tabla3[[#This Row],[Part.]])+SUMIFS(BD.PD[Pago 4],BD.PD[Per.P4],K$1,BD.PD[Pos],Tabla3[[#This Row],[Part.]])+SUMIFS(BD.PD[Pago 5],BD.PD[Per.P5],K$1,BD.PD[Pos],Tabla3[[#This Row],[Part.]]) -> 0 | ... AG31: =SUMIFS(BD.PD[Pago 1],BD.PD[Per.P1],AG$1,BD.PD[Pos],Tabla3[[#This Row],[Part.]])+SUMIFS(BD.PD[Pago 2],BD.PD[Per.P2],AG$1,BD.PD[Pos],Tabla3[[#This Row],[Part.]])+SUMIFS(BD.PD[Pago 3],BD.PD[Per.P3],AG$1,BD.PD[Pos],Tabla3[[#This Row],[Part.]])+SUMIFS(BD.PD[Pago 4],BD.PD[Per.P4],AG$1,BD.PD[Pos],Tabla3[[#This Row],[Part.]])+SUMIFS(BD.PD[Pago 5],BD.PD[Per.P5],AG$1,BD.PD[Pos],Tabla3[[#This Row],[Part.]]) -> 0 | AH31: =SUM(Tabla3[[#This Row],[P1]:[P24]]) -> 10411016
A32: 3.04 | B32: =VLOOKUP(Tabla3[[#This Row],[Part.]],PPto[],3,FALSE) -> 3.04 Inversor y UPS | C32: =SUMIF(BD.PD[Pos],Tabla3[[#This Row],[Part.]],BD.PD[Ppto. Orden Interna '[DOP']]) -> 1218735 | D32: =SUMIFS(BD.PD[Pago 1],BD.PD[Per.P1],D$1,BD.PD[Pos],Tabla3[[#This Row],[Part.]])+SUMIFS(BD.PD[Pago 2],BD.PD[Per.P2],D$1,BD.PD[Pos],Tabla3[[#This Row],[Part.]])+SUMIFS(BD.PD[Pago 3],BD.PD[Per.P3],D$1,BD.PD[Pos],Tabla3[[#This Row],[Part.]])+SUMIFS(BD.PD[Pago 4],BD.PD[Per.P4],D$1,BD.PD[Pos],Tabla3[[#This Row],[Part.]])+SUMIFS(BD.PD[Pago 5],BD.PD[Per.P5],D$1,BD.PD[Pos],Tabla3[[#This Row],[Part.]]) -> 0 | E32: =SUMIFS(BD.PD[Pago 1],BD.PD[Per.P1],E$1,BD.PD[Pos],Tabla3[[#This Row],[Part.]])+SUMIFS(BD.PD[Pago 2],BD.PD[Per.P2],E$1,BD.PD[Pos],Tabla3[[#This Row],[Part.]])+SUMIFS(BD.PD[Pago 3],BD.PD[Per.P3],E$1,BD.PD[Pos],Tabla3[[#This Row],[Part.]])+SUMIFS(BD.PD[Pago 4],BD.PD[Per.P4],E$1,BD.PD[Pos],Tabla3[[#This Row],[Part.]])+SUMIFS(BD.PD[Pago 5],BD.PD[Per.P5],E$1,BD.PD[Pos],Tabla3[[#This Row],[Part.]]) -> 0 | F32: =SUMIFS(BD.PD[Pago 1],BD.PD[Per.P1],F$1,BD.PD[Pos],Tabla3[[#This Row],[Part.]])+SUMIFS(BD.PD[Pago 2],BD.PD[Per.P2],F$1,BD.PD[Pos],Tabla3[[#This Row],[Part.]])+SUMIFS(BD.PD[Pago 3],BD.PD[Per.P3],F$1,BD.PD[Pos],Tabla3[[#This Row],[Part.]])+SUMIFS(BD.PD[Pago 4],BD.PD[Per.P4],F$1,BD.PD[Pos],Tabla3[[#This Row],[Part.]])+SUMIFS(BD.PD[Pago 5],BD.PD[Per.P5],F$1,BD.PD[Pos],Tabla3[[#This Row],[Part.]]) -> 0 | G32: =SUMIFS(BD.PD[Pago 1],BD.PD[Per.P1],G$1,BD.PD[Pos],Tabla3[[#This Row],[Part.]])+SUMIFS(BD.PD[Pago 2],BD.PD[Per.P2],G$1,BD.PD[Pos],Tabla3[[#This Row],[Part.]])+SUMIFS(BD.PD[Pago 3],BD.PD[Per.P3],G$1,BD.PD[Pos],Tabla3[[#This Row],[Part.]])+SUMIFS(BD.PD[Pago 4],BD.PD[Per.P4],G$1,BD.PD[Pos],Tabla3[[#This Row],[Part.]])+SUMIFS(BD.PD[Pago 5],BD.PD[Per.P5],G$1,BD.PD[Pos],Tabla3[[#This Row],[Part.]]) -> 0 | H32: =SUMIFS(BD.PD[Pago 1],BD.PD[Per.P1],H$1,BD.PD[Pos],Tabla3[[#This Row],[Part.]])+SUMIFS(BD.PD[Pago 2],BD.PD[Per.P2],H$1,BD.PD[Pos],Tabla3[[#This Row],[Part.]])+SUMIFS(BD.PD[Pago 3],BD.PD[Per.P3],H$1,BD.PD[Pos],Tabla3[[#This Row],[Part.]])+SUMIFS(BD.PD[Pago 4],BD.PD[Per.P4],H$1,BD.PD[Pos],Tabla3[[#This Row],[Part.]])+SUMIFS(BD.PD[Pago 5],BD.PD[Per.P5],H$1,BD.PD[Pos],Tabla3[[#This Row],[Part.]]) -> 0 | I32: =SUMIFS(BD.PD[Pago 1],BD.PD[Per.P1],I$1,BD.PD[Pos],Tabla3[[#This Row],[Part.]])+SUMIFS(BD.PD[Pago 2],BD.PD[Per.P2],I$1,BD.PD[Pos],Tabla3[[#This Row],[Part.]])+SUMIFS(BD.PD[Pago 3],BD.PD[Per.P3],I$1,BD.PD[Pos],Tabla3[[#This Row],[Part.]])+SUMIFS(BD.PD[Pago 4],BD.PD[Per.P4],I$1,BD.PD[Pos],Tabla3[[#This Row],[Part.]])+SUMIFS(BD.PD[Pago 5],BD.PD[Per.P5],I$1,BD.PD[Pos],Tabla3[[#This Row],[Part.]]) -> 0 | J32: =SUMIFS(BD.PD[Pago 1],BD.PD[Per.P1],J$1,BD.PD[Pos],Tabla3[[#This Row],[Part.]])+SUMIFS(BD.PD[Pago 2],BD.PD[Per.P2],J$1,BD.PD[Pos],Tabla3[[#This Row],[Part.]])+SUMIFS(BD.PD[Pago 3],BD.PD[Per.P3],J$1,BD.PD[Pos],Tabla3[[#This Row],[Part.]])+SUMIFS(BD.PD[Pago 4],BD.PD[Per.P4],J$1,BD.PD[Pos],Tabla3[[#This Row],[Part.]])+SUMIFS(BD.PD[Pago 5],BD.PD[Per.P5],J$1,BD.PD[Pos],Tabla3[[#This Row],[Part.]]) -> 0 | K32: =SUMIFS(BD.PD[Pago 1],BD.PD[Per.P1],K$1,BD.PD[Pos],Tabla3[[#This Row],[Part.]])+SUMIFS(BD.PD[Pago 2],BD.PD[Per.P2],K$1,BD.PD[Pos],Tabla3[[#This Row],[Part.]])+SUMIFS(BD.PD[Pago 3],BD.PD[Per.P3],K$1,BD.PD[Pos],Tabla3[[#This Row],[Part.]])+SUMIFS(BD.PD[Pago 4],BD.PD[Per.P4],K$1,BD.PD[Pos],Tabla3[[#This Row],[Part.]])+SUMIFS(BD.PD[Pago 5],BD.PD[Per.P5],K$1,BD.PD[Pos],Tabla3[[#This Row],[Part.]]) -> 0 | ... AG32: =SUMIFS(BD.PD[Pago 1],BD.PD[Per.P1],AG$1,BD.PD[Pos],Tabla3[[#This Row],[Part.]])+SUMIFS(BD.PD[Pago 2],BD.PD[Per.P2],AG$1,BD.PD[Pos],Tabla3[[#This Row],[Part.]])+SUMIFS(BD.PD[Pago 3],BD.PD[Per.P3],AG$1,BD.PD[Pos],Tabla3[[#This Row],[Part.]])+SUMIFS(BD.PD[Pago 4],BD.PD[Per.P4],AG$1,BD.PD[Pos],Tabla3[[#This Row],[Part.]])+SUMIFS(BD.PD[Pago 5],BD.PD[Per.P5],AG$1,BD.PD[Pos],Tabla3[[#This Row],[Part.]]) -> 0 | AH32: =SUM(Tabla3[[#This Row],[P1]:[P24]]) -> 1218735
A33: 4 | B33: =VLOOKUP(Tabla3[[#This Row],[Part.]],PPto[],3,FALSE) -> 4.00 Sistema de Climatización | C33: =SUM(C34:C36) -> 7596030.8 | D33: =SUM(D34:D36) -> 0 | E33: =SUM(E34:E36) -> 0 | F33: =SUM(F34:F36) -> 3208156.9 | G33: =SUM(G34:G36) -> 0 | H33: =SUM(H34:H36) -> 0 | I33: =SUM(I34:I36) -> 0 | J33: =SUM(J34:J36) -> 0 | ... N33: =SUM(N34:N36) -> 0 | O33: =SUM(O34:O44) -> 0 | P33: =SUM(P34:P36) -> 0 | Q33: =SUM(Q34:Q36) -> 0 | R33: =SUM(R34:R36) -> 0 | S33: =SUM(S34:S36) -> 0 | T33: =SUM(T34:T36) -> 0 | U33: =SUM(U34:U36) -> 0 | V33: =SUM(V34:V36) -> 0 | W33: =SUM(W34:W36) -> 0 | ... AA33: =SUM(AA34:AA36) -> 0 | AB33: =SUMIFS(BD.PD[Pago 1],BD.PD[Per.P1],AB$1,BD.PD[Pos],Tabla3[[#This Row],[Part.]])+SUMIFS(BD.PD[Pago 2],BD.PD[Per.P2],AB$1,BD.PD[Pos],Tabla3[[#This Row],[Part.]])+SUMIFS(BD.PD[Pago 3],BD.PD[Per.P3],AB$1,BD.PD[Pos],Tabla3[[#This Row],[Part.]])+SUMIFS(BD.PD[Pago 4],BD.PD[Per.P4],AB$1,BD.PD[Pos],Tabla3[[#This Row],[Part.]])+SUMIFS(BD.PD[Pago 5],BD.PD[Per.P5],AB$1,BD.PD[Pos],Tabla3[[#This Row],[Part.]]) -> 0 | AC33: =SUMIFS(BD.PD[Pago 1],BD.PD[Per.P1],AC$1,BD.PD[Pos],Tabla3[[#This Row],[Part.]])+SUMIFS(BD.PD[Pago 2],BD.PD[Per.P2],AC$1,BD.PD[Pos],Tabla3[[#This Row],[Part.]])+SUMIFS(BD.PD[Pago 3],BD.PD[Per.P3],AC$1,BD.PD[Pos],Tabla3[[#This Row],[Part.]])+SUMIFS(BD.PD[Pago 4],BD.PD[Per.P4],AC$1,BD.PD[Pos],Tabla3[[#This Row],[Part.]])+SUMIFS(BD.PD[Pago 5],BD.PD[Per.P5],AC$1,BD.PD[Pos],Tabla3[[#This Row],[Part.]]) -> 0 | AD33: =SUMIFS(BD.PD[Pago 1],BD.PD[Per.P1],AD$1,BD.PD[Pos],Tabla3[[#This Row],[Part.]])+SUMIFS(BD.PD[Pago 2],BD.PD[Per.P2],AD$1,BD.PD[Pos],Tabla3[[#This Row],[Part.]])+SUMIFS(BD.PD[Pago 3],BD.PD[Per.P3],AD$1,BD.PD[Pos],Tabla3[[#This Row],[Part.]])+SUMIFS(BD.PD[Pago 4],BD.PD[Per.P4],AD$1,BD.PD[Pos],Tabla3[[#This Row],[Part.]])+SUMIFS(BD.PD[Pago 5],BD.PD[Per.P5],AD$1,BD.PD[Pos],Tabla3[[#This Row],[Part.]]) -> 0 | AE33: =SUMIFS(BD.PD[Pago 1],BD.PD[Per.P1],AE$1,BD.PD[Pos],Tabla3[[#This Row],[Part.]])+SUMIFS(BD.PD[Pago 2],BD.PD[Per.P2],AE$1,BD.PD[Pos],Tabla3[[#This Row],[Part.]])+SUMIFS(BD.PD[Pago 3],BD.PD[Per.P3],AE$1,BD.PD[Pos],Tabla3[[#This Row],[Part.]])+SUMIFS(BD.PD[Pago 4],BD.PD[Per.P4],AE$1,BD.PD[Pos],Tabla3[[#This Row],[Part.]])+SUMIFS(BD.PD[Pago 5],BD.PD[Per.P5],AE$1,BD.PD[Pos],Tabla3[[#This Row],[Part.]]) -> 0 | AF33: =SUMIFS(BD.PD[Pago 1],BD.PD[Per.P1],AF$1,BD.PD[Pos],Tabla3[[#This Row],[Part.]])+SUMIFS(BD.PD[Pago 2],BD.PD[Per.P2],AF$1,BD.PD[Pos],Tabla3[[#This Row],[Part.]])+SUMIFS(BD.PD[Pago 3],BD.PD[Per.P3],AF$1,BD.PD[Pos],Tabla3[[#This Row],[Part.]])+SUMIFS(BD.PD[Pago 4],BD.PD[Per.P4],AF$1,BD.PD[Pos],Tabla3[[#This Row],[Part.]])+SUMIFS(BD.PD[Pago 5],BD.PD[Per.P5],AF$1,BD.PD[Pos],Tabla3[[#This Row],[Part.]]) -> 0 | AG33: =SUMIFS(BD.PD[Pago 1],BD.PD[Per.P1],AG$1,BD.PD[Pos],Tabla3[[#This Row],[Part.]])+SUMIFS(BD.PD[Pago 2],BD.PD[Per.P2],AG$1,BD.PD[Pos],Tabla3[[#This Row],[Part.]])+SUMIFS(BD.PD[Pago 3],BD.PD[Per.P3],AG$1,BD.PD[Pos],Tabla3[[#This Row],[Part.]])+SUMIFS(BD.PD[Pago 4],BD.PD[Per.P4],AG$1,BD.PD[Pos],Tabla3[[#This Row],[Part.]])+SUMIFS(BD.PD[Pago 5],BD.PD[Per.P5],AG$1,BD.PD[Pos],Tabla3[[#This Row],[Part.]]) -> 0 | AH33: =SUM(Tabla3[[#This Row],[P1]:[P24]]) -> 7596030.8
A34: 4.01 | B34: =VLOOKUP(Tabla3[[#This Row],[Part.]],PPto[],3,FALSE) -> 4.01 Suministro e instalación de Equipos | C34: =SUMIF(BD.PD[Pos],Tabla3[[#This Row],[Part.]],BD.PD[Ppto. Orden Interna '[DOP']]) -> 6416313.8 | D34: =SUMIFS(BD.PD[Pago 1],BD.PD[Per.P1],D$1,BD.PD[Pos],Tabla3[[#This Row],[Part.]])+SUMIFS(BD.PD[Pago 2],BD.PD[Per.P2],D$1,BD.PD[Pos],Tabla3[[#This Row],[Part.]])+SUMIFS(BD.PD[Pago 3],BD.PD[Per.P3],D$1,BD.PD[Pos],Tabla3[[#This Row],[Part.]])+SUMIFS(BD.PD[Pago 4],BD.PD[Per.P4],D$1,BD.PD[Pos],Tabla3[[#This Row],[Part.]])+SUMIFS(BD.PD[Pago 5],BD.PD[Per.P5],D$1,BD.PD[Pos],Tabla3[[#This Row],[Part.]]) -> 0 | E34: =SUMIFS(BD.PD[Pago 1],BD.PD[Per.P1],E$1,BD.PD[Pos],Tabla3[[#This Row],[Part.]])+SUMIFS(BD.PD[Pago 2],BD.PD[Per.P2],E$1,BD.PD[Pos],Tabla3[[#This Row],[Part.]])+SUMIFS(BD.PD[Pago 3],BD.PD[Per.P3],E$1,BD.PD[Pos],Tabla3[[#This Row],[Part.]])+SUMIFS(BD.PD[Pago 4],BD.PD[Per.P4],E$1,BD.PD[Pos],Tabla3[[#This Row],[Part.]])+SUMIFS(BD.PD[Pago 5],BD.PD[Per.P5],E$1,BD.PD[Pos],Tabla3[[#This Row],[Part.]]) -> 0 | F34: =SUMIFS(BD.PD[Pago 1],BD.PD[Per.P1],F$1,BD.PD[Pos],Tabla3[[#This Row],[Part.]])+SUMIFS(BD.PD[Pago 2],BD.PD[Per.P2],F$1,BD.PD[Pos],Tabla3[[#This Row],[Part.]])+SUMIFS(BD.PD[Pago 3],BD.PD[Per.P3],F$1,BD.PD[Pos],Tabla3[[#This Row],[Part.]])+SUMIFS(BD.PD[Pago 4],BD.PD[Per.P4],F$1,BD.PD[Pos],Tabla3[[#This Row],[Part.]])+SUMIFS(BD.PD[Pago 5],BD.PD[Per.P5],F$1,BD.PD[Pos],Tabla3[[#This Row],[Part.]]) -> 3208156.9 | G34: =SUMIFS(BD.PD[Pago 1],BD.PD[Per.P1],G$1,BD.PD[Pos],Tabla3[[#This Row],[Part.]])+SUMIFS(BD.PD[Pago 2],BD.PD[Per.P2],G$1,BD.PD[Pos],Tabla3[[#This Row],[Part.]])+SUMIFS(BD.PD[Pago 3],BD.PD[Per.P3],G$1,BD.PD[Pos],Tabla3[[#This Row],[Part.]])+SUMIFS(BD.PD[Pago 4],BD.PD[Per.P4],G$1,BD.PD[Pos],Tabla3[[#This Row],[Part.]])+SUMIFS(BD.PD[Pago 5],BD.PD[Per.P5],G$1,BD.PD[Pos],Tabla3[[#This Row],[Part.]]) -> 0 | H34: =SUMIFS(BD.PD[Pago 1],BD.PD[Per.P1],H$1,BD.PD[Pos],Tabla3[[#This Row],[Part.]])+SUMIFS(BD.PD[Pago 2],BD.PD[Per.P2],H$1,BD.PD[Pos],Tabla3[[#This Row],[Part.]])+SUMIFS(BD.PD[Pago 3],BD.PD[Per.P3],H$1,BD.PD[Pos],Tabla3[[#This Row],[Part.]])+SUMIFS(BD.PD[Pago 4],BD.PD[Per.P4],H$1,BD.PD[Pos],Tabla3[[#This Row],[Part.]])+SUMIFS(BD.PD[Pago 5],BD.PD[Per.P5],H$1,BD.PD[Pos],Tabla3[[#This Row],[Part.]]) -> 0 | I34: =SUMIFS(BD.PD[Pago 1],BD.PD[Per.P1],I$1,BD.PD[Pos],Tabla3[[#This Row],[Part.]])+SUMIFS(BD.PD[Pago 2],BD.PD[Per.P2],I$1,BD.PD[Pos],Tabla3[[#This Row],[Part.]])+SUMIFS(BD.PD[Pago 3],BD.PD[Per.P3],I$1,BD.PD[Pos],Tabla3[[#This Row],[Part.]])+SUMIFS(BD.PD[Pago 4],BD.PD[Per.P4],I$1,BD.PD[Pos],Tabla3[[#This Row],[Part.]])+SUMIFS(BD.PD[Pago 5],BD.PD[Per.P5],I$1,BD.PD[Pos],Tabla3[[#This Row],[Part.]]) -> 0 | J34: =SUMIFS(BD.PD[Pago 1],BD.PD[Per.P1],J$1,BD.PD[Pos],Tabla3[[#This Row],[Part.]])+SUMIFS(BD.PD[Pago 2],BD.PD[Per.P2],J$1,BD.PD[Pos],Tabla3[[#This Row],[Part.]])+SUMIFS(BD.PD[Pago 3],BD.PD[Per.P3],J$1,BD.PD[Pos],Tabla3[[#This Row],[Part.]])+SUMIFS(BD.PD[Pago 4],BD.PD[Per.P4],J$1,BD.PD[Pos],Tabla3[[#This Row],[Part.]])+SUMIFS(BD.PD[Pago 5],BD.PD[Per.P5],J$1,BD.PD[Pos],Tabla3[[#This Row],[Part.]]) -> 0 | K34: =SUMIFS(BD.PD[Pago 1],BD.PD[Per.P1],K$1,BD.PD[Pos],Tabla3[[#This Row],[Part.]])+SUMIFS(BD.PD[Pago 2],BD.PD[Per.P2],K$1,BD.PD[Pos],Tabla3[[#This Row],[Part.]])+SUMIFS(BD.PD[Pago 3],BD.PD[Per.P3],K$1,BD.PD[Pos],Tabla3[[#This Row],[Part.]])+SUMIFS(BD.PD[Pago 4],BD.PD[Per.P4],K$1,BD.PD[Pos],Tabla3[[#This Row],[Part.]])+SUMIFS(BD.PD[Pago 5],BD.PD[Per.P5],K$1,BD.PD[Pos],Tabla3[[#This Row],[Part.]]) -> 0 | ... AG34: =SUMIFS(BD.PD[Pago 1],BD.PD[Per.P1],AG$1,BD.PD[Pos],Tabla3[[#This Row],[Part.]])+SUMIFS(BD.PD[Pago 2],BD.PD[Per.P2],AG$1,BD.PD[Pos],Tabla3[[#This Row],[Part.]])+SUMIFS(BD.PD[Pago 3],BD.PD[Per.P3],AG$1,BD.PD[Pos],Tabla3[[#This Row],[Part.]])+SUMIFS(BD.PD[Pago 4],BD.PD[Per.P4],AG$1,BD.PD[Pos],Tabla3[[#This Row],[Part.]])+SUMIFS(BD.PD[Pago 5],BD.PD[Per.P5],AG$1,BD.PD[Pos],Tabla3[[#This Row],[Part.]]) -> 0 | AH34: =SUM(Tabla3[[#This Row],[P1]:[P24]]) -> 6416313.8
A35: 4.02 | B35: =VLOOKUP(Tabla3[[#This Row],[Part.]],PPto[],3,FALSE) -> 4.02 Supervisión Mecánica | C35: =SUMIF(BD.PD[Pos],Tabla3[[#This Row],[Part.]],BD.PD[Ppto. Orden Interna '[DOP']]) -> 0 | D35: =SUMIFS(BD.PD[Pago 1],BD.PD[Per.P1],D$1,BD.PD[Pos],Tabla3[[#This Row],[Part.]])+SUMIFS(BD.PD[Pago 2],BD.PD[Per.P2],D$1,BD.PD[Pos],Tabla3[[#This Row],[Part.]])+SUMIFS(BD.PD[Pago 3],BD.PD[Per.P3],D$1,BD.PD[Pos],Tabla3[[#This Row],[Part.]])+SUMIFS(BD.PD[Pago 4],BD.PD[Per.P4],D$1,BD.PD[Pos],Tabla3[[#This Row],[Part.]])+SUMIFS(BD.PD[Pago 5],BD.PD[Per.P5],D$1,BD.PD[Pos],Tabla3[[#This Row],[Part.]]) -> 0 | E35: =SUMIFS(BD.PD[Pago 1],BD.PD[Per.P1],E$1,BD.PD[Pos],Tabla3[[#This Row],[Part.]])+SUMIFS(BD.PD[Pago 2],BD.PD[Per.P2],E$1,BD.PD[Pos],Tabla3[[#This Row],[Part.]])+SUMIFS(BD.PD[Pago 3],BD.PD[Per.P3],E$1,BD.PD[Pos],Tabla3[[#This Row],[Part.]])+SUMIFS(BD.PD[Pago 4],BD.PD[Per.P4],E$1,BD.PD[Pos],Tabla3[[#This Row],[Part.]])+SUMIFS(BD.PD[Pago 5],BD.PD[Per.P5],E$1,BD.PD[Pos],Tabla3[[#This Row],[Part.]]) -> 0 | F35: =SUMIFS(BD.PD[Pago 1],BD.PD[Per.P1],F$1,BD.PD[Pos],Tabla3[[#This Row],[Part.]])+SUMIFS(BD.PD[Pago 2],BD.PD[Per.P2],F$1,BD.PD[Pos],Tabla3[[#This Row],[Part.]])+SUMIFS(BD.PD[Pago 3],BD.PD[Per.P3],F$1,BD.PD[Pos],Tabla3[[#This Row],[Part.]])+SUMIFS(BD.PD[Pago 4],BD.PD[Per.P4],F$1,BD.PD[Pos],Tabla3[[#This Row],[Part.]])+SUMIFS(BD.PD[Pago 5],BD.PD[Per.P5],F$1,BD.PD[Pos],Tabla3[[#This Row],[Part.]]) -> 0 | G35: =SUMIFS(BD.PD[Pago 1],BD.PD[Per.P1],G$1,BD.PD[Pos],Tabla3[[#This Row],[Part.]])+SUMIFS(BD.PD[Pago 2],BD.PD[Per.P2],G$1,BD.PD[Pos],Tabla3[[#This Row],[Part.]])+SUMIFS(BD.PD[Pago 3],BD.PD[Per.P3],G$1,BD.PD[Pos],Tabla3[[#This Row],[Part.]])+SUMIFS(BD.PD[Pago 4],BD.PD[Per.P4],G$1,BD.PD[Pos],Tabla3[[#This Row],[Part.]])+SUMIFS(BD.PD[Pago 5],BD.PD[Per.P5],G$1,BD.PD[Pos],Tabla3[[#This Row],[Part.]]) -> 0 | H35: =SUMIFS(BD.PD[Pago 1],BD.PD[Per.P1],H$1,BD.PD[Pos],Tabla3[[#This Row],[Part.]])+SUMIFS(BD.PD[Pago 2],BD.PD[Per.P2],H$1,BD.PD[Pos],Tabla3[[#This Row],[Part.]])+SUMIFS(BD.PD[Pago 3],BD.PD[Per.P3],H$1,BD.PD[Pos],Tabla3[[#This Row],[Part.]])+SUMIFS(BD.PD[Pago 4],BD.PD[Per.P4],H$1,BD.PD[Pos],Tabla3[[#This Row],[Part.]])+SUMIFS(BD.PD[Pago 5],BD.PD[Per.P5],H$1,BD.PD[Pos],Tabla3[[#This Row],[Part.]]) -> 0 | I35: =SUMIFS(BD.PD[Pago 1],BD.PD[Per.P1],I$1,BD.PD[Pos],Tabla3[[#This Row],[Part.]])+SUMIFS(BD.PD[Pago 2],BD.PD[Per.P2],I$1,BD.PD[Pos],Tabla3[[#This Row],[Part.]])+SUMIFS(BD.PD[Pago 3],BD.PD[Per.P3],I$1,BD.PD[Pos],Tabla3[[#This Row],[Part.]])+SUMIFS(BD.PD[Pago 4],BD.PD[Per.P4],I$1,BD.PD[Pos],Tabla3[[#This Row],[Part.]])+SUMIFS(BD.PD[Pago 5],BD.PD[Per.P5],I$1,BD.PD[Pos],Tabla3[[#This Row],[Part.]]) -> 0 | J35: =SUMIFS(BD.PD[Pago 1],BD.PD[Per.P1],J$1,BD.PD[Pos],Tabla3[[#This Row],[Part.]])+SUMIFS(BD.PD[Pago 2],BD.PD[Per.P2],J$1,BD.PD[Pos],Tabla3[[#This Row],[Part.]])+SUMIFS(BD.PD[Pago 3],BD.PD[Per.P3],J$1,BD.PD[Pos],Tabla3[[#This Row],[Part.]])+SUMIFS(BD.PD[Pago 4],BD.PD[Per.P4],J$1,BD.PD[Pos],Tabla3[[#This Row],[Part.]])+SUMIFS(BD.PD[Pago 5],BD.PD[Per.P5],J$1,BD.PD[Pos],Tabla3[[#This Row],[Part.]]) -> 0 | K35: =SUMIFS(BD.PD[Pago 1],BD.PD[Per.P1],K$1,BD.PD[Pos],Tabla3[[#This Row],[Part.]])+SUMIFS(BD.PD[Pago 2],BD.PD[Per.P2],K$1,BD.PD[Pos],Tabla3[[#This Row],[Part.]])+SUMIFS(BD.PD[Pago 3],BD.PD[Per.P3],K$1,BD.PD[Pos],Tabla3[[#This Row],[Part.]])+SUMIFS(BD.PD[Pago 4],BD.PD[Per.P4],K$1,BD.PD[Pos],Tabla3[[#This Row],[Part.]])+SUMIFS(BD.PD[Pago 5],BD.PD[Per.P5],K$1,BD.PD[Pos],Tabla3[[#This Row],[Part.]]) -> 0 | ... AG35: =SUMIFS(BD.PD[Pago 1],BD.PD[Per.P1],AG$1,BD.PD[Pos],Tabla3[[#This Row],[Part.]])+SUMIFS(BD.PD[Pago 2],BD.PD[Per.P2],AG$1,BD.PD[Pos],Tabla3[[#This Row],[Part.]])+SUMIFS(BD.PD[Pago 3],BD.PD[Per.P3],AG$1,BD.PD[Pos],Tabla3[[#This Row],[Part.]])+SUMIFS(BD.PD[Pago 4],BD.PD[Per.P4],AG$1,BD.PD[Pos],Tabla3[[#This Row],[Part.]])+SUMIFS(BD.PD[Pago 5],BD.PD[Per.P5],AG$1,BD.PD[Pos],Tabla3[[#This Row],[Part.]]) -> 0 | AH35: =SUM(Tabla3[[#This Row],[P1]:[P24]]) -> 0
A36: 4.03 | B36: =VLOOKUP(Tabla3[[#This Row],[Part.]],PPto[],3,FALSE) -> 4.03 Sistema de Extracción cocina | C36: =SUMIF(BD.PD[Pos],Tabla3[[#This Row],[Part.]],BD.PD[Ppto. Orden Interna '[DOP']]) -> 1179717 | D36: =SUMIFS(BD.PD[Pago 1],BD.PD[Per.P1],D$1,BD.PD[Pos],Tabla3[[#This Row],[Part.]])+SUMIFS(BD.PD[Pago 2],BD.PD[Per.P2],D$1,BD.PD[Pos],Tabla3[[#This Row],[Part.]])+SUMIFS(BD.PD[Pago 3],BD.PD[Per.P3],D$1,BD.PD[Pos],Tabla3[[#This Row],[Part.]])+SUMIFS(BD.PD[Pago 4],BD.PD[Per.P4],D$1,BD.PD[Pos],Tabla3[[#This Row],[Part.]])+SUMIFS(BD.PD[Pago 5],BD.PD[Per.P5],D$1,BD.PD[Pos],Tabla3[[#This Row],[Part.]]) -> 0 | E36: =SUMIFS(BD.PD[Pago 1],BD.PD[Per.P1],E$1,BD.PD[Pos],Tabla3[[#This Row],[Part.]])+SUMIFS(BD.PD[Pago 2],BD.PD[Per.P2],E$1,BD.PD[Pos],Tabla3[[#This Row],[Part.]])+SUMIFS(BD.PD[Pago 3],BD.PD[Per.P3],E$1,BD.PD[Pos],Tabla3[[#This Row],[Part.]])+SUMIFS(BD.PD[Pago 4],BD.PD[Per.P4],E$1,BD.PD[Pos],Tabla3[[#This Row],[Part.]])+SUMIFS(BD.PD[Pago 5],BD.PD[Per.P5],E$1,BD.PD[Pos],Tabla3[[#This Row],[Part.]]) -> 0 | F36: =SUMIFS(BD.PD[Pago 1],BD.PD[Per.P1],F$1,BD.PD[Pos],Tabla3[[#This Row],[Part.]])+SUMIFS(BD.PD[Pago 2],BD.PD[Per.P2],F$1,BD.PD[Pos],Tabla3[[#This Row],[Part.]])+SUMIFS(BD.PD[Pago 3],BD.PD[Per.P3],F$1,BD.PD[Pos],Tabla3[[#This Row],[Part.]])+SUMIFS(BD.PD[Pago 4],BD.PD[Per.P4],F$1,BD.PD[Pos],Tabla3[[#This Row],[Part.]])+SUMIFS(BD.PD[Pago 5],BD.PD[Per.P5],F$1,BD.PD[Pos],Tabla3[[#This Row],[Part.]]) -> 0 | G36: =SUMIFS(BD.PD[Pago 1],BD.PD[Per.P1],G$1,BD.PD[Pos],Tabla3[[#This Row],[Part.]])+SUMIFS(BD.PD[Pago 2],BD.PD[Per.P2],G$1,BD.PD[Pos],Tabla3[[#This Row],[Part.]])+SUMIFS(BD.PD[Pago 3],BD.PD[Per.P3],G$1,BD.PD[Pos],Tabla3[[#This Row],[Part.]])+SUMIFS(BD.PD[Pago 4],BD.PD[Per.P4],G$1,BD.PD[Pos],Tabla3[[#This Row],[Part.]])+SUMIFS(BD.PD[Pago 5],BD.PD[Per.P5],G$1,BD.PD[Pos],Tabla3[[#This Row],[Part.]]) -> 0 | H36: =SUMIFS(BD.PD[Pago 1],BD.PD[Per.P1],H$1,BD.PD[Pos],Tabla3[[#This Row],[Part.]])+SUMIFS(BD.PD[Pago 2],BD.PD[Per.P2],H$1,BD.PD[Pos],Tabla3[[#This Row],[Part.]])+SUMIFS(BD.PD[Pago 3],BD.PD[Per.P3],H$1,BD.PD[Pos],Tabla3[[#This Row],[Part.]])+SUMIFS(BD.PD[Pago 4],BD.PD[Per.P4],H$1,BD.PD[Pos],Tabla3[[#This Row],[Part.]])+SUMIFS(BD.PD[Pago 5],BD.PD[Per.P5],H$1,BD.PD[Pos],Tabla3[[#This Row],[Part.]]) -> 0 | I36: =SUMIFS(BD.PD[Pago 1],BD.PD[Per.P1],I$1,BD.PD[Pos],Tabla3[[#This Row],[Part.]])+SUMIFS(BD.PD[Pago 2],BD.PD[Per.P2],I$1,BD.PD[Pos],Tabla3[[#This Row],[Part.]])+SUMIFS(BD.PD[Pago 3],BD.PD[Per.P3],I$1,BD.PD[Pos],Tabla3[[#This Row],[Part.]])+SUMIFS(BD.PD[Pago 4],BD.PD[Per.P4],I$1,BD.PD[Pos],Tabla3[[#This Row],[Part.]])+SUMIFS(BD.PD[Pago 5],BD.PD[Per.P5],I$1,BD.PD[Pos],Tabla3[[#This Row],[Part.]]) -> 0 | J36: =SUMIFS(BD.PD[Pago 1],BD.PD[Per.P1],J$1,BD.PD[Pos],Tabla3[[#This Row],[Part.]])+SUMIFS(BD.PD[Pago 2],BD.PD[Per.P2],J$1,BD.PD[Pos],Tabla3[[#This Row],[Part.]])+SUMIFS(BD.PD[Pago 3],BD.PD[Per.P3],J$1,BD.PD[Pos],Tabla3[[#This Row],[Part.]])+SUMIFS(BD.PD[Pago 4],BD.PD[Per.P4],J$1,BD.PD[Pos],Tabla3[[#This Row],[Part.]])+SUMIFS(BD.PD[Pago 5],BD.PD[Per.P5],J$1,BD.PD[Pos],Tabla3[[#This Row],[Part.]]) -> 0 | K36: =SUMIFS(BD.PD[Pago 1],BD.PD[Per.P1],K$1,BD.PD[Pos],Tabla3[[#This Row],[Part.]])+SUMIFS(BD.PD[Pago 2],BD.PD[Per.P2],K$1,BD.PD[Pos],Tabla3[[#This Row],[Part.]])+SUMIFS(BD.PD[Pago 3],BD.PD[Per.P3],K$1,BD.PD[Pos],Tabla3[[#This Row],[Part.]])+SUMIFS(BD.PD[Pago 4],BD.PD[Per.P4],K$1,BD.PD[Pos],Tabla3[[#This Row],[Part.]])+SUMIFS(BD.PD[Pago 5],BD.PD[Per.P5],K$1,BD.PD[Pos],Tabla3[[#This Row],[Part.]]) -> 0 | ... AG36: =SUMIFS(BD.PD[Pago 1],BD.PD[Per.P1],AG$1,BD.PD[Pos],Tabla3[[#This Row],[Part.]])+SUMIFS(BD.PD[Pago 2],BD.PD[Per.P2],AG$1,BD.PD[Pos],Tabla3[[#This Row],[Part.]])+SUMIFS(BD.PD[Pago 3],BD.PD[Per.P3],AG$1,BD.PD[Pos],Tabla3[[#This Row],[Part.]])+SUMIFS(BD.PD[Pago 4],BD.PD[Per.P4],AG$1,BD.PD[Pos],Tabla3[[#This Row],[Part.]])+SUMIFS(BD.PD[Pago 5],BD.PD[Per.P5],AG$1,BD.PD[Pos],Tabla3[[#This Row],[Part.]]) -> 0 | AH36: =SUM(Tabla3[[#This Row],[P1]:[P24]]) -> 1179717
