Workbook
Name \4: #REF!
Name \6: #REF!
Name \A: #REF!
Name \E: #REF!
Name \I: #REF!
Name \M: #REF!
Name \N: #REF!
Name \O: #REF!
Name \U: #REF!
Name __DAT1: #REF!
Name __DAT10: #REF!
Name __DAT11: #REF!
Name __DAT12: #REF!
Name __DAT13: #REF!
Name __DAT14: #REF!
Name __DAT2: #REF!
Name __DAT3: #REF!
Name __DAT4: #REF!
Name __DAT5: #REF!
Name __DAT6: #REF!
Name __DAT7: #REF!
Name __DAT8: #REF!
Name __DAT9: #REF!
Name _DAT1: #REF!
Name _DAT10: #REF!
Name _DAT11: #REF!
Name _DAT12: #REF!
Name _DAT13: #REF!
Name _DAT14: #REF!
Name _DAT15: #REF!
Name _DAT16: #REF!
Name _DAT17: #REF!
Name _DAT18: #REF!
Name _DAT19: #REF!
Name _DAT2: #REF!
Name _DAT20: #REF!
Name _DAT21: #REF!
Name _DAT3: #REF!
Name _DAT4: #REF!
Name _DAT5: #REF!
Name _DAT6: #REF!
Name _DAT7: #REF!
Name _DAT8: #REF!
Name _DAT9: #REF!
Name _EV: [1]LoV!$A$147:$B$217
Name _EV: #REF!
Name _GC: [1]LoV!$U$2:$V$169
Name _GC: #REF!
Name _IIM: [1]LoV!$A$116:$B$133
Name _IIM: #REF!
Name _M: [1]LoV!$AC$2:$AD$11093
Name _M: #REF!
Name _PE: [1]LoV!$A$136:$B$144
Name _PE: #REF!
Name _T: [1]LoV!$A$220:$B$265
Name _T: #REF!
Name _TC: [1]LoV!$A$268:$B$271
Name _TC: #REF!
Name ACERO: #REF!
Name ACERO: #REF!

Sheet Plan OI
C1: Presupuesto Detallado - Propuesta para Sirena Compacta Las Terrenas
C2: Area de Compras de Activos
C3: 19 de agosto 2026
C4: Fecha Version: | D4: Alto Nivel | H4: Plan Detallado DOP | K4: Plan Detallado USD
D5: Total Presupuesto [DOP] | F5: Ppto OI [DOP] | G5: Ppto Capex [DOP] | H5: Total Iniciativa [DOP] | I5: Ppto OI [USD] | J5: Ppto Capex [USD] | K5: Total Iniciativa [USD]
C6: TOTAL GENERAL ESTIMADO | D6: 2.3949544e+08 | F6: =SUM(F9:F11) -> 2.295797e+08 | G6: =SUM(G9:G11) -> 0 | H6: =G6+F6 -> 2.295797e+08 | I6: =SUM(I9:I11) -> 3763601.6 | J6: =SUM(J9:J11) -> 0 | K6: =J6+I6 -> 3763601.6
C8: Resumen de Partidas
C9: EQUIPAMIENTO | D9: =SUMIF(PPto[Gran Part.],$C9,PPto[Total '[USD']]) -> 2.0460328e+08 | F9: =SUMIF(PPto[Gran Part.],$C9,PPto[Ppto. OI '[DOP']2]) -> 2.2249835e+08 | G9: =SUMIF(PPto[Gran Part.],$C9,PPto[Ppto. Capex '[DOP']]) -> 0 | H9: =G9+F9 -> 2.2249835e+08 | I9: =SUMIF(PPto[Gran Part.],C9,PPto[Ppto. OI '[USD']]) -> 3647514 | J9: =SUMIF(PPto[Gran Part.],C9,PPto[Ppto. Capex '[USD']]) -> 0 | K9: =J9+I9 -> 3647514
C10: EDIFICACIÓN | D10: =SUMIF(PPto[Gran Part.],$C10,PPto[Total '[USD']]) -> 7081344.5 | F10: =SUMIF(PPto[Gran Part.],$C10,PPto[Ppto. OI '[DOP']2]) -> 7081344.5 | G10: =SUMIF(PPto[Gran Part.],$C10,PPto[Ppto. Capex '[DOP']]) -> 0 | H10: =G10+F10 -> 7081344.5 | I10: =SUMIF(PPto[Gran Part.],C10,PPto[Ppto. OI '[USD']]) -> 116087.61 | J10: =SUMIF(PPto[Gran Part.],C10,PPto[Ppto. Capex '[USD']]) -> 0 | K10: =J10+I10 -> 116087.61
C11: TERRENO | D11: 0 | F11: =SUMIF(PPto[Gran Part.],$C11,PPto[Ppto. OI '[DOP']2]) -> 0 | G11: =SUMIF(PPto[Gran Part.],$C11,PPto[Ppto. Capex '[DOP']]) -> 0 | H11: =G11+F11 -> 0 | I11: =SUMIF(PPto[Gran Part.],C11,PPto[Ppto. OI '[USD']]) -> 0 | J11: =SUMIF(PPto[Gran Part.],C11,PPto[Ppto. Capex '[USD']]) -> 0 | K11: =J11+I11 -> 0
C12: Gasto | D12: 0 | F12: =SUMIF(PPto[Gran Part.],$C12,PPto[Ppto. OI '[DOP']2]) -> 0 | G12: =SUMIF(PPto[Gran Part.],$C12,PPto[Ppto. Capex '[DOP']]) -> 0 | H12: =G12+F12 -> 0 | I12: =SUMIF(PPto[Gran Part.],C12,PPto[Ppto. OI '[USD']]) -> 0 | J12: =SUMIF(PPto[Gran Part.],C12,PPto[Ppto. Capex '[USD']]) -> 0 | K12: =J12+I12 -> 0
C14: Área de la Localidad
C15: M² Construcción
C16: M² Sala de Ventas
C17: M² Terreno
F18: OI | G18: Capex | I18: OI | J18: Capex
A19: Part. | B19: Gran Part. | C19: Edificación, Instalaciones y Equipamientos | D19: Total [USD] | E19: Columna2 | F19: Ppto. OI [DOP]2 | G19: Ppto. Capex [DOP] | H19: Total [DOP] | I19: Ppto. OI [USD] | J19: Ppto. Capex [USD] | K19: Total [USD]2
A20: 1 | C20: 1.00 Estudios Preliminares | D20: =SUM(D21:D29) -> 0 | F20: =SUM(F21:F29) -> 0 | G20: =SUM(G21:G29) -> 0 | H20: =PPto[[#This Row],[Ppto. Capex '[DOP']]]+PPto[[#This Row],[Ppto. OI '[DOP']2]] -> 0 | I20: =SUM(I21:I29) -> 0 | J20: =SUM(J21:J29) -> 0 | K20: =PPto[[#This Row],[Ppto. Capex '[USD']]]+PPto[[#This Row],[Ppto. OI '[USD']]] -> 0
A21: 1.01 | B21: Edificación | C21: 1.01 Diseño arquitectónico | D21: 0 | F21: =SUMIFS(BD.PD[Ppto. Orden Interna '[DOP']],BD.PD[Pos],PPto[[#This Row],[Part.]],BD.PD[Tipo Ppto],F$18) -> 0 | G21: =SUMIFS(BD.PD[Ppto. Orden Interna '[DOP']],BD.PD[Pos],PPto[[#This Row],[Part.]],BD.PD[Tipo Ppto],G$18) -> 0 | H21: =PPto[[#This Row],[Ppto. Capex '[DOP']]]+PPto[[#This Row],[Ppto. OI '[DOP']2]] -> 0 | I21: =SUMIFS(BD.PD[Ppto. Orden Interna '[USD']],BD.PD[Pos],PPto[[#This Row],[Part.]],BD.PD[Tipo Ppto],I$18) -> 0 | J21: =SUMIFS(BD.PD[Ppto. Orden Interna '[USD']],BD.PD[Pos],PPto[[#This Row],[Part.]],BD.PD[Tipo Ppto],J$18) -> 0 | K21: =PPto[[#This Row],[Ppto. Capex '[USD']]]+PPto[[#This Row],[Ppto. OI '[USD']]] -> 0
A22: 1.02 | B22: Edificación | C22: 1.02 Diseño estructural | D22: 0 | F22: =SUMIFS(BD.PD[Ppto. Orden Interna '[DOP']],BD.PD[Pos],PPto[[#This Row],[Part.]],BD.PD[Tipo Ppto],F$18) -> 0 | G22: =SUMIFS(BD.PD[Ppto. Orden Interna '[DOP']],BD.PD[Pos],PPto[[#This Row],[Part.]],BD.PD[Tipo Ppto],G$18) -> 0 | H22: =PPto[[#This Row],[Ppto. Capex '[DOP']]]+PPto[[#This Row],[Ppto. OI '[DOP']2]] -> 0 | I22: =SUMIFS(BD.PD[Ppto. Orden Interna '[USD']],BD.PD[Pos],PPto[[#This Row],[Part.]],BD.PD[Tipo Ppto],I$18) -> 0 | J22: =SUMIFS(BD.PD[Ppto. Orden Interna '[USD']],BD.PD[Pos],PPto[[#This Row],[Part.]],BD.PD[Tipo Ppto],J$18) -> 0 | K22: =PPto[[#This Row],[Ppto. Capex '[USD']]]+PPto[[#This Row],[Ppto. OI '[USD']]] -> 0
A23: 1.03 | B23: Edificación | C23: 1.03 Diseño electromecánico | D23: 0 | F23: =SUMIFS(BD.PD[Ppto. Orden Interna '[DOP']],BD.PD[Pos],PPto[[#This Row],[Part.]],BD.PD[Tipo Ppto],F$18) -> 0 | G23: =SUMIFS(BD.PD[Ppto. Orden Interna '[DOP']],BD.PD[Pos],PPto[[#This Row],[Part.]],BD.PD[Tipo Ppto],G$18) -> 0 | H23: =PPto[[#This Row],[Ppto. Capex '[DOP']]]+PPto[[#This Row],[Ppto. OI '[DOP']2]] -> 0 | I23: =SUMIFS(BD.PD[Ppto. Orden Interna '[USD']],BD.PD[Pos],PPto[[#This Row],[Part.]],BD.PD[Tipo Ppto],I$18) -> 0 | J23: =SUMIFS(BD.PD[Ppto. Orden Interna '[USD']],BD.PD[Pos],PPto[[#This Row],[Part.]],BD.PD[Tipo Ppto],J$18) -> 0 | K23: =PPto[[#This Row],[Ppto. Capex '[USD']]]+PPto[[#This Row],[Ppto. OI '[USD']]] -> 0
A24: 1.04 | B24: Edificación | C24: 1.04 Diseño sanitario | D24: 0 | F24: =SUMIFS(BD.PD[Ppto. Orden Interna '[DOP']],BD.PD[Pos],PPto[[#This Row],[Part.]],BD.PD[Tipo Ppto],F$18) -> 0 | G24: =SUMIFS(BD.PD[Ppto. Orden Interna '[DOP']],BD.PD[Pos],PPto[[#This Row],[Part.]],BD.PD[Tipo Ppto],G$18) -> 0 | H24: =PPto[[#This Row],[Ppto. Capex '[DOP']]]+PPto[[#This Row],[Ppto. OI '[DOP']2]] -> 0 | I24: =SUMIFS(BD.PD[Ppto. Orden Interna '[USD']],BD.PD[Pos],PPto[[#This Row],[Part.]],BD.PD[Tipo Ppto],I$18) -> 0 | J24: =SUMIFS(BD.PD[Ppto. Orden Interna '[USD']],BD.PD[Pos],PPto[[#This Row],[Part.]],BD.PD[Tipo Ppto],J$18) -> 0 | K24: =PPto[[#This Row],[Ppto. Capex '[USD']]]+PPto[[#This Row],[Ppto. OI '[USD']]] -> 0
A25: 1.05 | B25: Edificación | C25: 1.05 Estudio Geotécnico | D25: 0 | F25: =SUMIFS(BD.PD[Ppto. Orden Interna '[DOP']],BD.PD[Pos],PPto[[#This Row],[Part.]],BD.PD[Tipo Ppto],F$18) -> 0 | G25: =SUMIFS(BD.PD[Ppto. Orden Interna '[DOP']],BD.PD[Pos],PPto[[#This Row],[Part.]],BD.PD[Tipo Ppto],G$18) -> 0 | H25: =PPto[[#This Row],[Ppto. Capex '[DOP']]]+PPto[[#This Row],[Ppto. OI '[DOP']2]] -> 0 | I25: =SUMIFS(BD.PD[Ppto. Orden Interna '[USD']],BD.PD[Pos],PPto[[#This Row],[Part.]],BD.PD[Tipo Ppto],I$18) -> 0 | J25: =SUMIFS(BD.PD[Ppto. Orden Interna '[USD']],BD.PD[Pos],PPto[[#This Row],[Part.]],BD.PD[Tipo Ppto],J$18) -> 0 | K25: =PPto[[#This Row],[Ppto. Capex '[USD']]]+PPto[[#This Row],[Ppto. OI '[USD']]] -> 0
A26: 1.06 | B26: Edificación | C26: 1.06 Levantamiento topográfico | D26: 0 | F26: =SUMIFS(BD.PD[Ppto. Orden Interna '[DOP']],BD.PD[Pos],PPto[[#This Row],[Part.]],BD.PD[Tipo Ppto],F$18) -> 0 | G26: =SUMIFS(BD.PD[Ppto. Orden Interna '[DOP']],BD.PD[Pos],PPto[[#This Row],[Part.]],BD.PD[Tipo Ppto],G$18) -> 0 | H26: =PPto[[#This Row],[Ppto. Capex '[DOP']]]+PPto[[#This Row],[Ppto. OI '[DOP']2]] -> 0 | I26: =SUMIFS(BD.PD[Ppto. Orden Interna '[USD']],BD.PD[Pos],PPto[[#This Row],[Part.]],BD.PD[Tipo Ppto],I$18) -> 0 | J26: =SUMIFS(BD.PD[Ppto. Orden Interna '[USD']],BD.PD[Pos],PPto[[#This Row],[Part.]],BD.PD[Tipo Ppto],J$18) -> 0 | K26: =PPto[[#This Row],[Ppto. Capex '[USD']]]+PPto[[#This Row],[Ppto. OI '[USD']]] -> 0
A27: 1.07 | B27: Edificación | C27: 1.07 Permisos | D27: 0 | F27: =SUMIFS(BD.PD[Ppto. Orden Interna '[DOP']],BD.PD[Pos],PPto[[#This Row],[Part.]],BD.PD[Tipo Ppto],F$18) -> 0 | G27: =SUMIFS(BD.PD[Ppto. Orden Interna '[DOP']],BD.PD[Pos],PPto[[#This Row],[Part.]],BD.PD[Tipo Ppto],G$18) -> 0 | H27: =PPto[[#This Row],[Ppto. Capex '[DOP']]]+PPto[[#This Row],[Ppto. OI '[DOP']2]] -> 0 | I27: =SUMIFS(BD.PD[Ppto. Orden Interna '[USD']],BD.PD[Pos],PPto[[#This Row],[Part.]],BD.PD[Tipo Ppto],I$18) -> 0 | J27: =SUMIFS(BD.PD[Ppto. Orden Interna '[USD']],BD.PD[Pos],PPto[[#This Row],[Part.]],BD.PD[Tipo Ppto],J$18) -> 0 | K27: =PPto[[#This Row],[Ppto. Capex '[USD']]]+PPto[[#This Row],[Ppto. OI '[USD']]] -> 0
A28: 1.08 | B28: Edificación | C28: 1.08 Diseño sistema contra incendios | D28: 0 | F28: =SUMIFS(BD.PD[Ppto. Orden Interna '[DOP']],BD.PD[Pos],PPto[[#This Row],[Part.]],BD.PD[Tipo Ppto],F$18) -> 0 | G28: =SUMIFS(BD.PD[Ppto. Orden Interna '[DOP']],BD.PD[Pos],PPto[[#This Row],[Part.]],BD.PD[Tipo Ppto],G$18) -> 0 | H28: =PPto[[#This Row],[Ppto. Capex '[DOP']]]+PPto[[#This Row],[Ppto. OI '[DOP']2]] -> 0 | I28: =SUMIFS(BD.PD[Ppto. Orden Interna '[USD']],BD.PD[Pos],PPto[[#This Row],[Part.]],BD.PD[Tipo Ppto],I$18) -> 0 | J28: =SUMIFS(BD.PD[Ppto. Orden Interna '[USD']],BD.PD[Pos],PPto[[#This Row],[Part.]],BD.PD[Tipo Ppto],J$18) -> 0 | K28: =PPto[[#This Row],[Ppto. Capex '[USD']]]+PPto[[#This Row],[Ppto. OI '[USD']]] -> 0
A29: 1.09 | B29: Edificación | C29: 1.09 Diseño sistema gas | D29: 0 | F29: =SUMIFS(BD.PD[Ppto. Orden Interna '[DOP']],BD.PD[Pos],PPto[[#This Row],[Part.]],BD.PD[Tipo Ppto],F$18) -> 0 | G29: =SUMIFS(BD.PD[Ppto. Orden Interna '[DOP']],BD.PD[Pos],PPto[[#This Row],[Part.]],BD.PD[Tipo Ppto],G$18) -> 0 | H29: =PPto[[#This Row],[Ppto. Capex '[DOP']]]+PPto[[#This Row],[Ppto. OI '[DOP']2]] -> 0 | I29: =SUMIFS(BD.PD[Ppto. Orden Interna '[USD']],BD.PD[Pos],PPto[[#This Row],[Part.]],BD.PD[Tipo Ppto],I$18) -> 0 | J29: =SUMIFS(BD.PD[Ppto. Orden Interna '[USD']],BD.PD[Pos],PPto[[#This Row],[Part.]],BD.PD[Tipo Ppto],J$18) -> 0 | K29: =PPto[[#This Row],[Ppto. Capex '[USD']]]+PPto[[#This Row],[Ppto. OI '[USD']]] -> 0
A30: 2 | C30: 2.00 Obra Civil | D30: =PPto[[#This Row],[Ppto. Capex '[DOP']]]+PPto[[#This Row],[Ppto. OI '[DOP']2]] -> 29340263 | F30: =SUM(F31:F41) -> 29340263 | G30: =SUM(G31:G41) -> 0 | H30: =PPto[[#This Row],[Ppto. Capex '[DOP']]]+PPto[[#This Row],[Ppto. OI '[DOP']2]] -> 29340263 | I30: =SUM(I31:I41) -> 480987.92 | J30: =SUM(J31:J41) -> 0 | K30: =PPto[[#This Row],[Ppto. Capex '[USD']]]+PPto[[#This Row],[Ppto. OI '[USD']]] -> 480987.92
A31: 2.01 | B31: Edificación | C31: 2.01 Edificación - Obra Civil | D31: =PPto[[#This Row],[Ppto. Capex '[DOP']]]+PPto[[#This Row],[Ppto. OI '[DOP']2]] -> 7081344.5 | F31: =SUMIFS(BD.PD[Ppto. Orden Interna '[DOP']],BD.PD[Pos],PPto[[#This Row],[Part.]],BD.PD[Tipo Ppto],F$18) -> 7081344.5 | G31: =SUMIFS(BD.PD[Ppto. Orden Interna '[DOP']],BD.PD[Pos],PPto[[#This Row],[Part.]],BD.PD[Tipo Ppto],G$18) -> 0 | H31: =PPto[[#This Row],[Ppto. Capex '[DOP']]]+PPto[[#This Row],[Ppto. OI '[DOP']2]] -> 7081344.5 | I31: =SUMIFS(BD.PD[Ppto. Orden Interna '[USD']],BD.PD[Pos],PPto[[#This Row],[Part.]],BD.PD[Tipo Ppto],I$18) -> 116087.61 | J31: =SUMIFS(BD.PD[Ppto. Orden Interna '[USD']],BD.PD[Pos],PPto[[#This Row],[Part.]],BD.PD[Tipo Ppto],J$18) -> 0 | K31: =PPto[[#This Row],[Ppto. Capex '[USD']]]+PPto[[#This Row],[Ppto. OI '[USD']]] -> 116087.61
A32: 2.02 | B32: Edificación | C32: 2.02 Edificación - Estructura Metálica | D32: 0 | F32: =SUMIFS(BD.PD[Ppto. Orden Interna '[DOP']],BD.PD[Pos],PPto[[#This Row],[Part.]],BD.PD[Tipo Ppto],F$18) -> 0 | G32: =SUMIFS(BD.PD[Ppto. Orden Interna '[DOP']],BD.PD[Pos],PPto[[#This Row],[Part.]],BD.PD[Tipo Ppto],G$18) -> 0 | H32: =PPto[[#This Row],[Ppto. Capex '[DOP']]]+PPto[[#This Row],[Ppto. OI '[DOP']2]] -> 0 | I32: =SUMIFS(BD.PD[Ppto. Orden Interna '[USD']],BD.PD[Pos],PPto[[#This Row],[Part.]],BD.PD[Tipo Ppto],I$18) -> 0 | J32: =SUMIFS(BD.PD[Ppto. Orden Interna '[USD']],BD.PD[Pos],PPto[[#This Row],[Part.]],BD.PD[Tipo Ppto],J$18) -> 0 | K32: =PPto[[#This Row],[Ppto. Capex '[USD']]]+PPto[[#This Row],[Ppto. OI '[USD']]] -> 0
A33: 2.03 | B33: Edificación | C33: 2.03 Edificación - Techo S.S. y Cerramientos Multipanel | D33: 0 | F33: =SUMIFS(BD.PD[Ppto. Orden Interna '[DOP']],BD.PD[Pos],PPto[[#This Row],[Part.]],BD.PD[Tipo Ppto],F$18) -> 0 | G33: =SUMIFS(BD.PD[Ppto. Orden Interna '[DOP']],BD.PD[Pos],PPto[[#This Row],[Part.]],BD.PD[Tipo Ppto],G$18) -> 0 | H33: =PPto[[#This Row],[Ppto. Capex '[DOP']]]+PPto[[#This Row],[Ppto. OI '[DOP']2]] -> 0 | I33: =SUMIFS(BD.PD[Ppto. Orden Interna '[USD']],BD.PD[Pos],PPto[[#This Row],[Part.]],BD.PD[Tipo Ppto],I$18) -> 0 | J33: =SUMIFS(BD.PD[Ppto. Orden Interna '[USD']],BD.PD[Pos],PPto[[#This Row],[Part.]],BD.PD[Tipo Ppto],J$18) -> 0 | K33: =PPto[[#This Row],[Ppto. Capex '[USD']]]+PPto[[#This Row],[Ppto. OI '[USD']]] -> 0
A34: 2.04 | B34: Edificación | C34: 2.04 Edificación - Tragaluces "Skylights" | D34: 0 | F34: =SUMIFS(BD.PD[Ppto. Orden Interna '[DOP']],BD.PD[Pos],PPto[[#This Row],[Part.]],BD.PD[Tipo Ppto],F$18) -> 0 | G34: =SUMIFS(BD.PD[Ppto. Orden Interna '[DOP']],BD.PD[Pos],PPto[[#This Row],[Part.]],BD.PD[Tipo Ppto],G$18) -> 0 | H34: =PPto[[#This Row],[Ppto. Capex '[DOP']]]+PPto[[#This Row],[Ppto. OI '[DOP']2]] -> 0 | I34: =SUMIFS(BD.PD[Ppto. Orden Interna '[USD']],BD.PD[Pos],PPto[[#This Row],[Part.]],BD.PD[Tipo Ppto],I$18) -> 0 | J34: =SUMIFS(BD.PD[Ppto. Orden Interna '[USD']],BD.PD[Pos],PPto[[#This Row],[Part.]],BD.PD[Tipo Ppto],J$18) -> 0 | K34: =PPto[[#This Row],[Ppto. Capex '[USD']]]+PPto[[#This Row],[Ppto. OI '[USD']]] -> 0
A35: 2.05 | B35: Equipamiento | C35: 2.05 Instalaciones Sanitarias | D35: =PPto[[#This Row],[Ppto. Capex '[DOP']]]+PPto[[#This Row],[Ppto. OI '[DOP']2]] -> 945223.71 | F35: =SUMIFS(BD.PD[Ppto. Orden Interna '[DOP']],BD.PD[Pos],PPto[[#This Row],[Part.]],BD.PD[Tipo Ppto],F$18) -> 945223.71 | G35: =SUMIFS(BD.PD[Ppto. Orden Interna '[DOP']],BD.PD[Pos],PPto[[#This Row],[Part.]],BD.PD[Tipo Ppto],G$18) -> 0 | H35: =PPto[[#This Row],[Ppto. Capex '[DOP']]]+PPto[[#This Row],[Ppto. OI '[DOP']2]] -> 945223.71 | I35: =SUMIFS(BD.PD[Ppto. Orden Interna '[USD']],BD.PD[Pos],PPto[[#This Row],[Part.]],BD.PD[Tipo Ppto],I$18) -> 15495.471 | J35: =SUMIFS(BD.PD[Ppto. Orden Interna '[USD']],BD.PD[Pos],PPto[[#This Row],[Part.]],BD.PD[Tipo Ppto],J$18) -> 0 | K35: =PPto[[#This Row],[Ppto. Capex '[USD']]]+PPto[[#This Row],[Ppto. OI '[USD']]] -> 15495.471
A36: 2.06 | B36: Equipamiento | C36: 2.06 Instalación de Gas | D36: =PPto[[#This Row],[Ppto. Capex '[DOP']]]+PPto[[#This Row],[Ppto. OI '[DOP']2]] -> 668846.99 | F36: =SUMIFS(BD.PD[Ppto. Orden Interna '[DOP']],BD.PD[Pos],PPto[[#This Row],[Part.]],BD.PD[Tipo Ppto],F$18) -> 668846.99 | G36: =SUMIFS(BD.PD[Ppto. Orden Interna '[DOP']],BD.PD[Pos],PPto[[#This Row],[Part.]],BD.PD[Tipo Ppto],G$18) -> 0 | H36: =PPto[[#This Row],[Ppto. Capex '[DOP']]]+PPto[[#This Row],[Ppto. OI '[DOP']2]] -> 668846.99 | I36: =SUMIFS(BD.PD[Ppto. Orden Interna '[USD']],BD.PD[Pos],PPto[[#This Row],[Part.]],BD.PD[Tipo Ppto],I$18) -> 10964.705 | J36: =SUMIFS(BD.PD[Ppto. Orden Interna '[USD']],BD.PD[Pos],PPto[[#This Row],[Part.]],BD.PD[Tipo Ppto],J$18) -> 0 | K36: =PPto[[#This Row],[Ppto. Capex '[USD']]]+PPto[[#This Row],[Ppto. OI '[USD']]] -> 10964.705
A37: 2.07 | B37: Equipamiento | C37: 2.07 Sistema Contra Incendios | D37: =PPto[[#This Row],[Ppto. Capex '[DOP']]]+PPto[[#This Row],[Ppto. OI '[DOP']2]] -> 5676792 | F37: =SUMIFS(BD.PD[Ppto. Orden Interna '[DOP']],BD.PD[Pos],PPto[[#This Row],[Part.]],BD.PD[Tipo Ppto],F$18) -> 5676792 | G37: =SUMIFS(BD.PD[Ppto. Orden Interna '[DOP']],BD.PD[Pos],PPto[[#This Row],[Part.]],BD.PD[Tipo Ppto],G$18) -> 0 | H37: =PPto[[#This Row],[Ppto. Capex '[DOP']]]+PPto[[#This Row],[Ppto. OI '[DOP']2]] -> 5676792 | I37: =SUMIFS(BD.PD[Ppto. Orden Interna '[USD']],BD.PD[Pos],PPto[[#This Row],[Part.]],BD.PD[Tipo Ppto],I$18) -> 93062.165 | J37: =SUMIFS(BD.PD[Ppto. Orden Interna '[USD']],BD.PD[Pos],PPto[[#This Row],[Part.]],BD.PD[Tipo Ppto],J$18) -> 0 | K37: =PPto[[#This Row],[Ppto. Capex '[USD']]]+PPto[[#This Row],[Ppto. OI '[USD']]] -> 93062.165
A38: 2.08 | B38: Equipamiento | C38: 2.08 Instalaciones Mecánicas | D38: =PPto[[#This Row],[Ppto. Capex '[DOP']]]+PPto[[#This Row],[Ppto. OI '[DOP']2]] -> 14306511 | F38: =SUMIFS(BD.PD[Ppto. Orden Interna '[DOP']],BD.PD[Pos],PPto[[#This Row],[Part.]],BD.PD[Tipo Ppto],F$18) -> 14306511 | G38: =SUMIFS(BD.PD[Ppto. Orden Interna '[DOP']],BD.PD[Pos],PPto[[#This Row],[Part.]],BD.PD[Tipo Ppto],G$18) -> 0 | H38: =PPto[[#This Row],[Ppto. Capex '[DOP']]]+PPto[[#This Row],[Ppto. OI '[DOP']2]] -> 14306511 | I38: =SUMIFS(BD.PD[Ppto. Orden Interna '[USD']],BD.PD[Pos],PPto[[#This Row],[Part.]],BD.PD[Tipo Ppto],I$18) -> 234532.97 | J38: =SUMIFS(BD.PD[Ppto. Orden Interna '[USD']],BD.PD[Pos],PPto[[#This Row],[Part.]],BD.PD[Tipo Ppto],J$18) -> 0 | K38: =PPto[[#This Row],[Ppto. Capex '[USD']]]+PPto[[#This Row],[Ppto. OI '[USD']]] -> 234532.97
A39: 2.09 | B39: Equipamiento | C39: 2.09 Rejillas y Sumideros | D39: =PPto[[#This Row],[Ppto. Capex '[DOP']]]+PPto[[#This Row],[Ppto. OI '[DOP']2]] -> 661544.36 | F39: =SUMIFS(BD.PD[Ppto. Orden Interna '[DOP']],BD.PD[Pos],PPto[[#This Row],[Part.]],BD.PD[Tipo Ppto],F$18) -> 661544.36 | G39: =SUMIFS(BD.PD[Ppto. Orden Interna '[DOP']],BD.PD[Pos],PPto[[#This Row],[Part.]],BD.PD[Tipo Ppto],G$18) -> 0 | H39: =PPto[[#This Row],[Ppto. Capex '[DOP']]]+PPto[[#This Row],[Ppto. OI '[DOP']2]] -> 661544.36 | I39: =SUMIFS(BD.PD[Ppto. Orden Interna '[USD']],BD.PD[Pos],PPto[[#This Row],[Part.]],BD.PD[Tipo Ppto],I$18) -> 10844.99 | J39: =SUMIFS(BD.PD[Ppto. Orden Interna '[USD']],BD.PD[Pos],PPto[[#This Row],[Part.]],BD.PD[Tipo Ppto],J$18) -> 0 | K39: =PPto[[#This Row],[Ppto. Capex '[USD']]]+PPto[[#This Row],[Ppto. OI '[USD']]] -> 10844.99
A40: 2.1 | B40: Edificación | C40: 2.10 Supervisión Civil y Sanitaria | D40: 0 | F40: =SUMIFS(BD.PD[Ppto. Orden Interna '[DOP']],BD.PD[Pos],PPto[[#This Row],[Part.]],BD.PD[Tipo Ppto],F$18) -> 0 | G40: =SUMIFS(BD.PD[Ppto. Orden Interna '[DOP']],BD.PD[Pos],PPto[[#This Row],[Part.]],BD.PD[Tipo Ppto],G$18) -> 0 | H40: =PPto[[#This Row],[Ppto. Capex '[DOP']]]+PPto[[#This Row],[Ppto. OI '[DOP']2]] -> 0 | I40: =SUMIFS(BD.PD[Ppto. Orden Interna '[USD']],BD.PD[Pos],PPto[[#This Row],[Part.]],BD.PD[Tipo Ppto],I$18) -> 0 | J40: =SUMIFS(BD.PD[Ppto. Orden Interna '[USD']],BD.PD[Pos],PPto[[#This Row],[Part.]],BD.PD[Tipo Ppto],J$18) -> 0 | K40: =PPto[[#This Row],[Ppto. Capex '[USD']]]+PPto[[#This Row],[Ppto. OI '[USD']]] -> 0
A41: 2.11 | B41: Edificación | C41: 2.11 Supervisión Arquitectónica | D41: 0 | F41: =SUMIFS(BD.PD[Ppto. Orden Interna '[DOP']],BD.PD[Pos],PPto[[#This Row],[Part.]],BD.PD[Tipo Ppto],F$18) -> 0 | G41: =SUMIFS(BD.PD[Ppto. Orden Interna '[DOP']],BD.PD[Pos],PPto[[#This Row],[Part.]],BD.PD[Tipo Ppto],G$18) -> 0 | H41: =PPto[[#This Row],[Ppto. Capex '[DOP']]]+PPto[[#This Row],[Ppto. OI '[DOP']2]] -> 0 | I41: =SUMIFS(BD.PD[Ppto. Orden Interna '[USD']],BD.PD[Pos],PPto[[#This Row],[Part.]],BD.PD[Tipo Ppto],I$18) -> 0 | J41: =SUMIFS(BD.PD[Ppto. Orden Interna '[USD']],BD.PD[Pos],PPto[[#This Row],[Part.]],BD.PD[Tipo Ppto],J$18) -> 0 | K41: =PPto[[#This Row],[Ppto. Capex '[USD']]]+PPto[[#This Row],[Ppto. OI '[USD']]] -> 0
A42: 3 | C42: 3.00 Sistema Eléctrico | D42: =PPto[[#This Row],[Ppto. Capex '[DOP']]]+PPto[[#This Row],[Ppto. OI '[DOP']2]] -> 27317363 | F42: =SUM(F43:F46) -> 27317363 | G42: =SUM(G43:G46) -> 0 | H42: =PPto[[#This Row],[Ppto. Capex '[DOP']]]+PPto[[#This Row],[Ppto. OI '[DOP']2]] -> 27317363 | I42: =SUM(I43:I46) -> 447825.63 | J42: =SUM(J43:J46) -> 0 | K42: =PPto[[#This Row],[Ppto. Capex '[USD']]]+PPto[[#This Row],[Ppto. OI '[USD']]] -> 447825.63
A43: 3.01 | B43: Equipamiento | C43: 3.01 Instalaciones Eléctricas | D43: 0 | F43: =SUMIFS(BD.PD[Ppto. Orden Interna '[DOP']],BD.PD[Pos],PPto[[#This Row],[Part.]],BD.PD[Tipo Ppto],F$18) -> 15842042 | G43: =SUMIFS(BD.PD[Ppto. Orden Interna '[DOP']],BD.PD[Pos],PPto[[#This Row],[Part.]],BD.PD[Tipo Ppto],G$18) -> 0 | H43: =PPto[[#This Row],[Ppto. Capex '[DOP']]]+PPto[[#This Row],[Ppto. OI '[DOP']2]] -> 15842042 | I43: =SUMIFS(BD.PD[Ppto. Orden Interna '[USD']],BD.PD[Pos],PPto[[#This Row],[Part.]],BD.PD[Tipo Ppto],I$18) -> 259705.61 | J43: =SUMIFS(BD.PD[Ppto. Orden Interna '[USD']],BD.PD[Pos],PPto[[#This Row],[Part.]],BD.PD[Tipo Ppto],J$18) -> 0 | K43: =PPto[[#This Row],[Ppto. Capex '[USD']]]+PPto[[#This Row],[Ppto. OI '[USD']]] -> 259705.61
A44: 3.02 | B44: Equipamiento | C44: 3.02 Supervisión Eléctrica | D44: 0 | F44: =SUMIFS(BD.PD[Ppto. Orden Interna '[DOP']],BD.PD[Pos],PPto[[#This Row],[Part.]],BD.PD[Tipo Ppto],F$18) -> 0 | G44: =SUMIFS(BD.PD[Ppto. Orden Interna '[DOP']],BD.PD[Pos],PPto[[#This Row],[Part.]],BD.PD[Tipo Ppto],G$18) -> 0 | H44: =PPto[[#This Row],[Ppto. Capex '[DOP']]]+PPto[[#This Row],[Ppto. OI '[DOP']2]] -> 0 | I44: =SUMIFS(BD.PD[Ppto. Orden Interna '[USD']],BD.PD[Pos],PPto[[#This Row],[Part.]],BD.PD[Tipo Ppto],I$18) -> 0 | J44: =SUMIFS(BD.PD[Ppto. Orden Interna '[USD']],BD.PD[Pos],PPto[[#This Row],[Part.]],BD.PD[Tipo Ppto],J$18) -> 0 | K44: =PPto[[#This Row],[Ppto. Capex '[USD']]]+PPto[[#This Row],[Ppto. OI '[USD']]] -> 0
A45: 3.03 | B45: Equipamiento | C45: 3.03 Generadores | D45: =PPto[[#This Row],[Ppto. Capex '[DOP']]]+PPto[[#This Row],[Ppto. OI '[DOP']2]] -> 10080507 | F45: =SUMIFS(BD.PD[Ppto. Orden Interna '[DOP']],BD.PD[Pos],PPto[[#This Row],[Part.]],BD.PD[Tipo Ppto],F$18) -> 10080507 | G45: =SUMIFS(BD.PD[Ppto. Orden Interna '[DOP']],BD.PD[Pos],PPto[[#This Row],[Part.]],BD.PD[Tipo Ppto],G$18) -> 0 | H45: =PPto[[#This Row],[Ppto. Capex '[DOP']]]+PPto[[#This Row],[Ppto. OI '[DOP']2]] -> 10080507 | I45: =SUMIFS(BD.PD[Ppto. Orden Interna '[USD']],BD.PD[Pos],PPto[[#This Row],[Part.]],BD.PD[Tipo Ppto],I$18) -> 165254.22 | J45: =SUMIFS(BD.PD[Ppto. Orden Interna '[USD']],BD.PD[Pos],PPto[[#This Row],[Part.]],BD.PD[Tipo Ppto],J$18) -> 0 | K45: =PPto[[#This Row],[Ppto. Capex '[USD']]]+PPto[[#This Row],[Ppto. OI '[USD']]] -> 165254.22
A46: 3.04 | B46: Equipamiento | C46: 3.04 Inversor y UPS | D46: =PPto[[#This Row],[Ppto. Capex '[DOP']]]+PPto[[#This Row],[Ppto. OI '[DOP']2]] -> 1394813.8 | F46: =SUMIFS(BD.PD[Ppto. Orden Interna '[DOP']],BD.PD[Pos],PPto[[#This Row],[Part.]],BD.PD[Tipo Ppto],F$18) -> 1394813.8 | G46: =SUMIFS(BD.PD[Ppto. Orden Interna '[DOP']],BD.PD[Pos],PPto[[#This Row],[Part.]],BD.PD[Tipo Ppto],G$18) -> 0 | H46: =PPto[[#This Row],[Ppto. Capex '[DOP']]]+PPto[[#This Row],[Ppto. OI '[DOP']2]] -> 1394813.8 | I46: =SUMIFS(BD.PD[Ppto. Orden Interna '[USD']],BD.PD[Pos],PPto[[#This Row],[Part.]],BD.PD[Tipo Ppto],I$18) -> 22865.8 | J46: =SUMIFS(BD.PD[Ppto. Orden Interna '[USD']],BD.PD[Pos],PPto[[#This Row],[Part.]],BD.PD[Tipo Ppto],J$18) -> 0 | K46: =PPto[[#This Row],[Ppto. Capex '[USD']]]+PPto[[#This Row],[Ppto. OI '[USD']]] -> 22865.8
A47: 4 | C47: 4.00 Sistema de Climatización | D47: =PPto[[#This Row],[Ppto. Capex '[DOP']]]+PPto[[#This Row],[Ppto. OI '[DOP']2]] -> 17894592 | F47: =SUM(F48:F50) -> 17894592 | G47: =SUM(G48:G50) -> 0 | H47: =PPto[[#This Row],[Ppto. Capex '[DOP']]]+PPto[[#This Row],[Ppto. OI '[DOP']2]] -> 17894592 | I47: =SUM(I48:I50) -> 293353.96 | J47: =SUM(J48:J50) -> 0 | K47: =PPto[[#This Row],[Ppto. Capex '[USD']]]+PPto[[#This Row],[Ppto. OI '[USD']]] -> 293353.96
A48: 4.01 | B48: Equipamiento | C48: 4.01 Suministro e instalación de Equipos | D48: =PPto[[#This Row],[Ppto. Capex '[DOP']]]+PPto[[#This Row],[Ppto. OI '[DOP']2]] -> 15961715 | F48: =SUMIFS(BD.PD[Ppto. Orden Interna '[DOP']],BD.PD[Pos],PPto[[#This Row],[Part.]],BD.PD[Tipo Ppto],F$18) -> 15961715 | G48: =SUMIFS(BD.PD[Ppto. Orden Interna '[DOP']],BD.PD[Pos],PPto[[#This Row],[Part.]],BD.PD[Tipo Ppto],G$18) -> 0 | H48: =PPto[[#This Row],[Ppto. Capex '[DOP']]]+PPto[[#This Row],[Ppto. OI '[DOP']2]] -> 15961715 | I48: =SUMIFS(BD.PD[Ppto. Orden Interna '[USD']],BD.PD[Pos],PPto[[#This Row],[Part.]],BD.PD[Tipo Ppto],I$18) -> 261667.45 | J48: =SUMIFS(BD.PD[Ppto. Orden Interna '[USD']],BD.PD[Pos],PPto[[#This Row],[Part.]],BD.PD[Tipo Ppto],J$18) -> 0 | K48: =PPto[[#This Row],[Ppto. Capex '[USD']]]+PPto[[#This Row],[Ppto. OI '[USD']]] -> 261667.45
A49: 4.02 | B49: Equipamiento | C49: 4.02 Supervisión Mecánica | D49: 0 | F49: =SUMIFS(BD.PD[Ppto. Orden Interna '[DOP']],BD.PD[Pos],PPto[[#This Row],[Part.]],BD.PD[Tipo Ppto],F$18) -> 0 | G49: =SUMIFS(BD.PD[Ppto. Orden Interna '[DOP']],BD.PD[Pos],PPto[[#This Row],[Part.]],BD.PD[Tipo Ppto],G$18) -> 0 | H49: =PPto[[#This Row],[Ppto. Capex '[DOP']]]+PPto[[#This Row],[Ppto. OI '[DOP']2]] -> 0 | I49: =SUMIFS(BD.PD[Ppto. Orden Interna '[USD']],BD.PD[Pos],PPto[[#This Row],[Part.]],BD.PD[Tipo Ppto],I$18) -> 0 | J49: =SUMIFS(BD.PD[Ppto. Orden Interna '[USD']],BD.PD[Pos],PPto[[#This Row],[Part.]],BD.PD[Tipo Ppto],J$18) -> 0 | K49: =PPto[[#This Row],[Ppto. Capex '[USD']]]+PPto[[#This Row],[Ppto. OI '[USD']]] -> 0
A50: 4.03 | B50: Equipamiento | C50: 4.03 Sistema de Extracción cocina | D50: =PPto[[#This Row],[Ppto. Capex '[DOP']]]+PPto[[#This Row],[Ppto. OI '[DOP']2]] -> 1932876.9 | F50: =SUMIFS(BD.PD[Ppto. Orden Interna '[DOP']],BD.PD[Pos],PPto[[#This Row],[Part.]],BD.PD[Tipo Ppto],F$18) -> 1932876.9 | G50: =SUMIFS(BD.PD[Ppto. Orden Interna '[DOP']],BD.PD[Pos],PPto[[#This Row],[Part.]],BD.PD[Tipo Ppto],G$18) -> 0 | H50: =PPto[[#This Row],[Ppto. Capex '[DOP']]]+PPto[[#This Row],[Ppto. OI '[DOP']2]] -> 1932876.9 | I50: =SUMIFS(BD.PD[Ppto. Orden Interna '[USD']],BD.PD[Pos],PPto[[#This Row],[Part.]],BD.PD[Tipo Ppto],I$18) -> 31686.507 | J50: =SUMIFS(BD.PD[Ppto. Orden Interna '[USD']],BD.PD[Pos],PPto[[#This Row],[Part.]],BD.PD[Tipo Ppto],J$18) -> 0 | K50: =PPto[[#This Row],[Ppto. Capex '[USD']]]+PPto[[#This Row],[Ppto. OI '[USD']]] -> 31686.507
A51: 5 | C51: 5.00 Frio Alimentario | D51: =PPto[[#This Row],[Ppto. Capex '[DOP']]]+PPto[[#This Row],[Ppto. OI '[DOP']2]] -> 66439178 | F51: =SUM(F52:F58) -> 66439178 | G51: =SUM(G52:G58) -> 0 | H51: =PPto[[#This Row],[Ppto. Capex '[DOP']]]+PPto[[#This Row],[Ppto. OI '[DOP']2]] -> 66439178 | I51: =SUM(I52:I58) -> 1089166.9 | J51: =SUM(J52:J58) -> 0 | K51: =PPto[[#This Row],[Ppto. Capex '[USD']]]+PPto[[#This Row],[Ppto. OI '[USD']]] -> 1089166.9
A52: 5.01 | B52: Equipamiento | C52: 5.01 Paneles | D52: =PPto[[#This Row],[Ppto. Capex '[DOP']]]+PPto[[#This Row],[Ppto. OI '[DOP']2]] -> 7484107.7 | F52: =SUMIFS(BD.PD[Ppto. Orden Interna '[DOP']],BD.PD[Pos],PPto[[#This Row],[Part.]],BD.PD[Tipo Ppto],F$18) -> 7484107.7 | G52: =SUMIFS(BD.PD[Ppto. Orden Interna '[DOP']],BD.PD[Pos],PPto[[#This Row],[Part.]],BD.PD[Tipo Ppto],G$18) -> 0 | H52: =PPto[[#This Row],[Ppto. Capex '[DOP']]]+PPto[[#This Row],[Ppto. OI '[DOP']2]] -> 7484107.7 | I52: =SUMIFS(BD.PD[Ppto. Orden Interna '[USD']],BD.PD[Pos],PPto[[#This Row],[Part.]],BD.PD[Tipo Ppto],I$18) -> 122690.29 | J52: =SUMIFS(BD.PD[Ppto. Orden Interna '[USD']],BD.PD[Pos],PPto[[#This Row],[Part.]],BD.PD[Tipo Ppto],J$18) -> 0 | K52: =PPto[[#This Row],[Ppto. Capex '[USD']]]+PPto[[#This Row],[Ppto. OI '[USD']]] -> 122690.29
A53: 5.02 | B53: Equipamiento | C53: 5.02 FRP y Diamond Plate | D53: =PPto[[#This Row],[Ppto. Capex '[DOP']]]+PPto[[#This Row],[Ppto. OI '[DOP']2]] -> 1767143.2 | F53: =SUMIFS(BD.PD[Ppto. Orden Interna '[DOP']],BD.PD[Pos],PPto[[#This Row],[Part.]],BD.PD[Tipo Ppto],F$18) -> 1767143.2 | G53: =SUMIFS(BD.PD[Ppto. Orden Interna '[DOP']],BD.PD[Pos],PPto[[#This Row],[Part.]],BD.PD[Tipo Ppto],G$18) -> 0 | H53: =PPto[[#This Row],[Ppto. Capex '[DOP']]]+PPto[[#This Row],[Ppto. OI '[DOP']2]] -> 1767143.2 | I53: =SUMIFS(BD.PD[Ppto. Orden Interna '[USD']],BD.PD[Pos],PPto[[#This Row],[Part.]],BD.PD[Tipo Ppto],I$18) -> 28969.56 | J53: =SUMIFS(BD.PD[Ppto. Orden Interna '[USD']],BD.PD[Pos],PPto[[#This Row],[Part.]],BD.PD[Tipo Ppto],J$18) -> 0 | K53: =PPto[[#This Row],[Ppto. Capex '[USD']]]+PPto[[#This Row],[Ppto. OI '[USD']]] -> 28969.56
A54: 5.03 | B54: Equipamiento | C54: 5.03 Neveras, Centrales y Evaporadores | D54: =PPto[[#This Row],[Ppto. Capex '[DOP']]]+PPto[[#This Row],[Ppto. OI '[DOP']2]] -> 40967987 | F54: =SUMIFS(BD.PD[Ppto. Orden Interna '[DOP']],BD.PD[Pos],PPto[[#This Row],[Part.]],BD.PD[Tipo Ppto],F$18) -> 40967987 | G54: =SUMIFS(BD.PD[Ppto. Orden Interna '[DOP']],BD.PD[Pos],PPto[[#This Row],[Part.]],BD.PD[Tipo Ppto],G$18) -> 0 | H54: =PPto[[#This Row],[Ppto. Capex '[DOP']]]+PPto[[#This Row],[Ppto. OI '[DOP']2]] -> 40967987 | I54: =SUMIFS(BD.PD[Ppto. Orden Interna '[USD']],BD.PD[Pos],PPto[[#This Row],[Part.]],BD.PD[Tipo Ppto],I$18) -> 671606.35 | J54: =SUMIFS(BD.PD[Ppto. Orden Interna '[USD']],BD.PD[Pos],PPto[[#This Row],[Part.]],BD.PD[Tipo Ppto],J$18) -> 0 | K54: =PPto[[#This Row],[Ppto. Capex '[USD']]]+PPto[[#This Row],[Ppto. OI '[USD']]] -> 671606.35
A55: 5.04 | B55: Equipamiento | C55: 5.04 Bumpers Mcue/ Rack | D55: =PPto[[#This Row],[Ppto. Capex '[DOP']]]+PPto[[#This Row],[Ppto. OI '[DOP']2]] -> 2490164.5 | F55: =SUMIFS(BD.PD[Ppto. Orden Interna '[DOP']],BD.PD[Pos],PPto[[#This Row],[Part.]],BD.PD[Tipo Ppto],F$18) -> 2490164.5 | G55: =SUMIFS(BD.PD[Ppto. Orden Interna '[DOP']],BD.PD[Pos],PPto[[#This Row],[Part.]],BD.PD[Tipo Ppto],G$18) -> 0 | H55: =PPto[[#This Row],[Ppto. Capex '[DOP']]]+PPto[[#This Row],[Ppto. OI '[DOP']2]] -> 2490164.5 | I55: =SUMIFS(BD.PD[Ppto. Orden Interna '[USD']],BD.PD[Pos],PPto[[#This Row],[Part.]],BD.PD[Tipo Ppto],I$18) -> 40822.369 | J55: =SUMIFS(BD.PD[Ppto. Orden Interna '[USD']],BD.PD[Pos],PPto[[#This Row],[Part.]],BD.PD[Tipo Ppto],J$18) -> 0 | K55: =PPto[[#This Row],[Ppto. Capex '[USD']]]+PPto[[#This Row],[Ppto. OI '[USD']]] -> 40822.369
A56: 5.05 | B56: Equipamiento | C56: 5.05 Trameria Cuarto Frio | D56: =PPto[[#This Row],[Ppto. Capex '[DOP']]]+PPto[[#This Row],[Ppto. OI '[DOP']2]] -> 2573135.6 | F56: =SUMIFS(BD.PD[Ppto. Orden Interna '[DOP']],BD.PD[Pos],PPto[[#This Row],[Part.]],BD.PD[Tipo Ppto],F$18) -> 2573135.6 | G56: =SUMIFS(BD.PD[Ppto. Orden Interna '[DOP']],BD.PD[Pos],PPto[[#This Row],[Part.]],BD.PD[Tipo Ppto],G$18) -> 0 | H56: =PPto[[#This Row],[Ppto. Capex '[DOP']]]+PPto[[#This Row],[Ppto. OI '[DOP']2]] -> 2573135.6 | I56: =SUMIFS(BD.PD[Ppto. Orden Interna '[USD']],BD.PD[Pos],PPto[[#This Row],[Part.]],BD.PD[Tipo Ppto],I$18) -> 42182.551 | J56: =SUMIFS(BD.PD[Ppto. Orden Interna '[USD']],BD.PD[Pos],PPto[[#This Row],[Part.]],BD.PD[Tipo Ppto],J$18) -> 0 | K56: =PPto[[#This Row],[Ppto. Capex '[USD']]]+PPto[[#This Row],[Ppto. OI '[USD']]] -> 42182.551
A57: 5.06 | B57: Equipamiento | C57: 5.06 Instalacion Frio Alimentario | D57: =PPto[[#This Row],[Ppto. Capex '[DOP']]]+PPto[[#This Row],[Ppto. OI '[DOP']2]] -> 6127746.4 | F57: =SUMIFS(BD.PD[Ppto. Orden Interna '[DOP']],BD.PD[Pos],PPto[[#This Row],[Part.]],BD.PD[Tipo Ppto],F$18) -> 6127746.4 | G57: =SUMIFS(BD.PD[Ppto. Orden Interna '[DOP']],BD.PD[Pos],PPto[[#This Row],[Part.]],BD.PD[Tipo Ppto],G$18) -> 0 | H57: =PPto[[#This Row],[Ppto. Capex '[DOP']]]+PPto[[#This Row],[Ppto. OI '[DOP']2]] -> 6127746.4 | I57: =SUMIFS(BD.PD[Ppto. Orden Interna '[USD']],BD.PD[Pos],PPto[[#This Row],[Part.]],BD.PD[Tipo Ppto],I$18) -> 100454.86 | J57: =SUMIFS(BD.PD[Ppto. Orden Interna '[USD']],BD.PD[Pos],PPto[[#This Row],[Part.]],BD.PD[Tipo Ppto],J$18) -> 0 | K57: =PPto[[#This Row],[Ppto. Capex '[USD']]]+PPto[[#This Row],[Ppto. OI '[USD']]] -> 100454.86
A58: 5.07 | B58: Equipamiento | C58: 5.07 Chase Doors | D58: =PPto[[#This Row],[Ppto. Capex '[DOP']]]+PPto[[#This Row],[Ppto. OI '[DOP']2]] -> 5028893.7 | F58: =SUMIFS(BD.PD[Ppto. Orden Interna '[DOP']],BD.PD[Pos],PPto[[#This Row],[Part.]],BD.PD[Tipo Ppto],F$18) -> 5028893.7 | G58: =SUMIFS(BD.PD[Ppto. Orden Interna '[DOP']],BD.PD[Pos],PPto[[#This Row],[Part.]],BD.PD[Tipo Ppto],G$18) -> 0 | H58: =PPto[[#This Row],[Ppto. Capex '[DOP']]]+PPto[[#This Row],[Ppto. OI '[DOP']2]] -> 5028893.7 | I58: =SUMIFS(BD.PD[Ppto. Orden Interna '[USD']],BD.PD[Pos],PPto[[#This Row],[Part.]],BD.PD[Tipo Ppto],I$18) -> 82440.88 | J58: =SUMIFS(BD.PD[Ppto. Orden Interna '[USD']],BD.PD[Pos],PPto[[#This Row],[Part.]],BD.PD[Tipo Ppto],J$18) -> 0 | K58: =PPto[[#This Row],[Ppto. Capex '[USD']]]+PPto[[#This Row],[Ppto. OI '[USD']]] -> 82440.88
A59: 6 | C59: 6.00 Tecnología, Seguridad y Tesorería | D59: =PPto[[#This Row],[Ppto. Capex '[DOP']]]+PPto[[#This Row],[Ppto. OI '[DOP']2]] -> 2053024.1 | F59: =SUM(F60:F64) -> 2053024.1 | G59: =SUM(G60:G64) -> 0 | H59: =PPto[[#This Row],[Ppto. Capex '[DOP']]]+PPto[[#This Row],[Ppto. OI '[DOP']2]] -> 2053024.1 | I59: =SUM(I60:I64) -> 33656.133 | J59: =SUM(J60:J64) -> 0 | K59: =PPto[[#This Row],[Ppto. Capex '[USD']]]+PPto[[#This Row],[Ppto. OI '[USD']]] -> 33656.133
A60: 6.01 | B60: Equipamiento | C60: 6.01 Sistema de cámaras CCTV | D60: =PPto[[#This Row],[Ppto. Capex '[DOP']]]+PPto[[#This Row],[Ppto. OI '[DOP']2]] -> 0 | F60: =SUMIFS(BD.PD[Ppto. Orden Interna '[DOP']],BD.PD[Pos],PPto[[#This Row],[Part.]],BD.PD[Tipo Ppto],F$18) -> 0 | G60: =SUMIFS(BD.PD[Ppto. Orden Interna '[DOP']],BD.PD[Pos],PPto[[#This Row],[Part.]],BD.PD[Tipo Ppto],G$18) -> 0 | H60: =PPto[[#This Row],[Ppto. Capex '[DOP']]]+PPto[[#This Row],[Ppto. OI '[DOP']2]] -> 0 | I60: =SUMIFS(BD.PD[Ppto. Orden Interna '[USD']],BD.PD[Pos],PPto[[#This Row],[Part.]],BD.PD[Tipo Ppto],I$18) -> 0 | J60: =SUMIFS(BD.PD[Ppto. Orden Interna '[USD']],BD.PD[Pos],PPto[[#This Row],[Part.]],BD.PD[Tipo Ppto],J$18) -> 0 | K60: =PPto[[#This Row],[Ppto. Capex '[USD']]]+PPto[[#This Row],[Ppto. OI '[USD']]] -> 0
A61: 6.02 | B61: Equipamiento | C61: 6.02 Antenas detección de robo | D61: 0 | F61: =SUMIFS(BD.PD[Ppto. Orden Interna '[DOP']],BD.PD[Pos],PPto[[#This Row],[Part.]],BD.PD[Tipo Ppto],F$18) -> 0 | G61: =SUMIFS(BD.PD[Ppto. Orden Interna '[DOP']],BD.PD[Pos],PPto[[#This Row],[Part.]],BD.PD[Tipo Ppto],G$18) -> 0 | H61: =PPto[[#This Row],[Ppto. Capex '[DOP']]]+PPto[[#This Row],[Ppto. OI '[DOP']2]] -> 0 | I61: =SUMIFS(BD.PD[Ppto. Orden Interna '[USD']],BD.PD[Pos],PPto[[#This Row],[Part.]],BD.PD[Tipo Ppto],I$18) -> 0 | J61: =SUMIFS(BD.PD[Ppto. Orden Interna '[USD']],BD.PD[Pos],PPto[[#This Row],[Part.]],BD.PD[Tipo Ppto],J$18) -> 0 | K61: =PPto[[#This Row],[Ppto. Capex '[USD']]]+PPto[[#This Row],[Ppto. OI '[USD']]] -> 0
A62: 6.03 | B62: Equipamiento | C62: 6.03 Puntos de Venta | D62: 0 | F62: =SUMIFS(BD.PD[Ppto. Orden Interna '[DOP']],BD.PD[Pos],PPto[[#This Row],[Part.]],BD.PD[Tipo Ppto],F$18) -> 0 | G62: =SUMIFS(BD.PD[Ppto. Orden Interna '[DOP']],BD.PD[Pos],PPto[[#This Row],[Part.]],BD.PD[Tipo Ppto],G$18) -> 0 | H62: =PPto[[#This Row],[Ppto. Capex '[DOP']]]+PPto[[#This Row],[Ppto. OI '[DOP']2]] -> 0 | I62: =SUMIFS(BD.PD[Ppto. Orden Interna '[USD']],BD.PD[Pos],PPto[[#This Row],[Part.]],BD.PD[Tipo Ppto],I$18) -> 0 | J62: =SUMIFS(BD.PD[Ppto. Orden Interna '[USD']],BD.PD[Pos],PPto[[#This Row],[Part.]],BD.PD[Tipo Ppto],J$18) -> 0 | K62: =PPto[[#This Row],[Ppto. Capex '[USD']]]+PPto[[#This Row],[Ppto. OI '[USD']]] -> 0
A63: 6.04 | B63: Equipamiento | C63: 6.04 Instalación de data y voz / Antenas de techo | D63: 0 | F63: =SUMIFS(BD.PD[Ppto. Orden Interna '[DOP']],BD.PD[Pos],PPto[[#This Row],[Part.]],BD.PD[Tipo Ppto],F$18) -> 0 | G63: =SUMIFS(BD.PD[Ppto. Orden Interna '[DOP']],BD.PD[Pos],PPto[[#This Row],[Part.]],BD.PD[Tipo Ppto],G$18) -> 0 | H63: =PPto[[#This Row],[Ppto. Capex '[DOP']]]+PPto[[#This Row],[Ppto. OI '[DOP']2]] -> 0 | I63: =SUMIFS(BD.PD[Ppto. Orden Interna '[USD']],BD.PD[Pos],PPto[[#This Row],[Part.]],BD.PD[Tipo Ppto],I$18) -> 0 | J63: =SUMIFS(BD.PD[Ppto. Orden Interna '[USD']],BD.PD[Pos],PPto[[#This Row],[Part.]],BD.PD[Tipo Ppto],J$18) -> 0 | K63: =PPto[[#This Row],[Ppto. Capex '[USD']]]+PPto[[#This Row],[Ppto. OI '[USD']]] -> 0
A64: 6.05 | B64: Equipamiento | C64: 6.05 Otros sum e inst Tecnología | D64: 0 | F64: =SUMIFS(BD.PD[Ppto. Orden Interna '[DOP']],BD.PD[Pos],PPto[[#This Row],[Part.]],BD.PD[Tipo Ppto],F$18) -> 2053024.1 | G64: =SUMIFS(BD.PD[Ppto. Orden Interna '[DOP']],BD.PD[Pos],PPto[[#This Row],[Part.]],BD.PD[Tipo Ppto],G$18) -> 0 | H64: =PPto[[#This Row],[Ppto. Capex '[DOP']]]+PPto[[#This Row],[Ppto. OI '[DOP']2]] -> 2053024.1 | I64: =SUMIFS(BD.PD[Ppto. Orden Interna '[USD']],BD.PD[Pos],PPto[[#This Row],[Part.]],BD.PD[Tipo Ppto],I$18) -> 33656.133 | J64: =SUMIFS(BD.PD[Ppto. Orden Interna '[USD']],BD.PD[Pos],PPto[[#This Row],[Part.]],BD.PD[Tipo Ppto],J$18) -> 0 | K64: =PPto[[#This Row],[Ppto. Capex '[USD']]]+PPto[[#This Row],[Ppto. OI '[USD']]] -> 33656.133
A65: 6.06 | B65: Equipamiento | C65: 6.06 Otros sum e inst Seguridad | D65: 0 | F65: =SUMIFS(BD.PD[Ppto. Orden Interna '[DOP']],BD.PD[Pos],PPto[[#This Row],[Part.]],BD.PD[Tipo Ppto],F$18) -> 0 | G65: =SUMIFS(BD.PD[Ppto. Orden Interna '[DOP']],BD.PD[Pos],PPto[[#This Row],[Part.]],BD.PD[Tipo Ppto],G$18) -> 0 | H65: =PPto[[#This Row],[Ppto. Capex '[DOP']]]+PPto[[#This Row],[Ppto. OI '[DOP']2]] -> 0 | I65: =SUMIFS(BD.PD[Ppto. Orden Interna '[USD']],BD.PD[Pos],PPto[[#This Row],[Part.]],BD.PD[Tipo Ppto],I$18) -> 0 | J65: =SUMIFS(BD.PD[Ppto. Orden Interna '[USD']],BD.PD[Pos],PPto[[#This Row],[Part.]],BD.PD[Tipo Ppto],J$18) -> 0 | K65: =PPto[[#This Row],[Ppto. Capex '[USD']]]+PPto[[#This Row],[Ppto. OI '[USD']]] -> 0
A66: 6.07 | B66: Equipamiento | C66: 6.07 Otros sum e inst Tesoreria | D66: 0 | F66: =SUMIFS(BD.PD[Ppto. Orden Interna '[DOP']],BD.PD[Pos],PPto[[#This Row],[Part.]],BD.PD[Tipo Ppto],F$18) -> 0 | G66: =SUMIFS(BD.PD[Ppto. Orden Interna '[DOP']],BD.PD[Pos],PPto[[#This Row],[Part.]],BD.PD[Tipo Ppto],G$18) -> 0 | H66: =PPto[[#This Row],[Ppto. Capex '[DOP']]]+PPto[[#This Row],[Ppto. OI '[DOP']2]] -> 0 | I66: =SUMIFS(BD.PD[Ppto. Orden Interna '[USD']],BD.PD[Pos],PPto[[#This Row],[Part.]],BD.PD[Tipo Ppto],I$18) -> 0 | J66: =SUMIFS(BD.PD[Ppto. Orden Interna '[USD']],BD.PD[Pos],PPto[[#This Row],[Part.]],BD.PD[Tipo Ppto],J$18) -> 0 | K66: =PPto[[#This Row],[Ppto. Capex '[USD']]]+PPto[[#This Row],[Ppto. OI '[USD']]] -> 0
A67: 7 | C67: 7.00 Equipamiento Produccion | D67: =PPto[[#This Row],[Ppto. Capex '[DOP']]]+PPto[[#This Row],[Ppto. OI '[DOP']2]] -> 36542696 | F67: =SUM(F68:F74) -> 36542696 | G67: =SUM(G68:G74) -> 0 | H67: =PPto[[#This Row],[Ppto. Capex '[DOP']]]+PPto[[#This Row],[Ppto. OI '[DOP']2]] -> 36542696 | I67: =SUM(I68:I74) -> 599060.58 | J67: =SUM(J68:J74) -> 0 | K67: =PPto[[#This Row],[Ppto. Capex '[USD']]]+PPto[[#This Row],[Ppto. OI '[USD']]] -> 599060.58
A68: 7.01 | B68: Equipamiento | C68: 7.01 Equipamiento de Acero Inoxidable | D68: =PPto[[#This Row],[Ppto. Capex '[DOP']]]+PPto[[#This Row],[Ppto. OI '[DOP']2]] -> 1908058.8 | F68: =SUMIFS(BD.PD[Ppto. Orden Interna '[DOP']],BD.PD[Pos],PPto[[#This Row],[Part.]],BD.PD[Tipo Ppto],F$18) -> 1908058.8 | G68: =SUMIFS(BD.PD[Ppto. Orden Interna '[DOP']],BD.PD[Pos],PPto[[#This Row],[Part.]],BD.PD[Tipo Ppto],G$18) -> 0 | H68: =PPto[[#This Row],[Ppto. Capex '[DOP']]]+PPto[[#This Row],[Ppto. OI '[DOP']2]] -> 1908058.8 | I68: =SUMIFS(BD.PD[Ppto. Orden Interna '[USD']],BD.PD[Pos],PPto[[#This Row],[Part.]],BD.PD[Tipo Ppto],I$18) -> 31279.652 | J68: =SUMIFS(BD.PD[Ppto. Orden Interna '[USD']],BD.PD[Pos],PPto[[#This Row],[Part.]],BD.PD[Tipo Ppto],J$18) -> 0 | K68: =PPto[[#This Row],[Ppto. Capex '[USD']]]+PPto[[#This Row],[Ppto. OI '[USD']]] -> 31279.652
A69: 7.02 | B69: Equipamiento | C69: 7.02 Cocina, Patio Comidas y Rostizería | D69: =PPto[[#This Row],[Ppto. Capex '[DOP']]]+PPto[[#This Row],[Ppto. OI '[DOP']2]] -> 2838308.9 | F69: =SUMIFS(BD.PD[Ppto. Orden Interna '[DOP']],BD.PD[Pos],PPto[[#This Row],[Part.]],BD.PD[Tipo Ppto],F$18) -> 2838308.9 | G69: =SUMIFS(BD.PD[Ppto. Orden Interna '[DOP']],BD.PD[Pos],PPto[[#This Row],[Part.]],BD.PD[Tipo Ppto],G$18) -> 0 | H69: =PPto[[#This Row],[Ppto. Capex '[DOP']]]+PPto[[#This Row],[Ppto. OI '[DOP']2]] -> 2838308.9 | I69: =SUMIFS(BD.PD[Ppto. Orden Interna '[USD']],BD.PD[Pos],PPto[[#This Row],[Part.]],BD.PD[Tipo Ppto],I$18) -> 46529.653 | J69: =SUMIFS(BD.PD[Ppto. Orden Interna '[USD']],BD.PD[Pos],PPto[[#This Row],[Part.]],BD.PD[Tipo Ppto],J$18) -> 0 | K69: =PPto[[#This Row],[Ppto. Capex '[USD']]]+PPto[[#This Row],[Ppto. OI '[USD']]] -> 46529.653
A70: 7.03 | B70: Equipamiento | C70: 7.03 Equipamiento Carniceria, Pescadería y Delicatesen | D70: =PPto[[#This Row],[Ppto. Capex '[DOP']]]+PPto[[#This Row],[Ppto. OI '[DOP']2]] -> 3772135.6 | F70: =SUMIFS(BD.PD[Ppto. Orden Interna '[DOP']],BD.PD[Pos],PPto[[#This Row],[Part.]],BD.PD[Tipo Ppto],F$18) -> 3772135.6 | G70: =SUMIFS(BD.PD[Ppto. Orden Interna '[DOP']],BD.PD[Pos],PPto[[#This Row],[Part.]],BD.PD[Tipo Ppto],G$18) -> 0 | H70: =PPto[[#This Row],[Ppto. Capex '[DOP']]]+PPto[[#This Row],[Ppto. OI '[DOP']2]] -> 3772135.6 | I70: =SUMIFS(BD.PD[Ppto. Orden Interna '[USD']],BD.PD[Pos],PPto[[#This Row],[Part.]],BD.PD[Tipo Ppto],I$18) -> 61838.289 | J70: =SUMIFS(BD.PD[Ppto. Orden Interna '[USD']],BD.PD[Pos],PPto[[#This Row],[Part.]],BD.PD[Tipo Ppto],J$18) -> 0 | K70: =PPto[[#This Row],[Ppto. Capex '[USD']]]+PPto[[#This Row],[Ppto. OI '[USD']]] -> 61838.289
A71: 7.04 | B71: Equipamiento | C71: 7.04 Equipamiento de Panaderia, Reposteria y Rosticería | D71: =PPto[[#This Row],[Ppto. Capex '[DOP']]]+PPto[[#This Row],[Ppto. OI '[DOP']2]] -> 20008960 | F71: =SUMIFS(BD.PD[Ppto. Orden Interna '[DOP']],BD.PD[Pos],PPto[[#This Row],[Part.]],BD.PD[Tipo Ppto],F$18) -> 20008960 | G71: =SUMIFS(BD.PD[Ppto. Orden Interna '[DOP']],BD.PD[Pos],PPto[[#This Row],[Part.]],BD.PD[Tipo Ppto],G$18) -> 0 | H71: =PPto[[#This Row],[Ppto. Capex '[DOP']]]+PPto[[#This Row],[Ppto. OI '[DOP']2]] -> 20008960 | I71: =SUMIFS(BD.PD[Ppto. Orden Interna '[USD']],BD.PD[Pos],PPto[[#This Row],[Part.]],BD.PD[Tipo Ppto],I$18) -> 328015.74 | J71: =SUMIFS(BD.PD[Ppto. Orden Interna '[USD']],BD.PD[Pos],PPto[[#This Row],[Part.]],BD.PD[Tipo Ppto],J$18) -> 0 | K71: =PPto[[#This Row],[Ppto. Capex '[USD']]]+PPto[[#This Row],[Ppto. OI '[USD']]] -> 328015.74
A72: 7.05 | B72: Equipamiento | C72: 7.05 Equipamiento de Frutas y Vegetales | D72: =PPto[[#This Row],[Ppto. Capex '[DOP']]]+PPto[[#This Row],[Ppto. OI '[DOP']2]] -> 291102.8 | F72: =SUMIFS(BD.PD[Ppto. Orden Interna '[DOP']],BD.PD[Pos],PPto[[#This Row],[Part.]],BD.PD[Tipo Ppto],F$18) -> 291102.8 | G72: =SUMIFS(BD.PD[Ppto. Orden Interna '[DOP']],BD.PD[Pos],PPto[[#This Row],[Part.]],BD.PD[Tipo Ppto],G$18) -> 0 | H72: =PPto[[#This Row],[Ppto. Capex '[DOP']]]+PPto[[#This Row],[Ppto. OI '[DOP']2]] -> 291102.8 | I72: =SUMIFS(BD.PD[Ppto. Orden Interna '[USD']],BD.PD[Pos],PPto[[#This Row],[Part.]],BD.PD[Tipo Ppto],I$18) -> 4772.177 | J72: =SUMIFS(BD.PD[Ppto. Orden Interna '[USD']],BD.PD[Pos],PPto[[#This Row],[Part.]],BD.PD[Tipo Ppto],J$18) -> 0 | K72: =PPto[[#This Row],[Ppto. Capex '[USD']]]+PPto[[#This Row],[Ppto. OI '[USD']]] -> 4772.177
A73: 7.06 | B73: Equipamiento | C73: 7.06 Balanzas | D73: =PPto[[#This Row],[Ppto. Capex '[DOP']]]+PPto[[#This Row],[Ppto. OI '[DOP']2]] -> 0 | F73: =SUMIFS(BD.PD[Ppto. Orden Interna '[DOP']],BD.PD[Pos],PPto[[#This Row],[Part.]],BD.PD[Tipo Ppto],F$18) -> 0 | G73: =SUMIFS(BD.PD[Ppto. Orden Interna '[DOP']],BD.PD[Pos],PPto[[#This Row],[Part.]],BD.PD[Tipo Ppto],G$18) -> 0 | H73: =PPto[[#This Row],[Ppto. Capex '[DOP']]]+PPto[[#This Row],[Ppto. OI '[DOP']2]] -> 0 | I73: =SUMIFS(BD.PD[Ppto. Orden Interna '[USD']],BD.PD[Pos],PPto[[#This Row],[Part.]],BD.PD[Tipo Ppto],I$18) -> 0 | J73: =SUMIFS(BD.PD[Ppto. Orden Interna '[USD']],BD.PD[Pos],PPto[[#This Row],[Part.]],BD.PD[Tipo Ppto],J$18) -> 0 | K73: =PPto[[#This Row],[Ppto. Capex '[USD']]]+PPto[[#This Row],[Ppto. OI '[USD']]] -> 0
A74: 7.07 | B74: Equipamiento | C74: 7.07 Otros Equipamientos de Producción | D74: =PPto[[#This Row],[Ppto. Capex '[DOP']]]+PPto[[#This Row],[Ppto. OI '[DOP']2]] -> 7724129.4 | F74: =SUMIFS(BD.PD[Ppto. Orden Interna '[DOP']],BD.PD[Pos],PPto[[#This Row],[Part.]],BD.PD[Tipo Ppto],F$18) -> 7724129.4 | G74: =SUMIFS(BD.PD[Ppto. Orden Interna '[DOP']],BD.PD[Pos],PPto[[#This Row],[Part.]],BD.PD[Tipo Ppto],G$18) -> 0 | H74: =PPto[[#This Row],[Ppto. Capex '[DOP']]]+PPto[[#This Row],[Ppto. OI '[DOP']2]] -> 7724129.4 | I74: =SUMIFS(BD.PD[Ppto. Orden Interna '[USD']],BD.PD[Pos],PPto[[#This Row],[Part.]],BD.PD[Tipo Ppto],I$18) -> 126625.07 | J74: =SUMIFS(BD.PD[Ppto. Orden Interna '[USD']],BD.PD[Pos],PPto[[#This Row],[Part.]],BD.PD[Tipo Ppto],J$18) -> 0 | K74: =PPto[[#This Row],[Ppto. Capex '[USD']]]+PPto[[#This Row],[Ppto. OI '[USD']]] -> 126625.07
A75: 8 | C75: 8.00 Equipamiento Tienda | D75: =PPto[[#This Row],[Ppto. Capex '[DOP']]]+PPto[[#This Row],[Ppto. OI '[DOP']2]] -> 49992580 | F75: =SUM(F76:F83) -> 49992580 | G75: =SUM(G76:G83) -> 0 | H75: =PPto[[#This Row],[Ppto. Capex '[DOP']]]+PPto[[#This Row],[Ppto. OI '[DOP']2]] -> 49992580 | I75: =SUM(I76:I83) -> 819550.49 | J75: =SUM(J76:J83) -> 0 | K75: =PPto[[#This Row],[Ppto. Capex '[USD']]]+PPto[[#This Row],[Ppto. OI '[USD']]] -> 819550.49
A76: 8.01 | B76: Equipamiento | C76: 8.01 Gondolas | D76: =PPto[[#This Row],[Ppto. Capex '[DOP']]]+PPto[[#This Row],[Ppto. OI '[DOP']2]] -> 22392511 | F76: =SUMIFS(BD.PD[Ppto. Orden Interna '[DOP']],BD.PD[Pos],PPto[[#This Row],[Part.]],BD.PD[Tipo Ppto],F$18) -> 22392511 | G76: =SUMIFS(BD.PD[Ppto. Orden Interna '[DOP']],BD.PD[Pos],PPto[[#This Row],[Part.]],BD.PD[Tipo Ppto],G$18) -> 0 | H76: =PPto[[#This Row],[Ppto. Capex '[DOP']]]+PPto[[#This Row],[Ppto. OI '[DOP']2]] -> 22392511 | I76: =SUMIFS(BD.PD[Ppto. Orden Interna '[USD']],BD.PD[Pos],PPto[[#This Row],[Part.]],BD.PD[Tipo Ppto],I$18) -> 367090.34 | J76: =SUMIFS(BD.PD[Ppto. Orden Interna '[USD']],BD.PD[Pos],PPto[[#This Row],[Part.]],BD.PD[Tipo Ppto],J$18) -> 0 | K76: =PPto[[#This Row],[Ppto. Capex '[USD']]]+PPto[[#This Row],[Ppto. OI '[USD']]] -> 367090.34
A77: 8.02 | B77: Equipamiento | C77: 8.02 Checkout | D77: =PPto[[#This Row],[Ppto. Capex '[DOP']]]+PPto[[#This Row],[Ppto. OI '[DOP']2]] -> 2633136.3 | F77: =SUMIFS(BD.PD[Ppto. Orden Interna '[DOP']],BD.PD[Pos],PPto[[#This Row],[Part.]],BD.PD[Tipo Ppto],F$18) -> 2633136.3 | G77: =SUMIFS(BD.PD[Ppto. Orden Interna '[DOP']],BD.PD[Pos],PPto[[#This Row],[Part.]],BD.PD[Tipo Ppto],G$18) -> 0 | H77: =PPto[[#This Row],[Ppto. Capex '[DOP']]]+PPto[[#This Row],[Ppto. OI '[DOP']2]] -> 2633136.3 | I77: =SUMIFS(BD.PD[Ppto. Orden Interna '[USD']],BD.PD[Pos],PPto[[#This Row],[Part.]],BD.PD[Tipo Ppto],I$18) -> 43166.169 | J77: =SUMIFS(BD.PD[Ppto. Orden Interna '[USD']],BD.PD[Pos],PPto[[#This Row],[Part.]],BD.PD[Tipo Ppto],J$18) -> 0 | K77: =PPto[[#This Row],[Ppto. Capex '[USD']]]+PPto[[#This Row],[Ppto. OI '[USD']]] -> 43166.169
A78: 8.03 | B78: Equipamiento | C78: 8.03 Carritos, Canastas y Accesorios | D78: =PPto[[#This Row],[Ppto. Capex '[DOP']]]+PPto[[#This Row],[Ppto. OI '[DOP']2]] -> 4792222.6 | F78: =SUMIFS(BD.PD[Ppto. Orden Interna '[DOP']],BD.PD[Pos],PPto[[#This Row],[Part.]],BD.PD[Tipo Ppto],F$18) -> 4792222.6 | G78: =SUMIFS(BD.PD[Ppto. Orden Interna '[DOP']],BD.PD[Pos],PPto[[#This Row],[Part.]],BD.PD[Tipo Ppto],G$18) -> 0 | H78: =PPto[[#This Row],[Ppto. Capex '[DOP']]]+PPto[[#This Row],[Ppto. OI '[DOP']2]] -> 4792222.6 | I78: =SUMIFS(BD.PD[Ppto. Orden Interna '[USD']],BD.PD[Pos],PPto[[#This Row],[Part.]],BD.PD[Tipo Ppto],I$18) -> 78561.027 | J78: =SUMIFS(BD.PD[Ppto. Orden Interna '[USD']],BD.PD[Pos],PPto[[#This Row],[Part.]],BD.PD[Tipo Ppto],J$18) -> 0 | K78: =PPto[[#This Row],[Ppto. Capex '[USD']]]+PPto[[#This Row],[Ppto. OI '[USD']]] -> 78561.027
A79: 8.04 | B79: Equipamiento | C79: 8.04 Trameria Almacen | D79: =PPto[[#This Row],[Ppto. Capex '[DOP']]]+PPto[[#This Row],[Ppto. OI '[DOP']2]] -> 334010 | F79: =SUMIFS(BD.PD[Ppto. Orden Interna '[DOP']],BD.PD[Pos],PPto[[#This Row],[Part.]],BD.PD[Tipo Ppto],F$18) -> 334010 | G79: =SUMIFS(BD.PD[Ppto. Orden Interna '[DOP']],BD.PD[Pos],PPto[[#This Row],[Part.]],BD.PD[Tipo Ppto],G$18) -> 0 | H79: =PPto[[#This Row],[Ppto. Capex '[DOP']]]+PPto[[#This Row],[Ppto. OI '[DOP']2]] -> 334010 | I79: =SUMIFS(BD.PD[Ppto. Orden Interna '[USD']],BD.PD[Pos],PPto[[#This Row],[Part.]],BD.PD[Tipo Ppto],I$18) -> 5475.5738 | J79: =SUMIFS(BD.PD[Ppto. Orden Interna '[USD']],BD.PD[Pos],PPto[[#This Row],[Part.]],BD.PD[Tipo Ppto],J$18) -> 0 | K79: =PPto[[#This Row],[Ppto. Capex '[USD']]]+PPto[[#This Row],[Ppto. OI '[USD']]] -> 5475.5738
A80: 8.05 | B80: Equipamiento | C80: 8.05 Mobiliario no operacional para Tiendas | D80: =PPto[[#This Row],[Ppto. Capex '[DOP']]]+PPto[[#This Row],[Ppto. OI '[DOP']2]] -> 3145377 | F80: =SUMIFS(BD.PD[Ppto. Orden Interna '[DOP']],BD.PD[Pos],PPto[[#This Row],[Part.]],BD.PD[Tipo Ppto],F$18) -> 3145377 | G80: =SUMIFS(BD.PD[Ppto. Orden Interna '[DOP']],BD.PD[Pos],PPto[[#This Row],[Part.]],BD.PD[Tipo Ppto],G$18) -> 0 | H80: =PPto[[#This Row],[Ppto. Capex '[DOP']]]+PPto[[#This Row],[Ppto. OI '[DOP']2]] -> 3145377 | I80: =SUMIFS(BD.PD[Ppto. Orden Interna '[USD']],BD.PD[Pos],PPto[[#This Row],[Part.]],BD.PD[Tipo Ppto],I$18) -> 51563.557 | J80: =SUMIFS(BD.PD[Ppto. Orden Interna '[USD']],BD.PD[Pos],PPto[[#This Row],[Part.]],BD.PD[Tipo Ppto],J$18) -> 0 | K80: =PPto[[#This Row],[Ppto. Capex '[USD']]]+PPto[[#This Row],[Ppto. OI '[USD']]] -> 51563.557
A81: 8.06 | B81: Equipamiento | C81: 8.06 Otros Equipamientos de Tienda | D81: =PPto[[#This Row],[Ppto. Capex '[DOP']]]+PPto[[#This Row],[Ppto. OI '[DOP']2]] -> 4898113.5 | F81: =SUMIFS(BD.PD[Ppto. Orden Interna '[DOP']],BD.PD[Pos],PPto[[#This Row],[Part.]],BD.PD[Tipo Ppto],F$18) -> 4898113.5 | G81: =SUMIFS(BD.PD[Ppto. Orden Interna '[DOP']],BD.PD[Pos],PPto[[#This Row],[Part.]],BD.PD[Tipo Ppto],G$18) -> 0 | H81: =PPto[[#This Row],[Ppto. Capex '[DOP']]]+PPto[[#This Row],[Ppto. OI '[DOP']2]] -> 4898113.5 | I81: =SUMIFS(BD.PD[Ppto. Orden Interna '[USD']],BD.PD[Pos],PPto[[#This Row],[Part.]],BD.PD[Tipo Ppto],I$18) -> 80296.942 | J81: =SUMIFS(BD.PD[Ppto. Orden Interna '[USD']],BD.PD[Pos],PPto[[#This Row],[Part.]],BD.PD[Tipo Ppto],J$18) -> 0 | K81: =PPto[[#This Row],[Ppto. Capex '[USD']]]+PPto[[#This Row],[Ppto. OI '[USD']]] -> 80296.942
A82: 8.07 | B82: Equipamiento | C82: 8.07 Señalizacion interiores | D82: =PPto[[#This Row],[Ppto. Capex '[DOP']]]+PPto[[#This Row],[Ppto. OI '[DOP']2]] -> 7256929.8 | F82: =SUMIFS(BD.PD[Ppto. Orden Interna '[DOP']],BD.PD[Pos],PPto[[#This Row],[Part.]],BD.PD[Tipo Ppto],F$18) -> 7256929.8 | G82: =SUMIFS(BD.PD[Ppto. Orden Interna '[DOP']],BD.PD[Pos],PPto[[#This Row],[Part.]],BD.PD[Tipo Ppto],G$18) -> 0 | H82: =PPto[[#This Row],[Ppto. Capex '[DOP']]]+PPto[[#This Row],[Ppto. OI '[DOP']2]] -> 7256929.8 | I82: =SUMIFS(BD.PD[Ppto. Orden Interna '[USD']],BD.PD[Pos],PPto[[#This Row],[Part.]],BD.PD[Tipo Ppto],I$18) -> 118966.06 | J82: =SUMIFS(BD.PD[Ppto. Orden Interna '[USD']],BD.PD[Pos],PPto[[#This Row],[Part.]],BD.PD[Tipo Ppto],J$18) -> 0 | K82: =PPto[[#This Row],[Ppto. Capex '[USD']]]+PPto[[#This Row],[Ppto. OI '[USD']]] -> 118966.06
A83: 8.08 | B83: Equipamiento | C83: 8.08 Señalizacion exteriores | D83: =PPto[[#This Row],[Ppto. Capex '[DOP']]]+PPto[[#This Row],[Ppto. OI '[DOP']2]] -> 4540279.6 | F83: =SUMIFS(BD.PD[Ppto. Orden Interna '[DOP']],BD.PD[Pos],PPto[[#This Row],[Part.]],BD.PD[Tipo Ppto],F$18) -> 4540279.6 | G83: =SUMIFS(BD.PD[Ppto. Orden Interna '[DOP']],BD.PD[Pos],PPto[[#This Row],[Part.]],BD.PD[Tipo Ppto],G$18) -> 0 | H83: =PPto[[#This Row],[Ppto. Capex '[DOP']]]+PPto[[#This Row],[Ppto. OI '[DOP']2]] -> 4540279.6 | I83: =SUMIFS(BD.PD[Ppto. Orden Interna '[USD']],BD.PD[Pos],PPto[[#This Row],[Part.]],BD.PD[Tipo Ppto],I$18) -> 74430.813 | J83: =SUMIFS(BD.PD[Ppto. Orden Interna '[USD']],BD.PD[Pos],PPto[[#This Row],[Part.]],BD.PD[Tipo Ppto],J$18) -> 0 | K83: =PPto[[#This Row],[Ppto. Capex '[USD']]]+PPto[[#This Row],[Ppto. OI '[USD']]] -> 74430.813
A84: 9 | C84: 9.00 Otros | D84: =SUM(D85:D90) -> 0 | F84: =SUM(F85:F90) -> 0 | G84: =SUM(G85:G90) -> 0 | H84: =PPto[[#This Row],[Ppto. Capex '[DOP']]]+PPto[[#This Row],[Ppto. OI '[DOP']2]] -> 0 | I84: =SUM(I85:I90) -> 0 | J84: =SUM(J85:J90) -> 0 | K84: =PPto[[#This Row],[Ppto. Capex '[USD']]]+PPto[[#This Row],[Ppto. OI '[USD']]] -> 0
A85: 9.01 | B85: Gasto | C85: 9.01 COMERCIALIZACION | D85: =SUM(D86:D92) -> 0 | F85: =SUMIFS(BD.PD[Ppto. Orden Interna '[DOP']],BD.PD[Pos],PPto[[#This Row],[Part.]],BD.PD[Tipo Ppto],F$18) -> 0 | G85: =SUMIFS(BD.PD[Ppto. Orden Interna '[DOP']],BD.PD[Pos],PPto[[#This Row],[Part.]],BD.PD[Tipo Ppto],G$18) -> 0 | H85: =PPto[[#This Row],[Ppto. Capex '[DOP']]]+PPto[[#This Row],[Ppto. OI '[DOP']2]] -> 0 | I85: =SUMIFS(BD.PD[Ppto. Orden Interna '[USD']],BD.PD[Pos],PPto[[#This Row],[Part.]],BD.PD[Tipo Ppto],I$18) -> 0 | J85: =SUMIFS(BD.PD[Ppto. Orden Interna '[USD']],BD.PD[Pos],PPto[[#This Row],[Part.]],BD.PD[Tipo Ppto],J$18) -> 0 | K85: =PPto[[#This Row],[Ppto. Capex '[USD']]]+PPto[[#This Row],[Ppto. OI '[USD']]] -> 0
A86: 9.02 | B86: Gasto | C86: 9.02 INSUMOS | D86: =SUM(D87:D93) -> 0 | F86: =SUMIFS(BD.PD[Ppto. Orden Interna '[DOP']],BD.PD[Pos],PPto[[#This Row],[Part.]],BD.PD[Tipo Ppto],F$18) -> 0 | G86: =SUMIFS(BD.PD[Ppto. Orden Interna '[DOP']],BD.PD[Pos],PPto[[#This Row],[Part.]],BD.PD[Tipo Ppto],G$18) -> 0 | H86: =PPto[[#This Row],[Ppto. Capex '[DOP']]]+PPto[[#This Row],[Ppto. OI '[DOP']2]] -> 0 | I86: =SUMIFS(BD.PD[Ppto. Orden Interna '[USD']],BD.PD[Pos],PPto[[#This Row],[Part.]],BD.PD[Tipo Ppto],I$18) -> 0 | J86: =SUMIFS(BD.PD[Ppto. Orden Interna '[USD']],BD.PD[Pos],PPto[[#This Row],[Part.]],BD.PD[Tipo Ppto],J$18) -> 0 | K86: =PPto[[#This Row],[Ppto. Capex '[USD']]]+PPto[[#This Row],[Ppto. OI '[USD']]] -> 0
A87: 9.03 | B87: Gasto | C87: 9.03 PUBLICIDAD Y MERCADEO | D87: =SUM(D88:D94) -> 0 | F87: =SUMIFS(BD.PD[Ppto. Orden Interna '[DOP']],BD.PD[Pos],PPto[[#This Row],[Part.]],BD.PD[Tipo Ppto],F$18) -> 0 | G87: =SUMIFS(BD.PD[Ppto. Orden Interna '[DOP']],BD.PD[Pos],PPto[[#This Row],[Part.]],BD.PD[Tipo Ppto],G$18) -> 0 | H87: =PPto[[#This Row],[Ppto. Capex '[DOP']]]+PPto[[#This Row],[Ppto. OI '[DOP']2]] -> 0 | I87: =SUMIFS(BD.PD[Ppto. Orden Interna '[USD']],BD.PD[Pos],PPto[[#This Row],[Part.]],BD.PD[Tipo Ppto],I$18) -> 0 | J87: =SUMIFS(BD.PD[Ppto. Orden Interna '[USD']],BD.PD[Pos],PPto[[#This Row],[Part.]],BD.PD[Tipo Ppto],J$18) -> 0 | K87: =PPto[[#This Row],[Ppto. Capex '[USD']]]+PPto[[#This Row],[Ppto. OI '[USD']]] -> 0
A88: 9.04 | B88: Gasto | C88: 9.04 MONTAJE | D88: =SUM(D89:D95) -> 0 | F88: =SUMIFS(BD.PD[Ppto. Orden Interna '[DOP']],BD.PD[Pos],PPto[[#This Row],[Part.]],BD.PD[Tipo Ppto],F$18) -> 0 | G88: =SUMIFS(BD.PD[Ppto. Orden Interna '[DOP']],BD.PD[Pos],PPto[[#This Row],[Part.]],BD.PD[Tipo Ppto],G$18) -> 0 | H88: =PPto[[#This Row],[Ppto. Capex '[DOP']]]+PPto[[#This Row],[Ppto. OI '[DOP']2]] -> 0 | I88: =SUMIFS(BD.PD[Ppto. Orden Interna '[USD']],BD.PD[Pos],PPto[[#This Row],[Part.]],BD.PD[Tipo Ppto],I$18) -> 0 | J88: =SUMIFS(BD.PD[Ppto. Orden Interna '[USD']],BD.PD[Pos],PPto[[#This Row],[Part.]],BD.PD[Tipo Ppto],J$18) -> 0 | K88: =PPto[[#This Row],[Ppto. Capex '[USD']]]+PPto[[#This Row],[Ppto. OI '[USD']]] -> 0
A89: 9.05 | B89: Gasto | C89: 9.05 DECORACIÓN TEMPORADAS | D89: =SUM(D90:D96) -> 0 | F89: =SUMIFS(BD.PD[Ppto. Orden Interna '[DOP']],BD.PD[Pos],PPto[[#This Row],[Part.]],BD.PD[Tipo Ppto],F$18) -> 0 | G89: =SUMIFS(BD.PD[Ppto. Orden Interna '[DOP']],BD.PD[Pos],PPto[[#This Row],[Part.]],BD.PD[Tipo Ppto],G$18) -> 0 | H89: =PPto[[#This Row],[Ppto. Capex '[DOP']]]+PPto[[#This Row],[Ppto. OI '[DOP']2]] -> 0 | I89: =SUMIFS(BD.PD[Ppto. Orden Interna '[USD']],BD.PD[Pos],PPto[[#This Row],[Part.]],BD.PD[Tipo Ppto],I$18) -> 0 | J89: =SUMIFS(BD.PD[Ppto. Orden Interna '[USD']],BD.PD[Pos],PPto[[#This Row],[Part.]],BD.PD[Tipo Ppto],J$18) -> 0 | K89: =PPto[[#This Row],[Ppto. Capex '[USD']]]+PPto[[#This Row],[Ppto. OI '[USD']]] -> 0
A90: 9.06 | B90: Gasto | C90: 9.06 - | D90: =SUM(D91:D97) -> 0 | F90: =SUMIFS(BD.PD[Ppto. Orden Interna '[DOP']],BD.PD[Pos],PPto[[#This Row],[Part.]],BD.PD[Tipo Ppto],F$18) -> 0 | G90: =SUMIFS(BD.PD[Ppto. Orden Interna '[DOP']],BD.PD[Pos],PPto[[#This Row],[Part.]],BD.PD[Tipo Ppto],G$18) -> 0 | H90: =PPto[[#This Row],[Ppto. Capex '[DOP']]]+PPto[[#This Row],[Ppto. OI '[DOP']2]] -> 0 | I90: =SUMIFS(BD.PD[Ppto. Orden Interna '[USD']],BD.PD[Pos],PPto[[#This Row],[Part.]],BD.PD[Tipo Ppto],I$18) -> 0 | J90: =SUMIFS(BD.PD[Ppto. Orden Interna '[USD']],BD.PD[Pos],PPto[[#This Row],[Part.]],BD.PD[Tipo Ppto],J$18) -> 0 | K90: =PPto[[#This Row],[Ppto. Capex '[USD']]]+PPto[[#This Row],[Ppto. OI '[USD']]] -> 0

Sheet Presupuesto
B3: Presupuesto Las Terrenas
B5: 60 | G5: N/A
G6: Presupuesto
B7: TOTAL GENERAL ESTIMADO | G7: =SUM(G10:G12) -> 3776925.1
B9: Resumen de Partidas
B10: EDIFICACION | G10: =SUMIF($C$18:$C$102,"2",$G$18:$G$102) -> 810851.33
B11: EQUIPAMIENTO | G11: =SUMIF($C$18:$C$102,"1",$G$18:$G$102) -> 2966073.8
B12: TERRENO | G12: 0
B13: Área de la Localidad
B14: M2 Construccion
B15: M2 Sala de Ventas
B16: M2 Terreno
B17: Edificación, Instalaciones y Equipamientos
A18: 1 | B18: Estudios Preliminares | G18: =SUM(G19:G27) -> 0
A19: 1.01 | B19: Diseño arquitectónico | C19: 2 | D19: USD | E19: =IF(D19="USD",1,$B$5) -> 1 | F19: 0 | G19: =IF(D19="DOP",F19/E19,F19) -> 0
A20: 1.02 | B20: Diseño estructural | C20: 2 | D20: USD | E20: =IF(D20="USD",1,$B$5) -> 1 | F20: 0 | G20: =IF(D20="DOP",F20/E20,F20) -> 0
A21: 1.03 | B21: Diseño electromecánico | C21: 2 | D21: USD | E21: =IF(D21="USD",1,$B$5) -> 1 | F21: 0 | G21: =IF(D21="DOP",F21/E21,F21) -> 0
A22: 1.04 | B22: Diseño sanitario | C22: 2 | D22: USD | E22: =IF(D22="USD",1,$B$5) -> 1 | F22: 0 | G22: =IF(D22="DOP",F22/E22,F22) -> 0
A23: 1.08 | B23: Diseño sistema contra incendios | C23: 2 | D23: USD | E23: =IF(D23="USD",1,$B$5) -> 1 | F23: 0 | G23: =IF(D23="DOP",F23/E23,F23) -> 0
A24: 1.09 | B24: Diseño sistema gas | C24: 2 | D24: USD | E24: =IF(D24="USD",1,$B$5) -> 1 | F24: 0 | G24: =IF(D24="DOP",F24/E24,F24) -> 0
A25: 1.05 | B25: Estudio Geotécnico | C25: 2 | D25: USD | E25: =IF(D25="USD",1,$B$5) -> 1 | F25: 0 | G25: =IF(D25="DOP",F25/E25,F25) -> 0
A26: 1.06 | B26: Levantamiento topográfico | C26: 2 | D26: USD | E26: =IF(D26="USD",1,$B$5) -> 1 | F26: 0 | G26: =IF(D26="DOP",F26/E26,F26) -> 0
A27: 1.07 | B27: Permisos | C27: 2 | D27: USD | E27: =IF(D27="USD",1,$B$5) -> 1 | F27: 0 | G27: =IF(D27="DOP",F27/E27,F27) -> 0
A29: 2 | B29: Obra Civil | G29: =SUM(G30:G41) -> 287553.13
A30: 2.01 | B30: Edificación - Obra Civil | C30: 2 | D30: USD | E30: =IF(D30="USD",1,$B$5) -> 1 | F30: 0 | G30: 18449.15
A31: 2.02 | B31: Edificación - Estructura Metálica | C31: 2 | D31: dop | E31: =IF(D31="USD",1,$B$5) -> 60 | F31: 0 | G31: 0
A32: 2.03 | B32: Edificación - Techo S.S. y Cerramientos Multipanel | C32: 2 | D32: dop | E32: =IF(D32="USD",1,$B$5) -> 60 | F32: 0 | G32: 0
A33: 2.04 | B33: Edificación - Tragaluces "Skylights" | C33: 2 | D33: dop | E33: =IF(D33="USD",1,$B$5) -> 60 | F33: 0 | G33: 0
A34: 2.05 | B34: Instalaciones Sanitarias | C34: 2 | D34: dop | E34: =IF(D34="USD",1,$B$5) -> 60 | F34: 0 | G34: 25100
A35: 2.06 | B35: Instalación de Gas | C35: 2 | D35: dop | E35: =IF(D35="USD",1,$B$5) -> 60 | F35: 0 | G35: 7500
A36: 2.07 | B36: Sistema Contra Incendios | C36: 2 | D36: dop | E36: =IF(D36="USD",1,$B$5) -> 60 | F36: 0 | G36: 113206.86
A37: 2.08 | B37: Instalaciones Mecánicas | C37: 2 | D37: dop | E37: =IF(D37="USD",1,$B$5) -> 60 | F37: 0 | G37: 112643.09
A38: 2.09 | B38: Rejillas y Sumideros | C38: 2 | D38: dop | E38: =IF(D38="USD",1,$B$5) -> 60 | F38: 0 | G38: 10654.035
A39: 2.1 | B39: Supervisión Civil y Sanitaria | C39: 2 | D39: dop | E39: =IF(D39="USD",1,$B$5) -> 60 | F39: 0 | G39: 0
A40: 2.11 | B40: Supervisión Arquitectónica | C40: 2 | D40: dop | E40: =IF(D40="USD",1,$B$5) -> 60 | F40: 0 | G40: 0
A42: 3 | B42: Sistema Eléctrico | G42: =SUBTOTAL(9,G43:G47) -> 235851.53
A43: 3.01 | B43: Instalaciones Eléctricas | C43: 2 | D43: USD | E43: =IF(D43="USD",1,$B$5) -> 1 | F43: 0 | G43: 0
A44: 3.02 | B44: Supervisión Eléctrica | C44: 2 | D44: dop | E44: =IF(D44="USD",1,$B$5) -> 60 | F44: 0 | G44: 0
A45: 3.03 | B45: Generadores | C45: 2 | D45: dop | E45: =IF(D45="USD",1,$B$5) -> 60 | F45: 0 | G45: 220508.5
A46: 3.04 | B46: Inversor y UPS | C46: 2 | D46: dop | E46: =IF(D46="USD",1,$B$5) -> 60 | F46: 0 | G46: 15343.026
A48: 4 | B48: Sistema de Climatización | G48: =SUM(G49:G52) -> 287446.67
A49: 4.01 | B49: Suministro e instalación de Equipos | C49: 2 | D49: USD | E49: =IF(D49="USD",1,$B$5) -> 1 | F49: 0 | G49: 252156.92
A50: 4.02 | B50: Supervisión Mecánica | C50: 2 | D50: dop | E50: =IF(D50="USD",1,$B$5) -> 60 | F50: 0 | G50: 0
A51: 4.03 | B51: Sistema de Extracción cocina | C51: 2 | D51: dop | E51: =IF(D51="USD",1,$B$5) -> 60 | F51: 0 | G51: 35289.75
A53: 5 | B53: Frio Alimentario | G53: =SUM(G54:G61) -> 1424274.2
A54: 5.01 | B54: Paneles | C54: 1 | D54: USD | E54: =IF(D54="USD",1,$B$5) -> 1 | F54: 0 | G54: 201600
A55: 5.02 | B55: FRP y Diamond Plate | C55: 1 | D55: dop | E55: =IF(D55="USD",1,$B$5) -> 60 | F55: 0 | G55: 42000
A56: 5.03 | B56: Neveras, Centrales y Evaporadores | C56: 1 | D56: dop | E56: =IF(D56="USD",1,$B$5) -> 60 | F56: 0 | G56: 779725.25
A57: 5.04 | B57: Bumpers Mcue | C57: 1 | D57: dop | E57: =IF(D57="USD",1,$B$5) -> 60 | F57: 0 | G57: 27571.7
A58: 5.05 | B58: Trameria Cuarto Frio | C58: 1 | D58: dop | E58: =IF(D58="USD",1,$B$5) -> 60 | F58: 0 | G58: 40175.556
A59: 5.06 | B59: Instalacion Frio Alimentario | C59: 1 | D59: dop | E59: =IF(D59="USD",1,$B$5) -> 60 | F59: 0 | G59: 273866.17
A60: 5.07 | B60: Chase Doors | C60: 1 | D60: dop | E60: =IF(D60="USD",1,$B$5) -> 60 | F60: 0 | G60: 59335.5
A62: 6 | B62: Tecnología, Seguridad y Tesorería | G62: =SUM(G63:G70) -> 29917.109
A63: 6.01 | B63: Sistema de cámaras CCTV | C63: 1 | D63: USD | E63: =IF(D63="USD",1,$B$5) -> 1 | F63: 0 | G63: 0
A64: 6.02 | B64: Antenas detección de robo | C64: 1 | D64: dop | E64: =IF(D64="USD",1,$B$5) -> 60 | F64: 0 | G64: 0
A65: 6.03 | B65: Puntos de Venta | C65: 1 | D65: dop | E65: =IF(D65="USD",1,$B$5) -> 60 | F65: 0 | G65: 0
A66: 6.04 | B66: Instalación de data y voz / Antenas de techo | C66: 1 | D66: dop | E66: =IF(D66="USD",1,$B$5) -> 60 | F66: 0 | G66: 0
A67: 6.05 | B67: Otros sum e inst Tecnología | C67: 1 | D67: dop | E67: =IF(D67="USD",1,$B$5) -> 60 | F67: 0 | G67: 29917.109
A68: 6.06 | B68: Otros sum e inst Seguridad | C68: 1 | D68: dop | E68: =IF(D68="USD",1,$B$5) -> 60 | F68: 0 | G68: 0
A69: 6.07 | B69: Otros sum e inst Tesoreria | C69: 1 | D69: dop | E69: =IF(D69="USD",1,$B$5) -> 60 | F69: 0 | G69: =IF(D69="DOP",F69/E69,F69) -> 0
A71: 7 | B71: Equipamiento Produccion | G71: =SUM(G72:G79) -> 527065.66
A72: 7.01 | B72: Equipamiento de Acero Inoxidable | C72: 1 | D72: USD | E72: =IF(D72="USD",1,$B$5) -> 1 | F72: 0 | G72: 24826.933
A73: 7.02 | B73: Cocina, Patio Comidas y Rostizería | C73: 1 | D73: dop | E73: =IF(D73="USD",1,$B$5) -> 60 | F73: 0 | G73: 57974.172
A74: 7.03 | B74: Equipamiento Carniceria, Pescadería y Delicatesen | C74: 1 | D74: dop | E74: =IF(D74="USD",1,$B$5) -> 60 | F74: 0 | G74: 113048.4
A75: 7.04 | B75: Equipamiento de Panaderia, Reposteria y Rosticería | C75: 1 | D75: dop | E75: =IF(D75="USD",1,$B$5) -> 60 | F75: 0 | G75: 270980.86
A76: 7.05 | B76: Equipamiento de Frutas y Vegetales | C76: 1 | D76: dop | E76: =IF(D76="USD",1,$B$5) -> 60 | F76: 0 | G76: 60235.302
A77: 7.06 | B77: Balanzas | C77: 1 | D77: dop | E77: =IF(D77="USD",1,$B$5) -> 60 | F77: 0 | G77: 0
A78: 7.07 | B78: Otros Equipamientos de Producción | C78: 1 | D78: dop | E78: =IF(D78="USD",1,$B$5) -> 60 | F78: 0 | G78: 0
A80: 8 | B80: Equipamiento Tienda | G80: =SUM(G81:G89) -> 984816.84
A81: 8.01 | B81: Gondolas | C81: 1 | D81: dop | E81: =IF(D81="USD",1,$B$5) -> 60 | F81: 0 | G81: 387226.84
A82: 8.02 | B82: Checkout | C82: 1 | D82: dop | E82: =IF(D82="USD",1,$B$5) -> 60 | F82: 0 | G82: 40802.583
A83: 8.03 | B83: Carritos, Canastas y Accesorios | C83: 1 | D83: dop | E83: =IF(D83="USD",1,$B$5) -> 60 | F83: 0 | G83: 46216.86
A84: 8.04 | B84: Trameria Almacen | C84: 1 | D84: dop | E84: =IF(D84="USD",1,$B$5) -> 60 | F84: 0 | G84: 56151.295
A85: 8.05 | B85: Mobiliario no operacional para Tiendas | C85: 1 | D85: dop | E85: =IF(D85="USD",1,$B$5) -> 60 | F85: 0 | G85: 109926.56
A86: 8.06 | B86: Otros Equipamientos de Tienda | C86: 1 | D86: dop | E86: =IF(D86="USD",1,$B$5) -> 60 | F86: 0 | G86: 57105.167
A87: 8.07 | B87: Señalizacion interiores | C87: 1 | D87: dop | E87: =IF(D87="USD",1,$B$5) -> 60 | F87: 0 | G87: 203468.25
A88: 8.08 | B88: Señalizacion exteriores | C88: 1 | D88: dop | E88: =IF(D88="USD",1,$B$5) -> 60 | F88: 0 | G88: 83919.283
A90: 9 | B90: Otros | G90: =SUM(G91:G95) -> 0
A91: 9.01 | B91: COMERCIALIZACION | C91: 2 | D91: USD | E91: =IF(D91="USD",1,$B$5) -> 1 | F91: 0 | G91: =IF(D91="DOP",F91/E91,F91) -> 0
A92: 9.02 | B92: INSUMOS | C92: 2 | D92: USD | E92: =IF(D92="USD",1,$B$5) -> 1 | F92: 0 | G92: =IF(D92="DOP",F92/E92,F92) -> 0
A93: 9.03 | B93: PUBLICIDAD Y MERCADEO | C93: 2 | D93: USD | E93: =IF(D93="USD",1,$B$5) -> 1 | F93: 0 | G93: =IF(D93="DOP",F93/E93,F93) -> 0
A94: 9.04 | B94: MONTAJE | C94: 2 | D94: USD | E94: =IF(D94="USD",1,$B$5) -> 1 | F94: 0 | G94: =IF(D94="DOP",F94/E94,F94) -> 0
A95: 9.05 | B95: DECORACIÓN TEMPORADAS | C95: 2 | D95: USD | E95: =IF(D95="USD",1,$B$5) -> 1 | F95: 0 | G95: =IF(D95="DOP",F95/E95,F95) -> 0
A96: 9.06 | B96: - | C96: 2 | D96: USD | E96: =IF(D96="USD",1,$B$5) -> 1 | F96: 0 | G96: =IF(D96="DOP",F96/E96,F96) -> 0

Sheet Presupuesto vs Real
B3: Presupuesto Terrenas MC33
K4: Optimización del presupuesto
B5: 60 | G5: N/A | H5: N/A | K5: =+I7*59 -> 1.3872683e+10
G6: Presupuestado | H6: Real | I6: Diferencia
B7: TOTAL GENERAL ESTIMADO | G7: 2.3889382e+08 | H7: =SUM(H10:H12) -> 3763601.6 | I7: =+G7-H7 -> 2.3513022e+08
B9: Resumen de Partidas
B10: EDIFICACION | G10: 2.3796806e+08 | H10: =SUMIF($C$18:$C$100,"2",H18:H94) -> 1222167.5
B11: EQUIPAMIENTO | G11: 925759.13 | H11: =SUMIF($C$18:$C$100,"1",H18:H94) -> 2541434.1
B12: TERRENO | G12: 0 | H12: 0
B13: Área de la Localidad
B14: M2 Construccion
B15: M2 Sala de Ventas
B16: M2 Terreno
B17: Edificación, Instalaciones y Equipamientos
A18: 1 | B18: Estudios Preliminares | G18: =SUM(G19:G27) -> 0 | H18: =SUM(H19:H27) -> 0 | I18: =SUM(I19:I27) -> 0
A19: 1.01 | B19: Diseño arquitectónico | C19: 2 | D19: USD | E19: =IF(D19="USD",1,$B$5) -> 1 | F19: 0 | G19: =IF(D19="DOP",F19/E19,F19) -> 0 | H19: =IF(E19="DOP",G19/F19,G19) -> 0 | I19: =IF(F19="DOP",H19/G19,H19) -> 0
A20: 1.02 | B20: Diseño estructural | C20: 2 | D20: USD | E20: =IF(D20="USD",1,$B$5) -> 1 | F20: 0 | G20: =IF(D20="DOP",F20/E20,F20) -> 0 | H20: =IF(E20="DOP",G20/F20,G20) -> 0 | I20: =IF(F20="DOP",H20/G20,H20) -> 0
A21: 1.03 | B21: Diseño electromecánico | C21: 2 | D21: USD | E21: =IF(D21="USD",1,$B$5) -> 1 | F21: 0 | G21: =IF(D21="DOP",F21/E21,F21) -> 0 | H21: =IF(E21="DOP",G21/F21,G21) -> 0 | I21: =IF(F21="DOP",H21/G21,H21) -> 0
A22: 1.04 | B22: Diseño sanitario | C22: 2 | D22: USD | E22: =IF(D22="USD",1,$B$5) -> 1 | F22: 0 | G22: =IF(D22="DOP",F22/E22,F22) -> 0 | H22: =IF(E22="DOP",G22/F22,G22) -> 0 | I22: =IF(F22="DOP",H22/G22,H22) -> 0
A23: 1.08 | B23: Diseño sistema contra incendios | C23: 2 | D23: USD | E23: =IF(D23="USD",1,$B$5) -> 1 | F23: 0 | G23: =IF(D23="DOP",F23/E23,F23) -> 0 | H23: =IF(E23="DOP",G23/F23,G23) -> 0 | I23: =IF(F23="DOP",H23/G23,H23) -> 0
A24: 1.09 | B24: Diseño sistema gas | C24: 2 | D24: USD | E24: =IF(D24="USD",1,$B$5) -> 1 | F24: 0 | G24: =IF(D24="DOP",F24/E24,F24) -> 0 | H24: =IF(E24="DOP",G24/F24,G24) -> 0 | I24: =IF(F24="DOP",H24/G24,H24) -> 0
A25: 1.05 | B25: Estudio Geotécnico | C25: 2 | D25: USD | E25: =IF(D25="USD",1,$B$5) -> 1 | F25: 0 | G25: =IF(D25="DOP",F25/E25,F25) -> 0 | H25: =IF(E25="DOP",G25/F25,G25) -> 0 | I25: =IF(F25="DOP",H25/G25,H25) -> 0
A26: 1.06 | B26: Levantamiento topográfico | C26: 2 | D26: USD | E26: =IF(D26="USD",1,$B$5) -> 1 | F26: 0 | G26: =IF(D26="DOP",F26/E26,F26) -> 0 | H26: =IF(E26="DOP",G26/F26,G26) -> 0 | I26: =IF(F26="DOP",H26/G26,H26) -> 0
A27: 1.07 | B27: Permisos | C27: 2 | D27: USD | E27: =IF(D27="USD",1,$B$5) -> 1 | F27: 0 | G27: =IF(D27="DOP",F27/E27,F27) -> 0 | H27: =IF(E27="DOP",G27/F27,G27) -> 0 | I27: =IF(F27="DOP",H27/G27,H27) -> 0
I28: =IF(F28="DOP",H28/G28,H28) -> 0
A29: 2 | B29: Obra Civil | G29: =SUM(G30:G41) -> 18750294 | H29: =SUM(H30:H41) -> 480987.92
A30: 2.01 | B30: Edificación - Obra Civil | C30: 2 | D30: USD | E30: =IF(D30="USD",1,$B$5) -> 1 | F30: 20484.94 | G30: 925759.13 | H30: 116087.61 | I30: =+G30-H30 -> 809671.52
A31: 2.02 | B31: Edificación - Estructura Metálica | C31: 2 | D31: USD | E31: =IF(D31="USD",1,$B$5) -> 1 | F31: 0 | G31: =IF(D31="DOP",F31/E31,F31) -> 0 | H31: 0 | I31: =+G31-H31 -> 0
A32: 2.03 | B32: Edificación - Techo S.S. y Cerramientos Multipanel | C32: 2 | D32: USD | E32: =IF(D32="USD",1,$B$5) -> 1 | F32: 0 | G32: =IF(D32="DOP",F32/E32,F32) -> 0 | H32: 0 | I32: =+G32-H32 -> 0
A33: 2.04 | B33: Edificación - Tragaluces "Skylights" | C33: 2 | D33: USD | E33: =IF(D33="USD",1,$B$5) -> 1 | F33: 0 | G33: =IF(D33="DOP",F33/E33,F33) -> 0 | H33: 0 | I33: =+G33-H33 -> 0
A34: 2.05 | B34: Instalaciones Sanitarias | C34: 2 | D34: USD | E34: =IF(D34="USD",1,$B$5) -> 1 | F34: 25100 | G34: 945223.71 | H34: 15495.471 | I34: =+G34-H34 -> 929728.24
A35: 2.06 | B35: Instalación de Gas | C35: 2 | D35: USD | E35: =IF(D35="USD",1,$B$5) -> 1 | F35: 7330.6452 | G35: 550000 | H35: 10964.705 | I35: =+G35-H35 -> 539035.3
A36: 2.07 | B36: Sistema Contra Incendios | C36: 2 | D36: USD | E36: =IF(D36="USD",1,$B$5) -> 1 | F36: 114712.49 | G36: 7031433.7 | H36: 93062.165 | I36: =+G36-H36 -> 6938371.6
A37: 2.08 | B37: Instalaciones Mecánicas | C37: 2 | D37: USD | E37: =IF(D37="USD",1,$B$5) -> 1 | F37: 80483.865 | G37: 8626672.8 | H37: 234532.97 | I37: =+G37-H37 -> 8392139.8
A38: 2.09 | B38: Rejillas y Sumideros | C38: 2 | D38: USD | E38: =IF(D38="USD",1,$B$5) -> 1 | F38: 12639.2 | G38: 671204.2 | H38: 10844.99 | I38: =+G38-H38 -> 660359.21
A39: 2.1 | B39: Supervisión Civil y Sanitaria | C39: 2 | D39: USD | E39: =IF(D39="USD",1,$B$5) -> 1 | F39: 0 | G39: =IF(D39="DOP",F39/E39,F39) -> 0 | H39: 0 | I39: =+G39-H39 -> 0
A40: 2.11 | B40: Supervisión Arquitectónica | C40: 2 | D40: USD | E40: =IF(D40="USD",1,$B$5) -> 1 | F40: 0 | G40: =IF(D40="DOP",F40/E40,F40) -> 0 | H40: 0 | I40: =+G40-H40 -> 0
I41: =+G41-H41 -> 0
A42: 3 | B42: Sistema Eléctrico | G42: =SUBTOTAL(9,G43:G47) -> 15163842 | H42: =SUBTOTAL(9,H43:H47) -> 447825.63
A43: 3.01 | B43: Instalaciones Eléctricas | C43: 2 | D43: USD | E43: =IF(D43="USD",1,$B$5) -> 1 | F43: 0 | G43: =IF(D43="DOP",F43/E43,F43) -> 0 | H43: 259705.61 | I43: =+G43-H43 -> -259705.61
A44: 3.02 | B44: Supervisión Eléctrica | C44: 2 | D44: USD | E44: =IF(D44="USD",1,$B$5) -> 1 | F44: 0 | G44: =IF(D44="DOP",F44/E44,F44) -> 0 | H44: 0 | I44: =+G44-H44 -> 0
A45: 3.03 | B45: Generadores | C45: 2 | D45: USD | E45: =IF(D45="USD",1,$B$5) -> 1 | F45: 165254.22 | G45: 14002290 | H45: 165254.22 | I45: =+G45-H45 -> 13837036
A46: 3.04 | B46: Inversor y UPS | C46: 2 | D46: USD | E46: =IF(D46="USD",1,$B$5) -> 1 | F46: 15453.026 | G46: 1161551.9 | H46: 22865.8 | I46: =+G46-H46 -> 1138686.1
I47: =+G47-H47 -> 0
A48: 4 | B48: Sistema de Climatización | G48: =SUM(G49:G52) -> 18184969 | H48: =SUM(H49:H52) -> 293353.96
A49: 4.01 | B49: Suministro e instalación de Equipos | C49: 2 | D49: USD | E49: =IF(D49="USD",1,$B$5) -> 1 | F49: 237554.27 | G49: 15961715 | H49: 261667.45 | I49: =+G49-H49 -> 15700047
A50: 4.02 | B50: Supervisión Mecánica | C50: 2 | D50: USD | E50: =IF(D50="USD",1,$B$5) -> 1 | F50: 0 | G50: 0 | H50: 0 | I50: =+G50-H50 -> 0
A51: 4.03 | B51: Sistema de Extracción cocina | C51: 2 | D51: USD | E51: =IF(D51="USD",1,$B$5) -> 1 | F51: 19149.985 | G51: 2223254.2 | H51: 31686.507 | I51: =+G51-H51 -> 2191567.7
I52: =+G52-H52 -> 0
A53: 5 | B53: Frio Alimentario | G53: =SUM(G54:G61) -> 88672240 | H53: =SUM(H54:H61) -> 1089166.9
A54: 5.01 | B54: Paneles | C54: 1 | D54: USD | E54: =IF(D54="USD",1,$B$5) -> 1 | F54: 178665.78 | G54: 12801600 | H54: 122690.29 | I54: =+G54-H54 -> 12678910
A55: 5.02 | B55: FRP y Diamond Plate | C55: 1 | D55: USD | E55: =IF(D55="USD",1,$B$5) -> 1 | F55: 32571.347 | G55: 2667000 | H55: 28969.56 | I55: =+G55-H55 -> 2638030.4
A56: 5.03 | B56: Neveras, Centrales y Evaporadores | C56: 1 | D56: USD | E56: =IF(D56="USD",1,$B$5) -> 1 | F56: 522416.38 | G56: 47209739 | H56: 671606.35 | I56: =+G56-H56 -> 46538133
A57: 5.04 | B57: Bumpers Mcue | C57: 1 | D57: USD | E57: =IF(D57="USD",1,$B$5) -> 1 | F57: 28768.6 | G57: 2279596.8 | H57: 40822.369 | I57: =+G57-H57 -> 2238774.4
A58: 5.05 | B58: Trameria Cuarto Frio | C58: 1 | D58: USD | E58: =IF(D58="USD",1,$B$5) -> 1 | F58: 37387.097 | G58: 2577520 | H58: 42182.551 | I58: =+G58-H58 -> 2535337.4
A59: 5.06 | B59: Instalacion Frio Alimentario | C59: 1 | D59: USD | E59: =IF(D59="USD",1,$B$5) -> 1 | F59: 173670.97 | G59: 17368980 | H59: 100454.86 | I59: =+G59-H59 -> 17268525
A60: 5.07 | B60: Chase Doors | C60: 1 | D60: USD | E60: =IF(D60="USD",1,$B$5) -> 1 | F60: 52527.65 | G60: 3767804.2 | H60: 82440.88 | I60: =+G60-H60 -> 3685363.4
A62: 6 | B62: Tecnología, Seguridad y Tesorería | G62: =SUM(G63:G68) -> 1892118.5 | H62: =SUM(H63:H68) -> 33656.133
A63: 6.01 | B63: Sistema de cámaras CCTV | C63: 1 | D63: USD | E63: =IF(D63="USD",1,$B$5) -> 1 | F63: 0 | G63: =IF(D63="DOP",F63/E63,F63) -> 0 | H63: =IF(E63="DOP",G63/F63,G63) -> 0
A64: 6.02 | B64: Antenas detección de robo | C64: 1 | D64: USD | E64: =IF(D64="USD",1,$B$5) -> 1 | F64: 0 | G64: =IF(D64="DOP",F64/E64,F64) -> 0 | H64: =IF(E64="DOP",G64/F64,G64) -> 0
A65: 6.03 | B65: Puntos de Venta | C65: 1 | D65: USD | E65: =IF(D65="USD",1,$B$5) -> 1 | F65: 0 | G65: =IF(D65="DOP",F65/E65,F65) -> 0 | H65: =IF(E65="DOP",G65/F65,G65) -> 0
A66: 6.04 | B66: Instalación de data y voz / Antenas de techo | C66: 1 | D66: USD | E66: =IF(D66="USD",1,$B$5) -> 1 | F66: 0 | G66: =IF(D66="DOP",F66/E66,F66) -> 0 | H66: =IF(E66="DOP",G66/F66,G66) -> 0
A67: 6.05 | B67: Otros sum e inst Tecnología | C67: 1 | D67: USD | E67: =IF(D67="USD",1,$B$5) -> 1 | F67: 38599.893 | G67: 1892118.5 | H67: 33656.133
A69: 7 | B69: Equipamiento Produccion | G69: =SUM(G70:G77) -> 35127061 | H69: =SUM(H70:H77) -> 599060.58
A70: 7.01 | B70: Equipamiento de Acero Inoxidable | C70: 1 | D70: USD | E70: =IF(D70="USD",1,$B$5) -> 1 | F70: 30862.977 | G70: 1564096.8 | H70: 31279.652 | I70: =+G70-H70 -> 1532817.1
A71: 7.02 | B71: Cocina, Patio Comidas y Rostizería | C71: 1 | D71: USD | E71: =IF(D71="USD",1,$B$5) -> 1 | F71: 74153.175 | G71: 3671404.4 | H71: 46529.653 | I71: =+G71-H71 -> 3624874.8
A72: 7.03 | B72: Equipamiento Carniceria, Pescadería y Delicatesen | C72: 1 | D72: USD | E72: =IF(D72="USD",1,$B$5) -> 1 | F72: 54138.493 | G72: 6561284.5 | H72: 61838.289 | I72: =+G72-H72 -> 6499446.2
A73: 7.04 | B73: Equipamiento de Panaderia, Reposteria y Rosticería | C73: 1 | D73: USD | E73: =IF(D73="USD",1,$B$5) -> 1 | F73: 163010.11 | G73: 18932010 | H73: 328015.74 | I73: =+G73-H73 -> 18603994
A74: 7.05 | B74: Equipamiento de Frutas y Vegetales | C74: 1 | D74: USD | E74: =IF(D74="USD",1,$B$5) -> 1 | F74: 64605.327 | G74: 4398264.6 | H74: 4772.177 | I74: =+G74-H74 -> 4393492.5
A75: 7.06 | B75: Balanzas | C75: 1 | D75: USD | E75: =IF(D75="USD",1,$B$5) -> 1 | F75: 0 | G75: =IF(D75="DOP",F75/E75,F75) -> 0 | H75: 0 | I75: =+G75-H75 -> 0
A76: 7.07 | B76: Otros Equipamientos de Producción | C76: 1 | D76: USD | E76: =IF(D76="USD",1,$B$5) -> 1 | F76: 0 | G76: =IF(D76="DOP",F76/E76,F76) -> 0 | H76: 126625.07 | I76: =+G76-H76 -> -126625.07
I77: =+G77-H77 -> 0
A78: 8 | B78: Equipamiento Tienda | G78: =SUM(G79:G87) -> 61103295 | H78: =SUM(H79:H87) -> 819550.49
A79: 8.01 | B79: Gondolas | C79: 1 | D79: USD | E79: =IF(D79="USD",1,$B$5) -> 1 | F79: 354682.58 | G79: 24539351 | H79: 367090.34 | I79: =+G79-H79 -> 24172261
A80: 8.02 | B80: Checkout | C80: 1 | D80: USD | E80: =IF(D80="USD",1,$B$5) -> 1 | F80: 32090.255 | G80: 2797707.4 | H80: 43166.169 | I80: =+G80-H80 -> 2754541.2
A81: 8.03 | B81: Carritos, Canastas y Accesorios | C81: 1 | D81: USD | E81: =IF(D81="USD",1,$B$5) -> 1 | F81: 49180.035 | G81: 2911662.2 | H81: 78561.027 | I81: =+G81-H81 -> 2833101.2
A82: 8.04 | B82: Trameria Almacen | C82: 1 | D82: USD | E82: =IF(D82="USD",1,$B$5) -> 1 | F82: 52592.266 | G82: 2689780.6 | H82: 5475.5738 | I82: =+G82-H82 -> 2684305
A83: 8.05 | B83: Mobiliario no operacional para Tiendas | C83: 1 | D83: USD | E83: =IF(D83="USD",1,$B$5) -> 1 | F83: 107865.25 | G83: 7083153.4 | H83: 51563.557 | I83: =+G83-H83 -> 7031589.9
A84: 8.06 | B84: Otros Equipamientos de Tienda | C84: 1 | D84: USD | E84: =IF(D84="USD",1,$B$5) -> 1 | F84: 44922.766 | G84: 2951475.5 | H84: 80296.942 | I84: =+G84-H84 -> 2871178.6
A85: 8.07 | B85: Señalizacion interiores | C85: 1 | D85: USD | E85: =IF(D85="USD",1,$B$5) -> 1 | F85: 124637.78 | G85: 12843250 | H85: 118966.06 | I85: =+G85-H85 -> 12724284
A86: 8.08 | B86: Señalizacion exteriores | C86: 1 | D86: USD | E86: =IF(D86="USD",1,$B$5) -> 1 | F86: 71661.29 | G86: 5286914.9 | H86: 74430.813 | I86: =+G86-H86 -> 5212484
I87: =+G87-H87 -> 0
A88: 9 | B88: Otros | G88: =SUM(G89:G93) -> 0 | H88: =SUM(H89:H93) -> 0
A89: 9.01 | B89: COMERCIALIZACION | C89: 2 | D89: USD | E89: =IF(D89="USD",1,$B$5) -> 1 | F89: 0 | G89: =IF(D89="DOP",F89/E89,F89) -> 0 | H89: =IF(E89="DOP",G89/F89,G89) -> 0
A90: 9.02 | B90: INSUMOS | C90: 2 | D90: USD | E90: =IF(D90="USD",1,$B$5) -> 1 | F90: 0 | G90: =IF(D90="DOP",F90/E90,F90) -> 0 | H90: =IF(E90="DOP",G90/F90,G90) -> 0
A91: 9.03 | B91: PUBLICIDAD Y MERCADEO | C91: 2 | D91: USD | E91: =IF(D91="USD",1,$B$5) -> 1 | F91: 0 | G91: =IF(D91="DOP",F91/E91,F91) -> 0 | H91: =IF(E91="DOP",G91/F91,G91) -> 0
A92: 9.04 | B92: MONTAJE | C92: 2 | D92: USD | E92: =IF(D92="USD",1,$B$5) -> 1 | F92: 0 | G92: =IF(D92="DOP",F92/E92,F92) -> 0 | H92: =IF(E92="DOP",G92/F92,G92) -> 0
A93: 9.05 | B93: DECORACIÓN TEMPORADAS | C93: 2 | D93: USD | E93: =IF(D93="USD",1,$B$5) -> 1 | F93: 0 | G93: =IF(D93="DOP",F93/E93,F93) -> 0 | H93: =IF(E93="DOP",G93/F93,G93) -> 0
A94: 9.06 | B94: - | C94: 2 | D94: USD | E94: =IF(D94="USD",1,$B$5) -> 1 | F94: 0 | G94: =IF(D94="DOP",F94/E94,F94) -> 0 | H94: =IF(E94="DOP",G94/F94,G94) -> 0

Sheet BD Plan Detallado
A1: Plan Detallado: Iniciativa Las Terrenas | K1: USD | L1: EUR | R1: Capex | W1: *** Per.P es igual al numero de mes, iniciando en Mayo 2023 como el mes (1) | AL1: Rojo: La sumatoria de pagos no coincide con Ppto.
A2: 46302 | J2: Tasa | K2: 61 | L2: 72 | R2: OI | W2: Planificación de Pagos por Partida
D3: OI / Capex | P3: =SUBTOTAL(109,BD.PD[Ppto. Orden Interna '[DOP']]) -> 2.3665605e+08 | Q3: =SUBTOTAL(109,BD.PD[Ppto. Orden Interna '[USD']]) -> 3879607.3 | W3: 1er Pago | Z3: 2do Pago | AC3: 3er Pago | AF3: 4to Pago | AI3: 5to Pago
A4: Pos | B4: . | C4: Partidas | D4: Tipo Ppto | E4: Plan | F4: Item | G4: Etapa | H4: Orden de compra | I4: Comentarios | J4: Fecha | K4: Cant. | L4: Mon | M4: Tasa | N4: Precio Und. | O4: Valor Neto [DOP] | P4: Liquid. [%] | Q4: Ppto. Orden Interna [DOP] | R4: Ppto. Orden Interna [USD] | S4: Comentario | T4: Notas | U4: Orden Interna | V4: AFeC | W4: Proveedor | X4: Per.P1 | Y4: Av.P1 [%] | Z4: Pago 1 | AA4: Per.P2 | AB4: Av.P2 [%] | AC4: Pago 2 | AD4: Per.P3 | AE4: Av.P3 [%] | AF4: Pago 3 | AG4: Per.P4 | AH4: Av.P4 [%] | AI4: Pago 4 | AJ4: Per.P5 | AK4: Av.P5 [%] | AL4: Pago 5 | AM4: Total Flujo Caja | AN4: Formato | AO4: Tienda | AP4: Nomenclatura | AQ4: Closter | AR4: Iniciativa | AS4: Status
A5: 1.01 | B5: * | C5: =VLOOKUP(BD.PD[[#This Row],[Pos]],PPto[],3,FALSE) -> 1.01 Diseño arquitectónico | D5: * | E5: =IF(BD.PD[[#This Row],[.]]="*",VLOOKUP(BD.PD[[#This Row],[Pos]],Presupuesto!A:H,7,FALSE),"") -> 0 | K5: 1 | L5: USD | M5: =IF(BD.PD[[#This Row],[Mon]]="DOP",1,HLOOKUP(BD.PD[[#This Row],[Mon]],$K$1:$L$2,2,FALSE)) -> 61 | N5: 0 | O5: =BD.PD[[#This Row],[Cant.]]*BD.PD[[#This Row],[ Tasa ]]*BD.PD[[#This Row],[ Precio Und.]] -> 0 | P5: 0 | Q5: =IF(BD.PD[[#This Row],[Liquid. '[%']]]<>0,(BD.PD[[#This Row],[Valor Neto '[DOP']]]*BD.PD[[#This Row],[Liquid. '[%']]])+BD.PD[[#This Row],[Valor Neto '[DOP']]],BD.PD[[#This Row],[Valor Neto '[DOP']]]) -> 0 | R5: =BD.PD[[#This Row],[Ppto. Orden Interna '[DOP']]]/HLOOKUP("USD",$K$1:$L$2,2,FALSE) -> 0 | Z5: =BD.PD[[#This Row],[Av.P1 '[%']]]*BD.PD[[#This Row],[Ppto. Orden Interna '[DOP']]] -> 0 | AC5: =BD.PD[[#This Row],[Av.P2 '[%']]]*BD.PD[[#This Row],[Ppto. Orden Interna '[DOP']]] -> 0 | AF5: =BD.PD[[#This Row],[Av.P3 '[%']]]*BD.PD[[#This Row],[Ppto. Orden Interna '[DOP']]] -> 0 | AM5: =BD.PD[[#This Row],[Pago 3]]+BD.PD[[#This Row],[Pago 2]]+BD.PD[[#This Row],[Pago 1]] -> 0
A6: 1.02 | B6: * | C6: =VLOOKUP(BD.PD[[#This Row],[Pos]],PPto[],3,FALSE) -> 1.02 Diseño estructural | D6: * | E6: =IF(BD.PD[[#This Row],[.]]="*",VLOOKUP(BD.PD[[#This Row],[Pos]],Presupuesto!A:H,7,FALSE),"") -> 0 | K6: 1 | L6: USD | M6: =IF(BD.PD[[#This Row],[Mon]]="DOP",1,HLOOKUP(BD.PD[[#This Row],[Mon]],$K$1:$L$2,2,FALSE)) -> 61 | N6: 0 | O6: =BD.PD[[#This Row],[Cant.]]*BD.PD[[#This Row],[ Tasa ]]*BD.PD[[#This Row],[ Precio Und.]] -> 0 | P6: 0 | Q6: =IF(BD.PD[[#This Row],[Liquid. '[%']]]<>0,(BD.PD[[#This Row],[Valor Neto '[DOP']]]*BD.PD[[#This Row],[Liquid. '[%']]])+BD.PD[[#This Row],[Valor Neto '[DOP']]],BD.PD[[#This Row],[Valor Neto '[DOP']]]) -> 0 | R6: =BD.PD[[#This Row],[Ppto. Orden Interna '[DOP']]]/HLOOKUP("USD",$K$1:$L$2,2,FALSE) -> 0 | Z6: =BD.PD[[#This Row],[Av.P1 '[%']]]*BD.PD[[#This Row],[Ppto. Orden Interna '[DOP']]] -> 0 | AC6: =BD.PD[[#This Row],[Av.P2 '[%']]]*BD.PD[[#This Row],[Ppto. Orden Interna '[DOP']]] -> 0 | AF6: =BD.PD[[#This Row],[Av.P3 '[%']]]*BD.PD[[#This Row],[Ppto. Orden Interna '[DOP']]] -> 0 | AM6: =BD.PD[[#This Row],[Pago 3]]+BD.PD[[#This Row],[Pago 2]]+BD.PD[[#This Row],[Pago 1]] -> 0
A7: 1.03 | B7: * | C7: =VLOOKUP(BD.PD[[#This Row],[Pos]],PPto[],3,FALSE) -> 1.03 Diseño electromecánico | D7: * | E7: =IF(BD.PD[[#This Row],[.]]="*",VLOOKUP(BD.PD[[#This Row],[Pos]],Presupuesto!A:H,7,FALSE),"") -> 0 | K7: 1 | L7: USD | M7: =IF(BD.PD[[#This Row],[Mon]]="DOP",1,HLOOKUP(BD.PD[[#This Row],[Mon]],$K$1:$L$2,2,FALSE)) -> 61 | N7: 0 | O7: =BD.PD[[#This Row],[Cant.]]*BD.PD[[#This Row],[ Tasa ]]*BD.PD[[#This Row],[ Precio Und.]] -> 0 | P7: 0 | Q7: =IF(BD.PD[[#This Row],[Liquid. '[%']]]<>0,(BD.PD[[#This Row],[Valor Neto '[DOP']]]*BD.PD[[#This Row],[Liquid. '[%']]])+BD.PD[[#This Row],[Valor Neto '[DOP']]],BD.PD[[#This Row],[Valor Neto '[DOP']]]) -> 0 | R7: =BD.PD[[#This Row],[Ppto. Orden Interna '[DOP']]]/HLOOKUP("USD",$K$1:$L$2,2,FALSE) -> 0 | Z7: =BD.PD[[#This Row],[Av.P1 '[%']]]*BD.PD[[#This Row],[Ppto. Orden Interna '[DOP']]] -> 0 | AC7: =BD.PD[[#This Row],[Av.P2 '[%']]]*BD.PD[[#This Row],[Ppto. Orden Interna '[DOP']]] -> 0 | AF7: =BD.PD[[#This Row],[Av.P3 '[%']]]*BD.PD[[#This Row],[Ppto. Orden Interna '[DOP']]] -> 0 | AM7: =BD.PD[[#This Row],[Pago 3]]+BD.PD[[#This Row],[Pago 2]]+BD.PD[[#This Row],[Pago 1]] -> 0
A8: 1.04 | B8: * | C8: =VLOOKUP(BD.PD[[#This Row],[Pos]],PPto[],3,FALSE) -> 1.04 Diseño sanitario | D8: * | E8: =IF(BD.PD[[#This Row],[.]]="*",VLOOKUP(BD.PD[[#This Row],[Pos]],Presupuesto!A:H,7,FALSE),"") -> 0 | K8: 1 | L8: USD | M8: =IF(BD.PD[[#This Row],[Mon]]="DOP",1,HLOOKUP(BD.PD[[#This Row],[Mon]],$K$1:$L$2,2,FALSE)) -> 61 | N8: 0 | O8: =BD.PD[[#This Row],[Cant.]]*BD.PD[[#This Row],[ Tasa ]]*BD.PD[[#This Row],[ Precio Und.]] -> 0 | P8: 0 | Q8: =IF(BD.PD[[#This Row],[Liquid. '[%']]]<>0,(BD.PD[[#This Row],[Valor Neto '[DOP']]]*BD.PD[[#This Row],[Liquid. '[%']]])+BD.PD[[#This Row],[Valor Neto '[DOP']]],BD.PD[[#This Row],[Valor Neto '[DOP']]]) -> 0 | R8: =BD.PD[[#This Row],[Ppto. Orden Interna '[DOP']]]/HLOOKUP("USD",$K$1:$L$2,2,FALSE) -> 0 | Z8: =BD.PD[[#This Row],[Av.P1 '[%']]]*BD.PD[[#This Row],[Ppto. Orden Interna '[DOP']]] -> 0 | AC8: =BD.PD[[#This Row],[Av.P2 '[%']]]*BD.PD[[#This Row],[Ppto. Orden Interna '[DOP']]] -> 0 | AF8: =BD.PD[[#This Row],[Av.P3 '[%']]]*BD.PD[[#This Row],[Ppto. Orden Interna '[DOP']]] -> 0 | AM8: =BD.PD[[#This Row],[Pago 3]]+BD.PD[[#This Row],[Pago 2]]+BD.PD[[#This Row],[Pago 1]] -> 0
A9: 1.05 | B9: * | C9: =VLOOKUP(BD.PD[[#This Row],[Pos]],PPto[],3,FALSE) -> 1.05 Estudio Geotécnico | D9: * | E9: =IF(BD.PD[[#This Row],[.]]="*",VLOOKUP(BD.PD[[#This Row],[Pos]],Presupuesto!A:H,7,FALSE),"") -> 0 | K9: 1 | L9: USD | M9: =IF(BD.PD[[#This Row],[Mon]]="DOP",1,HLOOKUP(BD.PD[[#This Row],[Mon]],$K$1:$L$2,2,FALSE)) -> 61 | N9: 0 | O9: =BD.PD[[#This Row],[Cant.]]*BD.PD[[#This Row],[ Tasa ]]*BD.PD[[#This Row],[ Precio Und.]] -> 0 | P9: 0 | Q9: =IF(BD.PD[[#This Row],[Liquid. '[%']]]<>0,(BD.PD[[#This Row],[Valor Neto '[DOP']]]*BD.PD[[#This Row],[Liquid. '[%']]])+BD.PD[[#This Row],[Valor Neto '[DOP']]],BD.PD[[#This Row],[Valor Neto '[DOP']]]) -> 0 | R9: =BD.PD[[#This Row],[Ppto. Orden Interna '[DOP']]]/HLOOKUP("USD",$K$1:$L$2,2,FALSE) -> 0 | Z9: =BD.PD[[#This Row],[Av.P1 '[%']]]*BD.PD[[#This Row],[Ppto. Orden Interna '[DOP']]] -> 0 | AC9: =BD.PD[[#This Row],[Av.P2 '[%']]]*BD.PD[[#This Row],[Ppto. Orden Interna '[DOP']]] -> 0 | AF9: =BD.PD[[#This Row],[Av.P3 '[%']]]*BD.PD[[#This Row],[Ppto. Orden Interna '[DOP']]] -> 0 | AM9: =BD.PD[[#This Row],[Pago 3]]+BD.PD[[#This Row],[Pago 2]]+BD.PD[[#This Row],[Pago 1]] -> 0
A10: 1.06 | B10: * | C10: =VLOOKUP(BD.PD[[#This Row],[Pos]],PPto[],3,FALSE) -> 1.06 Levantamiento topográfico | D10: * | E10: =IF(BD.PD[[#This Row],[.]]="*",VLOOKUP(BD.PD[[#This Row],[Pos]],Presupuesto!A:H,7,FALSE),"") -> 0 | K10: 1 | L10: USD | M10: =IF(BD.PD[[#This Row],[Mon]]="DOP",1,HLOOKUP(BD.PD[[#This Row],[Mon]],$K$1:$L$2,2,FALSE)) -> 61 | N10: 0 | O10: =BD.PD[[#This Row],[Cant.]]*BD.PD[[#This Row],[ Tasa ]]*BD.PD[[#This Row],[ Precio Und.]] -> 0 | P10: 0 | Q10: =IF(BD.PD[[#This Row],[Liquid. '[%']]]<>0,(BD.PD[[#This Row],[Valor Neto '[DOP']]]*BD.PD[[#This Row],[Liquid. '[%']]])+BD.PD[[#This Row],[Valor Neto '[DOP']]],BD.PD[[#This Row],[Valor Neto '[DOP']]]) -> 0 | R10: =BD.PD[[#This Row],[Ppto. Orden Interna '[DOP']]]/HLOOKUP("USD",$K$1:$L$2,2,FALSE) -> 0 | Z10: =BD.PD[[#This Row],[Av.P1 '[%']]]*BD.PD[[#This Row],[Ppto. Orden Interna '[DOP']]] -> 0 | AC10: =BD.PD[[#This Row],[Av.P2 '[%']]]*BD.PD[[#This Row],[Ppto. Orden Interna '[DOP']]] -> 0 | AF10: =BD.PD[[#This Row],[Av.P3 '[%']]]*BD.PD[[#This Row],[Ppto. Orden Interna '[DOP']]] -> 0 | AM10: =BD.PD[[#This Row],[Pago 3]]+BD.PD[[#This Row],[Pago 2]]+BD.PD[[#This Row],[Pago 1]] -> 0
A11: 1.07 | B11: * | C11: =VLOOKUP(BD.PD[[#This Row],[Pos]],PPto[],3,FALSE) -> 1.07 Permisos | D11: * | E11: =IF(BD.PD[[#This Row],[.]]="*",VLOOKUP(BD.PD[[#This Row],[Pos]],Presupuesto!A:H,7,FALSE),"") -> 0 | K11: 1 | L11: USD | M11: =IF(BD.PD[[#This Row],[Mon]]="DOP",1,HLOOKUP(BD.PD[[#This Row],[Mon]],$K$1:$L$2,2,FALSE)) -> 61 | N11: 0 | O11: =BD.PD[[#This Row],[Cant.]]*BD.PD[[#This Row],[ Tasa ]]*BD.PD[[#This Row],[ Precio Und.]] -> 0 | P11: 0 | Q11: =IF(BD.PD[[#This Row],[Liquid. '[%']]]<>0,(BD.PD[[#This Row],[Valor Neto '[DOP']]]*BD.PD[[#This Row],[Liquid. '[%']]])+BD.PD[[#This Row],[Valor Neto '[DOP']]],BD.PD[[#This Row],[Valor Neto '[DOP']]]) -> 0 | R11: =BD.PD[[#This Row],[Ppto. Orden Interna '[DOP']]]/HLOOKUP("USD",$K$1:$L$2,2,FALSE) -> 0 | Z11: =BD.PD[[#This Row],[Av.P1 '[%']]]*BD.PD[[#This Row],[Ppto. Orden Interna '[DOP']]] -> 0 | AC11: =BD.PD[[#This Row],[Av.P2 '[%']]]*BD.PD[[#This Row],[Ppto. Orden Interna '[DOP']]] -> 0 | AF11: =BD.PD[[#This Row],[Av.P3 '[%']]]*BD.PD[[#This Row],[Ppto. Orden Interna '[DOP']]] -> 0 | AM11: =BD.PD[[#This Row],[Pago 3]]+BD.PD[[#This Row],[Pago 2]]+BD.PD[[#This Row],[Pago 1]] -> 0
A12: 1.08 | B12: * | C12: =VLOOKUP(BD.PD[[#This Row],[Pos]],PPto[],3,FALSE) -> 1.08 Diseño sistema contra incendios | D12: * | E12: =IF(BD.PD[[#This Row],[.]]="*",VLOOKUP(BD.PD[[#This Row],[Pos]],Presupuesto!A:H,7,FALSE),"") -> 0 | K12: 1 | L12: USD | M12: =IF(BD.PD[[#This Row],[Mon]]="DOP",1,HLOOKUP(BD.PD[[#This Row],[Mon]],$K$1:$L$2,2,FALSE)) -> 61 | N12: 0 | O12: =BD.PD[[#This Row],[Cant.]]*BD.PD[[#This Row],[ Tasa ]]*BD.PD[[#This Row],[ Precio Und.]] -> 0 | P12: 0 | Q12: =IF(BD.PD[[#This Row],[Liquid. '[%']]]<>0,(BD.PD[[#This Row],[Valor Neto '[DOP']]]*BD.PD[[#This Row],[Liquid. '[%']]])+BD.PD[[#This Row],[Valor Neto '[DOP']]],BD.PD[[#This Row],[Valor Neto '[DOP']]]) -> 0 | R12: =BD.PD[[#This Row],[Ppto. Orden Interna '[DOP']]]/HLOOKUP("USD",$K$1:$L$2,2,FALSE) -> 0 | Z12: =BD.PD[[#This Row],[Av.P1 '[%']]]*BD.PD[[#This Row],[Ppto. Orden Interna '[DOP']]] -> 0 | AC12: =BD.PD[[#This Row],[Av.P2 '[%']]]*BD.PD[[#This Row],[Ppto. Orden Interna '[DOP']]] -> 0 | AF12: =BD.PD[[#This Row],[Av.P3 '[%']]]*BD.PD[[#This Row],[Ppto. Orden Interna '[DOP']]] -> 0 | AM12: =BD.PD[[#This Row],[Pago 3]]+BD.PD[[#This Row],[Pago 2]]+BD.PD[[#This Row],[Pago 1]] -> 0
A13: 1.09 | B13: * | C13: =VLOOKUP(BD.PD[[#This Row],[Pos]],PPto[],3,FALSE) -> 1.09 Diseño sistema gas | D13: * | E13: =IF(BD.PD[[#This Row],[.]]="*",VLOOKUP(BD.PD[[#This Row],[Pos]],Presupuesto!A:H,7,FALSE),"") -> 0 | K13: 1 | L13: USD | M13: =IF(BD.PD[[#This Row],[Mon]]="DOP",1,HLOOKUP(BD.PD[[#This Row],[Mon]],$K$1:$L$2,2,FALSE)) -> 61 | N13: 0 | O13: =BD.PD[[#This Row],[Cant.]]*BD.PD[[#This Row],[ Tasa ]]*BD.PD[[#This Row],[ Precio Und.]] -> 0 | P13: 0 | Q13: =IF(BD.PD[[#This Row],[Liquid. '[%']]]<>0,(BD.PD[[#This Row],[Valor Neto '[DOP']]]*BD.PD[[#This Row],[Liquid. '[%']]])+BD.PD[[#This Row],[Valor Neto '[DOP']]],BD.PD[[#This Row],[Valor Neto '[DOP']]]) -> 0 | R13: =BD.PD[[#This Row],[Ppto. Orden Interna '[DOP']]]/HLOOKUP("USD",$K$1:$L$2,2,FALSE) -> 0 | Z13: =BD.PD[[#This Row],[Av.P1 '[%']]]*BD.PD[[#This Row],[Ppto. Orden Interna '[DOP']]] -> 0 | AC13: =BD.PD[[#This Row],[Av.P2 '[%']]]*BD.PD[[#This Row],[Ppto. Orden Interna '[DOP']]] -> 0 | AF13: =BD.PD[[#This Row],[Av.P3 '[%']]]*BD.PD[[#This Row],[Ppto. Orden Interna '[DOP']]] -> 0 | AM13: =BD.PD[[#This Row],[Pago 3]]+BD.PD[[#This Row],[Pago 2]]+BD.PD[[#This Row],[Pago 1]] -> 0
A14: 2.01 | B14: * | C14: =VLOOKUP(BD.PD[[#This Row],[Pos]],PPto[],3,FALSE) -> 2.01 Edificación - Obra Civil | D14: * | E14: =IF(BD.PD[[#This Row],[.]]="*",VLOOKUP(BD.PD[[#This Row],[Pos]],Presupuesto!A:H,7,FALSE),"") -> 18449.15 | K14: 1 | L14: USD | M14: =IF(BD.PD[[#This Row],[Mon]]="DOP",1,HLOOKUP(BD.PD[[#This Row],[Mon]],$K$1:$L$2,2,FALSE)) -> 61 | N14: 0 | O14: =BD.PD[[#This Row],[Cant.]]*BD.PD[[#This Row],[ Tasa ]]*BD.PD[[#This Row],[ Precio Und.]] -> 0 | P14: 0 | Q14: =IF(BD.PD[[#This Row],[Liquid. '[%']]]<>0,(BD.PD[[#This Row],[Valor Neto '[DOP']]]*BD.PD[[#This Row],[Liquid. '[%']]])+BD.PD[[#This Row],[Valor Neto '[DOP']]],BD.PD[[#This Row],[Valor Neto '[DOP']]]) -> 0 | R14: =BD.PD[[#This Row],[Ppto. Orden Interna '[DOP']]]/HLOOKUP("USD",$K$1:$L$2,2,FALSE) -> 0 | Z14: =BD.PD[[#This Row],[Av.P1 '[%']]]*BD.PD[[#This Row],[Ppto. Orden Interna '[DOP']]] -> 0 | AC14: =BD.PD[[#This Row],[Av.P2 '[%']]]*BD.PD[[#This Row],[Ppto. Orden Interna '[DOP']]] -> 0 | AF14: =BD.PD[[#This Row],[Av.P3 '[%']]]*BD.PD[[#This Row],[Ppto. Orden Interna '[DOP']]] -> 0 | AM14: =BD.PD[[#This Row],[Pago 3]]+BD.PD[[#This Row],[Pago 2]]+BD.PD[[#This Row],[Pago 1]] -> 0
A15: 2.01 | C15: =VLOOKUP(BD.PD[[#This Row],[Pos]],PPto[],3,FALSE) -> 2.01 Edificación - Obra Civil | D15: OI | E15: =IF(BD.PD[[#This Row],[.]]="*",VLOOKUP(BD.PD[[#This Row],[Pos]],Presupuesto!A:H,7,FALSE),"") | F15: MARAZZI SISTEM S PELTRO NAT 60X60 - SALA VENTAS | K15: 0 | L15: USD | M15: =IF(BD.PD[[#This Row],[Mon]]="DOP",1,HLOOKUP(BD.PD[[#This Row],[Mon]],$K$1:$L$2,2,FALSE)) -> 61 | N15: 33 | O15: =BD.PD[[#This Row],[Cant.]]*BD.PD[[#This Row],[ Tasa ]]*BD.PD[[#This Row],[ Precio Und.]] -> 0 | P15: 0 | Q15: =IF(BD.PD[[#This Row],[Liquid. '[%']]]<>0,(BD.PD[[#This Row],[Valor Neto '[DOP']]]*BD.PD[[#This Row],[Liquid. '[%']]])+BD.PD[[#This Row],[Valor Neto '[DOP']]],BD.PD[[#This Row],[Valor Neto '[DOP']]]) -> 0 | R15: =BD.PD[[#This Row],[Ppto. Orden Interna '[DOP']]]/HLOOKUP("USD",$K$1:$L$2,2,FALSE) -> 0 | S15: HORMIGON PULIDO | Z15: =BD.PD[[#This Row],[Av.P1 '[%']]]*BD.PD[[#This Row],[Ppto. Orden Interna '[DOP']]] -> 0 | AC15: =BD.PD[[#This Row],[Av.P2 '[%']]]*BD.PD[[#This Row],[Ppto. Orden Interna '[DOP']]] -> 0 | AF15: =BD.PD[[#This Row],[Av.P3 '[%']]]*BD.PD[[#This Row],[Ppto. Orden Interna '[DOP']]] -> 0 | AM15: =BD.PD[[#This Row],[Pago 3]]+BD.PD[[#This Row],[Pago 2]]+BD.PD[[#This Row],[Pago 1]] -> 0
A16: 2.01 | C16: =VLOOKUP(BD.PD[[#This Row],[Pos]],PPto[],3,FALSE) -> 2.01 Edificación - Obra Civil | D16: OI | E16: =IF(BD.PD[[#This Row],[.]]="*",VLOOKUP(BD.PD[[#This Row],[Pos]],Presupuesto!A:H,7,FALSE),"") | F16: MARAZZI SISTEM S PELTRO NAT 30X60 - OFICINA | K16: 0 | L16: USD | M16: =IF(BD.PD[[#This Row],[Mon]]="DOP",1,HLOOKUP(BD.PD[[#This Row],[Mon]],$K$1:$L$2,2,FALSE)) -> 61 | N16: 28 | O16: =BD.PD[[#This Row],[Cant.]]*BD.PD[[#This Row],[ Tasa ]]*BD.PD[[#This Row],[ Precio Und.]] -> 0 | P16: 0 | Q16: =IF(BD.PD[[#This Row],[Liquid. '[%']]]<>0,(BD.PD[[#This Row],[Valor Neto '[DOP']]]*BD.PD[[#This Row],[Liquid. '[%']]])+BD.PD[[#This Row],[Valor Neto '[DOP']]],BD.PD[[#This Row],[Valor Neto '[DOP']]]) -> 0 | R16: =BD.PD[[#This Row],[Ppto. Orden Interna '[DOP']]]/HLOOKUP("USD",$K$1:$L$2,2,FALSE) -> 0 | S16: HORMIGON PULIDO | Z16: =BD.PD[[#This Row],[Av.P1 '[%']]]*BD.PD[[#This Row],[Ppto. Orden Interna '[DOP']]] -> 0 | AC16: =BD.PD[[#This Row],[Av.P2 '[%']]]*BD.PD[[#This Row],[Ppto. Orden Interna '[DOP']]] -> 0 | AF16: =BD.PD[[#This Row],[Av.P3 '[%']]]*BD.PD[[#This Row],[Ppto. Orden Interna '[DOP']]] -> 0 | AM16: =BD.PD[[#This Row],[Pago 3]]+BD.PD[[#This Row],[Pago 2]]+BD.PD[[#This Row],[Pago 1]] -> 0
A17: 2.01 | C17: =VLOOKUP(BD.PD[[#This Row],[Pos]],PPto[],3,FALSE) -> 2.01 Edificación - Obra Civil | D17: OI | E17: =IF(BD.PD[[#This Row],[.]]="*",VLOOKUP(BD.PD[[#This Row],[Pos]],Presupuesto!A:H,7,FALSE),"") | F17: MARAZZI SISTEM S GRAFITTE NAT. 60X60 - SALA VENTAS | K17: 0 | L17: USD | M17: =IF(BD.PD[[#This Row],[Mon]]="DOP",1,HLOOKUP(BD.PD[[#This Row],[Mon]],$K$1:$L$2,2,FALSE)) -> 61 | N17: 42.35 | O17: =BD.PD[[#This Row],[Cant.]]*BD.PD[[#This Row],[ Tasa ]]*BD.PD[[#This Row],[ Precio Und.]] -> 0 | P17: 0 | Q17: =IF(BD.PD[[#This Row],[Liquid. '[%']]]<>0,(BD.PD[[#This Row],[Valor Neto '[DOP']]]*BD.PD[[#This Row],[Liquid. '[%']]])+BD.PD[[#This Row],[Valor Neto '[DOP']]],BD.PD[[#This Row],[Valor Neto '[DOP']]]) -> 0 | R17: =BD.PD[[#This Row],[Ppto. Orden Interna '[DOP']]]/HLOOKUP("USD",$K$1:$L$2,2,FALSE) -> 0 | S17: HORMIGON PULIDO | Z17: =BD.PD[[#This Row],[Av.P1 '[%']]]*BD.PD[[#This Row],[Ppto. Orden Interna '[DOP']]] -> 0 | AC17: =BD.PD[[#This Row],[Av.P2 '[%']]]*BD.PD[[#This Row],[Ppto. Orden Interna '[DOP']]] -> 0 | AF17: =BD.PD[[#This Row],[Av.P3 '[%']]]*BD.PD[[#This Row],[Ppto. Orden Interna '[DOP']]] -> 0 | AM17: =BD.PD[[#This Row],[Pago 3]]+BD.PD[[#This Row],[Pago 2]]+BD.PD[[#This Row],[Pago 1]] -> 0
A18: 2.01 | C18: =VLOOKUP(BD.PD[[#This Row],[Pos]],PPto[],3,FALSE) -> 2.01 Edificación - Obra Civil | D18: OI | E18: =IF(BD.PD[[#This Row],[.]]="*",VLOOKUP(BD.PD[[#This Row],[Pos]],Presupuesto!A:H,7,FALSE),"") | F18: MARAZZI REVESTIMIENTO EQUIPE SIN BISELADO 10X40CM LIGHT GREY | G18: Etapa 1 -D/IR | H18: 4512892255 | I18: Real | J18: 25.06.2026 | K18: 31 | L18: USD | M18: =IF(BD.PD[[#This Row],[Mon]]="DOP",1,HLOOKUP(BD.PD[[#This Row],[Mon]],$K$1:$L$2,2,FALSE)) -> 61 | N18: 28.8 | O18: =BD.PD[[#This Row],[Cant.]]*BD.PD[[#This Row],[ Tasa ]]*BD.PD[[#This Row],[ Precio Und.]] -> 54460.8 | P18: 0 | Q18: =IF(BD.PD[[#This Row],[Liquid. '[%']]]<>0,(BD.PD[[#This Row],[Valor Neto '[DOP']]]*BD.PD[[#This Row],[Liquid. '[%']]])+BD.PD[[#This Row],[Valor Neto '[DOP']]],BD.PD[[#This Row],[Valor Neto '[DOP']]]) -> 54460.8 | R18: =BD.PD[[#This Row],[Ppto. Orden Interna '[DOP']]]/HLOOKUP("USD",$K$1:$L$2,2,FALSE) -> 892.8 | S18: ASISTIDO CARNES | U18: NTCO011104 | V18: 801667 | W18: 75322 EQUIPOS Y MATERIALES SG S. A | X18: 20 | Y18: 1 | Z18: =BD.PD[[#This Row],[Av.P1 '[%']]]*BD.PD[[#This Row],[Ppto. Orden Interna '[DOP']]] -> 54460.8 | AC18: =BD.PD[[#This Row],[Av.P2 '[%']]]*BD.PD[[#This Row],[Ppto. Orden Interna '[DOP']]] -> 0 | AF18: =BD.PD[[#This Row],[Av.P3 '[%']]]*BD.PD[[#This Row],[Ppto. Orden Interna '[DOP']]] -> 0 | AM18: =BD.PD[[#This Row],[Pago 3]]+BD.PD[[#This Row],[Pago 2]]+BD.PD[[#This Row],[Pago 1]] -> 54460.8 | AN18: Sirena Compacta | AO18: Sirena Las Terrenas | AP18: MC33 | AQ18: Marrón | AR18: 594 | AS18: Orden Colocada
A19: 2.01 | C19: =VLOOKUP(BD.PD[[#This Row],[Pos]],PPto[],3,FALSE) -> 2.01 Edificación - Obra Civil | D19: OI | E19: =IF(BD.PD[[#This Row],[.]]="*",VLOOKUP(BD.PD[[#This Row],[Pos]],Presupuesto!A:H,7,FALSE),"") | F19: MARAZZI PISO ART ANTHRATICE 60X60CM | G19: Etapa 1 -D/IR | H19: 4512892255 | I19: Real | J19: 25.06.2026 | K19: 156.6 | L19: USD | M19: =IF(BD.PD[[#This Row],[Mon]]="DOP",1,HLOOKUP(BD.PD[[#This Row],[Mon]],$K$1:$L$2,2,FALSE)) -> 61 | N19: 25.45 | O19: =BD.PD[[#This Row],[Cant.]]*BD.PD[[#This Row],[ Tasa ]]*BD.PD[[#This Row],[ Precio Und.]] -> 243113.67 | P19: 0 | Q19: =IF(BD.PD[[#This Row],[Liquid. '[%']]]<>0,(BD.PD[[#This Row],[Valor Neto '[DOP']]]*BD.PD[[#This Row],[Liquid. '[%']]])+BD.PD[[#This Row],[Valor Neto '[DOP']]],BD.PD[[#This Row],[Valor Neto '[DOP']]]) -> 243113.67 | R19: =BD.PD[[#This Row],[Ppto. Orden Interna '[DOP']]]/HLOOKUP("USD",$K$1:$L$2,2,FALSE) -> 3985.47 | S19: PISO BAÑOS CLIENTES | U19: NTCO011104 | V19: 801667 | W19: 75322 EQUIPOS Y MATERIALES SG S. A | X19: 20 | Y19: 1 | Z19: =BD.PD[[#This Row],[Av.P1 '[%']]]*BD.PD[[#This Row],[Ppto. Orden Interna '[DOP']]] -> 243113.67 | AC19: =BD.PD[[#This Row],[Av.P2 '[%']]]*BD.PD[[#This Row],[Ppto. Orden Interna '[DOP']]] -> 0 | AF19: =BD.PD[[#This Row],[Av.P3 '[%']]]*BD.PD[[#This Row],[Ppto. Orden Interna '[DOP']]] -> 0 | AM19: =BD.PD[[#This Row],[Pago 3]]+BD.PD[[#This Row],[Pago 2]]+BD.PD[[#This Row],[Pago 1]] -> 243113.67 | AN19: Sirena Compacta | AO19: Sirena Las Terrenas | AP19: MC33 | AQ19: Marrón | AR19: 594 | AS19: Orden Colocada
A20: 2.01 | C20: =VLOOKUP(BD.PD[[#This Row],[Pos]],PPto[],3,FALSE) -> 2.01 Edificación - Obra Civil | D20: OI | E20: =IF(BD.PD[[#This Row],[.]]="*",VLOOKUP(BD.PD[[#This Row],[Pos]],Presupuesto!A:H,7,FALSE),"") | F20: MARAZZI REVESTIMIENTO ART ANTHARCITE 60X60CM | G20: Etapa 1 -D/IR | H20: 4512892255 | I20: Real | J20: 25.06.2026 | K20: 83.16 | L20: USD | M20: =IF(BD.PD[[#This Row],[Mon]]="DOP",1,HLOOKUP(BD.PD[[#This Row],[Mon]],$K$1:$L$2,2,FALSE)) -> 61 | N20: 25.45 | O20: =BD.PD[[#This Row],[Cant.]]*BD.PD[[#This Row],[ Tasa ]]*BD.PD[[#This Row],[ Precio Und.]] -> 129101.74 | P20: 0 | Q20: =IF(BD.PD[[#This Row],[Liquid. '[%']]]<>0,(BD.PD[[#This Row],[Valor Neto '[DOP']]]*BD.PD[[#This Row],[Liquid. '[%']]])+BD.PD[[#This Row],[Valor Neto '[DOP']]],BD.PD[[#This Row],[Valor Neto '[DOP']]]) -> 129101.74 | R20: =BD.PD[[#This Row],[Ppto. Orden Interna '[DOP']]]/HLOOKUP("USD",$K$1:$L$2,2,FALSE) -> 2116.422 | S20: REVESTIMIENTO PAREDES BAÑOS | U20: NTCO011104 | V20: 801667 | W20: 75322 EQUIPOS Y MATERIALES SG S. A | X20: 20 | Y20: 1 | Z20: =BD.PD[[#This Row],[Av.P1 '[%']]]*BD.PD[[#This Row],[Ppto. Orden Interna '[DOP']]] -> 129101.74 | AC20: =BD.PD[[#This Row],[Av.P2 '[%']]]*BD.PD[[#This Row],[Ppto. Orden Interna '[DOP']]] -> 0 | AF20: =BD.PD[[#This Row],[Av.P3 '[%']]]*BD.PD[[#This Row],[Ppto. Orden Interna '[DOP']]] -> 0 | AM20: =BD.PD[[#This Row],[Pago 3]]+BD.PD[[#This Row],[Pago 2]]+BD.PD[[#This Row],[Pago 1]] -> 129101.74 | AN20: Sirena Compacta | AO20: Sirena Las Terrenas | AP20: MC33 | AQ20: Marrón | AR20: 594 | AS20: Orden Colocada
A21: 2.01 | C21: =VLOOKUP(BD.PD[[#This Row],[Pos]],PPto[],3,FALSE) -> 2.01 Edificación - Obra Civil | D21: OI | E21: =IF(BD.PD[[#This Row],[.]]="*",VLOOKUP(BD.PD[[#This Row],[Pos]],Presupuesto!A:H,7,FALSE),"") | F21: MARAZZI REVESTIMIENTO PINCH WHITE 60X60CM | G21: Etapa 1 -D/IR | H21: 4512892255 | I21: Real | J21: 25.06.2026 | K21: 81 | L21: USD | M21: =IF(BD.PD[[#This Row],[Mon]]="DOP",1,HLOOKUP(BD.PD[[#This Row],[Mon]],$K$1:$L$2,2,FALSE)) -> 61 | N21: 25.45 | O21: =BD.PD[[#This Row],[Cant.]]*BD.PD[[#This Row],[ Tasa ]]*BD.PD[[#This Row],[ Precio Und.]] -> 125748.45 | P21: 0 | Q21: =IF(BD.PD[[#This Row],[Liquid. '[%']]]<>0,(BD.PD[[#This Row],[Valor Neto '[DOP']]]*BD.PD[[#This Row],[Liquid. '[%']]])+BD.PD[[#This Row],[Valor Neto '[DOP']]],BD.PD[[#This Row],[Valor Neto '[DOP']]]) -> 125748.45 | R21: =BD.PD[[#This Row],[Ppto. Orden Interna '[DOP']]]/HLOOKUP("USD",$K$1:$L$2,2,FALSE) -> 2061.45 | S21: REVESTIMIENTO PAREDES BAÑOS | U21: NTCO011104 | V21: 801667 | W21: 75322 EQUIPOS Y MATERIALES SG S. A | X21: 20 | Y21: 1 | Z21: =BD.PD[[#This Row],[Av.P1 '[%']]]*BD.PD[[#This Row],[Ppto. Orden Interna '[DOP']]] -> 125748.45 | AC21: =BD.PD[[#This Row],[Av.P2 '[%']]]*BD.PD[[#This Row],[Ppto. Orden Interna '[DOP']]] -> 0 | AF21: =BD.PD[[#This Row],[Av.P3 '[%']]]*BD.PD[[#This Row],[Ppto. Orden Interna '[DOP']]] -> 0 | AM21: =BD.PD[[#This Row],[Pago 3]]+BD.PD[[#This Row],[Pago 2]]+BD.PD[[#This Row],[Pago 1]] -> 125748.45 | AN21: Sirena Compacta | AO21: Sirena Las Terrenas | AP21: MC33 | AQ21: Marrón | AR21: 594 | AS21: Orden Colocada
A22: 2.01 | C22: =VLOOKUP(BD.PD[[#This Row],[Pos]],PPto[],3,FALSE) -> 2.01 Edificación - Obra Civil | D22: OI | E22: =IF(BD.PD[[#This Row],[.]]="*",VLOOKUP(BD.PD[[#This Row],[Pos]],Presupuesto!A:H,7,FALSE),"") | F22: MARAZZI PROGRESS ANTRACITE 60X60CM | G22: Etapa 1 -D/IR | H22: 4512892255 | I22: Real | J22: 25.06.2026 | K22: 57.24 | L22: USD | M22: =IF(BD.PD[[#This Row],[Mon]]="DOP",1,HLOOKUP(BD.PD[[#This Row],[Mon]],$K$1:$L$2,2,FALSE)) -> 61 | N22: 25.45 | O22: =BD.PD[[#This Row],[Cant.]]*BD.PD[[#This Row],[ Tasa ]]*BD.PD[[#This Row],[ Precio Und.]] -> 88862.238 | P22: 0 | Q22: =IF(BD.PD[[#This Row],[Liquid. '[%']]]<>0,(BD.PD[[#This Row],[Valor Neto '[DOP']]]*BD.PD[[#This Row],[Liquid. '[%']]])+BD.PD[[#This Row],[Valor Neto '[DOP']]],BD.PD[[#This Row],[Valor Neto '[DOP']]]) -> 88862.238 | R22: =BD.PD[[#This Row],[Ppto. Orden Interna '[DOP']]]/HLOOKUP("USD",$K$1:$L$2,2,FALSE) -> 1456.758 | S22: PISO BAÑOS CLIENTES GALERIA COMERCIAL | U22: NTCO011104 | V22: 801667 | W22: 75322 EQUIPOS Y MATERIALES SG S. A | X22: 20 | Y22: 1 | Z22: =BD.PD[[#This Row],[Av.P1 '[%']]]*BD.PD[[#This Row],[Ppto. Orden Interna '[DOP']]] -> 88862.238 | AC22: =BD.PD[[#This Row],[Av.P2 '[%']]]*BD.PD[[#This Row],[Ppto. Orden Interna '[DOP']]] -> 0 | AF22: =BD.PD[[#This Row],[Av.P3 '[%']]]*BD.PD[[#This Row],[Ppto. Orden Interna '[DOP']]] -> 0 | AM22: =BD.PD[[#This Row],[Pago 3]]+BD.PD[[#This Row],[Pago 2]]+BD.PD[[#This Row],[Pago 1]] -> 88862.238 | AN22: Sirena Compacta | AO22: Sirena Las Terrenas | AP22: MC33 | AQ22: Marrón | AR22: 594 | AS22: Orden Colocada
A23: 2.01 | C23: =VLOOKUP(BD.PD[[#This Row],[Pos]],PPto[],3,FALSE) -> 2.01 Edificación - Obra Civil | D23: OI | E23: =IF(BD.PD[[#This Row],[.]]="*",VLOOKUP(BD.PD[[#This Row],[Pos]],Presupuesto!A:H,7,FALSE),"") | F23: MARAZZI MATERIKA OFF WHITE SPATULA 3D | G23: Etapa 1 -D/IR | H23: 4512892255 | I23: Real | J23: 25.06.2026 | K23: 49.68 | L23: USD | M23: =IF(BD.PD[[#This Row],[Mon]]="DOP",1,HLOOKUP(BD.PD[[#This Row],[Mon]],$K$1:$L$2,2,FALSE)) -> 61 | N23: 34 | O23: =BD.PD[[#This Row],[Cant.]]*BD.PD[[#This Row],[ Tasa ]]*BD.PD[[#This Row],[ Precio Und.]] -> 103036.32 | P23: 0 | Q23: =IF(BD.PD[[#This Row],[Liquid. '[%']]]<>0,(BD.PD[[#This Row],[Valor Neto '[DOP']]]*BD.PD[[#This Row],[Liquid. '[%']]])+BD.PD[[#This Row],[Valor Neto '[DOP']]],BD.PD[[#This Row],[Valor Neto '[DOP']]]) -> 103036.32 | R23: =BD.PD[[#This Row],[Ppto. Orden Interna '[DOP']]]/HLOOKUP("USD",$K$1:$L$2,2,FALSE) -> 1689.12 | S23: REVESTIMIENTO PARED ESPEJO BAÑOS CLIENTES GALERIA COMERCIAL | U23: NTCO011104 | V23: 801667 | W23: 75322 EQUIPOS Y MATERIALES SG S. A | X23: 20 | Y23: 1 | Z23: =BD.PD[[#This Row],[Av.P1 '[%']]]*BD.PD[[#This Row],[Ppto. Orden Interna '[DOP']]] -> 103036.32 | AC23: =BD.PD[[#This Row],[Av.P2 '[%']]]*BD.PD[[#This Row],[Ppto. Orden Interna '[DOP']]] -> 0 | AF23: =BD.PD[[#This Row],[Av.P3 '[%']]]*BD.PD[[#This Row],[Ppto. Orden Interna '[DOP']]] -> 0 | AM23: =BD.PD[[#This Row],[Pago 3]]+BD.PD[[#This Row],[Pago 2]]+BD.PD[[#This Row],[Pago 1]] -> 103036.32 | AN23: Sirena Compacta | AO23: Sirena Las Terrenas | AP23: MC33 | AQ23: Marrón | AR23: 594 | AS23: Orden Colocada
A24: 2.01 | C24: =VLOOKUP(BD.PD[[#This Row],[Pos]],PPto[],3,FALSE) -> 2.01 Edificación - Obra Civil | D24: OI | E24: =IF(BD.PD[[#This Row],[.]]="*",VLOOKUP(BD.PD[[#This Row],[Pos]],Presupuesto!A:H,7,FALSE),"") | F24: RAGNO CONCEPT GRIGIO | G24: Etapa 1 -D/IR | H24: 4512892255 | I24: Real | J24: 25.06.2026 | K24: 90.72 | L24: USD | M24: =IF(BD.PD[[#This Row],[Mon]]="DOP",1,HLOOKUP(BD.PD[[#This Row],[Mon]],$K$1:$L$2,2,FALSE)) -> 61 | N24: 26.2 | O24: =BD.PD[[#This Row],[Cant.]]*BD.PD[[#This Row],[ Tasa ]]*BD.PD[[#This Row],[ Precio Und.]] -> 144988.7 | P24: 0 | Q24: =IF(BD.PD[[#This Row],[Liquid. '[%']]]<>0,(BD.PD[[#This Row],[Valor Neto '[DOP']]]*BD.PD[[#This Row],[Liquid. '[%']]])+BD.PD[[#This Row],[Valor Neto '[DOP']]],BD.PD[[#This Row],[Valor Neto '[DOP']]]) -> 144988.7 | R24: =BD.PD[[#This Row],[Ppto. Orden Interna '[DOP']]]/HLOOKUP("USD",$K$1:$L$2,2,FALSE) -> 2376.864 | S24: PISO BAÑOS CLIENTES GALERIA COMERCIAL | U24: NTCO011104 | V24: 801667 | W24: 75322 EQUIPOS Y MATERIALES SG S. A | X24: 20 | Y24: 1 | Z24: =BD.PD[[#This Row],[Av.P1 '[%']]]*BD.PD[[#This Row],[Ppto. Orden Interna '[DOP']]] -> 144988.7 | AC24: =BD.PD[[#This Row],[Av.P2 '[%']]]*BD.PD[[#This Row],[Ppto. Orden Interna '[DOP']]] -> 0 | AF24: =BD.PD[[#This Row],[Av.P3 '[%']]]*BD.PD[[#This Row],[Ppto. Orden Interna '[DOP']]] -> 0 | AM24: =BD.PD[[#This Row],[Pago 3]]+BD.PD[[#This Row],[Pago 2]]+BD.PD[[#This Row],[Pago 1]] -> 144988.7 | AN24: Sirena Compacta | AO24: Sirena Las Terrenas | AP24: MC33 | AQ24: Marrón | AR24: 594 | AS24: Orden Colocada
A25: 2.01 | C25: =VLOOKUP(BD.PD[[#This Row],[Pos]],PPto[],3,FALSE) -> 2.01 Edificación - Obra Civil | D25: OI | E25: =IF(BD.PD[[#This Row],[.]]="*",VLOOKUP(BD.PD[[#This Row],[Pos]],Presupuesto!A:H,7,FALSE),"") | F25: SUM Y COL. REVEST. ACM ISLA | G25: Etapa 2 -D/IR | H25: 4513048855 | J25: 03.08.2026 | K25: 0 | L25: DOP | M25: =IF(BD.PD[[#This Row],[Mon]]="DOP",1,HLOOKUP(BD.PD[[#This Row],[Mon]],$K$1:$L$2,2,FALSE)) -> 1 | N25: 1715871.4 | O25: =BD.PD[[#This Row],[Cant.]]*BD.PD[[#This Row],[ Tasa ]]*BD.PD[[#This Row],[ Precio Und.]] -> 0 | P25: 0 | Q25: =IF(BD.PD[[#This Row],[Liquid. '[%']]]<>0,(BD.PD[[#This Row],[Valor Neto '[DOP']]]*BD.PD[[#This Row],[Liquid. '[%']]])+BD.PD[[#This Row],[Valor Neto '[DOP']]],BD.PD[[#This Row],[Valor Neto '[DOP']]]) -> 0 | R25: =BD.PD[[#This Row],[Ppto. Orden Interna '[DOP']]]/HLOOKUP("USD",$K$1:$L$2,2,FALSE) -> 0 | S25: 76815 LIKECORP SRL | U25: NTCO011104 | V25: 801667 | W25: 76815 LIKECORP SRL | X25: 20 | Y25: 0.6 | Z25: =BD.PD[[#This Row],[Av.P1 '[%']]]*BD.PD[[#This Row],[Ppto. Orden Interna '[DOP']]] -> 0 | AA25: 21 | AB25: 0.4 | AC25: =BD.PD[[#This Row],[Av.P2 '[%']]]*BD.PD[[#This Row],[Ppto. Orden Interna '[DOP']]] -> 0 | AF25: =BD.PD[[#This Row],[Av.P3 '[%']]]*BD.PD[[#This Row],[Ppto. Orden Interna '[DOP']]] -> 0 | AM25: =BD.PD[[#This Row],[Pago 3]]+BD.PD[[#This Row],[Pago 2]]+BD.PD[[#This Row],[Pago 1]] -> 0
A26: 2.01 | C26: =VLOOKUP(BD.PD[[#This Row],[Pos]],PPto[],3,FALSE) -> 2.01 Edificación - Obra Civil | D26: OI | E26: =IF(BD.PD[[#This Row],[.]]="*",VLOOKUP(BD.PD[[#This Row],[Pos]],Presupuesto!A:H,7,FALSE),"") | F26: SUM Y COL. REVEST. ACM ISLA | G26: Etapa 2 -D/IR | H26: 4513048855 | J26: 03.08.2026 | K26: 0 | L26: DOP | M26: =IF(BD.PD[[#This Row],[Mon]]="DOP",1,HLOOKUP(BD.PD[[#This Row],[Mon]],$K$1:$L$2,2,FALSE)) -> 1 | N26: 374739.78 | O26: =BD.PD[[#This Row],[Cant.]]*BD.PD[[#This Row],[ Tasa ]]*BD.PD[[#This Row],[ Precio Und.]] -> 0 | P26: 0 | Q26: =IF(BD.PD[[#This Row],[Liquid. '[%']]]<>0,(BD.PD[[#This Row],[Valor Neto '[DOP']]]*BD.PD[[#This Row],[Liquid. '[%']]])+BD.PD[[#This Row],[Valor Neto '[DOP']]],BD.PD[[#This Row],[Valor Neto '[DOP']]]) -> 0 | R26: =BD.PD[[#This Row],[Ppto. Orden Interna '[DOP']]]/HLOOKUP("USD",$K$1:$L$2,2,FALSE) -> 0 | S26: 76815 LIKECORP SRL | U26: NTCO011104 | V26: 801667 | W26: 76815 LIKECORP SRL | X26: 20 | Y26: 0.6 | Z26: =BD.PD[[#This Row],[Av.P1 '[%']]]*BD.PD[[#This Row],[Ppto. Orden Interna '[DOP']]] -> 0 | AA26: 21 | AB26: 0.4 | AC26: =BD.PD[[#This Row],[Av.P2 '[%']]]*BD.PD[[#This Row],[Ppto. Orden Interna '[DOP']]] -> 0 | AF26: =BD.PD[[#This Row],[Av.P3 '[%']]]*BD.PD[[#This Row],[Ppto. Orden Interna '[DOP']]] -> 0 | AM26: =BD.PD[[#This Row],[Pago 3]]+BD.PD[[#This Row],[Pago 2]]+BD.PD[[#This Row],[Pago 1]] -> 0
A27: 2.01 | C27: =VLOOKUP(BD.PD[[#This Row],[Pos]],PPto[],3,FALSE) -> 2.01 Edificación - Obra Civil | D27: OI | E27: =IF(BD.PD[[#This Row],[.]]="*",VLOOKUP(BD.PD[[#This Row],[Pos]],Presupuesto!A:H,7,FALSE),"") | F27: SUM Y COL. REVEST. ACM ISLA | G27: Etapa 2 -D/IR | H27: 4513048855 | J27: 03.08.2026 | K27: 0 | L27: DOP | M27: =IF(BD.PD[[#This Row],[Mon]]="DOP",1,HLOOKUP(BD.PD[[#This Row],[Mon]],$K$1:$L$2,2,FALSE)) -> 1 | N27: 51071.88 | O27: =BD.PD[[#This Row],[Cant.]]*BD.PD[[#This Row],[ Tasa ]]*BD.PD[[#This Row],[ Precio Und.]] -> 0 | P27: 0 | Q27: =IF(BD.PD[[#This Row],[Liquid. '[%']]]<>0,(BD.PD[[#This Row],[Valor Neto '[DOP']]]*BD.PD[[#This Row],[Liquid. '[%']]])+BD.PD[[#This Row],[Valor Neto '[DOP']]],BD.PD[[#This Row],[Valor Neto '[DOP']]]) -> 0 | R27: =BD.PD[[#This Row],[Ppto. Orden Interna '[DOP']]]/HLOOKUP("USD",$K$1:$L$2,2,FALSE) -> 0 | S27: 76815 LIKECORP SRL | U27: NTCO011104 | V27: 801667 | W27: 76815 LIKECORP SRL | X27: 20 | Y27: 0.6 | Z27: =BD.PD[[#This Row],[Av.P1 '[%']]]*BD.PD[[#This Row],[Ppto. Orden Interna '[DOP']]] -> 0 | AA27: 21 | AB27: 0.4 | AC27: =BD.PD[[#This Row],[Av.P2 '[%']]]*BD.PD[[#This Row],[Ppto. Orden Interna '[DOP']]] -> 0 | AF27: =BD.PD[[#This Row],[Av.P3 '[%']]]*BD.PD[[#This Row],[Ppto. Orden Interna '[DOP']]] -> 0 | AM27: =BD.PD[[#This Row],[Pago 3]]+BD.PD[[#This Row],[Pago 2]]+BD.PD[[#This Row],[Pago 1]] -> 0
A28: 2.01 | C28: =VLOOKUP(BD.PD[[#This Row],[Pos]],PPto[],3,FALSE) -> 2.01 Edificación - Obra Civil | D28: OI | E28: =IF(BD.PD[[#This Row],[.]]="*",VLOOKUP(BD.PD[[#This Row],[Pos]],Presupuesto!A:H,7,FALSE),"") | F28: SUM Y COL. PLAFON ACM MC33 | G28: Etapa 2 -D/IR | H28: 4513049208 | J28: 03.08.2026 | K28: 0 | L28: DOP | M28: =IF(BD.PD[[#This Row],[Mon]]="DOP",1,HLOOKUP(BD.PD[[#This Row],[Mon]],$K$1:$L$2,2,FALSE)) -> 1 | N28: 1601357.7 | O28: =BD.PD[[#This Row],[Cant.]]*BD.PD[[#This Row],[ Tasa ]]*BD.PD[[#This Row],[ Precio Und.]] -> 0 | P28: 0 | Q28: =IF(BD.PD[[#This Row],[Liquid. '[%']]]<>0,(BD.PD[[#This Row],[Valor Neto '[DOP']]]*BD.PD[[#This Row],[Liquid. '[%']]])+BD.PD[[#This Row],[Valor Neto '[DOP']]],BD.PD[[#This Row],[Valor Neto '[DOP']]]) -> 0 | R28: =BD.PD[[#This Row],[Ppto. Orden Interna '[DOP']]]/HLOOKUP("USD",$K$1:$L$2,2,FALSE) -> 0 | S28: 76815 LIKECORP SRL | U28: NTCO011104 | V28: 801667 | W28: 76815 LIKECORP SRL | X28: 20 | Y28: 0.6 | Z28: =BD.PD[[#This Row],[Av.P1 '[%']]]*BD.PD[[#This Row],[Ppto. Orden Interna '[DOP']]] -> 0 | AA28: 21 | AB28: 0.4 | AC28: =BD.PD[[#This Row],[Av.P2 '[%']]]*BD.PD[[#This Row],[Ppto. Orden Interna '[DOP']]] -> 0 | AF28: =BD.PD[[#This Row],[Av.P3 '[%']]]*BD.PD[[#This Row],[Ppto. Orden Interna '[DOP']]] -> 0 | AM28: =BD.PD[[#This Row],[Pago 3]]+BD.PD[[#This Row],[Pago 2]]+BD.PD[[#This Row],[Pago 1]] -> 0
A29: 2.01 | C29: =VLOOKUP(BD.PD[[#This Row],[Pos]],PPto[],3,FALSE) -> 2.01 Edificación - Obra Civil | D29: OI | E29: =IF(BD.PD[[#This Row],[.]]="*",VLOOKUP(BD.PD[[#This Row],[Pos]],Presupuesto!A:H,7,FALSE),"") | F29: SUM E INST. PALILLERIA SC TERRENAS MC33 | G29: Etapa 2 -D/IR | H29: 4513094595 | I29: Comprometido | J29: 08.09.2026 | K29: 1 | L29: DOP | M29: =IF(BD.PD[[#This Row],[Mon]]="DOP",1,HLOOKUP(BD.PD[[#This Row],[Mon]],$K$1:$L$2,2,FALSE)) -> 1 | N29: 5624996.5 | O29: =BD.PD[[#This Row],[Cant.]]*BD.PD[[#This Row],[ Tasa ]]*BD.PD[[#This Row],[ Precio Und.]] -> 5624996.5 | P29: 0 | Q29: =IF(BD.PD[[#This Row],[Liquid. '[%']]]<>0,(BD.PD[[#This Row],[Valor Neto '[DOP']]]*BD.PD[[#This Row],[Liquid. '[%']]])+BD.PD[[#This Row],[Valor Neto '[DOP']]],BD.PD[[#This Row],[Valor Neto '[DOP']]]) -> 5624996.5 | R29: =BD.PD[[#This Row],[Ppto. Orden Interna '[DOP']]]/HLOOKUP("USD",$K$1:$L$2,2,FALSE) -> 92213.058 | S29: 76815 LIKECORP SRL | U29: NTCO011104 | V29: 801667 | W29: 76815 LIKECORP SRL | X29: 21 | Y29: 0.6 | Z29: =BD.PD[[#This Row],[Av.P1 '[%']]]*BD.PD[[#This Row],[Ppto. Orden Interna '[DOP']]] -> 3374997.9 | AA29: 21 | AB29: 0.4 | AC29: =BD.PD[[#This Row],[Av.P2 '[%']]]*BD.PD[[#This Row],[Ppto. Orden Interna '[DOP']]] -> 2249998.6 | AF29: =BD.PD[[#This Row],[Av.P3 '[%']]]*BD.PD[[#This Row],[Ppto. Orden Interna '[DOP']]] -> 0 | AM29: =BD.PD[[#This Row],[Pago 3]]+BD.PD[[#This Row],[Pago 2]]+BD.PD[[#This Row],[Pago 1]] -> 5624996.5 | AN29: Sirena Compacta | AO29: Sirena Las Terrenas | AP29: MC33 | AQ29: Marrón | AR29: 594 | AS29: Orden Colocada
A30: 2.01 | C30: =VLOOKUP(BD.PD[[#This Row],[Pos]],PPto[],3,FALSE) -> 2.01 Edificación - Obra Civil | D30: OI | E30: =IF(BD.PD[[#This Row],[.]]="*",VLOOKUP(BD.PD[[#This Row],[Pos]],Presupuesto!A:H,7,FALSE),"") | F30: TRANSPORTE PERSONAL Y VIATICOS | G30: Etapa 2 -D/IR | H30: 4513094595 | I30: Comprometido | J30: 08.09.2026 | K30: 1 | L30: DOP | M30: =IF(BD.PD[[#This Row],[Mon]]="DOP",1,HLOOKUP(BD.PD[[#This Row],[Mon]],$K$1:$L$2,2,FALSE)) -> 1 | N30: 567036 | O30: =BD.PD[[#This Row],[Cant.]]*BD.PD[[#This Row],[ Tasa ]]*BD.PD[[#This Row],[ Precio Und.]] -> 567036 | P30: 0 | Q30: =IF(BD.PD[[#This Row],[Liquid. '[%']]]<>0,(BD.PD[[#This Row],[Valor Neto '[DOP']]]*BD.PD[[#This Row],[Liquid. '[%']]])+BD.PD[[#This Row],[Valor Neto '[DOP']]],BD.PD[[#This Row],[Valor Neto '[DOP']]]) -> 567036 | R30: =BD.PD[[#This Row],[Ppto. Orden Interna '[DOP']]]/HLOOKUP("USD",$K$1:$L$2,2,FALSE) -> 9295.6721 | S30: 76815 LIKECORP SRL | U30: NTCO011104 | V30: 801667 | W30: 76815 LIKECORP SRL | X30: 21 | Y30: 0.6 | Z30: =BD.PD[[#This Row],[Av.P1 '[%']]]*BD.PD[[#This Row],[Ppto. Orden Interna '[DOP']]] -> 340221.6 | AA30: 21 | AB30: 0.4 | AC30: =BD.PD[[#This Row],[Av.P2 '[%']]]*BD.PD[[#This Row],[Ppto. Orden Interna '[DOP']]] -> 226814.4 | AF30: =BD.PD[[#This Row],[Av.P3 '[%']]]*BD.PD[[#This Row],[Ppto. Orden Interna '[DOP']]] -> 0 | AM30: =BD.PD[[#This Row],[Pago 3]]+BD.PD[[#This Row],[Pago 2]]+BD.PD[[#This Row],[Pago 1]] -> 567036 | AN30: Sirena Compacta | AO30: Sirena Las Terrenas | AP30: MC33 | AQ30: Marrón | AR30: 594 | AS30: Orden Colocada
A31: 2.02 | B31: * | C31: =VLOOKUP(BD.PD[[#This Row],[Pos]],PPto[],3,FALSE) -> 2.02 Edificación - Estructura Metálica | D31: * | E31: =IF(BD.PD[[#This Row],[.]]="*",VLOOKUP(BD.PD[[#This Row],[Pos]],Presupuesto!A:H,7,FALSE),"") -> 0 | K31: 1 | L31: USD | M31: =IF(BD.PD[[#This Row],[Mon]]="DOP",1,HLOOKUP(BD.PD[[#This Row],[Mon]],$K$1:$L$2,2,FALSE)) -> 61 | N31: 0 | O31: =BD.PD[[#This Row],[Cant.]]*BD.PD[[#This Row],[ Tasa ]]*BD.PD[[#This Row],[ Precio Und.]] -> 0 | P31: 0 | Q31: =IF(BD.PD[[#This Row],[Liquid. '[%']]]<>0,(BD.PD[[#This Row],[Valor Neto '[DOP']]]*BD.PD[[#This Row],[Liquid. '[%']]])+BD.PD[[#This Row],[Valor Neto '[DOP']]],BD.PD[[#This Row],[Valor Neto '[DOP']]]) -> 0 | R31: =BD.PD[[#This Row],[Ppto. Orden Interna '[DOP']]]/HLOOKUP("USD",$K$1:$L$2,2,FALSE) -> 0 | Z31: =BD.PD[[#This Row],[Av.P1 '[%']]]*BD.PD[[#This Row],[Ppto. Orden Interna '[DOP']]] -> 0 | AC31: =BD.PD[[#This Row],[Av.P2 '[%']]]*BD.PD[[#This Row],[Ppto. Orden Interna '[DOP']]] -> 0 | AF31: =BD.PD[[#This Row],[Av.P3 '[%']]]*BD.PD[[#This Row],[Ppto. Orden Interna '[DOP']]] -> 0 | AM31: =BD.PD[[#This Row],[Pago 3]]+BD.PD[[#This Row],[Pago 2]]+BD.PD[[#This Row],[Pago 1]] -> 0
A32: 2.03 | B32: * | C32: =VLOOKUP(BD.PD[[#This Row],[Pos]],PPto[],3,FALSE) -> 2.03 Edificación - Techo S.S. y Cerramientos Multipanel | D32: * | E32: =IF(BD.PD[[#This Row],[.]]="*",VLOOKUP(BD.PD[[#This Row],[Pos]],Presupuesto!A:H,7,FALSE),"") -> 0 | K32: 1 | L32: USD | M32: =IF(BD.PD[[#This Row],[Mon]]="DOP",1,HLOOKUP(BD.PD[[#This Row],[Mon]],$K$1:$L$2,2,FALSE)) -> 61 | N32: 0 | O32: =BD.PD[[#This Row],[Cant.]]*BD.PD[[#This Row],[ Tasa ]]*BD.PD[[#This Row],[ Precio Und.]] -> 0 | P32: 0 | Q32: =IF(BD.PD[[#This Row],[Liquid. '[%']]]<>0,(BD.PD[[#This Row],[Valor Neto '[DOP']]]*BD.PD[[#This Row],[Liquid. '[%']]])+BD.PD[[#This Row],[Valor Neto '[DOP']]],BD.PD[[#This Row],[Valor Neto '[DOP']]]) -> 0 | R32: =BD.PD[[#This Row],[Ppto. Orden Interna '[DOP']]]/HLOOKUP("USD",$K$1:$L$2,2,FALSE) -> 0 | Z32: =BD.PD[[#This Row],[Av.P1 '[%']]]*BD.PD[[#This Row],[Ppto. Orden Interna '[DOP']]] -> 0 | AC32: =BD.PD[[#This Row],[Av.P2 '[%']]]*BD.PD[[#This Row],[Ppto. Orden Interna '[DOP']]] -> 0 | AF32: =BD.PD[[#This Row],[Av.P3 '[%']]]*BD.PD[[#This Row],[Ppto. Orden Interna '[DOP']]] -> 0 | AM32: =BD.PD[[#This Row],[Pago 3]]+BD.PD[[#This Row],[Pago 2]]+BD.PD[[#This Row],[Pago 1]] -> 0
A33: 2.04 | B33: * | C33: =VLOOKUP(BD.PD[[#This Row],[Pos]],PPto[],3,FALSE) -> 2.04 Edificación - Tragaluces "Skylights" | D33: * | E33: =IF(BD.PD[[#This Row],[.]]="*",VLOOKUP(BD.PD[[#This Row],[Pos]],Presupuesto!A:H,7,FALSE),"") -> 0 | K33: 1 | L33: USD | M33: =IF(BD.PD[[#This Row],[Mon]]="DOP",1,HLOOKUP(BD.PD[[#This Row],[Mon]],$K$1:$L$2,2,FALSE)) -> 61 | N33: 0 | O33: =BD.PD[[#This Row],[Cant.]]*BD.PD[[#This Row],[ Tasa ]]*BD.PD[[#This Row],[ Precio Und.]] -> 0 | P33: 0 | Q33: =IF(BD.PD[[#This Row],[Liquid. '[%']]]<>0,(BD.PD[[#This Row],[Valor Neto '[DOP']]]*BD.PD[[#This Row],[Liquid. '[%']]])+BD.PD[[#This Row],[Valor Neto '[DOP']]],BD.PD[[#This Row],[Valor Neto '[DOP']]]) -> 0 | R33: =BD.PD[[#This Row],[Ppto. Orden Interna '[DOP']]]/HLOOKUP("USD",$K$1:$L$2,2,FALSE) -> 0 | Z33: =BD.PD[[#This Row],[Av.P1 '[%']]]*BD.PD[[#This Row],[Ppto. Orden Interna '[DOP']]] -> 0 | AC33: =BD.PD[[#This Row],[Av.P2 '[%']]]*BD.PD[[#This Row],[Ppto. Orden Interna '[DOP']]] -> 0 | AF33: =BD.PD[[#This Row],[Av.P3 '[%']]]*BD.PD[[#This Row],[Ppto. Orden Interna '[DOP']]] -> 0 | AM33: =BD.PD[[#This Row],[Pago 3]]+BD.PD[[#This Row],[Pago 2]]+BD.PD[[#This Row],[Pago 1]] -> 0
A34: 2.05 | B34: * | C34: =VLOOKUP(BD.PD[[#This Row],[Pos]],PPto[],3,FALSE) -> 2.05 Instalaciones Sanitarias | D34: * | E34: =IF(BD.PD[[#This Row],[.]]="*",VLOOKUP(BD.PD[[#This Row],[Pos]],Presupuesto!A:H,7,FALSE),"") -> 25100 | K34: 1 | L34: USD | M34: =IF(BD.PD[[#This Row],[Mon]]="DOP",1,HLOOKUP(BD.PD[[#This Row],[Mon]],$K$1:$L$2,2,FALSE)) -> 61 | N34: 0 | O34: =BD.PD[[#This Row],[Cant.]]*BD.PD[[#This Row],[ Tasa ]]*BD.PD[[#This Row],[ Precio Und.]] -> 0 | P34: 0 | Q34: =IF(BD.PD[[#This Row],[Liquid. '[%']]]<>0,(BD.PD[[#This Row],[Valor Neto '[DOP']]]*BD.PD[[#This Row],[Liquid. '[%']]])+BD.PD[[#This Row],[Valor Neto '[DOP']]],BD.PD[[#This Row],[Valor Neto '[DOP']]]) -> 0 | R34: =BD.PD[[#This Row],[Ppto. Orden Interna '[DOP']]]/HLOOKUP("USD",$K$1:$L$2,2,FALSE) -> 0 | Z34: =BD.PD[[#This Row],[Av.P1 '[%']]]*BD.PD[[#This Row],[Ppto. Orden Interna '[DOP']]] -> 0 | AC34: =BD.PD[[#This Row],[Av.P2 '[%']]]*BD.PD[[#This Row],[Ppto. Orden Interna '[DOP']]] -> 0 | AF34: =BD.PD[[#This Row],[Av.P3 '[%']]]*BD.PD[[#This Row],[Ppto. Orden Interna '[DOP']]] -> 0 | AM34: =BD.PD[[#This Row],[Pago 3]]+BD.PD[[#This Row],[Pago 2]]+BD.PD[[#This Row],[Pago 1]] -> 0
A35: 2.05 | C35: =VLOOKUP(BD.PD[[#This Row],[Pos]],PPto[],3,FALSE) -> 2.05 Instalaciones Sanitarias | D35: OI | E35: =IF(BD.PD[[#This Row],[.]]="*",VLOOKUP(BD.PD[[#This Row],[Pos]],Presupuesto!A:H,7,FALSE),"") | F35: SISTEMA DE PURIFICACION DE AGUA | G35: Etapa 1 -D/IR | H35: 4512567980 | I35: Comprometido | J35: 25.06.2026 | K35: 1 | L35: DOP | M35: =IF(BD.PD[[#This Row],[Mon]]="DOP",1,HLOOKUP(BD.PD[[#This Row],[Mon]],$K$1:$L$2,2,FALSE)) -> 1 | N35: 945223.71 | O35: =BD.PD[[#This Row],[Cant.]]*BD.PD[[#This Row],[ Tasa ]]*BD.PD[[#This Row],[ Precio Und.]] -> 945223.71 | P35: 0 | Q35: =IF(BD.PD[[#This Row],[Liquid. '[%']]]<>0,(BD.PD[[#This Row],[Valor Neto '[DOP']]]*BD.PD[[#This Row],[Liquid. '[%']]])+BD.PD[[#This Row],[Valor Neto '[DOP']]],BD.PD[[#This Row],[Valor Neto '[DOP']]]) -> 945223.71 | R35: =BD.PD[[#This Row],[Ppto. Orden Interna '[DOP']]]/HLOOKUP("USD",$K$1:$L$2,2,FALSE) -> 15495.471 | S35: 77325 KEAN GROUP SRL | U35: NTCO011104 | V35: 801667 | W35: 77325 KEAN GROUP SRL | X35: 7 | Y35: 0.5 | Z35: =BD.PD[[#This Row],[Av.P1 '[%']]]*BD.PD[[#This Row],[Ppto. Orden Interna '[DOP']]] -> 472611.85 | AA35: 21 | AB35: 0.5 | AC35: =BD.PD[[#This Row],[Av.P2 '[%']]]*BD.PD[[#This Row],[Ppto. Orden Interna '[DOP']]] -> 472611.85 | AF35: =BD.PD[[#This Row],[Av.P3 '[%']]]*BD.PD[[#This Row],[Ppto. Orden Interna '[DOP']]] -> 0 | AM35: =BD.PD[[#This Row],[Pago 3]]+BD.PD[[#This Row],[Pago 2]]+BD.PD[[#This Row],[Pago 1]] -> 945223.71 | AN35: Sirena Compacta | AO35: Sirena Las Terrenas | AP35: MC33 | AQ35: Marrón | AR35: 594 | AS35: Orden Colocada
A36: 2.06 | C36: =VLOOKUP(BD.PD[[#This Row],[Pos]],PPto[],3,FALSE) -> 2.06 Instalación de Gas | D36: OI | E36: =IF(BD.PD[[#This Row],[.]]="*",VLOOKUP(BD.PD[[#This Row],[Pos]],Presupuesto!A:H,7,FALSE),"") | F36: SISTEMA DETECCION GAS COCINA | G36: Etapa 1 -D/IR | H36: 4513013952 | I36: Comprometido | J36: 07.07.2026 | K36: 1 | L36: DOP | M36: =IF(BD.PD[[#This Row],[Mon]]="DOP",1,HLOOKUP(BD.PD[[#This Row],[Mon]],$K$1:$L$2,2,FALSE)) -> 1 | N36: 668846.99 | O36: =BD.PD[[#This Row],[Cant.]]*BD.PD[[#This Row],[ Tasa ]]*BD.PD[[#This Row],[ Precio Und.]] -> 668846.99 | P36: 0 | Q36: =IF(BD.PD[[#This Row],[Liquid. '[%']]]<>0,(BD.PD[[#This Row],[Valor Neto '[DOP']]]*BD.PD[[#This Row],[Liquid. '[%']]])+BD.PD[[#This Row],[Valor Neto '[DOP']]],BD.PD[[#This Row],[Valor Neto '[DOP']]]) -> 668846.99 | R36: =BD.PD[[#This Row],[Ppto. Orden Interna '[DOP']]]/HLOOKUP("USD",$K$1:$L$2,2,FALSE) -> 10964.705 | S36: 77139 MULTISERVICIOS SMART FULL CONTROL M | U36: NTCO011104 | V36: 801667 | W36: 77139 MULTISERVICIOS SMART FULL CONTROL M | X36: 19 | Y36: 0.5 | Z36: =BD.PD[[#This Row],[Av.P1 '[%']]]*BD.PD[[#This Row],[Ppto. Orden Interna '[DOP']]] -> 334423.49 | AA36: 21 | AB36: 0.5 | AC36: =BD.PD[[#This Row],[Av.P2 '[%']]]*BD.PD[[#This Row],[Ppto. Orden Interna '[DOP']]] -> 334423.49 | AF36: =BD.PD[[#This Row],[Av.P3 '[%']]]*BD.PD[[#This Row],[Ppto. Orden Interna '[DOP']]] -> 0 | AM36: =BD.PD[[#This Row],[Pago 3]]+BD.PD[[#This Row],[Pago 2]]+BD.PD[[#This Row],[Pago 1]] -> 668846.99 | AN36: Sirena Compacta | AO36: Sirena Las Terrenas | AP36: MC33 | AQ36: Marrón | AR36: 594 | AS36: Orden Colocada
A37: 2.07 | B37: * | C37: =VLOOKUP(BD.PD[[#This Row],[Pos]],PPto[],3,FALSE) -> 2.07 Sistema Contra Incendios | D37: * | E37: =IF(BD.PD[[#This Row],[.]]="*",VLOOKUP(BD.PD[[#This Row],[Pos]],Presupuesto!A:H,7,FALSE),"") -> 113206.86 | K37: 1 | L37: USD | M37: =IF(BD.PD[[#This Row],[Mon]]="DOP",1,HLOOKUP(BD.PD[[#This Row],[Mon]],$K$1:$L$2,2,FALSE)) -> 61 | N37: 0 | O37: =BD.PD[[#This Row],[Cant.]]*BD.PD[[#This Row],[ Tasa ]]*BD.PD[[#This Row],[ Precio Und.]] -> 0 | P37: 0 | Q37: =IF(BD.PD[[#This Row],[Liquid. '[%']]]<>0,(BD.PD[[#This Row],[Valor Neto '[DOP']]]*BD.PD[[#This Row],[Liquid. '[%']]])+BD.PD[[#This Row],[Valor Neto '[DOP']]],BD.PD[[#This Row],[Valor Neto '[DOP']]]) -> 0 | R37: =BD.PD[[#This Row],[Ppto. Orden Interna '[DOP']]]/HLOOKUP("USD",$K$1:$L$2,2,FALSE) -> 0 | Z37: =BD.PD[[#This Row],[Av.P1 '[%']]]*BD.PD[[#This Row],[Ppto. Orden Interna '[DOP']]] -> 0 | AC37: =BD.PD[[#This Row],[Av.P2 '[%']]]*BD.PD[[#This Row],[Ppto. Orden Interna '[DOP']]] -> 0 | AF37: =BD.PD[[#This Row],[Av.P3 '[%']]]*BD.PD[[#This Row],[Ppto. Orden Interna '[DOP']]] -> 0 | AM37: =BD.PD[[#This Row],[Pago 3]]+BD.PD[[#This Row],[Pago 2]]+BD.PD[[#This Row],[Pago 1]] -> 0
A38: 2.07 | C38: =VLOOKUP(BD.PD[[#This Row],[Pos]],PPto[],3,FALSE) -> 2.07 Sistema Contra Incendios | D38: OI | E38: =IF(BD.PD[[#This Row],[.]]="*",VLOOKUP(BD.PD[[#This Row],[Pos]],Presupuesto!A:H,7,FALSE),"") | F38: EXTINTOR PORT. ABC 10LB BUCKEYE | G38: Etapa 2 -D/IR | H38: 4513015767 | I38: Comprometido | J38: 08.07.2026 | K38: 20 | L38: DOP | M38: =IF(BD.PD[[#This Row],[Mon]]="DOP",1,HLOOKUP(BD.PD[[#This Row],[Mon]],$K$1:$L$2,2,FALSE)) -> 1 | N38: 5926 | O38: =BD.PD[[#This Row],[Cant.]]*BD.PD[[#This Row],[ Tasa ]]*BD.PD[[#This Row],[ Precio Und.]] -> 118520 | P38: 0 | Q38: =IF(BD.PD[[#This Row],[Liquid. '[%']]]<>0,(BD.PD[[#This Row],[Valor Neto '[DOP']]]*BD.PD[[#This Row],[Liquid. '[%']]])+BD.PD[[#This Row],[Valor Neto '[DOP']]],BD.PD[[#This Row],[Valor Neto '[DOP']]]) -> 118520 | R38: =BD.PD[[#This Row],[Ppto. Orden Interna '[DOP']]]/HLOOKUP("USD",$K$1:$L$2,2,FALSE) -> 1942.9508 | S38: 7430 DE SOTO TRADING SRL | U38: NTCO011104 | V38: 801667 | W38: 7430 DE SOTO TRADING SRL | X38: 21 | Y38: 1 | Z38: =BD.PD[[#This Row],[Av.P1 '[%']]]*BD.PD[[#This Row],[Ppto. Orden Interna '[DOP']]] -> 118520 | AC38: =BD.PD[[#This Row],[Av.P2 '[%']]]*BD.PD[[#This Row],[Ppto. Orden Interna '[DOP']]] -> 0 | AF38: =BD.PD[[#This Row],[Av.P3 '[%']]]*BD.PD[[#This Row],[Ppto. Orden Interna '[DOP']]] -> 0 | AM38: =BD.PD[[#This Row],[Pago 3]]+BD.PD[[#This Row],[Pago 2]]+BD.PD[[#This Row],[Pago 1]] -> 118520 | AN38: Sirena Compacta | AO38: Sirena Las Terrenas | AP38: MC33 | AQ38: Marrón | AR38: 594 | AS38: Orden Colocada
A39: 2.07 | C39: =VLOOKUP(BD.PD[[#This Row],[Pos]],PPto[],3,FALSE) -> 2.07 Sistema Contra Incendios | D39: OI | E39: =IF(BD.PD[[#This Row],[.]]="*",VLOOKUP(BD.PD[[#This Row],[Pos]],Presupuesto!A:H,7,FALSE),"") | F39: EXTINTOR PORT. ABC 20LB BUCKEYE | G39: Etapa 2 -D/IR | H39: 4513015767 | I39: Comprometido | J39: 08.07.2026 | K39: 14 | L39: DOP | M39: =IF(BD.PD[[#This Row],[Mon]]="DOP",1,HLOOKUP(BD.PD[[#This Row],[Mon]],$K$1:$L$2,2,FALSE)) -> 1 | N39: 9230 | O39: =BD.PD[[#This Row],[Cant.]]*BD.PD[[#This Row],[ Tasa ]]*BD.PD[[#This Row],[ Precio Und.]] -> 129220 | P39: 0 | Q39: =IF(BD.PD[[#This Row],[Liquid. '[%']]]<>0,(BD.PD[[#This Row],[Valor Neto '[DOP']]]*BD.PD[[#This Row],[Liquid. '[%']]])+BD.PD[[#This Row],[Valor Neto '[DOP']]],BD.PD[[#This Row],[Valor Neto '[DOP']]]) -> 129220 | R39: =BD.PD[[#This Row],[Ppto. Orden Interna '[DOP']]]/HLOOKUP("USD",$K$1:$L$2,2,FALSE) -> 2118.3607 | S39: 7430 DE SOTO TRADING SRL | U39: NTCO011104 | V39: 801667 | W39: 7430 DE SOTO TRADING SRL | X39: 21 | Y39: 1 | Z39: =BD.PD[[#This Row],[Av.P1 '[%']]]*BD.PD[[#This Row],[Ppto. Orden Interna '[DOP']]] -> 129220 | AC39: =BD.PD[[#This Row],[Av.P2 '[%']]]*BD.PD[[#This Row],[Ppto. Orden Interna '[DOP']]] -> 0 | AF39: =BD.PD[[#This Row],[Av.P3 '[%']]]*BD.PD[[#This Row],[Ppto. Orden Interna '[DOP']]] -> 0 | AM39: =BD.PD[[#This Row],[Pago 3]]+BD.PD[[#This Row],[Pago 2]]+BD.PD[[#This Row],[Pago 1]] -> 129220 | AN39: Sirena Compacta | AO39: Sirena Las Terrenas | AP39: MC33 | AQ39: Marrón | AR39: 594 | AS39: Orden Colocada
A40: 2.07 | C40: =VLOOKUP(BD.PD[[#This Row],[Pos]],PPto[],3,FALSE) -> 2.07 Sistema Contra Incendios | D40: OI | E40: =IF(BD.PD[[#This Row],[.]]="*",VLOOKUP(BD.PD[[#This Row],[Pos]],Presupuesto!A:H,7,FALSE),"") | F40: EXTINTOR CO2 GAS CARBONICO 15LB | G40: Etapa 2 -D/IR | H40: 4513015767 | I40: Comprometido | J40: 08.07.2026 | K40: 2 | L40: DOP | M40: =IF(BD.PD[[#This Row],[Mon]]="DOP",1,HLOOKUP(BD.PD[[#This Row],[Mon]],$K$1:$L$2,2,FALSE)) -> 1 | N40: 18957 | O40: =BD.PD[[#This Row],[Cant.]]*BD.PD[[#This Row],[ Tasa ]]*BD.PD[[#This Row],[ Precio Und.]] -> 37914 | P40: 0 | Q40: =IF(BD.PD[[#This Row],[Liquid. '[%']]]<>0,(BD.PD[[#This Row],[Valor Neto '[DOP']]]*BD.PD[[#This Row],[Liquid. '[%']]])+BD.PD[[#This Row],[Valor Neto '[DOP']]],BD.PD[[#This Row],[Valor Neto '[DOP']]]) -> 37914 | R40: =BD.PD[[#This Row],[Ppto. Orden Interna '[DOP']]]/HLOOKUP("USD",$K$1:$L$2,2,FALSE) -> 621.54098 | S40: 7430 DE SOTO TRADING SRL | U40: NTCO011104 | V40: 801667 | W40: 7430 DE SOTO TRADING SRL | X40: 21 | Y40: 1 | Z40: =BD.PD[[#This Row],[Av.P1 '[%']]]*BD.PD[[#This Row],[Ppto. Orden Interna '[DOP']]] -> 37914 | AC40: =BD.PD[[#This Row],[Av.P2 '[%']]]*BD.PD[[#This Row],[Ppto. Orden Interna '[DOP']]] -> 0 | AF40: =BD.PD[[#This Row],[Av.P3 '[%']]]*BD.PD[[#This Row],[Ppto. Orden Interna '[DOP']]] -> 0 | AM40: =BD.PD[[#This Row],[Pago 3]]+BD.PD[[#This Row],[Pago 2]]+BD.PD[[#This Row],[Pago 1]] -> 37914 | AN40: Sirena Compacta | AO40: Sirena Las Terrenas | AP40: MC33 | AQ40: Marrón | AR40: 594 | AS40: Orden Colocada
A41: 2.07 | C41: =VLOOKUP(BD.PD[[#This Row],[Pos]],PPto[],3,FALSE) -> 2.07 Sistema Contra Incendios | D41: OI | E41: =IF(BD.PD[[#This Row],[.]]="*",VLOOKUP(BD.PD[[#This Row],[Pos]],Presupuesto!A:H,7,FALSE),"") | F41: EXTINTOR ABC HALOTRON AGENTE LIMPIO 11LB | G41: Etapa 2 -D/IR | H41: 4513015767 | I41: Comprometido | J41: 08.07.2026 | K41: 3 | L41: DOP | M41: =IF(BD.PD[[#This Row],[Mon]]="DOP",1,HLOOKUP(BD.PD[[#This Row],[Mon]],$K$1:$L$2,2,FALSE)) -> 1 | N41: 87646 | O41: =BD.PD[[#This Row],[Cant.]]*BD.PD[[#This Row],[ Tasa ]]*BD.PD[[#This Row],[ Precio Und.]] -> 262938 | P41: 0 | Q41: =IF(BD.PD[[#This Row],[Liquid. '[%']]]<>0,(BD.PD[[#This Row],[Valor Neto '[DOP']]]*BD.PD[[#This Row],[Liquid. '[%']]])+BD.PD[[#This Row],[Valor Neto '[DOP']]],BD.PD[[#This Row],[Valor Neto '[DOP']]]) -> 262938 | R41: =BD.PD[[#This Row],[Ppto. Orden Interna '[DOP']]]/HLOOKUP("USD",$K$1:$L$2,2,FALSE) -> 4310.459 | S41: 7430 DE SOTO TRADING SRL | U41: NTCO011104 | V41: 801667 | W41: 7430 DE SOTO TRADING SRL | X41: 21 | Y41: 1 | Z41: =BD.PD[[#This Row],[Av.P1 '[%']]]*BD.PD[[#This Row],[Ppto. Orden Interna '[DOP']]] -> 262938 | AC41: =BD.PD[[#This Row],[Av.P2 '[%']]]*BD.PD[[#This Row],[Ppto. Orden Interna '[DOP']]] -> 0 | AF41: =BD.PD[[#This Row],[Av.P3 '[%']]]*BD.PD[[#This Row],[Ppto. Orden Interna '[DOP']]] -> 0 | AM41: =BD.PD[[#This Row],[Pago 3]]+BD.PD[[#This Row],[Pago 2]]+BD.PD[[#This Row],[Pago 1]] -> 262938 | AN41: Sirena Compacta | AO41: Sirena Las Terrenas | AP41: MC33 | AQ41: Marrón | AR41: 594 | AS41: Orden Colocada
A42: 2.07 | C42: =VLOOKUP(BD.PD[[#This Row],[Pos]],PPto[],3,FALSE) -> 2.07 Sistema Contra Incendios | D42: OI | E42: =IF(BD.PD[[#This Row],[.]]="*",VLOOKUP(BD.PD[[#This Row],[Pos]],Presupuesto!A:H,7,FALSE),"") | F42: EXTINTOR CO2 GAS CARBONICO 10LB | G42: Etapa 2 -D/IR | H42: 4513015767 | I42: Comprometido | J42: 08.07.2026 | K42: 3 | L42: DOP | M42: =IF(BD.PD[[#This Row],[Mon]]="DOP",1,HLOOKUP(BD.PD[[#This Row],[Mon]],$K$1:$L$2,2,FALSE)) -> 1 | N42: 16606 | O42: =BD.PD[[#This Row],[Cant.]]*BD.PD[[#This Row],[ Tasa ]]*BD.PD[[#This Row],[ Precio Und.]] -> 49818 | P42: 0 | Q42: =IF(BD.PD[[#This Row],[Liquid. '[%']]]<>0,(BD.PD[[#This Row],[Valor Neto '[DOP']]]*BD.PD[[#This Row],[Liquid. '[%']]])+BD.PD[[#This Row],[Valor Neto '[DOP']]],BD.PD[[#This Row],[Valor Neto '[DOP']]]) -> 49818 | R42: =BD.PD[[#This Row],[Ppto. Orden Interna '[DOP']]]/HLOOKUP("USD",$K$1:$L$2,2,FALSE) -> 816.68852 | S42: 7430 DE SOTO TRADING SRL | U42: NTCO011104 | V42: 801667 | W42: 7430 DE SOTO TRADING SRL | X42: 21 | Y42: 1 | Z42: =BD.PD[[#This Row],[Av.P1 '[%']]]*BD.PD[[#This Row],[Ppto. Orden Interna '[DOP']]] -> 49818 | AC42: =BD.PD[[#This Row],[Av.P2 '[%']]]*BD.PD[[#This Row],[Ppto. Orden Interna '[DOP']]] -> 0 | AF42: =BD.PD[[#This Row],[Av.P3 '[%']]]*BD.PD[[#This Row],[Ppto. Orden Interna '[DOP']]] -> 0 | AM42: =BD.PD[[#This Row],[Pago 3]]+BD.PD[[#This Row],[Pago 2]]+BD.PD[[#This Row],[Pago 1]] -> 49818 | AN42: Sirena Compacta | AO42: Sirena Las Terrenas | AP42: MC33 | AQ42: Marrón | AR42: 594 | AS42: Orden Colocada
A43: 2.07 | C43: =VLOOKUP(BD.PD[[#This Row],[Pos]],PPto[],3,FALSE) -> 2.07 Sistema Contra Incendios | D43: OI | E43: =IF(BD.PD[[#This Row],[.]]="*",VLOOKUP(BD.PD[[#This Row],[Pos]],Presupuesto!A:H,7,FALSE),"") | F43: GABINETE P/EXTINTOR ABC 20 LB | G43: Etapa 2 -D/IR | H43: 4513015767 | I43: Comprometido | J43: 08.07.2026 | K43: 5 | L43: DOP | M43: =IF(BD.PD[[#This Row],[Mon]]="DOP",1,HLOOKUP(BD.PD[[#This Row],[Mon]],$K$1:$L$2,2,FALSE)) -> 1 | N43: 4200 | O43: =BD.PD[[#This Row],[Cant.]]*BD.PD[[#This Row],[ Tasa ]]*BD.PD[[#This Row],[ Precio Und.]] -> 21000 | P43: 0 | Q43: =IF(BD.PD[[#This Row],[Liquid. '[%']]]<>0,(BD.PD[[#This Row],[Valor Neto '[DOP']]]*BD.PD[[#This Row],[Liquid. '[%']]])+BD.PD[[#This Row],[Valor Neto '[DOP']]],BD.PD[[#This Row],[Valor Neto '[DOP']]]) -> 21000 | R43: =BD.PD[[#This Row],[Ppto. Orden Interna '[DOP']]]/HLOOKUP("USD",$K$1:$L$2,2,FALSE) -> 344.2623 | S43: 7430 DE SOTO TRADING SRL | U43: NTCO011104 | V43: 801667 | W43: 7430 DE SOTO TRADING SRL | X43: 21 | Y43: 1 | Z43: =BD.PD[[#This Row],[Av.P1 '[%']]]*BD.PD[[#This Row],[Ppto. Orden Interna '[DOP']]] -> 21000 | AC43: =BD.PD[[#This Row],[Av.P2 '[%']]]*BD.PD[[#This Row],[Ppto. Orden Interna '[DOP']]] -> 0 | AF43: =BD.PD[[#This Row],[Av.P3 '[%']]]*BD.PD[[#This Row],[Ppto. Orden Interna '[DOP']]] -> 0 | AM43: =BD.PD[[#This Row],[Pago 3]]+BD.PD[[#This Row],[Pago 2]]+BD.PD[[#This Row],[Pago 1]] -> 21000 | AN43: Sirena Compacta | AO43: Sirena Las Terrenas | AP43: MC33 | AQ43: Marrón | AR43: 594 | AS43: Orden Colocada
A44: 2.07 | C44: =VLOOKUP(BD.PD[[#This Row],[Pos]],PPto[],3,FALSE) -> 2.07 Sistema Contra Incendios | D44: OI | E44: =IF(BD.PD[[#This Row],[.]]="*",VLOOKUP(BD.PD[[#This Row],[Pos]],Presupuesto!A:H,7,FALSE),"") | F44: COVER PARA EXTINTORES | G44: Etapa 2 -D/IR | H44: 4513015767 | I44: Comprometido | J44: 08.07.2026 | K44: 3 | L44: DOP | M44: =IF(BD.PD[[#This Row],[Mon]]="DOP",1,HLOOKUP(BD.PD[[#This Row],[Mon]],$K$1:$L$2,2,FALSE)) -> 1 | N44: 7155 | O44: =BD.PD[[#This Row],[Cant.]]*BD.PD[[#This Row],[ Tasa ]]*BD.PD[[#This Row],[ Precio Und.]] -> 21465 | P44: 0 | Q44: =IF(BD.PD[[#This Row],[Liquid. '[%']]]<>0,(BD.PD[[#This Row],[Valor Neto '[DOP']]]*BD.PD[[#This Row],[Liquid. '[%']]])+BD.PD[[#This Row],[Valor Neto '[DOP']]],BD.PD[[#This Row],[Valor Neto '[DOP']]]) -> 21465 | R44: =BD.PD[[#This Row],[Ppto. Orden Interna '[DOP']]]/HLOOKUP("USD",$K$1:$L$2,2,FALSE) -> 351.88525 | S44: 7430 DE SOTO TRADING SRL | U44: NTCO011104 | V44: 801667 | W44: 7430 DE SOTO TRADING SRL | X44: 21 | Y44: 1 | Z44: =BD.PD[[#This Row],[Av.P1 '[%']]]*BD.PD[[#This Row],[Ppto. Orden Interna '[DOP']]] -> 21465 | AC44: =BD.PD[[#This Row],[Av.P2 '[%']]]*BD.PD[[#This Row],[Ppto. Orden Interna '[DOP']]] -> 0 | AF44: =BD.PD[[#This Row],[Av.P3 '[%']]]*BD.PD[[#This Row],[Ppto. Orden Interna '[DOP']]] -> 0 | AM44: =BD.PD[[#This Row],[Pago 3]]+BD.PD[[#This Row],[Pago 2]]+BD.PD[[#This Row],[Pago 1]] -> 21465 | AN44: Sirena Compacta | AO44: Sirena Las Terrenas | AP44: MC33 | AQ44: Marrón | AR44: 594 | AS44: Orden Colocada
A45: 2.07 | C45: =VLOOKUP(BD.PD[[#This Row],[Pos]],PPto[],3,FALSE) -> 2.07 Sistema Contra Incendios | D45: OI | E45: =IF(BD.PD[[#This Row],[.]]="*",VLOOKUP(BD.PD[[#This Row],[Pos]],Presupuesto!A:H,7,FALSE),"") | F45: INSTALACION DE EXINTORES | G45: Etapa 2 -D/IR | H45: 4513015767 | I45: Comprometido | J45: 08.07.2026 | K45: 42 | L45: DOP | M45: =IF(BD.PD[[#This Row],[Mon]]="DOP",1,HLOOKUP(BD.PD[[#This Row],[Mon]],$K$1:$L$2,2,FALSE)) -> 1 | N45: 150 | O45: =BD.PD[[#This Row],[Cant.]]*BD.PD[[#This Row],[ Tasa ]]*BD.PD[[#This Row],[ Precio Und.]] -> 6300 | P45: 0 | Q45: =IF(BD.PD[[#This Row],[Liquid. '[%']]]<>0,(BD.PD[[#This Row],[Valor Neto '[DOP']]]*BD.PD[[#This Row],[Liquid. '[%']]])+BD.PD[[#This Row],[Valor Neto '[DOP']]],BD.PD[[#This Row],[Valor Neto '[DOP']]]) -> 6300 | R45: =BD.PD[[#This Row],[Ppto. Orden Interna '[DOP']]]/HLOOKUP("USD",$K$1:$L$2,2,FALSE) -> 103.27869 | S45: 7430 DE SOTO TRADING SRL | U45: NTCO011104 | V45: 801667 | W45: 7430 DE SOTO TRADING SRL | X45: 21 | Y45: 1 | Z45: =BD.PD[[#This Row],[Av.P1 '[%']]]*BD.PD[[#This Row],[Ppto. Orden Interna '[DOP']]] -> 6300 | AC45: =BD.PD[[#This Row],[Av.P2 '[%']]]*BD.PD[[#This Row],[Ppto. Orden Interna '[DOP']]] -> 0 | AF45: =BD.PD[[#This Row],[Av.P3 '[%']]]*BD.PD[[#This Row],[Ppto. Orden Interna '[DOP']]] -> 0 | AM45: =BD.PD[[#This Row],[Pago 3]]+BD.PD[[#This Row],[Pago 2]]+BD.PD[[#This Row],[Pago 1]] -> 6300 | AN45: Sirena Compacta | AO45: Sirena Las Terrenas | AP45: MC33 | AQ45: Marrón | AR45: 594 | AS45: Orden Colocada
A46: 2.07 | C46: =VLOOKUP(BD.PD[[#This Row],[Pos]],PPto[],3,FALSE) -> 2.07 Sistema Contra Incendios | D46: OI | E46: =IF(BD.PD[[#This Row],[.]]="*",VLOOKUP(BD.PD[[#This Row],[Pos]],Presupuesto!A:H,7,FALSE),"") | F46: SERVICIO DE TRANSPORTE CON ITBIS | G46: Etapa 2 -D/IR | H46: 4513015767 | I46: Comprometido | J46: 08.07.2026 | K46: 1 | L46: DOP | M46: =IF(BD.PD[[#This Row],[Mon]]="DOP",1,HLOOKUP(BD.PD[[#This Row],[Mon]],$K$1:$L$2,2,FALSE)) -> 1 | N46: 15000 | O46: =BD.PD[[#This Row],[Cant.]]*BD.PD[[#This Row],[ Tasa ]]*BD.PD[[#This Row],[ Precio Und.]] -> 15000 | P46: 0 | Q46: =IF(BD.PD[[#This Row],[Liquid. '[%']]]<>0,(BD.PD[[#This Row],[Valor Neto '[DOP']]]*BD.PD[[#This Row],[Liquid. '[%']]])+BD.PD[[#This Row],[Valor Neto '[DOP']]],BD.PD[[#This Row],[Valor Neto '[DOP']]]) -> 15000 | R46: =BD.PD[[#This Row],[Ppto. Orden Interna '[DOP']]]/HLOOKUP("USD",$K$1:$L$2,2,FALSE) -> 245.90164 | S46: 7430 DE SOTO TRADING SRL | U46: NTCO011104 | V46: 801667 | W46: 7430 DE SOTO TRADING SRL | X46: 21 | Y46: 1 | Z46: =BD.PD[[#This Row],[Av.P1 '[%']]]*BD.PD[[#This Row],[Ppto. Orden Interna '[DOP']]] -> 15000 | AC46: =BD.PD[[#This Row],[Av.P2 '[%']]]*BD.PD[[#This Row],[Ppto. Orden Interna '[DOP']]] -> 0 | AF46: =BD.PD[[#This Row],[Av.P3 '[%']]]*BD.PD[[#This Row],[Ppto. Orden Interna '[DOP']]] -> 0 | AM46: =BD.PD[[#This Row],[Pago 3]]+BD.PD[[#This Row],[Pago 2]]+BD.PD[[#This Row],[Pago 1]] -> 15000 | AN46: Sirena Compacta | AO46: Sirena Las Terrenas | AP46: MC33 | AQ46: Marrón | AR46: 594 | AS46: Orden Colocada
A47: 2.07 | C47: =VLOOKUP(BD.PD[[#This Row],[Pos]],PPto[],3,FALSE) -> 2.07 Sistema Contra Incendios | D47: OI | E47: =IF(BD.PD[[#This Row],[.]]="*",VLOOKUP(BD.PD[[#This Row],[Pos]],Presupuesto!A:H,7,FALSE),"") | F47: GABINETE P/EXTINTOR ABC 20 LB- ADICIONAL | G47: Etapa 2 -D/IR | H47: 4513127976 | I47: Comprometido | J47: 07.10.2026 | K47: 4 | L47: DOP | M47: =IF(BD.PD[[#This Row],[Mon]]="DOP",1,HLOOKUP(BD.PD[[#This Row],[Mon]],$K$1:$L$2,2,FALSE)) -> 1 | N47: 3800 | O47: =BD.PD[[#This Row],[Cant.]]*BD.PD[[#This Row],[ Tasa ]]*BD.PD[[#This Row],[ Precio Und.]] -> 15200 | P47: 0 | Q47: =IF(BD.PD[[#This Row],[Liquid. '[%']]]<>0,(BD.PD[[#This Row],[Valor Neto '[DOP']]]*BD.PD[[#This Row],[Liquid. '[%']]])+BD.PD[[#This Row],[Valor Neto '[DOP']]],BD.PD[[#This Row],[Valor Neto '[DOP']]]) -> 15200 | R47: =BD.PD[[#This Row],[Ppto. Orden Interna '[DOP']]]/HLOOKUP("USD",$K$1:$L$2,2,FALSE) -> 249.18033 | S47: 7430 DE SOTO TRADING SRL | U47: NTCO011104 | V47: 801667 | W47: 7430 DE SOTO TRADING SRL | X47: 22 | Y47: 1 | Z47: =BD.PD[[#This Row],[Av.P1 '[%']]]*BD.PD[[#This Row],[Ppto. Orden Interna '[DOP']]] -> 15200 | AC47: =BD.PD[[#This Row],[Av.P2 '[%']]]*BD.PD[[#This Row],[Ppto. Orden Interna '[DOP']]] -> 0 | AF47: =BD.PD[[#This Row],[Av.P3 '[%']]]*BD.PD[[#This Row],[Ppto. Orden Interna '[DOP']]] -> 0 | AM47: =BD.PD[[#This Row],[Pago 3]]+BD.PD[[#This Row],[Pago 2]]+BD.PD[[#This Row],[Pago 1]] -> 15200 | AN47: Sirena Compacta | AO47: Sirena Las Terrenas | AP47: MC33 | AQ47: Marrón | AR47: 594 | AS47: Orden Colocada
A48: 2.07 | C48: =VLOOKUP(BD.PD[[#This Row],[Pos]],PPto[],3,FALSE) -> 2.07 Sistema Contra Incendios | D48: OI | E48: =IF(BD.PD[[#This Row],[.]]="*",VLOOKUP(BD.PD[[#This Row],[Pos]],Presupuesto!A:H,7,FALSE),"") | F48: BOMBA SCI 1,500 GPM @145 PSI | G48: Etapa 1 -D/IR | H48: 4600073043 | I48: Stock AF01 | J48: 25.06.2026 | K48: 1 | L48: DOP | M48: =IF(BD.PD[[#This Row],[Mon]]="DOP",1,HLOOKUP(BD.PD[[#This Row],[Mon]],$K$1:$L$2,2,FALSE)) -> 1 | N48: 3662506.3 | O48: =BD.PD[[#This Row],[Cant.]]*BD.PD[[#This Row],[ Tasa ]]*BD.PD[[#This Row],[ Precio Und.]] -> 3662506.3 | P48: 0 | Q48: =IF(BD.PD[[#This Row],[Liquid. '[%']]]<>0,(BD.PD[[#This Row],[Valor Neto '[DOP']]]*BD.PD[[#This Row],[Liquid. '[%']]])+BD.PD[[#This Row],[Valor Neto '[DOP']]],BD.PD[[#This Row],[Valor Neto '[DOP']]]) -> 3662506.3 | R48: =BD.PD[[#This Row],[Ppto. Orden Interna '[DOP']]]/HLOOKUP("USD",$K$1:$L$2,2,FALSE) -> 60041.087 | S48: 35675 PATTERSON PUMP COMPANY | U48: NTCO011104 | V48: 801667 | W48: 35675 PATTERSON PUMP COMPANY | X48: 4 | Y48: 0.5 | Z48: =BD.PD[[#This Row],[Av.P1 '[%']]]*BD.PD[[#This Row],[Ppto. Orden Interna '[DOP']]] -> 1831253.1 | AA48: 9 | AB48: 0.5 | AC48: =BD.PD[[#This Row],[Av.P2 '[%']]]*BD.PD[[#This Row],[Ppto. Orden Interna '[DOP']]] -> 1831253.1 | AF48: =BD.PD[[#This Row],[Av.P3 '[%']]]*BD.PD[[#This Row],[Ppto. Orden Interna '[DOP']]] -> 0 | AM48: =BD.PD[[#This Row],[Pago 3]]+BD.PD[[#This Row],[Pago 2]]+BD.PD[[#This Row],[Pago 1]] -> 3662506.3 | AN48: Sirena Compacta | AO48: Sirena Las Terrenas | AP48: MC33 | AQ48: Marrón | AR48: 594 | AS48: Orden Colocada
A49: 2.07 | C49: =VLOOKUP(BD.PD[[#This Row],[Pos]],PPto[],3,FALSE) -> 2.07 Sistema Contra Incendios | D49: OI | E49: =IF(BD.PD[[#This Row],[.]]="*",VLOOKUP(BD.PD[[#This Row],[Pos]],Presupuesto!A:H,7,FALSE),"") | F49: INSTALACION BOMBA SCI 1,500 GPM | G49: Etapa 1 -D/IR | H49: 4512979133 | I49: Comprometido | J49: 25.06.2026 | K49: 1 | L49: USD | M49: =IF(BD.PD[[#This Row],[Mon]]="DOP",1,HLOOKUP(BD.PD[[#This Row],[Mon]],$K$1:$L$2,2,FALSE)) -> 61 | N49: 10000 | O49: =BD.PD[[#This Row],[Cant.]]*BD.PD[[#This Row],[ Tasa ]]*BD.PD[[#This Row],[ Precio Und.]] -> 610000 | P49: 0 | Q49: =IF(BD.PD[[#This Row],[Liquid. '[%']]]<>0,(BD.PD[[#This Row],[Valor Neto '[DOP']]]*BD.PD[[#This Row],[Liquid. '[%']]])+BD.PD[[#This Row],[Valor Neto '[DOP']]],BD.PD[[#This Row],[Valor Neto '[DOP']]]) -> 610000 | R49: =BD.PD[[#This Row],[Ppto. Orden Interna '[DOP']]]/HLOOKUP("USD",$K$1:$L$2,2,FALSE) -> 10000 | S49: 77274 CONSTRUCTORA FIREPRO SRL | U49: NTCO011104 | V49: 801667 | W49: 77274 CONSTRUCTORA FIREPRO SRL | X49: 18 | Y49: 0.5 | Z49: =BD.PD[[#This Row],[Av.P1 '[%']]]*BD.PD[[#This Row],[Ppto. Orden Interna '[DOP']]] -> 305000 | AA49: 21 | AB49: 0.5 | AC49: =BD.PD[[#This Row],[Av.P2 '[%']]]*BD.PD[[#This Row],[Ppto. Orden Interna '[DOP']]] -> 305000 | AF49: =BD.PD[[#This Row],[Av.P3 '[%']]]*BD.PD[[#This Row],[Ppto. Orden Interna '[DOP']]] -> 0 | AM49: =BD.PD[[#This Row],[Pago 3]]+BD.PD[[#This Row],[Pago 2]]+BD.PD[[#This Row],[Pago 1]] -> 610000 | AN49: Sirena Compacta | AO49: Sirena Las Terrenas | AP49: MC33 | AQ49: Marrón | AR49: 594 | AS49: Orden Colocada
A50: 2.07 | C50: =VLOOKUP(BD.PD[[#This Row],[Pos]],PPto[],3,FALSE) -> 2.07 Sistema Contra Incendios | D50: OI | E50: =IF(BD.PD[[#This Row],[.]]="*",VLOOKUP(BD.PD[[#This Row],[Pos]],Presupuesto!A:H,7,FALSE),"") | F50: DIRECCION TECNICA | G50: Etapa 1 -D/IR | H50: 4512979133 | I50: Comprometido | J50: 25.06.2026 | K50: 1 | L50: USD | M50: =IF(BD.PD[[#This Row],[Mon]]="DOP",1,HLOOKUP(BD.PD[[#This Row],[Mon]],$K$1:$L$2,2,FALSE)) -> 61 | N50: 1000 | O50: =BD.PD[[#This Row],[Cant.]]*BD.PD[[#This Row],[ Tasa ]]*BD.PD[[#This Row],[ Precio Und.]] -> 61000 | P50: 0 | Q50: =IF(BD.PD[[#This Row],[Liquid. '[%']]]<>0,(BD.PD[[#This Row],[Valor Neto '[DOP']]]*BD.PD[[#This Row],[Liquid. '[%']]])+BD.PD[[#This Row],[Valor Neto '[DOP']]],BD.PD[[#This Row],[Valor Neto '[DOP']]]) -> 61000 | R50: =BD.PD[[#This Row],[Ppto. Orden Interna '[DOP']]]/HLOOKUP("USD",$K$1:$L$2,2,FALSE) -> 1000 | S50: 77274 CONSTRUCTORA FIREPRO SRL | U50: NTCO011104 | V50: 801667 | W50: 77274 CONSTRUCTORA FIREPRO SRL | X50: 18 | Y50: 0.5 | Z50: =BD.PD[[#This Row],[Av.P1 '[%']]]*BD.PD[[#This Row],[Ppto. Orden Interna '[DOP']]] -> 30500 | AA50: 21 | AB50: 0.5 | AC50: =BD.PD[[#This Row],[Av.P2 '[%']]]*BD.PD[[#This Row],[Ppto. Orden Interna '[DOP']]] -> 30500 | AF50: =BD.PD[[#This Row],[Av.P3 '[%']]]*BD.PD[[#This Row],[Ppto. Orden Interna '[DOP']]] -> 0 | AM50: =BD.PD[[#This Row],[Pago 3]]+BD.PD[[#This Row],[Pago 2]]+BD.PD[[#This Row],[Pago 1]] -> 61000 | AN50: Sirena Compacta | AO50: Sirena Las Terrenas | AP50: MC33 | AQ50: Marrón | AR50: 594 | AS50: Orden Colocada
A51: 2.07 | C51: =VLOOKUP(BD.PD[[#This Row],[Pos]],PPto[],3,FALSE) -> 2.07 Sistema Contra Incendios | D51: OI | E51: =IF(BD.PD[[#This Row],[.]]="*",VLOOKUP(BD.PD[[#This Row],[Pos]],Presupuesto!A:H,7,FALSE),"") | F51: EXTENSION LONGITUD BOMBA SCI E INSTALACION TRANSFORMADOR (ADICIONAL) | G51: Etapa 1 -D/IR | H51: 4513057034 | I51: Comprometido | J51: 10.08.2026 | K51: 1 | L51: USD | M51: =IF(BD.PD[[#This Row],[Mon]]="DOP",1,HLOOKUP(BD.PD[[#This Row],[Mon]],$K$1:$L$2,2,FALSE)) -> 61 | N51: 9987.79 | O51: =BD.PD[[#This Row],[Cant.]]*BD.PD[[#This Row],[ Tasa ]]*BD.PD[[#This Row],[ Precio Und.]] -> 609255.19 | P51: 0 | Q51: =IF(BD.PD[[#This Row],[Liquid. '[%']]]<>0,(BD.PD[[#This Row],[Valor Neto '[DOP']]]*BD.PD[[#This Row],[Liquid. '[%']]])+BD.PD[[#This Row],[Valor Neto '[DOP']]],BD.PD[[#This Row],[Valor Neto '[DOP']]]) -> 609255.19 | R51: =BD.PD[[#This Row],[Ppto. Orden Interna '[DOP']]]/HLOOKUP("USD",$K$1:$L$2,2,FALSE) -> 9987.79 | S51: 77274 CONSTRUCTORA FIREPRO SRL | U51: NTCO011104 | V51: 801667 | W51: 77274 CONSTRUCTORA FIREPRO SRL | X51: 21 | Y51: 1 | Z51: =BD.PD[[#This Row],[Av.P1 '[%']]]*BD.PD[[#This Row],[Ppto. Orden Interna '[DOP']]] -> 609255.19 | AC51: =BD.PD[[#This Row],[Av.P2 '[%']]]*BD.PD[[#This Row],[Ppto. Orden Interna '[DOP']]] -> 0 | AF51: =BD.PD[[#This Row],[Av.P3 '[%']]]*BD.PD[[#This Row],[Ppto. Orden Interna '[DOP']]] -> 0 | AM51: =BD.PD[[#This Row],[Pago 3]]+BD.PD[[#This Row],[Pago 2]]+BD.PD[[#This Row],[Pago 1]] -> 609255.19 | AN51: Sirena Compacta | AO51: Sirena Las Terrenas | AP51: MC33 | AQ51: Marrón | AR51: 594 | AS51: Orden Colocada
A52: 2.07 | C52: =VLOOKUP(BD.PD[[#This Row],[Pos]],PPto[],3,FALSE) -> 2.07 Sistema Contra Incendios | D52: OI | E52: =IF(BD.PD[[#This Row],[.]]="*",VLOOKUP(BD.PD[[#This Row],[Pos]],Presupuesto!A:H,7,FALSE),"") | F52: DIRECCION TECNICA (ADICIONAL) | G52: Etapa 1 -D/IR | H52: 4513057034 | I52: Comprometido | J52: 10.08.2026 | K52: 1 | L52: USD | M52: =IF(BD.PD[[#This Row],[Mon]]="DOP",1,HLOOKUP(BD.PD[[#This Row],[Mon]],$K$1:$L$2,2,FALSE)) -> 61 | N52: 928.78 | O52: =BD.PD[[#This Row],[Cant.]]*BD.PD[[#This Row],[ Tasa ]]*BD.PD[[#This Row],[ Precio Und.]] -> 56655.58 | P52: 0 | Q52: =IF(BD.PD[[#This Row],[Liquid. '[%']]]<>0,(BD.PD[[#This Row],[Valor Neto '[DOP']]]*BD.PD[[#This Row],[Liquid. '[%']]])+BD.PD[[#This Row],[Valor Neto '[DOP']]],BD.PD[[#This Row],[Valor Neto '[DOP']]]) -> 56655.58 | R52: =BD.PD[[#This Row],[Ppto. Orden Interna '[DOP']]]/HLOOKUP("USD",$K$1:$L$2,2,FALSE) -> 928.78 | S52: 77274 CONSTRUCTORA FIREPRO SRL | U52: NTCO011104 | V52: 801667 | W52: 77274 CONSTRUCTORA FIREPRO SRL | X52: 21 | Y52: 1 | Z52: =BD.PD[[#This Row],[Av.P1 '[%']]]*BD.PD[[#This Row],[Ppto. Orden Interna '[DOP']]] -> 56655.58 | AC52: =BD.PD[[#This Row],[Av.P2 '[%']]]*BD.PD[[#This Row],[Ppto. Orden Interna '[DOP']]] -> 0 | AF52: =BD.PD[[#This Row],[Av.P3 '[%']]]*BD.PD[[#This Row],[Ppto. Orden Interna '[DOP']]] -> 0 | AM52: =BD.PD[[#This Row],[Pago 3]]+BD.PD[[#This Row],[Pago 2]]+BD.PD[[#This Row],[Pago 1]] -> 56655.58 | AN52: Sirena Compacta | AO52: Sirena Las Terrenas | AP52: MC33 | AQ52: Marrón | AR52: 594 | AS52: Orden Colocada
A53: 2.08 | B53: * | C53: =VLOOKUP(BD.PD[[#This Row],[Pos]],PPto[],3,FALSE) -> 2.08 Instalaciones Mecánicas | D53: * | E53: =IF(BD.PD[[#This Row],[.]]="*",VLOOKUP(BD.PD[[#This Row],[Pos]],Presupuesto!A:H,7,FALSE),"") -> 112643.09 | K53: 1 | L53: USD | M53: =IF(BD.PD[[#This Row],[Mon]]="DOP",1,HLOOKUP(BD.PD[[#This Row],[Mon]],$K$1:$L$2,2,FALSE)) -> 61 | N53: 0 | O53: =BD.PD[[#This Row],[Cant.]]*BD.PD[[#This Row],[ Tasa ]]*BD.PD[[#This Row],[ Precio Und.]] -> 0 | P53: 0 | Q53: =IF(BD.PD[[#This Row],[Liquid. '[%']]]<>0,(BD.PD[[#This Row],[Valor Neto '[DOP']]]*BD.PD[[#This Row],[Liquid. '[%']]])+BD.PD[[#This Row],[Valor Neto '[DOP']]],BD.PD[[#This Row],[Valor Neto '[DOP']]]) -> 0 | R53: =BD.PD[[#This Row],[Ppto. Orden Interna '[DOP']]]/HLOOKUP("USD",$K$1:$L$2,2,FALSE) -> 0 | Z53: =BD.PD[[#This Row],[Av.P1 '[%']]]*BD.PD[[#This Row],[Ppto. Orden Interna '[DOP']]] -> 0 | AC53: =BD.PD[[#This Row],[Av.P2 '[%']]]*BD.PD[[#This Row],[Ppto. Orden Interna '[DOP']]] -> 0 | AF53: =BD.PD[[#This Row],[Av.P3 '[%']]]*BD.PD[[#This Row],[Ppto. Orden Interna '[DOP']]] -> 0 | AM53: =BD.PD[[#This Row],[Pago 3]]+BD.PD[[#This Row],[Pago 2]]+BD.PD[[#This Row],[Pago 1]] -> 0
A54: 2.08 | C54: =VLOOKUP(BD.PD[[#This Row],[Pos]],PPto[],3,FALSE) -> 2.08 Instalaciones Mecánicas | D54: OI | E54: =IF(BD.PD[[#This Row],[.]]="*",VLOOKUP(BD.PD[[#This Row],[Pos]],Presupuesto!A:H,7,FALSE),"") | F54: COMPACTADORA DE CARTON 3HP 208/3/60HZ | G54: Etapa 2 -D/IR | H54: 4600070965 | I54: Stock AF01 | J54: 25.06.2026 | K54: 1 | L54: DOP | M54: =IF(BD.PD[[#This Row],[Mon]]="DOP",1,HLOOKUP(BD.PD[[#This Row],[Mon]],$K$1:$L$2,2,FALSE)) -> 1 | N54: 579497.2 | O54: =BD.PD[[#This Row],[Cant.]]*BD.PD[[#This Row],[ Tasa ]]*BD.PD[[#This Row],[ Precio Und.]] -> 579497.2 | P54: 0 | Q54: =IF(BD.PD[[#This Row],[Liquid. '[%']]]<>0,(BD.PD[[#This Row],[Valor Neto '[DOP']]]*BD.PD[[#This Row],[Liquid. '[%']]])+BD.PD[[#This Row],[Valor Neto '[DOP']]],BD.PD[[#This Row],[Valor Neto '[DOP']]]) -> 579497.2 | R54: =BD.PD[[#This Row],[Ppto. Orden Interna '[DOP']]]/HLOOKUP("USD",$K$1:$L$2,2,FALSE) -> 9499.9541 | S54: 30270 IND. MATERIAL & EQUIPMENT (IMEQ) | U54: NTCO011104 | V54: 801667 | W54: 30270 IND. MATERIAL & EQUIPMENT (IMEQ) | X54: 8 | Y54: 1 | Z54: =BD.PD[[#This Row],[Av.P1 '[%']]]*BD.PD[[#This Row],[Ppto. Orden Interna '[DOP']]] -> 579497.2 | AC54: =BD.PD[[#This Row],[Av.P2 '[%']]]*BD.PD[[#This Row],[Ppto. Orden Interna '[DOP']]] -> 0 | AF54: =BD.PD[[#This Row],[Av.P3 '[%']]]*BD.PD[[#This Row],[Ppto. Orden Interna '[DOP']]] -> 0 | AM54: =BD.PD[[#This Row],[Pago 3]]+BD.PD[[#This Row],[Pago 2]]+BD.PD[[#This Row],[Pago 1]] -> 579497.2 | AN54: Sirena Compacta | AO54: Sirena Las Terrenas | AP54: MC33 | AQ54: Marrón | AR54: 594 | AS54: Orden Colocada
A55: 2.08 | C55: =VLOOKUP(BD.PD[[#This Row],[Pos]],PPto[],3,FALSE) -> 2.08 Instalaciones Mecánicas | D55: OI | E55: =IF(BD.PD[[#This Row],[.]]="*",VLOOKUP(BD.PD[[#This Row],[Pos]],Presupuesto!A:H,7,FALSE),"") | F55: EQUIPCO COMPACTADORA BASURA 30 YARDAS 10HP | G55: Etapa 2 -D/IR | H55: 4600078521 | I55: Stock AF01 | J55: 25.06.2026 | K55: 1 | L55: USD | M55: =IF(BD.PD[[#This Row],[Mon]]="DOP",1,HLOOKUP(BD.PD[[#This Row],[Mon]],$K$1:$L$2,2,FALSE)) -> 61 | N55: 22027.5 | O55: =BD.PD[[#This Row],[Cant.]]*BD.PD[[#This Row],[ Tasa ]]*BD.PD[[#This Row],[ Precio Und.]] -> 1343677.5 | P55: 0.25 | Q55: =IF(BD.PD[[#This Row],[Liquid. '[%']]]<>0,(BD.PD[[#This Row],[Valor Neto '[DOP']]]*BD.PD[[#This Row],[Liquid. '[%']]])+BD.PD[[#This Row],[Valor Neto '[DOP']]],BD.PD[[#This Row],[Valor Neto '[DOP']]]) -> 1679596.9 | R55: =BD.PD[[#This Row],[Ppto. Orden Interna '[DOP']]]/HLOOKUP("USD",$K$1:$L$2,2,FALSE) -> 27534.375 | S55: 30270 IND. MATERIAL & EQUIPMENT (IMEQ) | U55: NTCO011104 | V55: 801667 | W55: 30270 IND. MATERIAL & EQUIPMENT (IMEQ) | X55: 19 | Y55: 1 | Z55: =BD.PD[[#This Row],[Av.P1 '[%']]]*BD.PD[[#This Row],[Ppto. Orden Interna '[DOP']]] -> 1679596.9 | AC55: =BD.PD[[#This Row],[Av.P2 '[%']]]*BD.PD[[#This Row],[Ppto. Orden Interna '[DOP']]] -> 0 | AF55: =BD.PD[[#This Row],[Av.P3 '[%']]]*BD.PD[[#This Row],[Ppto. Orden Interna '[DOP']]] -> 0 | AM55: =BD.PD[[#This Row],[Pago 3]]+BD.PD[[#This Row],[Pago 2]]+BD.PD[[#This Row],[Pago 1]] -> 1679596.9 | AN55: Sirena Compacta | AO55: Sirena Las Terrenas | AP55: MC33 | AQ55: Marrón | AR55: 594 | AS55: Orden Colocada
A56: 2.08 | C56: =VLOOKUP(BD.PD[[#This Row],[Pos]],PPto[],3,FALSE) -> 2.08 Instalaciones Mecánicas | D56: OI | E56: =IF(BD.PD[[#This Row],[.]]="*",VLOOKUP(BD.PD[[#This Row],[Pos]],Presupuesto!A:H,7,FALSE),"") | F56: SUM E INST. MURO CORTINA CAN-01 (FACHADA EXTERIOR) | G56: Etapa 2 -D/IR | H56: 4512960367 | I56: Comprometido | J56: 25.06.2026 | K56: 1 | L56: DOP | M56: =IF(BD.PD[[#This Row],[Mon]]="DOP",1,HLOOKUP(BD.PD[[#This Row],[Mon]],$K$1:$L$2,2,FALSE)) -> 1 | N56: 1460713 | O56: =BD.PD[[#This Row],[Cant.]]*BD.PD[[#This Row],[ Tasa ]]*BD.PD[[#This Row],[ Precio Und.]] -> 1460713 | P56: 0 | Q56: =IF(BD.PD[[#This Row],[Liquid. '[%']]]<>0,(BD.PD[[#This Row],[Valor Neto '[DOP']]]*BD.PD[[#This Row],[Liquid. '[%']]])+BD.PD[[#This Row],[Valor Neto '[DOP']]],BD.PD[[#This Row],[Valor Neto '[DOP']]]) -> 1460713 | R56: =BD.PD[[#This Row],[Ppto. Orden Interna '[DOP']]]/HLOOKUP("USD",$K$1:$L$2,2,FALSE) -> 23946.115 | S56: 77463 SRAD PROYECTOS & SERVICIOS SRL | U56: NTCO011104 | V56: 801667 | W56: 77463 SRAD PROYECTOS & SERVICIOS SRL | X56: 18 | Y56: 0.3 | Z56: =BD.PD[[#This Row],[Av.P1 '[%']]]*BD.PD[[#This Row],[Ppto. Orden Interna '[DOP']]] -> 438213.9 | AA56: 21 | AB56: 0.7 | AC56: =BD.PD[[#This Row],[Av.P2 '[%']]]*BD.PD[[#This Row],[Ppto. Orden Interna '[DOP']]] -> 1022499.1 | AF56: =BD.PD[[#This Row],[Av.P3 '[%']]]*BD.PD[[#This Row],[Ppto. Orden Interna '[DOP']]] -> 0 | AM56: =BD.PD[[#This Row],[Pago 3]]+BD.PD[[#This Row],[Pago 2]]+BD.PD[[#This Row],[Pago 1]] -> 1460713 | AN56: Sirena Compacta | AO56: Sirena Las Terrenas | AP56: MC33 | AQ56: Marrón | AR56: 594 | AS56: Orden Colocada
A57: 2.08 | C57: =VLOOKUP(BD.PD[[#This Row],[Pos]],PPto[],3,FALSE) -> 2.08 Instalaciones Mecánicas | D57: OI | E57: =IF(BD.PD[[#This Row],[.]]="*",VLOOKUP(BD.PD[[#This Row],[Pos]],Presupuesto!A:H,7,FALSE),"") | F57: SUM E INST. MURO CORTINA CAN-01.2 (FACHADA EXTERIOR) | G57: Etapa 2 -D/IR | H57: 4512960367 | I57: Comprometido | J57: 25.06.2026 | K57: 1 | L57: DOP | M57: =IF(BD.PD[[#This Row],[Mon]]="DOP",1,HLOOKUP(BD.PD[[#This Row],[Mon]],$K$1:$L$2,2,FALSE)) -> 1 | N57: 585531 | O57: =BD.PD[[#This Row],[Cant.]]*BD.PD[[#This Row],[ Tasa ]]*BD.PD[[#This Row],[ Precio Und.]] -> 585531 | P57: 0 | Q57: =IF(BD.PD[[#This Row],[Liquid. '[%']]]<>0,(BD.PD[[#This Row],[Valor Neto '[DOP']]]*BD.PD[[#This Row],[Liquid. '[%']]])+BD.PD[[#This Row],[Valor Neto '[DOP']]],BD.PD[[#This Row],[Valor Neto '[DOP']]]) -> 585531 | R57: =BD.PD[[#This Row],[Ppto. Orden Interna '[DOP']]]/HLOOKUP("USD",$K$1:$L$2,2,FALSE) -> 9598.8689 | S57: 77463 SRAD PROYECTOS & SERVICIOS SRL | U57: NTCO011104 | V57: 801667 | W57: 77463 SRAD PROYECTOS & SERVICIOS SRL | X57: 18 | Y57: 0.3 | Z57: =BD.PD[[#This Row],[Av.P1 '[%']]]*BD.PD[[#This Row],[Ppto. Orden Interna '[DOP']]] -> 175659.3 | AA57: 21 | AB57: 0.7 | AC57: =BD.PD[[#This Row],[Av.P2 '[%']]]*BD.PD[[#This Row],[Ppto. Orden Interna '[DOP']]] -> 409871.7 | AF57: =BD.PD[[#This Row],[Av.P3 '[%']]]*BD.PD[[#This Row],[Ppto. Orden Interna '[DOP']]] -> 0 | AM57: =BD.PD[[#This Row],[Pago 3]]+BD.PD[[#This Row],[Pago 2]]+BD.PD[[#This Row],[Pago 1]] -> 585531 | AN57: Sirena Compacta | AO57: Sirena Las Terrenas | AP57: MC33 | AQ57: Marrón | AR57: 594 | AS57: Orden Colocada
A58: 2.08 | C58: =VLOOKUP(BD.PD[[#This Row],[Pos]],PPto[],3,FALSE) -> 2.08 Instalaciones Mecánicas | D58: OI | E58: =IF(BD.PD[[#This Row],[.]]="*",VLOOKUP(BD.PD[[#This Row],[Pos]],Presupuesto!A:H,7,FALSE),"") | F58: SUM E INST. MURO CORTINA CAN-02 (FACHADA EXTERIOR) | G58: Etapa 2 -D/IR | H58: 4512960367 | I58: Comprometido | J58: 25.06.2026 | K58: 1 | L58: DOP | M58: =IF(BD.PD[[#This Row],[Mon]]="DOP",1,HLOOKUP(BD.PD[[#This Row],[Mon]],$K$1:$L$2,2,FALSE)) -> 1 | N58: 2525394 | O58: =BD.PD[[#This Row],[Cant.]]*BD.PD[[#This Row],[ Tasa ]]*BD.PD[[#This Row],[ Precio Und.]] -> 2525394 | P58: 0 | Q58: =IF(BD.PD[[#This Row],[Liquid. '[%']]]<>0,(BD.PD[[#This Row],[Valor Neto '[DOP']]]*BD.PD[[#This Row],[Liquid. '[%']]])+BD.PD[[#This Row],[Valor Neto '[DOP']]],BD.PD[[#This Row],[Valor Neto '[DOP']]]) -> 2525394 | R58: =BD.PD[[#This Row],[Ppto. Orden Interna '[DOP']]]/HLOOKUP("USD",$K$1:$L$2,2,FALSE) -> 41399.902 | S58: 77463 SRAD PROYECTOS & SERVICIOS SRL | U58: NTCO011104 | V58: 801667 | W58: 77463 SRAD PROYECTOS & SERVICIOS SRL | X58: 18 | Y58: 0.3 | Z58: =BD.PD[[#This Row],[Av.P1 '[%']]]*BD.PD[[#This Row],[Ppto. Orden Interna '[DOP']]] -> 757618.2 | AA58: 21 | AB58: 0.7 | AC58: =BD.PD[[#This Row],[Av.P2 '[%']]]*BD.PD[[#This Row],[Ppto. Orden Interna '[DOP']]] -> 1767775.8 | AF58: =BD.PD[[#This Row],[Av.P3 '[%']]]*BD.PD[[#This Row],[Ppto. Orden Interna '[DOP']]] -> 0 | AM58: =BD.PD[[#This Row],[Pago 3]]+BD.PD[[#This Row],[Pago 2]]+BD.PD[[#This Row],[Pago 1]] -> 2525394 | AN58: Sirena Compacta | AO58: Sirena Las Terrenas | AP58: MC33 | AQ58: Marrón | AR58: 594 | AS58: Orden Colocada
A59: 2.08 | C59: =VLOOKUP(BD.PD[[#This Row],[Pos]],PPto[],3,FALSE) -> 2.08 Instalaciones Mecánicas | D59: OI | E59: =IF(BD.PD[[#This Row],[.]]="*",VLOOKUP(BD.PD[[#This Row],[Pos]],Presupuesto!A:H,7,FALSE),"") | F59: SUM E INST. PUERTA EN PERFILERIA PP1-7 (FACHADA EXTERIOR) | G59: Etapa 2 -D/IR | H59: 4512960367 | I59: Comprometido | J59: 25.06.2026 | K59: 7 | L59: DOP | M59: =IF(BD.PD[[#This Row],[Mon]]="DOP",1,HLOOKUP(BD.PD[[#This Row],[Mon]],$K$1:$L$2,2,FALSE)) -> 1 | N59: 27000 | O59: =BD.PD[[#This Row],[Cant.]]*BD.PD[[#This Row],[ Tasa ]]*BD.PD[[#This Row],[ Precio Und.]] -> 189000 | P59: 0 | Q59: =IF(BD.PD[[#This Row],[Liquid. '[%']]]<>0,(BD.PD[[#This Row],[Valor Neto '[DOP']]]*BD.PD[[#This Row],[Liquid. '[%']]])+BD.PD[[#This Row],[Valor Neto '[DOP']]],BD.PD[[#This Row],[Valor Neto '[DOP']]]) -> 189000 | R59: =BD.PD[[#This Row],[Ppto. Orden Interna '[DOP']]]/HLOOKUP("USD",$K$1:$L$2,2,FALSE) -> 3098.3607 | S59: 77463 SRAD PROYECTOS & SERVICIOS SRL | U59: NTCO011104 | V59: 801667 | W59: 77463 SRAD PROYECTOS & SERVICIOS SRL | X59: 18 | Y59: 0.3 | Z59: =BD.PD[[#This Row],[Av.P1 '[%']]]*BD.PD[[#This Row],[Ppto. Orden Interna '[DOP']]] -> 56700 | AA59: 21 | AB59: 0.7 | AC59: =BD.PD[[#This Row],[Av.P2 '[%']]]*BD.PD[[#This Row],[Ppto. Orden Interna '[DOP']]] -> 132300 | AF59: =BD.PD[[#This Row],[Av.P3 '[%']]]*BD.PD[[#This Row],[Ppto. Orden Interna '[DOP']]] -> 0 | AM59: =BD.PD[[#This Row],[Pago 3]]+BD.PD[[#This Row],[Pago 2]]+BD.PD[[#This Row],[Pago 1]] -> 189000 | AN59: Sirena Compacta | AO59: Sirena Las Terrenas | AP59: MC33 | AQ59: Marrón | AR59: 594 | AS59: Orden Colocada
A60: 2.08 | C60: =VLOOKUP(BD.PD[[#This Row],[Pos]],PPto[],3,FALSE) -> 2.08 Instalaciones Mecánicas | D60: OI | E60: =IF(BD.PD[[#This Row],[.]]="*",VLOOKUP(BD.PD[[#This Row],[Pos]],Presupuesto!A:H,7,FALSE),"") | F60: SUM E INST PUERTAS AUTOMATICAS PA (FACHADA EXTERIOR) | G60: Etapa 2 -D/IR | H60: 4512960367 | I60: Comprometido | J60: 25.06.2026 | K60: 1 | L60: DOP | M60: =IF(BD.PD[[#This Row],[Mon]]="DOP",1,HLOOKUP(BD.PD[[#This Row],[Mon]],$K$1:$L$2,2,FALSE)) -> 1 | N60: 470000 | O60: =BD.PD[[#This Row],[Cant.]]*BD.PD[[#This Row],[ Tasa ]]*BD.PD[[#This Row],[ Precio Und.]] -> 470000 | P60: 0 | Q60: =IF(BD.PD[[#This Row],[Liquid. '[%']]]<>0,(BD.PD[[#This Row],[Valor Neto '[DOP']]]*BD.PD[[#This Row],[Liquid. '[%']]])+BD.PD[[#This Row],[Valor Neto '[DOP']]],BD.PD[[#This Row],[Valor Neto '[DOP']]]) -> 470000 | R60: =BD.PD[[#This Row],[Ppto. Orden Interna '[DOP']]]/HLOOKUP("USD",$K$1:$L$2,2,FALSE) -> 7704.918 | S60: 77463 SRAD PROYECTOS & SERVICIOS SRL | U60: NTCO011104 | V60: 801667 | W60: 77463 SRAD PROYECTOS & SERVICIOS SRL | X60: 18 | Y60: 0.3 | Z60: =BD.PD[[#This Row],[Av.P1 '[%']]]*BD.PD[[#This Row],[Ppto. Orden Interna '[DOP']]] -> 141000 | AA60: 21 | AB60: 0.7 | AC60: =BD.PD[[#This Row],[Av.P2 '[%']]]*BD.PD[[#This Row],[Ppto. Orden Interna '[DOP']]] -> 329000 | AF60: =BD.PD[[#This Row],[Av.P3 '[%']]]*BD.PD[[#This Row],[Ppto. Orden Interna '[DOP']]] -> 0 | AM60: =BD.PD[[#This Row],[Pago 3]]+BD.PD[[#This Row],[Pago 2]]+BD.PD[[#This Row],[Pago 1]] -> 470000 | AN60: Sirena Compacta | AO60: Sirena Las Terrenas | AP60: MC33 | AQ60: Marrón | AR60: 594 | AS60: Orden Colocada
A61: 2.08 | C61: =VLOOKUP(BD.PD[[#This Row],[Pos]],PPto[],3,FALSE) -> 2.08 Instalaciones Mecánicas | D61: OI | E61: =IF(BD.PD[[#This Row],[.]]="*",VLOOKUP(BD.PD[[#This Row],[Pos]],Presupuesto!A:H,7,FALSE),"") | F61: SUM E INST. CORTINA DE AIRE FAAC (FACHADA EXTERIOR) | G61: Etapa 2 -D/IR | H61: 4512960367 | I61: Comprometido | J61: 25.06.2026 | K61: 1 | L61: DOP | M61: =IF(BD.PD[[#This Row],[Mon]]="DOP",1,HLOOKUP(BD.PD[[#This Row],[Mon]],$K$1:$L$2,2,FALSE)) -> 1 | N61: 400000 | O61: =BD.PD[[#This Row],[Cant.]]*BD.PD[[#This Row],[ Tasa ]]*BD.PD[[#This Row],[ Precio Und.]] -> 400000 | P61: 0 | Q61: =IF(BD.PD[[#This Row],[Liquid. '[%']]]<>0,(BD.PD[[#This Row],[Valor Neto '[DOP']]]*BD.PD[[#This Row],[Liquid. '[%']]])+BD.PD[[#This Row],[Valor Neto '[DOP']]],BD.PD[[#This Row],[Valor Neto '[DOP']]]) -> 400000 | R61: =BD.PD[[#This Row],[Ppto. Orden Interna '[DOP']]]/HLOOKUP("USD",$K$1:$L$2,2,FALSE) -> 6557.377 | S61: 77463 SRAD PROYECTOS & SERVICIOS SRL | U61: NTCO011104 | V61: 801667 | W61: 77463 SRAD PROYECTOS & SERVICIOS SRL | X61: 18 | Y61: 0.3 | Z61: =BD.PD[[#This Row],[Av.P1 '[%']]]*BD.PD[[#This Row],[Ppto. Orden Interna '[DOP']]] -> 120000 | AA61: 21 | AB61: 0.7 | AC61: =BD.PD[[#This Row],[Av.P2 '[%']]]*BD.PD[[#This Row],[Ppto. Orden Interna '[DOP']]] -> 280000 | AF61: =BD.PD[[#This Row],[Av.P3 '[%']]]*BD.PD[[#This Row],[Ppto. Orden Interna '[DOP']]] -> 0 | AM61: =BD.PD[[#This Row],[Pago 3]]+BD.PD[[#This Row],[Pago 2]]+BD.PD[[#This Row],[Pago 1]] -> 400000 | AN61: Sirena Compacta | AO61: Sirena Las Terrenas | AP61: MC33 | AQ61: Marrón | AR61: 594 | AS61: Orden Colocada
A62: 2.08 | C62: =VLOOKUP(BD.PD[[#This Row],[Pos]],PPto[],3,FALSE) -> 2.08 Instalaciones Mecánicas | D62: OI | E62: =IF(BD.PD[[#This Row],[.]]="*",VLOOKUP(BD.PD[[#This Row],[Pos]],Presupuesto!A:H,7,FALSE),"") | F62: TRANSPORTE (FACHADA EXTERIOR) | G62: Etapa 2 -D/IR | H62: 4512960367 | I62: Comprometido | J62: 25.06.2026 | K62: 1 | L62: DOP | M62: =IF(BD.PD[[#This Row],[Mon]]="DOP",1,HLOOKUP(BD.PD[[#This Row],[Mon]],$K$1:$L$2,2,FALSE)) -> 1 | N62: 66000 | O62: =BD.PD[[#This Row],[Cant.]]*BD.PD[[#This Row],[ Tasa ]]*BD.PD[[#This Row],[ Precio Und.]] -> 66000 | P62: 0 | Q62: =IF(BD.PD[[#This Row],[Liquid. '[%']]]<>0,(BD.PD[[#This Row],[Valor Neto '[DOP']]]*BD.PD[[#This Row],[Liquid. '[%']]])+BD.PD[[#This Row],[Valor Neto '[DOP']]],BD.PD[[#This Row],[Valor Neto '[DOP']]]) -> 66000 | R62: =BD.PD[[#This Row],[Ppto. Orden Interna '[DOP']]]/HLOOKUP("USD",$K$1:$L$2,2,FALSE) -> 1081.9672 | S62: 77463 SRAD PROYECTOS & SERVICIOS SRL | U62: NTCO011104 | V62: 801667 | W62: 77463 SRAD PROYECTOS & SERVICIOS SRL | X62: 18 | Y62: 0.3 | Z62: =BD.PD[[#This Row],[Av.P1 '[%']]]*BD.PD[[#This Row],[Ppto. Orden Interna '[DOP']]] -> 19800 | AA62: 21 | AB62: 0.7 | AC62: =BD.PD[[#This Row],[Av.P2 '[%']]]*BD.PD[[#This Row],[Ppto. Orden Interna '[DOP']]] -> 46200 | AF62: =BD.PD[[#This Row],[Av.P3 '[%']]]*BD.PD[[#This Row],[Ppto. Orden Interna '[DOP']]] -> 0 | AM62: =BD.PD[[#This Row],[Pago 3]]+BD.PD[[#This Row],[Pago 2]]+BD.PD[[#This Row],[Pago 1]] -> 66000 | AN62: Sirena Compacta | AO62: Sirena Las Terrenas | AP62: MC33 | AQ62: Marrón | AR62: 594 | AS62: Orden Colocada
A63: 2.08 | C63: =VLOOKUP(BD.PD[[#This Row],[Pos]],PPto[],3,FALSE) -> 2.08 Instalaciones Mecánicas | D63: OI | E63: =IF(BD.PD[[#This Row],[.]]="*",VLOOKUP(BD.PD[[#This Row],[Pos]],Presupuesto!A:H,7,FALSE),"") | F63: SUM. E INST. MURO CORTINA ISLA MC33 (ISLA) | G63: Etapa 2 -D/IR | H63: 4513026240 | I63: Comprometido | J63: 16.07.2026 | K63: 1 | L63: DOP | M63: =IF(BD.PD[[#This Row],[Mon]]="DOP",1,HLOOKUP(BD.PD[[#This Row],[Mon]],$K$1:$L$2,2,FALSE)) -> 1 | N63: 3018201 | O63: =BD.PD[[#This Row],[Cant.]]*BD.PD[[#This Row],[ Tasa ]]*BD.PD[[#This Row],[ Precio Und.]] -> 3018201 | P63: 0 | Q63: =IF(BD.PD[[#This Row],[Liquid. '[%']]]<>0,(BD.PD[[#This Row],[Valor Neto '[DOP']]]*BD.PD[[#This Row],[Liquid. '[%']]])+BD.PD[[#This Row],[Valor Neto '[DOP']]],BD.PD[[#This Row],[Valor Neto '[DOP']]]) -> 3018201 | R63: =BD.PD[[#This Row],[Ppto. Orden Interna '[DOP']]]/HLOOKUP("USD",$K$1:$L$2,2,FALSE) -> 49478.705 | S63: 77463 SRAD PROYECTOS & SERVICIOS SRL | U63: NTCO011104 | V63: 801667 | W63: 77463 SRAD PROYECTOS & SERVICIOS SRL | X63: 19 | Y63: 0.3 | Z63: =BD.PD[[#This Row],[Av.P1 '[%']]]*BD.PD[[#This Row],[Ppto. Orden Interna '[DOP']]] -> 905460.3 | AA63: 21 | AB63: 0.7 | AC63: =BD.PD[[#This Row],[Av.P2 '[%']]]*BD.PD[[#This Row],[Ppto. Orden Interna '[DOP']]] -> 2112740.7 | AF63: =BD.PD[[#This Row],[Av.P3 '[%']]]*BD.PD[[#This Row],[Ppto. Orden Interna '[DOP']]] -> 0 | AM63: =BD.PD[[#This Row],[Pago 3]]+BD.PD[[#This Row],[Pago 2]]+BD.PD[[#This Row],[Pago 1]] -> 3018201 | AN63: Sirena Compacta | AO63: Sirena Las Terrenas | AP63: MC33 | AQ63: Marrón | AR63: 594 | AS63: Orden Colocada
A64: 2.08 | C64: =VLOOKUP(BD.PD[[#This Row],[Pos]],PPto[],3,FALSE) -> 2.08 Instalaciones Mecánicas | D64: OI | E64: =IF(BD.PD[[#This Row],[.]]="*",VLOOKUP(BD.PD[[#This Row],[Pos]],Presupuesto!A:H,7,FALSE),"") | F64: ALQUILER PLATAFORMA ELEVADORA (ISLA) | G64: Etapa 2 -D/IR | H64: 4513026240 | I64: Comprometido | J64: 16.07.2026 | K64: 1 | L64: DOP | M64: =IF(BD.PD[[#This Row],[Mon]]="DOP",1,HLOOKUP(BD.PD[[#This Row],[Mon]],$K$1:$L$2,2,FALSE)) -> 1 | N64: 200000 | O64: =BD.PD[[#This Row],[Cant.]]*BD.PD[[#This Row],[ Tasa ]]*BD.PD[[#This Row],[ Precio Und.]] -> 200000 | P64: 0 | Q64: =IF(BD.PD[[#This Row],[Liquid. '[%']]]<>0,(BD.PD[[#This Row],[Valor Neto '[DOP']]]*BD.PD[[#This Row],[Liquid. '[%']]])+BD.PD[[#This Row],[Valor Neto '[DOP']]],BD.PD[[#This Row],[Valor Neto '[DOP']]]) -> 200000 | R64: =BD.PD[[#This Row],[Ppto. Orden Interna '[DOP']]]/HLOOKUP("USD",$K$1:$L$2,2,FALSE) -> 3278.6885 | S64: 77463 SRAD PROYECTOS & SERVICIOS SRL | U64: NTCO011104 | V64: 801667 | W64: 77463 SRAD PROYECTOS & SERVICIOS SRL | X64: 19 | Y64: 0.3 | Z64: =BD.PD[[#This Row],[Av.P1 '[%']]]*BD.PD[[#This Row],[Ppto. Orden Interna '[DOP']]] -> 60000 | AA64: 21 | AB64: 0.7 | AC64: =BD.PD[[#This Row],[Av.P2 '[%']]]*BD.PD[[#This Row],[Ppto. Orden Interna '[DOP']]] -> 140000 | AF64: =BD.PD[[#This Row],[Av.P3 '[%']]]*BD.PD[[#This Row],[Ppto. Orden Interna '[DOP']]] -> 0 | AM64: =BD.PD[[#This Row],[Pago 3]]+BD.PD[[#This Row],[Pago 2]]+BD.PD[[#This Row],[Pago 1]] -> 200000 | AN64: Sirena Compacta | AO64: Sirena Las Terrenas | AP64: MC33 | AQ64: Marrón | AR64: 594 | AS64: Orden Colocada
A65: 2.08 | C65: =VLOOKUP(BD.PD[[#This Row],[Pos]],PPto[],3,FALSE) -> 2.08 Instalaciones Mecánicas | D65: OI | E65: =IF(BD.PD[[#This Row],[.]]="*",VLOOKUP(BD.PD[[#This Row],[Pos]],Presupuesto!A:H,7,FALSE),"") | F65: TRANSPORTE (ISLA) | G65: Etapa 2 -D/IR | H65: 4513026240 | I65: Comprometido | J65: 16.07.2026 | K65: 1 | L65: DOP | M65: =IF(BD.PD[[#This Row],[Mon]]="DOP",1,HLOOKUP(BD.PD[[#This Row],[Mon]],$K$1:$L$2,2,FALSE)) -> 1 | N65: 66000 | O65: =BD.PD[[#This Row],[Cant.]]*BD.PD[[#This Row],[ Tasa ]]*BD.PD[[#This Row],[ Precio Und.]] -> 66000 | P65: 0 | Q65: =IF(BD.PD[[#This Row],[Liquid. '[%']]]<>0,(BD.PD[[#This Row],[Valor Neto '[DOP']]]*BD.PD[[#This Row],[Liquid. '[%']]])+BD.PD[[#This Row],[Valor Neto '[DOP']]],BD.PD[[#This Row],[Valor Neto '[DOP']]]) -> 66000 | R65: =BD.PD[[#This Row],[Ppto. Orden Interna '[DOP']]]/HLOOKUP("USD",$K$1:$L$2,2,FALSE) -> 1081.9672 | S65: 77463 SRAD PROYECTOS & SERVICIOS SRL | U65: NTCO011104 | V65: 801667 | W65: 77463 SRAD PROYECTOS & SERVICIOS SRL | X65: 19 | Y65: 0.3 | Z65: =BD.PD[[#This Row],[Av.P1 '[%']]]*BD.PD[[#This Row],[Ppto. Orden Interna '[DOP']]] -> 19800 | AA65: 21 | AB65: 0.7 | AC65: =BD.PD[[#This Row],[Av.P2 '[%']]]*BD.PD[[#This Row],[Ppto. Orden Interna '[DOP']]] -> 46200 | AF65: =BD.PD[[#This Row],[Av.P3 '[%']]]*BD.PD[[#This Row],[Ppto. Orden Interna '[DOP']]] -> 0 | AM65: =BD.PD[[#This Row],[Pago 3]]+BD.PD[[#This Row],[Pago 2]]+BD.PD[[#This Row],[Pago 1]] -> 66000 | AN65: Sirena Compacta | AO65: Sirena Las Terrenas | AP65: MC33 | AQ65: Marrón | AR65: 594 | AS65: Orden Colocada
A66: 2.08 | C66: =VLOOKUP(BD.PD[[#This Row],[Pos]],PPto[],3,FALSE) -> 2.08 Instalaciones Mecánicas | D66: OI | E66: =IF(BD.PD[[#This Row],[.]]="*",VLOOKUP(BD.PD[[#This Row],[Pos]],Presupuesto!A:H,7,FALSE),"") | F66: SUM E INST. MURO CORTINA MC33 (ADICIONAL-REDUCION FACHADA Y AUMENTO ALTURA) | G66: Etapa 2 -D/IR | H66: 4513032169 | I66: Comprometido | J66: 21.07.2026 | K66: 1 | L66: DOP | M66: =IF(BD.PD[[#This Row],[Mon]]="DOP",1,HLOOKUP(BD.PD[[#This Row],[Mon]],$K$1:$L$2,2,FALSE)) -> 1 | N66: 135000 | O66: =BD.PD[[#This Row],[Cant.]]*BD.PD[[#This Row],[ Tasa ]]*BD.PD[[#This Row],[ Precio Und.]] -> 135000 | P66: 0 | Q66: =IF(BD.PD[[#This Row],[Liquid. '[%']]]<>0,(BD.PD[[#This Row],[Valor Neto '[DOP']]]*BD.PD[[#This Row],[Liquid. '[%']]])+BD.PD[[#This Row],[Valor Neto '[DOP']]],BD.PD[[#This Row],[Valor Neto '[DOP']]]) -> 135000 | R66: =BD.PD[[#This Row],[Ppto. Orden Interna '[DOP']]]/HLOOKUP("USD",$K$1:$L$2,2,FALSE) -> 2213.1148 | S66: 77463 SRAD PROYECTOS & SERVICIOS SRL | U66: NTCO011104 | V66: 801667 | W66: 77463 SRAD PROYECTOS & SERVICIOS SRL | X66: 19 | Y66: 0.3 | Z66: =BD.PD[[#This Row],[Av.P1 '[%']]]*BD.PD[[#This Row],[Ppto. Orden Interna '[DOP']]] -> 40500 | AA66: 21 | AB66: 0.7 | AC66: =BD.PD[[#This Row],[Av.P2 '[%']]]*BD.PD[[#This Row],[Ppto. Orden Interna '[DOP']]] -> 94500 | AF66: =BD.PD[[#This Row],[Av.P3 '[%']]]*BD.PD[[#This Row],[Ppto. Orden Interna '[DOP']]] -> 0 | AM66: =BD.PD[[#This Row],[Pago 3]]+BD.PD[[#This Row],[Pago 2]]+BD.PD[[#This Row],[Pago 1]] -> 135000 | AN66: Sirena Compacta | AO66: Sirena Las Terrenas | AP66: MC33 | AQ66: Marrón | AR66: 594 | AS66: Orden Colocada
A67: 2.08 | C67: =VLOOKUP(BD.PD[[#This Row],[Pos]],PPto[],3,FALSE) -> 2.08 Instalaciones Mecánicas | D67: OI | E67: =IF(BD.PD[[#This Row],[.]]="*",VLOOKUP(BD.PD[[#This Row],[Pos]],Presupuesto!A:H,7,FALSE),"") | F67: SUM E INST. MURO CORTINA MC33 (ADICIONAL-REDUCION FACHADA Y AUMENTO ALTURA) | G67: Etapa 2 -D/IR | H67: 4513032169 | I67: Comprometido | J67: 21.07.2026 | K67: 1 | L67: DOP | M67: =IF(BD.PD[[#This Row],[Mon]]="DOP",1,HLOOKUP(BD.PD[[#This Row],[Mon]],$K$1:$L$2,2,FALSE)) -> 1 | N67: 105678 | O67: =BD.PD[[#This Row],[Cant.]]*BD.PD[[#This Row],[ Tasa ]]*BD.PD[[#This Row],[ Precio Und.]] -> 105678 | P67: 0 | Q67: =IF(BD.PD[[#This Row],[Liquid. '[%']]]<>0,(BD.PD[[#This Row],[Valor Neto '[DOP']]]*BD.PD[[#This Row],[Liquid. '[%']]])+BD.PD[[#This Row],[Valor Neto '[DOP']]],BD.PD[[#This Row],[Valor Neto '[DOP']]]) -> 105678 | R67: =BD.PD[[#This Row],[Ppto. Orden Interna '[DOP']]]/HLOOKUP("USD",$K$1:$L$2,2,FALSE) -> 1732.4262 | S67: 77463 SRAD PROYECTOS & SERVICIOS SRL | U67: NTCO011104 | V67: 801667 | W67: 77463 SRAD PROYECTOS & SERVICIOS SRL | X67: 19 | Y67: 0.3 | Z67: =BD.PD[[#This Row],[Av.P1 '[%']]]*BD.PD[[#This Row],[Ppto. Orden Interna '[DOP']]] -> 31703.4 | AA67: 21 | AB67: 0.7 | AC67: =BD.PD[[#This Row],[Av.P2 '[%']]]*BD.PD[[#This Row],[Ppto. Orden Interna '[DOP']]] -> 73974.6 | AF67: =BD.PD[[#This Row],[Av.P3 '[%']]]*BD.PD[[#This Row],[Ppto. Orden Interna '[DOP']]] -> 0 | AM67: =BD.PD[[#This Row],[Pago 3]]+BD.PD[[#This Row],[Pago 2]]+BD.PD[[#This Row],[Pago 1]] -> 105678 | AN67: Sirena Compacta | AO67: Sirena Las Terrenas | AP67: MC33 | AQ67: Marrón | AR67: 594 | AS67: Orden Colocada
... A69: 2.08 | C69: =VLOOKUP(BD.PD[[#This Row],[Pos]],PPto[],3,FALSE) -> 2.08 Instalaciones Mecánicas | D69: OI | E69: =IF(BD.PD[[#This Row],[.]]="*",VLOOKUP(BD.PD[[#This Row],[Pos]],Presupuesto!A:H,7,FALSE),"") | F69: TRANSPORTE (ADICIONAL-REDUCION FACHADA Y AUMENTO ALTURA) | G69: Etapa 2 -D/IR | H69: 4513032169 | I69: Comprometido | J69: 21.07.2026 | K69: 1 | L69: DOP | M69: =IF(BD.PD[[#This Row],[Mon]]="DOP",1,HLOOKUP(BD.PD[[#This Row],[Mon]],$K$1:$L$2,2,FALSE)) -> 1 | N69: 65000 | O69: =BD.PD[[#This Row],[Cant.]]*BD.PD[[#This Row],[ Tasa ]]*BD.PD[[#This Row],[ Precio Und.]] -> 65000 | P69: 0 | Q69: =IF(BD.PD[[#This Row],[Liquid. '[%']]]<>0,(BD.PD[[#This Row],[Valor Neto '[DOP']]]*BD.PD[[#This Row],[Liquid. '[%']]])+BD.PD[[#This Row],[Valor Neto '[DOP']]],BD.PD[[#This Row],[Valor Neto '[DOP']]]) -> 65000 | R69: =BD.PD[[#This Row],[Ppto. Orden Interna '[DOP']]]/HLOOKUP("USD",$K$1:$L$2,2,FALSE) -> 1065.5738 | S69: 77463 SRAD PROYECTOS & SERVICIOS SRL | U69: NTCO011104 | V69: 801667 | W69: 77463 SRAD PROYECTOS & SERVICIOS SRL | X69: 19 | Y69: 0.3 | Z69: =BD.PD[[#This Row],[Av.P1 '[%']]]*BD.PD[[#This Row],[Ppto. Orden Interna '[DOP']]] -> 19500 | AA69: 21 | AB69: 0.7 | AC69: =BD.PD[[#This Row],[Av.P2 '[%']]]*BD.PD[[#This Row],[Ppto. Orden Interna '[DOP']]] -> 45500 | AF69: =BD.PD[[#This Row],[Av.P3 '[%']]]*BD.PD[[#This Row],[Ppto. Orden Interna '[DOP']]] -> 0 | AM69: =BD.PD[[#This Row],[Pago 3]]+BD.PD[[#This Row],[Pago 2]]+BD.PD[[#This Row],[Pago 1]] -> 65000 | AN69: Sirena Compacta | AO69: Sirena Las Terrenas | AP69: MC33 | AQ69: Marrón | AR69: 594 | AS69: Orden Colocada
A70: 2.08 | C70: =VLOOKUP(BD.PD[[#This Row],[Pos]],PPto[],3,FALSE) -> 2.08 Instalaciones Mecánicas | D70: OI | E70: =IF(BD.PD[[#This Row],[.]]="*",VLOOKUP(BD.PD[[#This Row],[Pos]],Presupuesto!A:H,7,FALSE),"") | F70: RAMPA NIVELA 60X80 3000LB GPT3MGWPDG | G70: Etapa 2 -D/IR | I70: Stock AF01 | J70: 25.06.2026 | K70: 2 | L70: DOP | M70: =IF(BD.PD[[#This Row],[Mon]]="DOP",1,HLOOKUP(BD.PD[[#This Row],[Mon]],$K$1:$L$2,2,FALSE)) -> 1 | N70: 264075.18 | O70: =BD.PD[[#This Row],[Cant.]]*BD.PD[[#This Row],[ Tasa ]]*BD.PD[[#This Row],[ Precio Und.]] -> 528150.36 | P70: 0 | Q70: =IF(BD.PD[[#This Row],[Liquid. '[%']]]<>0,(BD.PD[[#This Row],[Valor Neto '[DOP']]]*BD.PD[[#This Row],[Liquid. '[%']]])+BD.PD[[#This Row],[Valor Neto '[DOP']]],BD.PD[[#This Row],[Valor Neto '[DOP']]]) -> 528150.36 | R70: =BD.PD[[#This Row],[Ppto. Orden Interna '[DOP']]]/HLOOKUP("USD",$K$1:$L$2,2,FALSE) -> 8658.2026 | S70: Disponible en AF01 | U70: NTCO011104 | V70: 801667 | W70: 30270 IND. MATERIAL & EQUIPMENT (IMEQ) | X70: 8 | Y70: 1 | Z70: =BD.PD[[#This Row],[Av.P1 '[%']]]*BD.PD[[#This Row],[Ppto. Orden Interna '[DOP']]] -> 528150.36 | AC70: =BD.PD[[#This Row],[Av.P2 '[%']]]*BD.PD[[#This Row],[Ppto. Orden Interna '[DOP']]] -> 0 | AF70: =BD.PD[[#This Row],[Av.P3 '[%']]]*BD.PD[[#This Row],[Ppto. Orden Interna '[DOP']]] -> 0 | AM70: =BD.PD[[#This Row],[Pago 3]]+BD.PD[[#This Row],[Pago 2]]+BD.PD[[#This Row],[Pago 1]] -> 528150.36 | AN70: Sirena Compacta | AO70: Sirena Las Terrenas | AP70: MC33 | AQ70: Marrón | AR70: 594 | AS70: Orden Colocada
A71: 2.08 | C71: =VLOOKUP(BD.PD[[#This Row],[Pos]],PPto[],3,FALSE) -> 2.08 Instalaciones Mecánicas | D71: OI | E71: =IF(BD.PD[[#This Row],[.]]="*",VLOOKUP(BD.PD[[#This Row],[Pos]],Presupuesto!A:H,7,FALSE),"") | F71: ELEVADOR AREA PRODUCCION, 1,000 KGS | G71: Etapa 1 -D/IR | H71: 4512453195 | I71: Comprometido | J71: 25.06.2026 | K71: 1 | L71: USD | M71: =IF(BD.PD[[#This Row],[Mon]]="DOP",1,HLOOKUP(BD.PD[[#This Row],[Mon]],$K$1:$L$2,2,FALSE)) -> 61 | N71: 25500 | O71: =BD.PD[[#This Row],[Cant.]]*BD.PD[[#This Row],[ Tasa ]]*BD.PD[[#This Row],[ Precio Und.]] -> 1555500 | P71: 0 | Q71: =IF(BD.PD[[#This Row],[Liquid. '[%']]]<>0,(BD.PD[[#This Row],[Valor Neto '[DOP']]]*BD.PD[[#This Row],[Liquid. '[%']]])+BD.PD[[#This Row],[Valor Neto '[DOP']]],BD.PD[[#This Row],[Valor Neto '[DOP']]]) -> 1555500 | R71: =BD.PD[[#This Row],[Ppto. Orden Interna '[DOP']]]/HLOOKUP("USD",$K$1:$L$2,2,FALSE) -> 25500 | S71: 75170 SERVICIOS E INST. TECNICAS S R L | U71: NTCO011104 | V71: 801667 | W71: 75170 SERVICIOS E INST. TECNICAS S R L | X71: 4 | Y71: 0.4 | Z71: =BD.PD[[#This Row],[Av.P1 '[%']]]*BD.PD[[#This Row],[Ppto. Orden Interna '[DOP']]] -> 622200 | AA71: 19 | AB71: 0.5 | AC71: =BD.PD[[#This Row],[Av.P2 '[%']]]*BD.PD[[#This Row],[Ppto. Orden Interna '[DOP']]] -> 777750 | AD71: 21 | AE71: 0.1 | AF71: =BD.PD[[#This Row],[Av.P3 '[%']]]*BD.PD[[#This Row],[Ppto. Orden Interna '[DOP']]] -> 155550 | AM71: =BD.PD[[#This Row],[Pago 3]]+BD.PD[[#This Row],[Pago 2]]+BD.PD[[#This Row],[Pago 1]] -> 1555500 | AN71: Sirena Compacta | AO71: Sirena Las Terrenas | AP71: MC33 | AQ71: Marrón | AR71: 594 | AS71: Orden Colocada
A72: 2.08 | C72: =VLOOKUP(BD.PD[[#This Row],[Pos]],PPto[],3,FALSE) -> 2.08 Instalaciones Mecánicas | D72: OI | E72: =IF(BD.PD[[#This Row],[.]]="*",VLOOKUP(BD.PD[[#This Row],[Pos]],Presupuesto!A:H,7,FALSE),"") | F72: INSTALACION ELEVADOR PRODUCCION 1,000 KGS | G72: Etapa 1 -D/IR | H72: 4512453195 | I72: Comprometido | J72: 25.06.2026 | K72: 1 | L72: USD | M72: =IF(BD.PD[[#This Row],[Mon]]="DOP",1,HLOOKUP(BD.PD[[#This Row],[Mon]],$K$1:$L$2,2,FALSE)) -> 61 | N72: 3000 | O72: =BD.PD[[#This Row],[Cant.]]*BD.PD[[#This Row],[ Tasa ]]*BD.PD[[#This Row],[ Precio Und.]] -> 183000 | P72: 0 | Q72: =IF(BD.PD[[#This Row],[Liquid. '[%']]]<>0,(BD.PD[[#This Row],[Valor Neto '[DOP']]]*BD.PD[[#This Row],[Liquid. '[%']]])+BD.PD[[#This Row],[Valor Neto '[DOP']]],BD.PD[[#This Row],[Valor Neto '[DOP']]]) -> 183000 | R72: =BD.PD[[#This Row],[Ppto. Orden Interna '[DOP']]]/HLOOKUP("USD",$K$1:$L$2,2,FALSE) -> 3000 | S72: 75170 SERVICIOS E INST. TECNICAS S R L | U72: NTCO011104 | V72: 801667 | W72: 75170 SERVICIOS E INST. TECNICAS S R L | X72: 4 | Y72: 0.4 | Z72: =BD.PD[[#This Row],[Av.P1 '[%']]]*BD.PD[[#This Row],[Ppto. Orden Interna '[DOP']]] -> 73200 | AA72: 19 | AB72: 0.5 | AC72: =BD.PD[[#This Row],[Av.P2 '[%']]]*BD.PD[[#This Row],[Ppto. Orden Interna '[DOP']]] -> 91500 | AD72: 21 | AE72: 0.1 | AF72: =BD.PD[[#This Row],[Av.P3 '[%']]]*BD.PD[[#This Row],[Ppto. Orden Interna '[DOP']]] -> 18300 | AM72: =BD.PD[[#This Row],[Pago 3]]+BD.PD[[#This Row],[Pago 2]]+BD.PD[[#This Row],[Pago 1]] -> 183000 | AN72: Sirena Compacta | AO72: Sirena Las Terrenas | AP72: MC33 | AQ72: Marrón | AR72: 594 | AS72: Orden Colocada
A73: 2.08 | C73: =VLOOKUP(BD.PD[[#This Row],[Pos]],PPto[],3,FALSE) -> 2.08 Instalaciones Mecánicas | D73: OI | E73: =IF(BD.PD[[#This Row],[.]]="*",VLOOKUP(BD.PD[[#This Row],[Pos]],Presupuesto!A:H,7,FALSE),"") | F73: TRANSPORTE ELEVADOR PRODUCCION | G73: Etapa 1 -D/IR | H73: 4512453195 | I73: Comprometido | J73: 25.06.2026 | K73: 1 | L73: USD | M73: =IF(BD.PD[[#This Row],[Mon]]="DOP",1,HLOOKUP(BD.PD[[#This Row],[Mon]],$K$1:$L$2,2,FALSE)) -> 61 | N73: 1500 | O73: =BD.PD[[#This Row],[Cant.]]*BD.PD[[#This Row],[ Tasa ]]*BD.PD[[#This Row],[ Precio Und.]] -> 91500 | P73: 0 | Q73: =IF(BD.PD[[#This Row],[Liquid. '[%']]]<>0,(BD.PD[[#This Row],[Valor Neto '[DOP']]]*BD.PD[[#This Row],[Liquid. '[%']]])+BD.PD[[#This Row],[Valor Neto '[DOP']]],BD.PD[[#This Row],[Valor Neto '[DOP']]]) -> 91500 | R73: =BD.PD[[#This Row],[Ppto. Orden Interna '[DOP']]]/HLOOKUP("USD",$K$1:$L$2,2,FALSE) -> 1500 | S73: 75170 SERVICIOS E INST. TECNICAS S R L | U73: NTCO011104 | V73: 801667 | W73: 75170 SERVICIOS E INST. TECNICAS S R L | X73: 4 | Y73: 0.4 | Z73: =BD.PD[[#This Row],[Av.P1 '[%']]]*BD.PD[[#This Row],[Ppto. Orden Interna '[DOP']]] -> 36600 | AA73: 19 | AB73: 0.5 | AC73: =BD.PD[[#This Row],[Av.P2 '[%']]]*BD.PD[[#This Row],[Ppto. Orden Interna '[DOP']]] -> 45750 | AD73: 21 | AE73: 0.1 | AF73: =BD.PD[[#This Row],[Av.P3 '[%']]]*BD.PD[[#This Row],[Ppto. Orden Interna '[DOP']]] -> 9150 | AM73: =BD.PD[[#This Row],[Pago 3]]+BD.PD[[#This Row],[Pago 2]]+BD.PD[[#This Row],[Pago 1]] -> 91500 | AN73: Sirena Compacta | AO73: Sirena Las Terrenas | AP73: MC33 | AQ73: Marrón | AR73: 594 | AS73: Orden Colocada
A74: 2.08 | C74: =VLOOKUP(BD.PD[[#This Row],[Pos]],PPto[],3,FALSE) -> 2.08 Instalaciones Mecánicas | D74: OI | E74: =IF(BD.PD[[#This Row],[.]]="*",VLOOKUP(BD.PD[[#This Row],[Pos]],Presupuesto!A:H,7,FALSE),"") | F74: FLETE ELEVADOR | G74: Etapa 1 -D/IR | H74: 4512453195 | I74: Comprometido | J74: 25.06.2026 | K74: 1 | L74: USD | M74: =IF(BD.PD[[#This Row],[Mon]]="DOP",1,HLOOKUP(BD.PD[[#This Row],[Mon]],$K$1:$L$2,2,FALSE)) -> 61 | N74: 2750 | O74: =BD.PD[[#This Row],[Cant.]]*BD.PD[[#This Row],[ Tasa ]]*BD.PD[[#This Row],[ Precio Und.]] -> 167750 | P74: 0 | Q74: =IF(BD.PD[[#This Row],[Liquid. '[%']]]<>0,(BD.PD[[#This Row],[Valor Neto '[DOP']]]*BD.PD[[#This Row],[Liquid. '[%']]])+BD.PD[[#This Row],[Valor Neto '[DOP']]],BD.PD[[#This Row],[Valor Neto '[DOP']]]) -> 167750 | R74: =BD.PD[[#This Row],[Ppto. Orden Interna '[DOP']]]/HLOOKUP("USD",$K$1:$L$2,2,FALSE) -> 2750 | S74: 75170 SERVICIOS E INST. TECNICAS S R L | U74: NTCO011104 | V74: 801667 | W74: 75170 SERVICIOS E INST. TECNICAS S R L | X74: 4 | Y74: 0.4 | Z74: =BD.PD[[#This Row],[Av.P1 '[%']]]*BD.PD[[#This Row],[Ppto. Orden Interna '[DOP']]] -> 67100 | AA74: 19 | AB74: 0.5 | AC74: =BD.PD[[#This Row],[Av.P2 '[%']]]*BD.PD[[#This Row],[Ppto. Orden Interna '[DOP']]] -> 83875 | AD74: 21 | AE74: 0.1 | AF74: =BD.PD[[#This Row],[Av.P3 '[%']]]*BD.PD[[#This Row],[Ppto. Orden Interna '[DOP']]] -> 16775 | AM74: =BD.PD[[#This Row],[Pago 3]]+BD.PD[[#This Row],[Pago 2]]+BD.PD[[#This Row],[Pago 1]] -> 167750 | AN74: Sirena Compacta | AO74: Sirena Las Terrenas | AP74: MC33 | AQ74: Marrón | AR74: 594 | AS74: Orden Colocada
A75: 2.09 | B75: * | C75: =VLOOKUP(BD.PD[[#This Row],[Pos]],PPto[],3,FALSE) -> 2.09 Rejillas y Sumideros | D75: * | E75: =IF(BD.PD[[#This Row],[.]]="*",VLOOKUP(BD.PD[[#This Row],[Pos]],Presupuesto!A:H,7,FALSE),"") -> 10654.035 | K75: 1 | L75: USD | M75: =IF(BD.PD[[#This Row],[Mon]]="DOP",1,HLOOKUP(BD.PD[[#This Row],[Mon]],$K$1:$L$2,2,FALSE)) -> 61 | N75: 0 | O75: =BD.PD[[#This Row],[Cant.]]*BD.PD[[#This Row],[ Tasa ]]*BD.PD[[#This Row],[ Precio Und.]] -> 0 | P75: 0 | Q75: =IF(BD.PD[[#This Row],[Liquid. '[%']]]<>0,(BD.PD[[#This Row],[Valor Neto '[DOP']]]*BD.PD[[#This Row],[Liquid. '[%']]])+BD.PD[[#This Row],[Valor Neto '[DOP']]],BD.PD[[#This Row],[Valor Neto '[DOP']]]) -> 0 | R75: =BD.PD[[#This Row],[Ppto. Orden Interna '[DOP']]]/HLOOKUP("USD",$K$1:$L$2,2,FALSE) -> 0 | Z75: =BD.PD[[#This Row],[Av.P1 '[%']]]*BD.PD[[#This Row],[Ppto. Orden Interna '[DOP']]] -> 0 | AC75: =BD.PD[[#This Row],[Av.P2 '[%']]]*BD.PD[[#This Row],[Ppto. Orden Interna '[DOP']]] -> 0 | AF75: =BD.PD[[#This Row],[Av.P3 '[%']]]*BD.PD[[#This Row],[Ppto. Orden Interna '[DOP']]] -> 0 | AM75: =BD.PD[[#This Row],[Pago 3]]+BD.PD[[#This Row],[Pago 2]]+BD.PD[[#This Row],[Pago 1]] -> 0
A76: 2.09 | C76: =VLOOKUP(BD.PD[[#This Row],[Pos]],PPto[],3,FALSE) -> 2.09 Rejillas y Sumideros | D76: OI | E76: =IF(BD.PD[[#This Row],[.]]="*",VLOOKUP(BD.PD[[#This Row],[Pos]],Presupuesto!A:H,7,FALSE),"") | F76: REJILLAS DE 1.20m x 0.15m | G76: Etapa 1 -D/IR | H76: 4600072801 | I76: Stock AF01 | J76: 25.06.2026 | K76: 9 | L76: DOP | M76: =IF(BD.PD[[#This Row],[Mon]]="DOP",1,HLOOKUP(BD.PD[[#This Row],[Mon]],$K$1:$L$2,2,FALSE)) -> 1 | N76: 20631 | O76: =BD.PD[[#This Row],[Cant.]]*BD.PD[[#This Row],[ Tasa ]]*BD.PD[[#This Row],[ Precio Und.]] -> 185679 | P76: 0 | Q76: =IF(BD.PD[[#This Row],[Liquid. '[%']]]<>0,(BD.PD[[#This Row],[Valor Neto '[DOP']]]*BD.PD[[#This Row],[Liquid. '[%']]])+BD.PD[[#This Row],[Valor Neto '[DOP']]],BD.PD[[#This Row],[Valor Neto '[DOP']]]) -> 185679 | R76: =BD.PD[[#This Row],[Ppto. Orden Interna '[DOP']]]/HLOOKUP("USD",$K$1:$L$2,2,FALSE) -> 3043.918 | S76: 35682- ACO CARIBE S.A. | U76: NTCO011104 | V76: 801667 | W76: 35682- ACO CARIBE S.A. | X76: 3 | Y76: 0.4 | Z76: =BD.PD[[#This Row],[Av.P1 '[%']]]*BD.PD[[#This Row],[Ppto. Orden Interna '[DOP']]] -> 74271.6 | AA76: 6 | AB76: 0.6 | AC76: =BD.PD[[#This Row],[Av.P2 '[%']]]*BD.PD[[#This Row],[Ppto. Orden Interna '[DOP']]] -> 111407.4 | AF76: =BD.PD[[#This Row],[Av.P3 '[%']]]*BD.PD[[#This Row],[Ppto. Orden Interna '[DOP']]] -> 0 | AM76: =BD.PD[[#This Row],[Pago 3]]+BD.PD[[#This Row],[Pago 2]]+BD.PD[[#This Row],[Pago 1]] -> 185679 | AN76: Sirena Compacta | AO76: Sirena Las Terrenas | AP76: MC33 | AQ76: Marrón | AR76: 594 | AS76: Orden Colocada
A77: 2.09 | C77: =VLOOKUP(BD.PD[[#This Row],[Pos]],PPto[],3,FALSE) -> 2.09 Rejillas y Sumideros | D77: OI | E77: =IF(BD.PD[[#This Row],[.]]="*",VLOOKUP(BD.PD[[#This Row],[Pos]],Presupuesto!A:H,7,FALSE),"") | F77: REJILLAS DE 1.50m x 0.15m | G77: Etapa 1 -D/IR | H77: 4600072801 | I77: Stock AF01 | J77: 25.06.2026 | K77: 9 | L77: DOP | M77: =IF(BD.PD[[#This Row],[Mon]]="DOP",1,HLOOKUP(BD.PD[[#This Row],[Mon]],$K$1:$L$2,2,FALSE)) -> 1 | N77: 24606 | O77: =BD.PD[[#This Row],[Cant.]]*BD.PD[[#This Row],[ Tasa ]]*BD.PD[[#This Row],[ Precio Und.]] -> 221454 | P77: 0 | Q77: =IF(BD.PD[[#This Row],[Liquid. '[%']]]<>0,(BD.PD[[#This Row],[Valor Neto '[DOP']]]*BD.PD[[#This Row],[Liquid. '[%']]])+BD.PD[[#This Row],[Valor Neto '[DOP']]],BD.PD[[#This Row],[Valor Neto '[DOP']]]) -> 221454 | R77: =BD.PD[[#This Row],[Ppto. Orden Interna '[DOP']]]/HLOOKUP("USD",$K$1:$L$2,2,FALSE) -> 3630.3934 | S77: 35682- ACO CARIBE S.A. | U77: NTCO011104 | V77: 801667 | W77: 35682- ACO CARIBE S.A. | X77: 3 | Y77: 0.4 | Z77: =BD.PD[[#This Row],[Av.P1 '[%']]]*BD.PD[[#This Row],[Ppto. Orden Interna '[DOP']]] -> 88581.6 | AA77: 6 | AB77: 0.6 | AC77: =BD.PD[[#This Row],[Av.P2 '[%']]]*BD.PD[[#This Row],[Ppto. Orden Interna '[DOP']]] -> 132872.4 | AF77: =BD.PD[[#This Row],[Av.P3 '[%']]]*BD.PD[[#This Row],[Ppto. Orden Interna '[DOP']]] -> 0 | AM77: =BD.PD[[#This Row],[Pago 3]]+BD.PD[[#This Row],[Pago 2]]+BD.PD[[#This Row],[Pago 1]] -> 221454 | AN77: Sirena Compacta | AO77: Sirena Las Terrenas | AP77: MC33 | AQ77: Marrón | AR77: 594 | AS77: Orden Colocada
A78: 2.09 | C78: =VLOOKUP(BD.PD[[#This Row],[Pos]],PPto[],3,FALSE) -> 2.09 Rejillas y Sumideros | D78: OI | E78: =IF(BD.PD[[#This Row],[.]]="*",VLOOKUP(BD.PD[[#This Row],[Pos]],Presupuesto!A:H,7,FALSE),"") | F78: REJILLAS DE 1.80m x 0.15m | G78: Etapa 1 -D/IR | H78: 4600072801 | I78: Stock AF01 | J78: 25.06.2026 | K78: 8 | L78: DOP | M78: =IF(BD.PD[[#This Row],[Mon]]="DOP",1,HLOOKUP(BD.PD[[#This Row],[Mon]],$K$1:$L$2,2,FALSE)) -> 1 | N78: 31801.42 | O78: =BD.PD[[#This Row],[Cant.]]*BD.PD[[#This Row],[ Tasa ]]*BD.PD[[#This Row],[ Precio Und.]] -> 254411.36 | P78: 0 | Q78: =IF(BD.PD[[#This Row],[Liquid. '[%']]]<>0,(BD.PD[[#This Row],[Valor Neto '[DOP']]]*BD.PD[[#This Row],[Liquid. '[%']]])+BD.PD[[#This Row],[Valor Neto '[DOP']]],BD.PD[[#This Row],[Valor Neto '[DOP']]]) -> 254411.36 | R78: =BD.PD[[#This Row],[Ppto. Orden Interna '[DOP']]]/HLOOKUP("USD",$K$1:$L$2,2,FALSE) -> 4170.678 | S78: 35682- ACO CARIBE S.A. | U78: NTCO011104 | V78: 801667 | W78: 35682- ACO CARIBE S.A. | X78: 3 | Y78: 0.4 | Z78: =BD.PD[[#This Row],[Av.P1 '[%']]]*BD.PD[[#This Row],[Ppto. Orden Interna '[DOP']]] -> 101764.54 | AA78: 6 | AB78: 0.6 | AC78: =BD.PD[[#This Row],[Av.P2 '[%']]]*BD.PD[[#This Row],[Ppto. Orden Interna '[DOP']]] -> 152646.82 | AF78: =BD.PD[[#This Row],[Av.P3 '[%']]]*BD.PD[[#This Row],[Ppto. Orden Interna '[DOP']]] -> 0 | AM78: =BD.PD[[#This Row],[Pago 3]]+BD.PD[[#This Row],[Pago 2]]+BD.PD[[#This Row],[Pago 1]] -> 254411.36 | AN78: Sirena Compacta | AO78: Sirena Las Terrenas | AP78: MC33 | AQ78: Marrón | AR78: 594 | AS78: Orden Colocada
A79: 2.1 | B79: * | C79: =VLOOKUP(BD.PD[[#This Row],[Pos]],PPto[],3,FALSE) -> 2.10 Supervisión Civil y Sanitaria | D79: * | E79: =IF(BD.PD[[#This Row],[.]]="*",VLOOKUP(BD.PD[[#This Row],[Pos]],Presupuesto!A:H,7,FALSE),"") -> 0 | K79: 1 | L79: USD | M79: =IF(BD.PD[[#This Row],[Mon]]="DOP",1,HLOOKUP(BD.PD[[#This Row],[Mon]],$K$1:$L$2,2,FALSE)) -> 61 | N79: 0 | O79: =BD.PD[[#This Row],[Cant.]]*BD.PD[[#This Row],[ Tasa ]]*BD.PD[[#This Row],[ Precio Und.]] -> 0 | P79: 0 | Q79: =IF(BD.PD[[#This Row],[Liquid. '[%']]]<>0,(BD.PD[[#This Row],[Valor Neto '[DOP']]]*BD.PD[[#This Row],[Liquid. '[%']]])+BD.PD[[#This Row],[Valor Neto '[DOP']]],BD.PD[[#This Row],[Valor Neto '[DOP']]]) -> 0 | R79: =BD.PD[[#This Row],[Ppto. Orden Interna '[DOP']]]/HLOOKUP("USD",$K$1:$L$2,2,FALSE) -> 0 | Z79: =BD.PD[[#This Row],[Av.P1 '[%']]]*BD.PD[[#This Row],[Ppto. Orden Interna '[DOP']]] -> 0 | AC79: =BD.PD[[#This Row],[Av.P2 '[%']]]*BD.PD[[#This Row],[Ppto. Orden Interna '[DOP']]] -> 0 | AF79: =BD.PD[[#This Row],[Av.P3 '[%']]]*BD.PD[[#This Row],[Ppto. Orden Interna '[DOP']]] -> 0 | AM79: =BD.PD[[#This Row],[Pago 3]]+BD.PD[[#This Row],[Pago 2]]+BD.PD[[#This Row],[Pago 1]] -> 0
A80: 2.11 | B80: * | C80: =VLOOKUP(BD.PD[[#This Row],[Pos]],PPto[],3,FALSE) -> 2.11 Supervisión Arquitectónica | D80: * | E80: =IF(BD.PD[[#This Row],[.]]="*",VLOOKUP(BD.PD[[#This Row],[Pos]],Presupuesto!A:H,7,FALSE),"") -> 0 | K80: 1 | L80: USD | M80: =IF(BD.PD[[#This Row],[Mon]]="DOP",1,HLOOKUP(BD.PD[[#This Row],[Mon]],$K$1:$L$2,2,FALSE)) -> 61 | N80: 0 | O80: =BD.PD[[#This Row],[Cant.]]*BD.PD[[#This Row],[ Tasa ]]*BD.PD[[#This Row],[ Precio Und.]] -> 0 | P80: 0 | Q80: =IF(BD.PD[[#This Row],[Liquid. '[%']]]<>0,(BD.PD[[#This Row],[Valor Neto '[DOP']]]*BD.PD[[#This Row],[Liquid. '[%']]])+BD.PD[[#This Row],[Valor Neto '[DOP']]],BD.PD[[#This Row],[Valor Neto '[DOP']]]) -> 0 | R80: =BD.PD[[#This Row],[Ppto. Orden Interna '[DOP']]]/HLOOKUP("USD",$K$1:$L$2,2,FALSE) -> 0 | Z80: =BD.PD[[#This Row],[Av.P1 '[%']]]*BD.PD[[#This Row],[Ppto. Orden Interna '[DOP']]] -> 0 | AC80: =BD.PD[[#This Row],[Av.P2 '[%']]]*BD.PD[[#This Row],[Ppto. Orden Interna '[DOP']]] -> 0 | AF80: =BD.PD[[#This Row],[Av.P3 '[%']]]*BD.PD[[#This Row],[Ppto. Orden Interna '[DOP']]] -> 0 | AM80: =BD.PD[[#This Row],[Pago 3]]+BD.PD[[#This Row],[Pago 2]]+BD.PD[[#This Row],[Pago 1]] -> 0
A81: 3.01 | B81: * | C81: =VLOOKUP(BD.PD[[#This Row],[Pos]],PPto[],3,FALSE) -> 3.01 Instalaciones Eléctricas | D81: * | E81: =IF(BD.PD[[#This Row],[.]]="*",VLOOKUP(BD.PD[[#This Row],[Pos]],Presupuesto!A:H,7,FALSE),"") -> 0 | K81: 1 | L81: USD | M81: =IF(BD.PD[[#This Row],[Mon]]="DOP",1,HLOOKUP(BD.PD[[#This Row],[Mon]],$K$1:$L$2,2,FALSE)) -> 61 | N81: 0 | O81: =BD.PD[[#This Row],[Cant.]]*BD.PD[[#This Row],[ Tasa ]]*BD.PD[[#This Row],[ Precio Und.]] -> 0 | P81: 0 | Q81: =IF(BD.PD[[#This Row],[Liquid. '[%']]]<>0,(BD.PD[[#This Row],[Valor Neto '[DOP']]]*BD.PD[[#This Row],[Liquid. '[%']]])+BD.PD[[#This Row],[Valor Neto '[DOP']]],BD.PD[[#This Row],[Valor Neto '[DOP']]]) -> 0 | R81: =BD.PD[[#This Row],[Ppto. Orden Interna '[DOP']]]/HLOOKUP("USD",$K$1:$L$2,2,FALSE) -> 0 | Z81: =BD.PD[[#This Row],[Av.P1 '[%']]]*BD.PD[[#This Row],[Ppto. Orden Interna '[DOP']]] -> 0 | AC81: =BD.PD[[#This Row],[Av.P2 '[%']]]*BD.PD[[#This Row],[Ppto. Orden Interna '[DOP']]] -> 0 | AF81: =BD.PD[[#This Row],[Av.P3 '[%']]]*BD.PD[[#This Row],[Ppto. Orden Interna '[DOP']]] -> 0 | AM81: =BD.PD[[#This Row],[Pago 3]]+BD.PD[[#This Row],[Pago 2]]+BD.PD[[#This Row],[Pago 1]] -> 0
A82: 3.01 | C82: =VLOOKUP(BD.PD[[#This Row],[Pos]],PPto[],3,FALSE) -> 3.01 Instalaciones Eléctricas | D82: OI | E82: =IF(BD.PD[[#This Row],[.]]="*",VLOOKUP(BD.PD[[#This Row],[Pos]],Presupuesto!A:H,7,FALSE),"") | F82: COOPER LT LUMINARIA 4APVTLD-SL3C3 | G82: Etapa 2 -D/IR | H82: 4600079254 | I82: Comprometido | J82: 03.07.2026 | K82: 162 | L82: USD | M82: =IF(BD.PD[[#This Row],[Mon]]="DOP",1,HLOOKUP(BD.PD[[#This Row],[Mon]],$K$1:$L$2,2,FALSE)) -> 61 | N82: 69.31 | O82: =BD.PD[[#This Row],[Cant.]]*BD.PD[[#This Row],[ Tasa ]]*BD.PD[[#This Row],[ Precio Und.]] -> 684921.42 | P82: 0 | Q82: =IF(BD.PD[[#This Row],[Liquid. '[%']]]<>0,(BD.PD[[#This Row],[Valor Neto '[DOP']]]*BD.PD[[#This Row],[Liquid. '[%']]])+BD.PD[[#This Row],[Valor Neto '[DOP']]],BD.PD[[#This Row],[Valor Neto '[DOP']]]) -> 684921.42 | R82: =BD.PD[[#This Row],[Ppto. Orden Interna '[DOP']]]/HLOOKUP("USD",$K$1:$L$2,2,FALSE) -> 11228.22 | S82: 35820 CORPEMC ELECTRIC MIAMI INC | U82: NTCO011106 | V82: 801668 | W82: 35820 CORPEMC ELECTRIC MIAMI INC | X82: 20 | Y82: 1 | Z82: =BD.PD[[#This Row],[Av.P1 '[%']]]*BD.PD[[#This Row],[Ppto. Orden Interna '[DOP']]] -> 684921.42 | AC82: =BD.PD[[#This Row],[Av.P2 '[%']]]*BD.PD[[#This Row],[Ppto. Orden Interna '[DOP']]] -> 0 | AF82: =BD.PD[[#This Row],[Av.P3 '[%']]]*BD.PD[[#This Row],[Ppto. Orden Interna '[DOP']]] -> 0 | AM82: =BD.PD[[#This Row],[Pago 3]]+BD.PD[[#This Row],[Pago 2]]+BD.PD[[#This Row],[Pago 1]] -> 684921.42 | AN82: Sirena Compacta | AO82: Sirena Las Terrenas | AP82: MC33 | AQ82: Marrón | AR82: 594 | AS82: Orden Colocada
A83: 3.01 | C83: =VLOOKUP(BD.PD[[#This Row],[Pos]],PPto[],3,FALSE) -> 3.01 Instalaciones Eléctricas | D83: OI | E83: =IF(BD.PD[[#This Row],[.]]="*",VLOOKUP(BD.PD[[#This Row],[Pos]],Presupuesto!A:H,7,FALSE),"") | F83: COOPER LUMINARIA CGTSURF22 | G83: Etapa 2 -D/IR | H83: 4600079254 | I83: Comprometido | J83: 03.07.2026 | K83: 6 | L83: USD | M83: =IF(BD.PD[[#This Row],[Mon]]="DOP",1,HLOOKUP(BD.PD[[#This Row],[Mon]],$K$1:$L$2,2,FALSE)) -> 61 | N83: 23.54 | O83: =BD.PD[[#This Row],[Cant.]]*BD.PD[[#This Row],[ Tasa ]]*BD.PD[[#This Row],[ Precio Und.]] -> 8615.64 | P83: 0 | Q83: =IF(BD.PD[[#This Row],[Liquid. '[%']]]<>0,(BD.PD[[#This Row],[Valor Neto '[DOP']]]*BD.PD[[#This Row],[Liquid. '[%']]])+BD.PD[[#This Row],[Valor Neto '[DOP']]],BD.PD[[#This Row],[Valor Neto '[DOP']]]) -> 8615.64 | R83: =BD.PD[[#This Row],[Ppto. Orden Interna '[DOP']]]/HLOOKUP("USD",$K$1:$L$2,2,FALSE) -> 141.24 | S83: 35820 CORPEMC ELECTRIC MIAMI INC | U83: NTCO011106 | V83: 801668 | W83: 35820 CORPEMC ELECTRIC MIAMI INC | X83: 20 | Y83: 1 | Z83: =BD.PD[[#This Row],[Av.P1 '[%']]]*BD.PD[[#This Row],[Ppto. Orden Interna '[DOP']]] -> 8615.64 | AC83: =BD.PD[[#This Row],[Av.P2 '[%']]]*BD.PD[[#This Row],[Ppto. Orden Interna '[DOP']]] -> 0 | AF83: =BD.PD[[#This Row],[Av.P3 '[%']]]*BD.PD[[#This Row],[Ppto. Orden Interna '[DOP']]] -> 0 | AM83: =BD.PD[[#This Row],[Pago 3]]+BD.PD[[#This Row],[Pago 2]]+BD.PD[[#This Row],[Pago 1]] -> 8615.64 | AN83: Sirena Compacta | AO83: Sirena Las Terrenas | AP83: MC33 | AQ83: Marrón | AR83: 594 | AS83: Orden Colocada
A84: 3.01 | C84: =VLOOKUP(BD.PD[[#This Row],[Pos]],PPto[],3,FALSE) -> 3.01 Instalaciones Eléctricas | D84: OI | E84: =IF(BD.PD[[#This Row],[.]]="*",VLOOKUP(BD.PD[[#This Row],[Pos]],Presupuesto!A:H,7,FALSE),"") | F84: COOPER LUMINARIA L80925WF930MB | G84: Etapa 2 -D/IR | H84: 4600079254 | I84: Comprometido | J84: 03.07.2026 | K84: 48 | L84: USD | M84: =IF(BD.PD[[#This Row],[Mon]]="DOP",1,HLOOKUP(BD.PD[[#This Row],[Mon]],$K$1:$L$2,2,FALSE)) -> 61 | N84: 142 | O84: =BD.PD[[#This Row],[Cant.]]*BD.PD[[#This Row],[ Tasa ]]*BD.PD[[#This Row],[ Precio Und.]] -> 415776 | P84: 0 | Q84: =IF(BD.PD[[#This Row],[Liquid. '[%']]]<>0,(BD.PD[[#This Row],[Valor Neto '[DOP']]]*BD.PD[[#This Row],[Liquid. '[%']]])+BD.PD[[#This Row],[Valor Neto '[DOP']]],BD.PD[[#This Row],[Valor Neto '[DOP']]]) -> 415776 | R84: =BD.PD[[#This Row],[Ppto. Orden Interna '[DOP']]]/HLOOKUP("USD",$K$1:$L$2,2,FALSE) -> 6816 | S84: 35820 CORPEMC ELECTRIC MIAMI INC | U84: NTCO011106 | V84: 801668 | W84: 35820 CORPEMC ELECTRIC MIAMI INC | X84: 20 | Y84: 1 | Z84: =BD.PD[[#This Row],[Av.P1 '[%']]]*BD.PD[[#This Row],[Ppto. Orden Interna '[DOP']]] -> 415776 | AC84: =BD.PD[[#This Row],[Av.P2 '[%']]]*BD.PD[[#This Row],[Ppto. Orden Interna '[DOP']]] -> 0 | AF84: =BD.PD[[#This Row],[Av.P3 '[%']]]*BD.PD[[#This Row],[Ppto. Orden Interna '[DOP']]] -> 0 | AM84: =BD.PD[[#This Row],[Pago 3]]+BD.PD[[#This Row],[Pago 2]]+BD.PD[[#This Row],[Pago 1]] -> 415776 | AN84: Sirena Compacta | AO84: Sirena Las Terrenas | AP84: MC33 | AQ84: Marrón | AR84: 594 | AS84: Orden Colocada
A85: 3.01 | C85: =VLOOKUP(BD.PD[[#This Row],[Pos]],PPto[],3,FALSE) -> 3.01 Instalaciones Eléctricas | D85: OI | E85: =IF(BD.PD[[#This Row],[.]]="*",VLOOKUP(BD.PD[[#This Row],[Pos]],Presupuesto!A:H,7,FALSE),"") | F85: COOPER LT LUMINARIA L653MB | G85: Etapa 2 -D/IR | H85: 4600079254 | I85: Comprometido | J85: 03.07.2026 | K85: 15 | L85: USD | M85: =IF(BD.PD[[#This Row],[Mon]]="DOP",1,HLOOKUP(BD.PD[[#This Row],[Mon]],$K$1:$L$2,2,FALSE)) -> 61 | N85: 65.17 | O85: =BD.PD[[#This Row],[Cant.]]*BD.PD[[#This Row],[ Tasa ]]*BD.PD[[#This Row],[ Precio Und.]] -> 59630.55 | P85: 0 | Q85: =IF(BD.PD[[#This Row],[Liquid. '[%']]]<>0,(BD.PD[[#This Row],[Valor Neto '[DOP']]]*BD.PD[[#This Row],[Liquid. '[%']]])+BD.PD[[#This Row],[Valor Neto '[DOP']]],BD.PD[[#This Row],[Valor Neto '[DOP']]]) -> 59630.55 | R85: =BD.PD[[#This Row],[Ppto. Orden Interna '[DOP']]]/HLOOKUP("USD",$K$1:$L$2,2,FALSE) -> 977.55 | S85: 35820 CORPEMC ELECTRIC MIAMI INC | U85: NTCO011106 | V85: 801668 | W85: 35820 CORPEMC ELECTRIC MIAMI INC | X85: 20 | Y85: 1 | Z85: =BD.PD[[#This Row],[Av.P1 '[%']]]*BD.PD[[#This Row],[Ppto. Orden Interna '[DOP']]] -> 59630.55 | AC85: =BD.PD[[#This Row],[Av.P2 '[%']]]*BD.PD[[#This Row],[Ppto. Orden Interna '[DOP']]] -> 0 | AF85: =BD.PD[[#This Row],[Av.P3 '[%']]]*BD.PD[[#This Row],[Ppto. Orden Interna '[DOP']]] -> 0 | AM85: =BD.PD[[#This Row],[Pago 3]]+BD.PD[[#This Row],[Pago 2]]+BD.PD[[#This Row],[Pago 1]] -> 59630.55 | AN85: Sirena Compacta | AO85: Sirena Las Terrenas | AP85: MC33 | AQ85: Marrón | AR85: 594 | AS85: Orden Colocada
A86: 3.01 | C86: =VLOOKUP(BD.PD[[#This Row],[Pos]],PPto[],3,FALSE) -> 3.01 Instalaciones Eléctricas | D86: OI | E86: =IF(BD.PD[[#This Row],[.]]="*",VLOOKUP(BD.PD[[#This Row],[Pos]],Presupuesto!A:H,7,FALSE),"") | F86: COOPER LT LUMINARIA L901MB | G86: Etapa 2 -D/IR | H86: 4600079254 | I86: Comprometido | J86: 03.07.2026 | K86: 15 | L86: USD | M86: =IF(BD.PD[[#This Row],[Mon]]="DOP",1,HLOOKUP(BD.PD[[#This Row],[Mon]],$K$1:$L$2,2,FALSE)) -> 61 | N86: 15.16 | O86: =BD.PD[[#This Row],[Cant.]]*BD.PD[[#This Row],[ Tasa ]]*BD.PD[[#This Row],[ Precio Und.]] -> 13871.4 | P86: 0 | Q86: =IF(BD.PD[[#This Row],[Liquid. '[%']]]<>0,(BD.PD[[#This Row],[Valor Neto '[DOP']]]*BD.PD[[#This Row],[Liquid. '[%']]])+BD.PD[[#This Row],[Valor Neto '[DOP']]],BD.PD[[#This Row],[Valor Neto '[DOP']]]) -> 13871.4 | R86: =BD.PD[[#This Row],[Ppto. Orden Interna '[DOP']]]/HLOOKUP("USD",$K$1:$L$2,2,FALSE) -> 227.4 | S86: 35820 CORPEMC ELECTRIC MIAMI INC | U86: NTCO011106 | V86: 801668 | W86: 35820 CORPEMC ELECTRIC MIAMI INC | X86: 20 | Y86: 1 | Z86: =BD.PD[[#This Row],[Av.P1 '[%']]]*BD.PD[[#This Row],[Ppto. Orden Interna '[DOP']]] -> 13871.4 | AC86: =BD.PD[[#This Row],[Av.P2 '[%']]]*BD.PD[[#This Row],[Ppto. Orden Interna '[DOP']]] -> 0 | AF86: =BD.PD[[#This Row],[Av.P3 '[%']]]*BD.PD[[#This Row],[Ppto. Orden Interna '[DOP']]] -> 0 | AM86: =BD.PD[[#This Row],[Pago 3]]+BD.PD[[#This Row],[Pago 2]]+BD.PD[[#This Row],[Pago 1]] -> 13871.4 | AN86: Sirena Compacta | AO86: Sirena Las Terrenas | AP86: MC33 | AQ86: Marrón | AR86: 594 | AS86: Orden Colocada
A87: 3.01 | C87: =VLOOKUP(BD.PD[[#This Row],[Pos]],PPto[],3,FALSE) -> 3.01 Instalaciones Eléctricas | D87: OI | E87: =IF(BD.PD[[#This Row],[.]]="*",VLOOKUP(BD.PD[[#This Row],[Pos]],Presupuesto!A:H,7,FALSE),"") | F87: COOPER LT LUMINARIA L908MB | G87: Etapa 2 -D/IR | H87: 4600079254 | I87: Comprometido | J87: 03.07.2026 | K87: 10 | L87: USD | M87: =IF(BD.PD[[#This Row],[Mon]]="DOP",1,HLOOKUP(BD.PD[[#This Row],[Mon]],$K$1:$L$2,2,FALSE)) -> 61 | N87: 14.85 | O87: =BD.PD[[#This Row],[Cant.]]*BD.PD[[#This Row],[ Tasa ]]*BD.PD[[#This Row],[ Precio Und.]] -> 9058.5 | P87: 0 | Q87: =IF(BD.PD[[#This Row],[Liquid. '[%']]]<>0,(BD.PD[[#This Row],[Valor Neto '[DOP']]]*BD.PD[[#This Row],[Liquid. '[%']]])+BD.PD[[#This Row],[Valor Neto '[DOP']]],BD.PD[[#This Row],[Valor Neto '[DOP']]]) -> 9058.5 | R87: =BD.PD[[#This Row],[Ppto. Orden Interna '[DOP']]]/HLOOKUP("USD",$K$1:$L$2,2,FALSE) -> 148.5 | S87: 35820 CORPEMC ELECTRIC MIAMI INC | U87: NTCO011106 | V87: 801668 | W87: 35820 CORPEMC ELECTRIC MIAMI INC | X87: 20 | Y87: 1 | Z87: =BD.PD[[#This Row],[Av.P1 '[%']]]*BD.PD[[#This Row],[Ppto. Orden Interna '[DOP']]] -> 9058.5 | AC87: =BD.PD[[#This Row],[Av.P2 '[%']]]*BD.PD[[#This Row],[Ppto. Orden Interna '[DOP']]] -> 0 | AF87: =BD.PD[[#This Row],[Av.P3 '[%']]]*BD.PD[[#This Row],[Ppto. Orden Interna '[DOP']]] -> 0 | AM87: =BD.PD[[#This Row],[Pago 3]]+BD.PD[[#This Row],[Pago 2]]+BD.PD[[#This Row],[Pago 1]] -> 9058.5 | AN87: Sirena Compacta | AO87: Sirena Las Terrenas | AP87: MC33 | AQ87: Marrón | AR87: 594 | AS87: Orden Colocada
A88: 3.01 | C88: =VLOOKUP(BD.PD[[#This Row],[Pos]],PPto[],3,FALSE) -> 3.01 Instalaciones Eléctricas | D88: OI | E88: =IF(BD.PD[[#This Row],[.]]="*",VLOOKUP(BD.PD[[#This Row],[Pos]],Presupuesto!A:H,7,FALSE),"") | F88: COOPER LUMINARIA DE600 | G88: Etapa 2 -D/IR | H88: 4600079254 | I88: Comprometido | J88: 03.07.2026 | K88: 15 | L88: USD | M88: =IF(BD.PD[[#This Row],[Mon]]="DOP",1,HLOOKUP(BD.PD[[#This Row],[Mon]],$K$1:$L$2,2,FALSE)) -> 61 | N88: 14.85 | O88: =BD.PD[[#This Row],[Cant.]]*BD.PD[[#This Row],[ Tasa ]]*BD.PD[[#This Row],[ Precio Und.]] -> 13587.75 | P88: 0 | Q88: =IF(BD.PD[[#This Row],[Liquid. '[%']]]<>0,(BD.PD[[#This Row],[Valor Neto '[DOP']]]*BD.PD[[#This Row],[Liquid. '[%']]])+BD.PD[[#This Row],[Valor Neto '[DOP']]],BD.PD[[#This Row],[Valor Neto '[DOP']]]) -> 13587.75 | R88: =BD.PD[[#This Row],[Ppto. Orden Interna '[DOP']]]/HLOOKUP("USD",$K$1:$L$2,2,FALSE) -> 222.75 | S88: 35820 CORPEMC ELECTRIC MIAMI INC | U88: NTCO011106 | V88: 801668 | W88: 35820 CORPEMC ELECTRIC MIAMI INC | X88: 20 | Y88: 1 | Z88: =BD.PD[[#This Row],[Av.P1 '[%']]]*BD.PD[[#This Row],[Ppto. Orden Interna '[DOP']]] -> 13587.75 | AC88: =BD.PD[[#This Row],[Av.P2 '[%']]]*BD.PD[[#This Row],[Ppto. Orden Interna '[DOP']]] -> 0 | AF88: =BD.PD[[#This Row],[Av.P3 '[%']]]*BD.PD[[#This Row],[Ppto. Orden Interna '[DOP']]] -> 0 | AM88: =BD.PD[[#This Row],[Pago 3]]+BD.PD[[#This Row],[Pago 2]]+BD.PD[[#This Row],[Pago 1]] -> 13587.75 | AN88: Sirena Compacta | AO88: Sirena Las Terrenas | AP88: MC33 | AQ88: Marrón | AR88: 594 | AS88: Orden Colocada
A89: 3.01 | C89: =VLOOKUP(BD.PD[[#This Row],[Pos]],PPto[],3,FALSE) -> 3.01 Instalaciones Eléctricas | D89: OI | E89: =IF(BD.PD[[#This Row],[.]]="*",VLOOKUP(BD.PD[[#This Row],[Pos]],Presupuesto!A:H,7,FALSE),"") | F89: COOPER LUMINARIA 8SLSTPSLC-UNV-MID-4000K | G89: Etapa 2 -D/IR | H89: 4600079254 | I89: Comprometido | J89: 03.07.2026 | K89: 289 | L89: USD | M89: =IF(BD.PD[[#This Row],[Mon]]="DOP",1,HLOOKUP(BD.PD[[#This Row],[Mon]],$K$1:$L$2,2,FALSE)) -> 61 | N89: 149.08 | O89: =BD.PD[[#This Row],[Cant.]]*BD.PD[[#This Row],[ Tasa ]]*BD.PD[[#This Row],[ Precio Und.]] -> 2628131.3 | P89: 0 | Q89: =IF(BD.PD[[#This Row],[Liquid. '[%']]]<>0,(BD.PD[[#This Row],[Valor Neto '[DOP']]]*BD.PD[[#This Row],[Liquid. '[%']]])+BD.PD[[#This Row],[Valor Neto '[DOP']]],BD.PD[[#This Row],[Valor Neto '[DOP']]]) -> 2628131.3 | R89: =BD.PD[[#This Row],[Ppto. Orden Interna '[DOP']]]/HLOOKUP("USD",$K$1:$L$2,2,FALSE) -> 43084.12 | S89: 35820 CORPEMC ELECTRIC MIAMI INC | U89: NTCO011106 | V89: 801668 | W89: 35820 CORPEMC ELECTRIC MIAMI INC | X89: 20 | Y89: 1 | Z89: =BD.PD[[#This Row],[Av.P1 '[%']]]*BD.PD[[#This Row],[Ppto. Orden Interna '[DOP']]] -> 2628131.3 | AC89: =BD.PD[[#This Row],[Av.P2 '[%']]]*BD.PD[[#This Row],[Ppto. Orden Interna '[DOP']]] -> 0 | AF89: =BD.PD[[#This Row],[Av.P3 '[%']]]*BD.PD[[#This Row],[Ppto. Orden Interna '[DOP']]] -> 0 | AM89: =BD.PD[[#This Row],[Pago 3]]+BD.PD[[#This Row],[Pago 2]]+BD.PD[[#This Row],[Pago 1]] -> 2628131.3 | AN89: Sirena Compacta | AO89: Sirena Las Terrenas | AP89: MC33 | AQ89: Marrón | AR89: 594 | AS89: Orden Colocada
